Workbook
Name \0: #REF!
Name \A: #REF!
Name \b: #REF!
Name \c: #REF!
Name \d: #REF!
Name \e: #REF!
Name \f: #REF!
Name \g: #REF!
Name \h: #REF!
Name \i: #REF!
Name \j: #REF!
Name \k: #REF!
Name \l: #REF!
Name \N: #REF!
Name \o: #REF!
Name \p: #REF!
Name \P1: #REF!
Name \q: #REF!
Name \r: #N/A
Name \s: #REF!
Name \t: #REF!
Name \u: #N/A
Name \v: #REF!
Name \VND: #REF!
Name \X: #REF!
Name \z: #REF!
Name _: #N/A
Name _??: NA()
Name _??_1: NA()
Name _??_1_1: NA()
Name _??_1_2: NA()
Name _??_1_3: NA()
Name _??_1_4: NA()
Name _??_1_5: NA()
Name _??_6: NA()
Name _??_7: NA()
Name _??_9: NA()
Name _?1: NA()
Name _?1_1: NA()
Name _?1_1_1: NA()
Name _?1_1_2: NA()
Name _?1_1_3: NA()
Name _?1_1_4: NA()
Name _?1_1_5: NA()
Name _?1_6: NA()
Name _?1_7: NA()
Name _?1_9: NA()
Name _?271: NA()
Name _?271_1: NA()
Name _?271_1_1: NA()
Name _?271_1_2: NA()
Name _?271_1_3: NA()
Name _?271_1_4: NA()
Name _?271_1_5: NA()
Name _?271_6: NA()
Name _?271_7: NA()
Name _?271_9: NA()
Name _?쾴?: #REF!
Name _?쾴?_?: #REF!
Name _?쾴?___P: #REF!

Sheet Cover
A2: BILL OF QUANTITIES BẢNG BÁO GIÁ
C7: PROJECT NAME / TÊN DỰ ÁN :
C8: LOCATION / ĐỊA ĐIỂM : GIANG DIEN INDUSTRIAL PARK - DONG NAI PROVINCE
C9: OWNER / CHỦ ĐẦU TƯ :
C10: CONSTRACTOR / NHÀ THẦU : CÔNG TY CỔ PHẦN TƯ VẤN ĐẦU TƯ XÂY DỰNG MỚI ( NICON)

Sheet Cover 1
A2: BILL OF QUANTITIES BẢNG BÁO GIÁ
C10: CONSTRUCTION COMPANY CÔNG TY DỰ THẦU
C11: GRAND TOTAL TỔNG GIÁ TRỊ | G11: ='00.Tổng Hợp'!E45 -> 0 | H11: VND | I11: excluded V.A.T
G12: =+G11/J12 -> 0 | H12: USD | I12: USD/VND | J12: ='00.Tổng Hợp'!G5 -> 26099
C16: =TODAY() -> 46301

Sheet 00.Tổng Hợp
A2: SUMMARY COST/ TỔNG HỢP CHI PHÍ
A3: =Cover!C7 -> PROJECT NAME / TÊN DỰ ÁN : | I3: =+A3 -> PROJECT NAME / TÊN DỰ ÁN :
F4: CURRENCY : USD/VND
F5: 1 USD/ | G5: 26099
A6: NO. STT | B6: DESCRIPTION DIỄN GIẢI | C6: UNIT / ĐƠN VỊ | D6: Q'TY/ KHỐI LƯỢNG | E6: TOTAL AMOUNT TỔNG GIÁ TRỊ (VND) | F6: TOTAL AMOUNT/ TỔNG GIÁ TRỊ (USD) | G6: REMARK GHI CHÚ
A8: (1) | B8: (2) | C8: (3) | D8: (4) | E8: (5) | F8: (6)
A9: I | B9: DIRECT COST/ CHI PHÍ TRỰC TIẾP | E9: =+E10+E26+E32 -> 0 | F9: =+E9/$G$5 -> 0
A10: A | B10: CONSTRUCTION WORK / CÔNG TÁC XÂY DỰNG | E10: =+SUM(E11:E25) -> 0 | F10: =+E10/$G$5 -> 0
A11: 1 | B11: TEMPORARY WORK/ CÔNG TÁC TẠM | C11: Lot | D11: 1 | E11: ='1.Công Tác Tạm'!J6 -> 0 | F11: =+E11/$G$5 -> 0
A12: 2 | B12: WORKSHOP & OFFICE / NHÀ XƯỞNG & VĂN PHÒNG | C12: Lot | D12: 1 | E12: ='2.Nhà Xưởng & Văn Phòng'!J6 -> 0 | F12: =+E12/$G$5 -> 0
A13: 3 | B13: MAINTENANCE HOUSE, BEAN ROASTING, PACKAGING / NHÀ BẢO TRÌ, RANG ĐẬU, BAO BÌ | C13: Lot | D13: 1 | E13: ='3.Nhà Bảo Trì, Rang Đậu, BB'!J6 -> 0 | F13: =+E13/$G$5 -> 0
A14: 4 | B14: GLASS AND CARTON PACKAGING HOUSE/ NHÀ BAO BÌ THUỶ TINH, CARTON | C14: Lot | D14: 1 | E14: ='4.Nhà BB Thuỷ Tinh, Carton'!J6 -> 0 | F14: =+E14/$G$5 -> 0
A15: 5 | B15: BOILER, AIR COMPRESSOR HOUSE/ NHÀ LÒ HƠI, NÉN KHÍ | C15: Lot | D15: 1 | E15: ='5.Nhà Lò Hơi & Nén Khí'!J6 -> 0 | F15: =+E15/$G$5 -> 0
A16: 6 | B16: BIKE PARKING/ NHÀ ĐỂ XE MÁY | C16: Lot | D16: 1 | E16: ='6.Nhà Để Xe Máy'!J6 -> 0 | F16: =+E16/$G$5 -> 0
A17: 7 | B17: DORMITORY HOUSE/ NHÀ NGHỈ GIỮA CA | C17: Lot | D17: 1 | E17: ='7.Nhà Nghỉ Giữa Ca'!J6 -> 0 | F17: =+E17/$G$5 -> 0
A18: 8 | B18: GUARD HOUSE 1/ NHÀ BẢO VỆ 1 | C18: Lot | D18: 1 | E18: ='8.Nhà Bảo Vệ 1'!J6 -> 0 | F18: =+E18/$G$5 -> 0
A19: 9 | B19: GUARD HOUSE 2/ NHÀ BẢO VỆ 2 | C19: Lot | D19: 1 | E19: ='9.Nhà Bảo Vệ 2'!J6 -> 0 | F19: =+E19/$G$5 -> 0
A20: 10 | B20: GARBAGE, TRANSFORMER HOUSE/ NHÀ RÁC, PHÒNG ĐIỆN | C20: Lot | D20: 1 | E20: ='7.Nhà Nghỉ Giữa Ca'!J9 -> 0 | F20: =+E20/$G$5 -> 0
A21: 11 | B21: WATER TANK FF/ BỂ NƯỚC NGẦM PCCC | C21: Lot | D21: 1 | E21: ='11.Bể Nước Ngầm PCCC'!J6 -> 0 | F21: =+E21/$G$5 -> 0
A22: 12 | B22: COLD WATER TANK/ BỂ NƯỚC XẢ NGUỘI 200M3 | C22: Lot | D22: 1 | E22: ='12.Bể Nước Ngầm Xả Nguội'!J6 -> 0 | F22: =+E22/$G$5 -> 0
A23: 13 | B23: WATER TANK RO/ BỂ NƯỚC NGẦM RO 200M3 | C23: Lot | D23: 1 | E23: ='13.Bể Nước Ngầm RO '!J6 -> 0 | F23: =+E23/$G$5 -> 0
A24: 14 | B24: WWS TANK/ BỂ XLNT | C24: Lot | D24: 1 | E24: ='14.Bể XLNT'!J6 -> 0 | F24: =+E24/$G$5 -> 0
A25: 15 | B25: FENCE & GATE/ HÀNG RÀO & CỔNG | C25: Lot | D25: 1 | E25: ='15.Hàng Rào & Cổng'!J6 -> 0 | F25: =+E25/$G$5 -> 0
A26: B | B26: CIVIL WORKS / CÔNG TÁC HẠ TẦNG | E26: =+SUM(E27:E31) -> 0 | F26: =+E26/$G$5 -> 0
A27: 1 | B27: ROAD/ ĐƯỜNG | C27: Lot | D27: 1 | E27: ='B.Hạ Tầng Kỹ Thuật'!J7 -> 0 | F27: =+E27/$G$5 -> 0
A28: =+A27+1 -> 2 | B28: STORM WATER DRAINAGE SYSTEM/ HỆ THỐNG THOÁT NƯỚC MƯA | C28: Lot | D28: 1 | E28: ='B.Hạ Tầng Kỹ Thuật'!J8 -> 0 | F28: =+E28/$G$5 -> 0
A29: 3 | B29: WASTE WATER DRAINAGE SYSTEM/ HỆ THỐNG THOÁT NƯỚC THẢI NGOÀI NHÀ | C29: Lot | D29: 1 | E29: ='B.Hạ Tầng Kỹ Thuật'!J9 -> 0 | F29: =+E29/$G$5 -> 0
A30: 4 | B30: LANDSCAPE/ CẢNH QUAN | C30: Lot | D30: 1 | E30: ='B.Hạ Tầng Kỹ Thuật'!J10 -> 0 | F30: =+E30/$G$5 -> 0 | J30: Xưởng bậc IV, Hạng sản xuất hạng D (đúc kim loại, ko có vật liệu dễ cháy)
A31: 5 | B31: SETPTIC TANK/ BỂ PHỐT | C31: Lot | D31: 1 | E31: ='B.Hạ Tầng Kỹ Thuật'!J11 -> 0 | F31: =+E31/$G$5 -> 0 | J31: Xưởng bậc IV, Hạng sản xuất hạng D (đúc kim loại, ko có vật liệu dễ cháy)
A32: C | B32: M&E WORKS & EQUIPMENT WORK / CÔNG TÁC CƠ ĐIỆN | E32: =+SUM(E33:E37) -> 0 | F32: =+E32/$G$5 -> 0
A33: 1 | B33: PLUMBING SYSTEM/ HỆ THỐNG CẤP THOÁT NƯỚC | C33: Lot | D33: 1 | E33: ='C1. Hệ Thống Plumbing'!J6 -> 0 | F33: =+E33/$G$5 -> 0 | J33: Báo giá tới thiết bị và lắp đặt trong phòng máy
A34: 2 | B34: WWS EQUIPMNT/ HỆ THỐNG THIẾT BỊ XLNT | C34: Lot | D34: 1 | E34: ='C2.Hệ Thống XLNT'!J6 -> 0 | F34: =+E34/$G$5 -> 0
A35: 3 | B35: FIRE FIGHTING SYSTEM/ HỆ THỐNG PCCC | C35: Lot | D35: 1 | E35: ='C3.Hệ Thống PCCC '!J7 -> 0 | F35: =+E35/$G$5 -> 0
A36: 4 | B36: ELECTRICAL SYSTEM/ HỆ THỐNG ĐIỆN | C36: Lot | D36: 1 | E36: ='C4.Hệ Thống Điện & Điện Nhẹ '!J7 -> 0 | F36: =+E36/$G$5 -> 0
A38: II | B38: INDIRECT COST/ CHI PHÍ GIÁN TIẾP | D38: =SUM(D39:D41) -> 0.06 | E38: =+SUM(E39:E41) -> 0 | F38: =+E38/$G$5 -> 0
A39: 1 | B39: INSURANCE FEE & ISSUE BOND/ BẢO HIỂM & BẢO LÃNH | C39: % | D39: 0.01 | E39: =E9*0.01 -> 0 | F39: =+E39/$G$5 -> 0
A40: 2 | B40: SITE EXPENSE & SITE MANAGEMENT/ CHI PHÍ CÔNG TRƯỜNG & CHI PHÍ QUẢN LÝ | C40: % | D40: 0.03 | E40: =E9*0.03 -> 0 | F40: =+E40/$G$5 -> 0
A41: 3 | B41: OVERHEAD/ QUẢN LÝ PHÍ | C41: % | D41: 0.02 | E41: =E9*0.02 -> 0 | F41: =+E41/$G$5 -> 0
B42: TOTAL AMOUNT (I + II) | E42: =+E9+E38 -> 0 | F42: =+E42/$G$5 -> 0
B43: DISCOUNT , ROUND OFF/ GIẢM GIÁ, LÀM TRÒN | E43: =-MOD(E42,1000000) -> 0
B45: ROUND TOTAL (EXCLUDING VAT) | E45: =+E42+E43+E44 -> 0 | F45: =+E45/$G$5 -> 0

Sheet 1.Công Tác Tạm
A1: BILL OF QUANTITIES
A2: ='C4.Hệ Thống Điện & Điện Nhẹ '!A2:K2 -> PROJECT NAME / TÊN DỰ ÁN :
A3: B1.TEMPORARY WORK/ CÔNG TÁC TẠM
A4: NO / STT | B4: WORK SCOPE / CÔNG VIỆC | C4: SPECIFICATION / ĐẶC ĐIỂM KỸ THUẬT | D4: UNIT/ ĐƠN VỊ | E4: QUANTITY / KHỐI LƯỢNG | F4: UNIT PRICE / ĐƠN GIÁ (VNĐ) | J4: AMOUNT / THÀNH TIỀN (VNĐ) | K4: REMARK / GHI CHÚ
F5: MATERIAL / VẬT LIỆU | G5: LABOUR / NHÂN CÔNG | H5: EQUIPMENT / THIẾT BỊ | I5: UNIT PRICE / TỔNG ĐƠN GIÁ
A6: B1 | B6: TEMPORARY WORK/ CÔNG TÁC TẠM | J6: =SUM(J7:J21) -> 0
A7: 1 | B7: Temporary electronic setting Connection & Authority Fee (EVN, etc) | D7: Lot | E7: 1 | G7: 0 | H7: 0 | I7: =+F7+G7+H7 -> 0 | J7: =+E7*I7 -> 0
A8: 2 | B8: Temporary Electronic Charge Cost Chi phí điện thi công | D8: Month | E8: 8 | G8: 0 | H8: 0 | I8: =+F8+G8+H8 -> 0 | J8: =+E8*I8 -> 0
A9: 3 | B9: Temporary water ,Supply & Charge Cost Chi phí nước thi công | D9: Month | E9: =E8 -> 8 | G9: 0 | H9: 0 | I9: =+F9+G9+H9 -> 0 | J9: =+E9*I9 -> 0
A10: 4 | B10: Temporary water connection costs Chi phí đấu nối nước tạm thi công | D10: Lot | E10: 1 | G10: 0 | H10: 0 | I10: =+F10+G10+H10 -> 0 | J10: =+E10*I10 -> 0
A11: 5 | B11: Temporary office -Contractor & Client (Container 3-SET) Văn phòng tạm (Container 2-SET) | D11: Month | E11: =E9 -> 8 | G11: 0 | H11: 0 | I11: =+F11+G11+H11 -> 0 | J11: =+E11*I11 -> 0 | K11: 3 set
A12: 6 | B12: Temporary-Toilet for worker Nhà vệ sinh tạm công nhân | D12: Month | E12: =E11 -> 8 | G12: 0 | H12: 0 | I12: =+F12+G12+H12 -> 0 | J12: =+E12*I12 -> 0
A13: 7 | B13: Warehouse Nhà kho | D13: Month | E13: =E12 -> 8 | G13: 0 | H13: 0 | I13: =+F13+G13+H13 -> 0 | J13: =+E13*I13 -> 0
A14: 8 | B14: Temporary Fence, Hàng rào tạm, | C14: Include steel frame, gate, color steel sheet | D14: m2 | E14: =(270+12+183)*2 -> 930 | H14: 0 | I14: =+F14+G14+H14 -> 0 | J14: =+E14*I14 -> 0
A15: 9 | B15: Security Fee 2-Person Phí bảo vệ (2 người) | D15: Month | E15: 8 | G15: 0 | H15: 0 | I15: =+F15+G15+H15 -> 0 | J15: =+E15*I15 -> 0
A16: 10 | B16: Temporary Guard house 3m x 3m Nhà bảo vệ tạm (3mx3m) | C16: 1 set | D16: Month | E16: =E15 -> 8 | G16: 0 | H16: 0 | I16: =+F16+G16+H16 -> 0 | J16: =+E16*I16 -> 0
A17: 11 | B17: Temporary lighting system Hệ thống chiếu sáng tạm | D17: Lot | E17: 1 | G17: 0 | H17: 0 | I17: =+F17+G17+H17 -> 0 | J17: =+E17*I17 -> 0
A18: 12 | B18: Project board Biển dự án | D18: Lot | E18: 1 | G18: 0 | H18: 0 | I18: =+F18+G18+H18 -> 0 | J18: =+E18*I18 -> 0
A19: 13 | B19: Chi phí làm lễ khởi công dự án Costs for project groundbreaking ceremony | D19: Lot | E19: 1 | G19: 0 | H19: 0 | I19: =+F19+G19+H19 -> 0 | J19: =+E19*I19 -> 0
A20: 14 | B20: Site clean up Vệ sinh công trường | D20: Month | E20: =E8 -> 8 | G20: 0 | H20: 0 | I20: =+F20+G20+H20 -> 0 | J20: =+E20*I20 -> 0
A21: 15 | B21: Final clean up Vệ sinh trước khi bàn giao | D21: Lot | E21: 1 | G21: 0 | H21: 0 | I21: =+F21+G21+H21 -> 0 | J21: =+E21*I21 -> 0

Sheet 2.Nhà Xưởng & Văn Phòng
A1: BILL OF QUANTITIES
A2: =Cover!C7 -> PROJECT NAME / TÊN DỰ ÁN :
A3: 2.WORKSHOP & OFFICE/ NHÀ XƯỞNG & VĂN PHÒNG
A4: NO / STT | B4: WORK SCOPE / CÔNG VIỆC | C4: SPECIFICATION / ĐẶC ĐIỂM KỸ THUẬT | D4: UNIT/ ĐƠN VỊ | E4: QUANTITY / KHỐI LƯỢNG | F4: UNIT PRICE / ĐƠN GIÁ (VNĐ) | J4: AMOUNT / THÀNH TIỀN (VNĐ) | K4: REMARK / GHI CHÚ
F5: MATERIAL / VẬT LIỆU | G5: LABOUR / NHÂN CÔNG | H5: EQUIPMENT / THIẾT BỊ | I5: UNIT PRICE / TỔNG ĐƠN GIÁ
A6: 2 | B6: WORKSHOP & OFFICE/ NHÀ XƯỞNG & VĂN PHÒNG | J6: =+J7+J14 -> 0
A7: A | B7: =B28 -> STRUCTURE WORK / CÔNG TÁC KẾT CẤU | J7: =SUM(J8:J12) -> 0
A8: 1 | B8: =+B29 -> EARTH WORK / CÔNG TÁC ĐẤT | D8: lot | E8: 1 | J8: =+J29 -> 0
A9: =+A8+1 -> 2 | B9: =+B38 -> CONCRETE WORK / CÔNG TÁC BÊ TÔNG | D9: lot | E9: 1 | J9: =+J38 -> 0
A10: =+A9+1 -> 3 | B10: =+B47 -> FORM WORK / CÔNG TÁC VÁN KHUÔN | D10: lot | E10: 1 | J10: =+J47 -> 0
A11: =+A10+1 -> 4 | B11: =+B52 -> REINFORCEMENT WORK / CÔNG TÁC CỐT THÉP | D11: lot | E11: 1 | J11: =+J52 -> 0
A12: =+A11+1 -> 5 | B12: =+B57 -> STEEL STRUCTURE WORK / CÔNG TÁC KẾT CẤU THÉP TIỀN CHẾ | D12: lot | E12: 1 | J12: =+J57 -> 0
A14: B | B14: =B90 -> FINISING WORK / CÔNG TÁC HOÀN THIỆN | J14: =SUM(J15:J25) -> 0
A15: 1 | B15: =B91 -> BRICK WORK / CÔNG TÁC XÂY | D15: lot | E15: 1 | J15: =J91 -> 0
A16: =+A15+1 -> 2 | B16: =B95 -> PLASTERING WORK / CÔNG TÁC TRÁT | D16: lot | E16: 1 | J16: =J95 -> 0
A17: =+A16+1 -> 3 | B17: =B99 -> PAINTING WORK / CÔNG TÁC SƠN | D17: lot | E17: 1 | J17: =J99 -> 0
A18: =+A17+1 -> 4 | B18: =B102 -> TILING & FLOOR FINISHING WORK / ỐP LÁT VÀ HOÀN THIỆN SÀN | D18: lot | E18: 1 | J18: =J102 -> 0
A19: =+A18+1 -> 5 | B19: =B117 -> CEILLING WORK / CÔNG TÁC TRẦN | D19: lot | E19: 1 | J19: =J117 -> 0
A20: =+A19+1 -> 6 | B20: =B129 -> OUTSIDE & INSIDE WALL PANEL WORK / CÔNG TÁC VÁCH PANEL | D20: lot | E20: 1
A21: =+A20+1 -> 7 | B21: =B166 -> ROOF WORK/ CÔNG TÁC MÁI | D21: lot | E21: 1 | J21: =J166 -> 0
A22: =+A21+1 -> 8 | B22: =B193 -> WATERPROOFING WORK/ CÔNG TÁC CHỐNG THẤM | D22: lot | E22: 1 | J22: =J193 -> 0
A23: =+A22+1 -> 9 | B23: =B202 -> DOOR AND WINDOW / CỬA ĐI VÀ CỬA SỔ | D23: lot | E23: 1 | J23: =J202 -> 0
A24: =+A23+1 -> 10 | B24: =B222 -> METAL WORK/ CÔNG TÁC KIM LOẠI | D24: lot | E24: 1 | J24: =J222 -> 0
A25: =+A24+1 -> 11 | B25: =B230 -> OTHERS WORK / CÔNG VIỆC KHÁC | D25: lot | E25: 1 | J25: =J230 -> 0
A28: A | B28: STRUCTURE WORK / CÔNG TÁC KẾT CẤU | J28: =+J29+J38+J47+J52+J57 -> 0
A29: 1 | B29: EARTH WORK / CÔNG TÁC ĐẤT | J29: =SUM(J30:J36) -> 0
A30: 1 | B30: Excavation (by Equipment) Đào đất bằng máy | D30: m3 | E30: 7470.6892 | H30: 0 | I30: =+SUM(F30:H30) -> 0 | J30: =ROUND(E30*I30,0) -> 0
A31: 2 | B31: Excavation (by worker) Đào đất thủ công | D31: m3 | E31: 747.06892 | H31: 0 | I31: =+SUM(F31:H31) -> 0 | J31: =ROUND(E31*I31,0) -> 0
A32: 3 | B32: Backfilling soil for foundation Đắp đất | D32: m3 | E32: 2988.2757 | H32: 0 | I32: =+SUM(F32:H32) -> 0 | J32: =ROUND(E32*I32,0) -> 0
A33: 4 | B33: Remove surplus soil Vận chuyển đất đổ đi | C33: Distance D<=1Km Khoảng cách D<=1Km | D33: m3 | E33: 5229.4824 | H33: 0 | I33: =+SUM(F33:H33) -> 0 | J33: =ROUND(E33*I33,0) -> 0
A34: 5 | B34: Earth compaction, K=0.9 Đầm đất, K=0.9 | D34: m2 | E34: 14352 | H34: 0 | I34: =+SUM(F34:H34) -> 0 | J34: =ROUND(E34*I34,0) -> 0
A35: 6 | B35: Compacting by stone aggregate K=0.95 Đá base đầm chặt K=0.95 | C35: Base type I / CPĐD - I Cấp phối đá dăm loại I | D35: m3 | E35: 3731.52 | H35: 0 | I35: =+SUM(F35:H35) -> 0 | J35: =ROUND(E35*I35,0) -> 0
A36: 7 | B36: 1 layer nylon thk. 0.3mm 1 lớp nylon dày 0.3mm | D36: m2 | E36: 14352 | H36: 0 | I36: =+SUM(F36:H36) -> 0 | J36: =ROUND(E36*I36,0) -> 0
A38: 2 | B38: CONCRETE WORK / CÔNG TÁC BÊ TÔNG | J38: =SUM(J39:J45) -> 0
A39: 1 | B39: Lean concrete for foundation, ground beam Bê tông lót cho móng, dầm | C39: Gr. 150 | D39: m3 | E39: 806.8093 | H39: 0 | I39: =F39+G39+H39 -> 0 | J39: =ROUND(E39*I39,0) -> 0
A40: 2 | B40: Concrete for foundation,beams, ground slab, scolumn Bê tông móng, dầm móng, nền, cổ cột | C40: Gr. 300 | D40: m3 | E40: 3626.9812 | H40: 0 | I40: =F40+G40+H40 -> 0 | J40: =ROUND(E40*I40,0) -> 0
A41: 3 | B41: Concrete for beams slab, column, bracing Bê tông dầm sàn, cột, giằng | C41: Gr. 300 | D41: m3 | E41: 190.51168 | H41: 0 | I41: =F41+G41+H41 -> 0 | J41: =ROUND(E41*I41,0) -> 0
A42: 4 | B42: Pump car Bơm bê tông | D42: m3 | E42: 4624.3022 | I42: =F42+G42+H42 -> 0 | J42: =ROUND(E42*I42,0) -> 0 | K42: đã bao gồm
A43: 5 | B43: Polishing for slab by machine Xoa nền bằng máy | D43: m2 | E43: 15471.808 | H43: 0 | I43: =F43+G43+H43 -> 0 | J43: =ROUND(E43*I43,0) -> 0
A44: 6 | B44: Cutting joint for floor/ Cắt mạch nền | D44: m | E44: 3414 | H44: 0 | I44: =F44+G44+H44 -> 0 | J44: =ROUND(E44*I44,0) -> 0
A45: 7 | B45: Expansion joint / Khe co giãn | D45: m | E45: 84 | H45: 0 | I45: =+SUM(F45:H45) -> 0 | J45: =ROUND(E45*I45,0) -> 0
A47: 4 | B47: FORM WORK / CÔNG TÁC VÁN KHUÔN | J47: =+SUM(J48:J51) -> 0
A48: 1 | B48: For lean concrete for foundation & ground beam Ván khuôn bê tông lót móng, dầm | D48: m2 | E48: 157.4475 | H48: 0 | I48: =+SUM(F48:H48) -> 0 | J48: =ROUND(E48*I48,0) -> 0
A49: 2 | B49: For foundation, ground beam, slab, scolumn Ván khuôn móng, dầm, nền, cổ cột | D49: m2 | E49: 3052.9233 | H49: 0 | I49: =+SUM(F49:H49) -> 0 | J49: =ROUND(E49*I49,0) -> 0
A50: 3 | B50: For column, beam, bracing Ván khuôn cột, dầm, giằng | C50: (including scaffolding, bracing, supports, etc.) | D50: m2 | E50: 286.85088 | H50: 0 | I50: =+SUM(F50:H50) -> 0 | J50: =ROUND(E50*I50,0) -> 0
A52: 5 | B52: REINFORCEMENT WORK / CÔNG TÁC CỐT THÉP | J52: =+SUM(J53:J55) -> 0 | K52: Thiếu 190T thép
A53: 1 | B53: Re-bar for foundation, ground beam, ground slab Cốt thép móng, dầm, nền | D53: ton | E53: 163.50027 | H53: 0 | I53: =+SUM(F53:H53) -> 0 | J53: =ROUND(E53*I53,0) -> 0 | K53: Hoa Phat/ Equivalent
A54: 2 | B54: Re-bar for column, beam, Cốt thép cho cột, dầm, | D54: ton | E54: 3.543406 | H54: 0 | I54: =+SUM(F54:H54) -> 0 | J54: =ROUND(E54*I54,0) -> 0 | K54: =K53 -> Hoa Phat/ Equivalent
A57: 6 | B57: STEEL STRUCTURE WORK / CÔNG TÁC KẾT CẤU THÉP TIỀN CHẾ | J57: =+SUM(J59:J89) -> 0
A58: I | B58: Steel structure Kết cấu thép
A59: 1 | B59: Fabrication of main steel structures (Rafter) Kết cấu khung thép chính (vì kèo) | C59: Thép SM490, Q355, hoặc tương đương. | D59: kg | E59: 480629.16 | H59: 0 | I59: =F59+G59+H59 -> 0 | J59: =ROUND(E59*I59,0) -> 0
A60: 2 | B60: Bracing systems Hệ giằng thép hình | C60: Thép SS400, Q235, CT3 hoặc tương đương. | D60: kg | E60: 66855.191 | H60: 0 | I60: =F60+G60+H60 -> 0 | J60: =ROUND(E60*I60,0) -> 0
A61: 3 | B61: Purlins Xà gồ mái | C61: Thép G450 mạ kẽm, Z275 | D61: kg | E61: 109351.55 | H61: 0 | I61: =F61+G61+H61 -> 0 | J61: =ROUND(E61*I61,0) -> 0
A62: 4 | B62: Purlin bracing Giằng xà gồ | C62: Mạ điện phân | D62: kg | E62: 3833.0396 | H62: 0 | I62: =F62+G62+H62 -> 0 | J62: =ROUND(E62*I62,0) -> 0
A63: 5 | B63: Steel ladder to roof Thang thép lên mái | C63: H=12m | D63: set | E63: 2 | H63: 0 | I63: =F63+G63+H63 -> 0 | J63: =ROUND(E63*I63,0) -> 0
A64: 6 | B64: Painting for steel structure/Sơn cho kết cấu thép | C64: Sơn chống rỉ + Sơn màu alkid SP dày 80mcr | D64: kg | E64: 547484.35 | H64: 0 | I64: =F64+G64+H64 -> 0 | J64: =ROUND(E64*I64,0) -> 0
A65: 7 | B65: Steel handrail for stair/ Lan can thép cho thang bộ | D65: m | E65: 108.6 | H65: 0 | I65: =F65+G65+H65 -> 0 | J65: =ROUND(E65*I65,0) -> 0
A66: 8 | B66: Anchor Bolts Bu lông neo | C66: 01 bộ: 01 thân+03 Ecu+02 đệm | I66: =F66+G66+H66 -> 0 | J66: =ROUND(E66*I66,0) -> 0
B67: M27*1200 (5.6) | C67: Cấp bền 5.6 mạ đầu ren | D67: set | E67: 132 | H67: 0 | I67: =F67+G67+H67 -> 0 | J67: =ROUND(E67*I67,0) -> 0
B68: M24*850 (5.6) | C68: Cấp bền 5.6 mạ đầu ren | D68: set | E68: 88 | H68: 0 | I68: =F68+G68+H68 -> 0 | J68: =ROUND(E68*I68,0) -> 0
B69: M20*750 (5.6) | C69: Cấp bền 5.6 mạ đầu ren | D69: set | E69: 562 | H69: 0 | I69: =F69+G69+H69 -> 0 | J69: =ROUND(E69*I69,0) -> 0
A70: 9 | B70: Connection bolt Bu lông liên kết | I70: =F70+G70+H70 -> 0 | J70: =ROUND(E70*I70,0) -> 0
B71: M36*100 | C71: Cấp bền 8.8 | D71: set | E71: 660 | H71: 0 | I71: =F71+G71+H71 -> 0 | J71: =ROUND(E71*I71,0) -> 0
B72: M27*90 | C72: Cấp bền 8.8 | D72: set | E72: 1650 | H72: 0 | I72: =F72+G72+H72 -> 0 | J72: =ROUND(E72*I72,0) -> 0
B73: M24*80 | C73: Cấp bền 8.8 | D73: set | E73: 1496 | H73: 0 | I73: =F73+G73+H73 -> 0 | J73: =ROUND(E73*I73,0) -> 0
B74: M20*70 | C74: Cấp bền 8.8 | D74: set | E74: 3814 | H74: 0 | I74: =F74+G74+H74 -> 0 | J74: =ROUND(E74*I74,0) -> 0
B75: M16*60 | C75: Cấp bền 8.8 | D75: set | E75: 296 | H75: 0 | I75: =F75+G75+H75 -> 0 | J75: =ROUND(E75*I75,0) -> 0
B76: M12*30 | C76: Cấp bền 8.8 | D76: set | E76: 10608 | H76: 0 | I76: =F76+G76+H76 -> 0 | J76: =ROUND(E76*I76,0) -> 0
A77: 10 | B77: Transportation of steel structures Vận chuyển kết cấu thép | D77: kg | E77: 660668.94 | H77: 0 | I77: =F77+G77+H77 -> 0 | J77: =ROUND(E77*I77,0) -> 0
A78: 11 | B78: Erection of steel structures Lắp dựng kết cấu thép | C78: . | D78: kg | E78: 660668.94 | H78: 0 | I78: =F78+G78+H78 -> 0 | J78: =ROUND(E78*I78,0) -> 0
A79: II | B79: Deck floor | I79: =+SUM(F79:G79) -> 0
A80: 1 | B80: Decking / Tôn sàn | C80: Galvanized 0.95mm Mạ kẽm dày 0.95mm | D80: m2 | E80: 1146.6 | H80: 0 | I80: =F80+G80+H80 -> 0 | J80: =ROUND(E80*I80,0) -> 0
A81: 2 | B81: Flashing/ Ke Diềm | D81: m | E81: 325.6 | H81: 0 | I81: =F81+G81+H81 -> 0 | J81: =ROUND(E81*I81,0) -> 0
A82: 3 | B82: Thanh giữ ke bo | D82: pcs | E82: 651.2 | H82: 0 | I82: =F82+G82+H82 -> 0 | J82: =ROUND(E82*I82,0) -> 0 | K82: đã bao gồm
A83: 4 | B83: Stud/ Đinh hàn | C83: D16*95 | D83: pcs | E83: 6874.5455 | H83: 0 | I83: =F83+G83+H83 -> 0 | J83: =ROUND(E83*I83,0) -> 0
A84: 5 | B84: Accessories / Vật tư phụ | C84: Screw/Vít bắn tôn sàn, silicon | D84: lot | E84: 1 | H84: 0 | I84: =F84+G84+H84 -> 0 | J84: =ROUND(E84*I84,0) -> 0
A85: 6 | B85: Transportation/ Vận chuyển | D85: lot | E85: 1 | H85: 0 | I85: =F85+G85+H85 -> 0 | J85: =ROUND(E85*I85,0) -> 0
A87: III | B87: Other/ Khác
A88: 1 | B88: Cement grout for base steel column Chèn vữa chân cột | C88: including formwork & silkgrount | D88: ea | E88: 120 | H88: 0 | I88: =F88+G88+H88 -> 0 | J88: =ROUND(E88*I88,0) -> 0
A90: B | B90: FINISING WORK / CÔNG TÁC HOÀN THIỆN | J90: =+J91+J95+J99+J102+J117+J129+J166+J202+J230 -> 0
A91: 1 | B91: BRICK WORK / CÔNG TÁC XÂY | J91: =+SUM(J92:J94) -> 0
A92: 1 | B92: Brick work wall Tường xây gạch | C92: Include linto, bracing | D92: m3 | E92: 292.4408 | H92: 0 | I92: =+SUM(F92:H92) -> 0 | J92: =ROUND(E92*I92,0) -> 0
A93: 2 | B93: Construction scaffolding Giàn giáo thi công | D93: lot | E93: 1 | H93: 0 | K93: đã bao gồm
A95: 2 | B95: PLASTERING WORK / CÔNG TÁC TRÁT | J95: =+SUM(J96:J98) -> 0
A96: 1 | B96: Plastering wall brick surfaces 1.5cm - outside Trát tường dày 1.5cm - ngoài nhà | D96: m2 | E96: 1462.204 | H96: 0 | I96: =+SUM(F96:H96) -> 0 | J96: =ROUND(E96*I96,0) -> 0
A97: 2 | B97: Plastering wall brick surfaces 1.5cm - inside Trát tường dày 1.5cm - trong nhà | D97: m2 | E97: 1462.204 | H97: 0 | I97: =+SUM(F97:H97) -> 0 | J97: =ROUND(E97*I97,0) -> 0
A99: 3 | B99: PAINTING WORK / CÔNG TÁC SƠN | J99: =+SUM(J100:J100) -> 0
A100: 1 | B100: Paint for wall (include putty) Sơn tường (bao gồm bả) | C100: 3 lớp (1 lót + 2 phủ) | D100: m2 | E100: 2924.408 | H100: 0 | I100: =+SUM(F100:H100) -> 0 | J100: =ROUND(E100*I100,0) -> 0 | K100: Dulux/ Jotun
A102: 4 | B102: TILING & FLOOR FINISHING WORK / ỐP LÁT VÀ HOÀN THIỆN SÀN | J102: =+SUM(J103:J116) -> 0
A103: 1 | B103: Non-slip ceramic tile for toilet / Gạch ceramic chống trơn chống trượt cho nhà vệ sinh | C103: 300x300mm | D103: m2 | E103: 58.8 | H103: 0 | I103: =+SUM(F103:H103) -> 0 | J103: =ROUND(E103*I103,0) -> 0
A104: 2 | B104: Ceramic tile for wall / Gạch ceramic cho tường | C104: 300x600mm | D104: m2 | E104: 133.56 | H104: 0 | I104: =+SUM(F104:H104) -> 0 | J104: =ROUND(E104*I104,0) -> 0
A105: 3 | B105: PVC tile for Guest room / Gạch nhựa PVC cho phòng khách chờ | C105: thk 3mm | D105: m2 | E105: 40.95 | H105: 0 | I105: =+SUM(F105:H105) -> 0 | J105: =ROUND(E105*I105,0) -> 0
A106: 4 | B106: Ceramic tile for office, canteen / Gạch ceramic cho văn phòng, nhà ăn | C106: 600x600mm | D106: m2 | E106: 996 | H106: 0 | I106: =+SUM(F106:H106) -> 0 | J106: =ROUND(E106*I106,0) -> 0
A107: 5 | B107: Granite for stair, lobby / Đá granit bậc thang, sảnh đón | C107: thk 20mm | D107: m2 | E107: 74.58 | H107: 0 | I107: =+SUM(F107:H107) -> 0 | J107: =ROUND(E107*I107,0) -> 0
A108: 6 | B108: Granite at the foot of the door, wall / Đá granit len chân cửa, chân tường | D108: m | E108: 210.6 | H108: 0 | I108: =+SUM(F108:H108) -> 0 | J108: =ROUND(E108*I108,0) -> 0
A109: 7 | B109: Cement for tiling | D109: m2 | E109: 1303.89 | H109: 0 | I109: =+SUM(F109:H109) -> 0 | J109: =ROUND(E109*I109,0) -> 0 | K109: Đã bao gồm
A110: 8 | B110: Surface hardener applied concrete slab Nền tăng cứng Hardener | D110: m2 | E110: 9084.6 | H110: 0 | I110: =+SUM(F110:H110) -> 0 | J110: =ROUND(E110*I110,0) -> 0
A111: 9 | B111: Ucrete painting, thk 6mm Nền Ucrete dày 6mm | C111: (UCEATE, HP Factory Spec.), BASF/ Vebro | D111: m2 | E111: 1260 | H111: 0 | I111: =+SUM(F111:H111) -> 0 | J111: =ROUND(E111*I111,0) -> 0
A112: 10 | B112: Ucrete painting, thk 4mm Nền Ucrete dày 4mm | C112: (UCEATE, HP Factory Spec.), BASF/ Vebro | D112: m2 | E112: 4132.8 | H112: 0 | I112: =+SUM(F112:H112) -> 0 | J112: =ROUND(E112*I112,0) -> 0
A113: 11 | B113: Food wall concrete for panel wall 50x100 Chân tường bê tông cho vách panel, 50x100 | C113: (inc formwork, steel drill, sika, material..vv) | D113: m | E113: 716 | H113: 0 | I113: =+SUM(F113:H113) -> 0 | J113: =ROUND(E113*I113,0) -> 0
...

Sheet 3.Nhà Bảo Trì, Rang Đậu, BB
A1: BILL OF QUANTITIES
A2: =+Cover!C7 -> PROJECT NAME / TÊN DỰ ÁN :
A3: 3.NHÀ BẢO TRÌ + NHÀ RANG ĐẬU + BAO BÌ
A4: NO / STT | B4: WORK SCOPE / CÔNG VIỆC | C4: SPECIFICATION / ĐẶC ĐIỂM KỸ THUẬT | D4: UNIT/ ĐƠN VỊ | E4: QUANTITY / KHỐI LƯỢNG | F4: UNIT PRICE / ĐƠN GIÁ (VNĐ) | J4: AMOUNT / THÀNH TIỀN (VNĐ) | K4: REMARK / GHI CHÚ
F5: MATERIAL / VẬT LIỆU | G5: LABOUR / NHÂN CÔNG | H5: EQUIPMENT / THIẾT BỊ | I5: UNIT PRICE / TỔNG ĐƠN GIÁ
A6: 3 | B6: NHÀ BẢO TRÌ + NHÀ RANG ĐẬU + BAO BÌ | J6: =+J7+J14 -> 0
A7: A | B7: =B25 -> STRUCTURE WORK / CÔNG TÁC KẾT CẤU | J7: =SUM(J8:J12) -> 0
A8: 1 | B8: =+B26 -> EARTH WORK / CÔNG TÁC ĐẤT | D8: lot | E8: 1 | J8: =+J26 -> 0
A9: =+A8+1 -> 2 | B9: =+B35 -> CONCRETE WORK / CÔNG TÁC BÊ TÔNG | D9: lot | E9: 1 | J9: =+J35 -> 0
A10: =+A9+1 -> 3 | B10: =+B42 -> FORM WORK / CÔNG TÁC VÁN KHUÔN | D10: lot | E10: 1 | J10: =+J42 -> 0
A11: =+A10+1 -> 4 | B11: =+B45 -> REINFORCEMENT WORK / CÔNG TÁC CỐT THÉP | D11: lot | E11: 1 | J11: =+J45 -> 0
A12: =+A11+1 -> 5 | B12: =+B50 -> STEEL STRUCTURE WORK / CÔNG TÁC KẾT CẤU THÉP TIỀN CHẾ | D12: lot | E12: 1 | J12: =+J50 -> 0
A14: B | B14: =B70 -> FINISING WORK / CÔNG TÁC HOÀN THIỆN | J14: =SUM(J15:J20) -> 0
A15: 1 | B15: =B71 -> FLOOR FINISHING WORK / HOÀN THIỆN SÀN | D15: lot | E15: 1 | J15: =J71 -> 0
A16: 2 | B16: =B74 -> CEILLING WORK / CÔNG TÁC TRẦN | D16: lot | E16: 1
A17: =+A16+1 -> 3 | B17: =B80 -> OUTSIDE & INSIDE WALL PANEL WORK / CÔNG TÁC VÁCH PANEL | D17: lot | E17: 1
A18: =+A17+1 -> 4 | B18: =B104 -> ROOF WORK/ CÔNG TÁC MÁI | D18: lot | E18: 1 | J18: =J104 -> 0
A19: =+A18+1 -> 5 | B19: =B126 -> DOOR AND WINDOW / CỬA ĐI VÀ CỬA SỔ | D19: lot | E19: 1 | J19: =J126 -> 0
A20: =+A19+1 -> 6 | B20: =B137 -> OTHERS WORK / CÔNG VIỆC KHÁC | D20: lot | E20: 1 | J20: =J137 -> 0
A25: A | B25: STRUCTURE WORK / CÔNG TÁC KẾT CẤU | J25: =+J26+J35+J42+J45+J50 -> 0
A26: 1 | B26: EARTH WORK / CÔNG TÁC ĐẤT | J26: =SUM(J27:J33) -> 0
A27: 1 | B27: Excavation (by Equipment) Đào đất bằng máy | D27: m3 | E27: 1310.699 | H27: 0 | I27: =+SUM(F27:H27) -> 0 | J27: =ROUND(E27*I27,0) -> 0
A28: 2 | B28: Excavation (by worker) Đào đất thủ công | D28: m3 | E28: 131.0699 | H28: 0 | I28: =+SUM(F28:H28) -> 0 | J28: =ROUND(E28*I28,0) -> 0
A29: 3 | B29: Backfilling soil for foundation Đắp đất | D29: m3 | E29: 524.2796 | H29: 0 | I29: =+SUM(F29:H29) -> 0 | J29: =ROUND(E29*I29,0) -> 0
A30: 4 | B30: Remove surplus soil Vận chuyển đất đổ đi | C30: Distance D<=1Km Khoảng cách D<=1Km | D30: m3 | E30: 917.4893 | H30: 0 | I30: =+SUM(F30:H30) -> 0 | J30: =ROUND(E30*I30,0) -> 0
A31: 5 | B31: Earth compaction, K=0.9 Đầm đất, K=0.9 | D31: m2 | E31: 2280 | H31: 0 | I31: =+SUM(F31:H31) -> 0 | J31: =ROUND(E31*I31,0) -> 0
A32: 6 | B32: Compacting by stone aggregate K=0.95 Đá base đầm chặt K=0.95 | C32: Base type I / CPĐD - I Cấp phối đá dăm loại I | D32: m3 | E32: 592.8 | H32: 0 | I32: =+SUM(F32:H32) -> 0 | J32: =ROUND(E32*I32,0) -> 0
A33: 7 | B33: 1 layer nylon thk. 0.3mm 1 lớp nylon dày 0.3mm | D33: m2 | E33: 2280 | H33: 0 | I33: =+SUM(F33:H33) -> 0 | J33: =ROUND(E33*I33,0) -> 0
A35: 2 | B35: CONCRETE WORK / CÔNG TÁC BÊ TÔNG | J35: =SUM(J36:J40) -> 0
A36: 1 | B36: Lean concrete for foundation, ground beam Bê tông lót cho móng, dầm | C36: Gr. 150 | D36: m3 | E36: 136.57182 | H36: 0 | I36: =F36+G36+H36 -> 0 | J36: =ROUND(E36*I36,0) -> 0
A37: 2 | B37: Concrete for foundation,beams, ground slab, scolumn Bê tông móng, dầm móng, nền, cổ cột | C37: Gr. 300 | D37: m3 | E37: 471.42375 | H37: 0 | I37: =F37+G37+H37 -> 0 | J37: =ROUND(E37*I37,0) -> 0
A38: 3 | B38: Pump car Bơm bê tông | D38: m3 | E38: 607.99557 | H38: 0 | I38: =F38+G38+H38 -> 0 | J38: =ROUND(E38*I38,0) -> 0 | K38: đã bao gồm
A39: 4 | B39: Polishing for slab by machine Xoa nền bằng máy | D39: m2 | E39: 2280 | H39: 0 | I39: =F39+G39+H39 -> 0 | J39: =ROUND(E39*I39,0) -> 0
A40: 5 | B40: Cutting joint for floor/ Cắt mạch nền | D40: m | E40: 626 | H40: 0 | I40: =F40+G40+H40 -> 0 | J40: =ROUND(E40*I40,0) -> 0
A42: 3 | B42: FORM WORK / CÔNG TÁC VÁN KHUÔN | J42: =+SUM(J43:J44) -> 0
A43: 1 | B43: For lean concrete for foundation & ground beam Ván khuôn bê tông lót móng, dầm | D43: m2 | E43: 60.40125 | H43: 0 | I43: =+SUM(F43:H43) -> 0 | J43: =ROUND(E43*I43,0) -> 0
A44: 2 | B44: For foundation, ground beam, slab, scolumn Ván khuôn móng, dầm, nền, cổ cột | D44: m2 | E44: 495.4572 | H44: 0 | I44: =+SUM(F44:H44) -> 0 | J44: =ROUND(E44*I44,0) -> 0
A45: 4 | B45: REINFORCEMENT WORK / CÔNG TÁC CỐT THÉP | J45: =+SUM(J46:J48) -> 0
A46: 1 | B46: Re-bar for foundation, ground beam, ground slab Cốt thép móng, dầm, cổ cột | D46: ton | E46: 5.03265 | H46: 0 | I46: =+SUM(F46:H46) -> 0 | J46: =ROUND(E46*I46,0) -> 0 | K46: Hoa Phat/ Equivalent
A47: 2 | B47: Re-bar for ground slab Cốt thép cho sàn | D47: ton | E47: 10.626 | H47: 0 | I47: =+SUM(F47:H47) -> 0 | J47: =ROUND(E47*I47,0) -> 0 | K47: =K46 -> Hoa Phat/ Equivalent
A48: 3 | B48: Re-bar for ground ramp Cốt thép cho ram dốc | D48: ton | E48: 0.4992 | H48: 0 | I48: =I47 -> 0 | J48: =ROUND(E48*I48,0) -> 0 | K48: =K47 -> Hoa Phat/ Equivalent
A50: 5 | B50: STEEL STRUCTURE WORK / CÔNG TÁC KẾT CẤU THÉP TIỀN CHẾ | J50: =+SUM(J52:J69) -> 0
A51: I | B51: Steel structure Kết cấu thép
A52: 1 | B52: Fabrication of main steel structures (Rafter) Kết cấu khung thép chính (vì kèo) | C52: Thép SM490, Q355, hoặc tương đương. | D52: kg | E52: 43590.196 | H52: 0 | I52: =F52+G52+H52 -> 0 | J52: =ROUND(E52*I52,0) -> 0
A53: 2 | B53: Bracing systems Hệ giằng thép hình | C53: Thép SS400, Q235, CT3 hoặc tương đương. | D53: kg | E53: 9293.8678 | H53: 0 | I53: =F53+G53+H53 -> 0 | J53: =ROUND(E53*I53,0) -> 0
A54: 3 | B54: Purlins Xà gồ mái | C54: Thép G450 mạ kẽm, Z275 | D54: kg | E54: 13789.651 | H54: 0 | I54: =F54+G54+H54 -> 0 | J54: =ROUND(E54*I54,0) -> 0
A55: 4 | B55: Purlin bracing Giằng xà gồ | C55: Mạ điện phân | D55: kg | E55: 481.0468 | H55: 0 | I55: =F55+G55+H55 -> 0 | J55: =ROUND(E55*I55,0) -> 0
A56: 5 | B56: Steel ladder to roof Thang thép lên mái | C56: H=14m | D56: set | E56: 1 | H56: 0 | I56: =F56+G56+H56 -> 0 | J56: =ROUND(E56*I56,0) -> 0
A57: 6 | B57: Painting for steel structure/Sơn cho kết cấu thép | C57: Sơn chống rỉ + Sơn màu alkid SP dày 80mcr | D57: kg | E57: 52884.064 | H57: 0 | I57: =F57+G57+H57 -> 0 | J57: =ROUND(E57*I57,0) -> 0
A58: 7 | B58: Anchor Bolts Bu lông neo | C58: 01 bộ: 01 thân+03 Ecu+02 đệm | I58: =F58+G58+H58 -> 0 | J58: =ROUND(E58*I58,0) -> 0
B59: M24*900 | C59: Cấp bền 5.6 mạ đầu ren | D59: set | E59: 72 | H59: 0 | I59: =F59+G59+H59 -> 0 | J59: =ROUND(E59*I59,0) -> 0
B60: M20*800 | C60: Cấp bền 5.6 mạ đầu ren | D60: set | E60: 48 | H60: 0 | I60: =F60+G60+H60 -> 0 | J60: =ROUND(E60*I60,0) -> 0
A61: 8 | B61: Connection bolt Bu lông liên kết | I61: =F61+G61+H61 -> 0 | J61: =ROUND(E61*I61,0) -> 0
B62: M24*80 | C62: Cấp bền 8.8 | D62: set | E62: 432 | H62: 0 | I62: =F62+G62+H62 -> 0 | J62: =ROUND(E62*I62,0) -> 0
B63: M20*70 | C63: Cấp bền 8.8 | D63: set | E63: 288 | H63: 0 | I63: =F63+G63+H63 -> 0 | J63: =ROUND(E63*I63,0) -> 0
B64: M12*30 | C64: Cấp bền 8.8 | D64: set | E64: 560 | H64: 0 | I64: =F64+G64+H64 -> 0 | J64: =ROUND(E64*I64,0) -> 0
A65: 9 | B65: Transportation of steel structures Vận chuyển kết cấu thép | D65: kg | E65: 67154.761 | H65: 0 | I65: =F65+G65+H65 -> 0 | J65: =ROUND(E65*I65,0) -> 0
A66: 10 | B66: Erection of steel structures Lắp dựng kết cấu thép | C66: . | D66: kg | E66: 67154.761 | H66: 0 | I66: =F66+G66+H66 -> 0 | J66: =ROUND(E66*I66,0) -> 0
A67: III | B67: Other/ Khác
A68: 1 | B68: Cement grout for base steel column Chèn vữa chân cột | C68: including formwork & silkgrount | D68: ea | E68: 30 | H68: 0 | I68: =F68+G68+H68 -> 0 | J68: =ROUND(E68*I68,0) -> 0
A70: B | B70: FINISING WORK / CÔNG TÁC HOÀN THIỆN | J70: =+J71+J74+J80+J104+J126+J137 -> 0
A71: 1 | B71: FLOOR FINISHING WORK / HOÀN THIỆN SÀN | J71: =+SUM(J72:J73) -> 0
A72: 1 | B72: Epoxy painting 3mm Sơn Epoxy 3mm | C72: thk 3.0 mm | D72: m2 | E72: 2280 | H72: 0 | I72: =+SUM(F72:H72) -> 0 | J72: =ROUND(E72*I72,0) -> 0
A74: 2 | B74: CEILLING WORK / CÔNG TÁC TRẦN | J74: =+SUM(J75:J78) -> 0
A75: 1 | B75: Celing panel EPS 50mm/ Trần panel EPS 50mm | D75: m2 | E75: 2280 | I75: =+SUM(F75:H75) -> 0 | J75: =ROUND(E75*I75,0) -> 0 | K75: Phuong Nam/ Matec
A76: 2 | B76: Purlin for ceiling panel/ Xà gồ cho panel trần | D76: kg | E76: 4560 | I76: =+SUM(F76:H76) -> 0 | J76: =ROUND(E76*I76,0) -> 0
A77: 3 | B77: Aluminum skirting Diềm, phào nhôm | D77: m | E77: 332 | I77: =+SUM(F77:H77) -> 0 | J77: =ROUND(E77*I77,0) -> 0
A78: 4 | B78: Accessories / Vật tư phụ | C78: 5% material | D78: lot | E78: 1 | I78: =+SUM(F78:H78) -> 0 | J78: =ROUND(E78*I78,0) -> 0
I79: =+SUM(F79:G79) -> 0
A80: 3 | B80: OUTSIDE & INSIDE WALL PANEL WORK / CÔNG TÁC VÁCH PANEL | J80: =+SUM(J81:J103) -> 0
A81: I | B81: Partition inside work/ công tác vách trong nhà
A82: 1 | B82: Panel wall FF EI45' Vách panel chống cháy EI45p | C82: Thk 75mm, RW 100kg/m3 | D82: m2 | E82: 256.725 | I82: =+SUM(F82:H82) -> 0 | J82: =ROUND(E82*I82,0) -> 0 | K82: According to fire safety standards
A83: 2 | B83: Accessories / Vật tư phụ | D83: lot | E83: 1 | I83: =+SUM(F83:H83) -> 0 | J83: =ROUND(E83*I83,0) -> 0
A84: 3 | B84: Steel box support for wall Thép hộp hỗ trợ vách tường | C84: Galvanized | D84: kg | E84: 949.8825 | I84: =+SUM(F84:H84) -> 0 | J84: =ROUND(E84*I84,0) -> 0 | K84: Hoa Phat/ Viet Duc
A85: 4 | B85: Transportation of steel structures Vận chuyển kết cấu thép | D85: kg | E85: 949.8825 | I85: =+SUM(F85:H85) -> 0 | J85: =ROUND(E85*I85,0) -> 0
A86: 5 | B86: Erection of steel structures, Lắp dựng kết cấu thép, sơn dặm mối hàn | C86: . | D86: kg | E86: 949.8825 | I86: =+SUM(F86:H86) -> 0 | J86: =ROUND(E86*I86,0) -> 0
A87: 6 | B87: Wall panel EPS 50mm Vách panel EPS 50mm | C87: (0.5/0.4; 12kg/m3) | D87: m2 | E87: 315 | I87: =+SUM(F87:H87) -> 0 | J87: =ROUND(E87*I87,0) -> 0 | K87: =K75 -> Phuong Nam/ Matec
A88: 7 | B88: Aluminum skirting Diềm, phào nhôm | D88: m | E88: 60 | I88: =+SUM(F88:H88) -> 0 | J88: =ROUND(E88*I88,0) -> 0
A90: II | B90: Partition outside work/ công tác vách ngoài
A91: 1 | B91: Thk75 glasswool panel for external wall/ Ốp tường ngoài bằng glasswool panel dày 75mm | C91: (0.5/0.4; 64kg/m3) | D91: m2 | E91: 2671.2 | H91: 0 | I91: =+SUM(F91:H91) -> 0 | J91: =ROUND(E91*I91,0) -> 0
A92: 2 | B92: C/S Top Parepet cover Diềm bo đỉnh thành parapet | D92: m | E92: 233.2 | H92: 0 | I92: =+SUM(F92:H92) -> 0 | J92: =ROUND(E92*I92,0) -> 0
A93: 3 | B93: Aluminum skirting Diềm, phào nhôm | D93: m | E93: 424 | H93: 0 | I93: =+SUM(F93:H93) -> 0 | J93: =ROUND(E93*I93,0) -> 0
A94: 4 | B94: C/S bottom flashing, cover edge door & windows Diềm chân tường tôn, diềm bao cửa | C94: 0.8T | D94: m | E94: 495 | H94: 0 | I94: =+SUM(F94:H94) -> 0 | J94: =ROUND(E94*I94,0) -> 0
A95: 5 | B95: Accessories / Vật tư phụ | D95: lot | E95: 1 | H95: 0 | I95: =+SUM(F95:H95) -> 0 | J95: =ROUND(E95*I95,0) -> 0
A96: 6 | B96: Steel box support for wall Thép hộp hỗ trợ vách tường | C96: Galvanized, steel box 100*100*2mm | D96: kg | E96: 10684.8 | H96: 0 | I96: =+SUM(F96:H96) -> 0 | J96: =ROUND(E96*I96,0) -> 0 | K96: =K84 -> Hoa Phat/ Viet Duc
A97: 7 | B97: Transportation of steel structures Vận chuyển kết cấu thép | D97: kg | E97: 10684.8 | H97: 0 | I97: =+SUM(F97:H97) -> 0 | J97: =ROUND(E97*I97,0) -> 0
A98: 8 | B98: Erection of steel structures, painting Lắp dựng kết cấu thép, sơn | C98: . | D98: kg | E98: 10684.8 | H98: 0 | I98: =+SUM(F98:H98) -> 0 | J98: =ROUND(E98*I98,0) -> 0
A99: 9 | B99: Forklifts for construction Xe nâng phục vụ thi công | C99: . | D99: lot | E99: 1 | H99: 0 | I99: =+SUM(F99:H99) -> 0 | J99: =ROUND(E99*I99,0) -> 0
A100: III | B100: Decor outside work/ công tác trang trí vách ngoài
A101: 1 | B101: Aluminium composite thk 4mm Tấm ốp nhôm composite dày 4mm | C101: Including steel frame | D101: m2 | E101: 42 | H101: 0 | I101: =+SUM(F101:H101) -> 0 | J101: =ROUND(E101*I101,0) -> 0 | K101: Alcorest
A102: 2 | B102: Accessories / Vật tư phụ | D102: lot | E102: 1 | H102: 0 | I102: =+SUM(F102:H102) -> 0 | J102: =ROUND(E102*I102,0) -> 0
A104: 8 | B104: ROOF WORK/ CÔNG TÁC MÁI | J104: =+SUM(J106:J124) -> 0
A105: I | B105: Roof/ Mái
A106: 1 | B106: Roof seamlock sheet thk 0.5mm / Mái seamlock dày 0.5mm | C106: AZ100 | D106: m2 | E106: 2508 | H106: 0 | I106: =+SUM(F106:H106) -> 0 | J106: =ROUND(E106*I106,0) -> 0 | K106: Dong A/ Hoa Sen
A107: 2 | B107: Xà gồ phụ Omega, con kê xà gồ, đai kẹp seam.../ Omega purlins, purlin spacers, seam clamps… | C107: galvanized steel thk 0.95mm/1.5mm | D107: m2 | E107: 2508 | H107: 0 | I107: =+SUM(F107:H107) -> 0 | J107: =ROUND(E107*I107,0) -> 0
A108: 3 | B108: Glasswood layer thk 50mm, 1 layer silver / Lớp glasswood dày 50mm, 1 mặt giấy bạc | C108: thk 64kg/m3 | D108: m2 | E108: 2508 | H108: 0 | I108: =+SUM(F108:H108) -> 0 | J108: =ROUND(E108*I108,0) -> 0 | K108: Cat Tuong/ Win
A109: 4 | B109: Steel mesh D1.2mm, size 100*100mm layer / Lưới thép sợi 1.2mm ô lưới 100mmx100mm | D109: m2 | E109: 2508 | H109: 0 | I109: =+SUM(F109:H109) -> 0 | J109: =ROUND(E109*I109,0) -> 0 | K109: =K106 -> Dong A/ Hoa Sen
A110: 5 | B110: Sheet metal color canopy thk 0.45mm / Tôn đơn mái sảnh, dày 0,45mm | C110: AZ100 | D110: m2 | E110: 128 | H110: 0 | I110: =+SUM(F110:H110) -> 0 | J110: =ROUND(E110*I110,0) -> 0 | K110: =K109 -> Dong A/ Hoa Sen
A111: 6 | B111: Ridge trim/ Diềm úp nóc | C111: Sheet metal color thk 0,45mm | D111: m | E111: 76 | H111: 0 | I111: =+SUM(F111:H111) -> 0 | J111: =ROUND(E111*I111,0) -> 0
A112: 7 | B112: Edge trim/ Diềm cạnh biên | C112: Sheet metal color thk 0,45mm | D112: m | E112: 292 | H112: 0 | I112: =+SUM(F112:H112) -> 0 | J112: =ROUND(E112*I112,0) -> 0
...

Sheet 4.Nhà BB Thuỷ Tinh, Carton
A1: ='3.Nhà Bảo Trì, Rang Đậu, BB'!A1:K1 -> BILL OF QUANTITIES
A2: =+Cover!C7 -> PROJECT NAME / TÊN DỰ ÁN :
A3: 4.NHÀ BAO BÌ THỦY TINH + NHÀ CARTON
A4: NO / STT | B4: WORK SCOPE / CÔNG VIỆC | C4: SPECIFICATION / ĐẶC ĐIỂM KỸ THUẬT | D4: UNIT/ ĐƠN VỊ | E4: QUANTITY / KHỐI LƯỢNG | F4: UNIT PRICE / ĐƠN GIÁ (VNĐ) | J4: AMOUNT / THÀNH TIỀN (VNĐ) | K4: REMARK / GHI CHÚ
F5: MATERIAL / VẬT LIỆU | G5: LABOUR / NHÂN CÔNG | H5: EQUIPMENT / THIẾT BỊ | I5: UNIT PRICE / TỔNG ĐƠN GIÁ
A6: 4 | B6: NHÀ BAO BÌ THỦY TINH + NHÀ CARTON | J6: =+J7+J14 -> 0
A7: A | B7: =B25 -> STRUCTURE WORK / CÔNG TÁC KẾT CẤU | J7: =SUM(J8:J12) -> 0
A8: 1 | B8: =+B26 -> EARTH WORK / CÔNG TÁC ĐẤT | D8: lot | E8: 1 | J8: =+J26 -> 0
A9: =+A8+1 -> 2 | B9: =+B35 -> CONCRETE WORK / CÔNG TÁC BÊ TÔNG | D9: lot | E9: 1 | J9: =+J35 -> 0
A10: =+A9+1 -> 3 | B10: =+B42 -> FORM WORK / CÔNG TÁC VÁN KHUÔN | D10: lot | E10: 1 | J10: =+J42 -> 0
A11: =+A10+1 -> 4 | B11: =+B45 -> REINFORCEMENT WORK / CÔNG TÁC CỐT THÉP | D11: lot | E11: 1 | J11: =+J45 -> 0
A12: =+A11+1 -> 5 | B12: =+B50 -> STEEL STRUCTURE WORK / CÔNG TÁC KẾT CẤU THÉP TIỀN CHẾ | D12: lot | E12: 1 | J12: =+J50 -> 0
A14: B | B14: =B70 -> FINISING WORK / CÔNG TÁC HOÀN THIỆN | J14: =SUM(J15:J20) -> 0
A15: 1 | B15: =B71 -> FLOOR FINISHING WORK / HOÀN THIỆN SÀN | D15: lot | E15: 1 | J15: =J71 -> 0
A16: 2 | B16: =B74 -> CEILLING WORK / CÔNG TÁC TRẦN | D16: lot | E16: 1 | J16: =J74 -> 0
A17: =+A16+1 -> 3 | B17: =B80 -> OUTSIDE & INSIDE WALL PANEL WORK / CÔNG TÁC VÁCH PANEL | D17: lot | E17: 1 | J17: =J80 -> 0
A18: =+A17+1 -> 4 | B18: =B99 -> ROOF WORK/ CÔNG TÁC MÁI | D18: lot | E18: 1 | J18: =J99 -> 0
A19: =+A18+1 -> 5 | B19: =B121 -> DOOR AND WINDOW / CỬA ĐI VÀ CỬA SỔ | D19: lot | E19: 1 | J19: =J121 -> 0
A20: =+A19+1 -> 6 | B20: =B130 -> OTHERS WORK / CÔNG VIỆC KHÁC | D20: lot | E20: 1 | J20: =J130 -> 0
A25: A | B25: STRUCTURE WORK / CÔNG TÁC KẾT CẤU | J25: =+J26+J35+J42+J45+J50 -> 0
A26: 1 | B26: EARTH WORK / CÔNG TÁC ĐẤT | J26: =SUM(J27:J33) -> 0
A27: 1 | B27: Excavation (by Equipment) Đào đất bằng máy | D27: m3 | E27: 1131.9321 | H27: 0 | I27: =+SUM(F27:H27) -> 0 | J27: =ROUND(E27*I27,0) -> 0
A28: 2 | B28: Excavation (by worker) Đào đất thủ công | D28: m3 | E28: 113.19321 | H28: 0 | I28: =+SUM(F28:H28) -> 0 | J28: =ROUND(E28*I28,0) -> 0
A29: 3 | B29: Backfilling soil for foundation Đắp đất | D29: m3 | E29: 452.77284 | H29: 0 | I29: =+SUM(F29:H29) -> 0 | J29: =ROUND(E29*I29,0) -> 0
A30: 4 | B30: Remove surplus soil Vận chuyển đất đổ đi | C30: Distance D<=1Km Khoảng cách D<=1Km | D30: m3 | E30: 792.35247 | H30: 0 | I30: =+SUM(F30:H30) -> 0 | J30: =ROUND(E30*I30,0) -> 0
A31: 5 | B31: Earth compaction, K=0.9 Đầm đất, K=0.9 | D31: m2 | E31: 1830 | H31: 0 | I31: =+SUM(F31:H31) -> 0 | J31: =ROUND(E31*I31,0) -> 0
A32: 6 | B32: Compacting by stone aggregate K=0.95 Đá base đầm chặt K=0.95 | C32: Base type I / CPĐD - I Cấp phối đá dăm loại I | D32: m3 | E32: 475.8 | H32: 0 | I32: =+SUM(F32:H32) -> 0 | J32: =ROUND(E32*I32,0) -> 0
A33: 7 | B33: 1 layer nylon thk. 0.3mm 1 lớp nylon dày 0.3mm | D33: m2 | E33: 1830 | H33: 0 | I33: =+SUM(F33:H33) -> 0 | J33: =ROUND(E33*I33,0) -> 0
A35: 2 | B35: CONCRETE WORK / CÔNG TÁC BÊ TÔNG | J35: =SUM(J36:J40) -> 0
A36: 1 | B36: Lean concrete for foundation, ground beam Bê tông lót cho móng, dầm | C36: Gr. 150 | D36: m3 | E36: 111.61389 | H36: 0 | I36: =F36+G36+H36 -> 0 | J36: =ROUND(E36*I36,0) -> 0
A37: 2 | B37: Concrete for foundation,beams, ground slab, scolumn Bê tông móng, dầm móng, nền, cổ cột | C37: Gr. 300 | D37: m3 | E37: 391.15354 | H37: 0 | I37: =F37+G37+H37 -> 0 | J37: =ROUND(E37*I37,0) -> 0
A38: 3 | B38: Pump car Bơm bê tông | D38: m3 | E38: 502.76743 | H38: 0 | I38: =F38+G38+H38 -> 0 | J38: =ROUND(E38*I38,0) -> 0 | K38: đã bao gồm
A39: 4 | B39: Polishing for slab by machine Xoa nền bằng máy | D39: m2 | E39: 1830 | H39: 0 | I39: =F39+G39+H39 -> 0 | J39: =ROUND(E39*I39,0) -> 0
A40: 5 | B40: Cutting joint for floor/ Cắt mạch nền | D40: m | E40: 626 | H40: 0 | I40: =F40+G40+H40 -> 0 | J40: =ROUND(E40*I40,0) -> 0
A42: 3 | B42: FORM WORK / CÔNG TÁC VÁN KHUÔN | J42: =+SUM(J43:J44) -> 0
A43: 1 | B43: For lean concrete for foundation & ground beam Ván khuôn bê tông lót móng, dầm | D43: m2 | E43: 53.74425 | H43: 0 | I43: =+SUM(F43:H43) -> 0 | J43: =ROUND(E43*I43,0) -> 0
A44: 2 | B44: For foundation, ground beam, slab, scolumn Ván khuôn móng, dầm, nền, cổ cột | D44: m2 | E44: 441.9954 | H44: 0 | I44: =+SUM(F44:H44) -> 0 | J44: =ROUND(E44*I44,0) -> 0
A45: 4 | B45: REINFORCEMENT WORK / CÔNG TÁC CỐT THÉP | J45: =+SUM(J46:J48) -> 0
A46: 1 | B46: Re-bar for foundation, ground beam, ground slab Cốt thép móng, dầm, cổ cột | D46: ton | E46: 4.4734667 | H46: 0 | I46: =+SUM(F46:H46) -> 0 | J46: =ROUND(E46*I46,0) -> 0 | K46: Hoa Phat/ Equivalent
A47: 2 | B47: Re-bar for ground slab Cốt thép cho sàn | D47: ton | E47: 8.5287632 | H47: 0 | I47: =+SUM(F47:H47) -> 0 | J47: =ROUND(E47*I47,0) -> 0 | K47: =K46 -> Hoa Phat/ Equivalent
A48: 3 | B48: Re-bar for ground ramp Cốt thép cho ram dốc | D48: ton | E48: 0.4992 | H48: 0 | I48: =I47 -> 0 | J48: =ROUND(E48*I48,0) -> 0 | K48: =K47 -> Hoa Phat/ Equivalent
A50: 5 | B50: STEEL STRUCTURE WORK / CÔNG TÁC KẾT CẤU THÉP TIỀN CHẾ | J50: =+SUM(J52:J69) -> 0
A51: I | B51: Steel structure Kết cấu thép
A52: 1 | B52: Fabrication of main steel structures (Rafter) Kết cấu khung thép chính (vì kèo) | C52: Thép SM490, Q355, hoặc tương đương. | D52: kg | E52: 44191.843 | H52: 0 | I52: =F52+G52+H52 -> 0 | J52: =ROUND(E52*I52,0) -> 0
A53: 2 | B53: Bracing systems Hệ giằng thép hình | C53: Thép SS400, Q235, CT3 hoặc tương đương. | D53: kg | E53: 5730.0133 | H53: 0 | I53: =F53+G53+H53 -> 0 | J53: =ROUND(E53*I53,0) -> 0
A54: 3 | B54: Purlins Xà gồ mái | C54: Thép G450 mạ kẽm, Z275 | D54: kg | E54: 10438.111 | H54: 0 | I54: =F54+G54+H54 -> 0 | J54: =ROUND(E54*I54,0) -> 0
A55: 4 | B55: Purlin bracing Giằng xà gồ | C55: Mạ điện phân | D55: kg | E55: 416.81207 | H55: 0 | I55: =F55+G55+H55 -> 0 | J55: =ROUND(E55*I55,0) -> 0
A56: 5 | B56: Steel ladder to roof Thang thép lên mái | C56: H=14m | D56: set | E56: 1 | H56: 0 | I56: =F56+G56+H56 -> 0 | J56: =ROUND(E56*I56,0) -> 0
A57: 6 | B57: Painting for steel structure/Sơn cho kết cấu thép | C57: Sơn chống rỉ + Sơn màu alkid SP dày 80mcr | D57: kg | E57: 49921.857 | H57: 0 | I57: =F57+G57+H57 -> 0 | J57: =ROUND(E57*I57,0) -> 0
A58: 7 | B58: Anchor Bolts Bu lông neo | C58: 01 bộ: 01 thân+03 Ecu+02 đệm | I58: =F58+G58+H58 -> 0 | J58: =ROUND(E58*I58,0) -> 0
B59: M24*900 | C59: Cấp bền 5.6 mạ đầu ren | D59: set | E59: 48 | H59: 0 | I59: =F59+G59+H59 -> 0 | J59: =ROUND(E59*I59,0) -> 0
B60: M20*800 | C60: Cấp bền 5.6 mạ đầu ren | D60: set | E60: 48 | H60: 0 | I60: =F60+G60+H60 -> 0 | J60: =ROUND(E60*I60,0) -> 0
A61: 8 | B61: Connection bolt Bu lông liên kết | I61: =F61+G61+H61 -> 0 | J61: =ROUND(E61*I61,0) -> 0
B62: M24*80 | C62: Cấp bền 8.8 | D62: set | E62: 288 | H62: 0 | I62: =F62+G62+H62 -> 0 | J62: =ROUND(E62*I62,0) -> 0
B63: M20*70 | C63: Cấp bền 8.8 | D63: set | E63: 216 | H63: 0 | I63: =F63+G63+H63 -> 0 | J63: =ROUND(E63*I63,0) -> 0
B64: M12*30 | C64: Cấp bền 8.8 | D64: set | E64: 392 | H64: 0 | I64: =F64+G64+H64 -> 0 | J64: =ROUND(E64*I64,0) -> 0
A65: 9 | B65: Transportation of steel structures Vận chuyển kết cấu thép | D65: kg | E65: 60776.779 | H65: 0 | I65: =F65+G65+H65 -> 0 | J65: =ROUND(E65*I65,0) -> 0
A66: 10 | B66: Erection of steel structures Lắp dựng kết cấu thép | C66: . | D66: kg | E66: 60776.779 | H66: 0 | I66: =F66+G66+H66 -> 0 | J66: =ROUND(E66*I66,0) -> 0
A67: III | B67: Other/ Khác
A68: 1 | B68: Cement grout for base steel column Chèn vữa chân cột | C68: including formwork & silkgrount | D68: ea | E68: 28 | H68: 0 | I68: =F68+G68+H68 -> 0 | J68: =ROUND(E68*I68,0) -> 0
A70: B | B70: FINISING WORK / CÔNG TÁC HOÀN THIỆN | J70: =+J71+J74+J80+J99+J121+J130 -> 0
A71: 1 | B71: FLOOR FINISHING WORK / HOÀN THIỆN SÀN | J71: =+SUM(J72:J73) -> 0
A72: 1 | B72: Epoxy painting 3mm Sơn Epoxy 3mm | C72: thk 3.0 mm | D72: m2 | E72: 1830 | H72: 0 | I72: =+SUM(F72:H72) -> 0 | J72: =ROUND(E72*I72,0) -> 0
A74: 2 | B74: CEILLING WORK / CÔNG TÁC TRẦN | J74: =+SUM(J75:J78) -> 0
A75: 1 | B75: Celing panel EPS 50mm/ Trần panel EPS 50mm | C75: (0.5/0.4; 12kg/m3) | D75: m2 | E75: 1830 | I75: =+SUM(F75:H75) -> 0 | J75: =ROUND(E75*I75,0) -> 0
A76: 2 | B76: Purlin for ceiling panel/ Xà gồ cho panel trần | D76: kg | E76: 3660 | I76: =+SUM(F76:H76) -> 0 | J76: =ROUND(E76*I76,0) -> 0
A77: 3 | B77: Aluminum skirting Diềm, phào nhôm | D77: m | E77: 242 | I77: =+SUM(F77:H77) -> 0 | J77: =ROUND(E77*I77,0) -> 0
A78: 4 | B78: Accessories / Vật tư phụ | C78: 5% material | D78: lot | E78: 1 | I78: =+SUM(F78:H78) -> 0 | J78: =ROUND(E78*I78,0) -> 0
I79: =+SUM(F79:G79) -> 0
A80: 3 | B80: OUTSIDE & INSIDE WALL PANEL WORK / CÔNG TÁC VÁCH PANEL | J80: =+SUM(J81:J98) -> 0
A81: I | B81: Partition inside work/ công tác vách trong nhà
A82: 1 | B82: Wall panel EPS 50mm Vách panel EPS 50mm | C82: (0.5/0.4; 12kg/m3) | D82: m2 | E82: 157.5 | I82: =+SUM(F82:H82) -> 0 | J82: =ROUND(E82*I82,0) -> 0 | K82: =K75 -> 0
A83: 2 | B83: Aluminum skirting Diềm, phào nhôm | D83: m | E83: 60 | I83: =+SUM(F83:H83) -> 0 | J83: =ROUND(E83*I83,0) -> 0
A85: II | B85: Partition outside work/ công tác vách ngoài
A86: 1 | B86: Thk75 glasswool panel for external wall/ Ốp tường ngoài bằng glasswool panel dày 75mm | C86: (0.5/0.4; 64kg/m3) | D86: m2 | E86: 1662.57 | I86: =+SUM(F86:H86) -> 0 | J86: =ROUND(E86*I86,0) -> 0 | K86: Phương Nam/ Matec
A87: 2 | B87: C/S Top Parepet cover Diềm bo đỉnh thành parapet | D87: m | E87: 200.2 | I87: =+SUM(F87:H87) -> 0 | J87: =ROUND(E87*I87,0) -> 0
A88: 3 | B88: Aluminum skirting Diềm, phào nhôm | D88: m | E88: 182 | I88: =+SUM(F88:H88) -> 0 | J88: =ROUND(E88*I88,0) -> 0
A89: 4 | B89: C/S bottom flashing, cover edge door & windows Diềm chân tường tôn, diềm bao cửa | C89: 0.45T | D89: m | E89: 449 | H89: 0 | I89: =+SUM(F89:H89) -> 0 | J89: =ROUND(E89*I89,0) -> 0
A90: 5 | B90: Accessories / Vật tư phụ | D90: lot | E90: 1 | H90: 0 | I90: =+SUM(F90:H90) -> 0 | J90: =ROUND(E90*I90,0) -> 0
A91: 6 | B91: Steel box support for wall Thép hộp hỗ trợ vách tường | C91: Galvanized, steel box 100*100*2mm | D91: kg | E91: 6650.28 | H91: 0 | I91: =+SUM(F91:H91) -> 0 | J91: =ROUND(E91*I91,0) -> 0 | K91: Hoa Phat/ Viet Duc
A92: 7 | B92: Transportation of steel structures Vận chuyển kết cấu thép | D92: kg | E92: 6650.28 | H92: 0 | I92: =+SUM(F92:H92) -> 0 | J92: =ROUND(E92*I92,0) -> 0
A93: 8 | B93: Erection of steel structures, painting Lắp dựng kết cấu thép, sơn | C93: . | D93: kg | E93: 6650.28 | I93: =+SUM(F93:H93) -> 0 | J93: =ROUND(E93*I93,0) -> 0
A94: 9 | B94: Forklifts for construction Xe nâng phục vụ thi công | C94: . | D94: lot | E94: 1 | H94: 0 | I94: =+SUM(F94:H94) -> 0 | J94: =ROUND(E94*I94,0) -> 0 | K94: Bao gồm
A95: III | B95: Decor outside work/ công tác trang trí vách ngoài
A96: 1 | B96: Aluminium composite thk 4mm Tấm ốp nhôm composite dày 4mm | C96: Including steel frame | D96: m2 | E96: 42 | H96: 0 | I96: =+SUM(F96:H96) -> 0 | J96: =ROUND(E96*I96,0) -> 0 | K96: Alcorest
A97: 2 | B97: Accessories / Vật tư phụ | D97: lot | E97: 1 | H97: 0 | I97: =+SUM(F97:H97) -> 0 | J97: =ROUND(E97*I97,0) -> 0
A99: 8 | B99: ROOF WORK/ CÔNG TÁC MÁI | J99: =+SUM(J101:J119) -> 0
A100: I | B100: Roof/ Mái
A101: 1 | B101: Roof seamlock sheet thk 0.5mm / Mái seamlock dày 0.5mm | C101: AZ100 | D101: m2 | E101: 2013 | H101: 0 | I101: =+SUM(F101:H101) -> 0 | J101: =ROUND(E101*I101,0) -> 0 | K101: Dong A/ Hoa Sen
A102: 2 | B102: Xà gồ phụ Omega, con kê xà gồ, đai kẹp seam.../ Omega purlins, purlin spacers, seam clamps… | C102: galvanized steel thk 0.95mm/1.5mm | D102: m2 | E102: 2013 | H102: 0 | I102: =+SUM(F102:H102) -> 0 | J102: =ROUND(E102*I102,0) -> 0
A103: 3 | B103: Glasswood layer thk 50mm, 1 layer silver / Lớp glasswood dày 50mm, 1 mặt giấy bạc | C103: thk 64kg/m3 | D103: m2 | E103: 2013 | H103: 0 | I103: =+SUM(F103:H103) -> 0 | J103: =ROUND(E103*I103,0) -> 0 | K103: Cat Tuong/ Win
A104: 4 | B104: Steel mesh D1.2mm, size 100*100mm layer / Lưới thép sợi 1.2mm ô lưới 100mmx100mm | D104: m2 | E104: 2013 | H104: 0 | I104: =+SUM(F104:H104) -> 0 | J104: =ROUND(E104*I104,0) -> 0 | K104: =K101 -> Dong A/ Hoa Sen
A105: 5 | B105: Sheet metal color canopy thk 0.45mm / Tôn đơn mái sảnh, dày 0,45mm | C105: AZ100 | D105: m2 | E105: 128 | H105: 0 | I105: =+SUM(F105:H105) -> 0 | J105: =ROUND(E105*I105,0) -> 0 | K105: =K104 -> Dong A/ Hoa Sen
A106: 6 | B106: Ridge trim/ Diềm úp nóc | C106: Sheet metal color thk 0,45mm | D106: m | E106: 61 | H106: 0 | I106: =+SUM(F106:H106) -> 0 | J106: =ROUND(E106*I106,0) -> 0
A107: 7 | B107: Edge trim/ Diềm cạnh biên | C107: Sheet metal color thk 0,45mm | D107: m | E107: 262 | H107: 0 | I107: =+SUM(F107:H107) -> 0 | J107: =ROUND(E107*I107,0) -> 0
A108: 8 | B108: Eave trim/ Diềm đầu hồi | C108: Sheet metal color thk 0,45mm | D108: m | E108: 66 | H108: 0 | I108: =+SUM(F108:H108) -> 0 | J108: =ROUND(E108*I108,0) -> 0
A109: 9 | B109: Flashing trim/ Diềm bo, gờ nước | C109: Sheet metal color thk 0,45mm | D109: m | E109: 230 | H109: 0 | I109: =+SUM(F109:H109) -> 0 | J109: =ROUND(E109*I109,0) -> 0
A110: 10 | B110: Supplies and accessories / Vật tư phụ | D110: Lot | E110: 1 | H110: 0 | I110: =+SUM(F110:H110) -> 0 | J110: =ROUND(E110*I110,0) -> 0
A111: 11 | B111: Transport cost / Chi phí vận chuyển | D111: Lot | E111: 7 | H111: 0 | I111: =+SUM(F111:H111) -> 0 | J111: =ROUND(E111*I111,0) -> 0
A112: II | B112: Roof drainage/ Hệ thống thoát nước mái
...

Sheet 5.Nhà Lò Hơi & Nén Khí
A1: ='4.Nhà BB Thuỷ Tinh, Carton'!A1:K1 -> BILL OF QUANTITIES
A2: =+Cover!C7 -> PROJECT NAME / TÊN DỰ ÁN :
A3: 5.NHÀ LÒ HƠI + NHÀ NÉN KHÍ
A4: NO / STT | B4: WORK SCOPE / CÔNG VIỆC | C4: SPECIFICATION / ĐẶC ĐIỂM KỸ THUẬT | D4: UNIT/ ĐƠN VỊ | E4: QUANTITY / KHỐI LƯỢNG | F4: UNIT PRICE / ĐƠN GIÁ (VNĐ) | J4: AMOUNT / THÀNH TIỀN (VNĐ) | K4: REMARK / GHI CHÚ
F5: MATERIAL / VẬT LIỆU | G5: LABOUR / NHÂN CÔNG | H5: EQUIPMENT / THIẾT BỊ | I5: UNIT PRICE / TỔNG ĐƠN GIÁ
A6: 5 | B6: NHÀ LÒ HƠI + NÉN KHÍ | J6: =+J7+J14 -> 0
A7: A | B7: =B25 -> STRUCTURE WORK / CÔNG TÁC KẾT CẤU | J7: =SUM(J8:J12) -> 0
A8: 1 | B8: =+B26 -> EARTH WORK / CÔNG TÁC ĐẤT | D8: lot | E8: 1 | J8: =+J26 -> 0
A9: =+A8+1 -> 2 | B9: =+B35 -> CONCRETE WORK / CÔNG TÁC BÊ TÔNG | D9: lot | E9: 1 | J9: =+J35 -> 0
A10: =+A9+1 -> 3 | B10: =+B42 -> FORM WORK / CÔNG TÁC VÁN KHUÔN | D10: lot | E10: 1 | J10: =+J42 -> 0
A11: =+A10+1 -> 4 | B11: =+B45 -> REINFORCEMENT WORK / CÔNG TÁC CỐT THÉP | D11: lot | E11: 1 | J11: =+J45 -> 0
A12: =+A11+1 -> 5 | B12: =+B50 -> STEEL STRUCTURE WORK / CÔNG TÁC KẾT CẤU THÉP TIỀN CHẾ | D12: lot | E12: 1 | J12: =+J50 -> 0
A14: B | B14: =B70 -> FINISING WORK / CÔNG TÁC HOÀN THIỆN | J14: =SUM(J15:J20) -> 0
A15: 1 | B15: =B71 -> FLOOR FINISHING WORK / HOÀN THIỆN SÀN | D15: lot | E15: 1 | J15: =J71 -> 0
A16: 2 | B16: =B74 -> CEILLING WORK / CÔNG TÁC TRẦN | D16: lot | E16: 1 | J16: =J74 -> 0
A17: =+A16+1 -> 3 | B17: =B79 -> OUTSIDE & INSIDE WALL PANEL WORK / CÔNG TÁC VÁCH PANEL | D17: lot | E17: 1 | J17: =J79 -> 0
A18: =+A17+1 -> 4 | B18: =B94 -> ROOF WORK/ CÔNG TÁC MÁI | D18: lot | E18: 1 | J18: =J94 -> 0
A19: =+A18+1 -> 5 | B19: =B116 -> DOOR AND WINDOW / CỬA ĐI VÀ CỬA SỔ | D19: lot | E19: 1 | J19: =J116 -> 0
A20: =+A19+1 -> 6 | B20: =B122 -> OTHERS WORK / CÔNG VIỆC KHÁC | D20: lot | E20: 1 | J20: =J122 -> 0
A25: A | B25: STRUCTURE WORK / CÔNG TÁC KẾT CẤU | J25: =+J26+J35+J42+J45+J50 -> 0
A26: 1 | B26: EARTH WORK / CÔNG TÁC ĐẤT | J26: =SUM(J27:J33) -> 0
A27: 1 | B27: Excavation (by Equipment) Đào đất bằng máy | D27: m3 | E27: 501.0902 | I27: =+SUM(F27:H27) -> 0 | J27: =ROUND(E27*I27,0) -> 0
A28: 2 | B28: Excavation (by worker) Đào đất thủ công | D28: m3 | E28: 50.10902 | I28: =+SUM(F28:H28) -> 0 | J28: =ROUND(E28*I28,0) -> 0
A29: 3 | B29: Backfilling soil for foundation Đắp đất | D29: m3 | E29: 200.43608 | I29: =+SUM(F29:H29) -> 0 | J29: =ROUND(E29*I29,0) -> 0
A30: 4 | B30: Remove surplus soil Vận chuyển đất đổ đi | C30: Distance D<=1Km Khoảng cách D<=1Km | D30: m3 | E30: 350.76314 | I30: =+SUM(F30:H30) -> 0 | J30: =ROUND(E30*I30,0) -> 0
A31: 5 | B31: Earth compaction, K=0.9 Đầm đất, K=0.9 | D31: m2 | E31: 600 | I31: =+SUM(F31:H31) -> 0 | J31: =ROUND(E31*I31,0) -> 0
A32: 6 | B32: Compacting by stone aggregate K=0.95 Đá base đầm chặt K=0.95 | C32: Base type I / CPĐD - I Cấp phối đá dăm loại I | D32: m3 | E32: 156 | I32: =+SUM(F32:H32) -> 0 | J32: =ROUND(E32*I32,0) -> 0
A33: 7 | B33: 1 layer nylon thk. 0.3mm 1 lớp nylon dày 0.3mm | D33: m2 | E33: 600 | I33: =+SUM(F33:H33) -> 0 | J33: =ROUND(E33*I33,0) -> 0
A35: 2 | B35: CONCRETE WORK / CÔNG TÁC BÊ TÔNG | J35: =SUM(J36:J40) -> 0
A36: 1 | B36: Lean concrete for foundation, ground beam Bê tông lót cho móng, dầm | C36: Gr. 150 | D36: m3 | E36: 39.84246 | I36: =F36+G36+H36 -> 0 | J36: =ROUND(E36*I36,0) -> 0
A37: 2 | B37: Concrete for foundation,beams, ground slab, scolumn Bê tông móng, dầm móng, nền, cổ cột | C37: Gr. 300 | D37: m3 | E37: 149.2648 | I37: =F37+G37+H37 -> 0 | J37: =ROUND(E37*I37,0) -> 0
A38: 3 | B38: Pump car Bơm bê tông | D38: m3 | E38: 189.10726 | I38: =F38+G38+H38 -> 0 | J38: =ROUND(E38*I38,0) -> 0 | K38: đã bao gồm
A39: 4 | B39: Polishing for slab by machine Xoa nền bằng máy | D39: m2 | E39: 600 | I39: =F39+G39+H39 -> 0 | J39: =ROUND(E39*I39,0) -> 0
A40: 5 | B40: Cutting joint for floor/ Cắt mạch nền | D40: m | E40: 626 | I40: =F40+G40+H40 -> 0 | J40: =ROUND(E40*I40,0) -> 0
A42: 3 | B42: FORM WORK / CÔNG TÁC VÁN KHUÔN | J42: =+SUM(J43:J44) -> 0
A43: 1 | B43: For lean concrete for foundation & ground beam Ván khuôn bê tông lót móng, dầm | D43: m2 | E43: 29.23725 | I43: =+SUM(F43:H43) -> 0 | J43: =ROUND(E43*I43,0) -> 0
A44: 2 | B44: For foundation, ground beam, slab, scolumn Ván khuôn móng, dầm, nền, cổ cột | D44: m2 | E44: 239.5596 | I44: =+SUM(F44:H44) -> 0 | J44: =ROUND(E44*I44,0) -> 0
A45: 4 | B45: REINFORCEMENT WORK / CÔNG TÁC CỐT THÉP | J45: =+SUM(J46:J48) -> 0
A46: 1 | B46: Re-bar for foundation, ground beam, ground slab Cốt thép móng, dầm, cổ cột | D46: ton | E46: 2.61826 | I46: =+SUM(F46:H46) -> 0 | J46: =ROUND(E46*I46,0) -> 0 | K46: Hoa Phat/ Equivalent
A47: 2 | B47: Re-bar for ground slab Cốt thép cho sàn | D47: ton | E47: 2.7963158 | I47: =+SUM(F47:H47) -> 0 | J47: =ROUND(E47*I47,0) -> 0 | K47: =K46 -> Hoa Phat/ Equivalent
A48: 3 | B48: Re-bar for ground ramp Cốt thép cho ram dốc | D48: ton | E48: 0.4992 | I48: =I47 -> 0 | J48: =ROUND(E48*I48,0) -> 0 | K48: =K47 -> Hoa Phat/ Equivalent
A50: 5 | B50: STEEL STRUCTURE WORK / CÔNG TÁC KẾT CẤU THÉP TIỀN CHẾ | J50: =+SUM(J52:J69) -> 0
A51: I | B51: Steel structure Kết cấu thép
A52: 1 | B52: Fabrication of main steel structures (Rafter) Kết cấu khung thép chính (vì kèo) | C52: Thép SM490, Q355, hoặc tương đương. | D52: kg | E52: 16995.286 | I52: =F52+G52+H52 -> 0 | J52: =ROUND(E52*I52,0) -> 0
A53: 2 | B53: Bracing systems Hệ giằng thép hình | C53: Thép SS400, Q235, CT3 hoặc tương đương. | D53: kg | E53: 4102.9153 | I53: =F53+G53+H53 -> 0 | J53: =ROUND(E53*I53,0) -> 0
A54: 3 | B54: Purlins Xà gồ mái | C54: Thép G450 mạ kẽm, Z275 | D54: kg | E54: 4129.5716 | I54: =F54+G54+H54 -> 0 | J54: =ROUND(E54*I54,0) -> 0
A55: 4 | B55: Purlin bracing Giằng xà gồ | C55: Mạ điện phân | D55: kg | E55: 135.60667 | I55: =F55+G55+H55 -> 0 | J55: =ROUND(E55*I55,0) -> 0
A56: 5 | B56: Steel ladder to roof Thang thép lên mái | C56: H=14m | D56: set | E56: 1 | I56: =F56+G56+H56 -> 0 | J56: =ROUND(E56*I56,0) -> 0
A57: 6 | B57: Painting for steel structure/Sơn cho kết cấu thép | C57: Sơn chống rỉ + Sơn màu alkid SP dày 80mcr | D57: kg | E57: 21098.201 | I57: =F57+G57+H57 -> 0 | J57: =ROUND(E57*I57,0) -> 0
A58: 7 | B58: Anchor Bolts Bu lông neo | C58: 01 bộ: 01 thân+03 Ecu+02 đệm | I58: =F58+G58+H58 -> 0 | J58: =ROUND(E58*I58,0) -> 0
B59: M24*900 | C59: Cấp bền 5.6 mạ đầu ren | D59: set | E59: 16 | I59: =F59+G59+H59 -> 0 | J59: =ROUND(E59*I59,0) -> 0
B60: M20*800 | C60: Cấp bền 5.6 mạ đầu ren | D60: set | E60: 48 | I60: =F60+G60+H60 -> 0 | J60: =ROUND(E60*I60,0) -> 0
A61: 8 | B61: Connection bolt Bu lông liên kết | I61: =F61+G61+H61 -> 0 | J61: =ROUND(E61*I61,0) -> 0
B62: M24*80 | C62: Cấp bền 8.8 | D62: set | E62: 96 | I62: =F62+G62+H62 -> 0 | J62: =ROUND(E62*I62,0) -> 0
B63: M20*70 | C63: Cấp bền 8.8 | D63: set | E63: 120 | I63: =F63+G63+H63 -> 0 | J63: =ROUND(E63*I63,0) -> 0
B64: M12*30 | C64: Cấp bền 8.8 | D64: set | E64: 168 | I64: =F64+G64+H64 -> 0 | J64: =ROUND(E64*I64,0) -> 0
A65: 9 | B65: Transportation of steel structures Vận chuyển kết cấu thép | D65: kg | E65: 25363.38 | I65: =F65+G65+H65 -> 0 | J65: =ROUND(E65*I65,0) -> 0
A66: 10 | B66: Erection of steel structures Lắp dựng kết cấu thép | C66: . | D66: kg | E66: 25363.38 | I66: =F66+G66+H66 -> 0 | J66: =ROUND(E66*I66,0) -> 0
A67: III | B67: Other/ Khác
A68: 1 | B68: Cement grout for base steel column Chèn vữa chân cột | C68: including formwork & silkgrount | D68: ea | E68: 30 | I68: =F68+G68+H68 -> 0 | J68: =ROUND(E68*I68,0) -> 0
A70: B | B70: FINISING WORK / CÔNG TÁC HOÀN THIỆN | J70: =+J71+J74+J79+J94+J116+J122 -> 0
A71: 1 | B71: FLOOR FINISHING WORK / HOÀN THIỆN SÀN | J71: =+SUM(J72:J73) -> 0
A72: 1 | B72: Epoxy painting 3mm Sơn Epoxy 3mm | C72: thk 3.0 mm | D72: m2 | E72: 600 | I72: =+SUM(F72:H72) -> 0 | J72: =ROUND(E72*I72,0) -> 0
A74: 2 | B74: CEILLING WORK / CÔNG TÁC TRẦN | J74: =+SUM(J75:J77) -> 0
A75: 1 | B75: Celing panel EPS 50mm/ Trần panel EPS 50mm | D75: m2 | E75: 600 | I75: =+SUM(F75:H75) -> 0 | J75: =ROUND(E75*I75,0) -> 0
A76: 2 | B76: Aluminum skirting Diềm, phào nhôm | D76: m | E76: 160 | I76: =+SUM(F76:H76) -> 0 | J76: =ROUND(E76*I76,0) -> 0
A77: 3 | B77: Accessories / Vật tư phụ | C77: 5% material | D77: lot | E77: 1 | I77: =+SUM(F77:H77) -> 0 | J77: =ROUND(E77*I77,0) -> 0
I78: =+SUM(F78:G78) -> 0
A79: 3 | B79: OUTSIDE & INSIDE WALL PANEL WORK / CÔNG TÁC VÁCH PANEL | J79: =+SUM(J80:J93) -> 0
A80: I | B80: Partition outside work/ công tác vách ngoài
A81: 1 | B81: Thk75 glasswool panel for external wall/ Ốp tường ngoài bằng glasswool panel dày 75mm | C81: (0.5/0.4; 64kg/m3) | D81: m2 | E81: 913.5 | I81: =+SUM(F81:H81) -> 0 | J81: =ROUND(E81*I81,0) -> 0 | K81: Phuong Nam/ Matec
A82: 2 | B82: C/S Top Parepet cover Diềm bo đỉnh thành parapet | D82: m | E82: 233.2 | I82: =+SUM(F82:H82) -> 0 | J82: =ROUND(E82*I82,0) -> 0
A83: 3 | B83: Aluminum skirting Diềm, phào nhôm | D83: m | E83: 100 | I83: =+SUM(F83:H83) -> 0 | J83: =ROUND(E83*I83,0) -> 0
A84: 4 | B84: C/S bottom flashing, cover edge door & windows Diềm chân tường tôn, diềm bao cửa | C84: 0.45T | D84: m | E84: 495 | I84: =+SUM(F84:H84) -> 0 | J84: =ROUND(E84*I84,0) -> 0
A85: 5 | B85: Accessories / Vật tư phụ | D85: lot | E85: 1 | I85: =+SUM(F85:H85) -> 0 | J85: =ROUND(E85*I85,0) -> 0
A86: 6 | B86: Steel box support for wall Thép hộp hỗ trợ vách tường | C86: Galvanized, steel box 100*100*2mm | D86: kg | E86: 3654 | I86: =+SUM(F86:H86) -> 0 | J86: =ROUND(E86*I86,0) -> 0
A87: 7 | B87: Transportation of steel structures Vận chuyển kết cấu thép | D87: kg | E87: 3654 | I87: =+SUM(F87:H87) -> 0 | J87: =ROUND(E87*I87,0) -> 0
A88: 8 | B88: Erection of steel structures, painting Lắp dựng kết cấu thép, sơn | C88: . | D88: kg | E88: 3654 | I88: =+SUM(F88:H88) -> 0 | J88: =ROUND(E88*I88,0) -> 0
A89: 9 | B89: Forklifts for construction Xe nâng phục vụ thi công | C89: . | D89: lot | E89: 1 | I89: =+SUM(F89:H89) -> 0 | J89: =ROUND(E89*I89,0) -> 0
A90: II | B90: Decor outside work/ công tác trang trí vách ngoài
A91: 1 | B91: Aluminium composite thk 4mm Tấm ốp nhôm composite dày 4mm | C91: Including steel frame | D91: m2 | E91: 42 | I91: =+SUM(F91:H91) -> 0 | J91: =ROUND(E91*I91,0) -> 0 | K91: Alcorest
A92: 2 | B92: Accessories / Vật tư phụ | D92: lot | E92: 1 | I92: =+SUM(F92:H92) -> 0 | J92: =ROUND(E92*I92,0) -> 0
A94: 8 | B94: ROOF WORK/ CÔNG TÁC MÁI | J94: =+SUM(J96:J114) -> 0
A95: I | B95: Roof/ Mái
A96: 1 | B96: Roof seamlock sheet thk 0.5mm / Mái seamlock dày 0.5mm | C96: AZ100 | D96: m2 | E96: 660 | I96: =+SUM(F96:H96) -> 0 | J96: =ROUND(E96*I96,0) -> 0 | K96: Dong A/ Hoa Sen
A97: 2 | B97: Xà gồ phụ Omega, con kê xà gồ, đai kẹp seam.../ Omega purlins, purlin spacers, seam clamps… | C97: galvanized steel thk 0.95mm/1.5mm | D97: m2 | E97: 660 | I97: =+SUM(F97:H97) -> 0 | J97: =ROUND(E97*I97,0) -> 0
A98: 3 | B98: Glasswood layer thk 50mm, 1 layer silver / Lớp glasswood dày 50mm, 1 mặt giấy bạc | C98: thk 64kg/m3 | D98: m2 | E98: 660 | I98: =+SUM(F98:H98) -> 0 | J98: =ROUND(E98*I98,0) -> 0 | K98: Cat Tuong/ Win
A99: 4 | B99: Steel mesh D1.2mm, size 100*100mm layer / Lưới thép sợi 1.2mm ô lưới 100mmx100mm | D99: m2 | E99: 660 | I99: =+SUM(F99:H99) -> 0 | J99: =ROUND(E99*I99,0) -> 0 | K99: =K96 -> Dong A/ Hoa Sen
A100: 5 | B100: Sheet metal color canopy thk 0.45mm / Tôn đơn mái sảnh, dày 0,45mm | C100: AZ100 | D100: m2 | E100: 16 | I100: =+SUM(F100:H100) -> 0 | J100: =ROUND(E100*I100,0) -> 0 | K100: =K99 -> Dong A/ Hoa Sen
A101: 6 | B101: Ridge trim/ Diềm úp nóc | C101: Sheet metal color thk 0,45mm | D101: m | E101: 20 | I101: =+SUM(F101:H101) -> 0 | J101: =ROUND(E101*I101,0) -> 0
A102: 7 | B102: Edge trim/ Diềm cạnh biên | C102: Sheet metal color thk 0,45mm | D102: m | E102: 180 | I102: =+SUM(F102:H102) -> 0 | J102: =ROUND(E102*I102,0) -> 0
A103: 8 | B103: Eave trim/ Diềm đầu hồi | C103: Sheet metal color thk 0,45mm | D103: m | E103: 66 | I103: =+SUM(F103:H103) -> 0 | J103: =ROUND(E103*I103,0) -> 0
A104: 9 | B104: Flashing trim/ Diềm bo, gờ nước | C104: Sheet metal color thk 0,45mm | D104: m | E104: 148 | I104: =+SUM(F104:H104) -> 0 | J104: =ROUND(E104*I104,0) -> 0
A105: 10 | B105: Supplies and accessories / Vật tư phụ | D105: Lot | E105: 1 | I105: =+SUM(F105:H105) -> 0 | J105: =ROUND(E105*I105,0) -> 0
A106: 11 | B106: Transport cost / Chi phí vận chuyển | D106: Lot | E106: 7 | I106: =+SUM(F106:H106) -> 0 | J106: =ROUND(E106*I106,0) -> 0
A107: II | B107: Roof drainage/ Hệ thống thoát nước mái
A108: 1 | B108: Drain pipe pvc D114/ Ống dẫn nước pvc D114 | C108: PN9, thk 5.0mm | D108: m | E108: 76 | I108: =+SUM(F108:H108) -> 0 | J108: =ROUND(E108*I108,0) -> 0 | K108: Tien Phong/Binh Minh
A109: 2 | B109: Downspout elbow/Đai kẹp ống | D109: psc | E109: 63.333333 | I109: =+SUM(F109:H109) -> 0 | J109: =ROUND(E109*I109,0) -> 0 | K109: Bao gồm
A110: 3 | B110: Cầu chắn rác/ Garbage blocking bridge | D110: psc | E110: 8 | I110: =+SUM(F110:H110) -> 0 | J110: =ROUND(E110*I110,0) -> 0
A111: 4 | B111: Máng xối inox 304/ Gutter 304 SUS | C111: W800, thk 0.6mm | D111: m | E111: 72 | I111: =+SUM(F111:H111) -> 0 | J111: =ROUND(E111*I111,0) -> 0
...

Sheet 6.Nhà Để Xe Máy
A1: BILL OF QUANTITIES
A2: =Cover!C7 -> PROJECT NAME / TÊN DỰ ÁN :
A3: 6. BIKE PARKING & PUMP ROOM/ NHÀ XE MÁY & PHÒNG BƠM
A4: NO / STT | B4: WORK SCOPE / CÔNG VIỆC | C4: SPECIFICATION / ĐẶC ĐIỂM KỸ THUẬT | D4: UNIT/ ĐƠN VỊ | E4: QUANTITY / KHỐI LƯỢNG | F4: UNIT PRICE / ĐƠN GIÁ (VNĐ) | J4: AMOUNT / THÀNH TIỀN (VNĐ) | K4: REMARK / GHI CHÚ
F5: MATERIAL / VẬT LIỆU | G5: LABOUR / NHÂN CÔNG | H5: EQUIPMENT / THIẾT BỊ | I5: UNIT PRICE / TỔNG ĐƠN GIÁ
A6: 6 | B6: BIKE PARKING & PUMP ROOM/ NHÀ XE MÁY & PHÒNG BƠM | J6: =+J7+J14 -> 0
A7: A | B7: =B26 -> STRUCTURE WORK / CÔNG TÁC KẾT CẤU | J7: =SUM(J8:J12) -> 0
A8: 1 | B8: =+B27 -> EARTH WORK / CÔNG TÁC ĐẤT | D8: lot | E8: 1 | J8: =+J27 -> 0
A9: =+A8+1 -> 2 | B9: =+B36 -> CONCRETE WORK / CÔNG TÁC BÊ TÔNG | D9: lot | E9: 1 | J9: =+J36 -> 0
A10: =+A9+1 -> 3 | B10: =+B44 -> FORM WORK / CÔNG TÁC VÁN KHUÔN | D10: lot | E10: 1 | J10: =+J44 -> 0
A11: =+A10+1 -> 4 | B11: =+B47 -> REINFORCEMENT WORK / CÔNG TÁC CỐT THÉP | D11: lot | E11: 1 | J11: =+J47 -> 0
A12: =+A11+1 -> 5 | B12: =+B51 -> STEEL STRUCTURE WORK / CÔNG TÁC KẾT CẤU THÉP TIỀN CHẾ | D12: lot | E12: 1 | J12: =+J51 -> 0
A14: B | B14: =B80 -> FINISING WORK / CÔNG TÁC HOÀN THIỆN | J14: =SUM(J15:J21) -> 0
A15: 1 | B15: =B81 -> BRICK WORK / CÔNG TÁC XÂY | D15: lot | E15: 1 | J15: =J81 -> 0
A16: =+A15+1 -> 2 | B16: =B84 -> PLASTERING WORK / CÔNG TÁC TRÁT | D16: lot | E16: 1 | J16: =J84 -> 0
A17: =+A16+1 -> 3 | B17: =B88 -> PAINTING WORK / CÔNG TÁC SƠN | D17: lot | E17: 1 | J17: =J88 -> 0
A18: =+A17+1 -> 4 | B18: =B91 -> TILING & FLOOR FINISHING WORK / ỐP LÁT VÀ HOÀN THIỆN SÀN | D18: lot | E18: 1 | J18: =J91 -> 0
A19: =+A18+1 -> 5 | B19: =B94 -> ROOF WORK/ CÔNG TÁC MÁI | D19: lot | E19: 1 | J19: =J94 -> 0
A20: =+A19+1 -> 6 | B20: =B111 -> DOOR AND WINDOW / CỬA ĐI VÀ CỬA SỔ | D20: lot | E20: 1 | J20: =J111 -> 0
A21: =+A20+1 -> 7 | B21: =B115 -> OTHERS WORK / CÔNG VIỆC KHÁC | D21: lot | E21: 1 | J21: =J115 -> 0
A26: A | B26: STRUCTURE WORK / CÔNG TÁC KẾT CẤU | J26: =+J27+J36+J44+J47+J51 -> 0
A27: 1 | B27: EARTH WORK / CÔNG TÁC ĐẤT | J27: =SUM(J28:J34) -> 0
A28: 1 | B28: Excavation (by Equipment) Đào đất bằng máy | D28: m3 | E28: 579.6336 | I28: =+SUM(F28:H28) -> 0 | J28: =ROUND(E28*I28,0) -> 0
A29: 2 | B29: Excavation (by worker) Đào đất thủ công | D29: m3 | E29: 57.96336 | I29: =+SUM(F29:H29) -> 0 | J29: =ROUND(E29*I29,0) -> 0
A30: 3 | B30: Backfilling soil for foundation Đắp đất | D30: m3 | E30: 231.85344 | I30: =+SUM(F30:H30) -> 0 | J30: =ROUND(E30*I30,0) -> 0
A31: 4 | B31: Remove surplus soil Vận chuyển đất đổ đi | C31: Distance D<=1Km Khoảng cách D<=1Km | D31: m3 | E31: 405.74352 | I31: =+SUM(F31:H31) -> 0 | J31: =ROUND(E31*I31,0) -> 0
A32: 5 | B32: Earth compaction, K=0.9 Đầm đất, K=0.9 | D32: m2 | E32: 370 | I32: =+SUM(F32:H32) -> 0 | J32: =ROUND(E32*I32,0) -> 0
A33: 6 | B33: Compacting by stone aggregate K=0.95 Đá base đầm chặt K=0.95 | C33: Base type I / CPĐD - I Cấp phối đá dăm loại I | D33: m3 | E33: 144.3 | I33: =+SUM(F33:H33) -> 0 | J33: =ROUND(E33*I33,0) -> 0
A34: 7 | B34: 1 layer nylon thk. 0.3mm 1 lớp nylon dày 0.3mm | D34: m2 | E34: 370 | I34: =+SUM(F34:H34) -> 0 | J34: =ROUND(E34*I34,0) -> 0
A36: 3 | B36: CONCRETE WORK / CÔNG TÁC BÊ TÔNG | J36: =SUM(J37:J42) -> 0
A37: 1 | B37: Lean concrete for foundation, ground beam Bê tông lót cho móng, dầm | C37: Gr. 150 | D37: m3 | E37: 6.7568 | I37: =F37+G37+H37 -> 0 | J37: =ROUND(E37*I37,0) -> 0
A38: 2 | B38: Concrete for foundation,beams, ground slab, scolumn Bê tông móng, dầm móng, nền, cổ cột | C38: Gr. 300 | D38: m3 | E38: 89.5688 | I38: =F38+G38+H38 -> 0 | J38: =ROUND(E38*I38,0) -> 0
A39: 3 | B39: Concrete for beams, column Bê tông dầm, cột | C39: Gr. 300 | D39: m3 | E39: 57.9272 | I39: =F39+G39+H39 -> 0 | J39: =ROUND(E39*I39,0) -> 0
A40: 4 | B40: Pump car Bơm bê tông | D40: m3 | E40: 154.2528 | I40: =F40+G40+H40 -> 0 | J40: =ROUND(E40*I40,0) -> 0 | K40: đã bao gồm
A41: 5 | B41: Polishing for slab by machine Xoa nền bằng máy | D41: m2 | E41: 570 | I41: =F41+G41+H41 -> 0 | J41: =ROUND(E41*I41,0) -> 0
A42: 6 | B42: Cutting joint for floor/ Cắt mạch nền | D42: m | E42: 257 | I42: =F42+G42+H42 -> 0 | J42: =ROUND(E42*I42,0) -> 0
A44: 4 | B44: FORM WORK / CÔNG TÁC VÁN KHUÔN | J44: =+SUM(J45:J46) -> 0
A45: 1 | B45: For lean concrete for foundation & ground beam Ván khuôn bê tông lót móng, dầm | D45: m2 | E45: 20.307 | I45: =+SUM(F45:H45) -> 0 | J45: =ROUND(E45*I45,0) -> 0
A46: 2 | B46: For foundation, ground beam, slab, scolumn Ván khuôn móng, dầm, nền, cổ cột | D46: m2 | E46: 397.53 | I46: =+SUM(F46:H46) -> 0 | J46: =ROUND(E46*I46,0) -> 0
A47: 5 | B47: REINFORCEMENT WORK / CÔNG TÁC CỐT THÉP | J47: =+SUM(J48:J49) -> 0
A48: 1 | B48: Re-bar for foundation, ground beam, ground slab Cốt thép móng, dầm, nền | D48: ton | E48: 10.698063 | I48: =+SUM(F48:H48) -> 0 | J48: =ROUND(E48*I48,0) -> 0 | K48: =#REF! -> #REF!
A49: 2 | B49: Re-bar for slab Cốt thép cho sàn | D49: ton | E49: 5.03328 | I49: =+SUM(F49:H49) -> 0 | J49: =ROUND(E49*I49,0) -> 0 | K49: =K48 -> #REF!
A51: 6 | B51: STEEL STRUCTURE WORK / CÔNG TÁC KẾT CẤU THÉP TIỀN CHẾ | J51: =+SUM(J53:J79) -> 0
A52: I | B52: Steel structure Kết cấu thép | I52: =+SUM(F52:G52) -> 0
A53: 1 | B53: Fabrication of main steel structures Kết cấu khung thép chính | C53: Thép SM490, Q355, hoặc tương đương. | D53: kg | E53: 19724.945 | I53: =F53+G53+H53 -> 0 | J53: =ROUND(E53*I53,0) -> 0
A54: 2 | B54: Bracing systems, steel stair Hệ giằng thép hình, thang thép | C54: Thép SS400, Q235, CT3 hoặc tương đương. | D54: kg | E54: 725.04641 | I54: =F54+G54+H54 -> 0 | J54: =ROUND(E54*I54,0) -> 0
A55: 3 | B55: Purlins Xà gồ mái | C55: Thép G350 mạ kẽm, Z275 | D55: kg | E55: 2018.7663 | I55: =F55+G55+H55 -> 0 | J55: =ROUND(E55*I55,0) -> 0
A56: 4 | B56: Purlin bracing Giằng xà gồ | C56: Mạ điện phân | D56: kg | E56: 198.41396 | I56: =F56+G56+H56 -> 0 | J56: =ROUND(E56*I56,0) -> 0
A57: 5 | B57: Painting for steel structure/Sơn cho kết cấu thép | C57: Sơn chống rỉ + Sơn màu alkid SP dày 80mcr | D57: kg | E57: 20449.992 | I57: =F57+G57+H57 -> 0 | J57: =ROUND(E57*I57,0) -> 0
A58: 6 | B58: Steel handrail/ Lan can thép | D58: m | E58: 354 | I58: =F58+G58+H58 -> 0 | J58: =ROUND(E58*I58,0) -> 0
A59: 7 | B59: Anchor Bolts Bu lông neo | C59: 01 bộ: 01 thân+03 Ecu+02 đệm | I59: =F59+G59+H59 -> 0 | J59: =ROUND(E59*I59,0) -> 0
B60: M20*900 | C60: Cấp bền 5.6 mạ đầu ren | D60: set | E60: 120 | I60: =F60+G60+H60 -> 0 | J60: =ROUND(E60*I60,0) -> 0
B61: M16*600 | C61: Cấp bền 5.6 mạ đầu ren | D61: set | E61: 16 | I61: =F61+G61+H61 -> 0 | J61: =ROUND(E61*I61,0) -> 0
A62: 8 | B62: Connection bolt Bu lông liên kết | I62: =F62+G62+H62 -> 0 | J62: =ROUND(E62*I62,0) -> 0
B63: M20*70 | C63: Cấp bền 8.8 | D63: set | E63: 56 | I63: =F63+G63+H63 -> 0 | J63: =ROUND(E63*I63,0) -> 0
B64: M16*50 | C64: Cấp bền 8.8 | D64: set | E64: 600 | I64: =F64+G64+H64 -> 0 | J64: =ROUND(E64*I64,0) -> 0
B65: M14*50 | C65: Cấp bền 8.8 | D65: set | E65: 36 | I65: =F65+G65+H65 -> 0 | J65: =ROUND(E65*I65,0) -> 0
B66: M12*30 | C66: Cấp bền 8.8 | D66: set | E66: 752 | I66: =F66+G66+H66 -> 0 | J66: =ROUND(E66*I66,0) -> 0
A67: 9 | B67: Transportation of steel structures Vận chuyển kết cấu thép | D67: kg | E67: 22667.172 | I67: =F67+G67+H67 -> 0 | J67: =ROUND(E67*I67,0) -> 0
A68: 10 | B68: Erection of steel structures Lắp dựng kết cấu thép | C68: . | D68: kg | E68: 22667.172 | I68: =F68+G68+H68 -> 0 | J68: =ROUND(E68*I68,0) -> 0
A69: II | B69: Deck floor | I69: =+SUM(F69:G69) -> 0
A70: 1 | B70: Decking / Tôn sàn | C70: Galvanized 0.95mm Mạ kẽm dày 0.95mm | D70: m2 | E70: 402.344 | I70: =F70+G70+H70 -> 0 | J70: =ROUND(E70*I70,0) -> 0
A71: 2 | B71: Flashing/ Ke Diềm | D71: m | E71: 187.704 | I71: =F71+G71+H71 -> 0 | J71: =ROUND(E71*I71,0) -> 0
A72: 3 | B72: Thanh giữ ke bo | D72: pcs | E72: 375.408 | I72: =F72+G72+H72 -> 0 | J72: =ROUND(E72*I72,0) -> 0
A73: 4 | B73: Stud/ Đinh hàn | C73: D16*95. | D73: pcs | E73: 935 | I73: =F73+G73+H73 -> 0 | J73: =ROUND(E73*I73,0) -> 0
A74: 5 | B74: Accessories / Vật tư phụ | C74: Screw/Vít bắn tôn sàn, silicon | D74: lot | E74: 1 | I74: =F74+G74+H74 -> 0 | J74: =ROUND(E74*I74,0) -> 0
A75: 6 | B75: Transportation/ Vận chuyển | D75: lot | E75: 1 | I75: =F75+G75+H75 -> 0 | J75: =ROUND(E75*I75,0) -> 0
A77: III | B77: Other/ Khác
A78: 1 | B78: Cement grout for base steel column Chèn vữa chân cột | C78: including formwork & silkgrount | D78: ea | E78: 36 | I78: =F78+G78+H78 -> 0 | J78: =ROUND(E78*I78,0) -> 0
A80: B | B80: FINISING WORK / CÔNG TÁC HOÀN THIỆN | J80: =+J81+J84+J88+J91+J94+J111+J115 -> 0
A81: 1 | B81: BRICK WORK / CÔNG TÁC XÂY | J81: =+SUM(J82:J83) -> 0
A82: 1 | B82: Brick work wall Tường xây gạch | C82: Include linto, bracing | D82: m3 | E82: 12.02 | I82: =+SUM(F82:H82) -> 0 | J82: =ROUND(E82*I82,0) -> 0
A84: 2 | B84: PLASTERING WORK / CÔNG TÁC TRÁT | J84: =+SUM(J85:J87) -> 0
A85: 1 | B85: Plastering wall brick surfaces 1.5cm - outside Trát tường dày 1.5cm - ngoài nhà | D85: m2 | E85: 60.1 | I85: =+SUM(F85:H85) -> 0 | J85: =ROUND(E85*I85,0) -> 0
A86: 2 | B86: Plastering wall brick surfaces 1.5cm - inside Trát tường dày 1.5cm - trong nhà | D86: m2 | E86: 60.1 | I86: =+SUM(F86:H86) -> 0 | J86: =ROUND(E86*I86,0) -> 0
A88: 3 | B88: PAINTING WORK / CÔNG TÁC SƠN | J88: =+SUM(J89:J89) -> 0
A89: 1 | B89: Paint for wall (include putty) Sơn tường (bao gồm bả) | C89: 3 lớp (1 lót + 2 phủ) | D89: m2 | E89: 120.2 | I89: =+SUM(F89:H89) -> 0 | J89: =ROUND(E89*I89,0) -> 0 | K89: =#REF! -> #REF!
A91: 4 | B91: TILING & FLOOR FINISHING WORK / ỐP LÁT VÀ HOÀN THIỆN SÀN | J91: =+SUM(J92:J93) -> 0
A92: 1 | B92: Polishing for slab by liquid hardener Đánh bóng sàn nhà bằng liquid hardener | D92: m2 | E92: 720 | I92: =+SUM(F92:H92) -> 0 | J92: =ROUND(E92*I92,0) -> 0
A94: 5 | B94: ROOF WORK/ CÔNG TÁC MÁI | J94: =+SUM(J96:J109) -> 0
A95: I | B95: Roof/ Mái
A96: 1 | B96: Sheet metal roof thk 0.45mm / Tôn đơn mái dày 0,45mm | C96: AZ100 | D96: m2 | E96: 520.8 | I96: =+SUM(F96:H96) -> 0 | J96: =ROUND(E96*I96,0) -> 0
A97: 2 | B97: Ridge trim/ Diềm úp nóc | C97: Sheet metal color thk 0,45mm | D97: m | E97: 60 | I97: =+SUM(F97:H97) -> 0 | J97: =ROUND(E97*I97,0) -> 0
A98: 3 | B98: Edge trim/ Diềm cạnh biên | C98: Sheet metal color thk 0,45mm | D98: m | E98: 120 | I98: =+SUM(F98:H98) -> 0 | J98: =ROUND(E98*I98,0) -> 0
A99: 4 | B99: Eave trim/ Diềm đầu hồi | C99: Sheet metal color thk 0,45mm | D99: m | E99: 16 | I99: =+SUM(F99:H99) -> 0 | J99: =ROUND(E99*I99,0) -> 0
A100: 5 | B100: Flashing trim/ Diềm bo, gờ nước | C100: Sheet metal color thk 0,45mm | D100: m | E100: 264 | I100: =+SUM(F100:H100) -> 0 | J100: =ROUND(E100*I100,0) -> 0
A101: 6 | B101: Supplies and accessories / Vật tư phụ | D101: Lot | E101: 1 | I101: =+SUM(F101:H101) -> 0 | J101: =ROUND(E101*I101,0) -> 0
A102: II | B102: Roof drainage/ Hệ thống thoát nước mái
A103: 1 | B103: Drain pipe pvc D90/ Ống dẫn nước pvc D90 | D103: m | E103: 260 | I103: =+SUM(F103:H103) -> 0 | J103: =ROUND(E103*I103,0) -> 0 | K103: =#REF! -> #REF!
A104: 2 | B104: Downspout elbow/Đai kẹp ống | D104: psc | E104: 216.66667 | I104: =+SUM(F104:H104) -> 0 | J104: =ROUND(E104*I104,0) -> 0
A105: 3 | B105: Cầu chắn rác/ Garbage blocking bridge | D105: psc | E105: 26 | I105: =+SUM(F105:H105) -> 0 | J105: =ROUND(E105*I105,0) -> 0
A106: 4 | B106: Máng xối inox 304/ Gutter 304 SUS | C106: W600, thk 0.6mm | D106: m | E106: 120 | I106: =+SUM(F106:H106) -> 0 | J106: =ROUND(E106*I106,0) -> 0
A107: 5 | B107: Giá nâng máng xối/ support gutter | D107: ea | E107: 120 | I107: =+SUM(F107:H107) -> 0 | J107: =ROUND(E107*I107,0) -> 0
A108: 6 | B108: Drain pipe inox D90/ Ống dẫn nước inox D90 | D108: m | E108: 26 | I108: =+SUM(F108:H108) -> 0 | J108: =ROUND(E108*I108,0) -> 0
A109: 7 | B109: Accessories / Vật tư phụ | D109: Lot | E109: 1 | I109: =+SUM(F109:H109) -> 0 | J109: =ROUND(E109*I109,0) -> 0
I110: =+SUM(F110:G110) -> 0
A111: 6 | B111: DOOR AND WINDOW / CỬA ĐI VÀ CỬA SỔ | J111: =+SUM(J112:J113) -> 0
A112: 1 | B112: Steel door Cửa đi thép | C112: included accessory/ Bao gồm phụ kiện | D112: m2 | E112: 4.4 | I112: =+SUM(F112:H112) -> 0 | J112: =ROUND(E112*I112,0) -> 0
A113: 2 | B113: Aluminum louver window Cửa chớp nhôm | C113: included accessory/ Bao gồm phụ kiện | D113: m2 | E113: 5.04 | I113: =+SUM(F113:H113) -> 0 | J113: =ROUND(E113*I113,0) -> 0
A115: 7 | B115: OTHERS WORK / CÔNG VIỆC KHÁC | J115: =+SUM(J116:J121) -> 0
...

Sheet 7.Nhà Nghỉ Giữa Ca
A1: BILL OF QUANTITIES
A2: ='C4.Hệ Thống Điện & Điện Nhẹ '!A2:K2 -> PROJECT NAME / TÊN DỰ ÁN :
A3: 7. DORMITORY HOUSE/ NHÀ NGHỈ GIỮA CA
A4: NO / STT | B4: WORK SCOPE / CÔNG VIỆC | C4: SPECIFICATION / ĐẶC ĐIỂM KỸ THUẬT | D4: UNIT/ ĐƠN VỊ | E4: QUANTITY / KHỐI LƯỢNG | F4: UNIT PRICE / ĐƠN GIÁ (VNĐ) | J4: AMOUNT / THÀNH TIỀN (VNĐ) | K4: REMARK / GHI CHÚ
F5: MATERIAL / VẬT LIỆU | G5: LABOUR / NHÂN CÔNG | H5: EQUIPMENT / THIẾT BỊ | I5: UNIT PRICE / TỔNG ĐƠN GIÁ
A6: 7 | B6: DORMITORY HOUSE/ NHÀ NGHỈ GIỮA CA | J6: =+J7+J12 -> 0
A7: A | B7: =$B$23 -> STRUCTURE WORK / CÔNG TÁC KẾT CẤU | J7: =SUM(J8:J11) -> 0
A8: 1 | B8: =+B24 -> EARTH WORK / CÔNG TÁC ĐẤT | D8: lot | E8: 1 | J8: =+J24 -> 0
A9: 2 | B9: =+B33 -> CONCRETE WORK / CÔNG TÁC BÊ TÔNG | D9: lot | E9: 1 | J9: =+J33 -> 0
A10: =+A9+1 -> 3 | B10: =+B40 -> FORM WORK / CÔNG TÁC VÁN KHUÔN | D10: lot | E10: 1 | J10: =+J40 -> 0
A11: =+A10+1 -> 4 | B11: =+B45 -> REINFORCEMENT WORK / CÔNG TÁC CỐT THÉP | D11: lot | E11: 1 | J11: =+J45 -> 0
A12: B | B12: =B50 -> FINISING WORK / CÔNG TÁC HOÀN THIỆN | J12: =SUM(J13:J19) -> 0
A13: 1 | B13: =+B51 -> BRICK WORK / CÔNG TÁC XÂY | D13: lot | E13: 1 | J13: =+J51 -> 0
A14: =+A13+1 -> 2 | B14: =+B54 -> PLASTERING WORK / CÔNG TÁC TRÁT | D14: lot | E14: 1 | J14: =+J54 -> 0
A15: =+A14+1 -> 3 | B15: =+B40 -> FORM WORK / CÔNG TÁC VÁN KHUÔN | D15: lot | E15: 1 | J15: =+J58 -> 0
A16: =+A15+1 -> 4 | B16: =+B45 -> REINFORCEMENT WORK / CÔNG TÁC CỐT THÉP | D16: lot | E16: 1 | J16: =+J61 -> 0
A17: =+A16+1 -> 5 | B17: =+B71 -> WET FINISHING WORK / CÔNG TÁC HOÀN THIỆN MỀM | D17: lot | E17: 1 | J17: =+J71 -> 0
A18: =+A17+1 -> 6 | B18: =+B75 -> DOOR AND WINDOW / CỬA ĐI VÀ CỬA SỔ | D18: lot | E18: 1 | J18: =+J75 -> 0
A19: =+A18+1 -> 7 | B19: =+B79 -> OTHERS WORK/ CÔNG VIỆC KHÁC | D19: lot | E19: 1 | J19: =+J79 -> 0
A23: A | B23: STRUCTURE WORK / CÔNG TÁC KẾT CẤU | J23: =+J24+J33+J40+J45 -> 0
A24: 1 | B24: EARTH WORK / CÔNG TÁC ĐẤT | J24: =SUM(J25:J31) -> 0
A25: 1 | B25: Excavation (by Equipment) Đào đất bằng máy | D25: m3 | E25: 167.5024 | I25: =+SUM(F25:H25) -> 0 | J25: =ROUND(E25*I25,0) -> 0
A26: 2 | B26: Excavation (by worker) Đào đất thủ công | D26: m3 | E26: 33.50048 | I26: =+SUM(F26:H26) -> 0 | J26: =ROUND(E26*I26,0) -> 0
A27: 3 | B27: Backfilling soil for foundation Đắp đất | D27: m3 | E27: 50.25072 | I27: =+SUM(F27:H27) -> 0 | J27: =ROUND(E27*I27,0) -> 0
A28: 4 | B28: Remove surplus soil Vận chuyển đất đổ đi | C28: Distance D<=1Km Khoảng cách D<=1Km | D28: m3 | E28: 150.75216 | I28: =+SUM(F28:H28) -> 0 | J28: =ROUND(E28*I28,0) -> 0
A29: 5 | B29: Earth compaction, K=0.9 Đầm đất, K=0.9 | D29: m2 | E29: 120 | I29: =+SUM(F29:H29) -> 0 | J29: =ROUND(E29*I29,0) -> 0
A30: 6 | B30: Compacting by stone aggregate K=0.95 Đá base đầm chặt K=0.95 | D30: m3 | E30: 46.8 | I30: =+SUM(F30:H30) -> 0 | J30: =ROUND(E30*I30,0) -> 0
A31: 7 | B31: 1 layer nylon thk. 0.3mm 1 lớp nylon dày 0.3mm | D31: m2 | E31: 120 | I31: =+SUM(F31:H31) -> 0 | J31: =ROUND(E31*I31,0) -> 0
A33: 2 | B33: CONCRETE WORK / CÔNG TÁC BÊ TÔNG | J33: =SUM(J34:J38) -> 0
A34: 1 | B34: Lean concrete for foundation & ground beam Bê tông lót cho móng, dầm | C34: Gr. 100 | D34: m3 | E34: 2.40608 | I34: =+SUM(F34:H34) -> 0 | J34: =ROUND(E34*I34,0) -> 0
A35: 2 | B35: Concrete for foundation,beams, ground slab Bê tông móng, dầm móng, nền | C35: Gr. 300 | D35: m3 | E35: 26.93244 | I35: =+SUM(F35:H35) -> 0 | J35: =ROUND(E35*I35,0) -> 0
A36: 3 | B36: Concrete for column, beams, slab roof Bê tông cột, dầm, sàn tầng mái | C36: Gr.300 | D36: m3 | E36: 27.94184 | I36: =+SUM(F36:H36) -> 0 | J36: =ROUND(E36*I36,0) -> 0
A37: 4 | B37: Pump car Bơm bê tông | D37: m3 | E37: 57.28036 | I37: =+SUM(F37:H37) -> 0 | J37: =ROUND(E37*I37,0) -> 0 | K37: đã bao gồm
A38: 5 | B38: Polishing for slab Xoa nền | D38: m2 | E38: 267 | I38: =+SUM(F38:H38) -> 0 | J38: =ROUND(E38*I38,0) -> 0
A40: 3 | B40: FORM WORK / CÔNG TÁC VÁN KHUÔN | J40: =+SUM(J41:J43) -> 0
A41: 1 | B41: For lean concrete for foundation Ván khuôn bê tông lót móng | D41: m2 | E41: 9.66 | I41: =+SUM(F41:H41) -> 0 | J41: =ROUND(E41*I41,0) -> 0
A42: 2 | B42: For foundation, ground beam, slab Ván khuôn móng, dầm, nền | D42: m2 | E42: 110.565 | I42: =+SUM(F42:H42) -> 0 | J42: =ROUND(E42*I42,0) -> 0
A43: 3 | B43: For column, beams, slab roof Ván khuôn cột, dầm, sàn tầng mái | D43: m2 | E43: 271.614 | I43: =+SUM(F43:H43) -> 0 | J43: =ROUND(E43*I43,0) -> 0
A45: 4 | B45: REINFORCEMENT WORK / CÔNG TÁC CỐT THÉP | J45: =+SUM(J46:J48) -> 0
A46: 1 | B46: Re-bar for foundation, ground beam, slab Cốt thép móng, dầm, nền | D46: ton | E46: 2.967066 | I46: =+SUM(F46:H46) -> 0 | J46: =ROUND(E46*I46,0) -> 0
A47: 2 | B47: Re-bar for column, beams, slab roof Cốt thép cột, dầm, sàn tầng mái | D47: ton | E47: 4.017816 | I47: =+SUM(F47:H47) -> 0 | J47: =ROUND(E47*I47,0) -> 0
A50: B | B50: FINISING WORK / CÔNG TÁC HOÀN THIỆN | J50: =+J51+J54+J58+J61+J71+J75+J79 -> 0
A51: 1 | B51: BRICK WORK / CÔNG TÁC XÂY | J51: =+SUM(J52:J53) -> 0
A52: 1 | B52: Brick work wall Tường xây gạch | D52: m3 | E52: 41.61885 | I52: =+SUM(F52:H52) -> 0 | J52: =ROUND(E52*I52,0) -> 0
A54: 2 | B54: PLASTERING WORK / CÔNG TÁC TRÁT | J54: =+SUM(J55:J56) -> 0
A55: 1 | B55: Plastering wall brick surfaces 2.0cm Trát tường dày 2.0cm | D55: m2 | E55: 406.077 | I55: =+SUM(F55:H55) -> 0 | J55: =ROUND(E55*I55,0) -> 0
A56: 2 | B56: Plastering column, celling concrete 2.0cm Trát cột, trần bê tông dày 2.0cm | D56: m2 | E56: 271.614 | I56: =+SUM(F56:H56) -> 0 | J56: =ROUND(E56*I56,0) -> 0
A58: 3 | B58: PAINTING WORK / CÔNG TÁC SƠN | J58: =+SUM(J59:J59) -> 0
A59: 1 | B59: Paint for wall (include putty) Sơn tường (bao gồm bả) | C59: 3 lớp (1 lót + 2 phủ) | D59: m2 | E59: 677.691 | I59: =+SUM(F59:H59) -> 0 | J59: =ROUND(E59*I59,0) -> 0
A61: 4 | B61: TILING & FLOOR FINISHING WORK / ỐP LÁT VÀ HOÀN THIỆN SÀN | J61: =+SUM(J62:J69) -> 0
A62: 1 | B62: Ceramic tile 600x600 / Gạch ceramic 600x600 | C62: 600x600mm | D62: m2 | E62: 25.83 | I62: =+SUM(F62:H62) -> 0 | J62: =ROUND(E62*I62,0) -> 0
A63: 2 | B63: Gạch chân tường 600x100/ skirting ceramic | C63: 600x100mm | D63: m2 | E63: 4.2 | I63: =+SUM(F63:H63) -> 0 | J63: =ROUND(E63*I63,0) -> 0
A64: 3 | B64: Đá granite len cửa/ Granite table | C64: thk 20mm | D64: m | E64: 2.7 | I64: =+SUM(F64:H64) -> 0 | J64: =ROUND(E64*I64,0) -> 0
A65: 4 | B65: Cement for tiling | D65: m2 | E65: 32.73 | I65: =+SUM(F65:H65) -> 0 | J65: =ROUND(E65*I65,0) -> 0 | K65: Bao gồm
A66: 5 | B66: Cement mortar Vữa xi măng tạo dốc mái và mái lanh tô | D66: m2 | E66: 154.35 | I66: =+SUM(F66:H66) -> 0 | J66: =ROUND(E66*I66,0) -> 0
A67: 6 | B67: Gypsum tex 600x600 moisture resistant/ Trần thạch cao xương nổi 600x600mm chống ẩm | C67: For toilet | D67: m2 | E67: 4.914 | I67: =+SUM(F67:H67) -> 0 | J67: =ROUND(E67*I67,0) -> 0
A68: 7 | B68: Gypsum tex 600x600 dày 9mm/ Trần thạch cao xương nổi 600x600mm dày 9mm | D68: m2 | E68: 22.146 | I68: =+SUM(F68:H68) -> 0 | J68: =ROUND(E68*I68,0) -> 0
A69: 8 | B69: Accessories / Vật tư phụ | C69: 5% material | D69: lot | E69: 1 | I69: =+SUM(F69:H69) -> 0 | J69: =ROUND(E69*I69,0) -> 0
A71: 5 | B71: WET FINISHING WORK / CÔNG TÁC HOÀN THIỆN MỀM | J71: =+SUM(J72:J73) -> 0
A72: 1 | B72: Water proofing for concrete roof (include parabet wall ) Chống thấm cho mái ( bao gồm cả parabet ) | C72: Urethane water proofing 3mm thk | D72: m2 | E72: 154.35 | I72: =+SUM(F72:H72) -> 0 | J72: =ROUND(E72*I72,0) -> 0
A73: 2 | B73: Liquid water proofing for toilet 2 layer Lớp chống thấm cho phòng vệ sinh 2 lớp | C73: Silk Seal -wp1000, 1.5 kg /m2 / layer, mortar protection 15mm | D73: m2 | E73: 15.74 | I73: =+SUM(F73:H73) -> 0 | J73: =ROUND(E73*I73,0) -> 0
A75: 6 | B75: DOOR AND WINDOW / CỬA ĐI VÀ CỬA SỔ | J75: =+SUM(J76:J77) -> 0
A76: 1 | B76: Aluminum door Cửa đi nhôm kính | C76: included accessory/ Bao gồm phụ kiện | D76: m2 | E76: 5.94 | I76: =+SUM(F76:H76) -> 0 | J76: =ROUND(E76*I76,0) -> 0 | K76: ='[79]2.Nhà Xưởng & Văn Phòng'!K214 -> Xingfa
A77: 2 | B77: Aluminum window Cửa sổ nhôm kính | C77: included accessory/ Bao gồm phụ kiện | D77: m2 | E77: 19.44 | I77: =+SUM(F77:H77) -> 0 | J77: =ROUND(E77*I77,0) -> 0 | K77: =K76 -> Xingfa
A79: 7 | B79: OTHERS WORK/ CÔNG VIỆC KHÁC | J79: =+SUM(J80:J82) -> 0
A80: 1 | B80: UPVC dowspout D90 Ống dẫn nước UPVC D90 | D80: m | E80: 72 | I80: =+SUM(F80:H80) -> 0 | J80: =ROUND(E80*I80,0) -> 0
A81: 2 | B81: Cút D90 | D81: set | E81: 12 | I81: =+SUM(F81:H81) -> 0 | J81: =ROUND(E81*I81,0) -> 0
A82: 3 | B82: Accessories / Vật tư phụ | D82: lot | E82: 1 | I82: =+SUM(F82:H82) -> 0 | J82: =ROUND(E82*I82,0) -> 0 | K82: bao gồm

Sheet 8.Nhà Bảo Vệ 1
A1: BILL OF QUANTITIES
A2: ='C4.Hệ Thống Điện & Điện Nhẹ '!A2:K2 -> PROJECT NAME / TÊN DỰ ÁN :
A3: 8. GUARD HOUSE 1/ NHÀ BẢO VỆ 1
A4: NO / STT | B4: WORK SCOPE / CÔNG VIỆC | C4: SPECIFICATION / ĐẶC ĐIỂM KỸ THUẬT | D4: UNIT/ ĐƠN VỊ | E4: QUANTITY / KHỐI LƯỢNG | F4: UNIT PRICE / ĐƠN GIÁ (VNĐ) | J4: AMOUNT / THÀNH TIỀN (VNĐ) | K4: REMARK / GHI CHÚ
F5: MATERIAL / VẬT LIỆU | G5: LABOUR / NHÂN CÔNG | H5: EQUIPMENT / THIẾT BỊ | I5: UNIT PRICE / TỔNG ĐƠN GIÁ
A6: 8 | B6: GUARD HOUSE 1/ NHÀ BẢO VỆ 1 | J6: =+J7+J12 -> 0
A7: A | B7: =$B$23 -> STRUCTURE WORK / CÔNG TÁC KẾT CẤU | J7: =SUM(J8:J11) -> 0
A8: 1 | B8: =+B24 -> EARTH WORK / CÔNG TÁC ĐẤT | D8: lot | E8: 1 | J8: =+J24 -> 0
A9: 2 | B9: =+B33 -> CONCRETE WORK / CÔNG TÁC BÊ TÔNG | D9: lot | E9: 1 | J9: =+J33 -> 0
A10: =+A9+1 -> 3 | B10: =+B40 -> FORM WORK / CÔNG TÁC VÁN KHUÔN | D10: lot | E10: 1 | J10: =+J40 -> 0
A11: =+A10+1 -> 4 | B11: =+B45 -> REINFORCEMENT WORK / CÔNG TÁC CỐT THÉP | D11: lot | E11: 1 | J11: =+J45 -> 0
A12: B | B12: =B50 -> FINISING WORK / CÔNG TÁC HOÀN THIỆN | J12: =SUM(J13:J19) -> 0
A13: 1 | B13: =+B51 -> BRICK WORK / CÔNG TÁC XÂY | D13: lot | E13: 1 | J13: =+J51 -> 0
A14: =+A13+1 -> 2 | B14: =+B54 -> PLASTERING WORK / CÔNG TÁC TRÁT | D14: lot | E14: 1 | J14: =+J54 -> 0
A15: =+A14+1 -> 3 | B15: =+B40 -> FORM WORK / CÔNG TÁC VÁN KHUÔN | D15: lot | E15: 1 | J15: =+J58 -> 0
A16: =+A15+1 -> 4 | B16: =+B45 -> REINFORCEMENT WORK / CÔNG TÁC CỐT THÉP | D16: lot | E16: 1 | J16: =+J61 -> 0
A17: =+A16+1 -> 5 | B17: =+B71 -> WET FINISHING WORK / CÔNG TÁC HOÀN THIỆN MỀM | D17: lot | E17: 1 | J17: =+J71 -> 0
A18: =+A17+1 -> 6 | B18: =+B75 -> DOOR AND WINDOW / CỬA ĐI VÀ CỬA SỔ | D18: lot | E18: 1 | J18: =+J75 -> 0
A19: =+A18+1 -> 7 | B19: =+B79 -> OTHERS WORK/ CÔNG VIỆC KHÁC | D19: lot | E19: 1 | J19: =+J79 -> 0
A23: A | B23: STRUCTURE WORK / CÔNG TÁC KẾT CẤU | J23: =+J24+J33+J40+J45 -> 0
A24: 1 | B24: EARTH WORK / CÔNG TÁC ĐẤT | J24: =SUM(J25:J31) -> 0
A25: 1 | B25: Excavation (by Equipment) Đào đất bằng máy | D25: m3 | E25: 50.4088 | I25: =+SUM(F25:H25) -> 0 | J25: =ROUND(E25*I25,0) -> 0
A26: 2 | B26: Excavation (by worker) Đào đất thủ công | D26: m3 | E26: 10.08176 | I26: =+SUM(F26:H26) -> 0 | J26: =ROUND(E26*I26,0) -> 0
A27: 3 | B27: Backfilling soil for foundation Đắp đất | D27: m3 | E27: 15.12264 | I27: =+SUM(F27:H27) -> 0 | J27: =ROUND(E27*I27,0) -> 0
A28: 4 | B28: Remove surplus soil Vận chuyển đất đổ đi | C28: Distance D<=1Km Khoảng cách D<=1Km | D28: m3 | E28: 45.36792 | I28: =+SUM(F28:H28) -> 0 | J28: =ROUND(E28*I28,0) -> 0
A29: 5 | B29: Earth compaction, K=0.9 Đầm đất, K=0.9 | D29: m2 | E29: 15 | I29: =+SUM(F29:H29) -> 0 | J29: =ROUND(E29*I29,0) -> 0
A30: 6 | B30: Compacting by stone aggregate K=0.95 Đá base đầm chặt K=0.95 | D30: m3 | E30: 5.85 | I30: =+SUM(F30:H30) -> 0 | J30: =ROUND(E30*I30,0) -> 0
A31: 7 | B31: 1 layer nylon thk. 0.3mm 1 lớp nylon dày 0.3mm | D31: m2 | E31: 15 | I31: =+SUM(F31:H31) -> 0 | J31: =ROUND(E31*I31,0) -> 0
A33: 2 | B33: CONCRETE WORK / CÔNG TÁC BÊ TÔNG | J33: =SUM(J34:J38) -> 0
A34: 1 | B34: Lean concrete for foundation & ground beam Bê tông lót cho móng, dầm | C34: Gr. 100 | D34: m3 | E34: 0.8446 | I34: =+SUM(F34:H34) -> 0 | J34: =ROUND(E34*I34,0) -> 0
A35: 2 | B35: Concrete for foundation,beams, ground slab Bê tông móng, dầm móng, nền | C35: Gr. 300 | D35: m3 | E35: 6.30978 | I35: =+SUM(F35:H35) -> 0 | J35: =ROUND(E35*I35,0) -> 0
A36: 3 | B36: Concrete for column, beams, slab roof Bê tông cột, dầm, sàn tầng mái | C36: Gr.300 | D36: m3 | E36: 5.0264 | I36: =+SUM(F36:H36) -> 0 | J36: =ROUND(E36*I36,0) -> 0
A37: 4 | B37: Pump car Bơm bê tông | D37: m3 | E37: 12.18078 | I37: =+SUM(F37:H37) -> 0 | J37: =ROUND(E37*I37,0) -> 0 | K37: đã bao gồm
A38: 5 | B38: Polishing for slab Xoa nền | D38: m2 | E38: 39 | I38: =+SUM(F38:H38) -> 0 | J38: =ROUND(E38*I38,0) -> 0
A40: 3 | B40: FORM WORK / CÔNG TÁC VÁN KHUÔN | J40: =+SUM(J41:J43) -> 0
A41: 1 | B41: For lean concrete for foundation Ván khuôn bê tông lót móng | D41: m2 | E41: 3.465 | I41: =+SUM(F41:H41) -> 0 | J41: =ROUND(E41*I41,0) -> 0
A42: 2 | B42: For foundation, ground beam, slab Ván khuôn móng, dầm, nền | D42: m2 | E42: 37.926 | I42: =+SUM(F42:H42) -> 0 | J42: =ROUND(E42*I42,0) -> 0
A43: 3 | B43: For column, beams, slab roof Ván khuôn cột, dầm, sàn tầng mái | D43: m2 | E43: 51.576 | I43: =+SUM(F43:H43) -> 0 | J43: =ROUND(E43*I43,0) -> 0
A45: 4 | B45: REINFORCEMENT WORK / CÔNG TÁC CỐT THÉP | J45: =+SUM(J46:J48) -> 0
A46: 1 | B46: Re-bar for foundation, ground beam, slab Cốt thép móng, dầm, nền | D46: ton | E46: 0.630978 | I46: =+SUM(F46:H46) -> 0 | J46: =ROUND(E46*I46,0) -> 0
A47: 2 | B47: Re-bar for column, beams, slab roof Cốt thép cột, dầm, sàn tầng mái | D47: ton | E47: 0.75396 | I47: =+SUM(F47:H47) -> 0 | J47: =ROUND(E47*I47,0) -> 0
A50: B | B50: FINISING WORK / CÔNG TÁC HOÀN THIỆN | J50: =+J51+J54+J58+J61+J71+J75+J79 -> 0
A51: 1 | B51: BRICK WORK / CÔNG TÁC XÂY | J51: =+SUM(J52:J53) -> 0
A52: 1 | B52: Brick work wall Tường xây gạch | D52: m3 | E52: 13.0326 | I52: =+SUM(F52:H52) -> 0 | J52: =ROUND(E52*I52,0) -> 0
A54: 2 | B54: PLASTERING WORK / CÔNG TÁC TRÁT | J54: =+SUM(J55:J56) -> 0
A55: 1 | B55: Plastering wall brick surfaces 2.0cm Trát tường dày 2.0cm | D55: m2 | E55: 139.692 | I55: =+SUM(F55:H55) -> 0 | J55: =ROUND(E55*I55,0) -> 0
A56: 2 | B56: Plastering column, celling concrete 2.0cm Trát cột, trần bê tông dày 2.0cm | D56: m2 | E56: 51.576 | I56: =+SUM(F56:H56) -> 0 | J56: =ROUND(E56*I56,0) -> 0
A58: 3 | B58: PAINTING WORK / CÔNG TÁC SƠN | J58: =+SUM(J59:J59) -> 0
A59: 1 | B59: Paint for wall (include putty) Sơn tường (bao gồm bả) | C59: 3 lớp (1 lót + 2 phủ) | D59: m2 | E59: 191.268 | I59: =+SUM(F59:H59) -> 0 | J59: =ROUND(E59*I59,0) -> 0
A61: 4 | B61: TILING & FLOOR FINISHING WORK / ỐP LÁT VÀ HOÀN THIỆN SÀN | J61: =+SUM(J62:J69) -> 0
A62: 1 | B62: Ceramic tile 600x600 / Gạch ceramic 600x600 | C62: 600x600mm | D62: m2 | E62: 15.75 | I62: =+SUM(F62:H62) -> 0 | J62: =ROUND(E62*I62,0) -> 0
A63: 2 | B63: Gạch chân tường 600x100/ skirting ceramic | C63: 600x100mm | D63: m2 | E63: 3.36 | I63: =+SUM(F63:H63) -> 0 | J63: =ROUND(E63*I63,0) -> 0
A64: 3 | B64: Đá granite bậu cửa/ Granite table | C64: thk 20mm, W600 | D64: m | E64: 6 | I64: =+SUM(F64:H64) -> 0 | J64: =ROUND(E64*I64,0) -> 0
A65: 4 | B65: Cement for tiling | D65: m2 | E65: 25.11 | I65: =+SUM(F65:H65) -> 0 | J65: =ROUND(E65*I65,0) -> 0 | K65: Đã bao gồm
A66: 5 | B66: Cement mortar Vữa xi măng tạo dốc mái và mái lanh tô | D66: m2 | E66: 25.2 | I66: =+SUM(F66:H66) -> 0 | J66: =ROUND(E66*I66,0) -> 0
A67: 6 | B67: Gypsum tex 600x600 moisture resistant/ Trần thạch cao xương nổi 600x600mm chống ẩm | C67: For toilet | D67: m2 | E67: 3.96 | I67: =+SUM(F67:H67) -> 0 | J67: =ROUND(E67*I67,0) -> 0
A68: 7 | B68: Gypsum tex 600x600 dày 9mm/ Trần thạch cao xương nổi 600x600mm dày 9mm | D68: m2 | E68: 18.04 | I68: =+SUM(F68:H68) -> 0 | J68: =ROUND(E68*I68,0) -> 0
A69: 8 | B69: Accessories / Vật tư phụ | C69: 5% material | D69: lot | E69: 1 | I69: =+SUM(F69:H69) -> 0 | J69: =ROUND(E69*I69,0) -> 0
A71: 5 | B71: WET FINISHING WORK / CÔNG TÁC HOÀN THIỆN MỀM | J71: =+SUM(J72:J73) -> 0
A72: 1 | B72: Water proofing for concrete roof (include parabet wall ) Chống thấm cho mái ( bao gồm cả parabet ) | C72: Urethane water proofing 3mm thk | D72: m2 | E72: 25.2 | I72: =+SUM(F72:H72) -> 0 | J72: =ROUND(E72*I72,0) -> 0
A73: 2 | B73: Liquid water proofing for toilet 2 layer Lớp chống thấm cho phòng vệ sinh 2 lớp | C73: Silk Seal -wp1000, 1.5 kg /m2 / layer, mortar protection 15mm | D73: m2 | E73: 12.96 | I73: =+SUM(F73:H73) -> 0 | J73: =ROUND(E73*I73,0) -> 0
A75: 6 | B75: DOOR AND WINDOW / CỬA ĐI VÀ CỬA SỔ | J75: =+SUM(J76:J77) -> 0
A76: 1 | B76: Aluminum door Cửa đi nhôm kính | C76: included accessory/ Bao gồm phụ kiện | D76: m2 | E76: 3.96 | I76: =+SUM(F76:H76) -> 0 | J76: =ROUND(E76*I76,0) -> 0 | K76: ='[79]2.Nhà Xưởng & Văn Phòng'!K214 -> Xingfa
A77: 2 | B77: Aluminum window Cửa sổ nhôm kính | C77: included accessory/ Bao gồm phụ kiện | D77: m2 | E77: 7.92 | I77: =+SUM(F77:H77) -> 0 | J77: =ROUND(E77*I77,0) -> 0 | K77: =K76 -> Xingfa
A79: 7 | B79: OTHERS WORK/ CÔNG VIỆC KHÁC | J79: =+SUM(J80:J82) -> 0
A80: 1 | B80: UPVC dowspout D60 Ống dẫn nước UPVC D60 | D80: m | E80: 16 | I80: =+SUM(F80:H80) -> 0 | J80: =ROUND(E80*I80,0) -> 0
A81: 2 | B81: Cút D60 | D81: set | E81: 8 | I81: =+SUM(F81:H81) -> 0 | J81: =ROUND(E81*I81,0) -> 0
A82: 3 | B82: Accessories / Vật tư phụ | D82: lot | E82: 1 | I82: =+SUM(F82:H82) -> 0 | J82: =ROUND(E82*I82,0) -> 0 | K82: bao gồm

Sheet 9.Nhà Bảo Vệ 2
A1: BILL OF QUANTITIES
A2: ='C4.Hệ Thống Điện & Điện Nhẹ '!A2:K2 -> PROJECT NAME / TÊN DỰ ÁN :
A3: 9. GUARD HOUSE 2/ NHÀ BẢO VỆ 2
A4: NO / STT | B4: WORK SCOPE / CÔNG VIỆC | C4: SPECIFICATION / ĐẶC ĐIỂM KỸ THUẬT | D4: UNIT/ ĐƠN VỊ | E4: QUANTITY / KHỐI LƯỢNG | F4: UNIT PRICE / ĐƠN GIÁ (VNĐ) | J4: AMOUNT / THÀNH TIỀN (VNĐ) | K4: REMARK / GHI CHÚ
F5: MATERIAL / VẬT LIỆU | G5: LABOUR / NHÂN CÔNG | H5: EQUIPMENT / THIẾT BỊ | I5: UNIT PRICE / TỔNG ĐƠN GIÁ
A6: 9 | B6: GUARD HOUSE 2/ NHÀ BẢO VỆ 2 | J6: =+J7+J12 -> 0
A7: A | B7: =$B$23 -> STRUCTURE WORK / CÔNG TÁC KẾT CẤU | J7: =SUM(J8:J11) -> 0
A8: 1 | B8: =+B24 -> EARTH WORK / CÔNG TÁC ĐẤT | D8: lot | E8: 1 | J8: =+J24 -> 0
A9: 2 | B9: =+B33 -> CONCRETE WORK / CÔNG TÁC BÊ TÔNG | D9: lot | E9: 1 | J9: =+J33 -> 0
A10: =+A9+1 -> 3 | B10: =+B40 -> FORM WORK / CÔNG TÁC VÁN KHUÔN | D10: lot | E10: 1 | J10: =+J40 -> 0
A11: =+A10+1 -> 4 | B11: =+B45 -> REINFORCEMENT WORK / CÔNG TÁC CỐT THÉP | D11: lot | E11: 1 | J11: =+J45 -> 0
A12: B | B12: =B50 -> FINISING WORK / CÔNG TÁC HOÀN THIỆN | J12: =SUM(J13:J19) -> 0
A13: 1 | B13: =+B51 -> BRICK WORK / CÔNG TÁC XÂY | D13: lot | E13: 1 | J13: =+J51 -> 0
A14: =+A13+1 -> 2 | B14: =+B54 -> PLASTERING WORK / CÔNG TÁC TRÁT | D14: lot | E14: 1 | J14: =+J54 -> 0
A15: =+A14+1 -> 3 | B15: =+B40 -> FORM WORK / CÔNG TÁC VÁN KHUÔN | D15: lot | E15: 1 | J15: =+J58 -> 0
A16: =+A15+1 -> 4 | B16: =+B45 -> REINFORCEMENT WORK / CÔNG TÁC CỐT THÉP | D16: lot | E16: 1 | J16: =+J61 -> 0
A17: =+A16+1 -> 5 | B17: =+B71 -> WET FINISHING WORK / CÔNG TÁC HOÀN THIỆN MỀM | D17: lot | E17: 1 | J17: =+J71 -> 0
A18: =+A17+1 -> 6 | B18: =+B75 -> DOOR AND WINDOW / CỬA ĐI VÀ CỬA SỔ | D18: lot | E18: 1 | J18: =+J75 -> 0
A19: =+A18+1 -> 7 | B19: =+B79 -> OTHERS WORK/ CÔNG VIỆC KHÁC | D19: lot | E19: 1 | J19: =+J79 -> 0
A23: A | B23: STRUCTURE WORK / CÔNG TÁC KẾT CẤU | J23: =+J24+J33+J40+J45 -> 0
A24: 1 | B24: EARTH WORK / CÔNG TÁC ĐẤT | J24: =SUM(J25:J31) -> 0
A25: 1 | B25: Excavation (by Equipment) Đào đất bằng máy | D25: m3 | E25: 50.4088 | I25: =+SUM(F25:H25) -> 0 | J25: =ROUND(E25*I25,0) -> 0
A26: 2 | B26: Excavation (by worker) Đào đất thủ công | D26: m3 | E26: 10.08176 | I26: =+SUM(F26:H26) -> 0 | J26: =ROUND(E26*I26,0) -> 0
A27: 3 | B27: Backfilling soil for foundation Đắp đất | D27: m3 | E27: 15.12264 | I27: =+SUM(F27:H27) -> 0 | J27: =ROUND(E27*I27,0) -> 0
A28: 4 | B28: Remove surplus soil Vận chuyển đất đổ đi | C28: Distance D<=1Km Khoảng cách D<=1Km | D28: m3 | E28: 45.36792 | I28: =+SUM(F28:H28) -> 0 | J28: =ROUND(E28*I28,0) -> 0
A29: 5 | B29: Earth compaction, K=0.9 Đầm đất, K=0.9 | D29: m2 | E29: 15 | I29: =+SUM(F29:H29) -> 0 | J29: =ROUND(E29*I29,0) -> 0
A30: 6 | B30: Compacting by stone aggregate K=0.95 Đá base đầm chặt K=0.95 | D30: m3 | E30: 5.85 | I30: =+SUM(F30:H30) -> 0 | J30: =ROUND(E30*I30,0) -> 0
A31: 7 | B31: 1 layer nylon thk. 0.3mm 1 lớp nylon dày 0.3mm | D31: m2 | E31: 15 | I31: =+SUM(F31:H31) -> 0 | J31: =ROUND(E31*I31,0) -> 0
A33: 2 | B33: CONCRETE WORK / CÔNG TÁC BÊ TÔNG | J33: =SUM(J34:J38) -> 0
A34: 1 | B34: Lean concrete for foundation & ground beam Bê tông lót cho móng, dầm | C34: Gr. 100 | D34: m3 | E34: 0.8446 | I34: =+SUM(F34:H34) -> 0 | J34: =ROUND(E34*I34,0) -> 0
A35: 2 | B35: Concrete for foundation,beams, ground slab Bê tông móng, dầm móng, nền | C35: Gr. 300 | D35: m3 | E35: 6.30978 | I35: =+SUM(F35:H35) -> 0 | J35: =ROUND(E35*I35,0) -> 0
A36: 3 | B36: Concrete for column, beams, slab roof Bê tông cột, dầm, sàn tầng mái | C36: Gr.300 | D36: m3 | E36: 5.0264 | I36: =+SUM(F36:H36) -> 0 | J36: =ROUND(E36*I36,0) -> 0
A37: 4 | B37: Pump car Bơm bê tông | D37: m3 | E37: 12.18078 | I37: =+SUM(F37:H37) -> 0 | J37: =ROUND(E37*I37,0) -> 0 | K37: đã bao gồm
A38: 5 | B38: Polishing for slab Xoa nền | D38: m2 | E38: 39 | I38: =+SUM(F38:H38) -> 0 | J38: =ROUND(E38*I38,0) -> 0
A40: 3 | B40: FORM WORK / CÔNG TÁC VÁN KHUÔN | J40: =+SUM(J41:J43) -> 0
A41: 1 | B41: For lean concrete for foundation Ván khuôn bê tông lót móng | D41: m2 | E41: 3.465 | I41: =+SUM(F41:H41) -> 0 | J41: =ROUND(E41*I41,0) -> 0
A42: 2 | B42: For foundation, ground beam, slab Ván khuôn móng, dầm, nền | D42: m2 | E42: 37.926 | I42: =+SUM(F42:H42) -> 0 | J42: =ROUND(E42*I42,0) -> 0
A43: 3 | B43: For column, beams, slab roof Ván khuôn cột, dầm, sàn tầng mái | D43: m2 | E43: 51.576 | I43: =+SUM(F43:H43) -> 0 | J43: =ROUND(E43*I43,0) -> 0
A45: 4 | B45: REINFORCEMENT WORK / CÔNG TÁC CỐT THÉP | J45: =+SUM(J46:J48) -> 0
A46: 1 | B46: Re-bar for foundation, ground beam, slab Cốt thép móng, dầm, nền | D46: ton | E46: 0.630978 | I46: =+SUM(F46:H46) -> 0 | J46: =ROUND(E46*I46,0) -> 0
A47: 2 | B47: Re-bar for column, beams, slab roof Cốt thép cột, dầm, sàn tầng mái | D47: ton | E47: 0.75396 | I47: =+SUM(F47:H47) -> 0 | J47: =ROUND(E47*I47,0) -> 0
A50: B | B50: FINISING WORK / CÔNG TÁC HOÀN THIỆN | J50: =+J51+J54+J58+J61+J71+J75+J79 -> 0
A51: 1 | B51: BRICK WORK / CÔNG TÁC XÂY | J51: =+SUM(J52:J53) -> 0
A52: 1 | B52: Brick work wall Tường xây gạch | D52: m3 | E52: 13.0326 | I52: =+SUM(F52:H52) -> 0 | J52: =ROUND(E52*I52,0) -> 0
A54: 2 | B54: PLASTERING WORK / CÔNG TÁC TRÁT | J54: =+SUM(J55:J56) -> 0
A55: 1 | B55: Plastering wall brick surfaces 2.0cm Trát tường dày 2.0cm | D55: m2 | E55: 139.692 | I55: =+SUM(F55:H55) -> 0 | J55: =ROUND(E55*I55,0) -> 0
A56: 2 | B56: Plastering column, celling concrete 2.0cm Trát cột, trần bê tông dày 2.0cm | D56: m2 | E56: 51.576 | I56: =+SUM(F56:H56) -> 0 | J56: =ROUND(E56*I56,0) -> 0
A58: 3 | B58: PAINTING WORK / CÔNG TÁC SƠN | J58: =+SUM(J59:J59) -> 0
A59: 1 | B59: Paint for wall (include putty) Sơn tường (bao gồm bả) | C59: 3 lớp (1 lót + 2 phủ) | D59: m2 | E59: 191.268 | I59: =+SUM(F59:H59) -> 0 | J59: =ROUND(E59*I59,0) -> 0
A61: 4 | B61: TILING & FLOOR FINISHING WORK / ỐP LÁT VÀ HOÀN THIỆN SÀN | J61: =+SUM(J62:J69) -> 0
A62: 1 | B62: Ceramic tile 600x600 / Gạch ceramic 600x600 | C62: 600x600mm | D62: m2 | E62: 15.75 | I62: =+SUM(F62:H62) -> 0 | J62: =ROUND(E62*I62,0) -> 0
A63: 2 | B63: Gạch chân tường 600x100/ skirting ceramic | C63: 600x100mm | D63: m2 | E63: 3.36 | I63: =+SUM(F63:H63) -> 0 | J63: =ROUND(E63*I63,0) -> 0
A64: 3 | B64: Đá granite bậu cửa/ Granite table | C64: thk 20mm, W600 | D64: m | E64: 6 | I64: =+SUM(F64:H64) -> 0 | J64: =ROUND(E64*I64,0) -> 0
A65: 4 | B65: Cement for tiling | D65: m2 | E65: 25.11 | I65: =+SUM(F65:H65) -> 0 | J65: =ROUND(E65*I65,0) -> 0 | K65: Đã bao gồm
A66: 5 | B66: Cement mortar Vữa xi măng tạo dốc mái và mái lanh tô | D66: m2 | E66: 25.2 | I66: =+SUM(F66:H66) -> 0 | J66: =ROUND(E66*I66,0) -> 0
A67: 6 | B67: Gypsum tex 600x600 moisture resistant/ Trần thạch cao xương nổi 600x600mm chống ẩm | C67: For toilet | D67: m2 | E67: 3.96 | I67: =+SUM(F67:H67) -> 0 | J67: =ROUND(E67*I67,0) -> 0
A68: 7 | B68: Gypsum tex 600x600 dày 9mm/ Trần thạch cao xương nổi 600x600mm dày 9mm | D68: m2 | E68: 18.04 | I68: =+SUM(F68:H68) -> 0 | J68: =ROUND(E68*I68,0) -> 0
A69: 8 | B69: Accessories / Vật tư phụ | C69: 5% material | D69: lot | E69: 1 | I69: =+SUM(F69:H69) -> 0 | J69: =ROUND(E69*I69,0) -> 0
A71: 5 | B71: WET FINISHING WORK / CÔNG TÁC HOÀN THIỆN MỀM | J71: =+SUM(J72:J73) -> 0
A72: 1 | B72: Water proofing for concrete roof (include parabet wall ) Chống thấm cho mái ( bao gồm cả parabet ) | C72: Urethane water proofing 3mm thk | D72: m2 | E72: 25.2 | I72: =+SUM(F72:H72) -> 0 | J72: =ROUND(E72*I72,0) -> 0
A73: 2 | B73: Liquid water proofing for toilet 2 layer Lớp chống thấm cho phòng vệ sinh 2 lớp | C73: Silk Seal -wp1000, 1.5 kg /m2 / layer, mortar protection 15mm | D73: m2 | E73: 12.96 | I73: =+SUM(F73:H73) -> 0 | J73: =ROUND(E73*I73,0) -> 0
A75: 6 | B75: DOOR AND WINDOW / CỬA ĐI VÀ CỬA SỔ | J75: =+SUM(J76:J77) -> 0
A76: 1 | B76: Aluminum door Cửa đi nhôm kính | C76: included accessory/ Bao gồm phụ kiện | D76: m2 | E76: 3.96 | I76: =+SUM(F76:H76) -> 0 | J76: =ROUND(E76*I76,0) -> 0 | K76: ='[79]2.Nhà Xưởng & Văn Phòng'!K214 -> Xingfa
A77: 2 | B77: Aluminum window Cửa sổ nhôm kính | C77: included accessory/ Bao gồm phụ kiện | D77: m2 | E77: 7.92 | I77: =+SUM(F77:H77) -> 0 | J77: =ROUND(E77*I77,0) -> 0 | K77: =K76 -> Xingfa
A79: 7 | B79: OTHERS WORK/ CÔNG VIỆC KHÁC | J79: =+SUM(J80:J82) -> 0
A80: 1 | B80: UPVC dowspout D60 Ống dẫn nước UPVC D60 | D80: m | E80: 16 | I80: =+SUM(F80:H80) -> 0 | J80: =ROUND(E80*I80,0) -> 0
A81: 2 | B81: Cút D60 | D81: set | E81: 8 | I81: =+SUM(F81:H81) -> 0 | J81: =ROUND(E81*I81,0) -> 0
A82: 3 | B82: Accessories / Vật tư phụ | D82: lot | E82: 1 | I82: =+SUM(F82:H82) -> 0 | J82: =ROUND(E82*I82,0) -> 0

Sheet 10.Nhà Rác, Phòng Điện
A1: BILL OF QUANTITIES
A2: ='C4.Hệ Thống Điện & Điện Nhẹ '!A2:K2 -> PROJECT NAME / TÊN DỰ ÁN :
A3: 10. GARBAGE, TRANSFORMER HOUSE/ NHÀ RÁC, PHÒNG ĐIỆN
A4: NO / STT | B4: WORK SCOPE / CÔNG VIỆC | C4: SPECIFICATION / ĐẶC ĐIỂM KỸ THUẬT | D4: UNIT/ ĐƠN VỊ | E4: QUANTITY / KHỐI LƯỢNG | F4: UNIT PRICE / ĐƠN GIÁ (VNĐ) | J4: AMOUNT / THÀNH TIỀN (VNĐ) | K4: REMARK / GHI CHÚ
F5: MATERIAL / VẬT LIỆU | G5: LABOUR / NHÂN CÔNG | H5: EQUIPMENT / THIẾT BỊ | I5: UNIT PRICE / TỔNG ĐƠN GIÁ
A6: 10 | B6: GARBAGE, TRANSFORMER HOUSE/ NHÀ RÁC, PHÒNG ĐIỆN | J6: =+J7+J12 -> 0
A7: A | B7: =$B$23 -> STRUCTURE WORK / CÔNG TÁC KẾT CẤU | J7: =SUM(J8:J11) -> 0
A8: 1 | B8: =+B24 -> EARTH WORK / CÔNG TÁC ĐẤT | D8: lot | E8: 1 | J8: =+J24 -> 0
A9: 2 | B9: =+B33 -> CONCRETE WORK / CÔNG TÁC BÊ TÔNG | D9: lot | E9: 1 | J9: =+J33 -> 0
A10: =+A9+1 -> 3 | B10: =+B40 -> FORM WORK / CÔNG TÁC VÁN KHUÔN | D10: lot | E10: 1 | J10: =+J40 -> 0
A11: =+A10+1 -> 4 | B11: =+B45 -> REINFORCEMENT WORK / CÔNG TÁC CỐT THÉP | D11: lot | E11: 1 | J11: =+J45 -> 0
A12: B | B12: =B50 -> FINISING WORK / CÔNG TÁC HOÀN THIỆN | J12: =SUM(J13:J19) -> 0
A13: 1 | B13: =+B51 -> BRICK WORK / CÔNG TÁC XÂY | D13: lot | E13: 1 | J13: =+J51 -> 0
A14: =+A13+1 -> 2 | B14: =+B54 -> PLASTERING WORK / CÔNG TÁC TRÁT | D14: lot | E14: 1 | J14: =+J54 -> 0
A15: =+A14+1 -> 3 | B15: =+B40 -> FORM WORK / CÔNG TÁC VÁN KHUÔN | D15: lot | E15: 1 | J15: =+J58 -> 0
A16: =+A15+1 -> 4 | B16: =+B45 -> REINFORCEMENT WORK / CÔNG TÁC CỐT THÉP | D16: lot | E16: 1 | J16: =+J61 -> 0
A17: =+A16+1 -> 5 | B17: =+B65 -> WET FINISHING WORK / CÔNG TÁC HOÀN THIỆN MỀM | D17: lot | E17: 1 | J17: =+J65 -> 0
A18: =+A17+1 -> 6 | B18: =+B68 -> DOOR AND WINDOW / CỬA ĐI VÀ CỬA SỔ | D18: lot | E18: 1 | J18: =+J68 -> 0
A19: =+A18+1 -> 7 | B19: =+B72 -> OTHERS WORK/ CÔNG VIỆC KHÁC | D19: lot | E19: 1 | J19: =+J72 -> 0
A23: A | B23: STRUCTURE WORK / CÔNG TÁC KẾT CẤU | J23: =+J24+J33+J40+J45 -> 0
A24: 1 | B24: EARTH WORK / CÔNG TÁC ĐẤT | J24: =SUM(J25:J31) -> 0
A25: 1 | B25: Excavation (by Equipment) Đào đất bằng máy | D25: m3 | E25: 203.2784 | I25: =+SUM(F25:H25) -> 0 | J25: =ROUND(E25*I25,0) -> 0
A26: 2 | B26: Excavation (by worker) Đào đất thủ công | D26: m3 | E26: 40.65568 | I26: =+SUM(F26:H26) -> 0 | J26: =ROUND(E26*I26,0) -> 0
A27: 3 | B27: Backfilling soil for foundation Đắp đất | D27: m3 | E27: 60.98352 | I27: =+SUM(F27:H27) -> 0 | J27: =ROUND(E27*I27,0) -> 0
A28: 4 | B28: Remove surplus soil Vận chuyển đất đổ đi | C28: Distance D<=1Km Khoảng cách D<=1Km | D28: m3 | E28: 182.95056 | I28: =+SUM(F28:H28) -> 0 | J28: =ROUND(E28*I28,0) -> 0
A29: 5 | B29: Earth compaction, K=0.9 Đầm đất, K=0.9 | D29: m2 | E29: 180 | I29: =+SUM(F29:H29) -> 0 | J29: =ROUND(E29*I29,0) -> 0
A30: 6 | B30: Compacting by stone aggregate K=0.95 Đá base đầm chặt K=0.95 | D30: m3 | E30: 70.2 | I30: =+SUM(F30:H30) -> 0 | J30: =ROUND(E30*I30,0) -> 0
A31: 7 | B31: 1 layer nylon thk. 0.3mm 1 lớp nylon dày 0.3mm | D31: m2 | E31: 180 | I31: =+SUM(F31:H31) -> 0 | J31: =ROUND(E31*I31,0) -> 0
A33: 2 | B33: CONCRETE WORK / CÔNG TÁC BÊ TÔNG | J33: =SUM(J34:J38) -> 0
A34: 1 | B34: Lean concrete for foundation & ground beam Bê tông lót cho móng, dầm | C34: Gr. 100 | D34: m3 | E34: 2.8634 | I34: =+SUM(F34:H34) -> 0 | J34: =ROUND(E34*I34,0) -> 0
A35: 2 | B35: Concrete for foundation,beams, ground slab Bê tông móng, dầm móng, nền | C35: Gr. 300 | D35: m3 | E35: 36.81426 | I35: =+SUM(F35:H35) -> 0 | J35: =ROUND(E35*I35,0) -> 0
A36: 3 | B36: Concrete for column, beams, slab roof Bê tông cột, dầm, sàn tầng mái | C36: Gr.300 | D36: m3 | E36: 48.14014 | I36: =+SUM(F36:H36) -> 0 | J36: =ROUND(E36*I36,0) -> 0
A37: 4 | B37: Pump car Bơm bê tông | D37: m3 | E37: 87.8178 | I37: =+SUM(F37:H37) -> 0 | J37: =ROUND(E37*I37,0) -> 0 | K37: đã bao gồm
A38: 5 | B38: Polishing for slab Xoa nền | D38: m2 | E38: 397 | I38: =+SUM(F38:H38) -> 0 | J38: =ROUND(E38*I38,0) -> 0
A40: 3 | B40: FORM WORK / CÔNG TÁC VÁN KHUÔN | J40: =+SUM(J41:J43) -> 0
A41: 1 | B41: For lean concrete for foundation Ván khuôn bê tông lót móng | D41: m2 | E41: 9.597 | I41: =+SUM(F41:H41) -> 0 | J41: =ROUND(E41*I41,0) -> 0
A42: 2 | B42: For foundation, ground beam, slab Ván khuôn móng, dầm, nền | D42: m2 | E42: 107.94 | I42: =+SUM(F42:H42) -> 0 | J42: =ROUND(E42*I42,0) -> 0
A43: 3 | B43: For column, beams, slab roof Ván khuôn cột, dầm, sàn tầng mái | D43: m2 | E43: 462.819 | I43: =+SUM(F43:H43) -> 0 | J43: =ROUND(E43*I43,0) -> 0
A45: 4 | B45: REINFORCEMENT WORK / CÔNG TÁC CỐT THÉP | J45: =+SUM(J46:J48) -> 0
A46: 1 | B46: Re-bar for foundation, ground beam, slab Cốt thép móng, dầm, nền | D46: ton | E46: 3.912939 | I46: =+SUM(F46:H46) -> 0 | J46: =ROUND(E46*I46,0) -> 0
A47: 2 | B47: Re-bar for column, beams, slab roof Cốt thép cột, dầm, sàn tầng mái | D47: ton | E47: 7.694081 | I47: =+SUM(F47:H47) -> 0 | J47: =ROUND(E47*I47,0) -> 0
A50: B | B50: FINISING WORK / CÔNG TÁC HOÀN THIỆN | J50: =+J51+J54+J58+J61+J65+J68+J72 -> 0
A51: 1 | B51: BRICK WORK / CÔNG TÁC XÂY | J51: =+SUM(J52:J53) -> 0
A52: 1 | B52: Brick work wall Tường xây gạch | D52: m3 | E52: 71.736 | I52: =+SUM(F52:H52) -> 0 | J52: =ROUND(E52*I52,0) -> 0
A54: 2 | B54: PLASTERING WORK / CÔNG TÁC TRÁT | J54: =+SUM(J55:J56) -> 0
A55: 1 | B55: Plastering wall brick surfaces 2.0cm Trát tường dày 2.0cm | D55: m2 | E55: 692.37 | I55: =+SUM(F55:H55) -> 0 | J55: =ROUND(E55*I55,0) -> 0
A56: 2 | B56: Plastering column, celling concrete 2.0cm Trát cột, trần bê tông dày 2.0cm | D56: m2 | E56: 462.819 | I56: =+SUM(F56:H56) -> 0 | J56: =ROUND(E56*I56,0) -> 0
A58: 3 | B58: PAINTING WORK / CÔNG TÁC SƠN | J58: =+SUM(J59:J59) -> 0
A59: 1 | B59: Paint for wall (include putty) Sơn tường (bao gồm bả) | C59: 3 lớp (1 lót + 2 phủ) | D59: m2 | E59: 1155.189 | I59: =+SUM(F59:H59) -> 0 | J59: =ROUND(E59*I59,0) -> 0
A61: 4 | B61: TILING & FLOOR FINISHING WORK / ỐP LÁT VÀ HOÀN THIỆN SÀN | J61: =+SUM(J62:J63) -> 0
A62: 1 | B62: Polishing for slab by liquid hardener Đánh bóng sàn nhà bằng liquid hardener | D62: m2 | E62: 210 | I62: =+SUM(F62:H62) -> 0 | J62: =ROUND(E62*I62,0) -> 0
A63: 2 | B63: Cement mortar Vữa xi măng tạo dốc mái và mái lanh tô | D63: m2 | E63: 271.95 | I63: =+SUM(F63:H63) -> 0 | J63: =ROUND(E63*I63,0) -> 0
A65: 5 | B65: WET FINISHING WORK / CÔNG TÁC HOÀN THIỆN MỀM | J65: =+SUM(J66:J66) -> 0
A66: 1 | B66: Water proofing for concrete roof (include parabet wall ) Chống thấm cho mái ( bao gồm cả parabet ) | C66: Urethane water proofing 3mm thk | D66: m2 | E66: 271.95 | I66: =+SUM(F66:H66) -> 0 | J66: =ROUND(E66*I66,0) -> 0
A68: 6 | B68: DOOR AND WINDOW / CỬA ĐI VÀ CỬA SỔ | J68: =+SUM(J69:J70) -> 0
A69: 1 | B69: Steel double door Cửa đi thép 2 cánh | C69: included accessory/ Bao gồm phụ kiện | D69: m2 | E69: 30.8 | I69: =+SUM(F69:H69) -> 0 | J69: =ROUND(E69*I69,0) -> 0
A70: 2 | B70: Aluminum louver window Cửa chớp nhôm | C70: included accessory/ Bao gồm phụ kiện | D70: m2 | E70: 10.5 | I70: =+SUM(F70:H70) -> 0 | J70: =ROUND(E70*I70,0) -> 0
A72: 7 | B72: OTHERS WORK/ CÔNG VIỆC KHÁC | J72: =+SUM(J73:J75) -> 0
A73: 1 | B73: UPVC dowspout D75 Ống dẫn nước UPVC D75 | D73: m | E73: 108 | I73: =+SUM(F73:H73) -> 0 | J73: =ROUND(E73*I73,0) -> 0
A74: 2 | B74: Cút D75 | D74: set | E74: 18 | I74: =+SUM(F74:H74) -> 0 | J74: =ROUND(E74*I74,0) -> 0
A75: 3 | B75: Accessories / Vật tư phụ | D75: lot | E75: 1 | I75: =+SUM(F75:H75) -> 0 | J75: =ROUND(E75*I75,0) -> 0

Sheet 11.Bể Nước Ngầm PCCC
A1: BILL OF QUANTITIES
A2: ='C4.Hệ Thống Điện & Điện Nhẹ '!A2:K2 -> PROJECT NAME / TÊN DỰ ÁN :
A3: 11. WATER TANK FF/ BỂ NƯỚC NGẦM PCCC
A4: NO / STT | B4: WORK SCOPE / CÔNG VIỆC | C4: SPECIFICATION / ĐẶC ĐIỂM KỸ THUẬT | D4: UNIT/ ĐƠN VỊ | E4: QUANTITY / KHỐI LƯỢNG | F4: UNIT PRICE / ĐƠN GIÁ (VNĐ) | J4: AMOUNT / THÀNH TIỀN (VNĐ) | K4: REMARK / GHI CHÚ
F5: MATERIAL / VẬT LIỆU | G5: LABOUR / NHÂN CÔNG | H5: EQUIPMENT / THIẾT BỊ | I5: UNIT PRICE / TỔNG ĐƠN GIÁ
A6: 11 | B6: WATER TANK FF/ BỂ NƯỚC NGẦM PCCC | J6: =+J7+J13 -> 0
A7: A | B7: =$B$20 -> STRUCTURE WORK / CÔNG TÁC KẾT CẤU | J7: =+SUM(J8:J11) -> 0
A8: 1 | B8: =+B21 -> EARTH WORK / CÔNG TÁC ĐẤT | D8: lot | E8: 1 | J8: =+J21 -> 0
A9: =+A8+1 -> 2 | B9: =+B30 -> CONCRETE WORK / CÔNG TÁC BÊ TÔNG | D9: lot | E9: 1 | J9: =+J30 -> 0
A10: =+A9+1 -> 3 | B10: =+B38 -> FORM WORK / CÔNG TÁC VÁN KHUÔN | D10: lot | E10: 1 | J10: =+J38 -> 0
A11: =+A10+1 -> 4 | B11: =+B44 -> REINFORCEMENT WORK / CÔNG TÁC CỐT THÉP | D11: lot | E11: 1 | J11: =+J44 -> 0
A13: B | B13: =B49 -> FINISING WORK / CÔNG TÁC HOÀN THIỆN | J13: =+SUM(J14:J15) -> 0
A14: 1 | B14: WET FINISHING WORK | D14: lot | E14: 1 | J14: =+J50 -> 0
A15: 2 | B15: =$B$55 -> OTHERS WORK/ CÔNG VIỆC KHÁC | D15: lot | E15: 1 | J15: =+J55 -> 0
A20: A | B20: STRUCTURE WORK / CÔNG TÁC KẾT CẤU | J20: =+J21+J30+J38+J44 -> 0
A21: 1 | B21: EARTH WORK / CÔNG TÁC ĐẤT | J21: =+SUM(J22:J28) -> 0
A22: 1 | B22: Sheet pile cover for tank area Thi công cừ chắn cho khu vực bể | C22: Sheet pile 6m including transport & install | D22: lot | E22: 1 | I22: =+SUM(F22:H22) -> 0 | J22: =ROUND(E22*I22,0) -> 0
A23: 2 | B23: Excavation (by Equipment) Đào đất bằng máy | D23: m3 | E23: 942.5 | I23: =+SUM(F23:H23) -> 0 | J23: =ROUND(E23*I23,0) -> 0
A24: 3 | B24: Excavation (by worker) Đào đất thủ công | D24: m3 | E24: 141.375 | I24: =+SUM(F24:H24) -> 0 | J24: =ROUND(E24*I24,0) -> 0
A25: 4 | B25: Backfilling soil for foundation Đắp đất | D25: m3 | E25: 282.75 | I25: =+SUM(F25:H25) -> 0 | J25: =ROUND(E25*I25,0) -> 0
A26: 5 | B26: Remove surplus soil Vận chuyển đất đổ | C26: Distance D<=1Km Khoảng cách D<=1Km | D26: m3 | E26: 801.125 | I26: =+SUM(F26:H26) -> 0 | J26: =ROUND(E26*I26,0) -> 0
A27: =+A26+1 -> 6 | B27: Earth compaction, K=0.9 Đầm đất, K=0.9 | D27: m2 | E27: 290 | I27: =+SUM(F27:H27) -> 0 | J27: =ROUND(E27*I27,0) -> 0
A28: =+A27+1 -> 7 | B28: 1 layer nylon thk. 0.3mm 1 lớp nylon dày 0.3mm | D28: m2 | E28: 290 | I28: =+SUM(F28:H28) -> 0 | J28: =ROUND(E28*I28,0) -> 0
A30: 2 | B30: CONCRETE WORK / CÔNG TÁC BÊ TÔNG | J30: =+SUM(J31:J36) -> 0
A31: 1 | B31: Lean concrete for tank Bê tông lót | C31: Gr. 100 | D31: m3 | E31: 8.37184 | I31: =+SUM(F31:H31) -> 0 | J31: =ROUND(E31*I31,0) -> 0
A32: 2 | B32: Concrete for bottom Bê tông đáy bể | C32: Gr. 300 | D32: m3 | E32: 56.32452 | I32: =+SUM(F32:H32) -> 0 | J32: =ROUND(E32*I32,0) -> 0
A33: 3 | B33: Concrete for wall & column Bê tông thành bể và cột | C33: Gr. 300 | D33: m3 | E33: 45.3715 | I33: =+SUM(F33:H33) -> 0 | J33: =ROUND(E33*I33,0) -> 0
A34: 4 | B34: Concrete for cover slab Bê tông nắp bể | C34: Gr. 300 | D34: m3 | E34: 36.3075 | I34: =+SUM(F34:H34) -> 0 | J34: =ROUND(E34*I34,0) -> 0
A35: 6 | B35: Pump car Bơm bê tông | D35: m3 | E35: 146.37536 | I35: =+SUM(F35:H35) -> 0 | J35: =ROUND(E35*I35,0) -> 0 | K35: đã bao gồm
A36: 7 | B36: Polishing for bottom, cover slab Đánh bóng đáy bể, mặt bể | D36: m2 | E36: 770.24 | I36: =+SUM(F36:H36) -> 0 | J36: =ROUND(E36*I36,0) -> 0
A38: 4 | B38: FORM WORK / CÔNG TÁC VÁN KHUÔN | J38: =+SUM(J39:J42) -> 0
A39: 1 | B39: For lean concrete Ván khuôn bê tông lót | D39: m2 | E39: 3.339 | I39: =+SUM(F39:H39) -> 0 | J39: =ROUND(E39*I39,0) -> 0
A40: 2 | B40: Formwork for bottom Ván khuôn đáy bể | D40: m2 | E40: 23.079 | I40: =+SUM(F40:H40) -> 0 | J40: =ROUND(E40*I40,0) -> 0
A41: 3 | B41: Formwork for wall, colum Ván khuôn thành bể, cột | C41: (including scaffolding, bracing, supports, etc.) | D41: m2 | E41: 380.1 | I41: =+SUM(F41:H41) -> 0 | J41: =ROUND(E41*I41,0) -> 0
A42: 4 | B42: Formwork for cover slab Ván khuôn nắp bể | C42: (including scaffolding, bracing, supports, etc.) | D42: m2 | E42: 268.8 | I42: =+SUM(F42:H42) -> 0 | J42: =ROUND(E42*I42,0) -> 0
A44: 5 | B44: REINFORCEMENT WORK / CÔNG TÁC CỐT THÉP | J44: =+SUM(J45:J47) -> 0
A45: 1 | B45: Re-bar for bottom Cốt thép đáy bể | D45: ton | E45: 5.2934112 | I45: =+SUM(F45:H45) -> 0 | J45: =ROUND(E45*I45,0) -> 0 | K45: ='[79]14.Bể XLNT'!K43 -> Hoa Phat/ Equivalent
A46: 2 | B46: Re-bar for wall, colum Cốt thép thành bể, cột | D46: ton | E46: 4.61008 | I46: =+SUM(F46:H46) -> 0 | J46: =ROUND(E46*I46,0) -> 0 | K46: =K45 -> Hoa Phat/ Equivalent
A47: 3 | B47: Re-bar for cover slab Cốt thép thành nắp bể | D47: ton | E47: 2.772 | I47: =+SUM(F47:H47) -> 0 | J47: =ROUND(E47*I47,0) -> 0 | K47: =K46 -> Hoa Phat/ Equivalent
A49: B | B49: FINISING WORK / CÔNG TÁC HOÀN THIỆN | J49: =+J50+J55 -> 0
A50: 1 | B50: WET FINISHING WORK / CÔNG TÁC HOÀN THIỆN MỀM | J50: =+SUM(J51:J53) -> 0
A51: 1 | B51: Bitum waterproofing Chống thấm bằng bitum | C51: Outside & Top Slab of water tank 3 layer, membrane 1.5kg/m2/lớp | D51: m2 | E51: 770.24 | I51: =+SUM(F51:H51) -> 0 | J51: =ROUND(E51*I51,0) -> 0
A52: 2 | B52: Expoxy memberane waterproofing (non posion ) Màng chống thấm expoxy ( không độc hại) | C52: finishing 2 layer / hoàn thiện 2 lớp | D52: m2 | E52: 770.24 | I52: =+SUM(F52:H52) -> 0 | J52: =ROUND(E52*I52,0) -> 0
A53: 3 | B53: Liquid water proofing with protection mortar 15mm | C53: Silk Seal -wp1000 / Cement mortar grade 75 | D53: m2 | E53: 770.24 | I53: =+SUM(F53:H53) -> 0 | J53: =ROUND(E53*I53,0) -> 0
A55: 2 | B55: OTHERS WORK/ CÔNG VIỆC KHÁC | J55: =+SUM(J56:J60) -> 0
A56: 1 | B56: Nắp bể / Inox cover thk 3mm | C56: SUS 304, thk 3mm, 800x800 | D56: ea | E56: 2 | I56: =+SUM(F56:H56) -> 0 | J56: =ROUND(E56*I56,0) -> 0
A57: 2 | B57: Ladder for tank Thang leo xuống bể | C57: sus 304 | D57: ea | E57: 2 | I57: =+SUM(F57:H57) -> 0 | J57: =ROUND(E57*I57,0) -> 0
A58: 3 | B58: UPVC dowspout D90 Ống dẫn nước UPVC D90 | D58: m | E58: 24 | I58: =+SUM(F58:H58) -> 0 | J58: =ROUND(E58*I58,0) -> 0
A59: 4 | B59: Cút D90 | D59: ea | E59: 16 | I59: =+SUM(F59:H59) -> 0 | J59: =ROUND(E59*I59,0) -> 0 | K59: bao gồm
A60: 5 | B60: Water stop for concrete pour Băng cản nước mạch ngừng đổ bê tông | D60: m | E60: 124 | I60: =+SUM(F60:H60) -> 0 | J60: =ROUND(E60*I60,0) -> 0

Sheet 12.Bể Nước Ngầm Xả Nguội
A1: BILL OF QUANTITIES
A2: ='C4.Hệ Thống Điện & Điện Nhẹ '!A2:K2 -> PROJECT NAME / TÊN DỰ ÁN :
A3: 12. COLD WATER TANK/ BỂ NƯỚC XẢ NGUỘI
A4: NO / STT | B4: WORK SCOPE / CÔNG VIỆC | C4: SPECIFICATION / ĐẶC ĐIỂM KỸ THUẬT | D4: UNIT/ ĐƠN VỊ | E4: QUANTITY / KHỐI LƯỢNG | F4: UNIT PRICE / ĐƠN GIÁ (VNĐ) | J4: AMOUNT / THÀNH TIỀN (VNĐ) | K4: REMARK / GHI CHÚ
F5: MATERIAL / VẬT LIỆU | G5: LABOUR / NHÂN CÔNG | H5: EQUIPMENT / THIẾT BỊ | I5: UNIT PRICE / TỔNG ĐƠN GIÁ
A6: 12 | B6: COLD WATER TANK/ BỂ NƯỚC XẢ NGUỘI | J6: =+J7+J13 -> 0
A7: A | B7: =$B$20 -> STRUCTURE WORK / CÔNG TÁC KẾT CẤU | J7: =+SUM(J8:J11) -> 0
A8: 1 | B8: =+B21 -> EARTH WORK / CÔNG TÁC ĐẤT | D8: lot | E8: 1 | J8: =+J21 -> 0
A9: =+A8+1 -> 2 | B9: =+B30 -> CONCRETE WORK / CÔNG TÁC BÊ TÔNG | D9: lot | E9: 1 | J9: =+J30 -> 0
A10: =+A9+1 -> 3 | B10: =+B38 -> FORM WORK / CÔNG TÁC VÁN KHUÔN | D10: lot | E10: 1 | J10: =+J38 -> 0
A11: =+A10+1 -> 4 | B11: =+B44 -> REINFORCEMENT WORK / CÔNG TÁC CỐT THÉP | D11: lot | E11: 1 | J11: =+J44 -> 0
A13: B | B13: =B49 -> FINISING WORK / CÔNG TÁC HOÀN THIỆN | J13: =+SUM(J14:J15) -> 0
A14: 1 | B14: WET FINISHING WORK | D14: lot | E14: 1 | J14: =+J50 -> 0
A15: 2 | B15: =$B$55 -> OTHERS WORK/ CÔNG VIỆC KHÁC | D15: lot | E15: 1 | J15: =+J55 -> 0
A20: A | B20: STRUCTURE WORK / CÔNG TÁC KẾT CẤU | J20: =+J21+J30+J38+J44 -> 0
A21: 1 | B21: EARTH WORK / CÔNG TÁC ĐẤT | J21: =+SUM(J22:J28) -> 0
A22: 1 | B22: Sheet pile cover for tank area Thi công cừ chắn cho khu vực bể | C22: Sheet pile 6m including transport & install | D22: lot | E22: 1 | I22: =+SUM(F22:H22) -> 0 | J22: =ROUND(E22*I22,0) -> 0
A23: 2 | B23: Excavation (by Equipment) Đào đất bằng máy | D23: m3 | E23: 617.5 | I23: =+SUM(F23:H23) -> 0 | J23: =ROUND(E23*I23,0) -> 0
A24: 3 | B24: Excavation (by worker) Đào đất thủ công | D24: m3 | E24: 92.625 | I24: =+SUM(F24:H24) -> 0 | J24: =ROUND(E24*I24,0) -> 0
A25: 4 | B25: Backfilling soil for foundation Đắp đất | D25: m3 | E25: 185.25 | I25: =+SUM(F25:H25) -> 0 | J25: =ROUND(E25*I25,0) -> 0
A26: 5 | B26: Remove surplus soil Vận chuyển đất đổ | C26: Distance D<=1Km Khoảng cách D<=1Km | D26: m3 | E26: 524.875 | I26: =+SUM(F26:H26) -> 0 | J26: =ROUND(E26*I26,0) -> 0
A27: =+A26+1 -> 6 | B27: Earth compaction, K=0.9 Đầm đất, K=0.9 | D27: m2 | E27: 190 | I27: =+SUM(F27:H27) -> 0 | J27: =ROUND(E27*I27,0) -> 0
A28: =+A27+1 -> 7 | B28: 1 layer nylon thk. 0.3mm 1 lớp nylon dày 0.3mm | D28: m2 | E28: 190 | I28: =+SUM(F28:H28) -> 0 | J28: =ROUND(E28*I28,0) -> 0
A30: 2 | B30: CONCRETE WORK / CÔNG TÁC BÊ TÔNG | J30: =+SUM(J31:J36) -> 0
A31: 1 | B31: Lean concrete for tank Bê tông lót | C31: Gr. 100 | D31: m3 | E31: 5.07584 | I31: =+SUM(F31:H31) -> 0 | J31: =ROUND(E31*I31,0) -> 0
A32: 2 | B32: Concrete for bottom Bê tông đáy bể | C32: Gr. 300 | D32: m3 | E32: 33.97352 | I32: =+SUM(F32:H32) -> 0 | J32: =ROUND(E32*I32,0) -> 0
A33: 3 | B33: Concrete for wall & column Bê tông thành bể và cột | C33: Gr. 300 | D33: m3 | E33: 34.32475 | I33: =+SUM(F33:H33) -> 0 | J33: =ROUND(E33*I33,0) -> 0
A34: 4 | B34: Concrete for cover slab Bê tông nắp bể | C34: Gr. 300 | D34: m3 | E34: 28.65975 | I34: =+SUM(F34:H34) -> 0 | J34: =ROUND(E34*I34,0) -> 0
A35: 6 | B35: Pump car Bơm bê tông | D35: m3 | E35: 102.03386 | I35: =+SUM(F35:H35) -> 0 | J35: =ROUND(E35*I35,0) -> 0 | K35: đã bao gồm
A36: 7 | B36: Polishing for bottom, cover slab Đánh bóng đáy bể, mặt bể | D36: m2 | E36: 519.24 | I36: =+SUM(F36:H36) -> 0 | J36: =ROUND(E36*I36,0) -> 0
A38: 4 | B38: FORM WORK / CÔNG TÁC VÁN KHUÔN | J38: =+SUM(J39:J42) -> 0
A39: 1 | B39: For lean concrete Ván khuôn bê tông lót | D39: m2 | E39: 2.289 | I39: =+SUM(F39:H39) -> 0 | J39: =ROUND(E39*I39,0) -> 0
A40: 2 | B40: Formwork for bottom Ván khuôn đáy bể | D40: m2 | E40: 15.729 | I40: =+SUM(F40:H40) -> 0 | J40: =ROUND(E40*I40,0) -> 0
A41: 3 | B41: Formwork for wall, colum Ván khuôn thành bể, cột | C41: (including scaffolding, bracing, supports, etc.) | D41: m2 | E41: 295.05 | I41: =+SUM(F41:H41) -> 0 | J41: =ROUND(E41*I41,0) -> 0
A42: 4 | B42: Formwork for cover slab Ván khuôn nắp bể | C42: (including scaffolding, bracing, supports, etc.) | D42: m2 | E42: 179.55 | I42: =+SUM(F42:H42) -> 0 | J42: =ROUND(E42*I42,0) -> 0
A44: 5 | B44: REINFORCEMENT WORK / CÔNG TÁC CỐT THÉP | J44: =+SUM(J45:J47) -> 0
A45: 1 | B45: Re-bar for bottom Cốt thép đáy bể | D45: ton | E45: 3.1928512 | I45: =+SUM(F45:H45) -> 0 | J45: =ROUND(E45*I45,0) -> 0 | K45: ='[79]14.Bể XLNT'!K43 -> Hoa Phat/ Equivalent
A46: 2 | B46: Re-bar for wall, colum Cốt thép thành bể, cột | D46: ton | E46: 3.43555 | I46: =+SUM(F46:H46) -> 0 | J46: =ROUND(E46*I46,0) -> 0 | K46: =K45 -> Hoa Phat/ Equivalent
A47: 3 | B47: Re-bar for cover slab Cốt thép thành nắp bể | D47: ton | E47: 1.6632 | I47: =+SUM(F47:H47) -> 0 | J47: =ROUND(E47*I47,0) -> 0 | K47: =K46 -> Hoa Phat/ Equivalent
A49: B | B49: FINISING WORK / CÔNG TÁC HOÀN THIỆN | J49: =+J50+J55 -> 0
A50: 1 | B50: WET FINISHING WORK / CÔNG TÁC HOÀN THIỆN MỀM | J50: =+SUM(J51:J53) -> 0
A51: 1 | B51: Bitum waterproofing Chống thấm bằng bitum | C51: Outside & Top Slab of water tank 3 layer, membrane 1.5kg/m2/lớp | D51: m2 | E51: 519.24 | I51: =+SUM(F51:H51) -> 0 | J51: =ROUND(E51*I51,0) -> 0
A52: 2 | B52: Expoxy memberane waterproofing (non posion ) Màng chống thấm expoxy ( không độc hại) | C52: finishing 2 layer / hoàn thiện 2 lớp | D52: m2 | E52: 519.24 | I52: =+SUM(F52:H52) -> 0 | J52: =ROUND(E52*I52,0) -> 0
A53: 3 | B53: Liquid water proofing with protection mortar 15mm | C53: Silk Seal -wp1000 / Cement mortar grade 75 | D53: m2 | E53: 519.24 | I53: =+SUM(F53:H53) -> 0 | J53: =ROUND(E53*I53,0) -> 0
A55: 2 | B55: OTHERS WORK/ CÔNG VIỆC KHÁC | J55: =+SUM(J56:J60) -> 0
A56: 1 | B56: Nắp bể / Inox cover thk 3mm | C56: SUS 304, thk 3mm, 800x800 | D56: ea | E56: 2 | I56: =+SUM(F56:H56) -> 0 | J56: =ROUND(E56*I56,0) -> 0
A57: 2 | B57: Ladder for tank Thang leo xuống bể | C57: sus 304 | D57: ea | E57: 2 | I57: =+SUM(F57:H57) -> 0 | J57: =ROUND(E57*I57,0) -> 0
A58: 3 | B58: UPVC dowspout D90 Ống dẫn nước UPVC D90 | D58: m | E58: 24 | I58: =+SUM(F58:H58) -> 0 | J58: =ROUND(E58*I58,0) -> 0
A59: 4 | B59: Cút D90 | D59: ea | E59: 16 | I59: =+SUM(F59:H59) -> 0 | J59: =ROUND(E59*I59,0) -> 0
A60: 5 | B60: Water stop for concrete pour Băng cản nước mạch ngừng đổ bê tông | D60: m | E60: 84 | I60: =+SUM(F60:H60) -> 0 | J60: =ROUND(E60*I60,0) -> 0

Sheet 13.Bể Nước Ngầm RO 
A1: BILL OF QUANTITIES
A2: ='C4.Hệ Thống Điện & Điện Nhẹ '!A2:K2 -> PROJECT NAME / TÊN DỰ ÁN :
A3: 13. WATER TANK RO/ BỂ NƯỚC NGẦM RO
A4: NO / STT | B4: WORK SCOPE / CÔNG VIỆC | C4: SPECIFICATION / ĐẶC ĐIỂM KỸ THUẬT | D4: UNIT/ ĐƠN VỊ | E4: QUANTITY / KHỐI LƯỢNG | F4: UNIT PRICE / ĐƠN GIÁ (VNĐ) | J4: AMOUNT / THÀNH TIỀN (VNĐ) | K4: REMARK / GHI CHÚ
F5: MATERIAL / VẬT LIỆU | G5: LABOUR / NHÂN CÔNG | H5: EQUIPMENT / THIẾT BỊ | I5: UNIT PRICE / TỔNG ĐƠN GIÁ
A6: 13 | B6: WATER TANK RO/ BỂ NƯỚC NGẦM RO | J6: =+J7+J13 -> 0
A7: A | B7: =$B$20 -> STRUCTURE WORK / CÔNG TÁC KẾT CẤU | J7: =+SUM(J8:J11) -> 0
A8: 1 | B8: =+B21 -> EARTH WORK / CÔNG TÁC ĐẤT | D8: lot | E8: 1 | J8: =+J21 -> 0
A9: =+A8+1 -> 2 | B9: =+B30 -> CONCRETE WORK / CÔNG TÁC BÊ TÔNG | D9: lot | E9: 1 | J9: =+J30 -> 0
A10: =+A9+1 -> 3 | B10: =+B38 -> FORM WORK / CÔNG TÁC VÁN KHUÔN | D10: lot | E10: 1 | J10: =+J38 -> 0
A11: =+A10+1 -> 4 | B11: =+B44 -> REINFORCEMENT WORK / CÔNG TÁC CỐT THÉP | D11: lot | E11: 1 | J11: =+J44 -> 0
A13: B | B13: =B49 -> FINISING WORK / CÔNG TÁC HOÀN THIỆN | J13: =+SUM(J14:J15) -> 0
A14: 1 | B14: WET FINISHING WORK | D14: lot | E14: 1 | J14: =+J50 -> 0
A15: 2 | B15: =$B$55 -> OTHERS WORK/ CÔNG VIỆC KHÁC | D15: lot | E15: 1 | J15: =+J55 -> 0
A20: A | B20: STRUCTURE WORK / CÔNG TÁC KẾT CẤU | J20: =+J21+J30+J38+J44 -> 0
A21: 1 | B21: EARTH WORK / CÔNG TÁC ĐẤT | J21: =+SUM(J22:J28) -> 0
A22: 1 | B22: Sheet pile cover for tank area Thi công cừ chắn cho khu vực bể | C22: Sheet pile 6m including transport & install | D22: lot | E22: 1 | I22: =+SUM(F22:H22) -> 0 | J22: =ROUND(E22*I22,0) -> 0
A23: 2 | B23: Excavation (by Equipment) Đào đất bằng máy | D23: m3 | E23: 663 | I23: =+SUM(F23:H23) -> 0 | J23: =ROUND(E23*I23,0) -> 0
A24: 3 | B24: Excavation (by worker) Đào đất thủ công | D24: m3 | E24: 99.45 | I24: =+SUM(F24:H24) -> 0 | J24: =ROUND(E24*I24,0) -> 0
A25: 4 | B25: Backfilling soil for foundation Đắp đất | D25: m3 | E25: 198.9 | I25: =+SUM(F25:H25) -> 0 | J25: =ROUND(E25*I25,0) -> 0
A26: 5 | B26: Remove surplus soil Vận chuyển đất đổ | C26: Distance D<=1Km Khoảng cách D<=1Km | D26: m3 | E26: 563.55 | I26: =+SUM(F26:H26) -> 0 | J26: =ROUND(E26*I26,0) -> 0
A27: =+A26+1 -> 6 | B27: Earth compaction, K=0.9 Đầm đất, K=0.9 | D27: m2 | E27: 204 | I27: =+SUM(F27:H27) -> 0 | J27: =ROUND(E27*I27,0) -> 0
A28: =+A27+1 -> 7 | B28: 1 layer nylon thk. 0.3mm 1 lớp nylon dày 0.3mm | D28: m2 | E28: 204 | I28: =+SUM(F28:H28) -> 0 | J28: =ROUND(E28*I28,0) -> 0
A30: 2 | B30: CONCRETE WORK / CÔNG TÁC BÊ TÔNG | J30: =+SUM(J31:J36) -> 0
A31: 1 | B31: Lean concrete for tank Bê tông lót | C31: Gr. 100 | D31: m3 | E31: 5.79684 | I31: =+SUM(F31:H31) -> 0 | J31: =ROUND(E31*I31,0) -> 0
A32: 2 | B32: Concrete for bottom Bê tông đáy bể | C32: Gr. 300 | D32: m3 | E32: 39.02052 | I32: =+SUM(F32:H32) -> 0 | J32: =ROUND(E32*I32,0) -> 0
A33: 3 | B33: Concrete for wall & column Bê tông thành bể và cột | C33: Gr. 300 | D33: m3 | E33: 30.3335 | I33: =+SUM(F33:H33) -> 0 | J33: =ROUND(E33*I33,0) -> 0
A34: 4 | B34: Concrete for cover slab Bê tông nắp bể | C34: Gr. 300 | D34: m3 | E34: 31.63645 | I34: =+SUM(F34:H34) -> 0 | J34: =ROUND(E34*I34,0) -> 0
A35: 6 | B35: Pump car Bơm bê tông | D35: m3 | E35: 106.78731 | I35: =+SUM(F35:H35) -> 0 | J35: =ROUND(E35*I35,0) -> 0 | K35: đã bao gồm
A36: 7 | B36: Polishing for bottom, cover slab Đánh bóng đáy bể, mặt bể | D36: m2 | E36: 530.24 | I36: =+SUM(F36:H36) -> 0 | J36: =ROUND(E36*I36,0) -> 0
A38: 4 | B38: FORM WORK / CÔNG TÁC VÁN KHUÔN | J38: =+SUM(J39:J42) -> 0
A39: 1 | B39: For lean concrete Ván khuôn bê tông lót | D39: m2 | E39: 2.289 | I39: =+SUM(F39:H39) -> 0 | J39: =ROUND(E39*I39,0) -> 0
A40: 2 | B40: Formwork for bottom Ván khuôn đáy bể | D40: m2 | E40: 15.729 | I40: =+SUM(F40:H40) -> 0 | J40: =ROUND(E40*I40,0) -> 0
A41: 3 | B41: Formwork for wall, colum Ván khuôn thành bể, cột | C41: (including scaffolding, bracing, supports, etc.) | D41: m2 | E41: 262.5 | I41: =+SUM(F41:H41) -> 0 | J41: =ROUND(E41*I41,0) -> 0
A42: 4 | B42: Formwork for cover slab Ván khuôn nắp bể | C42: (including scaffolding, bracing, supports, etc.) | D42: m2 | E42: 194.67 | I42: =+SUM(F42:H42) -> 0 | J42: =ROUND(E42*I42,0) -> 0
A44: 5 | B44: REINFORCEMENT WORK / CÔNG TÁC CỐT THÉP | J44: =+SUM(J45:J47) -> 0
A45: 1 | B45: Re-bar for bottom Cốt thép đáy bể | D45: ton | E45: 2.6670336 | I45: =+SUM(F45:H45) -> 0 | J45: =ROUND(E45*I45,0) -> 0 | K45: ='[79]14.Bể XLNT'!K43 -> Hoa Phat/ Equivalent
A46: 2 | B46: Re-bar for wall, colum Cốt thép thành bể, cột | D46: ton | E46: 3.05363 | I46: =+SUM(F46:H46) -> 0 | J46: =ROUND(E46*I46,0) -> 0 | K46: =K45 -> Hoa Phat/ Equivalent
A47: 3 | B47: Re-bar for cover slab Cốt thép thành nắp bể | D47: ton | E47: 1.92192 | I47: =+SUM(F47:H47) -> 0 | J47: =ROUND(E47*I47,0) -> 0 | K47: =K46 -> Hoa Phat/ Equivalent
A49: B | B49: FINISING WORK / CÔNG TÁC HOÀN THIỆN | J49: =+J50+J55 -> 0
A50: 1 | B50: WET FINISHING WORK / CÔNG TÁC HOÀN THIỆN MỀM | J50: =+SUM(J51:J53) -> 0
A51: 1 | B51: Bitum waterproofing Chống thấm bằng bitum | C51: Outside & Top Slab of water tank 3 layer, membrane 1.5kg/m2/lớp | D51: m2 | E51: 530.24 | I51: =+SUM(F51:H51) -> 0 | J51: =ROUND(E51*I51,0) -> 0
A52: 2 | B52: Expoxy memberane waterproofing (non posion ) Màng chống thấm expoxy ( không độc hại) | C52: finishing 2 layer / hoàn thiện 2 lớp | D52: m2 | E52: 530.24 | I52: =+SUM(F52:H52) -> 0 | J52: =ROUND(E52*I52,0) -> 0
A53: 3 | B53: Liquid water proofing with protection mortar 15mm | C53: Silk Seal -wp1000 / Cement mortar grade 75 | D53: m2 | E53: 530.24 | I53: =+SUM(F53:H53) -> 0 | J53: =ROUND(E53*I53,0) -> 0
A55: 2 | B55: OTHERS WORK/ CÔNG VIỆC KHÁC | J55: =+SUM(J56:J60) -> 0
A56: 1 | B56: Nắp bể / Inox cover thk 3mm | C56: SUS 304, thk 3mm, 800x800 | D56: ea | E56: 2 | I56: =+SUM(F56:H56) -> 0 | J56: =ROUND(E56*I56,0) -> 0
A57: 2 | B57: Ladder for tank Thang leo xuống bể | C57: sus 304 | D57: ea | E57: 2 | I57: =+SUM(F57:H57) -> 0 | J57: =ROUND(E57*I57,0) -> 0
A58: 3 | B58: UPVC dowspout D90 Ống dẫn nước UPVC D90 | D58: m | E58: 24 | I58: =+SUM(F58:H58) -> 0 | J58: =ROUND(E58*I58,0) -> 0
A59: 4 | B59: Cút D90 | D59: ea | E59: 16 | I59: =+SUM(F59:H59) -> 0 | J59: =ROUND(E59*I59,0) -> 0
A60: 5 | B60: Water stop for concrete pour Băng cản nước mạch ngừng đổ bê tông | D60: m | E60: 84 | I60: =+SUM(F60:H60) -> 0 | J60: =ROUND(E60*I60,0) -> 0

Sheet 14.Bể XLNT
A1: BILL OF QUANTITIES
A2: ='C4.Hệ Thống Điện & Điện Nhẹ '!A2:K2 -> PROJECT NAME / TÊN DỰ ÁN :
A3: 14. WATERWASTE TREATMENT TANK/ 오폐수 처리장 공사
A4: NO / STT | B4: WORK SCOPE / CÔNG VIỆC | C4: SPECIFICATION / ĐẶC ĐIỂM KỸ THUẬT | D4: UNIT/ ĐƠN VỊ | E4: QUANTITY / KHỐI LƯỢNG | F4: UNIT PRICE / ĐƠN GIÁ (VNĐ) | J4: AMOUNT / THÀNH TIỀN (VNĐ) | K4: REMARK / GHI CHÚ
F5: MATERIAL / VẬT LIỆU | G5: LABOUR / NHÂN CÔNG | H5: EQUIPMENT / THIẾT BỊ | I5: UNIT PRICE / TỔNG ĐƠN GIÁ
A6: 14 | B6: WATERWASTE TREATMENT TANK/ BỂ XLNT | J6: =+J7+J13 -> 0
A7: A | B7: STRUCTURE WORK / CÔNG TÁC KẾT CẤU | J7: =+SUM(J8:J11) -> 0
A8: 1 | B8: =+B20 -> EARTH WORK / CÔNG TÁC ĐẤT | D8: lot | E8: 1 | J8: =+J20 -> 0
A9: =+A8+1 -> 2 | B9: =+B28 -> CONCRETE WORK / CÔNG TÁC BÊ TÔNG | D9: lot | E9: 1 | J9: =+J28 -> 0
A10: =+A9+1 -> 3 | B10: =+B36 -> FORM WORK / CÔNG TÁC VÁN KHUÔN | D10: lot | E10: 1 | J10: =+J36 -> 0
A11: =+A10+1 -> 4 | B11: =+B42 -> REINFORCEMENT WORK / CÔNG TÁC CỐT THÉP | D11: lot | E11: 1 | J11: =+J42 -> 0
A13: B | B13: =B47 -> FINISING WORK / CÔNG TÁC HOÀN THIỆN | J13: =+SUM(J14:J16) -> 0
A14: 1 | B14: WET FINISHING WORK | D14: lot | E14: 1 | J14: =+J48 -> 0
A15: 2 | B15: =$B$53 -> OTHERS WORK/ CÔNG VIỆC KHÁC | D15: lot | E15: 1 | J15: =+J53 -> 0
A19: A | B19: STRUCTURE WORK / CÔNG TÁC KẾT CẤU | J19: =J20+J28+J36+J42 -> 0
A20: 1 | B20: EARTH WORK / CÔNG TÁC ĐẤT | J20: =+SUM(J21:J26) -> 0
A21: 1 | B21: Sheet pile cover for tank area Thi công cừ chắn cho khu vực bể | C21: Sheet pile 6m including transport & install | D21: lot | E21: 1 | I21: =+SUM(F21:H21) -> 0 | J21: =ROUND(E21*I21,0) -> 0
A22: 2 | B22: Excavation (by Equipment) Đào đất bằng máy | D22: m3 | E22: 1952.4862 | I22: =+SUM(F22:H22) -> 0 | J22: =ROUND(E22*I22,0) -> 0
A23: 3 | B23: Excavation (by worker) Đào đất thủ công | D23: m3 | E23: 292.87294 | I23: =+SUM(F23:H23) -> 0 | J23: =ROUND(E23*I23,0) -> 0
A24: 4 | B24: Backfilling soil for foundation Đắp đất | D24: m3 | E24: 585.74587 | I24: =+SUM(F24:H24) -> 0 | J24: =ROUND(E24*I24,0) -> 0
A25: 5 | B25: Remove surplus soil Vận chuyển đất đổ | C25: Distance D<=1Km Khoảng cách D<=1Km | D25: m3 | E25: 1659.6133 | I25: =+SUM(F25:H25) -> 0 | J25: =ROUND(E25*I25,0) -> 0
A26: =+A25+1 -> 6 | B26: Earth compaction, K=0.9 Đầm đất, K=0.9 | D26: m2 | E26: 500.6375 | I26: =+SUM(F26:H26) -> 0 | J26: =ROUND(E26*I26,0) -> 0
A28: 3 | B28: CONCRETE WORK / CÔNG TÁC BÊ TÔNG | J28: =+SUM(J29:J34) -> 0
A29: 1 | B29: Lean concrete for tank Bê tông lót | C29: Gr. 100 | D29: m3 | E29: 17.773551 | I29: =+SUM(F29:H29) -> 0 | J29: =ROUND(E29*I29,0) -> 0
A30: 2 | B30: Concrete for bottom Bê tông đáy bể | C30: Gr. 300 | D30: m3 | E30: 121.57412 | I30: =+SUM(F30:H30) -> 0 | J30: =ROUND(E30*I30,0) -> 0
A31: 3 | B31: Concrete for wall & column Bê tông thành bể và cột | C31: Gr. 300 | D31: m3 | E31: 93.511125 | I31: =+SUM(F31:H31) -> 0 | J31: =ROUND(E31*I31,0) -> 0
A32: 4 | B32: Concrete for cover slab Bê tông nắp bể | C32: Gr. 300 | D32: m3 | E32: 62.902744 | I32: =+SUM(F32:H32) -> 0 | J32: =ROUND(E32*I32,0) -> 0
A33: 6 | B33: Pump car Bơm bê tông | D33: m3 | E33: 295.76154 | I33: =+SUM(F33:H33) -> 0 | J33: =ROUND(E33*I33,0) -> 0 | K33: đã bao gồm
A34: 7 | B34: Polishing for bottom, cover slab Đánh bóng đáy bể, mặt bể | D34: m2 | E34: 1727.2125 | I34: =+SUM(F34:H34) -> 0 | J34: =ROUND(E34*I34,0) -> 0
A36: 4 | B36: FORM WORK / CÔNG TÁC VÁN KHUÔN | J36: =+SUM(J37:J40) -> 0
A37: 1 | B37: For lean concrete Ván khuôn bê tông lót | D37: m2 | E37: 4.158 | I37: =+SUM(F37:H37) -> 0 | J37: =ROUND(E37*I37,0) -> 0
A38: 2 | B38: Formwork for bottom Ván khuôn đáy bể | D38: m2 | E38: 28.812 | I38: =+SUM(F38:H38) -> 0 | J38: =ROUND(E38*I38,0) -> 0
A39: 3 | B39: Formwork for wall, colum Ván khuôn thành bể, cột | C39: (including scaffolding, bracing, supports, etc.) | D39: m2 | E39: 770.175 | I39: =+SUM(F39:H39) -> 0 | J39: =ROUND(E39*I39,0) -> 0
A40: 4 | B40: Formwork for cover slab Ván khuôn nắp bể | C40: (including scaffolding, bracing, supports, etc.) | D40: m2 | E40: 453.18262 | I40: =+SUM(F40:H40) -> 0 | J40: =ROUND(E40*I40,0) -> 0
A42: 5 | B42: REINFORCEMENT WORK / CÔNG TÁC CỐT THÉP | J42: =+SUM(J43:J45) -> 0
A43: 1 | B43: Re-bar for bottom Cốt thép đáy bể | D43: ton | E43: 12.097419 | I43: =+SUM(F43:H43) -> 0 | J43: =ROUND(E43*I43,0) -> 0 | K43: Hoa Phat/ Equivalent
A44: 2 | B44: Re-bar for wall, colum Cốt thép thành bể, cột | D44: ton | E44: 8.855631 | I44: =+SUM(F44:H44) -> 0 | J44: =ROUND(E44*I44,0) -> 0 | K44: =K43 -> Hoa Phat/ Equivalent
A45: 3 | B45: Re-bar for cover slab Cốt thép thành nắp bể | D45: ton | E45: 2.8714649 | I45: =+SUM(F45:H45) -> 0 | J45: =ROUND(E45*I45,0) -> 0 | K45: =K44 -> Hoa Phat/ Equivalent
A47: B | B47: FINISING WORK / CÔNG TÁC HOÀN THIỆN | J47: =+J48+J53 -> 0
A48: 1 | B48: WET FINISHING WORK / CÔNG TÁC HOÀN THIỆN MỀM | J48: =+SUM(J49:J51) -> 0
A49: 1 | B49: Bitum waterproofing Chống thấm bằng bitum | C49: Outside & Top Slab of water tank 3 layer, membrane 1.5kg/m2/lớp | D49: m2 | E49: 1727.2125 | I49: =+SUM(F49:H49) -> 0 | J49: =ROUND(E49*I49,0) -> 0
A50: 2 | B50: Expoxy memberane waterproofing (non posion ) Màng chống thấm expoxy ( không độc hại) | C50: finishing 2 layer / hoàn thiện 2 lớp | D50: m2 | E50: 1727.2125 | I50: =+SUM(F50:H50) -> 0 | J50: =ROUND(E50*I50,0) -> 0
A51: 3 | B51: Liquid water proofing with protection mortar 15mm | C51: Silk Seal -wp1000 / Cement mortar grade 75 | D51: m2 | E51: 1727.2125 | I51: =+SUM(F51:H51) -> 0 | J51: =ROUND(E51*I51,0) -> 0
A53: 2 | B53: OTHERS WORK/ CÔNG VIỆC KHÁC | J53: =+SUM(J54:J58) -> 0
A54: 1 | B54: Nắp bể / Inox cover thk 3mm | C54: SUS 304, thk 3mm, 800x800 | D54: ea | E54: 20 | I54: =+SUM(F54:H54) -> 0 | J54: =ROUND(E54*I54,0) -> 0
A55: 2 | B55: Ladder for tank Thang leo xuống bể | C55: sus 304 | D55: ea | E55: 16 | I55: =+SUM(F55:H55) -> 0 | J55: =ROUND(E55*I55,0) -> 0
A56: 3 | B56: UPVC dowspout D90 Ống dẫn nước UPVC D90 | D56: m | E56: 100 | I56: =+SUM(F56:H56) -> 0 | J56: =ROUND(E56*I56,0) -> 0
A57: 4 | B57: Cút D90 | D57: ea | E57: 16 | I57: =+SUM(F57:H57) -> 0 | J57: =ROUND(E57*I57,0) -> 0
A58: 5 | B58: Water stop for concrete pour Băng cản nước mạch ngừng đổ bê tông | D58: m | E58: 286.2 | I58: =+SUM(F58:H58) -> 0 | J58: =ROUND(E58*I58,0) -> 0

Sheet 15.Hàng Rào & Cổng
A1: BILL OF QUANTITIES
A2: ='C4.Hệ Thống Điện & Điện Nhẹ '!A2:K2 -> PROJECT NAME / TÊN DỰ ÁN :
A3: 15. BOUNDARY WALL & GATE/ HÀNG RÀO & CỔNG
A4: NO / STT | B4: WORK SCOPE / CÔNG VIỆC | C4: SPECIFICATION / ĐẶC ĐIỂM KỸ THUẬT | D4: UNIT/ ĐƠN VỊ | E4: QUANTITY / KHỐI LƯỢNG | F4: UNIT PRICE / ĐƠN GIÁ (VNĐ) | J4: AMOUNT / THÀNH TIỀN (VNĐ) | K4: REMARK / GHI CHÚ
F5: MATERIAL / VẬT LIỆU | G5: LABOUR / NHÂN CÔNG | H5: EQUIPMENT / THIẾT BỊ | I5: UNIT PRICE / TỔNG ĐƠN GIÁ
A6: 15 | B6: BOUNDARY WALL & GATE/ HÀNG RÀO & CỔNG | J6: =+J7+J13 -> 0
A7: A | B7: =$B$26 -> FENCE / HÀNG RÀO | J7: =+SUM(J8:J12) -> 0
A8: 1 | B8: =+B27 -> EARTH WORK / CÔNG TÁC ĐẤT | D8: lot | E8: 1 | J8: =+J27 -> 0
A9: 2 | B9: =+B32 -> CONCRETE WORK / CÔNG TÁC BÊ TÔNG | D9: lot | E9: 1 | J9: =+J32 -> 0
A10: 3 | B10: =+B36 -> FORM WORK / CÔNG TÁC VÁN KHUÔN | D10: lot | E10: 1 | J10: =+J36 -> 0
A11: 4 | B11: =+B41 -> REINFORCEMENT WORK / CÔNG TÁC CỐT THÉP | D11: lot | E11: 1 | J11: =+J41 -> 0
A12: 5 | B12: =+B44 -> FINISING WORK / CÔNG TÁC HOÀN THIỆN | J12: =+J44 -> 0
A13: C | B13: GATE & SIGNBOARD/ CỔNG VÀ BIỂN HIỆU | J13: =SUM(J14:J22) -> 0
A14: 1 | B14: EARTH WORK / CÔNG TÁC ĐẤT | D14: lot | E14: 1 | J14: =J51 -> 0
A15: 2 | B15: CONCRETE WORK / CÔNG TÁC BÊ TÔNG | D15: lot | E15: 1 | J15: =J57 -> 0
A16: 3 | B16: FORM WORK / CÔNG TÁC VÁN KHUÔN | D16: lot | E16: 1 | J16: =J62 -> 0
A17: 4 | B17: REINFORCEMENT WORK / CÔNG TÁC CỐT THÉP | D17: lot | E17: 1 | J17: =J67 -> 0
A18: 5 | B18: BRICK WORK / CÔNG TÁC XÂY | D18: lot | E18: 1 | J18: =J70 -> 0
A19: 6 | B19: PLASTERING WORK / CÔNG TÁC TRÁT | D19: lot | E19: 1 | J19: =J73 -> 0
A20: 7 | B20: PAINTING WORK / CÔNG TÁC SƠN | D20: lot | E20: 1 | J20: =J76 -> 0
A21: 8 | B21: GRANITE & FINISHING WORK / ỐP VÀ HOÀN THIỆN | D21: lot | E21: 1 | J21: =J79 -> 0
A22: 9 | B22: OTHERS WORK/ CÔNG VIỆC KHÁC | D22: lot | E22: 1 | J22: =J83 -> 0
A26: A | B26: FENCE / HÀNG RÀO | J26: =+J27+J32+J36+J41+J44 -> 0
A27: 1 | B27: EARTH WORK / CÔNG TÁC ĐẤT | J27: =+SUM(J28:J31) -> 0
A28: 1 | B28: Excavation Đào đất | D28: m3 | E28: 1116.57 | I28: =+SUM(F28:H28) -> 0 | J28: =ROUND(E28*I28,0) -> 0
A29: 2 | B29: Backfilling soil for foundation Đắp đất | D29: m3 | E29: 334.971 | I29: =+SUM(F29:H29) -> 0 | J29: =ROUND(E29*I29,0) -> 0
A30: 3 | B30: Remove surplus soil Vận chuyển đất đổ | C30: Distance D<=1Km Khoảng cách D<=1Km | D30: m3 | E30: 781.599 | I30: =+SUM(F30:H30) -> 0 | J30: =ROUND(E30*I30,0) -> 0
A32: 2 | B32: CONCRETE WORK / CÔNG TÁC BÊ TÔNG | J32: =+SUM(J33:J34) -> 0
A33: 1 | B33: Lean concrete for foundation & ground beam Bê tông lót cho móng, dầm | C33: Gr. 100 | D33: m3 | E33: 33.3205 | I33: =+SUM(F33:H33) -> 0 | J33: =ROUND(E33*I33,0) -> 0
A34: 2 | B34: Concrete for foundation & ground beam Bê tông móng, dầm móng | C34: Gr. 250 | D34: m3 | E34: 184.52244 | I34: =+SUM(F34:H34) -> 0 | J34: =ROUND(E34*I34,0) -> 0
A36: 3 | B36: FORM WORK / CÔNG TÁC VÁN KHUÔN | J36: =+SUM(J37:J40) -> 0
A37: 1 | B37: For lean concrete for foundation Ván khuôn bê tông lót móng | D37: m2 | E37: 125.7795 | I37: =+SUM(F37:H37) -> 0 | J37: =ROUND(E37*I37,0) -> 0
A38: 2 | B38: For foundation & ground beam Ván khuôn cho móng, dầm | D38: m2 | E38: 905.751 | I38: =+SUM(F38:H38) -> 0 | J38: =ROUND(E38*I38,0) -> 0
A39: 3 | B39: For column Ván khuôn cho cột, giằng tường | D39: m2 | E39: 305.025 | I39: =+SUM(F39:H39) -> 0 | J39: =ROUND(E39*I39,0) -> 0
A41: 4 | B41: REINFORCEMENT WORK / CÔNG TÁC CỐT THÉP | J41: =+SUM(J42:J42) -> 0
A42: 1 | B42: Re-bar for fence style 1 Cốt thép cho hàng rào loại 1 | D42: ton | E42: 20.758775 | I42: =+SUM(F42:H42) -> 0 | J42: =ROUND(E42*I42,0) -> 0 | K42: Hoa Phat
A44: 5 | B44: FINISING WORK / CÔNG TÁC HOÀN THIỆN | J44: =+SUM(J45:J48) -> 0
A45: 1 | B45: Brick work wall Tường gạch xây | D45: m3 | E45: 67.9455 | I45: =+SUM(F45:H45) -> 0 | J45: =ROUND(E45*I45,0) -> 0
A46: 2 | B46: Plastering wall brick outside surfaces 2.0cm / trát ngoài tường gạch dày 2.0cm | C46: Cement motar grade 75 Vữa XM 75# | D46: m2 | E46: 1358.91 | I46: =+SUM(F46:H46) -> 0 | J46: =ROUND(E46*I46,0) -> 0
A47: 3 | B47: Paint for wall Sơn tường | C47: Bao gồm bả/ include putty | D47: m2 | E47: 1358.91 | I47: =+SUM(F47:H47) -> 0 | J47: =ROUND(E47*I47,0) -> 0 | K47: ='[79]2.Nhà Xưởng & Văn Phòng'!K100 -> Dulux/ Jotun
A48: 4 | B48: Steel frence Hàng rào thép | C48: Welded wire mesh fence | D48: m2 | E48: 700.875 | I48: =+SUM(F48:H48) -> 0 | J48: =ROUND(E48*I48,0) -> 0
A50: B | B50: GATE & SIGNBOARD, FLAG POLE/ CỔNG VÀ BIỂN HIỆU, CỘT CỜ | J50: =+J51+J57+J62+J67+J70+J73+J76+J79+J83 -> 0
A51: 1 | B51: EARTH WORK / CÔNG TÁC ĐẤT | J51: =SUM(J52:J55) -> 0
A52: 1 | B52: Excavation Đào đất | D52: m3 | E52: 15.35952 | I52: =+SUM(F52:H52) -> 0 | J52: =ROUND(E52*I52,0) -> 0
A53: 2 | B53: Backfilling soil for foundation Đắp đất | D53: m3 | E53: 5.11984 | I53: =+SUM(F53:H53) -> 0 | J53: =ROUND(E53*I53,0) -> 0
A54: 3 | B54: Remove surplus soil Vận chuyển đất đổ đi | C54: Distance D<=1Km Khoảng cách D<=1Km | D54: m3 | E54: 10.23968 | I54: =+SUM(F54:H54) -> 0 | J54: =ROUND(E54*I54,0) -> 0
A55: 4 | B55: Earth compaction, K=0.9 Đầm đất, K=0.9 | D55: m2 | E55: 13.8 | I55: =+SUM(F55:H55) -> 0 | J55: =ROUND(E55*I55,0) -> 0
A57: 2 | B57: CONCRETE WORK / CÔNG TÁC BÊ TÔNG | J57: =SUM(J58:J61) -> 0
A58: 1 | B58: Lean concrete Bê tông lót | C58: Gr. 100 | D58: m3 | E58: 0.634995 | I58: =+SUM(F58:H58) -> 0 | J58: =ROUND(E58*I58,0) -> 0
A59: 2 | B59: Concrete for wall bracing Bê tông giằng tường | C59: Gr. 250 | D59: m3 | E59: 1.04236 | I59: =+SUM(F59:H59) -> 0 | J59: =ROUND(E59*I59,0) -> 0
A60: 3 | B60: Concrete for slab Bê tông cho sàn | C60: Gr. 250 | D60: m3 | E60: 2.3175 | I60: =+SUM(F60:H60) -> 0 | J60: =ROUND(E60*I60,0) -> 0
A62: 3 | B62: FORM WORK / CÔNG TÁC VÁN KHUÔN | J62: =+SUM(J63:J66) -> 0
A63: 1 | B63: Form work for lean concrete Ván khuôn bê tông lót | D63: m2 | E63: 4.738 | I63: =+SUM(F63:H63) -> 0 | J63: =ROUND(E63*I63,0) -> 0
A64: 2 | B64: Form work for wall bracing Ván khuôn bê tông giằng tường | D64: m2 | E64: 9.476 | I64: =+SUM(F64:H64) -> 0 | J64: =ROUND(E64*I64,0) -> 0
A65: 3 | B65: Form work for slab Ván khuôn cho sàn | D65: m2 | E65: 19.0035 | I65: =+SUM(F65:H65) -> 0 | J65: =ROUND(E65*I65,0) -> 0
A67: 4 | B67: REINFORCEMENT WORK / CÔNG TÁC CỐT THÉP | J67: =+SUM(J68:J69) -> 0
A68: 1 | B68: Re-bar for gate Cốt thép | D68: ton | E68: 0.3107 | I68: =+SUM(F68:H68) -> 0 | J68: =ROUND(E68*I68,0) -> 0
A70: 5 | B70: BRICK WORK / CÔNG TÁC XÂY | J70: =+SUM(J71:J72) -> 0
A71: 1 | B71: Brick work wall Tường xây gạch | D71: m3 | E71: 15.348751 | I71: =+SUM(F71:H71) -> 0 | J71: =ROUND(E71*I71,0) -> 0
A73: 6 | B73: PLASTERING WORK / CÔNG TÁC TRÁT | J73: =+SUM(J74:J75) -> 0
A74: 1 | B74: Plastering wall brick surfaces 2.0cm Trát tường dày 2.0cm | D74: m2 | E74: 99.69366 | I74: =+SUM(F74:H74) -> 0 | J74: =ROUND(E74*I74,0) -> 0
A76: 7 | B76: PAINTING WORK / CÔNG TÁC SƠN | J76: =+SUM(J77:J77) -> 0
A77: 1 | B77: Paint for wall Sơn tường | C77: 3 lớp (1 lót + 2 phủ) | D77: m2 | E77: 99.69366 | I77: =+SUM(F77:H77) -> 0 | J77: =ROUND(E77*I77,0) -> 0
A79: 8 | B79: GRANITE & FINISHING WORK / ỐP VÀ HOÀN THIỆN | J79: =+SUM(J80:J81) -> 0
A80: 1 | B80: Granite stone for gate Ốp đá granite | C80: thk 20mm | D80: m2 | E80: 109.92 | I80: =+SUM(F80:H80) -> 0 | J80: =ROUND(E80*I80,0) -> 0
A81: 2 | B81: Cement for granit Vữa xi măng cho công tác ốp đá granit | D81: m2 | E81: 109.92 | I81: =+SUM(F81:H81) -> 0 | J81: =ROUND(E81*I81,0) -> 0 | K81: bao gồm
A83: 9 | B83: OTHERS WORK/ CÔNG VIỆC KHÁC | J83: =+SUM(J84:J88) -> 0
A84: 1 | B84: Sus swing gate Cổng mở inox | C84: L=1.2m | D84: lot | E84: 2 | I84: =+SUM(F84:H84) -> 0 | J84: =ROUND(E84*I84,0) -> 0
A85: 2 | B85: Auto gate Cổng xếp tự động | C85: L=11m, H=1,6m | D85: lot | E85: 2 | I85: =+SUM(F85:H85) -> 0 | J85: =ROUND(E85*I85,0) -> 0 | K85: Thuan Xuong Mon
A86: 3 | B86: Motor for auto gate Mô tơ cho cổng tự dộng | D86: set | E86: 2 | I86: =+SUM(F86:H86) -> 0 | J86: =ROUND(E86*I86,0) -> 0 | K86: Thuan Xuong Mon
A87: 4 | B87: Logo name of factory Logo tên công ty | C87: Sus304 | D87: set | E87: 2 | I87: =+SUM(F87:H87) -> 0 | J87: =ROUND(E87*I87,0) -> 0
A88: 5 | B88: Flag pole inox 10.0m Cột cờ inox cao 10.0m | D88: set | E88: 3 | I88: =+SUM(F88:H88) -> 0 | J88: =ROUND(E88*I88,0) -> 0

Sheet B.Hạ Tầng Kỹ Thuật
A1: BILL OF QUANTITIES
A2: ='C4.Hệ Thống Điện & Điện Nhẹ '!A2:K2 -> PROJECT NAME / TÊN DỰ ÁN :
A3: B.CIVIL WORKS/ HẠ TẦNG KỸ THUẬT
A4: NO / STT | B4: WORK SCOPE / CÔNG VIỆC | C4: SPECIFICATION / ĐẶC ĐIỂM KỸ THUẬT | D4: UNIT/ ĐƠN VỊ | E4: QUANTITY / KHỐI LƯỢNG | F4: UNIT PRICE / ĐƠN GIÁ (VNĐ) | J4: AMOUNT / THÀNH TIỀN (VNĐ) | K4: REMARK / GHI CHÚ
F5: MATERIAL / VẬT LIỆU | G5: LABOUR / NHÂN CÔNG | H5: EQUIPMENT / THIẾT BỊ | I5: UNIT PRICE / TỔNG ĐƠN GIÁ
A6: B | B6: CIVIL WORKS/ PHẦN NGOÀI NHÀ | J6: =+SUM(J7:J11) -> 0
A7: 1 | B7: ROAD/ ĐƯỜNG | D7: Lot | E7: 1 | J7: =+J14 -> 0
A8: 2 | B8: STORM WATER DRAINAGE SYSTEM/ HỆ THỐNG THOÁT NƯỚC MƯA | D8: Lot | E8: 1 | J8: =+J54 -> 0
A9: 3 | B9: WASTE WATER DRAINAGE SYSTEM/ HỆ THỐNG THOÁT NƯỚC THẢI NGOÀI NHÀ | D9: Lot | E9: 1 | J9: =+J129 -> 0
A10: 4 | B10: LANDSCAPE/ CẢNH QUAN | D10: Lot | E10: 1 | J10: =+J156 -> 0
A11: 5 | B11: SETPTIC TANK/ BỂ PHỐT | D11: Lot | E11: 1 | J11: =J163 -> 0
A14: 1 | B14: ROAD/ ĐƯỜNG | J14: =+SUM(J16:J52) -> 0
A15: I | B15: ROAD TYPE I / ĐƯỜNG NỘI BỘ LOẠI I
A16: 1 | B16: Excavation/ Đào đất | D16: m3 | E16: 2585.804 | I16: =+SUM(F16:H16) -> 0 | J16: =ROUND(E16*I16,0) -> 0
A17: 2 | B17: Remove surplus soil/ Vận chuyển đất đổ đi | C17: Distance D<=1Km Khoảng cách D<=1Km | D17: m3 | E17: 2585.804 | I17: =+SUM(F17:H17) -> 0 | J17: =ROUND(E17*I17,0) -> 0
A18: 3 | B18: Earth compaction, K=0.9 Đầm đất, K=0.9 | C18: K=0.9 | D18: m2 | E18: 9945.4 | I18: =+SUM(F18:H18) -> 0 | J18: =ROUND(E18*I18,0) -> 0
A19: 4 | B19: Compacting by stone aggregate K=0.95 Đá cấp phối đầm chặt K=0.95 | C19: Stone 0x4 Cấp phối đá dăm | D19: m3 | E19: 3878.706 | I19: =+SUM(F19:H19) -> 0 | J19: =ROUND(E19*I19,0) -> 0
A20: 5 | B20: 1 layer nylon thk. 0.3mm 1 lớp nylon dày 0.3mm | D20: m2 | E20: 9945.4 | I20: =+SUM(F20:H20) -> 0 | J20: =ROUND(E20*I20,0) -> 0
A21: 6 | B21: Formwork/ Ván khuôn. | D21: m2 | E21: 994.54 | I21: =+SUM(F21:H21) -> 0 | J21: =ROUND(E21*I21,0) -> 0
A22: 7 | B22: Rebar Cốt thép | C22: Fi10@200, 2 layer | D22: tons | E22: 126.40802 | I22: =+SUM(F22:H22) -> 0 | J22: =ROUND(E22*I22,0) -> 0
A23: 8 | B23: Concrete for road type 1 Bê tông cho đường loại 1 | C23: G.250, thk 200mm | D23: m3 | E23: 2088.534 | I23: =+SUM(F23:H23) -> 0 | J23: =ROUND(E23*I23,0) -> 0
A24: 9 | B24: Pump car Bơm bê tông | D24: m3 | E24: 2088.534 | I24: =+SUM(F24:H24) -> 0 | J24: =ROUND(E24*I24,0) -> 0 | K24: đã bao gồm
A25: 10 | B25: Polishing for slab Xoa nền | D25: m2 | E25: 9945.4 | I25: =+SUM(F25:H25) -> 0 | J25: =ROUND(E25*I25,0) -> 0
A26: 13 | B26: Painting oil roading Sơn dầu vạch kẻ đường | D26: lot | E26: 1 | I26: =+SUM(F26:H26) -> 0 | J26: =ROUND(E26*I26,0) -> 0
A27: II | B27: ROAD TYPE II / ĐƯỜNG NỘI BỘ LOẠI II
A28: 1 | B28: Excavation/ Đào đất | D28: m3 | E28: 73.84 | I28: =+SUM(F28:H28) -> 0 | J28: =ROUND(E28*I28,0) -> 0
A29: =A28+1 -> 2 | B29: Remove surplus soil/ Vận chuyển đất đổ đi | C29: Distance D<=1Km Khoảng cách D<=1Km | D29: m3 | E29: 73.84 | I29: =+SUM(F29:H29) -> 0 | J29: =ROUND(E29*I29,0) -> 0
A30: =A29+1 -> 3 | B30: Earth compaction, K=0.9 Đầm đất, K=0.9 | D30: m2 | E30: 284 | I30: =+SUM(F30:H30) -> 0 | J30: =ROUND(E30*I30,0) -> 0
A31: =A30+1 -> 4 | B31: Compacting by stone aggregate K=0.95 Đá cấp phối đầm chặt K=0.95 | C31: Stone 0x4 Cấp phối đá dăm | D31: m3 | E31: 73.84 | I31: =+SUM(F31:H31) -> 0 | J31: =ROUND(E31*I31,0) -> 0
A32: =A31+1 -> 5 | B32: 1 layer nylon thk. 0.3mm 1 lớp nylon dày 0.3mm | D32: m2 | E32: 284 | I32: =+SUM(F32:H32) -> 0 | J32: =ROUND(E32*I32,0) -> 0
A33: =A32+1 -> 6 | B33: Formwork/ Ván khuôn. | D33: m2 | E33: 9.34 | I33: =+SUM(F33:H33) -> 0 | J33: =ROUND(E33*I33,0) -> 0
A34: =A33+1 -> 7 | B34: Rebar D10@200 1 layer Cốt thép đường 1 lớp D10@200 | C34: D10@200 1 layer 1 lớp D10@200 | D34: tons | E34: 1.8048484 | I34: =+SUM(F34:H34) -> 0 | J34: =ROUND(E34*I34,0) -> 0
A35: =A34+1 -> 8 | B35: Concrete for road type Bê tông cho đường loại 2 | C35: G.250, thk 100mm | D35: m3 | E35: 29.82 | I35: =+SUM(F35:H35) -> 0 | J35: =ROUND(E35*I35,0) -> 0
A36: =A35+1 -> 9 | B36: Pump car Bơm bê tông | D36: m3 | E36: 29.82 | I36: =+SUM(F36:H36) -> 0 | J36: =ROUND(E36*I36,0) -> 0 | K36: đã bao gồm
A37: =A36+1 -> 10 | B37: Polishing for slab Xoa nền | D37: m2 | E37: 284 | I37: =+SUM(F37:H37) -> 0 | J37: =ROUND(E37*I37,0) -> 0
A38: =A37+1 -> 11 | B38: Bituminous Prime Coat 1kg/m2 Tưới nhựa thấm bám 1kg/m2 | D38: m2 | E38: 284 | I38: =+SUM(F38:H38) -> 0 | J38: =ROUND(E38*I38,0) -> 0
A39: =A38+1 -> 12 | B39: Course Asphalt Concrete compact, thick 50mm Bê tông nhựa chặt 12 dầy50mm | C39: Asphalt concrete C12.5 50mm thk | D39: m3 | E39: 14.91 | I39: =+SUM(F39:H39) -> 0 | J39: =ROUND(E39*I39,0) -> 0
A40: =A39+1 -> 13 | B40: Bituminous Tack Coat 0.5kg/m2 Tưới nhựa dính bám | D40: m2 | E40: 284 | I40: =+SUM(F40:H40) -> 0 | J40: =ROUND(E40*I40,0) -> 0
A41: =A40+1 -> 14 | B41: Final Asphalt Concrete Compact Bê Tông Nhựa Chặt 9.5 | C41: Asphalt Concrete C9.5 Thk 40mm | D41: m3 | E41: 11.928 | I41: =+SUM(F41:H41) -> 0 | J41: =ROUND(E41*I41,0) -> 0
A42: =A41+1 -> 15 | B42: Painting oil roading Sơn dầu vạch kẻ đường | D42: lot | E42: 2 | I42: =+SUM(F42:H42) -> 0 | J42: =ROUND(E42*I42,0) -> 0
A43: =A42+1 -> 16 | B43: Cutting, breaking curb, pavement/ Cắt đục bó vỉa, vỉa hè | D43: lot | E43: 120 | I43: =+SUM(F43:H43) -> 0 | J43: =ROUND(E43*I43,0) -> 0
A44: =A43+1 -> 17 | B44: Transport derbis/ Vận chuyển xà bần | D44: Lot | E44: 46.8 | I44: =+SUM(F44:H44) -> 0 | J44: =ROUND(E44*I44,0) -> 0
A45: =A44+1 -> 18 | B45: Re install curb, conection road ip/ Thi công lại bó vỉa, kết nối đường KCN | D45: lot | E45: 1 | I45: =+SUM(F45:H45) -> 0 | J45: =ROUND(E45*I45,0) -> 0
A46: =A45+1 -> 19 | B46: Relocation of infrastructure systems for IP Di dời hệ thống hạ tầng của KCN | D46: lot | E46: 1 | I46: =+SUM(F46:H46) -> 0 | J46: =ROUND(E46*I46,0) -> 0
A48: III | B48: CURVE CONCRETE WORK/ CÔNG TÁC BÓ VỈA BÊ TÔNG
A49: 1 | B49: Formwork/ Ván khuôn. | D49: m2 | E49: 268.418 | I49: =+SUM(F49:H49) -> 0 | J49: =ROUND(E49*I49,0) -> 0
A50: 2 | B50: Lean concrete for curb block Bê tông lót cho bó vỉa | C50: Gr. 100 | D50: m3 | E50: 36.961159 | I50: =+SUM(F50:H50) -> 0 | J50: =ROUND(E50*I50,0) -> 0
A51: 3 | B51: Cement motar for curb block Vữa đệm bó vỉa | D51: m3 | E51: 7.3922317 | I51: =+SUM(F51:H51) -> 0 | J51: =ROUND(E51*I51,0) -> 0
A52: 4 | B52: Concrete curb block Bó vỉa bê tông | C52: 80X22x20cm; Gr. 250 | D52: m | E52: 1342.09 | I52: =+SUM(F52:H52) -> 0 | J52: =ROUND(E52*I52,0) -> 0
A54: 2 | B54: STORM WATER DRAINAGE SYSTEM/ HỆ THỐNG THOÁT NƯỚC MƯA | J54: =+SUM(J55:J128) -> 0
A55: I | B55: Manhole type MH-1/ Hố ga loại MH-1 | C55: On pavement/ Hố ga trên vỉa hè | D55: ea | E55: 41
A56: 1 | B56: Excavation/ Đào đất | D56: m3 | E56: 229.36909 | I56: =+SUM(F56:H56) -> 0 | J56: =ROUND(E56*I56,0) -> 0
A57: 2 | B57: Backfilling soil for foundation/ Lấp đất hố móng | D57: m3 | E57: 76.456363 | I57: =+SUM(F57:H57) -> 0 | J57: =ROUND(E57*I57,0) -> 0
A58: 3 | B58: Remove surplus soil/ Vận chuyển đất | C58: Distance D<=1Km Khoảng cách D<=1Km | D58: m3 | E58: 152.91273 | I58: =+SUM(F58:H58) -> 0 | J58: =ROUND(E58*I58,0) -> 0
A59: 4 | B59: Earth compaction Đầm đất | D59: m2 | E59: 110.2736 | I59: =+SUM(F59:H59) -> 0 | J59: =ROUND(E59*I59,0) -> 0
A60: 5 | B60: Lean concrete Bê tông lót M100 | D60: m3 | E60: 11.358181 | I60: =+SUM(F60:H60) -> 0 | J60: =ROUND(E60*I60,0) -> 0
A61: 6 | B61: Formwork/ Ván khuôn | D61: m2 | E61: 638.43314 | I61: =+SUM(F61:H61) -> 0 | J61: =ROUND(E61*I61,0) -> 0
A62: 7 | B62: Concrete for manhole/ Bê tông | C62: Gr. 200 | D62: m3 | E62: 111.93732 | I62: =+SUM(F62:H62) -> 0 | J62: =ROUND(E62*I62,0) -> 0
A63: 8 | B63: Re-bar for manhole/ Thép | D63: kg | E63: 4922.46 | I63: =+SUM(F63:H63) -> 0 | J63: =ROUND(E63*I63,0) -> 0
A64: 9 | B64: Steel angle 100x100x8mm Thép hàn góc 100x100x8mm | D64: m | E64: 210.084 | I64: =+SUM(F64:H64) -> 0 | J64: =ROUND(E64*I64,0) -> 0
A65: 10 | B65: Steel plate100x5mm Thép tấm 100x5mm quanh tấm đan | D65: m | E65: 401.6565 | I65: =+SUM(F65:H65) -> 0 | J65: =ROUND(E65*I65,0) -> 0
A66: 11 | B66: Plastering work/ Trát | D66: m2 | E66: 633.778 | I66: =+SUM(F66:H66) -> 0 | J66: =ROUND(E66*I66,0) -> 0
A67: 12 | B67: Screen (600x140)mm Lưới chắn rác (600x140)mm | C67: D10a150 | D67: lot | E67: 41 | I67: =+SUM(F67:H67) -> 0 | J67: =ROUND(E67*I67,0) -> 0
A68: 13 | B68: Stair Thang xuống thăm hố ga | C68: D25 | D68: lot | E68: 41 | I68: =+SUM(F68:H68) -> 0 | J68: =ROUND(E68*I68,0) -> 0
A70: II | B70: Manhole type MH-1A/ Hố ga loại MH-1A | C70: On road/ Hố ga trên đường | D70: ea | E70: 20
A71: 1 | B71: Excavation/ Đào đất | D71: m3 | E71: 111.88736 | I71: =+SUM(F71:H71) -> 0 | J71: =ROUND(E71*I71,0) -> 0
A72: 2 | B72: Backfilling soil for foundation/ Lấp đất hố móng | D72: m3 | E72: 37.295787 | I72: =+SUM(F72:H72) -> 0 | J72: =ROUND(E72*I72,0) -> 0
A73: 3 | B73: Remove surplus soil/ Vận chuyển đất | D73: m3 | E73: 74.591573 | I73: =+SUM(F73:H73) -> 0 | J73: =ROUND(E73*I73,0) -> 0
A74: 4 | B74: Earth compaction Đầm đất | D74: m2 | E74: 53.792 | I74: =+SUM(F74:H74) -> 0 | J74: =ROUND(E74*I74,0) -> 0
A75: 5 | B75: Lean concrete Bê tông lót M100 | D75: m3 | E75: 0.80724 | I75: =+SUM(F75:H75) -> 0 | J75: =ROUND(E75*I75,0) -> 0
A76: 6 | B76: Formwork/ Ván khuôn | D76: m2 | E76: 5.208 | I76: =+SUM(F76:H76) -> 0 | J76: =ROUND(E76*I76,0) -> 0
A77: 7 | B77: Concrete for manhole/ Bê tông | C77: Gr. 200 | D77: m3 | E77: 1.61448 | I77: =+SUM(F77:H77) -> 0 | J77: =ROUND(E77*I77,0) -> 0
A78: 8 | B78: Re-bar for manhole/ Thép | D78: kg | E78: 2664.8 | I78: =+SUM(F78:H78) -> 0 | J78: =ROUND(E78*I78,0) -> 0
A79: 9 | B79: Steel angle 50x50x5mm Thép hàn góc 50x50x5mm | D79: m | E79: 61.74 | I79: =+SUM(F79:H79) -> 0 | J79: =ROUND(E79*I79,0) -> 0
A80: 10 | B80: Plastering work/ Trát | D80: m2 | E80: 309.16 | I80: =+SUM(F80:H80) -> 0 | J80: =ROUND(E80*I80,0) -> 0
A81: 11 | B81: Cast iron plate, grade C, load >= 250KN Tấm gang, cấp C, tải trọng >= 250KN | C81: 960x530mm | D81: lot | E81: 20 | I81: =+SUM(F81:H81) -> 0 | J81: =ROUND(E81*I81,0) -> 0
A82: 12 | B82: Stair Thang xuống thăm hố ga | C82: D25 | D82: lot | E82: 20 | I82: =+SUM(F82:H82) -> 0 | J82: =ROUND(E82*I82,0) -> 0
A83: III | B83: Manhole type MH-3/ Hố ga loại MH-3 | C83: Collection drainage roof/ Thu nước mái | D83: ea | E83: 38
A84: 1 | B84: Excavation/ Đào đất | D84: m3 | E84: 61.674912 | I84: =+SUM(F84:H84) -> 0 | J84: =ROUND(E84*I84,0) -> 0
A85: 2 | B85: Backfilling soil for foundation/ Lấp đất hố móng | D85: m3 | E85: 20.558304 | I85: =+SUM(F85:H85) -> 0 | J85: =ROUND(E85*I85,0) -> 0
A86: 3 | B86: Remove surplus soil/ Vận chuyển đất | D86: m3 | E86: 41.116608 | I86: =+SUM(F86:H86) -> 0 | J86: =ROUND(E86*I86,0) -> 0
A87: 4 | B87: Earth compaction Đầm đất | D87: m2 | E87: 39.5352 | I87: =+SUM(F87:H87) -> 0 | J87: =ROUND(E87*I87,0) -> 0
A88: 5 | B88: Lean concrete Bê tông lót M100 | D88: m3 | E88: 4.0721256 | I88: =+SUM(F88:H88) -> 0 | J88: =ROUND(E88*I88,0) -> 0
A89: 6 | B89: Formwork/ Ván khuôn | D89: m2 | E89: 12.83792 | I89: =+SUM(F89:H89) -> 0 | J89: =ROUND(E89*I89,0) -> 0
A90: 7 | B90: Concrete for manhole/ Bê tông | C90: Gr. 200 | D90: m3 | E90: 5.2635472 | I90: =+SUM(F90:H90) -> 0 | J90: =ROUND(E90*I90,0) -> 0
A91: 8 | B91: Xây tường | D91: m3 | E91: 30.16288 | I91: =+SUM(F91:H91) -> 0 | J91: =ROUND(E91*I91,0) -> 0
A92: 9 | B92: Plastering work/ Trát | D92: m2 | E92: 269.7696 | I92: =+SUM(F92:H92) -> 0 | J92: =ROUND(E92*I92,0) -> 0
A93: 10 | B93: Steel angle 50x50x5mm Thép hàn góc 50x50x5mm | D93: m | E93: 124.64 | I93: =+SUM(F93:H93) -> 0 | J93: =ROUND(E93*I93,0) -> 0
A94: 11 | B94: Zinc-dipped steel manhole cover 700x700x30mm Nắp hố ga bằng thép nhúng kẽm 700x700x30mm | D94: set | E94: 38 | I94: =+SUM(F94:H94) -> 0 | J94: =ROUND(E94*I94,0) -> 0
A95: IV | B95: Manhole type MH-4/ Hố ga loại MH4 | C95: Collection drainage roof/ Thu nước mái | D95: ea | E95: 47
A96: 1 | B96: Excavation/ Đào đất | D96: m3 | E96: 43.609236 | I96: =+SUM(F96:H96) -> 0 | J96: =ROUND(E96*I96,0) -> 0
A97: 2 | B97: Backfilling soil for foundation/ Lấp đất hố móng | D97: m3 | E97: 14.536412 | I97: =+SUM(F97:H97) -> 0 | J97: =ROUND(E97*I97,0) -> 0
A98: 3 | B98: Remove surplus soil/ Vận chuyển đất | D98: m3 | E98: 29.072824 | I98: =+SUM(F98:H98) -> 0 | J98: =ROUND(E98*I98,0) -> 0
A99: 4 | B99: Earth compaction Đầm đất | D99: m2 | E99: 27.954638 | I99: =+SUM(F99:H99) -> 0 | J99: =ROUND(E99*I99,0) -> 0
A100: 5 | B100: Lean concrete Bê tông lót M100 | D100: m3 | E100: 2.8793277 | I100: =+SUM(F100:H100) -> 0 | J100: =ROUND(E100*I100,0) -> 0
A101: 6 | B101: Formwork/ Ván khuôn | D101: m2 | E101: 9.0774654 | I101: =+SUM(F101:H101) -> 0 | J101: =ROUND(E101*I101,0) -> 0
A102: 7 | B102: Concrete for manhole/ Bê tông | C102: Gr. 200 | D102: m3 | E102: 1.897014 | I102: =+SUM(F102:H102) -> 0 | J102: =ROUND(E102*I102,0) -> 0
A103: 8 | B103: Xây tường | D103: m3 | E103: 37.30672 | I103: =+SUM(F103:H103) -> 0 | J103: =ROUND(E103*I103,0) -> 0
A104: 9 | B104: Plastering work/ Trát | D104: m2 | E104: 333.6624 | I104: =+SUM(F104:H104) -> 0 | J104: =ROUND(E104*I104,0) -> 0
A105: 10 | B105: Steel angle 50x50x5mm Thép hàn góc 50x50x5mm | D105: m | E105: 116.56 | I105: =+SUM(F105:H105) -> 0 | J105: =ROUND(E105*I105,0) -> 0
...

Sheet C1. Hệ Thống Plumbing
A1: BILL OF QUANTITIES
A3: C1.PLUMBING SYSTEM/ HỆ THỐNG CẤP THOÁT NƯỚC
A4: NO / STT | B4: WORK SCOPE / CÔNG VIỆC | C4: SPECIFICATION / ĐẶC ĐIỂM KỸ THUẬT | D4: UNIT/ ĐƠN VỊ | E4: QUANTITY / KHỐI LƯỢNG | F4: UNIT PRICE / ĐƠN GIÁ (VNĐ) | J4: AMOUNT / THÀNH TIỀN (VNĐ) | K4: REMARK / GHI CHÚ
F5: MATERIAL / VẬT LIỆU | G5: LABOUR / NHÂN CÔNG | H5: EQUIPMENT / THIẾT BỊ | I5: UNIT PRICE / TỔNG ĐƠN GIÁ
A6: C1 | B6: PLUMBING SYSTEM/ HỆ THỐNG CẤP THOÁT NƯỚC | J6: =+SUM(J7:J9) -> 0
A7: 1 | B7: =B11 -> WATER SUPPLY SYSTEM / HỆ THỐNG CẤP NƯỚC | D7: lot | E7: 1 | J7: =+J11 -> 0
A8: 2 | B8: =+B62 -> WASTE WATER SYSTEM / HỆ THỐNG THOÁT NƯỚC THẢI | D8: lot | E8: 1 | J8: =+J62 -> 0
A9: 3 | B9: =+B74 -> SANITARY EQUIPMENT / THIẾT BỊ VỆ SINH | D9: lot | E9: 1 | J9: =+J74 -> 0
A11: 1 | B11: WATER SUPPLY SYSTEM / HỆ THỐNG CẤP NƯỚC | J11: =+SUM(J12:J61) -> 0
A12: A | B12: WATER SUPPLY INTO UNDERGROUND TANKS CẤP NƯỚC VÀO BỂ CHỨA NGẦM
A13: 1 | B13: PP-R pipe Ống PP-R | C13: DN63, PN10 | D13: m | E13: 40 | I13: =+SUM(F13:H13) -> 0 | J13: =ROUND(E13*I13,0) -> 0 | K13: Bình Minh/TP
A14: 2 | B14: Water metter Đồng hồ nước | C14: DN63 | D14: set | E14: 1 | I14: =+SUM(F14:H14) -> 0 | J14: =ROUND(E14*I14,0) -> 0 | K14: Zenner/TĐ
A15: =A14+1 -> 3 | B15: Gate valve Van cổng | C15: DN63 | D15: Set | E15: 1 | I15: =+SUM(F15:H15) -> 0 | J15: =ROUND(E15*I15,0) -> 0 | K15: Viet Nam
A16: =A15+1 -> 4 | B16: Check Valve Van một chiều | C16: DN63 | D16: set | E16: 1 | I16: =+SUM(F16:H16) -> 0 | J16: =ROUND(E16*I16,0) -> 0 | K16: Viet Nam
A17: =A16+1 -> 5 | B17: Soft Coupling Khớp nối mềm | C17: DN63 | D17: Set | E17: 1 | I17: =+SUM(F17:H17) -> 0 | J17: =ROUND(E17*I17,0) -> 0 | K17: Viet Nam
A18: =A17+1 -> 6 | B18: Float valve Van phao | C18: DN63 | D18: Set | E18: 1 | I18: =+SUM(F18:H18) -> 0 | J18: =ROUND(E18*I18,0) -> 0 | K18: Viet Nam
A19: =A18+1 -> 7 | B19: PP-R fitting Phụ kiện ống PP-R | D19: lot | E19: 1 | I19: =+SUM(F19:H19) -> 0 | J19: =ROUND(E19*I19,0) -> 0 | K19: =K13 -> Bình Minh/TP
A20: =A19+1 -> 8 | B20: Connection fee with IZ Chi phí đấu nối | D20: lot | E20: 1 | I20: =+SUM(F20:H20) -> 0 | J20: =ROUND(E20*I20,0) -> 0
A21: =A20+1 -> 9 | B21: Water meter pit with cover Hố đồng hồ nước kèm nắp | D21: pcs | E21: 1 | I21: =+SUM(F21:H21) -> 0 | J21: =ROUND(E21*I21,0) -> 0
A22: =A21+1 -> 10 | B22: Digging and backfilling pipes Đào và lấp đất đường ống | D22: md | E22: 40 | I22: =+SUM(F22:H22) -> 0 | J22: =ROUND(E22*I22,0) -> 0
A23: =A22+1 -> 11 | B23: Sub-Material above Vật tư phụ | D23: lot | E23: 1 | I23: =+SUM(F23:H23) -> 0 | J23: =ROUND(E23*I23,0) -> 0
A24: =A23+1 -> 12 | B24: Transportation Vận chuyển | D24: lot | E24: 1 | I24: =+SUM(F24:H24) -> 0 | J24: =ROUND(E24*I24,0) -> 0 | K24: Đã bao gồm
A25: B | B25: PUMP ROOM / PHÒNG BƠM
A26: 1 | B26: Water supply pump with Inverter Bơm cấp nước có biến tần | C26: 10.8m3/h*39m - 2pump 1 set TAKASI-VN | D26: set | E26: 1 | I26: =+SUM(F26:H26) -> 0 | J26: =ROUND(E26*I26,0) -> 0 | K26: TAKASI-VN
A27: =A26+1 -> 2 | B27: Pressure tank 100liters Bình áp lực 100l | C27: 100L - 10bar | D27: ea | E27: 1 | I27: =+SUM(F27:H27) -> 0 | J27: =ROUND(E27*I27,0) -> 0 | K27: Varem/China
A28: =A27+1 -> 3 | B28: Support pump Giá đỡ bơm | C28: Viet nam | D28: lot | E28: 1 | I28: =+SUM(F28:H28) -> 0 | J28: =ROUND(E28*I28,0) -> 0 | K28: Viet Nam
A29: =A28+1 -> 4 | B29: Pad for Machine Khớp chống trung cho bơm | D29: lot | E29: 1 | I29: =+SUM(F29:H29) -> 0 | J29: =ROUND(E29*I29,0) -> 0 | K29: Viet Nam
A30: =A29+1 -> 5 | B30: Water supply pump control panel Tủ điều khiển bơm cấp nước | D30: ea | E30: 1 | I30: =+SUM(F30:H30) -> 0 | J30: =ROUND(E30*I30,0) -> 0 | K30: LS/Huyndai
A31: =A30+1 -> 6 | B31: PPR Pipe Ống PPR | C31: DN63 | D31: m | E31: 12 | I31: =+SUM(F31:H31) -> 0 | J31: =ROUND(E31*I31,0) -> 0 | K31: =K19 -> Bình Minh/TP
A32: =A31+1 -> 7 | B32: Khớp nối mềm Flexible connection | C32: DN63 | D32: ea | E32: 2 | I32: =+SUM(F32:H32) -> 0 | J32: =ROUND(E32*I32,0) -> 0 | K32: Viet Nam
A33: =A32+1 -> 8 | B33: Y lọc Y strainer | C33: DN63 | D33: ea | E33: 2 | I33: =+SUM(F33:H33) -> 0 | J33: =ROUND(E33*I33,0) -> 0 | K33: Viet Nam
A34: =A33+1 -> 9 | B34: Van một chiều Check valve | C34: DN63 | D34: ea | E34: 2 | I34: =+SUM(F34:H34) -> 0 | J34: =ROUND(E34*I34,0) -> 0 | K34: Viet Nam
A35: =A34+1 -> 10 | B35: Van cổng Gate valve | C35: DN63 | D35: ea | E35: 2 | I35: =+SUM(F35:H35) -> 0 | J35: =ROUND(E35*I35,0) -> 0 | K35: Viet Nam
A36: =A35+1 -> 11 | B36: Van chân(Rọ bơm) Foot valve | C36: DN63 | D36: ea | E36: 2 | I36: =+SUM(F36:H36) -> 0 | J36: =ROUND(E36*I36,0) -> 0 | K36: Viet Nam
A37: =A36+1 -> 12 | B37: Fitting for valve Phụ kiên van | D37: lot | E37: 1 | I37: =+SUM(F37:H37) -> 0 | J37: =ROUND(E37*I37,0) -> 0 | K37: Viet Nam
A38: =A37+1 -> 13 | B38: PP-R fitting Phụ kiện ống PP-R | D38: lot | E38: 1 | I38: =+SUM(F38:H38) -> 0 | J38: =ROUND(E38*I38,0) -> 0 | K38: =K31 -> Bình Minh/TP
A39: =A38+1 -> 14 | B39: Cable and PVC conduit Dây cáp điện và ống luồn | D39: lot | E39: 1 | I39: =+SUM(F39:H39) -> 0 | J39: =ROUND(E39*I39,0) -> 0 | K39: Viet Nam
A40: =A39+1 -> 15 | B40: Suppot for piping Giá đỡ cho ống | D40: lot | E40: 1 | I40: =+SUM(F40:H40) -> 0 | J40: =ROUND(E40*I40,0) -> 0
A41: =A40+1 -> 16 | B41: Accessories Vật tư phụ | D41: lot | E41: 1 | I41: =+SUM(F41:H41) -> 0 | J41: =ROUND(E41*I41,0) -> 0
A42: =A41+1 -> 17 | B42: Transportation Vận chuyển | D42: lot | E42: 1 | I42: =+SUM(F42:H42) -> 0 | J42: =ROUND(E42*I42,0) -> 0 | K42: Đã bao gồm
A43: C | B43: WATER SUPPLY PIPE FOR TREE AND TOILET SYSTEM / HỆ THỐNG ỐNG CẤP NƯỚC TƯỚI CÂY VÀ KHU VỆ SINH
A44: 1 | B44: Gavalnize Steel Pipe D100 Ống thép bảo vệ đường ống | C44: DN65 | D44: m | E44: 47 | I44: =+SUM(F44:H44) -> 0 | J44: =ROUND(E44*I44,0) -> 0 | K44: Viet Nam
A45: =A44+1 -> 2 | B45: PP-R pipe Ống PP-R | C45: DN63 | D45: m | E45: 395 | I45: =+SUM(F45:H45) -> 0 | J45: =ROUND(E45*I45,0) -> 0 | K45: =K38 -> Bình Minh/TP
A46: =A45+1 -> 3 | B46: PP-R pipe Ống PP-R | C46: DN50 | D46: m | E46: 657 | I46: =+SUM(F46:H46) -> 0 | J46: =ROUND(E46*I46,0) -> 0 | K46: =K45 -> Bình Minh/TP
A47: =A46+1 -> 4 | B47: PP-R pipe Ống PP-R | C47: DN40 | D47: m | E47: 80 | I47: =+SUM(F47:H47) -> 0 | J47: =ROUND(E47*I47,0) -> 0 | K47: =K46 -> Bình Minh/TP
A48: =A47+1 -> 5 | B48: PP-R pipe Ống PP-R | C48: DN32 | D48: m | E48: 153 | I48: =+SUM(F48:H48) -> 0 | J48: =ROUND(E48*I48,0) -> 0 | K48: =K47 -> Bình Minh/TP
A49: =A48+1 -> 6 | B49: PP-R pipe Ống PP-R | C49: DN25 | D49: m | E49: 119 | I49: =+SUM(F49:H49) -> 0 | J49: =ROUND(E49*I49,0) -> 0 | K49: =K48 -> Bình Minh/TP
A50: =A49+1 -> 7 | B50: PP-R pipe Ống PP-R | C50: DN20 | D50: m | E50: 152 | I50: =+SUM(F50:H50) -> 0 | J50: =ROUND(E50*I50,0) -> 0 | K50: =K49 -> Bình Minh/TP
A51: =A50+1 -> 8 | B51: Gate Valve PPR Van PPR | C51: DN63 | D51: Pcs | E51: 7 | I51: =+SUM(F51:H51) -> 0 | J51: =ROUND(E51*I51,0) -> 0 | K51: =K50 -> Bình Minh/TP
A52: =A51+1 -> 9 | B52: Gate Valve PPR Van PPR | C52: DN50 | D52: Pcs | E52: 4 | I52: =+SUM(F52:H52) -> 0 | J52: =ROUND(E52*I52,0) -> 0 | K52: =K51 -> Bình Minh/TP
A53: =A52+1 -> 10 | B53: Gate Valve PPR Van PPR | C53: DN32 | D53: Pcs | E53: 8 | I53: =+SUM(F53:H53) -> 0 | J53: =ROUND(E53*I53,0) -> 0 | K53: =K52 -> Bình Minh/TP
A54: =A51+1 -> 9 | B54: Gate Valve PPR Van PPR | C54: DN25 | D54: Pcs | E54: 33 | I54: =+SUM(F54:H54) -> 0 | J54: =ROUND(E54*I54,0) -> 0 | K54: =K51 -> Bình Minh/TP
B55: Gate Valve PPR Van PPR | C55: DN20 | D55: Pcs | E55: 6 | I55: =+SUM(F55:H55) -> 0 | J55: =ROUND(E55*I55,0) -> 0 | K55: =K54 -> Bình Minh/TP
A56: =A54+1 -> 10 | B56: PPR Piping fitting Phụ kiện ống | C56: 20% of pipe | D56: Lot | E56: 1 | I56: =+SUM(F56:H56) -> 0 | J56: =ROUND(E56*I56,0) -> 0 | K56: =K54 -> Bình Minh/TP
A57: =A56+1 -> 11 | B57: Sub-Material above Vật tư treo ống | C57: 5% of pipe | D57: lot | E57: 1 | I57: =+SUM(F57:H57) -> 0 | J57: =ROUND(E57*I57,0) -> 0
A58: =A57+1 -> 12 | B58: Pressure test the pipeline Thử áp lực đường ống | D58: lot | E58: 1 | I58: =+SUM(F58:H58) -> 0 | J58: =ROUND(E58*I58,0) -> 0
A59: =A58+1 -> 13 | B59: Accessories Vật tư phụ | C59: 5% of meterial and labor | D59: lot | E59: 1 | I59: =+SUM(F59:H59) -> 0 | J59: =ROUND(E59*I59,0) -> 0
A60: =A59+1 -> 14 | B60: Excavation and back fill/ Chi phí đào đất , đục tường | D60: lot | E60: 1 | I60: =+SUM(F60:H60) -> 0 | J60: =ROUND(E60*I60,0) -> 0
A61: =A60+1 -> 15 | B61: Transportation Vận chuyển | D61: lot | E61: 1
A62: 2 | B62: WASTE WATER SYSTEM / HỆ THỐNG THOÁT NƯỚC THẢI | J62: =+SUM(J63:J72) -> 0
A63: 1 | B63: Pipe u.PVC Ống nhưa u.PVC | C63: D125, PN10 | D63: m | E63: 81 | I63: =+SUM(F63:H63) -> 0 | J63: =ROUND(E63*I63,0) -> 0 | K63: =K55 -> Bình Minh/TP
A64: =A63+1 -> 2 | B64: Pipe u.PVC Ống nhưa u.PVC | C64: D110, PN10 | D64: m | E64: 75 | I64: =+SUM(F64:H64) -> 0 | J64: =ROUND(E64*I64,0) -> 0 | K64: =K56 -> Bình Minh/TP
A65: =A64+1 -> 3 | B65: Pipe u.PVC Ống nhưa u.PVC | C65: D90, PN10 | D65: m | E65: 97.5 | I65: =+SUM(F65:H65) -> 0 | J65: =ROUND(E65*I65,0) -> 0 | K65: =K64 -> Bình Minh/TP
A66: =A65+1 -> 4 | B66: Pipe u.PVC Ống nhưa u.PVC | C66: D60 | D66: m | E66: 130 | I66: =+SUM(F66:H66) -> 0 | J66: =ROUND(E66*I66,0) -> 0 | K66: =K65 -> Bình Minh/TP
A67: =A66+1 -> 5 | B67: Pipe u.PVC Ống nhưa u.PVC | C67: D42 | D67: m | E67: 92 | I67: =+SUM(F67:H67) -> 0 | J67: =ROUND(E67*I67,0) -> 0 | K67: =K66 -> Bình Minh/TP
A68: =A67+1 -> 6 | B68: PVC Piping fitting Phụ kiện ống PVC | C68: 20% of pipe | D68: Lot | E68: 1 | I68: =+SUM(F68:H68) -> 0 | J68: =ROUND(E68*I68,0) -> 0 | K68: =K67 -> Bình Minh/TP
A69: =A68+1 -> 7 | B69: Sub-Material above Vật tư treo ống | C69: 15% of pipe | D69: lot | E69: 1 | I69: =+SUM(F69:H69) -> 0 | J69: =ROUND(E69*I69,0) -> 0 | K69: Viet Nam
A70: =A69+1 -> 8 | B70: Test to seal the pipe Thử kín đường ống | D70: lot | E70: 1 | I70: =+SUM(F70:H70) -> 0 | J70: =ROUND(E70*I70,0) -> 0
A71: =A70+1 -> 9 | B71: Accessories Vật tư phụ | C71: 5% of meterial and labor | D71: lot | E71: 1 | I71: =+SUM(F71:H71) -> 0 | J71: =ROUND(E71*I71,0) -> 0
A72: =A71+1 -> 10 | B72: Transportation Fee Phí vận chuyển | D72: lot | E72: 1 | I72: =+SUM(F72:H72) -> 0 | J72: =ROUND(E72*I72,0) -> 0
A74: 3 | B74: SANITARY EQUIPMENT / THIẾT BỊ VỆ SINH | J74: =+SUM(J75:J107) -> 0
A75: 1 | B75: Toilet bowl Bồn cầu 2 khối | C75: Inax AC-902VN | D75: Set | E75: 12 | I75: =+SUM(F75:H75) -> 0 | J75: =ROUND(E75*I75,0) -> 0 | K75: For WC of WORKSHOP AND OFFICE
A76: =A75+1 -> 2 | B76: Spray hose for toilet Vòi xịt bồn cầu | C76: Inax CFV-102M | D76: Pcs | E76: 12 | I76: =+SUM(F76:H76) -> 0 | J76: =ROUND(E76*I76,0) -> 0
A77: =A76+1 -> 3 | B77: T-valve for Closet Van T cho bồn cầu | C77: Inax A-703-4 | D77: Pcs | E77: 12 | I77: =+SUM(F77:H77) -> 0 | J77: =ROUND(E77*I77,0) -> 0
A78: =A77+1 -> 4 | B78: Lavatory on table Chậu rửa tay inox | C78: Inox 304 | D78: Set | E78: 13 | I78: =+SUM(F78:H78) -> 0 | J78: =ROUND(E78*I78,0) -> 0
A79: =A78+1 -> 5 | B79: Accessory for lavatory Phụ kiện chậu rửa | D79: Set | E79: 26 | I79: =+SUM(F79:H79) -> 0 | J79: =ROUND(E79*I79,0) -> 0
A80: =A79+1 -> 6 | B80: Hole Lavatory Faucets inox Vòi chậu rửa inox | D80: Set | E80: 26 | I80: =+SUM(F80:H80) -> 0 | J80: =ROUND(E80*I80,0) -> 0
A81: =A80+1 -> 7 | B81: T-valve for Lavatory Van T cho chậu rửa | D81: Pcs | E81: 26 | I81: =+SUM(F81:H81) -> 0 | J81: =ROUND(E81*I81,0) -> 0
A82: =A81+1 -> 8 | B82: Bowl urinal Tiểu nam | C82: Inax U431VR | D82: Set | E82: 4 | I82: =+SUM(F82:H82) -> 0 | J82: =ROUND(E82*I82,0) -> 0
A83: =A82+1 -> 9 | B83: Sensor urinal flush valve & accessories Van xả tiểu cảm ứng và phụ kiện tiểu nam | C83: Inax OKUV-30SM | D83: Set | E83: 4 | I83: =+SUM(F83:H83) -> 0 | J83: =ROUND(E83*I83,0) -> 0
A84: =A83+1 -> 10 | B84: Liquid soap dispenser Hộp đựng xà phòng nước inox | D84: Set | E84: 26 | I84: =+SUM(F84:H84) -> 0 | J84: =ROUND(E84*I84,0) -> 0
A85: =A84+1 -> 11 | B85: Toilet Paper Box Hộp giấy vệ sinh | C85: CAESAR Q7304V | D85: Set | E85: 12 | I85: =+SUM(F85:H85) -> 0 | J85: =ROUND(E85*I85,0) -> 0
A86: =A85+1 -> 12 | B86: Floor drain Thoát sàn | C86: CAESAR ST1414L | D86: Set | E86: 6 | I86: =+SUM(F86:H86) -> 0 | J86: =ROUND(E86*I86,0) -> 0
A87: =A86+1 -> 13 | B87: Mirror for lavatory Gương soi dày 5mm chậu rửa KT 1000x800 | C87: 1000x800 | D87: set | E87: 13 | I87: =+SUM(F87:H87) -> 0 | J87: =ROUND(E87*I87,0) -> 0
A88: =A87+1 -> 14 | B88: Hand dryer Máy sấy tay | C88: Caesar A801 | D88: set | E88: 9 | I88: =+SUM(F88:H88) -> 0 | J88: =ROUND(E88*I88,0) -> 0
A89: =A88+1 -> 15 | B89: Toilet bowl Bồn cầu 2 khối | C89: Inax AC-902VN | D89: Set | E89: 3 | I89: =+SUM(F89:H89) -> 0 | J89: =ROUND(E89*I89,0) -> 0 | K89: For WC of DORMITORY, GUARDHOUSE
A90: =A89+1 -> 16 | B90: Spray hose for toilet Vòi xịt bồn cầu | C90: Inax CFV-102M | D90: Pcs | E90: 3 | I90: =+SUM(F90:H90) -> 0 | J90: =ROUND(E90*I90,0) -> 0
A91: =A90+1 -> 17 | B91: T-valve for Closet Van T cho bồn cầu | C91: Inax A-703-4 | D91: Pcs | E91: 3 | I91: =+SUM(F91:H91) -> 0 | J91: =ROUND(E91*I91,0) -> 0
A92: =A91+1 -> 18 | B92: Lavatory Chậu rửa đơn dương vành | C92: Inax AL-2395V (EC/FC) | D92: Set | E92: 3 | I92: =+SUM(F92:H92) -> 0 | J92: =ROUND(E92*I92,0) -> 0
A93: =A92+1 -> 19 | B93: Accessory for lavatory Phụ kiện chậu rửa | C93: Inax A-674V + A-016V | D93: Set | E93: 3 | I93: =+SUM(F93:H93) -> 0 | J93: =ROUND(E93*I93,0) -> 0
A94: =A93+1 -> 20 | B94: Hole Lavatory Faucets Vòi chậu rửa đơn | C94: Inax LFV-22S | D94: Set | E94: 3 | I94: =+SUM(F94:H94) -> 0 | J94: =ROUND(E94*I94,0) -> 0
A95: =A94+1 -> 21 | B95: T-valve for Lavatory Van T cho chậu rửa | C95: Inax A-703-4 | D95: Pcs | E95: 3 | I95: =+SUM(F95:H95) -> 0 | J95: =ROUND(E95*I95,0) -> 0
A96: =A95+1 -> 22 | B96: Toilet Paper Box Hộp giấy vệ sinh | C96: Inax H-486V | D96: Set | E96: 3 | I96: =+SUM(F96:H96) -> 0 | J96: =ROUND(E96*I96,0) -> 0
A97: =A96+1 -> 23 | B97: Floor drain Thoát sàn | C97: Inax PBFV-110 | D97: Set | E97: 5 | I97: =+SUM(F97:H97) -> 0 | J97: =ROUND(E97*I97,0) -> 0
A98: =A97+1 -> 24 | B98: Flexible connection Dây mềm | C98: Inax A-701-7 | D98: Set | E98: 6 | I98: =+SUM(F98:H98) -> 0 | J98: =ROUND(E98*I98,0) -> 0
A99: =A98+1 -> 25 | B99: Shower Vòi tắm | C99: Inax BFV-3415T-3C | D99: set | E99: 2 | I99: =+SUM(F99:H99) -> 0 | J99: =ROUND(E99*I99,0) -> 0
A100: =A99+1 -> 26 | B100: 10mm thick tempered glass shower enclosure Buồng kính tắm cường lực dày 10mm | D100: set | E100: 2 | I100: =+SUM(F100:H100) -> 0 | J100: =ROUND(E100*I100,0) -> 0
A101: =A100+1 -> 27 | B101: Mirrors Gương soi | D101: set | E101: 3 | I101: =+SUM(F101:H101) -> 0 | J101: =ROUND(E101*I101,0) -> 0
A102: =A101+1 -> 28 | B102: Soap shelf Kệ xà phòng | C102: Inax H-484V | D102: set | E102: 3 | I102: =+SUM(F102:H102) -> 0 | J102: =ROUND(E102*I102,0) -> 0
A103: =A102+1 -> 29 | B103: Support for table Giá đỡ bàn đá | C103: Inax Inox 304 | D103: set | E103: 3 | I103: =+SUM(F103:H103) -> 0 | J103: =ROUND(E103*I103,0) -> 0
...

Sheet C2.Hệ Thống XLNT
A1: BILL OF QUANTITIES
A3: C2.WWS SYSTEM/ HỆ THỐNG XLNT
A4: NO / STT | B4: WORK SCOPE / CÔNG VIỆC | C4: SPECIFICATION / ĐẶC ĐIỂM KỸ THUẬT | D4: UNIT/ ĐƠN VỊ | E4: QUANTITY / KHỐI LƯỢNG | F4: UNIT PRICE / ĐƠN GIÁ (VNĐ) | J4: AMOUNT / THÀNH TIỀN (VNĐ) | K4: REMARK / GHI CHÚ
F5: MATERIAL / VẬT LIỆU | G5: LABOUR / NHÂN CÔNG | H5: EQUIPMENT / THIẾT BỊ | I5: UNIT PRICE / TỔNG ĐƠN GIÁ
A6: C2 | B6: WWS SYSTEM/ HỆ THỐNG XLNT | J6: =+SUM(J7:J11) -> 0
A7: A | B7: =+B12 -> THIẾT BỊ | D7: lot | E7: 1 | J7: =J12 -> 0
A8: B | B8: HỆ THỐNG ĐƯỜNG ỐNG CÔNG NGHỆ | D8: lot | E8: 1 | J8: =J89 -> 0
A9: C | B9: HỆ THỐNG ĐIỆN | D9: lot | E9: 1 | J9: =J92 -> 0
A10: D | B10: CÔNG TÁC KHÁC | D10: lot | E10: 1 | J10: =J95 -> 0
A12: A | B12: THIẾT BỊ | J12: =SUM(J14:J88) -> 0
A13: 1 | B13: Bể thu gom
B14: Song chắn rác | C14: - Vật liệu: Thép không gỉ SUS 304; - Mắt lưới: 5.0 mm; - Xuất xứ: I-GREEN - Vietnam | D14: Bộ | E14: 1 | I14: =H14+F14+G14 -> 0 | J14: =I14*E14 -> 0
B15: Cảm biến mức nước | C15: - Cảm biến đo mức nước trong bể điều hòa nước thải để điều khiển 2 bơm chìm, ON mức nước cao & OFF mức nước thấp - Xuất xứ: HCP - Trung Quốc | D15: Cái | E15: 1 | I15: =H15+F15+G15 -> 0 | J15: =I15*E15 -> 0
B16: Bơm chìm nước thải bể thu gom | C16: - Loại: bơm chìm; - Lưu lượng: Q= 10 m3/h; - Cột áp: H= 12 mH2O; - Công suất: 0.75kW/ 3phase/ 380V/ 50Hz; - Xuất xứ: Kaiquan - Trung Quốc; | D16: Cái | E16: 2 | I16: =H16+F16+G16 -> 0 | J16: =I16*E16 -> 0
B17: Khớp nối nhanh | C17: - Vật liệu: khớp nối bằng gang, thanh dẫn hướng SUS304; - Khớp nối nhanh tùy chọn giúp lắp và tháo bơm chìm dễ dàng; - Xuất xứ: Kaiquan - Trung Quốc; | D17: Cái | E17: 2 | I17: =H17+F17+G17 -> 0 | J17: =I17*E17 -> 0
A18: 2 | B18: Bể điều hòa
B19: Cảm biến mức nước | C19: - Cảm biến đo mức nước trong bể điều hòa nước thải để điều khiển 2 bơm chìm, ON mức nước cao & OFF mức nước thấp - Xuất xứ: HCP - Trung Quốc | D19: Cái | E19: 1 | I19: =H19+F19+G19 -> 0 | J19: =I19*E19 -> 0
B20: Bơm chìm nước thải bể điều hòa | C20: - Loại: bơm chìm; - Lưu lượng: Q= 10 m3/h; - Cột áp: H= 12 mH2O; - Công suất: 0.75kW/ 3phase/ 380V/ 50Hz; - Xuất xứ: Kaiquan - Trung Quốc; | D20: Cái | E20: 2 | I20: =H20+F20+G20 -> 0 | J20: =I20*E20 -> 0
B21: Khớp nối nhanh | C21: - Vật liệu: khớp nối bằng gang, thanh dẫn hướng SUS304; - Khớp nối nhanh tùy chọn giúp lắp và tháo bơm chìm dễ dàng; - Xuất xứ: Kaiquan - Trung Quốc; | D21: Cái | E21: 2 | I21: =H21+F21+G21 -> 0 | J21: =I21*E21 -> 0
B22: Đĩa phân phối khí mịn | C22: - Lưu lượng Q=2-5 m3/h; - Kích thước D=270 mm; - Vật liệu : màng EPDM, khung PP; - Xuất xứ: Jaeger - Đức | D22: Cái | E22: 35 | I22: =H22+F22+G22 -> 0 | J22: =I22*E22 -> 0
B23: Lưu lượng kế điện từ | C23: - Lưu lượng kế điện từ - Hình thức: Thiết bị đo lưu lượng nước thải điện từ, lắp đặt trên đường ống, nối mặt bích - Quy cách：DN65 - Tín hiệu ra : 4-20mA/ Dữ liệu truyền đến tủ điện điều khiển - Chất liệu：FC+PTFE - Xuất xứ: Supmea - Trung Quốc | D23: Cái | E23: 1 | I23: =H23+F23+G23 -> 0 | J23: =I23*E23 -> 0
A24: 3 | B24: Thiết bị tuyển nổi không khí hoà tan DAF
B25: Thiết bị tuyển nổi không khí hòa tan | C25: -Năng lưc xử lý : 9m3/h -Kích thước ngoại hình: L*W*H=5000*1500*2100 mm (hoặc kích thước tương đương) -Nguồn điện: ≤1.65kW/ 3ψ/380V/50Hz -Chất liệu ：SUS304 -Cửa vào/ra nước thải：DN125 -Cửa ra bùn thải：DN80 - Xuất xứ: Mega - Việt Nam -Phụ kiện: * Bơm tuần hoàn 2.2kW x 2 máy * Máy nén khí 2.2kW x 1 máy * Thiết bị vớt váng nổi 0.4kW × 1 máy * Máy khuấy đông tự 0.75kW × 2 máy * Máy khuấy keo tụ 0.75kW × 1 máy * Lan can, sàn thao tác× 1bộ * Thiết bị tạo vi bọt: D350xH1500mm x 1 bộ | D25: Máy | E25: 1 | I25: =H25+F25+G25 -> 0 | J25: =I25*E25 -> 0
B26: Thiết bị khống chế pH | C26: -Hình thức：công nghệ dùng trên dưới 2 tiếp điểm - Hình thức điều khiển： Hi / Lo。 - Phạm vi ： 0.00~14.00 pH - Phụ kiện: Bảo vệ sensor bằng PTFE, holder có định sensor và tủ đặt controller - Xuất xứ: Supmea - Trung Quốc | D26: Bộ | E26: 1 | I26: =H26+F26+G26 -> 0 | J26: =I26*E26 -> 0
B27: Bơm định lượng NaOH | C27: - Kiểu: Bơm màng; - Lưu lượng: 141.3 L/h (max); - Phạm vi điều chỉnh 0-10; - Cột áp: H = 5 bar; - Nguồn điện: 90W/3 pha/380V/ 50Hz; - Vật liệu: đầu bơm PVC - Xuất xứ: Nikkiso - Đài Loan | D27: Cái | E27: 2 | I27: =H27+F27+G27 -> 0 | J27: =I27*E27 -> 0
B28: Bơm định lượng PAC | C28: - Kiểu: Bơm màng; - Lưu lượng: 141.3 L/h (max); - Phạm vi điều chỉnh 0-10; - Cột áp: H = 5 bar; - Nguồn điện: 90W/3 pha/380V/ 50Hz; - Vật liệu: đầu bơm PVC - Xuất xứ: Nikkiso - Đài Loan | D28: Cái | E28: 2 | I28: =H28+F28+G28 -> 0 | J28: =I28*E28 -> 0
B29: Bơm định lượng PAM | C29: - Kiểu: Bơm màng; - Lưu lượng: 141.3 L/h (max); - Phạm vi điều chỉnh 0-10; - Cột áp: H = 5 bar; - Nguồn điện: 90W/3 pha/380V/ 50Hz; - Vật liệu: đầu bơm PVC - Xuất xứ: Nikkiso - Đài Loan | D29: Cái | E29: 2 | I29: =H29+F29+G29 -> 0 | J29: =I29*E29 -> 0
A30: 4 | B30: Bể kỵ khí
B31: Máy khuấy chìm | C31: -Máy khuấy chìm bể thiếu khí - Hình thức：Máy khuấy chìm (có nắp bảo vệ) - Quy cách：1.5Kw*960rpm*6P - Chất liệu：SUS304 - Xuất xứ: GSD - Đài Loan | D31: Cái | E31: 2 | I31: =H31+F31+G31 -> 0 | J31: =I31*E31 -> 0
B32: Thanh dẫn hướng & nối nhanh | C32: - Vật liệu: SUS304; - Thanh dẫn hướng giúp lắp và tháo máy khuấy chìm, định hướng dòng chảy; - Hãng: I-GREEN/ Xuất xứ: Việt Nam; | D32: Cái | E32: 2 | I32: =H32+F32+G32 -> 0 | J32: =I32*E32 -> 0
B33: Giá thể sinh học dạng sợi | C33: - Vật liệu: PP/nylon. - Diện tích tiếp xúc cao: 5600 - 6500 m2/m3 - 1m3 tương đương 100m dài - Xuất xứ: Qijing - Trung Quốc | D33: m | E33: 6750 | I33: =H33+F33+G33 -> 0 | J33: =I33*E33 -> 0
B34: Khung giá thể | C34: - Vật liệu: SUS304 - Xuất xứ: Việt Nam | D34: Bộ | E34: 1 | I34: =H34+F34+G34 -> 0 | J34: =I34*E34 -> 0
A35: 5 | B35: Bể thiếu khí
B36: Máy khuấy chìm | C36: -Máy khuấy chìm bể thiếu khí - Hình thức：Máy khuấy chìm (có nắp bảo vệ) - Quy cách：0.85Kw*740rpm - Chất liệu：SUS304 - Xuất xứ: GSD - Đài Loan | D36: Cái | E36: 2 | I36: =H36+F36+G36 -> 0 | J36: =I36*E36 -> 0
B37: Thanh dẫn hướng & nối nhanh | C37: - Vật liệu: SUS304; - Thanh dẫn hướng giúp lắp và tháo máy khuấy chìm, định hướng dòng chảy; - Hãng: I-GREEN/ Xuất xứ: Việt Nam; | D37: Cái | E37: 2 | I37: =H37+F37+G37 -> 0 | J37: =I37*E37 -> 0
B38: Bơm định lượng dinh dưỡng | C38: - Kiểu: Bơm màng; - Lưu lượng: 141.3 L/h (max); - Phạm vi điều chỉnh 0-10; - Cột áp: H = 5 bar; - Nguồn điện: 90W/3 pha/380V/ 50Hz; - Vật liệu: đầu bơm PVC - Xuất xứ: Nikkiso - Đài Loan | D38: Cái | E38: 2 | I38: =H38+F38+G38 -> 0 | J38: =I38*E38 -> 0
B39: Giá thể sinh học dạng sợi | C39: - Vật liệu: PP/nylon. - Diện tích tiếp xúc cao: 5600 - 6500 m2/m3 - 1m3 tương đương 100m dài - Xuất xứ: Qijing - Trung Quốc | D39: m | E39: 3600 | I39: =H39+F39+G39 -> 0 | J39: =I39*E39 -> 0
B40: Khung giá thể | C40: - Vật liệu: SUS304 - Xuất xứ: Việt Nam | D40: Bộ | E40: 1 | I40: =H40+F40+G40 -> 0 | J40: =I40*E40 -> 0
A41: 6 | B41: Bể hiếu khí
B42: Máy thổi khí đặt cạn (bao gồm phụ kiện) | C42: - Lưu lượng Q = 7.5 m3/phút; - Cột áp H = 3.0 mH2O; - Công suất P = 7.5 kW/50Hz; - Phụ kiện đầy đủ: lọc gió, giảm chấn, khớp nối mềm,... - Xuất xứ: Longtech - Đài Loan; | D42: Cái | E42: 2 | I42: =H42+F42+G42 -> 0 | J42: =I42*E42 -> 0
B43: Đĩa phân phối khí mịn | C43: - Lưu lượng Q=2-5 m3/h; - Kích thước D=270 mm; - Vật liệu : màng EPDM, khung PP; - Xuất xứ: Jaeger - Đức | D43: Cái | E43: 56 | I43: =H43+F43+G43 -> 0 | J43: =I43*E43 -> 0
B44: Bơm nội tuần hoàn | C44: - Loại: bơm chìm; - Lưu lượng: Q= 10 m3/h; - Cột áp: H= 12 mH2O; - Công suất: 0.75kW/ 3phase/ 380V/ 50Hz; - Xuất xứ: Kaiquan - Trung Quốc; | D44: Cái | E44: 2 | I44: =H44+F44+G44 -> 0 | J44: =I44*E44 -> 0
B45: Khớp nối nhanh | C45: - Vật liệu: khớp nối bằng gang, thanh dẫn hướng SUS304; - Khớp nối nhanh tùy chọn giúp lắp và tháo bơm chìm dễ dàng; - Xuất xứ: Kaiquan - Trung Quốc; | D45: Cái | E45: 2 | I45: =H45+F45+G45 -> 0 | J45: =I45*E45 -> 0
B46: Giá thể sinh học dạng sợi | C46: - Vật liệu: PP/nylon. - Diện tích tiếp xúc cao: 5600 - 6500 m2/m3 - 1m3 tương đương 100m dài - Xuất xứ: Qijing - Trung Quốc | D46: m | E46: 3750 | I46: =H46+F46+G46 -> 0 | J46: =I46*E46 -> 0
B47: Khung giá thể | C47: - Vật liệu: SUS304 - Xuất xứ: Việt Nam | D47: Bộ | E47: 1 | I47: =H47+F47+G47 -> 0 | J47: =I47*E47 -> 0
A48: 7 | B48: Bể lắng sinh học
B49: Ống phân phối trung tâm | C49: - Hình dạng: thân trụ, miệng loe hình côn; - Kích thước: DxH = 800x1500 mm; - Vật liệu: SUS304; - Chiều dày: 2 mm - Xuất xứ: I-GREEN - Việt Nam; | D49: Cái | E49: 1 | I49: =H49+F49+G49 -> 0 | J49: =I49*E49 -> 0
B50: Vách chắn bọt và máng thu nước | C50: - Kích thước tiết diện ngang điển hình: H = 250mm x L=16.4m bao quanh miệng bể lắng (hoặc tương đương theo thiết kế thi công).; - Vật liệu: SUS304. - Xuất xứ: I-GREEN - Việt Nam; | D50: Bộ | E50: 1 | I50: =H50+F50+G50 -> 0 | J50: =I50*E50 -> 0
B51: Thiết bị thu váng nổi | C51: - Hình thức: Khí nâng, khống áp bằng tay - Quy cách：2” - Vật liệu ：PVC | D51: Cái | E51: 2 | I51: =H51+F51+G51 -> 0 | J51: =I51*E51 -> 0
B52: Cánh gạt bùn | C52: - Vật liệu: SUS304 (+ dao gạt bằng cao su/PU cào trên mặt bêtông) - Khung đỡ và tay đòn với toàn bộ đường kính hố thu bùn, Kích thước: D4.5 m (tương đương đường kính hố thu bùn bể lắng) - Xuất xứ: I-GREEN - VN; | D52: Cái | E52: 1 | I52: =H52+F52+G52 -> 0 | J52: =I52*E52 -> 0
B53: Động cơ giảm tốc cánh gạt bùn | C53: - Kiểu: máy khuấy cạn, lắp mặt bích; - Tỷ số truyền: 1/7000 - Tốc độ vòng quay: 0.2 vòng/phút; - Trục khuấy: SUS304 (I-GREEN thiết kế & chế tạo); - Nguồn điện: 0.75kW/3f/380V; - Xuất xứ: Tunglee - Đài Loan; | D53: Cái Ea | E53: 1 | I53: =H53+F53+G53 -> 0 | J53: =I53*E53 -> 0
A54: 8 | B54: Bể bơm bùn
B55: Bơm bùn | C55: - Loại: bơm chìm; - Lưu lượng: Q= 10 m3/h; - Cột áp: H= 12 mH2O; - Công suất: 0.75kW/ 3phase/ 380V/ 50Hz; - Xuất xứ: Kaiquan - Trung Quốc; | D55: Cái | E55: 2 | I55: =H55+F55 -> 0 | J55: =I55*E55 -> 0
B56: Khớp nối nhanh | C56: - Vật liệu: khớp nối bằng gang, thanh dẫn hướng SUS304; - Khớp nối nhanh tùy chọn giúp lắp và tháo bơm chìm dễ dàng; - Xuất xứ: Kaiquan - Trung Quốc; | D56: Cái | E56: 2 | I56: =H56+F56 -> 0 | J56: =I56*E56 -> 0
A57: 8 | B57: Bể điều chỉnh pH
B58: Máy khuấy phản ứng | C58: - Hình thức：Máy khuấy dạng mái chèo phẳng 3 lưỡi - Quy cách ：Động cơ giảm tốc 1.5kW*75rpm - Chất liệu: SUS-304 phía dưới khớp nối - Phụ kiện lắp đặt: Khung đỡ động cơ, khớp xích, bạc đạn ở phía trên, chống tâm SUS304+PTFE phía dưới bể - Xuất xứ: Tunglee-Đài Loan | D58: Cái | E58: 1 | I58: =H58+F58+G58 -> 0 | J58: =I58*E58 -> 0
B59: Thiết bị khống chế pH | C59: -Hình thức：công nghệ dùng trên dưới 2 tiếp điểm - Hình thức điều khiển： Hi / Lo。 - Phạm vi ： 0.00~14.00 pH - Phụ kiện: Bảo vệ sensor bằng PTFE, holder có định sensor và tủ đặt controller - Xuất xứ: Supmea - Trung Quốc | D59: Bộ | E59: 1 | I59: =H59+F59+G59 -> 0 | J59: =I59*E59 -> 0
B60: Bơm định lượng NaOH | C60: - Kiểu: Bơm màng; - Lưu lượng: 141.3 L/h (max); - Phạm vi điều chỉnh 0-10; - Cột áp: H = 5 bar; - Nguồn điện: 90W/3 pha/380V/ 50Hz; - Vật liệu: đầu bơm PVC - Xuất xứ: Nikkiso - Đài Loan | D60: Cái | E60: 2 | I60: =H60+F60+G60 -> 0 | J60: =I60*E60 -> 0
A61: 9 | B61: Bể trộn nhanh
B62: Máy khuấy phản ứng | C62: - Hình thức：Máy khuấy dạng mái chèo phẳng 3 lưỡi - Quy cách ：Động cơ giảm tốc 1.5kW*75rpm - Chất liệu: SUS-304 phía dưới khớp nối - Phụ kiện lắp đặt: Khung đỡ động cơ, khớp xích, bạc đạn ở phía trên, chống tâm SUS304+PTFE phía dưới bể - Xuất xứ: Tunglee-Đài Loan | D62: Cái | E62: 1 | I62: =H62+F62+G62 -> 0 | J62: =I62*E62 -> 0
B63: Bơm định lượng PAC | C63: - Kiểu: Bơm màng; - Lưu lượng: 141.3 L/h (max); - Phạm vi điều chỉnh 0-10; - Cột áp: H = 5 bar; - Nguồn điện: 90W/3 pha/380V/ 50Hz; - Vật liệu: đầu bơm PVC - Xuất xứ: Nikkiso - Đài Loan | D63: Cái | E63: 2 | I63: =H63+F63+G63 -> 0 | J63: =I63*E63 -> 0
A64: 10 | B64: Bể trộn chậm
B65: Máy khuấy phản ứng | C65: - Hình thức：Máy khuấy dạng mái chèo phẳng 3 lưỡi - Quy cách ：Động cơ giảm tốc 1.5kW*30rpm - Chất liệu: SUS-304 phía dưới khớp nối - Phụ kiện lắp đặt: Khung đỡ động cơ, khớp xích, bạc đạn ở phía trên, chống tâm SUS304+PTFE phía dưới bể - Xuất xứ: Tunglee-Đài Loan | D65: Cái | E65: 1 | I65: =H65+F65 -> 0 | J65: =I65*E65 -> 0
B66: Bơm định lượng PAM | C66: - Kiểu: Bơm màng; - Lưu lượng: 141.3 L/h (max); - Phạm vi điều chỉnh 0-10; - Cột áp: H = 5 bar; - Nguồn điện: 90W/3 pha/380V/ 50Hz; - Vật liệu: đầu bơm PVC - Xuất xứ: Nikkiso - Đài Loan | D66: Cái | E66: 2 | I66: =H66+F66 -> 0 | J66: =I66*E66 -> 0
A67: 11 | B67: Bể lắng hoá lý
B68: Ống phân phối trung tâm | C68: - Hình dạng: thân trụ, miệng loe hình côn; - Kích thước: DxH = 800x1500 mm; - Vật liệu: SUS304; - Chiều dày: 2 mm - Xuất xứ: I-GREEN - Việt Nam; | D68: Cái | E68: 1 | I68: =H68+F68+G68 -> 0 | J68: =I68*E68 -> 0
B69: Vách chắn bọt và máng thu nước | C69: - Kích thước tiết diện ngang điển hình: H = 250mm x L=16.4m bao quanh miệng bể lắng (hoặc tương đương theo thiết kế thi công).; - Vật liệu: SUS304. - Xuất xứ: I-GREEN - Việt Nam; | D69: Bộ | E69: 1 | I69: =H69+F69+G69 -> 0 | J69: =I69*E69 -> 0
B70: Cánh gạt bùn | C70: - Vật liệu: SUS304 (+ dao gạt bằng cao su/PU cào trên mặt bêtông) - Khung đỡ và tay đòn với toàn bộ đường kính hố thu bùn, Kích thước: D4 m (tương đương đường kính hố thu bùn bể lắng) - Xuất xứ: I-GREEN - VN; | D70: Cái | E70: 1 | I70: =H70+F70+G70 -> 0 | J70: =I70*E70 -> 0
B71: Động cơ giảm tốc cánh gạt bùn | C71: - Kiểu: máy khuấy cạn, lắp mặt bích; - Tỷ số truyền: 1/7000 - Tốc độ vòng quay: 0.2 vòng/phút; - Trục khuấy: SUS304 (I-GREEN thiết kế & chế tạo); - Nguồn điện: 0.75kW/3f/380V; - Xuất xứ: Tunglee - Đài Loan; | D71: Cái Ea | E71: 1 | I71: =H71+F71+G71 -> 0 | J71: =I71*E71 -> 0
B72: Bơm thu bùn | C72: - Hình thức： Bơm màng khí nén - Quy cách：0.17m3/min*8.4 bar (max)*1.5'' - Chất liệu ：PP + Teflon - Xuất xứ: GODO - Trung Quốc | D72: Cái | E72: 2 | I72: =H72+F72+G72 -> 0 | J72: =I72*E72 -> 0
A73: 12 | B73: Bể khử trùng
B74: Bơm định lượng NaOCl | C74: - Kiểu: Bơm màng; - Lưu lượng: 141.3 L/h (max); - Phạm vi điều chỉnh 0-10; - Cột áp: H = 5 bar; - Nguồn điện: 90W/3 pha/380V/ 50Hz; - Vật liệu: đầu bơm PVC - Xuất xứ: Nikkiso - Đài Loan | D74: Cái | E74: 2 | I74: =H74+F74+G74 -> 0 | J74: =I74*E74 -> 0
B75: Đồng hồ đo lưu lượng nước thải đầu ra | C75: - Lưu lượng kế điện từ - Hình thức: Thiết bị đo lưu lượng nước thải điện từ, lắp đặt trên đường ống, nối mặt bích - Quy cách：DN65 - Tín hiệu ra : 4-20mA/ Dữ liệu truyền đến tủ điện điều khiển - Chất liệu：FC+PTFE - Xuất xứ: Supmea - Trung Quốc | D75: Cái | E75: 1 | I75: =H75+F75+G75 -> 0 | J75: =I75*E75 -> 0
B76: Cảm biến mức nước | C76: - Cảm biến đo mức nước trong bể điều hòa nước thải để điều khiển 2 bơm chìm, ON mức nước cao & OFF mức nước thấp - Xuất xứ: HCP - Trung Quốc | D76: Cái | E76: 1 | I76: =H76+F76+G76 -> 0 | J76: =I76*E76 -> 0
B77: Bơm chìm nước thải bể thu gom | C77: - Loại: bơm chìm; - Lưu lượng: Q= 10 m3/h; - Cột áp: H= 16 mH2O; - Công suất: 1.5kW/ 3phase/ 380V/ 50Hz; - Xuất xứ: Kaiquan - Trung Quốc; | D77: Cái | E77: 2 | I77: =H77+F77+G77 -> 0 | J77: =I77*E77 -> 0
B78: Khớp nối nhanh | C78: - Vật liệu: khớp nối bằng gang, thanh dẫn hướng SUS304; - Khớp nối nhanh tùy chọn giúp lắp và tháo bơm chìm dễ dàng; - Xuất xứ: Kaiquan - Trung Quốc; | D78: Cái | E78: 2 | I78: =H78+F78+G78 -> 0 | J78: =I78*E78 -> 0
A79: 13 | B79: Bể chứa bùn
A80: 14 | B80: Máy ép bùn khung bản
B81: Bơm nạp bùn | C81: - Hình thức： Bơm màng khí nén - Quy cách：0.17m3/min*8.4 bar (max)*1.5'' - Chất liệu ：PP + Teflon - Xuất xứ: GODO - Trung Quốc | D81: Cái | E81: 2 | I81: =H81+F81+G81 -> 0 | J81: =I81*E81 -> 0
B82: Máy nén khí | C82: - Hình thức： Máy nén khí dây đai - Quy cách：360L/min*8bar (max)*230L - Công suất: 4HP/380V/50Hz - Xuất xứ: GODO - Trung Quốc | D82: Cái | E82: 1 | I82: =H82+F82+G82 -> 0 | J82: =I82*E82 -> 0
B83: Máy ép bùn | C83: - Hình thức: Máy ép bùn khung bản - Thể tích buồng lọc ép： ~270L/mẻ - Diện tích lọc: 18m2 - Độ ẩm bùn sau ép: ≤70 % - Công suất điện: 2.2kW - Kích thước tấm lọc: 630 x 630 mm (Độ dày tấm lọc: 50mm) - Số lượng tấm lọc: 30tấm - Kích thước tạm thời bên ngoài: L x W x H (mm) = 3034x920x1704mm (hoặc kích thước tương đương ) - Phương pháp dỡ bùn: Dỡ bùn tự động - Thiết bị phụ trợ： * Tủ điện tự động: 1 bộ * Hệ thống điều khiển điện-thủy lực: 1 bộ - Xuất xứ: Mega - Việt Nam | D83: Máy | E83: 1 | I83: =H83+F83+G83 -> 0 | J83: =I83*E83 -> 0
B84: Thùng chứa bùn & phễu xả bánh bùn | C84: Vật liệu: SUS304 | D84: Bộ | E84: 1 | I84: =H84+F84+G84 -> 0 | J84: =I84*E84 -> 0
B85: Giá đỡ máy ép bùn, sàn thao tác | C85: Vật liệu: thép mạ kẽm | D85: Bộ | E85: 1 | I85: =H85+F85+G85 -> 0 | J85: =I85*E85 -> 0
A86: 15 | B86: Hệ thống cấp, pha hóa chất
B87: Bồn chứa hóa chất | C87: -Vật liệu: PE, chịu ăn mòn hóa chất; - Thể tích: 1000 L; -Xuất xứ: Tân Á - Vietnam - Material: PE, chemical corrosion resitance; - Volume: 1000 L - Origin: Tân Á - Vietnam | D87: Cái/ Ea | E87: 5 | I87: =H87+F87+G87 -> 0 | J87: =I87*E87 -> 0
B88: Động cơ khuấy pha hóa chất (kèm cánh khuấy) | C88: - Kiểu: máy khuấy cạn, lắp mặt bích. - Tốc độ trục quay: 50 - 70 rpm. - Trục khuấy: SUS304 (I-GREEN thiết kế & chế tạo). - Nguồn điện: 0.4kW/380V/3phase/50Hz - Xuất xứ: Tunglee - Đài Loan; | D88: Cái/ Ea | E88: 4 | I88: =H88+F88+G88 -> 0 | J88: =I88*E88 -> 0
A89: B | B89: Hệ thống đường ống công nghệ | J89: =SUM(J90:J91) -> 0
B90: Hệ thống đường ống nước, bùn, khí hoặc hóa chất | C90: - Hệ thống đường ống nước, bùn, khí hoặc hóa chất ngập nước hoặc được che khuất: PVC/PPR; - Các đường ống dẫn khí có nhiệt độ cao được thi công bằng vật liệu thép mạ kẽm; + Xuất xứ ống: Hòa Phát, Tiền Phong hoặc tương đương - Việt Nam - Phụ kiện: Mặt bích, van bướm, van một chiều, khớp nối mềm; + Xuất xứ phụ kiện: Shinyi, Cangzhou, Dyben hoặc tương đương - Việt Nam, Trung Quốc, Hàn Quốc,... | D90: Hệ | E90: 1 | I90: =H90+F90+G90 -> 0 | J90: =I90*E90 -> 0
B91: Hệ thống khung & giá đỡ, treo ống | C91: - Vật liệu thép mạ kẽm hoặc SUS304 đối với trường hợp thi công dưới nước hoặc chịu ăn mòn - Xuất xứ: Sơn Hà, Hòa Phát, Gia Anh - Việt Nam | D91: Hệ | E91: 1 | I91: =H91+F91+G91 -> 0 | J91: =I91*E91 -> 0
A92: C | B92: Hệ thống đường điện | J92: =SUM(J93:J94) -> 0
B93: Cáp điện và phụ kiện | C93: - Các loại dây cáp nhiều cỡ & số lõi tùy thuộc từng động cơ - Quy cách vật liệu lõi đồng, cách điện, vỏ bọc HDPE hoặc PVC - Phụ kiện kèm theo: ống luồn dây, máng cáp (thép sơn tĩnh điện hoặc mạ kẽm),….. - Xuất xứ: Cadisun. Trần Phú, ... - Việt Nam | D93: Hệ | E93: 1 | I93: =H93+F93+G93 -> 0 | J93: =I93*E93 -> 0
B94: Tủ điện điều khiển | C94: - Vỏ tủ chế tạo bằng thép sơn tĩnh điện, 2 lớp cửa, kiểu đặt đứng trên bệ đỡ - Thiết kế đầy đủ cấp bảo vệ cho các thiết bị & động cơ - Các linh kiện chính hãng: MCCB,MB,MC và các linh kiện khác (đèn báo, nút bấm,....): Chint, Shilin, IDEC, Huyndai, Siemens, Schneider... - Xuất xứ: I-GREEN - Việt Nam (thiết kế & lắp đặt) | D94: Bộ | E94: 1 | I94: =H94+F94+G94 -> 0 | J94: =I94*E94 -> 0
A95: E | B95: Chi phí khác | J95: =SUM(J96:J99) -> 0
B96: Chi phí vận chuyển | C96: - Vận chuyển vật tư, thiết bị tới công trường | D96: Hệ | E96: 1 | I96: =H96+F96+G96 -> 0 | J96: =I96*E96 -> 0
B97: Vận hành thử nghiệm | C97: - Chi phí vận hành chạy thử kể từ khi hoàn thành lắp đặt có thể tiếp nhận nước thải vào trạm xử lý đến khi hệ chất lượng nước thải đầu ra đạt yêu cầu. | D97: Hệ | E97: 1 | I97: =H97+F97+G97 -> 0 | J97: =I97*E97 -> 0
B98: Chi phí lấy mẫu và phân tích nước thải | C98: - Chi phí lấy mẫu phân tích đánh giá chất lượng nước sau xử lý để phục vụ vận hành & nghiệm thu | D98: Hệ | E98: 1 | I98: =H98+F98+G98 -> 0 | J98: =I98*E98 -> 0
B99: Bùn hoạt tính và Hóa chất sử dụng trong giai đoạn vận hành thử nghiệm | C99: - Chi phí hóa chất ( dinh dưỡng, hóa chất khử trùng) và bùn hoạt tính trong thời gian vận hành chạy thử ban đầu (dự kiến 1-2 tháng) | D99: Hệ | E99: 1 | I99: =H99+F99+G99 -> 0 | J99: =I99*E99 -> 0

Sheet C3.Hệ Thống PCCC 
A1: BILL OF QUANTITY
A2: ='C4.Hệ Thống Điện & Điện Nhẹ '!A2:K2 -> PROJECT NAME / TÊN DỰ ÁN :
A3: C3.FIRE FIGHTIGN SYSTEM/ HỆ THỐNG PCCC
A4: NO | B4: DESCRIPTION MÔ TẢ | C4: STANDARD TIÊU CHUẨN | D4: UNIT ĐƠN VỊ | E4: Q'TY KHỐI LƯỢNG | F4: UNIT PRICE / ĐƠN GIÁ (VNĐ) | J4: AMOUNT / THÀNH TIỀN (VNĐ) | K4: REMARK GHI CHÚ
F5: MATERIAL / VẬT LIỆU | G5: LABOUR / NHÂN CÔNG | H5: EQUIPMENT / THIẾT BỊ | I5: UNIT PRICE / TỔNG ĐƠN GIÁ
A6: C3 | B6: FIRE FIGHTIGN SYSTEM HỆ THỐNG PCCC
B7: [ TOTAL ] | J7: =SUM(J8:J13) -> 0
A8: I | B8: =+B15 -> FIRE ALARM SYSTEM HỆ THỐNG BÁO CHÁY | J8: =J16 -> 0
A9: II | B9: =+B111 -> INDOOR FIRE FIGHTING WATER SUPPLY SYSTEM HỆ THỐNG CẤP NƯỚC CHỮA CHÁY TRONG NHÀ | J9: =J112 -> 0
A10: III | B10: =+B272 -> FIRE PUMPING STATION SYSTEM HỆ THỐNG TRẠM BƠM CHỮA CHÁY | J10: =J273 -> 0
A11: IV | B11: =+B317 -> EMERGENCE LIGHTING SYSTEM + EXIT HỆ THỐNG ĐÈN CHIẾU SÁNG SỰ CỐ + EXIT | J11: =J318 -> 0
A12: V | B12: =+B375 -> SMOKE EXTRACTION AND COMPENSATION AIR SUPPLY SYSTEM HỆ THỐNG HÚT KHÓI, CẤP KHÍ BÙ | J12: =J376 -> 0
A13: VI | B13: =+B458 -> OTHER FEE CHI PHÍ KHÁC | J13: =J459 -> 0
A15: I | B15: FIRE ALARM SYSTEM HỆ THỐNG BÁO CHÁY
B16: [ Sub - total ] | J16: =SUM(J17:J109) -> 0
B17: Tổng thể
B18: Tủ trung tâm báo cháy 3 loop | D18: Bộ | E18: 1 | I18: =F18+G18+H18 -> 0 | J18: =I18*E18 -> 0 | K18: TC Fire/Horing
B19: Tủ nguồn phụ | D19: Bộ | E19: 1 | I19: =F19+G19+H19 -> 0 | J19: =I19*E19 -> 0 | K19: TC Fire/Horing
B20: Đầu báo khói địa chỉ dưới trần | D20: Cái | E20: 1 | I20: =F20+G20+H20 -> 0 | J20: =I20*E20 -> 0 | K20: TC Fire/Horing
B21: Ống HDPE 50/40 | D21: Mét | E21: 1000 | I21: =F21+G21+H21 -> 0 | J21: =I21*E21 -> 0 | K21: Việt Nam
B22: Vật tư phụ (ốc, vít, tắc kê, băng keo điện, dây rút, …) | D22: Lô | E22: 1 | I22: =F22+G22+H22 -> 0 | J22: =I22*E22 -> 0 | K22: Việt Nam
B23: Nhà xưởng + văn phòng tầng 1 | I23: =F23+G23+H23 -> 0 | J23: =I23*E23 -> 0
B24: Đầu báo khói địa chỉ dưới trần | D24: Cái | E24: 35 | I24: =F24+G24+H24 -> 0 | J24: =I24*E24 -> 0 | K24: TC Fire/Horing
B25: Đầu báo khói địa chỉ trên trần | D25: Cái | E25: 20 | I25: =F25+G25+H25 -> 0 | J25: =I25*E25 -> 0 | K25: TC Fire/Horing
B26: Chuông đèn kết hợp địa chỉ | D26: Cái | E26: 3 | I26: =F26+G26+H26 -> 0 | J26: =I26*E26 -> 0 | K26: TC Fire/Horing
B27: Nút nhấn địa chỉ | D27: Cái | E27: 3 | I27: =F27+G27+H27 -> 0 | J27: =I27*E27 -> 0 | K27: TC Fire/Horing
B28: Đèn báo có chữ Fire | D28: Cái | E28: 2 | I28: =F28+G28+H28 -> 0 | J28: =I28*E28 -> 0 | K28: TC Fire/Horing
B29: Module giám sát | D29: Cái | E29: 3 | I29: =F29+G29+H29 -> 0 | J29: =I29*E29 -> 0 | K29: TC Fire/Horing
B30: Module điều khiển chuông | D30: Cái | E30: 1 | I30: =F30+G30+H30 -> 0 | J30: =I30*E30 -> 0 | K30: TC Fire/Horing
B31: Dây tín hiệu báo cháy 2Cx1,5mm2 | D31: Mét | E31: 400 | I31: =F31+G31+H31 -> 0 | J31: =I31*E31 -> 0 | K31: SPL
B32: Dây cấp nguồn chống cháy 2Cx1,5mm2 | D32: Mét | E32: 200 | I32: =F32+G32+H32 -> 0 | J32: =I32*E32 -> 0 | K32: SPL
B33: Ống luồn dây dẫn PVC D20 | D33: Mét | E33: 600 | I33: =F33+G33+H33 -> 0 | J33: =I33*E33 -> 0 | K33: HDV
B34: Phụ kiện ống (nối trơn, kẹp C, nói răng, …) | D34: Lô | E34: 1 | I34: =F34+G34+H34 -> 0 | J34: =I34*E34 -> 0 | K34: HDV
B35: Vật tư phụ (ốc, vít, tắc kê, băng keo điện, dây rút, …) | D35: Lô | E35: 1 | I35: =F35+G35+H35 -> 0 | J35: =I35*E35 -> 0 | K35: Việt Nam
B36: Nhà xưởng + văn phòng tầng 2
B37: Đầu báo khói địa chỉ dưới trần | D37: Cái | E37: 186 | I37: =F37+G37+H37 -> 0 | J37: =I37*E37 -> 0 | K37: TC Fire/Horing
B38: Đầu báo khói địa chỉ trên trần | D38: Cái | E38: 9 | I38: =F38+G38+H38 -> 0 | J38: =I38*E38 -> 0 | K38: TC Fire/Horing
B39: Đầu báo nhiệt địa chỉ | D39: Cái | E39: 24 | I39: =F39+G39+H39 -> 0 | J39: =I39*E39 -> 0 | K39: TC Fire/Horing
B40: Đầu báo khói kiểu hút | D40: Cái | E40: 2 | I40: =F40+G40+H40 -> 0 | J40: =I40*E40 -> 0 | K40: TC Fire/Horing
B41: Đầu hút của đầu báo khói kiểu hút | D41: Cái | E41: 16 | I41: =F41+G41+H41 -> 0 | J41: =I41*E41 -> 0 | K41: TC Fire/Horing
B42: Bẫy thu nước loại bỏ nước | D42: Cái | E42: 4 | I42: =F42+G42+H42 -> 0 | J42: =I42*E42 -> 0 | K42: TC Fire/Horing
B43: Thiết bị lọc bụi trong không khí cho đầu dò | D43: Cái | E43: 4 | I43: =F43+G43+H43 -> 0 | J43: =I43*E43 -> 0 | K43: TC Fire/Horing
B44: Ống lấy mẫu PVC D20 | D44: Mét | E44: 130 | I44: =F44+G44+H44 -> 0 | J44: =I44*E44 -> 0 | K44: TC Fire/Horing
B45: Chuông đèn kết hợp địa chỉ | D45: Cái | E45: 37 | I45: =F45+G45+H45 -> 0 | J45: =I45*E45 -> 0 | K45: TC Fire/Horing
B46: Nút nhấn địa chỉ | D46: Cái | E46: 37 | I46: =F46+G46+H46 -> 0 | J46: =I46*E46 -> 0 | K46: TC Fire/Horing
B47: Đèn báo có chữ Fire | D47: Cái | E47: 14 | I47: =F47+G47+H47 -> 0 | J47: =I47*E47 -> 0 | K47: TC Fire/Horing
B48: Module giám sát | D48: Cái | E48: 13 | I48: =F48+G48+H48 -> 0 | J48: =I48*E48 -> 0 | K48: TC Fire/Horing
... B54: Vật tư phụ (ốc, vít, tắc kê, băng keo điện, dây rút, …) | D54: Lô | E54: 1 | I54: =F54+G54+H54 -> 0 | J54: =I54*E54 -> 0 | K54: Việt Nam
B55: Áp trần nhà xưởng
B56: Đầu báo khói địa chỉ dưới trần | D56: Cái | E56: 12 | I56: =F56+G56+H56 -> 0 | J56: =I56*E56 -> 0 | K56: TC Fire
B57: Đầu báo khói địa chỉ trên trần | D57: Cái | E57: 14 | I57: =F57+G57+H57 -> 0 | J57: =I57*E57 -> 0 | K57: TC Fire
B58: Dây tín hiệu báo cháy 2Cx1,5mm2 | D58: Mét | E58: 150 | I58: =F58+G58+H58 -> 0 | J58: =I58*E58 -> 0 | K58: SPL
B59: Ống luồn dây dẫn PVC D20 | D59: Mét | E59: 150 | I59: =F59+G59+H59 -> 0 | J59: =I59*E59 -> 0 | K59: HDV
B60: Phụ kiện ống (nối trơn, kẹp C, nói răng, …) | D60: Lô | E60: 1 | I60: =F60+G60+H60 -> 0 | J60: =I60*E60 -> 0 | K60: HDV
B61: Vật tư phụ (ốc, vít, tắc kê, băng keo điện, dây rút, …) | D61: Lô | E61: 1 | I61: =F61+G61+H61 -> 0 | J61: =I61*E61 -> 0 | K61: Việt Nam
B62: Nhà Nghỉ giữa ca + nhà rác + nhà điện
B63: Đầu báo khói địa chỉ dưới trần | D63: Cái | E63: 7 | I63: =F63+G63+H63 -> 0 | J63: =I63*E63 -> 0 | K63: TC Fire/Horing
B64: Đầu báo nhiệt địa chỉ | D64: Cái | E64: 4 | I64: =F64+G64+H64 -> 0 | J64: =I64*E64 -> 0 | K64: TC Fire/Horing
B65: Chuông đèn kết hợp địa chỉ | D65: Cái | E65: 2 | I65: =F65+G65+H65 -> 0 | J65: =I65*E65 -> 0 | K65: TC Fire/Horing
B66: Nút nhấn địa chỉ | D66: Cái | E66: 2 | I66: =F66+G66+H66 -> 0 | J66: =I66*E66 -> 0 | K66: TC Fire/Horing
B67: Đèn báo có chữ Fire | D67: Cái | E67: 4 | I67: =F67+G67+H67 -> 0 | J67: =I67*E67 -> 0 | K67: TC Fire/Horing
B68: Module giám sát | D68: Cái | E68: 1 | I68: =F68+G68+H68 -> 0 | J68: =I68*E68 -> 0 | K68: TC Fire/Horing
B69: Module điều khiển chuông | D69: Cái | E69: 2 | I69: =F69+G69+H69 -> 0 | J69: =I69*E69 -> 0 | K69: TC Fire/Horing
B70: Dây tín hiệu báo cháy 2Cx1,5mm2 | D70: Mét | E70: 400 | I70: =F70+G70+H70 -> 0 | J70: =I70*E70 -> 0 | K70: SPL
B71: Dây cấp nguồn chống chát 2Cx1,5mm2 | D71: Mét | E71: 300 | I71: =F71+G71+H71 -> 0 | J71: =I71*E71 -> 0 | K71: SPL
B72: Ống luồn dây dẫn PVC D20 | D72: Mét | E72: 700 | I72: =F72+G72+H72 -> 0 | J72: =I72*E72 -> 0 | K72: HDV
B73: Phụ kiện ống (nối trơn, kẹp C, nói răng, …) | D73: Lô | E73: 1 | I73: =F73+G73+H73 -> 0 | J73: =I73*E73 -> 0 | K73: HDV
B74: Vật tư phụ (ốc, vít, tắc kê, băng keo điện, dây rút, …) | D74: Lô | E74: 1 | I74: =F74+G74+H74 -> 0 | J74: =I74*E74 -> 0 | K74: Việt Nam
B75: Nhà bao bì thủy tinh + phòng RO + rang đậu & thổi chai + bảo trì + phụ trợ
B76: Đầu báo khói địa chỉ dưới trần | D76: Cái | E76: 32 | I76: =F76+G76+H76 -> 0 | J76: =I76*E76 -> 0 | K76: TC Fire/Horing
B77: Đầu báo nhiệt địa chỉ | D77: Cái | E77: 15 | I77: =F77+G77+H77 -> 0 | J77: =I77*E77 -> 0 | K77: TC Fire/Horing
B78: Chuông đèn kết hợp địa chỉ | D78: Cái | E78: 10 | I78: =F78+G78+H78 -> 0 | J78: =I78*E78 -> 0 | K78: TC Fire/Horing
B79: Nút nhấn địa chỉ | D79: Cái | E79: 10 | I79: =F79+G79+H79 -> 0 | J79: =I79*E79 -> 0 | K79: TC Fire/Horing
B80: Đèn báo có chữ Fire | D80: Cái | E80: 7 | I80: =F80+G80+H80 -> 0 | J80: =I80*E80 -> 0 | K80: TC Fire/Horing
B81: Module giám sát | D81: Cái | E81: 2 | I81: =F81+G81+H81 -> 0 | J81: =I81*E81 -> 0 | K81: TC Fire/Horing
B82: Module điều khiển chuông | D82: Cái | E82: 1 | I82: =F82+G82+H82 -> 0 | J82: =I82*E82 -> 0 | K82: TC Fire/Horing
B83: Dây tín hiệu báo cháy 2Cx1,5mm2 | D83: Mét | E83: 500 | I83: =F83+G83+H83 -> 0 | J83: =I83*E83 -> 0 | K83: SPL
B84: Dây cấp nguồn chống chát 2Cx1,5mm2 | D84: Mét | E84: 250 | I84: =F84+G84+H84 -> 0 | J84: =I84*E84 -> 0 | K84: SPL
B85: Ống luồn dây dẫn PVC D20 | D85: Mét | E85: 750 | I85: =F85+G85+H85 -> 0 | J85: =I85*E85 -> 0 | K85: HDV
B86: Phụ kiện ống (nối trơn, kẹp C, nói răng, …) | D86: Lô | E86: 1 | I86: =F86+G86+H86 -> 0 | J86: =I86*E86 -> 0 | K86: HDV
B87: Vật tư phụ (ốc, vít, tắc kê, băng keo điện, dây rút, …) | D87: Lô | E87: 1 | I87: =F87+G87+H87 -> 0 | J87: =I87*E87 -> 0 | K87: Việt Nam
B88: Nhà Carton + nhà bao bì nhựa & thổi chai
B89: Đầu báo khói địa chỉ dưới trần | D89: Cái | E89: 32 | I89: =F89+G89+H89 -> 0 | J89: =I89*E89 -> 0 | K89: TC Fire/Horing
B90: Chuông đèn kết hợp địa chỉ | D90: Cái | E90: 9 | I90: =F90+G90+H90 -> 0 | J90: =I90*E90 -> 0 | K90: TC Fire/Horing
B91: Nút nhấn địa chỉ | D91: Cái | E91: 9 | I91: =F91+G91+H91 -> 0 | J91: =I91*E91 -> 0 | K91: TC Fire/Horing
B92: Đèn báo có chữ Fire | D92: Cái | E92: 7 | I92: =F92+G92+H92 -> 0 | J92: =I92*E92 -> 0 | K92: TC Fire/Horing
B93: Module giám sát | D93: Cái | E93: 2 | I93: =F93+G93+H93 -> 0 | J93: =I93*E93 -> 0 | K93: TC Fire/Horing
B94: Module điều khiển chuông | D94: Cái | E94: 1 | I94: =F94+G94+H94 -> 0 | J94: =I94*E94 -> 0 | K94: TC Fire/Horing
B95: Dây tín hiệu báo cháy 2Cx1,5mm2 | D95: Mét | E95: 500 | I95: =F95+G95+H95 -> 0 | J95: =I95*E95 -> 0 | K95: SPL
B96: Dây cấp nguồn chống chát 2Cx1,5mm2 | D96: Mét | E96: 250 | I96: =F96+G96+H96 -> 0 | J96: =I96*E96 -> 0 | K96: SPL
B97: Ống luồn dây dẫn PVC D20 | D97: Mét | E97: 750 | I97: =F97+G97+H97 -> 0 | J97: =I97*E97 -> 0 | K97: HDV
B98: Phụ kiện ống (nối trơn, kẹp C, nói răng, …) | D98: Lô | E98: 1 | I98: =F98+G98+H98 -> 0 | J98: =I98*E98 -> 0 | K98: HDV
B99: Vật tư phụ (ốc, vít, tắc kê, băng keo điện, dây rút, …) | D99: Lô | E99: 1 | I99: =F99+G99+H99 -> 0 | J99: =I99*E99 -> 0 | K99: Việt Nam
B100: Nhà máy khí nén + lò hơi | I100: =F100+G100+H100 -> 0 | J100: =I100*E100 -> 0
B101: Chuông đèn kết hợp địa chỉ | D101: Cái | E101: 4 | I101: =F101+G101+H101 -> 0 | J101: =I101*E101 -> 0 | K101: TC Fire/Horing
B102: Nút nhấn địa chỉ | D102: Cái | E102: 4 | I102: =F102+G102+H102 -> 0 | J102: =I102*E102 -> 0 | K102: TC Fire/Horing
B103: Đèn báo có chữ Fire | D103: Cái | E103: 2 | I103: =F103+G103+H103 -> 0 | J103: =I103*E103 -> 0 | K103: TC Fire/Horing
