Workbook
Name ________________P3: #REF!
Name ________________P3: #REF!
Name ________________PPP3: #REF!
Name ________________PPP3: #REF!
Name ________________PPP33: #REF!
Name ________________PPP33: #REF!
Name ________________ppp34: #REF!
Name ________________ppp34: #REF!
Name ________________ppp3444: #REF!
Name ________________ppp3444: #REF!
Name _______________P3: #REF!
Name _______________P3: #REF!
Name _______________PPP3: #REF!
Name _______________PPP3: #REF!
Name _______________PPP33: #REF!
Name _______________PPP33: #REF!
Name _______________ppp34: #REF!
Name _______________ppp34: #REF!
Name _______________ppp3444: #REF!
Name _______________ppp3444: #REF!
Name ______________P3: #REF!
Name ______________P3: #REF!
Name ______________PPP3: #REF!
Name ______________PPP3: #REF!
Name ______________PPP33: #REF!
Name ______________PPP33: #REF!
Name ______________ppp34: #REF!
Name ______________ppp34: #REF!
Name ______________ppp3444: #REF!
Name ______________ppp3444: #REF!
Name _____________P3: #REF!
Name _____________P3: #REF!
Name _____________PPP3: #REF!
Name _____________PPP3: #REF!
Name _____________PPP33: #REF!
Name _____________PPP33: #REF!
Name _____________ppp34: #REF!
Name _____________ppp34: #REF!
Name _____________ppp3444: #REF!
Name _____________ppp3444: #REF!
Name ____________P3: #REF!
Name ____________P3: #REF!
Name ____________PPP3: #REF!
Name ____________PPP3: #REF!
Name ____________PPP33: #REF!
Name ____________PPP33: #REF!
Name ____________ppp34: #REF!
Name ____________ppp34: #REF!
Name ____________ppp3444: #REF!
Name ____________ppp3444: #REF!
Name ___________dam24: [1]GIAVLIEU!$M$51
Name ___________TVL1: #REF!
Name ___________TVL1: #REF!
Name ___________TVL1: #REF!
Name ___________TVL1: #REF!
Name __________dam24: [1]GIAVLIEU!$M$51
Name __________P3: #REF!
Name __________P3: #REF!
Name __________PPP3: #REF!
Name __________PPP3: #REF!

Sheet 01.BÌA
C5: BẢNG DỰ TOÁN/BILL OF QUANTITY
C8: DỰ ÁN/PROJECT | D8: : | E8: NEW WAREHOUSE/NHÀ KHO
C9: HẠNG MỤC/ITEM | D9: : | E9: CSA WORKS
C10: ĐỊA ĐIỂM/LOCATION | D10: : | E10: VSIP 3, BINH DUONG, VIETNAM
C11: CHỦ ĐẦU TƯ/OWNER | D11: :
C12: NHÀ THẦU/CONTRACTOR | D12: :
C14: NGÀY/DATE: | E14: =TODAY() -> 46301

Sheet Total Amount 
A8: No: 01-2024.NICON
A10: BẢNG DỰ TOÁN/ BILL OF QUANTITY
A12: Project / Dự án : NEW WAREHOUSE/NHÀ KHO
A13: Owner/ Chủ đầu tư :
A14: Location / Địa điểm :
A15: Items / Hạng mục : CIVIL CONSTRUCTION / XÂY DỰNG
A16: Kindly to /Kính gửi :
A17: TỔNG HỢP CHI PHÍ
F19: Currency: VND
A20: PART | B20: NO | C20: DESCRIPTION | E20: AMOUNT | G20: REMARK
A22: CONSTRUCTION | C22: CONSTRUCTION WORKS COST/ CHI PHÍ THI CÔNG XÂY DỰNG | E22: =' COST SUMMARY'!D12 -> 0 | G22: Detail next page
C23: GRAND-TOTAL/ TỔNG CỘNG | E23: =SUM(E22) -> 0
C24: VAT 8%/ THUẾ VAT 8% | E24: =E23*0.08 -> 0
C25: GRAND-TOTAL AFTER TAX VAT/ TỔNG CỘNG VAT | E25: =E23+E24 -> 0
A27: NIPPON ENGINEERING PROCUREMENT AND CONSTRUCTION JSC | E27: NEW INVESTMENT CONSTRUCTION CONSULTANT JOINT STOCK COMPANY
A28: General Director | E28: General Director
E32: VO TRI NGUYEN

Sheet  COST SUMMARY
A1: TỔNG HỢP CHI PHÍ/COST SUMMARY
A2: PROJECT/ DỰ ÁN : NEW WAREHOUSE/NHÀ KHO
A3: ITEM/HẠNG MỤC : CIVIL CONSTRUCTION / XÂY DỰNG
A4: DATE/NGÀY : | C4: =TODAY() -> 46301
D5: Currency: VND
A6: SECTION | B6: No. | C6: DESCRIPTION | E6: REMARK
D7: TOTAL
A8: CHI PHÍ TRỰC TIẾP/DIRECT COST | B8: 1 | C8: BILL No.1: PRELIMINARY & GENERAL REQUIREMENTS/ TIỆN ÍCH VÀ YÊU CẦU CHUNG | D8: ='Bill 1- Premilinary & General'!F5 -> 0 | E8: Detail next page
B9: 2 | C9: BILL No.2: MAIN BUILDING WORKS | D9: ='Bill 2-Main building works'!Q6 -> 0 | E9: Detail next page
B10: 3 | C10: BILL No.3: EXTERNAL WORKS | D10: ='Bill 3-External works'!Q6 -> 0 | E10: Detail next page
C12: TỔNG CỘNG/SUB-TOTAL | D12: =SUBTOTAL(109,D8:D11) -> 0
A13: TỔNG CỘNG CHI PHÍ/GRAND-TOTAL | D13: =D12 -> 0
A14: NOTE: | B14: - | C14: 'V.A.T IS EXCLUDED

Sheet Bill 1- Premilinary & General
A1: PROJECT/ DỰ ÁN : NEW WAREHOUSE/NHÀ KHO
A2: ADDRESS/ĐỊA CHỈ : VSIP 3, BINH DUONG, VIETNAM
A3: BILL No.01 : PRELIMINARY & GENERAL REQUIREMENTS/ CÔNG TÁC TẠM VÀ CÁC YÊU CẦU CHUNG
A4: No. | B4: DESCRIPTION | C4: UNIT | D4: Q'TY | E4: PRICE | F4: AMOUNT | G4: REMARK
A5: No.01 | B5: TOTAL OF BILL No.1: PRELIMINARY & GENERAL REQUIREMENTS/ TIỆN ÍCH VÀ YÊU CẦU CHUNG | F5: =SUBTOTAL(9,F6:F69) -> 0
B6: The Contractor shall refer to the General Requirements and other tender documents and he is to include all items that he considers necessary for completion of the Works and complying with all the requirements contained therein, whether or not they are specifically mentioned in this Bill of Quantities./Nhà thầu phải tham khảo các Yêu cầu chung và các tài liệu đấu thầu khác và Nhà thầu phải đưa vào tất cả các hạng mục mà Nhà thầu cho là cần thiết để hoàn thành Công trình và tuân thủ tất cả các yêu cầu có trong đó, cho dù chúng có được đề cập cụ thể trong Bảng khối lượng này hay không.
A7: I | B7: PERMANENT VALUE
A8: 1.1 | B8: Groundbreaking | C8: item
A9: 1.2 | B9: Insurance
A10: 1.2.1 | B10: Workmen's compensation insurance for all workers and sub-contractors with minium coverage, USD3,000/person | C10: item
A11: 1.2.2 | B11: Third Party Insurance(USD300,000) | C11: item
A12: 1.3 | B12: Performance bond
A13: 1.3.1 | B13: Advance payment bond fee | C13: item
A14: 1.3.2 | B14: Performance bond fee | C14: item
A15: 1.3.3 | B15: Warranty guarantee | C15: item
A16: 1.4 | B16: Site Safety Measures
A17: 1.4.1 | B17: Signs | C17: item
A18: 1.4.2 | B18: Flagman | C18: item
A19: 1.4.3 | B19: Safety Barriers | C19: item
A20: 1.4.4 | B20: PPE to Workers & Visitors | C20: item
A21: 1.5 | B21: Temporary Fecility
A22: 1.5.1 | B22: Site Office for Constructor | C22: item
A23: 1.5.2 | B23: Site Office for Client(20ft, including desks and chairs, shelves, air conditioners) | C23: item
A24: 1.5.3 | B24: Site Office for Consultant(20ft, including desks and chairs, shelves, air conditioners, printers, essential stationery…) | C24: item
A25: 1.5.4 | B25: Meeting room | C25: item
A26: 1.5.5 | B26: Safety training area | C26: item
A27: 1.5.6 | B27: Storehouse & Workshop | C27: item
A28: 1.5.7 | B28: Bike parking | C28: item
A29: 1.5.8 | B29: Toilet for contractor | C29: item
A30: 1.5.9 | B30: Toilet for Client & Consultant | C30: item
A31: 1.5.10 | B31: Toilet for worker | C31: item
A32: 1.5.11 | B32: Temporary road | C32: item
A33: 1.6 | B33: Temporary service
A34: 1.6.1 | B34: Power supply sysem | C34: item
A35: 1.6.2 | B35: Lightings system | C35: item
A36: 1.6.3 | B36: Water Supply system | C36: item
A37: 1.6.4 | B37: Telephone & Internet | C37: item
A38: 1.6.5 | B38: Waste water Sewerage | C38: item
A39: 1.7 | B39: Survey & Setting Out | C39: item
A40: 1.8 | B40: Temporary fence (1.50m to 2.10m high) & Gates | C40: item
A41: 1.9 | B41: Project Signboard | C41: item
A42: 1.1 | B42: Construction Access
A43: 1.10.1 | B43: Heavy Duty Paver Entrance | C43: item
A44: 1.10.2 | B44: Silt Trap & Temporary drainage | C44: item
A45: 1.10.3 | B45: Washing Bay | C45: item
A46: 1.11 | B46: Method of Statements | C46: item
A47: 1.12 | B47: Shop Drawings & As-built Plans | C47: item
A48: 1.13 | B48: Quality Control Measures
A49: 1.13.1 | B49: Testing & Commissioning | C49: item
A50: 1.13.2 | B50: Material Catalogue & Samples | C50: item
A51: 1.13.3 | B51: QAQC Inspection | C51: item
A52: 1.14 | B52: Authorities’ Construction Working Permit from VSIP | C52: item
A53: 1.15 | B53: Security
A54: 1.15.1 | B54: Watch-cabin | C54: item
A55: 1.15.2 | B55: Security equipment | C55: item
A56: 1.15.3 | B56: Security CCTV | C56: item
A57: 1.16 | B57: Cleaning and handover | C57: item
A58: 1.17 | B58: As-built | C58: item
A59: II | B59: MONTHLY VALUE
A60: 1.18 | B60: Preliminaries
A61: 1.18.1 | B61: Temporary Power & water - Monthly consumption | C61: month
A62: 1.18.2 | B62: Duty person for site electrical & water | C62: month
A63: 1.18.3 | B63: Temporary telephone, fax, internet systems | C63: month
A64: 1.19 | B64: Safety man, environment protection, and fire prevention | C64: month
A65: 1.2 | B65: Security staff | C65: month
A66: 1.21 | B66: Cleaning for office and construction site | C66: month
A67: 1.22 | B67: Scafffolding | C67: lot
A68: 1.23 | B68: Management fee (Site team) | C68: month

Sheet Bill 2-Main building works
A1: PROJECT/ DỰ ÁN : NEW WAREHOUSE/NHÀ KHO
A2: ADDRESS/ĐỊA CHỈ : VSIP 3, BINH DUONG, VIETNAM
A3: BILL No.02 : MAIN BUILDING WORKS
A4: No. | B4: DESCRIPTION | C4: STANDARD | D4: Unit | E4: DIMENSION | J4: QUANTITY | K4: Q'TY | L4: MATERIAL | N4: LABOUR & EQUIPMENT | P4: TOTAL COST(VND) | R4: REMARK
E5: No | F5: L | G5: W | H5: H | I5: HS | J5: COMPONENT | L5: MATERIAL | M5: AMOUNT | N5: UNIT | O5: AMOUNT | P5: UNIT | Q5: AMOUNT
A6: No.02 | B6: TOTAL OF BILL No.2: MAIN BUILDING WORKS
A7: =A13 -> C.01 | B7: =B13 -> WAREHOUSE / NHÀ KHO
A8: =A261 -> C.02 | B8: =B261 -> OFFICE/ VĂN PHÒNG
A9: =A449 -> C.03 | B9: =B449 -> WATER TANK/ BỂ NƯỚC
A10: =A515 -> C.04 | B10: =B515 -> PUPM ROOM+ELECTRIC+TRANFORMER/NHÀ BƠM +NHÀ ĐIỆN, MÁY PHÁT
A11: =A573 -> C.05 | B11: =B573 -> GUARD HOUSE/NHÀ BẢO VỆ
A12: =A641 -> C.06 | B12: =B641 -> MOTOBIKE HOUSE / NHÀ XE MÁY
A13: C.01 | B13: WAREHOUSE / NHÀ KHO
A14: I | B14: EARTH WORK/ CÔNG TÁC ĐẤT
A15: 1 | B15: Excavation of Soil/ Công tác đào đất | C15: Soil grade 3 | D15: m3
B16: M1 | E16: 8 | F16: 2 | G16: 3.5 | H16: 2.55 | I16: 1.3 | J16: =PRODUCT(E16:I16) -> 185.64
B17: M2 | E17: 7 | F17: 2.8 | G17: 4 | H17: 2.55 | I17: 1.3 | J17: =PRODUCT(E17:I17) -> 259.896
B18: M3 | E18: 20 | F18: 3 | G18: 4.5 | H18: 2.55 | I18: 1.3 | J18: =PRODUCT(E18:I18) -> 895.05
B19: M4 | E19: 32 | F19: 2.4 | G19: 3 | H19: 2.55 | I19: 1.3 | J19: =PRODUCT(E19:I19) -> 763.776
B20: M4a | E20: 2 | F20: 2.5 | G20: 3 | H20: 2.55 | I20: 1.3 | J20: =PRODUCT(E20:I20) -> 49.725
B21: M5 | E21: =42-13 -> 29 | F21: 2.2 | G21: 2.2 | H21: 2.55 | I21: 1.3 | J21: =PRODUCT(E21:I21) -> 465.2934
B22: M6 | E22: 24 | F22: 2.2 | G22: 2.2 | H22: 2.55 | I22: 1.3 | J22: =PRODUCT(E22:I22) -> 385.0704
B23: M7 | E23: 12 | F23: 2.5 | G23: 2.5 | H23: 2.55 | I23: 1.3 | J23: =PRODUCT(E23:I23) -> 248.625
B24: M8 | E24: 1 | F24: 2.8 | G24: 2.8 | H24: 2.55 | I24: 1.3 | J24: =PRODUCT(E24:I24) -> 25.9896
B25: M9 | E25: 16 | F25: 2 | G25: 2 | H25: 2.55 | I25: 1.3 | J25: =PRODUCT(E25:I25) -> 212.16
B26: DK 200x800 | E26: 1 | F26: =14.05+40+30+15.7 -> 99.75 | G26: 0.2 | H26: 0.85 | I26: 1.3 | J26: =PRODUCT(E26:I26) -> 22.04475
B27: DK 200x1000 | E27: 1 | F27: =(110+112.5)*2 -> 445 | G27: 0.2 | H27: 1.05 | I27: 1.3 | J27: =PRODUCT(E27:I27) -> 121.485
A28: 2 | B28: Backfilling soil for foundation/ Lấp đất móng | C28: Compact layer by layer, each layer 0.3m | D28: m3
A29: 3 | B29: Remove surplus soil/ Vận chuyển đất dư | C29: Distance D<=1Km | D29: m3
A30: 4 | B30: Natural soil well compacted, k = 0.95/ Đầm chặt nền đất | D30: m2
B31: Nền xưởng 2T | E31: 1 | F31: 70 | G31: 28.05 | J31: =G31*F31 -> 1963.5
B32: Nền xưởng 5T | E32: 1 | I32: =(110*112.5)-(70*28.05)-(15.7*29.4) -> 9949.92 | J32: =I32 -> 9949.92
A33: 5 | B33: Foundation, ground beam soil well compacted, k = 0.95/ Đầm chặt đất móng, đà kiềng | D33: m2
B34: M1 | E34: 8 | F34: 2 | G34: 3.5 | J34: =E34*(F34+0.2)*(G34+0.2) -> 65.12
B35: M2 | E35: 7 | F35: 2.8 | G35: 4 | J35: =E35*(F35+0.2)*(G35+0.2) -> 88.2
B36: M3 | E36: 20 | F36: 3 | G36: 4.5 | J36: =E36*(F36+0.2)*(G36+0.2) -> 300.8
B37: M4 | E37: 32 | F37: 2.4 | G37: 3 | J37: =E37*(F37+0.2)*(G37+0.2) -> 266.24
B38: M4a | E38: 2 | F38: 2.5 | G38: 3 | J38: =E38*(F38+0.2)*(G38+0.2) -> 17.28
B39: M5 | E39: =42-13 -> 29 | F39: 2.2 | G39: 2.2 | J39: =E39*(F39+0.2)*(G39+0.2) -> 167.04
B40: M6 | E40: 24 | F40: 2.2 | G40: 2.2 | J40: =E40*(F40+0.2)*(G40+0.2) -> 138.24
B41: M7 | E41: 12 | F41: 2.5 | G41: 2.5 | J41: =E41*(F41+0.2)*(G41+0.2) -> 87.48
B42: M8 | E42: 1 | F42: 2.8 | G42: 2.8 | J42: =E42*(F42+0.2)*(G42+0.2) -> 9
B43: M9 | E43: 16 | F43: 2 | G43: 2 | J43: =E43*(F43+0.2)*(G43+0.2) -> 77.44
B44: DK 200x800 | E44: 1 | F44: =14.05+40+30+15.7 -> 99.75 | G44: 0.2 | J44: =E44*(F44+0.2)*(G44+0.2) -> 39.98
B45: DK 200x1000 | E45: 1 | F45: =(110+112.5)*2 -> 445 | G45: 0.2 | J45: =E45*(F45+0.2)*(G45+0.2) -> 178.08
A46: 6 | B46: Crushed aggregate base course 0x4 , well compacted K>=0.98, / Lớp đá 0x4 đầm chặt K>=0.98, | D46: m3
B47: Nền xưởng 2T | E47: 1 | F47: 70 | G47: 28.05 | H47: 0.2 | I47: 1.42 | J47: =PRODUCT(E47:I47) -> 557.634
B48: Nền xưởng 5T | E48: 1 | F48: =(110*112.5)-(70*28.05)-(15.7*29.4) -> 9949.92 | H48: 0.4 | I48: 1.42 | J48: =F48*H48*I48 -> 5651.5546
A49: 7 | B49: PVC sheet/ Lớp PVC | C49: PVC 0.3mm | D49: m2
A50: II | B50: ANTI TERMITE TREATMENT/ CHỐNG MỐI
A51: 1 | B51: Pre-treatment of basement ground surface/ Chống mối cho nền | C51: Termize 200sc solution 0.25%, 5 liters/m2 | D51: m2
A52: III | B52: REINFORCED CONCRETE WORK/ BÊ TÔNG CỐT THÉP
A53: * | B53: Concrete work/ Công tác bê tông
A54: 1 | B54: Lean concrete/ Bê tông lót | C54: Grade B12.5 | D54: m3
B55: M1 | E55: 8 | F55: 2 | G55: 3.5 | H55: 0.1 | J55: =E55*(F55+0.2)*(G55+0.2)*H55 -> 6.512
B56: M2 | E56: 7 | F56: 2.8 | G56: 4 | H56: 0.1 | J56: =E56*(F56+0.2)*(G56+0.2)*H56 -> 8.82
B57: M3 | E57: 20 | F57: 3 | G57: 4.5 | H57: 0.1 | J57: =E57*(F57+0.2)*(G57+0.2)*H57 -> 30.08
B58: M4 | E58: 32 | F58: 2.4 | G58: 3 | H58: 0.1 | J58: =E58*(F58+0.2)*(G58+0.2)*H58 -> 26.624
B59: M4a | E59: 2 | F59: 2.5 | G59: 3 | H59: 0.1 | J59: =E59*(F59+0.2)*(G59+0.2)*H59 -> 1.728
B60: M5 | E60: =42-13 -> 29 | F60: 2.2 | G60: 2.2 | H60: 0.1 | J60: =E60*(F60+0.2)*(G60+0.2)*H60 -> 16.704
B61: M6 | E61: 24 | F61: 2.2 | G61: 2.2 | H61: 0.1 | J61: =E61*(F61+0.2)*(G61+0.2)*H61 -> 13.824
B62: M7 | E62: 12 | F62: 2.5 | G62: 2.5 | H62: 0.1 | J62: =E62*(F62+0.2)*(G62+0.2)*H62 -> 8.748
B63: M8 | E63: 1 | F63: 2.8 | G63: 2.8 | H63: 0.1 | J63: =E63*(F63+0.2)*(G63+0.2)*H63 -> 0.9
B64: M9 | E64: 16 | F64: 2 | G64: 2 | H64: 0.1 | J64: =E64*(F64+0.2)*(G64+0.2)*H64 -> 7.744
B65: DK 200x800 | E65: 1 | F65: =14.05+40+30+15.7 -> 99.75 | G65: 0.2 | H65: 0.1 | J65: =E65*(F65+0.2)*(G65+0.2)*H65 -> 3.998
B66: DK 200x1000 | E66: 1 | F66: =(110+112.5)*2 -> 445 | G66: 0.2 | H66: 0.1 | J66: =E66*(F66+0.2)*(G66+0.2)*H66 -> 17.808
A67: 2 | B67: Foundation/ Bê tông móng | C67: Grade B20 | D67: m3 | J67: =PRODUCT(E67:I67) -> 0
B68: M1 | E68: 8 | F68: 2 | G68: 3.5 | H68: 0.5 | I68: 1 | J68: =PRODUCT(E68:I68) -> 28
B69: M2 | E69: 7 | F69: 2.8 | G69: 4 | H69: 0.5 | I69: 1 | J69: =PRODUCT(E69:I69) -> 39.2
B70: M3 | E70: 20 | F70: 3 | G70: 4.5 | H70: 0.5 | I70: 1 | J70: =PRODUCT(E70:I70) -> 135
B71: M4 | E71: 32 | F71: 2.4 | G71: 3 | H71: 0.5 | I71: 1 | J71: =PRODUCT(E71:I71) -> 115.2
B72: M4a | E72: 2 | F72: 2.5 | G72: 3 | H72: 0.5 | I72: 1 | J72: =PRODUCT(E72:I72) -> 7.5
B73: M5 | E73: =42-13 -> 29 | F73: 2.2 | G73: 2.2 | H73: 0.5 | I73: 1 | J73: =PRODUCT(E73:I73) -> 70.18
B74: M6 | E74: 24 | F74: 2.2 | G74: 2.2 | H74: 0.5 | I74: 1 | J74: =PRODUCT(E74:I74) -> 58.08
B75: M7 | E75: 12 | F75: 2.5 | G75: 2.5 | H75: 0.5 | I75: 1 | J75: =PRODUCT(E75:I75) -> 37.5
B76: M8 | E76: 1 | F76: 2.8 | G76: 2.8 | H76: 0.5 | I76: 1 | J76: =PRODUCT(E76:I76) -> 3.92
B77: M9 | E77: 16 | F77: 2 | G77: 2 | H77: 0.5 | I77: 1 | J77: =PRODUCT(E77:I77) -> 32
A78: 3 | B78: Stump column / Bê tông cổ cột | C78: =C67 -> Grade B20 | D78: m3 | J78: =PRODUCT(E78:I78) -> 0
B79: C1 | E79: 10 | F79: 0.4 | G79: 0.8 | H79: 1.9 | I79: 1 | J79: =PRODUCT(E79:I79) -> 6.08
B80: C1a | E80: 4 | F80: 0.4 | G80: 0.8 | H80: 1.9 | I80: 1 | J80: =PRODUCT(E80:I80) -> 2.432
B81: C2 | E81: 4 | F81: 0.4 | G81: 0.8 | H81: 1.9 | I81: 1 | J81: =PRODUCT(E81:I81) -> 2.432
B82: C3 | E82: 4 | F82: 0.4 | G82: 0.8 | H82: 1.9 | I82: 1 | J82: =PRODUCT(E82:I82) -> 2.432
B83: C4 | E83: 3 | F83: 0.4 | G83: 0.8 | H83: 1.9 | I83: 1 | J83: =PRODUCT(E83:I83) -> 1.824
B84: C5 | E84: 3 | F84: 0.4 | G84: 0.8 | H84: 1.9 | I84: 1 | J84: =PRODUCT(E84:I84) -> 1.824
B85: C6 | E85: 20 | F85: 0.4 | G85: 0.8 | H85: 1.9 | I85: 1 | J85: =PRODUCT(E85:I85) -> 12.16
B86: C7 | E86: 9 | F86: 0.4 | G86: 0.8 | H86: 1.9 | I86: 1 | J86: =PRODUCT(E86:I86) -> 5.472
B87: SC | E87: =12*5 -> 60 | F87: 0.4 | G87: 0.4 | H87: 1.9 | I87: 1 | J87: =PRODUCT(E87:I87) -> 18.24
A88: 4 | B88: Ground beam/ Bê tông đà kiềng | C88: Grade B25 | D88: m3 | J88: =PRODUCT(E88:I88) -> 0
B89: DK 200x800 | E89: 1 | F89: =14.05+40+30+15.7 -> 99.75 | G89: 0.2 | H89: 0.8 | I89: 1 | J89: =PRODUCT(E89:I89) -> 15.96
B90: DK 200x1000 | E90: 1 | F90: =(110+112.5)*2 -> 445 | G90: 0.2 | H90: 1 | I90: 1 | J90: =PRODUCT(E90:I90) -> 89
A91: 5 | B91: Ground floor/ Bê tông nền | C91: Grade B25 | D91: m3
B92: Nền xưởng 2T | E92: 1 | F92: 70 | G92: 28.05 | H92: 0.2 | I92: 1 | J92: =PRODUCT(E92:I92) -> 392.7
B93: Nền xưởng 5T | E93: 1 | H93: 0.4 | I93: =(110*112.5)-(70*28.05)-(15.7*29.4) -> 9949.92 | J93: =I93*H93 -> 3979.968
A94: 6 | B94: Column Concrete/ Bê tông cho cột | C94: Grade B25 | D94: m3
B95: C1 | E95: 10 | F95: 0.4 | G95: 0.8 | H95: 13 | I95: 1 | J95: =PRODUCT(E95:I95) -> 41.6
B96: C1a | E96: 4 | F96: 0.4 | G96: 0.8 | H96: 13 | I96: 1 | J96: =PRODUCT(E96:I96) -> 16.64
B97: C2 | E97: 4 | F97: 0.4 | G97: 0.8 | H97: 13 | I97: 1 | J97: =PRODUCT(E97:I97) -> 16.64
B98: C3 | E98: 4 | F98: 0.4 | G98: 0.8 | H98: 13 | I98: 1 | J98: =PRODUCT(E98:I98) -> 16.64
B99: C4 | E99: 3 | F99: 0.4 | G99: 0.8 | H99: 13 | I99: 1 | J99: =PRODUCT(E99:I99) -> 12.48
B100: C5 | E100: 3 | F100: 0.4 | G100: 0.8 | H100: 13 | I100: 1 | J100: =PRODUCT(E100:I100) -> 12.48
...

Sheet C02.CSA_OFFICE
A1: ESTIMATE DETAIL TABLE
A2: ='Bill 3-External works'!#REF! -> #REF!
A3: ITEM/HẠNG MỤC : COMPLETE CONSTRUCTION /XÂY DỰNG HOÀN THIỆN
R4: VND
A5: No. | B5: DESCRIPTION | C5: STANDARD | D5: Unit | E5: DIMENSION | J5: QUANTITY | K5: Q'TY | L5: MATERIAL | N5: LABOUR & EQUIPMENT | P5: TOTAL COST(VND) | R5: REMARK | S5: Profit | T5: ='Bill 2-Main building works'!#REF! -> #REF!
E6: No | F6: L | G6: W | H6: H | I6: HS | J6: COMPONENT | L6: UNIT | M6: AMOUNT | N6: UNIT | O6: AMOUNT | P6: UNIT | Q6: AMOUNT | T6: Vật tư | U6: Nhân công
A7: C02 | B7: OFFICE/ VĂN PHÒNG | K7: =I288+I322*0.5+264.2 -> 679.68 | M7: =SUBTOTAL(9,M8:M17) -> #REF! | O7: =SUBTOTAL(9,O8:O17) -> #REF! | Q7: =SUBTOTAL(9,Q8:Q17) -> #REF!
A8: I | B8: EARTH WORK/ CÔNG TÁC ĐẤT | M8: =M18 -> #REF! | N8: =N18 -> 0 | O8: =O18 -> #REF! | Q8: =O8+M8 -> #REF!
A9: II | B9: ANTI TERMITE TREATMENT/ CHỐNG MỐI | M9: =M128 -> #REF! | O9: =O128 -> #REF! | Q9: =O9+M9 -> #REF!
A10: III | B10: REINFORCED CONCRETE WORK/ BÊ TÔNG CỐT THÉP | M10: =M131 -> #REF! | O10: =O131 -> #REF! | Q10: =O10+M10 -> #REF!
A11: IV | B11: FLOOR FINISHING WORKS/ HOÀN THIỆN NỀN | M11: =M690 -> #REF! | O11: =O690 -> #REF! | Q11: =O11+M11 -> #REF!
A12: V | B12: WALL FINISHING WORKS/ CÔNG TÁC HOÀN THIỆN TƯỜNG | M12: =M766 -> #REF! | O12: =O766 -> #REF! | Q12: =O12+M12 -> #REF!
A13: VI | B13: CEILING FINISHING WORKS/ CÔNG TÁC HOÀN THIỆN TRẦN | M13: =M1307 -> #REF! | O13: =O1307 -> #REF! | Q13: =Q1307 -> #REF!
A14: VII | B14: DOORS AND WINDOWS/ CỬA ĐI. CỬA SỔ | M14: =M1316 -> #REF! | O14: =O1316 -> #REF! | Q14: =O14+M14 -> #REF!
A15: VIII | B15: METAL WORKS/ CÔNG TÁC KIM LOẠI | M15: =M1359 -> #REF! | O15: =O1359 -> #REF! | Q15: =Q1359 -> #REF!
A16: IX | B16: OTHERS WORKS/ CÔNG TÁC KHÁC | M16: =M1364 -> #REF! | O16: =O1364 -> #REF! | Q16: =O16+M16 -> #REF!
A18: I | B18: EARTH WORK/ CÔNG TÁC ĐẤT | M18: =SUBTOTAL(109,M19:M127) -> #REF! | O18: =SUM(O19:O126) -> #REF! | Q18: =O18+M18 -> #REF!
A19: 1 | B19: Excavation of Soil/ Công tác đào đất | C19: Soil grade 3 | D19: m3 | K19: =+SUBTOTAL(9,J21:J63) -> 349.2135 | L19: =T19*$T$5 -> #REF! | M19: =ROUND(L19*K19,0) -> #REF! | N19: =U19*$T$5 -> #REF! | O19: =ROUND(N19*K19,0) -> #REF! | P19: =N19+L19 -> #REF! | Q19: =O19+M19 -> #REF! | U19: 35000
B20: Foudation | L20: =T20*$T$5 -> #REF! | M20: =ROUND(L20*K20,0) -> #REF! | N20: =U20*$T$5 -> #REF! | O20: =ROUND(N20*K20,0) -> #REF! | Q20: =O20+M20 -> #REF!
B21: M1 | E21: 1 | F21: 1 | G21: 1 | H21: 2.25 | I21: 1.3 | J21: =PRODUCT(E21:I21) -> 2.925 | L21: =T21*$T$5 -> #REF! | M21: =ROUND(L21*K21,0) -> #REF! | N21: =U21*$T$5 -> #REF! | O21: =ROUND(N21*K21,0) -> #REF! | Q21: =O21+M21 -> #REF!
B22: M2 | E22: 1 | F22: 1.6 | G22: 1.6 | H22: 2.25 | I22: 1.3 | J22: =PRODUCT(E22:I22) -> 7.488 | L22: =T22*$T$5 -> #REF! | M22: =ROUND(L22*K22,0) -> #REF! | N22: =U22*$T$5 -> #REF! | O22: =ROUND(N22*K22,0) -> #REF! | Q22: =O22+M22 -> #REF!
B23: M3 | E23: 2 | F23: 1.8 | G23: 1.8 | H23: 2.25 | I23: 1.3 | J23: =PRODUCT(E23:I23) -> 18.954 | L23: =T23*$T$5 -> #REF! | M23: =ROUND(L23*K23,0) -> #REF! | N23: =U23*$T$5 -> #REF! | O23: =ROUND(N23*K23,0) -> #REF! | Q23: =O23+M23 -> #REF! | T23: =7/13 -> 0.53846154
B24: M4 | E24: 2 | F24: 2 | G24: 2 | H24: 2.25 | I24: 1.3 | J24: =PRODUCT(E24:I24) -> 23.4 | L24: =T24*$T$5 -> #REF! | M24: =ROUND(L24*K24,0) -> #REF! | N24: =U24*$T$5 -> #REF! | O24: =ROUND(N24*K24,0) -> #REF! | Q24: =O24+M24 -> #REF!
B25: M5 | E25: 3 | F25: 2.2 | G25: 2.2 | H25: 2.25 | I25: 1.3 | J25: =PRODUCT(E25:I25) -> 42.471 | L25: =T25*$T$5 -> #REF! | M25: =ROUND(L25*K25,0) -> #REF! | N25: =U25*$T$5 -> #REF! | O25: =ROUND(N25*K25,0) -> #REF! | Q25: =O25+M25 -> #REF!
B26: M6 | E26: 5 | F26: 2.4 | G26: 2.4 | H26: 2.25 | I26: 1.3 | J26: =PRODUCT(E26:I26) -> 84.24 | L26: =T26*$T$5 -> #REF! | M26: =ROUND(L26*K26,0) -> #REF! | N26: =U26*$T$5 -> #REF! | O26: =ROUND(N26*K26,0) -> #REF! | Q26: =O26+M26 -> #REF!
B27: M7 | E27: 3 | F27: 2.6 | G27: 2.6 | H27: 2.25 | I27: 1.3 | J27: =PRODUCT(E27:I27) -> 59.319 | L27: =T27*$T$5 -> #REF! | M27: =ROUND(L27*K27,0) -> #REF! | N27: =U27*$T$5 -> #REF! | O27: =ROUND(N27*K27,0) -> #REF! | Q27: =O27+M27 -> #REF!
B28: M8 | E28: 2 | F28: 2.8 | G28: 2.8 | H28: 2.25 | I28: 1.3 | J28: =PRODUCT(E28:I28) -> 45.864 | L28: =T28*$T$5 -> #REF! | M28: =ROUND(L28*K28,0) -> #REF! | N28: =U28*$T$5 -> #REF! | O28: =ROUND(N28*K28,0) -> #REF! | Q28: =O28+M28 -> #REF!
B29: M9 | E29: 1 | F29: 2.6 | G29: 4.2 | H29: 2.25 | I29: 1.3 | J29: =PRODUCT(E29:I29) -> 31.941 | L29: =T29*$T$5 -> #REF! | M29: =ROUND(L29*K29,0) -> #REF! | N29: =U29*$T$5 -> #REF! | O29: =ROUND(N29*K29,0) -> #REF! | Q29: =O29+M29 -> #REF!
B30: M10 | E30: 1 | F30: 2.4 | G30: 3.2 | H30: 2.25 | I30: 1.3 | J30: =PRODUCT(E30:I30) -> 22.464 | L30: =T30*$T$5 -> #REF! | M30: =ROUND(L30*K30,0) -> #REF! | N30: =U30*$T$5 -> #REF! | O30: =ROUND(N30*K30,0) -> #REF! | Q30: =O30+M30 -> #REF!
B31: Ground beam | L31: =T31*$T$5 -> #REF! | M31: =ROUND(L31*K31,0) -> #REF! | N31: =U31*$T$5 -> #REF! | O31: =ROUND(N31*K31,0) -> #REF! | Q31: =O31+M31 -> #REF!
B32: D1-1 | C32: 200x400 | E32: 1 | F32: 15.4 | G32: 0.4 | H32: 0.15 | J32: =PRODUCT(E32:I32) -> 0.924 | L32: =T32*$T$5 -> #REF! | M32: =ROUND(L32*K32,0) -> #REF! | N32: =U32*$T$5 -> #REF! | O32: =ROUND(N32*K32,0) -> #REF! | Q32: =O32+M32 -> #REF!
B33: D1-1a | C33: 200x400(-0.150) | E33: 1 | F33: 3.8 | G33: 0.4 | H33: 0.45 | J33: =PRODUCT(E33:I33) -> 0.684 | L33: =T33*$T$5 -> #REF! | M33: =ROUND(L33*K33,0) -> #REF! | N33: =U33*$T$5 -> #REF! | O33: =ROUND(N33*K33,0) -> #REF! | Q33: =O33+M33 -> #REF!
B34: D1-2 | C34: 200x300 | E34: 1 | F34: 8.75 | G34: 0.4 | H34: 0.05 | J34: =PRODUCT(E34:I34) -> 0.175 | L34: =T34*$T$5 -> #REF! | M34: =ROUND(L34*K34,0) -> #REF! | N34: =U34*$T$5 -> #REF! | O34: =ROUND(N34*K34,0) -> #REF! | Q34: =O34+M34 -> #REF!
B35: D1-2a | C35: 200x300(-0.150) | E35: 1 | F35: 3.8 | G35: 0.4 | H35: 0.35 | J35: =PRODUCT(E35:I35) -> 0.532 | L35: =T35*$T$5 -> #REF! | M35: =ROUND(L35*K35,0) -> #REF! | N35: =U35*$T$5 -> #REF! | O35: =ROUND(N35*K35,0) -> #REF! | Q35: =O35+M35 -> #REF!
B36: D1-3 | C36: 200x300 | E36: 1 | F36: 5.8 | G36: 0.4 | H36: 0.05 | J36: =PRODUCT(E36:I36) -> 0.116 | L36: =T36*$T$5 -> #REF! | M36: =ROUND(L36*K36,0) -> #REF! | N36: =U36*$T$5 -> #REF! | O36: =ROUND(N36*K36,0) -> #REF! | Q36: =O36+M36 -> #REF!
B37: D1-4 | C37: 200x400 | E37: 1 | F37: 5.9 | G37: 0.4 | H37: 0.15 | J37: =PRODUCT(E37:I37) -> 0.354 | L37: =T37*$T$5 -> #REF! | M37: =ROUND(L37*K37,0) -> #REF! | N37: =U37*$T$5 -> #REF! | O37: =ROUND(N37*K37,0) -> #REF! | Q37: =O37+M37 -> #REF!
C38: 200x300 | E38: 1 | F38: 4.4 | G38: 0.4 | H38: 0.05 | J38: =PRODUCT(E38:I38) -> 0.088 | L38: =T38*$T$5 -> #REF! | M38: =ROUND(L38*K38,0) -> #REF! | N38: =U38*$T$5 -> #REF! | O38: =ROUND(N38*K38,0) -> #REF! | Q38: =O38+M38 -> #REF!
B39: D1-4a | C39: 200x300(-0.150) | E39: 1 | F39: 3.8 | G39: 0.4 | H39: 0.35 | J39: =PRODUCT(E39:I39) -> 0.532 | L39: =T39*$T$5 -> #REF! | M39: =ROUND(L39*K39,0) -> #REF! | N39: =U39*$T$5 -> #REF! | O39: =ROUND(N39*K39,0) -> #REF! | Q39: =O39+M39 -> #REF!
B40: D1-5 | C40: 200x400 | E40: 1 | F40: 19 | G40: 0.4 | H40: 0.15 | J40: =PRODUCT(E40:I40) -> 1.14 | L40: =T40*$T$5 -> #REF! | M40: =ROUND(L40*K40,0) -> #REF! | N40: =U40*$T$5 -> #REF! | O40: =ROUND(N40*K40,0) -> #REF! | Q40: =O40+M40 -> #REF!
B41: D1-6 | C41: 200x400 | E41: 1 | F41: 2.5 | G41: 0.4 | H41: 0.15 | J41: =PRODUCT(E41:I41) -> 0.15 | L41: =T41*$T$5 -> #REF! | M41: =ROUND(L41*K41,0) -> #REF! | N41: =U41*$T$5 -> #REF! | O41: =ROUND(N41*K41,0) -> #REF! | Q41: =O41+M41 -> #REF!
B42: D1-7 | C42: 200x400 | E42: 1 | F42: 12.5 | G42: 0.4 | H42: 0.15 | J42: =PRODUCT(E42:I42) -> 0.75 | L42: =T42*$T$5 -> #REF! | M42: =ROUND(L42*K42,0) -> #REF! | N42: =U42*$T$5 -> #REF! | O42: =ROUND(N42*K42,0) -> #REF! | Q42: =O42+M42 -> #REF!
B43: D1-8 | C43: 200x300 | E43: 1 | F43: 7.4 | G43: 0.4 | H43: 0.05 | J43: =PRODUCT(E43:I43) -> 0.148 | L43: =T43*$T$5 -> #REF! | M43: =ROUND(L43*K43,0) -> #REF! | N43: =U43*$T$5 -> #REF! | O43: =ROUND(N43*K43,0) -> #REF! | Q43: =O43+M43 -> #REF!
B44: D1-9 | C44: 200x300 | E44: 1 | F44: 6.7 | G44: 0.4 | H44: 0.05 | J44: =PRODUCT(E44:I44) -> 0.134 | L44: =T44*$T$5 -> #REF! | M44: =ROUND(L44*K44,0) -> #REF! | N44: =U44*$T$5 -> #REF! | O44: =ROUND(N44*K44,0) -> #REF! | Q44: =O44+M44 -> #REF!
B45: D1-10 | C45: 200x300 | E45: 1 | F45: 1.3 | G45: 0.4 | H45: 0.05 | J45: =PRODUCT(E45:I45) -> 0.026 | L45: =T45*$T$5 -> #REF! | M45: =ROUND(L45*K45,0) -> #REF! | N45: =U45*$T$5 -> #REF! | O45: =ROUND(N45*K45,0) -> #REF! | Q45: =O45+M45 -> #REF!
B46: D1-11 | C46: 200x400 | E46: 1 | F46: 5.2 | G46: 0.4 | H46: 0.15 | J46: =PRODUCT(E46:I46) -> 0.312 | L46: =T46*$T$5 -> #REF! | M46: =ROUND(L46*K46,0) -> #REF! | N46: =U46*$T$5 -> #REF! | O46: =ROUND(N46*K46,0) -> #REF! | Q46: =O46+M46 -> #REF!
B47: D1-12 | C47: 200x400 | E47: 1 | F47: 6.7 | G47: 0.4 | H47: 0.15 | J47: =PRODUCT(E47:I47) -> 0.402 | L47: =T47*$T$5 -> #REF! | M47: =ROUND(L47*K47,0) -> #REF! | N47: =U47*$T$5 -> #REF! | O47: =ROUND(N47*K47,0) -> #REF! | Q47: =O47+M47 -> #REF!
B48: D1-13 | C48: 200x300 | E48: 1 | F48: 1.3 | G48: 0.4 | H48: 0.05 | J48: =PRODUCT(E48:I48) -> 0.026 | L48: =T48*$T$5 -> #REF! | M48: =ROUND(L48*K48,0) -> #REF! | N48: =U48*$T$5 -> #REF! | O48: =ROUND(N48*K48,0) -> #REF! | Q48: =O48+M48 -> #REF!
E49: 1 | F49: 1.6 | G49: 0.4 | H49: 0.05 | J49: =PRODUCT(E49:I49) -> 0.032 | L49: =T49*$T$5 -> #REF! | M49: =ROUND(L49*K49,0) -> #REF! | N49: =U49*$T$5 -> #REF! | O49: =ROUND(N49*K49,0) -> #REF! | Q49: =O49+M49 -> #REF!
B50: D1-14 | C50: 100x300 | E50: 1 | F50: 2 | G50: 0.3 | H50: 0.05 | J50: =PRODUCT(E50:I50) -> 0.03 | L50: =T50*$T$5 -> #REF! | M50: =ROUND(L50*K50,0) -> #REF! | N50: =U50*$T$5 -> #REF! | O50: =ROUND(N50*K50,0) -> #REF! | Q50: =O50+M50 -> #REF!
B51: D1-15 | C51: 100x300 | E51: 1 | F51: 3.1 | G51: 0.3 | H51: 0.05 | J51: =PRODUCT(E51:I51) -> 0.0465 | L51: =T51*$T$5 -> #REF! | M51: =ROUND(L51*K51,0) -> #REF! | N51: =U51*$T$5 -> #REF! | O51: =ROUND(N51*K51,0) -> #REF! | Q51: =O51+M51 -> #REF!
B52: D1-16 | C52: 200x300 | E52: 1 | F52: 1.3 | G52: 0.4 | H52: 0.05 | J52: =PRODUCT(E52:I52) -> 0.026 | L52: =T52*$T$5 -> #REF! | M52: =ROUND(L52*K52,0) -> #REF! | N52: =U52*$T$5 -> #REF! | O52: =ROUND(N52*K52,0) -> #REF! | Q52: =O52+M52 -> #REF!
B53: D1-16a | C53: 200x300(-0.150) | E53: 1 | F53: 3.3 | G53: 0.4 | H53: 0.35 | J53: =PRODUCT(E53:I53) -> 0.462 | L53: =T53*$T$5 -> #REF! | M53: =ROUND(L53*K53,0) -> #REF! | N53: =U53*$T$5 -> #REF! | O53: =ROUND(N53*K53,0) -> #REF! | Q53: =O53+M53 -> #REF!
B54: D1-17 | C54: 100x300(-0.150) | E54: 1 | F54: 1.7 | G54: 0.3 | H54: 0.35 | J54: =PRODUCT(E54:I54) -> 0.1785 | L54: =T54*$T$5 -> #REF! | M54: =ROUND(L54*K54,0) -> #REF! | N54: =U54*$T$5 -> #REF! | O54: =ROUND(N54*K54,0) -> #REF! | Q54: =O54+M54 -> #REF!
B55: D1-18 | C55: 200x300(-0.150) | E55: 1 | F55: 3.2 | G55: 0.4 | H55: 0.35 | J55: =PRODUCT(E55:I55) -> 0.448 | L55: =T55*$T$5 -> #REF! | M55: =ROUND(L55*K55,0) -> #REF! | N55: =U55*$T$5 -> #REF! | O55: =ROUND(N55*K55,0) -> #REF! | Q55: =O55+M55 -> #REF!
B56: D1-19 | C56: 200x400 | E56: 1 | F56: 7.3 | G56: 0.4 | H56: 0.15 | J56: =PRODUCT(E56:I56) -> 0.438 | L56: =T56*$T$5 -> #REF! | M56: =ROUND(L56*K56,0) -> #REF! | N56: =U56*$T$5 -> #REF! | O56: =ROUND(N56*K56,0) -> #REF! | Q56: =O56+M56 -> #REF!
B57: D1-19a | C57: 200x400(-0.150) | E57: 1 | F57: 7 | G57: 0.4 | H57: 0.45 | J57: =PRODUCT(E57:I57) -> 1.26 | L57: =T57*$T$5 -> #REF! | M57: =ROUND(L57*K57,0) -> #REF! | N57: =U57*$T$5 -> #REF! | O57: =ROUND(N57*K57,0) -> #REF! | Q57: =O57+M57 -> #REF!
B58: D1-20 | C58: 200x400 | E58: 1 | F58: 1.8 | G58: 0.4 | H58: 0.15 | J58: =PRODUCT(E58:I58) -> 0.108 | L58: =T58*$T$5 -> #REF! | M58: =ROUND(L58*K58,0) -> #REF! | N58: =U58*$T$5 -> #REF! | O58: =ROUND(N58*K58,0) -> #REF! | Q58: =O58+M58 -> #REF!
B59: D1-21 | C59: 250x300 | E59: 1 | F59: 1.8 | G59: 0.45 | H59: 0.05 | J59: =PRODUCT(E59:I59) -> 0.0405 | L59: =T59*$T$5 -> #REF! | M59: =ROUND(L59*K59,0) -> #REF! | N59: =U59*$T$5 -> #REF! | O59: =ROUND(N59*K59,0) -> #REF! | Q59: =O59+M59 -> #REF!
B60: D1-22 | C60: 200x200(-0.400) | E60: 1 | F60: 1.3 | G60: 0.4 | H60: 0.1 | J60: =PRODUCT(E60:I60) -> 0.052 | L60: =T60*$T$5 -> #REF! | M60: =ROUND(L60*K60,0) -> #REF! | N60: =U60*$T$5 -> #REF! | O60: =ROUND(N60*K60,0) -> #REF! | Q60: =O60+M60 -> #REF!
B61: D1-23 | C61: 200x350 | E61: 2 | F61: 2.1 | G61: 0.4 | H61: 0.05 | J61: =PRODUCT(E61:I61) -> 0.084 | L61: =T61*$T$5 -> #REF! | M61: =ROUND(L61*K61,0) -> #REF! | N61: =U61*$T$5 -> #REF! | O61: =ROUND(N61*K61,0) -> #REF! | Q61: =O61+M61 -> #REF!
... B63: D1-24 | C63: 200x350 | E63: 1 | F63: 5.5 | G63: 0.4 | H63: 0.05 | J63: =PRODUCT(E63:I63) -> 0.11 | L63: =T63*$T$5 -> #REF! | M63: =ROUND(L63*K63,0) -> #REF! | N63: =U63*$T$5 -> #REF! | O63: =ROUND(N63*K63,0) -> #REF! | Q63: =O63+M63 -> #REF!
A64: 2 | B64: Backfilling soil for foundation/ Lấp đất móng | C64: Compact layer by layer, each layer 0.3m | D64: m3 | K64: =K19-K133-K178-K191 -> 297.46569 | L64: =T64*$T$5 -> #REF! | M64: =ROUND(L64*K64,0) -> #REF! | N64: =U64*$T$5 -> #REF! | O64: =ROUND(N64*K64,0) -> #REF! | P64: =N64+L64 -> #REF! | Q64: =O64+M64 -> #REF! | U64: 55000
A65: 3 | B65: Remove surplus soil/ Vận chuyển đất dư | C65: Distance D<=1Km | D65: m3 | K65: =K19-K64 -> 51.747806 | L65: =T65*$T$5 -> #REF! | M65: =ROUND(L65*K65,0) -> #REF! | N65: =U65*$T$5 -> #REF! | O65: =ROUND(N65*K65,0) -> #REF! | P65: =N65+L65 -> #REF! | Q65: =O65+M65 -> #REF! | U65: 28000
A66: 4 | B66: Natural soil well compacted, k = 0.95/ Đầm chặt nền đất | D66: m2 | K66: =SUM(J67:J80) -> 215.035 | L66: =T66*$T$5 -> #REF! | M66: =ROUND(L66*K66,0) -> #REF! | N66: =U66*$T$5 -> #REF! | O66: =ROUND(N66*K66,0) -> #REF! | P66: =N66+L66 -> #REF! | Q66: =O66+M66 -> #REF! | U66: 19000
B67: Hack trên bản vẽ | I67: 66.575 | J67: =PRODUCT(E67:I67) -> 66.575 | L67: =T67*$T$5 -> #REF! | M67: =ROUND(L67*K67,0) -> #REF! | N67: =U67*$T$5 -> #REF! | O67: =ROUND(N67*K67,0) -> #REF! | Q67: =O67+M67 -> #REF!
I68: 2.43 | J68: =PRODUCT(E68:I68) -> 2.43 | L68: =T68*$T$5 -> #REF! | M68: =ROUND(L68*K68,0) -> #REF! | N68: =U68*$T$5 -> #REF! | O68: =ROUND(N68*K68,0) -> #REF! | Q68: =O68+M68 -> #REF!
I69: 18.98 | J69: =PRODUCT(E69:I69) -> 18.98 | L69: =T69*$T$5 -> #REF! | M69: =ROUND(L69*K69,0) -> #REF! | N69: =U69*$T$5 -> #REF! | O69: =ROUND(N69*K69,0) -> #REF! | Q69: =O69+M69 -> #REF!
I70: 51.22 | J70: =PRODUCT(E70:I70) -> 51.22 | L70: =T70*$T$5 -> #REF! | M70: =ROUND(L70*K70,0) -> #REF! | N70: =U70*$T$5 -> #REF! | O70: =ROUND(N70*K70,0) -> #REF! | Q70: =O70+M70 -> #REF!
I71: 4 | J71: =PRODUCT(E71:I71) -> 4 | L71: =T71*$T$5 -> #REF! | M71: =ROUND(L71*K71,0) -> #REF! | N71: =U71*$T$5 -> #REF! | O71: =ROUND(N71*K71,0) -> #REF! | Q71: =O71+M71 -> #REF!
I72: 7.29 | J72: =PRODUCT(E72:I72) -> 7.29 | L72: =T72*$T$5 -> #REF! | M72: =ROUND(L72*K72,0) -> #REF! | N72: =U72*$T$5 -> #REF! | O72: =ROUND(N72*K72,0) -> #REF! | Q72: =O72+M72 -> #REF!
I73: 2.17 | J73: =PRODUCT(E73:I73) -> 2.17 | L73: =T73*$T$5 -> #REF! | M73: =ROUND(L73*K73,0) -> #REF! | N73: =U73*$T$5 -> #REF! | O73: =ROUND(N73*K73,0) -> #REF! | Q73: =O73+M73 -> #REF!
I74: 2.84 | J74: =PRODUCT(E74:I74) -> 2.84 | L74: =T74*$T$5 -> #REF! | M74: =ROUND(L74*K74,0) -> #REF! | N74: =U74*$T$5 -> #REF! | O74: =ROUND(N74*K74,0) -> #REF! | Q74: =O74+M74 -> #REF!
I75: =13.69-1.6*0.2 -> 13.37 | J75: =PRODUCT(E75:I75) -> 13.37 | L75: =T75*$T$5 -> #REF! | M75: =ROUND(L75*K75,0) -> #REF! | N75: =U75*$T$5 -> #REF! | O75: =ROUND(N75*K75,0) -> #REF! | Q75: =O75+M75 -> #REF!
I76: 11.55 | J76: =PRODUCT(E76:I76) -> 11.55 | L76: =T76*$T$5 -> #REF! | M76: =ROUND(L76*K76,0) -> #REF! | N76: =U76*$T$5 -> #REF! | O76: =ROUND(N76*K76,0) -> #REF! | Q76: =O76+M76 -> #REF!
I77: 12.96 | J77: =PRODUCT(E77:I77) -> 12.96 | L77: =T77*$T$5 -> #REF! | M77: =ROUND(L77*K77,0) -> #REF! | N77: =U77*$T$5 -> #REF! | O77: =ROUND(N77*K77,0) -> #REF! | Q77: =O77+M77 -> #REF!
I78: =17.53-0.1*2 -> 17.33 | J78: =PRODUCT(E78:I78) -> 17.33 | L78: =T78*$T$5 -> #REF! | M78: =ROUND(L78*K78,0) -> #REF! | N78: =U78*$T$5 -> #REF! | O78: =ROUND(N78*K78,0) -> #REF! | Q78: =O78+M78 -> #REF!
I79: =1.2*0.4 -> 0.48 | J79: =PRODUCT(E79:I79) -> 0.48 | L79: =T79*$T$5 -> #REF! | M79: =ROUND(L79*K79,0) -> #REF! | N79: =U79*$T$5 -> #REF! | O79: =ROUND(N79*K79,0) -> #REF! | Q79: =O79+M79 -> #REF!
I80: =3.84 -> 3.84 | J80: =PRODUCT(E80:I80) -> 3.84 | L80: =T80*$T$5 -> #REF! | M80: =ROUND(L80*K80,0) -> #REF! | N80: =U80*$T$5 -> #REF! | O80: =ROUND(N80*K80,0) -> #REF! | Q80: =O80+M80 -> #REF!
A81: 5 | B81: Foundation, ground beam soil well compacted, k = 0.95/ Đầm chặt đất móng, đà kiềng | D81: m2 | K81: =SUBTOTAL(9,J82:J124) -> 180.26 | L81: =T81*$T$5 -> #REF! | M81: =ROUND(L81*K81,0) -> #REF! | N81: =U81*$T$5 -> #REF! | O81: =ROUND(N81*K81,0) -> #REF! | P81: =N81+L81 -> #REF! | Q81: =O81+M81 -> #REF! | U81: 22000
B82: Foundation | L82: =T82*$T$5 -> #REF! | M82: =ROUND(L82*K82,0) -> #REF! | N82: =U82*$T$5 -> #REF! | O82: =ROUND(N82*K82,0) -> #REF! | Q82: =O82+M82 -> #REF!
B83: M1 | C83: 0 | D83: 0 | E83: =E21 -> 1 | F83: =F21 -> 1 | G83: =G21 -> 1 | J83: =PRODUCT(E83:I83) -> 1 | L83: =T83*$T$5 -> #REF! | M83: =ROUND(L83*K83,0) -> #REF! | N83: =U83*$T$5 -> #REF! | O83: =ROUND(N83*K83,0) -> #REF! | Q83: =O83+M83 -> #REF!
B84: M2 | C84: 0 | D84: 0 | E84: =E22 -> 1 | F84: =F22 -> 1.6 | G84: =G22 -> 1.6 | J84: =PRODUCT(E84:I84) -> 2.56 | L84: =T84*$T$5 -> #REF! | M84: =ROUND(L84*K84,0) -> #REF! | N84: =U84*$T$5 -> #REF! | O84: =ROUND(N84*K84,0) -> #REF! | Q84: =O84+M84 -> #REF!
B85: M3 | C85: 0 | D85: 0 | E85: =E23 -> 2 | F85: =F23 -> 1.8 | G85: =G23 -> 1.8 | J85: =PRODUCT(E85:I85) -> 6.48 | L85: =T85*$T$5 -> #REF! | M85: =ROUND(L85*K85,0) -> #REF! | N85: =U85*$T$5 -> #REF! | O85: =ROUND(N85*K85,0) -> #REF! | Q85: =O85+M85 -> #REF!
B86: M4 | C86: 0 | D86: 0 | E86: =E24 -> 2 | F86: =F24 -> 2 | G86: =G24 -> 2 | J86: =PRODUCT(E86:I86) -> 8 | L86: =T86*$T$5 -> #REF! | M86: =ROUND(L86*K86,0) -> #REF! | N86: =U86*$T$5 -> #REF! | O86: =ROUND(N86*K86,0) -> #REF! | Q86: =O86+M86 -> #REF!
B87: M5 | C87: 0 | D87: 0 | E87: =E25 -> 3 | F87: =F25 -> 2.2 | G87: =G25 -> 2.2 | J87: =PRODUCT(E87:I87) -> 14.52 | L87: =T87*$T$5 -> #REF! | M87: =ROUND(L87*K87,0) -> #REF! | N87: =U87*$T$5 -> #REF! | O87: =ROUND(N87*K87,0) -> #REF! | Q87: =O87+M87 -> #REF!
B88: M6 | C88: 0 | D88: 0 | E88: =E26 -> 5 | F88: =F26 -> 2.4 | G88: =G26 -> 2.4 | J88: =PRODUCT(E88:I88) -> 28.8 | L88: =T88*$T$5 -> #REF! | M88: =ROUND(L88*K88,0) -> #REF! | N88: =U88*$T$5 -> #REF! | O88: =ROUND(N88*K88,0) -> #REF! | Q88: =O88+M88 -> #REF!
B89: M7 | C89: 0 | D89: 0 | E89: =E27 -> 3 | F89: =F27 -> 2.6 | G89: =G27 -> 2.6 | J89: =PRODUCT(E89:I89) -> 20.28 | L89: =T89*$T$5 -> #REF! | M89: =ROUND(L89*K89,0) -> #REF! | N89: =U89*$T$5 -> #REF! | O89: =ROUND(N89*K89,0) -> #REF! | Q89: =O89+M89 -> #REF!
B90: M8 | C90: 0 | D90: 0 | E90: =E28 -> 2 | F90: =F28 -> 2.8 | G90: =G28 -> 2.8 | J90: =PRODUCT(E90:I90) -> 15.68 | L90: =T90*$T$5 -> #REF! | M90: =ROUND(L90*K90,0) -> #REF! | N90: =U90*$T$5 -> #REF! | O90: =ROUND(N90*K90,0) -> #REF! | Q90: =O90+M90 -> #REF!
B91: M9 | C91: 0 | D91: 0 | E91: =E29 -> 1 | F91: =F29 -> 2.6 | G91: =G29 -> 4.2 | J91: =PRODUCT(E91:I91) -> 10.92 | L91: =T91*$T$5 -> #REF! | M91: =ROUND(L91*K91,0) -> #REF! | N91: =U91*$T$5 -> #REF! | O91: =ROUND(N91*K91,0) -> #REF! | Q91: =O91+M91 -> #REF!
B92: M10 | C92: 0 | D92: 0 | E92: =E30 -> 1 | F92: =F30 -> 2.4 | G92: =G30 -> 3.2 | J92: =PRODUCT(E92:I92) -> 7.68 | L92: =T92*$T$5 -> #REF! | M92: =ROUND(L92*K92,0) -> #REF! | N92: =U92*$T$5 -> #REF! | O92: =ROUND(N92*K92,0) -> #REF! | Q92: =O92+M92 -> #REF!
B93: Ground beam | L93: =T93*$T$5 -> #REF! | M93: =ROUND(L93*K93,0) -> #REF! | N93: =U93*$T$5 -> #REF! | O93: =ROUND(N93*K93,0) -> #REF! | Q93: =O93+M93 -> #REF!
B94: D1-1 | E94: =E32 -> 1 | F94: =F32 -> 15.4 | G94: =G32 -> 0.4 | J94: =PRODUCT(E94:I94) -> 6.16 | L94: =T94*$T$5 -> #REF! | M94: =ROUND(L94*K94,0) -> #REF! | N94: =U94*$T$5 -> #REF! | O94: =ROUND(N94*K94,0) -> #REF! | Q94: =O94+M94 -> #REF!
B95: D1-1a | E95: =E33 -> 1 | F95: =F33 -> 3.8 | G95: =G33 -> 0.4 | J95: =PRODUCT(E95:I95) -> 1.52 | L95: =T95*$T$5 -> #REF! | M95: =ROUND(L95*K95,0) -> #REF! | N95: =U95*$T$5 -> #REF! | O95: =ROUND(N95*K95,0) -> #REF! | Q95: =O95+M95 -> #REF!
B96: D1-2 | E96: =E34 -> 1 | F96: =F34 -> 8.75 | G96: =G34 -> 0.4 | J96: =PRODUCT(E96:I96) -> 3.5 | L96: =T96*$T$5 -> #REF! | M96: =ROUND(L96*K96,0) -> #REF! | N96: =U96*$T$5 -> #REF! | O96: =ROUND(N96*K96,0) -> #REF! | Q96: =O96+M96 -> #REF!
B97: D1-2a | E97: =E35 -> 1 | F97: =F35 -> 3.8 | G97: =G35 -> 0.4 | J97: =PRODUCT(E97:I97) -> 1.52 | L97: =T97*$T$5 -> #REF! | M97: =ROUND(L97*K97,0) -> #REF! | N97: =U97*$T$5 -> #REF! | O97: =ROUND(N97*K97,0) -> #REF! | Q97: =O97+M97 -> #REF!
B98: D1-3 | E98: =E36 -> 1 | F98: =F36 -> 5.8 | G98: =G36 -> 0.4 | J98: =PRODUCT(E98:I98) -> 2.32 | L98: =T98*$T$5 -> #REF! | M98: =ROUND(L98*K98,0) -> #REF! | N98: =U98*$T$5 -> #REF! | O98: =ROUND(N98*K98,0) -> #REF! | Q98: =O98+M98 -> #REF!
B99: D1-4 | E99: =E37 -> 1 | F99: =F37 -> 5.9 | G99: =G37 -> 0.4 | J99: =PRODUCT(E99:I99) -> 2.36 | L99: =T99*$T$5 -> #REF! | M99: =ROUND(L99*K99,0) -> #REF! | N99: =U99*$T$5 -> #REF! | O99: =ROUND(N99*K99,0) -> #REF! | Q99: =O99+M99 -> #REF!
B100: 0 | E100: =E38 -> 1 | F100: =F38 -> 4.4 | G100: =G38 -> 0.4 | J100: =PRODUCT(E100:I100) -> 1.76 | L100: =T100*$T$5 -> #REF! | M100: =ROUND(L100*K100,0) -> #REF! | N100: =U100*$T$5 -> #REF! | O100: =ROUND(N100*K100,0) -> #REF! | Q100: =O100+M100 -> #REF!
B101: D1-4a | E101: =E39 -> 1 | F101: =F39 -> 3.8 | G101: =G39 -> 0.4 | J101: =PRODUCT(E101:I101) -> 1.52 | L101: =T101*$T$5 -> #REF! | M101: =ROUND(L101*K101,0) -> #REF! | N101: =U101*$T$5 -> #REF! | O101: =ROUND(N101*K101,0) -> #REF! | Q101: =O101+M101 -> #REF!
B102: D1-5 | E102: =E40 -> 1 | F102: =F40 -> 19 | G102: =G40 -> 0.4 | J102: =PRODUCT(E102:I102) -> 7.6 | L102: =T102*$T$5 -> #REF! | M102: =ROUND(L102*K102,0) -> #REF! | N102: =U102*$T$5 -> #REF! | O102: =ROUND(N102*K102,0) -> #REF! | Q102: =O102+M102 -> #REF!
...

Sheet C03.CSA_ANCILLARAY
A1: ESTIMATE DETAIL TABLE
A2: PROJECT/ DỰ ÁN : WAREHOUSE/NHÀ KHO
A3: ITEM/HẠNG MỤC : ANCILLARY ITEMS /HẠNG MỤC PHỤ
R4: VND
A5: No. | B5: DESCRIPTION | C5: STANDARD | D5: Unit | E5: DIMENSION | J5: QUANTITY | K5: Q'TY | L5: MATERIAL | N5: LABOUR & EQUIPMENT | P5: TOTAL COST(VND) | R5: REMARK | S5: ='C02.CSA_OFFICE'!S5 -> Profit | T5: ='C02.CSA_OFFICE'!T5 -> #REF!
E6: No | F6: L | G6: W | H6: H | I6: HS | J6: COMPONENT | L6: UNIT | M6: AMOUNT | N6: UNIT | O6: AMOUNT | P6: UNIT | Q6: AMOUNT | T6: ='C02.CSA_OFFICE'!T6 -> Vật tư | U6: ='C02.CSA_OFFICE'!U6 -> Nhân công
A7: C03 | B7: ANCILLARY ITEMS/ HẠNG MỤC PHỤ | M7: =SUBTOTAL(9,M8:M12) -> #REF! | O7: =SUBTOTAL(9,O8:O12) -> #REF! | P7: =SUBTOTAL(9,P8:P12) -> 0 | Q7: =SUBTOTAL(9,Q8:Q12) -> #REF!
A8: =A14 -> I | B8: WATER TANK/ BỂ NƯỚC | M8: =M14 -> #REF! | O8: =O14 -> #REF! | Q8: =O8+M8 -> #REF!
A9: =A110 -> II | B9: GUARD HOUSE/NHÀ BẢO VỆ | M9: =M110 -> #REF! | O9: =O110 -> #REF! | Q9: =O9+M9 -> #REF!
A10: =A341 -> III | B10: PUPM ROOM+TRASH ROOM/NHÀ BƠM +NHÀ RÁC | K10: =9000*6000 -> 54000000 | M10: =M341 -> #REF! | O10: =O341 -> #REF! | Q10: =O10+M10 -> #REF!
A11: =A495 -> IV | B11: FENCE/ HÀNG RÀO | M11: =M495 -> #REF! | O11: =O495 -> #REF! | Q11: =O11+M11 -> #REF!
A12: =A604 -> V | B12: MOTOBIKE HOUSE / NHÀ XE MÁY | M12: =M604 -> #REF! | N12: =N604 -> 0 | O12: =O604 -> #REF! | Q12: =O12+M12 -> #REF!
A14: I | B14: WATER TANK/ BỂ NƯỚC | M14: =SUBTOTAL(109,M15:M109) -> #REF! | O14: =SUBTOTAL(109,O15:O109) -> #REF! | Q14: =O14+M14 -> #REF! | S14: m3 | T14: =234*2.8 -> 655.2
B15: EARTH WORK/ CÔNG TÁC ĐẤT
A16: 1 | B16: Excavation of Soil/ Công tác đào đất | C16: Soil grade 3 | D16: m3 | K16: =+SUBTOTAL(9,J17:J18) -> 870.455 | L16: =T16*$T$5 -> #REF! | M16: =ROUND(L16*K16,0) -> #REF! | N16: =U16*$T$5 -> #REF! | O16: =ROUND(N16*K16,0) -> #REF! | P16: =N16+L16 -> #REF! | Q16: =P16*K16 -> #REF! | T16: ='Bill 2-Main building works'!#REF! -> #REF! | U16: ='Bill 2-Main building works'!#REF! -> #REF!
B17: Dđào đất bể nước | E17: 1 | G17: 249.5 | H17: =3.45 -> 3.45 | J17: =PRODUCT(G17:I17) -> 860.775 | L17: =T17*$T$5 -> #REF! | M17: =ROUND(L17*K17,0) -> #REF! | N17: =U17*$T$5 -> #REF! | O17: =ROUND(N17*K17,0) -> #REF! | P17: =N17+L17 -> #REF! | Q17: =P17*K17 -> #REF!
B18: Móng đáy bể | E18: 8 | F18: 2.2 | G18: 2.2 | H18: 0.25 | J18: =PRODUCT(E18:I18) -> 9.68 | L18: =T18*$T$5 -> #REF! | M18: =ROUND(L18*K18,0) -> #REF! | N18: =U18*$T$5 -> #REF! | O18: =ROUND(N18*K18,0) -> #REF! | P18: =N18+L18 -> #REF! | Q18: =P18*K18 -> #REF!
A19: 2 | B19: Backfilling soil for foundation/ Lấp đất móng | D19: m3 | K19: =(K16-J20-J21) -> 42.78 | L19: =T19*$T$5 -> #REF! | M19: =ROUND(L19*K19,0) -> #REF! | N19: =U19*$T$5 -> #REF! | O19: =ROUND(N19*K19,0) -> #REF! | P19: =N19+L19 -> #REF! | Q19: =P19*K19 -> #REF! | T19: ='Bill 2-Main building works'!#REF! -> #REF! | U19: ='Bill 2-Main building works'!#REF! -> #REF!
B20: bê tông lót | E20: 1 | G20: =K31 -> 24.95 | J20: =PRODUCT(E20:I20) -> 24.95 | L20: =T20*$T$5 -> #REF! | M20: =ROUND(L20*K20,0) -> #REF! | N20: =U20*$T$5 -> #REF! | O20: =ROUND(N20*K20,0) -> #REF! | P20: =N20+L20 -> #REF! | Q20: =P20*K20 -> #REF!
B21: bêể nước | E21: 1 | G21: 243.25 | H21: 3.3 | J21: =PRODUCT(E21:I21) -> 802.725 | L21: =T21*$T$5 -> #REF! | M21: =ROUND(L21*K21,0) -> #REF! | N21: =U21*$T$5 -> #REF! | O21: =ROUND(N21*K21,0) -> #REF! | P21: =N21+L21 -> #REF! | Q21: =P21*K21 -> #REF!
A22: 3 | B22: Remove surplus soil/ Vận chuyển đất dư | C22: Distance D<=1Km | D22: m3 | K22: =K16-K19 -> 827.675 | L22: =T22*$T$5 -> #REF! | M22: =ROUND(L22*K22,0) -> #REF! | N22: =U22*$T$5 -> #REF! | O22: =ROUND(N22*K22,0) -> #REF! | P22: =N22+L22 -> #REF! | Q22: =P22*K22 -> #REF! | T22: ='Bill 2-Main building works'!#REF! -> #REF! | U22: ='Bill 2-Main building works'!#REF! -> #REF!
A23: 4 | B23: Natural soil well compacted, k = 0.95/ Đầm chặt nền đất | D23: m2 | K23: =+SUBTOTAL(9,J24:J25) -> 249.5 | L23: =T23*$T$5 -> #REF! | M23: =ROUND(L23*K23,0) -> #REF! | N23: =U23*$T$5 -> #REF! | O23: =ROUND(N23*K23,0) -> #REF! | P23: =N23+L23 -> #REF! | Q23: =P23*K23 -> #REF! | T23: ='Bill 2-Main building works'!#REF! -> #REF! | U23: ='Bill 2-Main building works'!#REF! -> #REF!
B24: đáy bể | E24: 1 | J24: =G17 -> 249.5 | L24: =T24*$T$5 -> #REF! | M24: =ROUND(L24*K24,0) -> #REF! | N24: =U24*$T$5 -> #REF! | O24: =ROUND(N24*K24,0) -> #REF! | P24: =N24+L24 -> #REF! | Q24: =P24*K24 -> #REF!
L25: =T25*$T$5 -> #REF! | M25: =ROUND(L25*K25,0) -> #REF! | N25: =U25*$T$5 -> #REF! | O25: =ROUND(N25*K25,0) -> #REF! | P25: =N25+L25 -> #REF! | Q25: =P25*K25 -> #REF!
A26: 6 | B26: PVC sheet/ Lớp PVC | C26: PVC 0.3mm | D26: m2 | K26: =G17 -> 249.5 | L26: =T26*$T$5 -> #REF! | M26: =ROUND(L26*K26,0) -> #REF! | N26: =U26*$T$5 -> #REF! | O26: =ROUND(N26*K26,0) -> #REF! | P26: =N26+L26 -> #REF! | Q26: =P26*K26 -> #REF! | T26: ='Bill 2-Main building works'!#REF! -> #REF! | U26: ='Bill 2-Main building works'!#REF! -> #REF!
B27: ANTI TERMITE TREATMENT/ CHỐNG MỐI | M27: =SUM(M28) -> 0 | O27: =SUM(O28) -> 0 | Q27: =O27+M27 -> 0
A28: 1 | B28: Pre-treatment of basement ground surface/ Chống mối cho nền | C28: ='C02.CSA_OFFICE'!C129 -> Termize 200sc solution 0.25%, 5 liters/m2 | D28: m2 | M28: =L28*K28 -> 0 | O28: =N28*K28 -> 0 | P28: =N28+L28 -> 0 | Q28: =O28+M28 -> 0 | R28: Exclude
B29: REINFORCED CONCRETE WORK/ BÊ TÔNG CỐT THÉP
A30: * | B30: Concrete work/ Công tác bê tông
A31: 1 | B31: Lean concrete/ Bê tông lót | C31: Grade B7.5 | D31: m3 | K31: =+SUBTOTAL(9,J32) -> 24.95 | L31: =T31*$T$5 -> #REF! | M31: =ROUND(L31*K31,0) -> #REF! | N31: =U31*$T$5 -> #REF! | O31: =ROUND(N31*K31,0) -> #REF! | P31: =N31+L31 -> #REF! | Q31: =P31*K31 -> #REF! | T31: ='Bill 2-Main building works'!#REF! -> #REF! | U31: ='Bill 2-Main building works'!#REF! -> #REF!
G32: =G17 -> 249.5 | H32: 0.1 | I32: 1 | J32: =PRODUCT(E32:I32) -> 24.95 | L32: =T32*$T$5 -> #REF! | M32: =ROUND(L32*K32,0) -> #REF! | N32: =U32*$T$5 -> #REF! | O32: =ROUND(N32*K32,0) -> #REF! | P32: =N32+L32 -> #REF! | Q32: =P32*K32 -> #REF!
A33: 2 | B33: Bottom slab/ Bê tông bản đáy | C33: Grade B25 | D33: m3 | K33: =+SUBTOTAL(9,J34:J35) -> 81 | L33: =T33*$T$5 -> #REF! | M33: =ROUND(L33*K33,0) -> #REF! | N33: =U33*$T$5 -> #REF! | O33: =ROUND(N33*K33,0) -> #REF! | P33: =N33+L33 -> #REF! | Q33: =P33*K33 -> #REF! | T33: ='Bill 2-Main building works'!#REF! -> #REF! | U33: ='Bill 2-Main building works'!#REF! -> #REF!
E34: 1 | G34: 243 | H34: 0.25 | I34: 1 | J34: =PRODUCT(E34:I34) -> 60.75 | L34: =T34*$T$5 -> #REF! | M34: =ROUND(L34*K34,0) -> #REF! | N34: =U34*$T$5 -> #REF! | O34: =ROUND(N34*K34,0) -> #REF! | P34: =N34+L34 -> #REF! | Q34: =P34*K34 -> #REF!
B35: 0 | E35: 8 | F35: =(2.5+2)/2 -> 2.25 | G35: =(2.5+2)/2 -> 2.25 | H35: 0.5 | I35: 1 | J35: =PRODUCT(E35:I35) -> 20.25 | L35: =T35*$T$5 -> #REF! | M35: =ROUND(L35*K35,0) -> #REF! | N35: =U35*$T$5 -> #REF! | O35: =ROUND(N35*K35,0) -> #REF! | P35: =N35+L35 -> #REF! | Q35: =P35*K35 -> #REF!
A36: 3 | B36: Wall/ Bê tông tường bể | C36: Grade B25 | D36: m3 | K36: =+SUBTOTAL(9,J37) -> 46.871875 | L36: =T36*$T$5 -> #REF! | M36: =ROUND(L36*K36,0) -> #REF! | N36: =U36*$T$5 -> #REF! | O36: =ROUND(N36*K36,0) -> #REF! | P36: =N36+L36 -> #REF! | Q36: =P36*K36 -> #REF! | T36: =T33 -> #REF! | U36: =U33 -> #REF!
B37: Tbn1 | E37: 1 | F37: =18.7+8.5+15.6+4.7+21.85+1.4 -> 70.75 | G37: 0.25 | H37: 2.65 | I37: 1 | J37: =PRODUCT(E37:I37) -> 46.871875 | L37: =T37*$T$5 -> #REF! | M37: =ROUND(L37*K37,0) -> #REF! | N37: =U37*$T$5 -> #REF! | O37: =ROUND(N37*K37,0) -> #REF! | P37: =N37+L37 -> #REF! | Q37: =P37*K37 -> #REF!
B38: Tbn2 | E38: 1 | F38: 12 | G38: 0.25 | H38: 2.95 | I38: 1 | J38: =PRODUCT(E38:I38) -> 8.85 | L38: =T38*$T$5 -> #REF! | M38: =ROUND(L38*K38,0) -> #REF! | N38: =U38*$T$5 -> #REF! | O38: =ROUND(N38*K38,0) -> #REF! | P38: =N38+L38 -> #REF! | Q38: =P38*K38 -> #REF!
B39: Góc vát chân | E39: 1 | F39: =F38+F37 -> 82.75 | G39: 0.25 | H39: 0.25 | I39: 1 | J39: =PRODUCT(E39:I39)/2 -> 2.5859375 | L39: =T39*$T$5 -> #REF! | M39: =ROUND(L39*K39,0) -> #REF! | N39: =U39*$T$5 -> #REF! | O39: =ROUND(N39*K39,0) -> #REF! | P39: =N39+L39 -> #REF! | Q39: =P39*K39 -> #REF!
B40: góc vát đứng | E40: 3 | F40: 0.25 | G40: 0.25 | H40: 2.65 | I40: 1 | J40: =PRODUCT(E40:I40)/2 -> 0.2484375 | L40: =T40*$T$5 -> #REF! | M40: =ROUND(L40*K40,0) -> #REF! | N40: =U40*$T$5 -> #REF! | O40: =ROUND(N40*K40,0) -> #REF! | P40: =N40+L40 -> #REF! | Q40: =P40*K40 -> #REF!
A41: 4 | B41: Column/ Bê tông cho cột | C41: Grade B25 | D41: m3 | K41: =+SUBTOTAL(9,J42:J44) -> 2.421875 | L41: =T41*$T$5 -> #REF! | M41: =ROUND(L41*K41,0) -> #REF! | N41: =U41*$T$5 -> #REF! | O41: =ROUND(N41*K41,0) -> #REF! | P41: =N41+L41 -> #REF! | Q41: =P41*K41 -> #REF! | T41: =T36 -> #REF! | U41: =U36 -> #REF!
B42: Cột C1 | E42: 11 | F42: 0.25 | G42: 0.25 | H42: 3 | I42: 1 | J42: =PRODUCT(E42:I42) -> 2.0625 | L42: =T42*$T$5 -> #REF! | M42: =ROUND(L42*K42,0) -> #REF! | N42: =U42*$T$5 -> #REF! | O42: =ROUND(N42*K42,0) -> #REF! | P42: =N42+L42 -> #REF! | Q42: =P42*K42 -> #REF!
B43: Cột C2 | E43: 1 | F43: 0.25 | G43: 0.25 | H43: 3 | I43: 1 | J43: =PRODUCT(E43:I43) -> 0.1875 | L43: =T43*$T$5 -> #REF! | M43: =ROUND(L43*K43,0) -> #REF! | N43: =U43*$T$5 -> #REF! | O43: =ROUND(N43*K43,0) -> #REF! | P43: =N43+L43 -> #REF! | Q43: =P43*K43 -> #REF!
B44: Cột C3 | E44: 1 | F44: 0.25 | G44: 0.25 | H44: 2.75 | I44: 1 | J44: =PRODUCT(E44:I44) -> 0.171875 | L44: =T44*$T$5 -> #REF! | M44: =ROUND(L44*K44,0) -> #REF! | N44: =U44*$T$5 -> #REF! | O44: =ROUND(N44*K44,0) -> #REF! | P44: =N44+L44 -> #REF! | Q44: =P44*K44 -> #REF!
A45: 5 | B45: Top slab / Bê tông bản nắp | C45: =C33 -> Grade B25 | D45: m3 | K45: =+SUBTOTAL(9,J46:J54) -> 43.8975 | L45: =T45*$T$5 -> #REF! | M45: =ROUND(L45*K45,0) -> #REF! | N45: =U45*$T$5 -> #REF! | O45: =ROUND(N45*K45,0) -> #REF! | P45: =N45+L45 -> #REF! | Q45: =P45*K45 -> #REF! | T45: =T41 -> #REF! | U45: =U41 -> #REF!
B46: Nắp bể | E46: 1 | G46: =243.25-90 -> 153.25 | H46: 0.15 | I46: 1 | J46: =PRODUCT(E46:I46) -> 22.9875 | L46: =T46*$T$5 -> #REF! | M46: =ROUND(L46*K46,0) -> #REF! | N46: =U46*$T$5 -> #REF! | O46: =ROUND(N46*K46,0) -> #REF! | P46: =N46+L46 -> #REF! | Q46: =P46*K46 -> #REF!
E47: 1 | G47: 90 | H47: 0.2 | I47: 1 | J47: =PRODUCT(E47:I47) -> 18 | L47: =T47*$T$5 -> #REF! | M47: =ROUND(L47*K47,0) -> #REF! | N47: =U47*$T$5 -> #REF! | O47: =ROUND(N47*K47,0) -> #REF! | P47: =N47+L47 -> #REF! | Q47: =P47*K47 -> #REF!
E48: 1 | F48: 2 | G48: 2 | H48: 0.15 | I48: 1 | J48: =PRODUCT(E48:I48) -> 0.6 | L48: =T48*$T$5 -> #REF! | M48: =ROUND(L48*K48,0) -> #REF! | N48: =U48*$T$5 -> #REF! | O48: =ROUND(N48*K48,0) -> #REF! | P48: =N48+L48 -> #REF! | Q48: =P48*K48 -> #REF!
B49: Trừ nắp thăm | E49: -2 | F49: 0.6 | G49: 0.6 | H49: 0.2 | J49: =PRODUCT(E49:I49) -> -0.144 | L49: =T49*$T$5 -> #REF! | M49: =ROUND(L49*K49,0) -> #REF! | N49: =U49*$T$5 -> #REF! | O49: =ROUND(N49*K49,0) -> #REF! | P49: =N49+L49 -> #REF! | Q49: =P49*K49 -> #REF!
B50: Đà nắp | L50: =T50*$T$5 -> #REF! | M50: =ROUND(L50*K50,0) -> #REF! | N50: =U50*$T$5 -> #REF! | O50: =ROUND(N50*K50,0) -> #REF! | P50: =N50+L50 -> #REF! | Q50: =P50*K50 -> #REF!
B51: D1-1 (20x50) | E51: 1 | F51: =12-0.25*4 -> 11 | G51: 0.2 | H51: =0.5-0.2 -> 0.3 | I51: 1 | J51: =PRODUCT(E51:I51) -> 0.66 | L51: =T51*$T$5 -> #REF! | M51: =ROUND(L51*K51,0) -> #REF! | N51: =U51*$T$5 -> #REF! | O51: =ROUND(N51*K51,0) -> #REF! | P51: =N51+L51 -> #REF! | Q51: =P51*K51 -> #REF!
B52: D1-2(20x40) | E52: 1 | F52: =12-0.25*4 -> 11 | G52: 0.2 | H52: 0.2 | I52: 1 | J52: =PRODUCT(E52:I52) -> 0.44 | L52: =T52*$T$5 -> #REF! | M52: =ROUND(L52*K52,0) -> #REF! | N52: =U52*$T$5 -> #REF! | O52: =ROUND(N52*K52,0) -> #REF! | P52: =N52+L52 -> #REF! | Q52: =P52*K52 -> #REF!
B53: D1-3 (20x50) | E53: 2 | F53: =7.25-0.25*2 -> 6.75 | G53: 0.2 | H53: 0.3 | I53: 1 | J53: =PRODUCT(E53:I53) -> 0.81 | L53: =T53*$T$5 -> #REF! | M53: =ROUND(L53*K53,0) -> #REF! | N53: =U53*$T$5 -> #REF! | O53: =ROUND(N53*K53,0) -> #REF! | P53: =N53+L53 -> #REF! | Q53: =P53*K53 -> #REF!
B54: D1-4 (20x40) | E54: 2 | F54: =7.05-0.25 -> 6.8 | G54: 0.2 | H54: 0.2 | I54: 1 | J54: =PRODUCT(E54:I54) -> 0.544 | L54: =T54*$T$5 -> #REF! | M54: =ROUND(L54*K54,0) -> #REF! | N54: =U54*$T$5 -> #REF! | O54: =ROUND(N54*K54,0) -> #REF! | P54: =N54+L54 -> #REF! | Q54: =P54*K54 -> #REF!
B55: cổ nắp thăm | E55: 2 | F55: =(0.6+0.8)*2 -> 2.8 | G55: 0.3 | H55: 0.1 | I55: 1 | J55: =PRODUCT(E55:I55) -> 0.168 | L55: =T55*$T$5 -> #REF! | M55: =ROUND(L55*K55,0) -> #REF! | N55: =U55*$T$5 -> #REF! | O55: =ROUND(N55*K55,0) -> #REF! | P55: =N55+L55 -> #REF! | Q55: =P55*K55 -> #REF!
L56: =T56*$T$5 -> #REF! | M56: =ROUND(L56*K56,0) -> #REF! | N56: =U56*$T$5 -> #REF! | O56: =ROUND(N56*K56,0) -> #REF! | P56: =N56+L56 -> #REF! | Q56: =P56*K56 -> #REF!
A57: * | B57: Formwork/ Ván Khuôn
A58: 6 | B58: Lean concrete/ Ván khuôn bê tông lót | C58: Steel standard & Fly wood form | D58: m2 | K58: =+SUBTOTAL(9,J59) -> 6.42 | L58: =T58*$T$5 -> #REF! | M58: =ROUND(L58*K58,0) -> #REF! | N58: =U58*$T$5 -> #REF! | O58: =ROUND(N58*K58,0) -> #REF! | P58: =N58+L58 -> #REF! | Q58: =P58*K58 -> #REF! | T58: ='Bill 2-Main building works'!#REF! -> #REF! | U58: ='Bill 2-Main building works'!#REF! -> #REF!
E59: 1 | F59: 64.2 | H59: 0.1 | I59: 1 | J59: =PRODUCT(E59:I59) -> 6.42 | L59: =T59*$T$5 -> #REF! | M59: =ROUND(L59*K59,0) -> #REF! | N59: =U59*$T$5 -> #REF! | O59: =ROUND(N59*K59,0) -> #REF! | P59: =N59+L59 -> #REF! | Q59: =P59*K59 -> #REF!
A60: 7 | B60: Bottom slab/ Ván khuôn bản đáy | C60: Steel standard & Fly wood form | D60: m2 | K60: =+SUBTOTAL(9,J61:J62) -> 26.89625 | L60: =T60*$T$5 -> #REF! | M60: =ROUND(L60*K60,0) -> #REF! | N60: =U60*$T$5 -> #REF! | O60: =ROUND(N60*K60,0) -> #REF! | P60: =N60+L60 -> #REF! | Q60: =P60*K60 -> #REF! | T60: =T58 -> #REF! | U60: =U58 -> #REF!
B61: 0 | E61: =E35 -> 8 | F61: =15.5+18.9+8.5+15.825+4.7 -> 63.425 | H61: 0.25 | I61: 1 | J61: =F61*H61 -> 15.85625 | L61: =T61*$T$5 -> #REF! | M61: =ROUND(L61*K61,0) -> #REF! | N61: =U61*$T$5 -> #REF! | O61: =ROUND(N61*K61,0) -> #REF! | P61: =N61+L61 -> #REF! | Q61: =P61*K61 -> #REF!
B62: Góc vác | E62: 8 | H62: 0.345 | J62: =E62*H62*4 -> 11.04 | L62: =T62*$T$5 -> #REF! | M62: =ROUND(L62*K62,0) -> #REF! | N62: =U62*$T$5 -> #REF! | O62: =ROUND(N62*K62,0) -> #REF! | P62: =N62+L62 -> #REF! | Q62: =P62*K62 -> #REF!
A63: 8 | B63: Wall/ Ván khuôn thành bể | C63: Steel standard & Fly wood form | D63: m2 | K63: =+SUBTOTAL(9,J64:J67) -> 340.3005 | L63: =T63*$T$5 -> #REF! | M63: =ROUND(L63*K63,0) -> #REF! | N63: =U63*$T$5 -> #REF! | O63: =ROUND(N63*K63,0) -> #REF! | P63: =N63+L63 -> #REF! | Q63: =P63*K63 -> #REF! | T63: =T58 -> #REF! | U63: =U58 -> #REF!
B64: Tbn1 | E64: =E37 -> 1 | F64: 47.91 | H64: 2.8 | I64: 1 | J64: =F64*H64 -> 134.148 | L64: =T64*$T$5 -> #REF! | M64: =ROUND(L64*K64,0) -> #REF! | N64: =U64*$T$5 -> #REF! | O64: =ROUND(N64*K64,0) -> #REF! | P64: =N64+L64 -> #REF! | Q64: =P64*K64 -> #REF!
E65: 1 | F65: =F64 -> 47.91 | H65: 2.75 | I65: 1 | J65: =F65*H65 -> 131.7525 | L65: =T65*$T$5 -> #REF! | M65: =ROUND(L65*K65,0) -> #REF! | N65: =U65*$T$5 -> #REF! | O65: =ROUND(N65*K65,0) -> #REF! | P65: =N65+L65 -> #REF! | Q65: =P65*K65 -> #REF!
B66: Tbn2 | E66: =E38 -> 1 | F66: =F38 -> 12 | H66: =2.95+0.2 -> 3.15 | I66: 1 | J66: =F66*H66 -> 37.8 | L66: =T66*$T$5 -> #REF! | M66: =ROUND(L66*K66,0) -> #REF! | N66: =U66*$T$5 -> #REF! | O66: =ROUND(N66*K66,0) -> #REF! | P66: =N66+L66 -> #REF! | Q66: =P66*K66 -> #REF!
E67: 1 | F67: =F66 -> 12 | H67: =2.7+0.35 -> 3.05 | I67: 1 | J67: =F67*H67 -> 36.6 | L67: =T67*$T$5 -> #REF! | M67: =ROUND(L67*K67,0) -> #REF! | N67: =U67*$T$5 -> #REF! | O67: =ROUND(N67*K67,0) -> #REF! | P67: =N67+L67 -> #REF! | Q67: =P67*K67 -> #REF!
A68: 9 | B68: Column/ Ván khuôn cột | C68: Steel standard & Fly wood form | D68: m2 | K68: =+SUBTOTAL(9,J69:J71) -> 26.75 | L68: =T68*$T$5 -> #REF! | M68: =ROUND(L68*K68,0) -> #REF! | N68: =U68*$T$5 -> #REF! | O68: =ROUND(N68*K68,0) -> #REF! | P68: =N68+L68 -> #REF! | Q68: =P68*K68 -> #REF! | T68: =T60 -> #REF! | U68: =U60 -> #REF!
B69: Cột C1 | E69: 7 | F69: =F42 -> 0.25 | G69: =G42 -> 0.25 | H69: =H42 -> 3 | I69: =I42 -> 1 | J69: =E69*F69*H69*4 -> 21 | L69: =T69*$T$5 -> #REF! | M69: =ROUND(L69*K69,0) -> #REF! | N69: =U69*$T$5 -> #REF! | O69: =ROUND(N69*K69,0) -> #REF! | P69: =N69+L69 -> #REF! | Q69: =P69*K69 -> #REF!
B70: Cột C2 | E70: =E43 -> 1 | F70: =F43 -> 0.25 | G70: =G43 -> 0.25 | H70: =H43 -> 3 | I70: =I43 -> 1 | J70: =E70*F70*H70*4 -> 3 | L70: =T70*$T$5 -> #REF! | M70: =ROUND(L70*K70,0) -> #REF! | N70: =U70*$T$5 -> #REF! | O70: =ROUND(N70*K70,0) -> #REF! | P70: =N70+L70 -> #REF! | Q70: =P70*K70 -> #REF!
B71: Cột C3 | E71: =E44 -> 1 | F71: =F44 -> 0.25 | G71: =G44 -> 0.25 | H71: =H44 -> 2.75 | I71: =I44 -> 1 | J71: =E71*F71*H71*4 -> 2.75 | L71: =T71*$T$5 -> #REF! | M71: =ROUND(L71*K71,0) -> #REF! | N71: =U71*$T$5 -> #REF! | O71: =ROUND(N71*K71,0) -> #REF! | P71: =N71+L71 -> #REF! | Q71: =P71*K71 -> #REF!
A72: 10 | B72: Top slab/ Ván khuôn cho nắp bể | C72: Steel standard & Fly wood form | D72: m2 | E72: 1 | K72: =+SUBTOTAL(9,J73:J85) -> 300.25 | L72: =T72*$T$5 -> #REF! | M72: =ROUND(L72*K72,0) -> #REF! | N72: =U72*$T$5 -> #REF! | O72: =ROUND(N72*K72,0) -> #REF! | P72: =N72+L72 -> #REF! | Q72: =P72*K72 -> #REF! | T72: =T68 -> #REF! | U72: =U68 -> #REF!
B73: Nắp bể | C73: =C46 -> 0 | D73: =D46 -> 0 | E73: 1 | G73: =243.25-90 -> 153.25 | I73: 1 | J73: =PRODUCT(E73:I73) -> 153.25 | L73: =T73*$T$5 -> #REF! | M73: =ROUND(L73*K73,0) -> #REF! | N73: =U73*$T$5 -> #REF! | O73: =ROUND(N73*K73,0) -> #REF! | P73: =N73+L73 -> #REF! | Q73: =P73*K73 -> #REF!
E74: 1 | G74: 90 | I74: 1 | J74: =PRODUCT(E74:I74) -> 90 | L74: =T74*$T$5 -> #REF! | M74: =ROUND(L74*K74,0) -> #REF! | N74: =U74*$T$5 -> #REF! | O74: =ROUND(N74*K74,0) -> #REF! | P74: =N74+L74 -> #REF! | Q74: =P74*K74 -> #REF!
E75: 1 | F75: 2 | G75: 2 | H75: 0.15 | I75: 1 | J75: =F75*4*E75*H75*I75 -> 1.2 | L75: =T75*$T$5 -> #REF! | M75: =ROUND(L75*K75,0) -> #REF! | N75: =U75*$T$5 -> #REF! | O75: =ROUND(N75*K75,0) -> #REF! | P75: =N75+L75 -> #REF! | Q75: =P75*K75 -> #REF!
B76: Trừ nắp thăm | C76: =C49 -> 0 | D76: =D49 -> 0 | E76: =E49 -> -2 | F76: =F49 -> 0.6 | G76: =G49 -> 0.6 | J76: =PRODUCT(E76:I76) -> -0.72 | L76: =T76*$T$5 -> #REF! | M76: =ROUND(L76*K76,0) -> #REF! | N76: =U76*$T$5 -> #REF! | O76: =ROUND(N76*K76,0) -> #REF! | P76: =N76+L76 -> #REF! | Q76: =P76*K76 -> #REF!
B77: nắp thăm | E77: 2 | F77: 0.6 | H77: 0.15 | I77: 1 | J77: =F77*4*E77*H77*I77 -> 0.72 | L77: =T77*$T$5 -> #REF! | M77: =ROUND(L77*K77,0) -> #REF! | N77: =U77*$T$5 -> #REF! | O77: =ROUND(N77*K77,0) -> #REF! | P77: =N77+L77 -> #REF! | Q77: =P77*K77 -> #REF!
B78: Dầm nắp bể | L78: =T78*$T$5 -> #REF! | M78: =ROUND(L78*K78,0) -> #REF! | N78: =U78*$T$5 -> #REF! | O78: =ROUND(N78*K78,0) -> #REF! | P78: =N78+L78 -> #REF! | Q78: =P78*K78 -> #REF!
B79: D1-1 (20x50) | C79: =C51 -> 0 | D79: =D51 -> 0 | E79: 2 | F79: =F51 -> 11 | H79: =H51 -> 0.3 | I79: 1 | J79: =E79*F79*H79*2 -> 13.2 | L79: =T79*$T$5 -> #REF! | M79: =ROUND(L79*K79,0) -> #REF! | N79: =U79*$T$5 -> #REF! | O79: =ROUND(N79*K79,0) -> #REF! | P79: =N79+L79 -> #REF! | Q79: =P79*K79 -> #REF!
B80: D1-2(20x40) | C80: =C52 -> 0 | D80: =D52 -> 0 | E80: 2 | F80: =F52 -> 11 | H80: =H52 -> 0.2 | I80: =I52 -> 1 | J80: =E80*F80*H80*2 -> 8.8 | L80: =T80*$T$5 -> #REF! | M80: =ROUND(L80*K80,0) -> #REF! | N80: =U80*$T$5 -> #REF! | O80: =ROUND(N80*K80,0) -> #REF! | P80: =N80+L80 -> #REF! | Q80: =P80*K80 -> #REF!
B81: D1-3 (20x50) | C81: =C53 -> 0 | D81: =D53 -> 0 | E81: 4 | F81: =F53 -> 6.75 | H81: =H53 -> 0.3 | I81: =I53 -> 1 | J81: =E81*F81*H81*2 -> 16.2 | L81: =T81*$T$5 -> #REF! | M81: =ROUND(L81*K81,0) -> #REF! | N81: =U81*$T$5 -> #REF! | O81: =ROUND(N81*K81,0) -> #REF! | P81: =N81+L81 -> #REF! | Q81: =P81*K81 -> #REF!
B82: D1-4 (20x40) | C82: =C54 -> 0 | D82: =D54 -> 0 | E82: 4 | F82: =F54 -> 6.8 | H82: =H54 -> 0.2 | I82: =I54 -> 1 | J82: =E82*F82*H82*2 -> 10.88 | L82: =T82*$T$5 -> #REF! | M82: =ROUND(L82*K82,0) -> #REF! | N82: =U82*$T$5 -> #REF! | O82: =ROUND(N82*K82,0) -> #REF! | P82: =N82+L82 -> #REF! | Q82: =P82*K82 -> #REF!
B83: Cổ nắp thăm | E83: 2 | F83: =0.8*4 -> 3.2 | H83: 0.3 | I83: 1 | J83: =E83*F83*H83*2 -> 3.84 | L83: =T83*$T$5 -> #REF! | M83: =ROUND(L83*K83,0) -> #REF! | N83: =U83*$T$5 -> #REF! | O83: =ROUND(N83*K83,0) -> #REF! | P83: =N83+L83 -> #REF! | Q83: =P83*K83 -> #REF!
E84: 2 | F84: =0.6*4 -> 2.4 | H84: 0.3 | I84: 1 | J84: =E84*F84*H84*2 -> 2.88 | L84: =T84*$T$5 -> #REF! | M84: =ROUND(L84*K84,0) -> #REF! | N84: =U84*$T$5 -> #REF! | O84: =ROUND(N84*K84,0) -> #REF! | P84: =N84+L84 -> #REF! | Q84: =P84*K84 -> #REF!
L85: =T85*$T$5 -> #REF! | M85: =ROUND(L85*K85,0) -> #REF! | N85: =U85*$T$5 -> #REF! | O85: =ROUND(N85*K85,0) -> #REF! | P85: =N85+L85 -> #REF! | Q85: =P85*K85 -> #REF!
A86: * | B86: Rebar work/Cốt thép
A87: 11 | B87: Bottom slabn/ Cốt thép cho bản đáy | D87: kg | K87: =8514.5+91.5+1290.4 -> 9896.4 | L87: =T87*$T$5 -> #REF! | M87: =ROUND(L87*K87,0) -> #REF! | N87: =U87*$T$5 -> #REF! | O87: =ROUND(N87*K87,0) -> #REF! | P87: =N87+L87 -> #REF! | Q87: =P87*K87 -> #REF! | T87: ='Bill 2-Main building works'!#REF! -> #REF! | U87: ='Bill 2-Main building works'!#REF! -> #REF!
A88: 12 | B88: Wall/ Cốt thép cho thành bể | D88: kg | K88: =67.4+35.5+31.9+1295.6+3441+335.6+3.8+383.9+7.6+354.6+889.4+82.3 -> 6928.6 | L88: =T88*$T$5 -> #REF! | M88: =ROUND(L88*K88,0) -> #REF! | N88: =U88*$T$5 -> #REF! | O88: =ROUND(N88*K88,0) -> #REF! | P88: =N88+L88 -> #REF! | Q88: =P88*K88 -> #REF! | T88: =T87 -> #REF! | U88: =U87 -> #REF!
A89: 13 | B89: Column/ Cốt thép cho cột | D89: kg | K89: =79.1+628.5+3.2+29+2.9+27.1+61.9 -> 831.7 | L89: =T89*$T$5 -> #REF! | M89: =ROUND(L89*K89,0) -> #REF! | N89: =U89*$T$5 -> #REF! | O89: =ROUND(N89*K89,0) -> #REF! | P89: =N89+L89 -> #REF! | Q89: =P89*K89 -> #REF! | T89: =T88 -> #REF! | U89: =U88 -> #REF!
A90: 14 | B90: Top slab/ Cốt thép cho nắp bể | D90: kg | K90: =3710.5+365.6+161.1+42.9+100.5+19.9+96+53.7+110.3+24.9+108.7 -> 4794.1 | L90: =T90*$T$5 -> #REF! | M90: =ROUND(L90*K90,0) -> #REF! | N90: =U90*$T$5 -> #REF! | O90: =ROUND(N90*K90,0) -> #REF! | P90: =N90+L90 -> #REF! | Q90: =P90*K90 -> #REF! | T90: =T89 -> #REF! | U90: =U89 -> #REF!
B92: OTHERS WORKS/ CÔNG TÁC KHÁC
A93: 1 | B93: Waterproofing/Chống thấm cho bể | C93: BASF Masterseal 540 | D93: m2 | K93: =+SUBTOTAL(9,J94:J99) -> 553.19365 | L93: =T93*$T$5 -> #REF! | M93: =ROUND(L93*K93,0) -> #REF! | N93: =U93*$T$5 -> #REF! | O93: =ROUND(N93*K93,0) -> #REF! | P93: =N93+L93 -> #REF! | Q93: =P93*K93 -> #REF! | T93: ='Bill 2-Main building works'!#REF! -> #REF! | U93: ='Bill 2-Main building works'!#REF! -> #REF!
B94: Đáy bể | E94: 1 | G94: 212.48 | I94: 1 | J94: =PRODUCT(E94:I94) -> 212.48 | L94: =T94*$T$5 -> #REF! | M94: =ROUND(L94*K94,0) -> #REF! | N94: =U94*$T$5 -> #REF! | O94: =ROUND(N94*K94,0) -> #REF! | P94: =N94+L94 -> #REF! | Q94: =P94*K94 -> #REF!
B95: vát góc | E95: 1 | F95: =(61.06+59.4)/2 -> 60.23 | G95: 0.355 | I95: 1 | J95: =PRODUCT(E95:I95) -> 21.38165 | L95: =T95*$T$5 -> #REF! | M95: =ROUND(L95*K95,0) -> #REF! | N95: =U95*$T$5 -> #REF! | O95: =ROUND(N95*K95,0) -> #REF! | P95: =N95+L95 -> #REF! | Q95: =P95*K95 -> #REF!
B96: tbn1 | E96: 1 | F96: =F64 -> 47.91 | H96: 2.4 | I96: 1 | J96: =PRODUCT(E96:I96) -> 114.984 | L96: =T96*$T$5 -> #REF! | M96: =ROUND(L96*K96,0) -> #REF! | N96: =U96*$T$5 -> #REF! | O96: =ROUND(N96*K96,0) -> #REF! | P96: =N96+L96 -> #REF! | Q96: =P96*K96 -> #REF!
E97: 1 | F97: =F96 -> 47.91 | H97: =H96+0.4 -> 2.8 | I97: 1 | J97: =PRODUCT(E97:I97) -> 134.148 | L97: =T97*$T$5 -> #REF! | M97: =ROUND(L97*K97,0) -> #REF! | N97: =U97*$T$5 -> #REF! | O97: =ROUND(N97*K97,0) -> #REF! | P97: =N97+L97 -> #REF! | Q97: =P97*K97 -> #REF!
B98: tbn2 | E98: 1 | F98: =F67 -> 12 | H98: 2.7 | I98: 1 | J98: =PRODUCT(E98:I98) -> 32.4 | L98: =T98*$T$5 -> #REF! | M98: =ROUND(L98*K98,0) -> #REF! | N98: =U98*$T$5 -> #REF! | O98: =ROUND(N98*K98,0) -> #REF! | P98: =N98+L98 -> #REF! | Q98: =P98*K98 -> #REF!
E99: 1 | F99: =F98 -> 12 | H99: =H98+0.45 -> 3.15 | I99: 1 | J99: =PRODUCT(E99:I99) -> 37.8 | L99: =T99*$T$5 -> #REF! | M99: =ROUND(L99*K99,0) -> #REF! | N99: =U99*$T$5 -> #REF! | O99: =ROUND(N99*K99,0) -> #REF! | P99: =N99+L99 -> #REF! | Q99: =P99*K99 -> #REF!
A100: 2 | B100: Waterbar/Thanh chặn nước cho mạch ngừng thi công | C100: Waterbar V20 | D100: md | K100: =+SUBTOTAL(9,J101) -> 63.43 | L100: =T100*$T$5 -> #REF! | M100: =ROUND(L100*K100,0) -> #REF! | N100: =U100*$T$5 -> #REF! | O100: =ROUND(N100*K100,0) -> #REF! | P100: =N100+L100 -> #REF! | Q100: =P100*K100 -> #REF! | T100: 145000 | U100: 20000
E101: 1 | F101: 63.43 | I101: 1 | J101: =PRODUCT(E101:I101) -> 63.43 | L101: =T101*$T$5 -> #REF! | M101: =ROUND(L101*K101,0) -> #REF! | N101: =U101*$T$5 -> #REF! | O101: =ROUND(N101*K101,0) -> #REF! | P101: =N101+L101 -> #REF! | Q101: =P101*K101 -> #REF!
A102: 3 | B102: Cover for visting hole/ Nắp thăm bể | C102: 800x800 SS304 | D102: set | K102: 2 | L102: =T102*$T$5 -> #REF! | M102: =ROUND(L102*K102,0) -> #REF! | N102: =U102*$T$5 -> #REF! | O102: =ROUND(N102*K102,0) -> #REF! | P102: =N102+L102 -> #REF! | Q102: =P102*K102 -> #REF! | T102: 2500000 | U102: 350000
...

Sheet Bill 3-External works
A1: PROJECT/ DỰ ÁN : NEW WAREHOUSE/NHÀ KHO
A2: ADDRESS/ĐỊA CHỈ : VSIP 3, BINH DUONG, VIETNAM
A3: BILL No.04 : EXTERNAL WORKS
A4: No. | B4: DESCRIPTION | C4: STANDARD | D4: Unit | E4: DIMENSION | J4: QUANTITY | K4: Q'TY | L4: MATERIAL | N4: LABOUR & EQUIPMENT | P4: TOTAL COST(VND) | R4: REMARK
E5: No | F5: L | G5: W | H5: H | I5: HS | J5: COMPONENT | L5: UNIT | M5: AMOUNT | N5: UNIT | O5: AMOUNT | P5: UNIT | Q5: AMOUNT
A6: No.04 | B6: TOTAL OF BILL No.4: EXTERNAL WORKS
A7: =A14 -> IN.01 | B7: =B14 -> CLEARING AND LEVELING / DỌN DẸP VÀ SAN LẤP MẶT BẰNG
A8: =A19 -> IN.02 | B8: =B19 -> STORM DRAINAGE SYSTEM
A9: =A42 -> IN.03 | B9: =B42 -> ROAD WORKS / CÔNG TÁC ĐƯỜNG
A10: =A66 -> IN.04 | B10: =B66 -> FENCCING & GATES/ HÀNG RÀO VÀ CỔNG
A11: =A139 -> IN.05 | B11: =B139 -> LANDSCAPING WORKS/ CÔNG TÁC CẢNH QUAN
A12: =A142 -> IN.06 | B12: =B142 -> FLAG POLE/ CÔNG TÁC CỘT CỜ
A13: =A144 -> IN.07 | B13: =B144 -> OTHERS WORKS / CÔNG TÁC KHÁC
A14: IN.01 | B14: CLEARING AND LEVELING / DỌN DẸP VÀ SAN LẤP MẶT BẰNG
A15: 1 | B15: All trees, grass, roots, rubbish have to be removed out the site before the execution of cutting & filling work/Toàn bộ cây cối, cỏ, rễ cây, rác thải phải được dọn sạch khỏi công trường trước khi thực hiện công tác san lấp | D15: m2
A16: 2 | B16: Cutting soil/ Cắt lớp đất nền đến cao độ thiết kế | C16: Using soil from excavation and Levelling for elevation 0.3m , to ensure water drainage to VSIP | D16: m3
A17: 3 | B17: Remove surplus soil to to the land consolidation yard of VSIP1 industrial park/ Vận chuyển đất dư đến bải đổ đất của KCN VSIP | D17: m3
A19: IN.02 | B19: STORM DRAINAGE SYSTEM
A20: I | B20: MANHOLE/ HỐ GA
B21: R.C Manhole (including excavation, backfill. Compaction, formwork, rebars, concrete,bricks, concrete cover,edge steel etc.)
A22: 1 | B22: RC Manhole M1 | C22: 900x900xH1250-1500 | D22: pcs
A23: 2 | B23: RC Manhole M2 | C23: 1100x1100xH1550-1900 | D23: pcs
A24: 4 | B24: RC Manhole M3 | C24: 1300x1300xH1900-2400 | D24: pcs
A25: 5 | B25: RC Manhole M3a | C25: 1300x1300xH1900-2400 | D25: pcs
A26: 7 | B26: Waste water Manhole | C26: 800x800xH1200-2400 | D26: pcs
A27: II | B27: PIPING & FITTINGS/ ỐNG VÀ PHỤ KIỆN
B28: Male/female type with shaped concr. Supports, including excavation, backfill, compaction, etc. Combine with TCXDVN 372-2006
A29: 9 | B29: R.C pipe H30 DN300 | C29: ACC, Hung Vuong or equal | D29: m
A30: 11 | B30: R.C pipe H30 DN400 | C30: ACC, Hung Vuong or equal | D30: m
A31: 13 | B31: R.C pipe H30 DN500 | C31: ACC, Hung Vuong or equal | D31: m
A32: 15 | B32: R.C pipe H30 DN800 | C32: ACC, Hung Vuong or equal | D32: m
B33: uPVC storm pipe (PN10) - Underground pipe (including, hanger,support, accessories, excavation, backfill, compaction, etc, ...)
A34: 16 | B34: uPVC pipe D90 | C34: Bình Minh,Tien Phong | D34: m
A35: 16 | B35: uPVC pipe D140 | C35: Bình Minh,Tien Phong | D35: m
A36: 17 | B36: uPVC pipe D220 | C36: Bình Minh,Tien Phong | D36: m
A37: III | B37: OTHER WORKS/CÔNG TÁC KHÁC
A38: 1 | B38: Permit to connect storm drainage water system to the industrial waste water system/ Xin phép đầu nối nước mưa vào hệ thống nước mưa KCN | D38: lot
A39: 2 | B39: Return to their original state/ Hoàn trả lại hiện trạng sau khi kết nối nước mưa vào khu công nghiệp | D39: lot
A40: 3 | B40: Permit to connect industrial road system/ Xin phép đầu nối đường giao thông | D40: lot
A42: IN.03 | B42: ROAD WORKS / CÔNG TÁC ĐƯỜNG
A43: II | B43: INTERNAL ROAD/ ĐƯỜNG BÊN NỘI BỘ
B44: RC.ROAD AREA / ĐƯỜNG BÊ TÔNG CỐT THÉP
A45: 1 | B45: Excavation of Soil/ Công tác đào đất | C45: Soil grade 3 | D45: m3
A46: 2 | B46: Remove surplus soil/ Vận chuyển đất dư | C46: Distance D<=1Km | D46: m3
A47: 3 | B47: Natural soil well compacted, k = 0.95/ Đầm chặt nền đất | D47: m2
A48: 4 | B48: Crushed aggregate base course, well compacted K>=0.95 (02 layer)/ Lớp đá đầm chặt (02 lớp) | C48: 200mm thk/ 1 layer | D48: m3
A49: 5 | B49: PVC layer/ Nylon lót | C49: 0.2mm thk | D49: m2
A50: 6 | B50: Concrete works for ground slab/ Bê tông nền đường | C50: Grade M250, 200mm thk | D50: m3
A51: 7 | B51: Reinforcement for ground slab/ Cốt thép nền đường | C51: Song Hop Luc, Toan Tam | D51: kg
A52: 8 | B52: Make slab surface smooth by machine and cuting joint / Xoa nền làm phẳng và cắt joint | D52: m2
A53: 9 | B53: Contraction joint (CTJ) | C53: Sikaflex+Backer rod | D53: m
B55: GRASS CONCRETE BLOCK ROAD/ ĐƯỜNG BÊ TÔNG GẠCH TRỒNG CỎ
A56: 10 | B56: Excavation of Soil/ Công tác đào đất | D56: m3
A57: 11 | B57: Remove surplus soil/ Vận chuyển đất dư | D57: m3
A58: 12 | B58: Natural soil well compacted,/ Đầm chặt nền đất | D58: m2
A59: 13 | B59: 200mm thk, 2 layer. Crushed aggregate base, compacted 95% | C59: 0x4cm, H=250mm, Phu Giao, Tan Uyen Bình Dương | D59: m3
A60: 14 | B60: Clean wet sand layer , well compact / Lớp cát sạch, tưới nước, đầm kĩ | C60: 120mm thk | D60: m3
A61: 15 | B61: 80mm thk. Interlocking block | C61: Grade 200, insert soil for grass | D61: m2
B63: CURB/ BÓ VỈA
A64: 16 | B64: Curb / Bó vỉa | D64: m
A66: IN.04 | B66: FENCCING & GATES/ HÀNG RÀO VÀ CỔNG
A67: I | B67: FENCING/HÀNG RÀO
B68: EARTH WORK/ CÔNG TÁC ĐẤT
A69: 1 | B69: Excavation of Soil/ Công tác đào đất | C69: Soil grade 3 | D69: m3
B70: Foundation
B71: F1 | E71: 194 | F71: 1.2 | G71: 1.2 | H71: 0.25 | I71: 1.5 | J71: =E71*(F71+0.6)*(G71+0.6)*I71 -> 942.84
B72: Ground beam
E73: 1 | F73: =(130+155)*2 -> 570 | G73: 0.2 | H73: 0.5 | I73: 1.3 | J73: =PRODUCT(E73:I73) -> 74.1
A74: 2 | B74: Backfilling soil for foundation/ Lấp đất móng | C74: Compact layer by layer, each layer 0.3m | D74: m3
A75: 3 | B75: Remove surplus soil/ Vận chuyển đất dư | C75: Distance D<=1Km | D75: m3
A76: 4 | B76: Natural soil well compacted, k = 0.95/ Đầm chặt nền đất | D76: m2
B77: F1 | E77: 194 | F77: 1.4 | G77: 1.4 | J77: =PRODUCT(E77:I77) -> 380.24
B78: ANTI TERMITE TREATMENT/ CHỐNG MỐI
B79: REINFORCED CONCRETE WORK/ BÊ TÔNG CỐT THÉP
A80: * | B80: Concrete work/ Công tác bê tông
A81: 5 | B81: Lean concrete/ Bê tông lót | C81: Grade B7.5 | D81: m3
B82: F1 | E82: 194 | F82: 1.4 | G82: 1.4 | H82: 0.1 | I82: 1 | J82: =PRODUCT(E82:I82) -> 38.024
A83: 6 | B83: Concrete works for Foundation/ Bê tông móng | C83: Grade M250 | D83: m3 | J83: =PRODUCT(E83:I83) -> 0
B84: F1 | E84: 194 | F84: 1.2 | G84: 1.2 | H84: 0.25 | I84: 1 | J84: =PRODUCT(E84:I84) -> 69.84
A85: 7 | B85: Concrete works for base column / Bê tông cổ cột | C85: Grade M250 | D85: m3 | J85: =PRODUCT(E85:I85) -> 0
B86: Cr1 | E86: 194 | F86: 0.25 | G86: 0.25 | H86: 1 | I86: 1 | J86: =PRODUCT(E86:I86) -> 12.125
A87: 8 | B87: Concrete works for Ground beam/ Bê tông đà kiềng | C87: Grade M250 | D87: m3 | J87: =PRODUCT(E87:I87) -> 0
E88: 1 | F88: =(130+155)*2 -> 570 | G88: 0.2 | H88: 0.5 | I88: 1 | J88: =PRODUCT(E88:I88) -> 57
A89: 9 | B89: Concrete works for column / Bê tông cột | C89: Grade M250 | D89: m3 | J89: =PRODUCT(E89:I89) -> 0
B90: Cr1 | E90: 194 | F90: 0.2 | G90: 0.2 | H90: 2 | I90: 1 | J90: =PRODUCT(E90:I90) -> 15.52
A91: 10 | B91: Concrete works for attached column, brace beam/ Bê tông cho bổ trụ, giằng tường | C91: Grade B20 | D91: m3
E92: 1 | F92: =F88 -> 570 | G92: 0.2 | H92: 0.1 | I92: 1 | J92: =PRODUCT(E92:I92) -> 11.4
A93: * | B93: Formwork/ Ván Khuôn
A94: 11 | B94: Lean concrete/ Bê tông lót | C94: Steel frame & Plywood form | D94: m2
B95: F1 | E95: 194 | F95: 1.4 | G95: 1.4 | H95: 0.1 | I95: 1 | J95: =I95*(G95+F95)*2*H95*E95 -> 108.64
A96: 12 | B96: Foundation/ Ván khuôn móng | C96: =C94 -> Steel frame & Plywood form | D96: m2 | J96: =PRODUCT(E96:I96) -> 0
B97: F1 | E97: 194 | F97: 1.2 | G97: 1.2 | H97: 0.25 | I97: 1 | J97: =I97*(G97+F97)*2*H97*E97 -> 232.8
A98: 13 | B98: Stump column / Ván khuôn cổ cột | C98: =C96 -> Steel frame & Plywood form | D98: m2 | J98: =PRODUCT(E98:I98) -> 0
B99: Cr1 | E99: 194 | F99: 0.25 | G99: 0.25 | H99: 1 | I99: 1 | J99: =I99*(G99+F99)*2*H99*E99 -> 194
A100: 14 | B100: Ground beam / Ván khuôn đà kiềng | C100: =C98 -> Steel frame & Plywood form | D100: m2 | J100: =PRODUCT(E100:I100) -> 0
E101: 1 | F101: =(130+155)*2 -> 570 | G101: 0.2 | H101: 0.5 | I101: 1 | J101: =I101*(G101+F101)*2*H101*E101 -> 570.2
A102: 15 | B102: Column/ Ván khuôn cột | C102: =C100 -> Steel frame & Plywood form | D102: m2 | J102: =PRODUCT(E102:I102) -> 0
B103: Cr1 | E103: 194 | F103: 0.2 | G103: 0.2 | H103: 2 | I103: 1 | J103: =I103*(G103+F103)*2*H103*E103 -> 310.4
A104: 16 | B104: Attached column, brace beam/ Ván khuôn bổ trụ, giằng tường | C104: =C102 -> Steel frame & Plywood form | D104: m2
E105: 1 | F105: =F101 -> 570 | G105: 0.2 | H105: 0.1 | I105: 1 | J105: =I105*(G105+F105)*2*H105*E105 -> 114.04
...

Sheet SCHEDULE OF RATES 
A1: #REF!
A2: #REF!
A4: SCHEDULE OF RATES
A6: ITEM | B6: DESCRIPTION | C6: BASE SUPPLIER BRAND (BY NICON) | D6: BIDDER'S QTY | E6: UNIT | F6: MATERIAL RATE (VND) | G6: INSTALLATION RATE (VND) | H6: UNIT RATE (VND) | I6: AMOUNT (BIDDER QTY, VND) | J6: NICON REMARKS
B7: CSA
A8: 1 | B8: Earth works
B9: Non-woven geotextile layer | D9: 1 | E9: m2 | H9: =F9+G9 -> 0 | I9: =H9*D9 -> 0
B10: Woven geotextile layer | D10: 1 | E10: m2 | H10: =F10+G10 -> 0 | I10: =H10*D10 -> 0
B11: PE sheet 0.15mm | D11: 1 | E11: m2 | H11: =F11+G11 -> 0 | I11: =H11*D11 -> 0
B12: PE sheet 0.20mm | D12: 1 | E12: m2 | H12: =F12+G12 -> 0 | I12: =H12*D12 -> 0
B13: PE sheet 0.25mm | D13: 1 | E13: m2 | H13: =F13+G13 -> 0 | I13: =H13*D13 -> 0
B14: Polyolefin vaporbarrier-Perminator 15mil, 0.381mm thk. | D14: 1 | E14: m2 | H14: =F14+G14 -> 0 | I14: =H14*D14 -> 0
B15: Crushed stone, compacted | D15: 1 | E15: m3 | H15: =F15+G15 -> 0 | I15: =H15*D15 -> 0
B16: Laterite soil, compacted | D16: 1 | E16: m3 | H16: =F16+G16 -> 0 | I16: =H16*D16 -> 0
B17: Sand filling, compacted | D17: 1 | E17: m3 | H17: =F17+G17 -> 0 | I17: =H17*D17 -> 0
B18: Soil filling, compacted | D18: 1 | E18: m3 | H18: =F18+G18 -> 0 | I18: =H18*D18 -> 0
A19: 2 | B19: Piling works
B20: Supply PHC spun pile D300mm | D20: 1 | E20: m | H20: =F20+G20 -> 0 | I20: =H20*D20 -> 0
B21: Supply PHC spun pile D350mm | D21: 1 | E21: m | H21: =F21+G21 -> 0 | I21: =H21*D21 -> 0
B22: Supply PHC spun pile D400mm | D22: 1 | E22: m | H22: =F22+G22 -> 0 | I22: =H22*D22 -> 0
B23: Pressing PHC spun pile D300mm | D23: 1 | E23: m | H23: =F23+G23 -> 0 | I23: =H23*D23 -> 0
B24: Pressing PHC spun pile D350mm | D24: 1 | E24: m | H24: =F24+G24 -> 0 | I24: =H24*D24 -> 0
B25: Pressing PHC spun pile D400mm | D25: 1 | E25: m | H25: =F25+G25 -> 0 | I25: =H25*D25 -> 0
B26: Pre-drill PHC spun pile D300mm | D26: 1 | E26: m | H26: =F26+G26 -> 0 | I26: =H26*D26 -> 0
B27: Pre-drill PHC spun pile D350mm | D27: 1 | E27: m | H27: =F27+G27 -> 0 | I27: =H27*D27 -> 0
B28: Pre-drill PHC spun pile D400mm | D28: 1 | E28: m | H28: =F28+G28 -> 0 | I28: =H28*D28 -> 0
B29: Pile heads cut off and disposal surplus debris to assigned location, spun pile D300mm | D29: 1 | E29: nr | H29: =F29+G29 -> 0 | I29: =H29*D29 -> 0
B30: Pile heads cut off and disposal surplus debris to assigned location, spun pile D350mm | D30: 1 | E30: nr | H30: =F30+G30 -> 0 | I30: =H30*D30 -> 0
B31: Pile heads cut off and disposal surplus debris to assigned location, spun pile D400mm | D31: 1 | E31: nr | H31: =F31+G31 -> 0 | I31: =H31*D31 -> 0
A32: 3 | B32: Concrete works
B33: Structure concrete, type B, grade B20 | D33: 1 | E33: m3 | H33: =F33+G33 -> 0 | I33: =H33*D33 -> 0
B34: Structure concrete, type C, grade B22.5 | D34: 1 | E34: m3 | H34: =F34+G34 -> 0 | I34: =H34*D34 -> 0
B35: Structure concrete, type D, grade B30 | D35: 1 | E35: m3 | H35: =F35+G35 -> 0 | I35: =H35*D35 -> 0
B36: Steel fair-face formworks | D36: 1 | E36: m2 | H36: =F36+G36 -> 0 | I36: =H36*D36 -> 0
B37: Plywood fair-face formworks | D37: 1 | E37: m2 | H37: =F37+G37 -> 0 | I37: =H37*D37 -> 0
B38: Steel weldmesh Ø12-150 | D38: 1 | E38: m2 | H38: =F38+G38 -> 0 | I38: =H38*D38 -> 0
B39: Steel weldmesh Ø12-200 | D39: 1 | E39: m2 | H39: =F39+G39 -> 0 | I39: =H39*D39 -> 0
B40: Steel weldmesh Ø10-150 | D40: 1 | E40: m2 | H40: =F40+G40 -> 0 | I40: =H40*D40 -> 0
B41: Steel weldmesh Ø10-200 | D41: 1 | E41: m2 | H41: =F41+G41 -> 0 | I41: =H41*D41 -> 0
B42: Steel weldmesh Ø8-150 | D42: 1 | E42: m2 | H42: =F42+G42 -> 0 | I42: =H42*D42 -> 0
B43: Steel weldmesh Ø8-200 | D43: 1 | E43: m2 | H43: =F43+G43 -> 0 | I43: =H43*D43 -> 0
B44: Non-shrink grouting | D44: 1 | E44: m3 | H44: =F44+G44 -> 0 | I44: =H44*D44 -> 0
... B51: Drill hole into reinforcement concrete and apply chemical for installation of rebar/anchor (Diameter of rebar/anchor : 25mm) | D51: 1 | E51: nr | H51: =F51+G51 -> 0 | I51: =H51*D51 -> 0
A52: 4 | B52: Metal works
B53: Mild steel - Hot roll profile | D53: 1 | E53: kg | H53: =F53+G53 -> 0 | I53: =H53*D53 -> 0
B54: Mild steel - Built-up profile | D54: 1 | E54: kg | H54: =F54+G54 -> 0 | I54: =H54*D54 -> 0
B55: Hot-dip galvanized steel | D55: 1 | E55: kg | H55: =F55+G55 -> 0 | I55: =H55*D55 -> 0
B56: Galvanized steel | D56: 1 | E56: kg | H56: =F56+G56 -> 0 | I56: =H56*D56 -> 0
B57: Stainless steel 304 | D57: 1 | E57: kg | H57: =F57+G57 -> 0 | I57: =H57*D57 -> 0
B58: Stainless steel 316 | D58: 1 | E58: kg | H58: =F58+G58 -> 0 | I58: =H58*D58 -> 0
B59: Steel plate 5mm | D59: 1 | E59: kg | H59: =F59+G59 -> 0 | I59: =H59*D59 -> 0
B60: Steel plate 6mm - 8mm | D60: 1 | E60: kg | H60: =F60+G60 -> 0 | I60: =H60*D60 -> 0
B61: Steel plate 10mm - 19mm | D61: 1 | E61: kg | H61: =F61+G61 -> 0 | I61: =H61*D61 -> 0
B62: Galvanized steel grating | D62: 1 | E62: kg | H62: =F62+G62 -> 0 | I62: =H62*D62 -> 0
B63: Galvanized steel grating, heavy duty | D63: 1 | E63: kg | H63: =F63+G63 -> 0 | I63: =H63*D63 -> 0
B64: SUS grating | D64: 1 | E64: kg | H64: =F64+G64 -> 0 | I64: =H64*D64 -> 0
... B68: Checker plate 8.0mm thk. | D68: 1 | E68: m2 | H68: =F68+G68 -> 0 | I68: =H68*D68 -> 0
B70: Roofing, Cladding & Paneling:
B71: Metal roof sheet 0.50 APT, incl flashing and accessories | D71: 1 | E71: m2 | H71: =F71+G71 -> 0 | I71: =H71*D71 -> 0
B72: Metal cladding sheet 0.50 APT, incl flashing and accessories | D72: 1 | E72: m2 | H72: =F72+G72 -> 0 | I72: =H72*D72 -> 0
B73: Fiber glass 24kg/m3, 50mm thk. with aluminum foil and wire mesh | D73: 1 | E73: m2 | H73: =F73+G73 -> 0 | I73: =H73*D73 -> 0
B74: Fiber glass 24kg/m3, 50mm thk. with aluminum foil and without wire mesh | D74: 1 | E74: m2 | H74: =F74+G74 -> 0 | I74: =H74*D74 -> 0
B75: Penetration on roof | D75: 1 | E75: nr | H75: =F75+G75 -> 0 | I75: =H75*D75 -> 0
B76: Galvanized purlin, Z30024 | D76: 1 | E76: m | H76: =F76+G76 -> 0 | I76: =H76*D76 -> 0
B77: Galvanized purlin, Z20024 | D77: 1 | E77: m | H77: =F77+G77 -> 0 | I77: =H77*D77 -> 0
B78: Galvanized purlin, Z20019 | D78: 1 | E78: m | H78: =F78+G78 -> 0 | I78: =H78*D78 -> 0
B79: Galvanized purlin, Z15019 | D79: 1 | E79: m | H79: =F79+G79 -> 0 | I79: =H79*D79 -> 0
B80: Galvanized purlin, Z15015 | D80: 1 | E80: m | H80: =F80+G80 -> 0 | I80: =H80*D80 -> 0
B81: Steel handrail (epoxy paint) | D81: 1 | E81: m | H81: =F81+G81 -> 0 | I81: =H81*D81 -> 0
B82: Stainless steel handrail | D82: 1 | E82: m | H82: =F82+G82 -> 0 | I82: =H82*D82 -> 0
B83: Fire rate paint for steel structure :
B84: Fire rate 60' | D84: 1 | E84: m2 | H84: =F84+G84 -> 0 | I84: =H84*D84 -> 0
B85: Fire rate 90' | D85: 1 | E85: m2 | H85: =F85+G85 -> 0 | I85: =H85*D85 -> 0
B86: Fire rate 120' | D86: 1 | E86: m2 | H86: =F86+G86 -> 0 | I86: =H86*D86 -> 0
B87: Fire rate 150' | D87: 1 | E87: m2 | H87: =F87+G87 -> 0 | I87: =H87*D87 -> 0
B88: Fire rate 60' | D88: 1 | E88: m2 | H88: =F88+G88 -> 0 | I88: =H88*D88 -> 0
B89: Fire rate 90' | D89: 1 | E89: m2 | H89: =F89+G89 -> 0 | I89: =H89*D89 -> 0
B90: Fire rate 120' | D90: 1 | E90: m2 | H90: =F90+G90 -> 0 | I90: =H90*D90 -> 0
B91: Fire rate 150' | D91: 1 | E91: m2 | H91: =F91+G91 -> 0 | I91: =H91*D91 -> 0
A92: 5 | B92: Masonry
B93: AAC block wall 200mm | D93: 1 | E93: m2 | H93: =F93+G93 -> 0 | I93: =H93*D93 -> 0
B94: AAC block wall 100mm | D94: 1 | E94: m2 | H94: =F94+G94 -> 0 | I94: =H94*D94 -> 0
B95: AAC block wall 200mm, fire rating 120 minutes | D95: 1 | E95: m2 | H95: =F95+G95 -> 0 | I95: =H95*D95 -> 0
B96: AAC block wall 200mm, fire rating 90 minutes | D96: 1 | E96: m2 | H96: =F96+G96 -> 0 | I96: =H96*D96 -> 0
B97: Red brickwall 100mm | D97: 1 | E97: m2 | H97: =F97+G97 -> 0 | I97: =H97*D97 -> 0
B98: Wall plastering 15mm thk. | D98: 1 | E98: m2 | H98: =F98+G98 -> 0 | I98: =H98*D98 -> 0
A99: 6 | B99: Finishing
B100: Floor
B101: Liquid floor hardener | D101: 1 | E101: m2 | H101: =F101+G101 -> 0 | I101: =H101*D101 -> 0
B102: Polyurethane floor 6.0mm thk., slip resistance | E102: m2 | H102: =F102+G102 -> 0 | I102: =H102*D102 -> 0
B103: Polyurethane floor for high temperature and cold room 12.0mm thk., slip resistance | E103: m2 | H103: =F103+G103 -> 0 | I103: =H103*D103 -> 0
B104: Floor flatness with floor classification FM2 | E104: m2 | H104: =F104+G104 -> 0 | I104: =H104*D104 -> 0
B105: Dry shake floor hardener | D105: 1 | E105: m2 | H105: =F105+G105 -> 0 | I105: =H105*D105 -> 0
B106: Ceramic floor tile | D106: 1 | E106: m2 | H106: =F106+G106 -> 0 | I106: =H106*D106 -> 0
B107: Homogeneous ceramic floor tile 600x600x12mm | E107: m2 | H107: =F107+G107 -> 0 | I107: =H107*D107 -> 0
B108: Non-slip homogeneous ceramic floor tile 600x600x12mm, slip resistance R10 | E108: m2 | H108: =F108+G108 -> 0 | I108: =H108*D108 -> 0
B109: Raised floor 600m high | E109: m2 | H109: =F109+G109 -> 0 | I109: =H109*D109 -> 0
B110: Raised floor 1000m high | E110: m2 | H110: =F110+G110 -> 0 | I110: =H110*D110 -> 0
B111: Wall
B112: Cement board wall, 1 side with gal. steel stud | D112: 1 | E112: m2 | H112: =F112+G112 -> 0 | I112: =H112*D112 -> 0
...

Sheet E02.ELV SYSTEM 
A1: ESTIMATE DETAIL TABLE
A2: ='Bill 3-External works'!#REF! -> #REF!
A3: ITEM/HẠNG MỤC : ELV SYSTEM/ HỆ THỐNG ĐIỆN NHẸ
A5: No. | B5: DESCRIPTION | C5: STANDARD | D5: Unit | E5: DIMENSION | J5: QUANTITY | K5: Q'TY | L5: MATERIAL | N5: LABOUR & EQUIPMENT | P5: TOTAL COST | R5: REMARK | S5: =#REF! -> #REF! | T5: =#REF! -> #REF!
E6: No | F6: L | G6: W | H6: H | I6: HS | J6: COMPONENT | L6: UNIT | M6: AMOUNT | N6: UNIT | O6: AMOUNT | P6: UNIT | Q6: AMOUNT | T6: =#REF! -> #REF! | U6: =#REF! -> #REF!
A7: E02 | B7: ELV SYSTEM/ HỆ THỐNG ĐIỆN NHẸ | M7: =SUBTOTAL(109,M8:M13) -> #REF! | O7: =SUBTOTAL(109,O8:O13) -> #REF! | Q7: =O7+M7 -> #REF!
A8: =A14 -> I | B8: =B14 -> DATA AND TEL SYSTEM/ HỆ THỐNG MẠNG, ĐIỆN THOẠI | M8: =M14 -> #REF! | O8: =O14 -> #REF! | Q8: =O8+M8 -> #REF!
A9: =A38 -> II | B9: =B38 -> CAMERA SYSTEM / HỆ THỐNG CAMERA | M9: =M38 -> #REF! | O9: =O38 -> #REF! | Q9: =O9+M9 -> #REF!
A10: =A62 -> III | B10: =B62 -> PA SYSTEM/ HỆ THỐNG ÂM THANH | M10: =M62 -> #REF! | O10: =O62 -> #REF! | Q10: =O10+M10 -> #REF!
A11: =A80 -> IV | B11: =B80 -> DOOR ACCESS CONTROL SYSTEM / HỆ THỐNG KIỂM SOÁT RA / VÀO | M11: =M80 -> #REF! | O11: =O80 -> #REF! | Q11: =O11+M11 -> #REF!
A12: =A95 -> V | B12: =B95 -> ELV EARTHING SYSTEM / HỆ THỐNG NỐI ĐẤT ELV | M12: =M95 -> #REF! | O12: =O95 -> #REF! | Q12: =O12+M12 -> #REF!
A14: I | B14: DATA AND TEL SYSTEM/ HỆ THỐNG MẠNG, ĐIỆN THOẠI | M14: =SUBTOTAL(109,M15:M37) -> #REF! | O14: =SUBTOTAL(109,O15:O37) -> #REF! | Q14: =O14+M14 -> #REF!
A15: 1 | B15: Cabinet 19" - 27U Rack Power Distribution Unit, 6 Universal Outlets, 16A, 250V, MCB/ Tủ rack điện nhẹ 19" - 27U, 6 Universal Outlets, 16A, 250V, MCB | C15: VN | D15: set | K15: 1 | L15: =T15*$T$5 -> #REF! | M15: =ROUND(L15*K15,0) -> #REF! | N15: =U15*$T$5 -> #REF! | O15: =ROUND(N15*K15,0) -> #REF! | P15: =N15+L15 -> #REF! | Q15: =P15*K15 -> #REF! | T15: 7285000 | U15: 420000
A16: 2 | B16: MDF 200pairs/ Hộp điện thoại 200 đôi | C16: Krone VN | D16: set | K16: 1 | L16: =T16*$T$5 -> #REF! | M16: =ROUND(L16*K16,0) -> #REF! | N16: =U16*$T$5 -> #REF! | O16: =ROUND(N16*K16,0) -> #REF! | P16: =N16+L16 -> #REF! | Q16: =P16*K16 -> #REF! | T16: 1635000 | U16: 490500
A17: 3 | B17: Patch panel 24 ports - CAT6/ Thanh đấu nối cáp | C17: COMMSCOPE | D17: set | K17: 5 | L17: =T17*$T$5 -> #REF! | M17: =ROUND(L17*K17,0) -> #REF! | N17: =U17*$T$5 -> #REF! | O17: =ROUND(N17*K17,0) -> #REF! | P17: =N17+L17 -> #REF! | Q17: =P17*K17 -> #REF! | T17: 4224000 | U17: 397400
A18: 4 | B18: ODF 24 cores - Singlemode/ Hộp đấu nối sợi quang 24 cores | C18: VN | D18: set | K18: 1 | L18: =T18*$T$5 -> #REF! | M18: =ROUND(L18*K18,0) -> #REF! | N18: =U18*$T$5 -> #REF! | O18: =ROUND(N18*K18,0) -> #REF! | P18: =N18+L18 -> #REF! | Q18: =P18*K18 -> #REF! | T18: 1750000 | U18: 525000
A19: 5 | B19: ODF 6 cores - Singlemode/ Hộp đấu nối sợi quang 6 cores | C19: VN | D19: set | K19: 3 | L19: =T19*$T$5 -> #REF! | M19: =ROUND(L19*K19,0) -> #REF! | N19: =U19*$T$5 -> #REF! | O19: =ROUND(N19*K19,0) -> #REF! | P19: =N19+L19 -> #REF! | Q19: =P19*K19 -> #REF! | T19: 605000 | U19: 181500
A20: 6 | B20: Fiber optic cable assembly/ Cáp đấu nối sợi quang | C20: VN | D20: pcs | K20: =24 -> 24 | L20: =T20*$T$5 -> #REF! | M20: =ROUND(L20*K20,0) -> #REF! | N20: =U20*$T$5 -> #REF! | O20: =ROUND(N20*K20,0) -> #REF! | P20: =N20+L20 -> #REF! | Q20: =P20*K20 -> #REF! | T20: 125000 | U20: 136000
A21: 7 | B21: Converter/ Bộ chuyển đổi quang | C21: TPLINK | D21: set | K21: 6 | L21: =T21*$T$5 -> #REF! | M21: =ROUND(L21*K21,0) -> #REF! | N21: =U21*$T$5 -> #REF! | O21: =ROUND(N21*K21,0) -> #REF! | P21: =N21+L21 -> #REF! | Q21: =P21*K21 -> #REF! | T21: 2600000 | U21: 520000
A22: 8 | B22: Tray power Media converter 6 modules/ Khay nguồn bộ chuyển đổi 6 modules | C22: VN | D22: set | K22: 1 | L22: =T22*$T$5 -> #REF! | M22: =ROUND(L22*K22,0) -> #REF! | N22: =U22*$T$5 -> #REF! | O22: =ROUND(N22*K22,0) -> #REF! | P22: =N22+L22 -> #REF! | Q22: =P22*K22 -> #REF! | T22: 2300000 | U22: 150000
A23: 9 | B23: Core Switch - 24port/ Thiết bị chuyển mạch 24 cổng | C23: RUIJIE | D23: pcs | K23: 1 | L23: =T23*$T$5 -> #REF! | M23: =ROUND(L23*K23,0) -> #REF! | N23: =U23*$T$5 -> #REF! | O23: =ROUND(N23*K23,0) -> #REF! | P23: =N23+L23 -> #REF! | Q23: =P23*K23 -> #REF! | T23: 7144800 | U23: 580000
A24: 10 | B24: UPS 3KVA, backup 30mins / Bộ lưu điện 3KVA , lưu điện 30 phút | C24: SANTAK | D24: pcs | K24: 1 | L24: =T24*$T$5 -> #REF! | M24: =ROUND(L24*K24,0) -> #REF! | N24: =U24*$T$5 -> #REF! | O24: =ROUND(N24*K24,0) -> #REF! | P24: =N24+L24 -> #REF! | Q24: =P24*K24 -> #REF! | T24: 27370000 | U24: 350000
A25: 11 | B25: PABX 3CO/64EX/ Tổng đài điện thoại | C25: NEC | D25: pcs | K25: 1 | L25: =T25*$T$5 -> #REF! | M25: =ROUND(L25*K25,0) -> #REF! | N25: =U25*$T$5 -> #REF! | O25: =ROUND(N25*K25,0) -> #REF! | P25: =N25+L25 -> #REF! | Q25: =P25*K25 -> #REF! | T25: 52000000 | U25: 1800000
A26: 12 | B26: Telephone/data socket, floor outlet/ Ổ cắm điện thoại, mạng, lắp âm sàn | C26: SINO | D26: pcs | K26: =6+12 -> 18 | L26: =T26*$T$5 -> #REF! | M26: =ROUND(L26*K26,0) -> #REF! | N26: =U26*$T$5 -> #REF! | O26: =ROUND(N26*K26,0) -> #REF! | P26: =N26+L26 -> #REF! | Q26: =P26*K26 -> #REF! | T26: 858000 | U26: 257400
A27: 13 | B27: Telephone socket/ Data socket outlet (CAT6), wall mounted/ Ổ cắm điện thoại/ mạng gắn tường | C27: SINO | D27: pcs | K27: =1+6+4+1 -> 12 | L27: =T27*$T$5 -> #REF! | M27: =ROUND(L27*K27,0) -> #REF! | N27: =U27*$T$5 -> #REF! | O27: =ROUND(N27*K27,0) -> #REF! | P27: =N27+L27 -> #REF! | Q27: =P27*K27 -> #REF! | T27: 27000 | U27: 8100
A28: 14 | B28: Data socket outlet (CAT6), wall mounted/ Ổ cắm mạng gắn tường | C28: SINO | D28: pcs | K28: =3+3 -> 6 | L28: =T28*$T$5 -> #REF! | M28: =ROUND(L28*K28,0) -> #REF! | N28: =U28*$T$5 -> #REF! | O28: =ROUND(N28*K28,0) -> #REF! | P28: =N28+L28 -> #REF! | Q28: =P28*K28 -> #REF! | T28: 27000 | U28: 8100
A29: 15 | B29: Telephone socket outlet (CAT6), wall mounted/ Ổ cắm điện thoại gắn tường | C29: SINO | D29: pcs | K29: 1 | L29: =T29*$T$5 -> #REF! | M29: =ROUND(L29*K29,0) -> #REF! | N29: =U29*$T$5 -> #REF! | O29: =ROUND(N29*K29,0) -> #REF! | P29: =N29+L29 -> #REF! | Q29: =P29*K29 -> #REF! | T29: 27000 | U29: 8100
A30: 16 | B30: Patch cord FTP, CAT6, 4pair/ Dây nhảy | C30: SINO | D30: pcs | K30: =K26*2+K27*2+K28+K29+15 -> 82 | L30: =T30*$T$5 -> #REF! | M30: =ROUND(L30*K30,0) -> #REF! | N30: =U30*$T$5 -> #REF! | O30: =ROUND(N30*K30,0) -> #REF! | P30: =N30+L30 -> #REF! | Q30: =P30*K30 -> #REF! | T30: 32000 | U30: 136000
A31: 17 | B31: Telephone cable 10P - 0.5mm/ Cáp điện thoại 10 đôi, 0.5mm | C31: SINO | D31: m | K31: 121 | L31: =T31*$T$5 -> #REF! | M31: =ROUND(L31*K31,0) -> #REF! | N31: =U31*$T$5 -> #REF! | O31: =ROUND(N31*K31,0) -> #REF! | P31: =N31+L31 -> #REF! | Q31: =P31*K31 -> #REF! | T31: 25920 | U31: 7776
A32: 18 | B32: Cable UTP CAT5e/ Cáp UTP CAT5e | C32: COMMSCOPE | D32: m | K32: 690 | L32: =T32*$T$5 -> #REF! | M32: =ROUND(L32*K32,0) -> #REF! | N32: =U32*$T$5 -> #REF! | O32: =ROUND(N32*K32,0) -> #REF! | P32: =N32+L32 -> #REF! | Q32: =P32*K32 -> #REF! | T32: 7300 | U32: 2190
A33: 19 | B33: Cable FTP, CAT6, 4pair/ Cáp FTP, CAT6, 4pair | D33: m | K33: 1955 | L33: =T33*$T$5 -> #REF! | M33: =ROUND(L33*K33,0) -> #REF! | N33: =U33*$T$5 -> #REF! | O33: =ROUND(N33*K33,0) -> #REF! | P33: =N33+L33 -> #REF! | Q33: =P33*K33 -> #REF! | T33: 19500 | U33: 6200
A34: 20 | B34: PVC conduit D20/ Ống điện D20 | D34: m | K34: 1150 | L34: =T34*$T$5 -> #REF! | M34: =ROUND(L34*K34,0) -> #REF! | N34: =U34*$T$5 -> #REF! | O34: =ROUND(N34*K34,0) -> #REF! | P34: =N34+L34 -> #REF! | Q34: =P34*K34 -> #REF! | U34: 22000
A35: 21 | B35: Testing and comisioning/ Kiểm tra và vận hành thử | D35: lot | K35: 1 | L35: =T35*$T$5 -> #REF! | M35: =ROUND(L35*K35,0) -> #REF! | N35: =U35*$T$5 -> #REF! | O35: =ROUND(N35*K35,0) -> #REF! | P35: =N35+L35 -> #REF! | Q35: =P35*K35 -> #REF! | U35: 25000000
A36: 22 | B36: Accessories / Vật tư phụ | D36: lot | K36: 1 | L36: =T36*$T$5 -> #REF! | M36: =ROUND(L36*K36,0) -> #REF! | N36: =U36*$T$5 -> #REF! | O36: =ROUND(N36*K36,0) -> #REF! | P36: =N36+L36 -> #REF! | Q36: =P36*K36 -> #REF! | T36: 13745000
A38: II | B38: CAMERA SYSTEM / HỆ THỐNG CAMERA | M38: =SUBTOTAL(9,M39:M60) -> #REF! | O38: =SUBTOTAL(9,O39:O60) -> #REF! | Q38: =O38+M38 -> #REF!
A39: 1 | B39: Cabinet 19" - 9U Rack Power Distribution Unit, 6 Universal Outlets, 16A, 250V, MCB/ Tủ rack điện nhẹ 19" - 9U, 6 Universal Outlets, 16A, 250V, MCB | D39: set | K39: 3 | L39: =T39*$T$5 -> #REF! | M39: =ROUND(L39*K39,0) -> #REF! | N39: =U39*$T$5 -> #REF! | O39: =ROUND(N39*K39,0) -> #REF! | P39: =N39+L39 -> #REF! | Q39: =P39*K39 -> #REF! | T39: 7285000 | U39: 420000
A40: 2 | B40: Camera dome IP Dome colors IP camera - 24/7 Colorful imaging - High quality imaging with 2 MP resolution - Efficient H.265+ compression technology - Maximum IR beam distance : 15m | C40: HIKVISION | D40: pcs | K40: 5 | L40: =T40*$T$5 -> #REF! | M40: =ROUND(L40*K40,0) -> #REF! | N40: =U40*$T$5 -> #REF! | O40: =ROUND(N40*K40,0) -> #REF! | P40: =N40+L40 -> #REF! | Q40: =P40*K40 -> #REF! | T40: 1701000 | U40: 180000
A41: 3 | B41: Camera IP thân dài Colors IP camera - 24/7 Colorful imaging - High quality imaging with 2 MP resolution - Efficient H.265+ compression technology - Water and dust resistant (IP66) - Maximum IR beam distance : 30m | C41: HIKVISION | D41: pcs | K41: 23 | L41: =T41*$T$5 -> #REF! | M41: =ROUND(L41*K41,0) -> #REF! | N41: =U41*$T$5 -> #REF! | O41: =ROUND(N41*K41,0) -> #REF! | P41: =N41+L41 -> #REF! | Q41: =P41*K41 -> #REF! | T41: 1701000 | U41: 180000
A42: 4 | B42: Camera IP thân dài Colors IP camera - 24/7 Colorful imaging - High quality imaging with 2 MP resolution - Efficient H.265+ compression technology - Water and dust resistant (IP66) - Maximum IR beam distance : 50m | C42: HIKVISION | D42: pcs | K42: 4 | L42: =T42*$T$5 -> #REF! | M42: =ROUND(L42*K42,0) -> #REF! | N42: =U42*$T$5 -> #REF! | O42: =ROUND(N42*K42,0) -> #REF! | P42: =N42+L42 -> #REF! | Q42: =P42*K42 -> #REF! | T42: 2025000 | U42: 180000
A43: 5 | B43: NVR 32chance - H.265+/H.265/H.264+/H.264 video formats - Intelligent analytics based on deep learning algorithm - Up to 4 SATA interfaces for HDD connection - 2 self-adaptive 10/100/1000 Mbps Ethernet interfaces | C43: COMMSCOPE | D43: set | K43: 1 | L43: =T43*$T$5 -> #REF! | M43: =ROUND(L43*K43,0) -> #REF! | N43: =U43*$T$5 -> #REF! | O43: =ROUND(N43*K43,0) -> #REF! | P43: =N43+L43 -> #REF! | Q43: =P43*K43 -> #REF! | T43: 10560000 | U43: 320000
A44: 6 | B44: Patch panel 24 ports - CAT6/ Thanh đấu nối cáp | C44: COMMSCOPE | D44: pcs | K44: 2 | L44: =T44*$T$5 -> #REF! | M44: =ROUND(L44*K44,0) -> #REF! | N44: =U44*$T$5 -> #REF! | O44: =ROUND(N44*K44,0) -> #REF! | P44: =N44+L44 -> #REF! | Q44: =P44*K44 -> #REF! | T44: 4224000 | U44: 397400
A45: 7 | B45: Patch cord FTP, CAT6, 4pair/ Dây nhảy | C45: COMMSCOPE | D45: pcs | K45: 32 | L45: =T45*$T$5 -> #REF! | M45: =ROUND(L45*K45,0) -> #REF! | N45: =U45*$T$5 -> #REF! | O45: =ROUND(N45*K45,0) -> #REF! | P45: =N45+L45 -> #REF! | Q45: =P45*K45 -> #REF! | T45: 32000 | U45: 136000
A46: 8 | B46: Switch 8 port POE gigabit/ Thiết bị chuyển mạch | C46: HIKVISION | D46: pcs | K46: 1 | L46: =T46*$T$5 -> #REF! | M46: =ROUND(L46*K46,0) -> #REF! | N46: =U46*$T$5 -> #REF! | O46: =ROUND(N46*K46,0) -> #REF! | P46: =N46+L46 -> #REF! | Q46: =P46*K46 -> #REF! | T46: 1760000 | U46: 120000
A47: 9 | B47: Thiết bị chuyển mạch 16 cổng Switch 16 port POE gigabit | C47: HIKVISION | D47: pcs | K47: 2 | L47: =T47*$T$5 -> #REF! | M47: =ROUND(L47*K47,0) -> #REF! | N47: =U47*$T$5 -> #REF! | O47: =ROUND(N47*K47,0) -> #REF! | P47: =N47+L47 -> #REF! | Q47: =P47*K47 -> #REF! | T47: 4816000 | U47: 150000
A48: 10 | B48: HDD 16TB/Ổ cứng HDD 16TB | D48: pcs | K48: 1 | L48: =T48*$T$5 -> #REF! | M48: =ROUND(L48*K48,0) -> #REF! | N48: =U48*$T$5 -> #REF! | O48: =ROUND(N48*K48,0) -> #REF! | P48: =N48+L48 -> #REF! | Q48: =P48*K48 -> #REF! | T48: 12030000 | U48: 80000
A49: 11 | B49: Monitor CCTV 47"/ Màn hình hiển thị CCTV 47'' | D49: pcs | K49: 2 | L49: =T49*$T$5 -> #REF! | M49: =ROUND(L49*K49,0) -> #REF! | N49: =U49*$T$5 -> #REF! | O49: =ROUND(N49*K49,0) -> #REF! | P49: =N49+L49 -> #REF! | Q49: =P49*K49 -> #REF! | T49: 5500000 | U49: 350000
A50: 12 | B50: Cable HDMI 30m/ Dây HDMI 30m | C50: Ugreen | D50: pcs | K50: 1 | L50: =T50*$T$5 -> #REF! | M50: =ROUND(L50*K50,0) -> #REF! | N50: =U50*$T$5 -> #REF! | O50: =ROUND(N50*K50,0) -> #REF! | P50: =N50+L50 -> #REF! | Q50: =P50*K50 -> #REF! | T50: 1450000 | U50: 320000
A51: 13 | B51: Máy bộ Dell Core i5 + bàn phím + chuột Computer Dell Core i5 - Intel Core i5 - 6500 ( 3.20GHz upto 3.60GHz) - H110 chipset intel. DDR4 8G Bus 2400 - SSD 120G sata III. HDD Seagate 1TB - NVIDIA Quadro K620 2Gb DDR3 128 Bit - Dell 24 Inch Led | D51: set | K51: 1 | L51: =T51*$T$5 -> #REF! | M51: =ROUND(L51*K51,0) -> #REF! | N51: =U51*$T$5 -> #REF! | O51: =ROUND(N51*K51,0) -> #REF! | P51: =N51+L51 -> #REF! | Q51: =P51*K51 -> #REF! | T51: 17000000 | U51: 320000
A52: 14 | B52: Cable FTP, CAT6, 4pair/ Cáp FTP, CAT6, 4pair | D52: m | K52: 1340 | L52: =T52*$T$5 -> #REF! | M52: =ROUND(L52*K52,0) -> #REF! | N52: =U52*$T$5 -> #REF! | O52: =ROUND(N52*K52,0) -> #REF! | P52: =N52+L52 -> #REF! | Q52: =P52*K52 -> #REF! | T52: 19500 | U52: 6200
A53: 15 | B53: Optical fiber 4FO Singlemode (OS1)/ Cáp quang 4FO Singlemode (OS1) | D53: m | K53: 168 | L53: =T53*$T$5 -> #REF! | M53: =ROUND(L53*K53,0) -> #REF! | N53: =U53*$T$5 -> #REF! | O53: =ROUND(N53*K53,0) -> #REF! | P53: =N53+L53 -> #REF! | Q53: =P53*K53 -> #REF! | T53: 6900 | U53: 4800
A54: 16 | B54: Cable 2C*2.5mm2 cu/xlpe/pvc + PE 1C*2.5mm2 CV/ Cáp 2C*2.5mm2 cu/xlpe/pvc + PE 1C*2.5mm2 CV | D54: m | K54: 168 | L54: =T54*$T$5 -> #REF! | M54: =ROUND(L54*K54,0) -> #REF! | N54: =U54*$T$5 -> #REF! | O54: =ROUND(N54*K54,0) -> #REF! | P54: =N54+L54 -> #REF! | Q54: =P54*K54 -> #REF! | T54: 35800 | U54: 11000
A55: 17 | B55: PVC conduit D20/ Ống điện D20 | D55: m | K55: 1020 | L55: =T55*$T$5 -> #REF! | M55: =ROUND(L55*K55,0) -> #REF! | N55: =U55*$T$5 -> #REF! | O55: =ROUND(N55*K55,0) -> #REF! | P55: =N55+L55 -> #REF! | Q55: =P55*K55 -> #REF! | U55: 22000
A56: 18 | B56: HDPE pipe D32/25/ Ống HDPE D32/25 | D56: m | K56: 64 | L56: =T56*$T$5 -> #REF! | M56: =ROUND(L56*K56,0) -> #REF! | N56: =U56*$T$5 -> #REF! | O56: =ROUND(N56*K56,0) -> #REF! | P56: =N56+L56 -> #REF! | Q56: =P56*K56 -> #REF! | T56: 13500 | U56: 18000
A57: 19 | B57: Steel colunm 3m, DN60/ Trụ sắt, cao 3m, DN60 | D57: pcs | K57: 3 | L57: =T57*$T$5 -> #REF! | M57: =ROUND(L57*K57,0) -> #REF! | N57: =U57*$T$5 -> #REF! | O57: =ROUND(N57*K57,0) -> #REF! | P57: =N57+L57 -> #REF! | Q57: =P57*K57 -> #REF! | T57: 220000 | U57: 55000
A58: 20 | B58: Vật tư phụ / Accessories | D58: lot | K58: 1 | L58: =T58*$T$5 -> #REF! | M58: =ROUND(L58*K58,0) -> #REF! | N58: =U58*$T$5 -> #REF! | O58: =ROUND(N58*K58,0) -> #REF! | P58: =N58+L58 -> #REF! | Q58: =P58*K58 -> #REF! | T58: 11700000
A59: 21 | B59: Install system, transport and programming using/ Lắp đặt, vận chuyển và cài đặt | D59: lot | K59: 1 | L59: =T59*$T$5 -> #REF! | M59: =ROUND(L59*K59,0) -> #REF! | N59: =U59*$T$5 -> #REF! | O59: =ROUND(N59*K59,0) -> #REF! | P59: =N59+L59 -> #REF! | Q59: =P59*K59 -> #REF! | U59: 35100000
A60: 22 | B60: Testing and comisioning/ Kiểm tra và vận hành thử | D60: lot | K60: 1 | L60: =T60*$T$5 -> #REF! | M60: =ROUND(L60*K60,0) -> #REF! | N60: =U60*$T$5 -> #REF! | O60: =ROUND(N60*K60,0) -> #REF! | P60: =N60+L60 -> #REF! | Q60: =P60*K60 -> #REF! | U60: 20000000
M61: =K61*L61 -> 0 | O61: =K61*N61 -> 0 | P61: =L61+N61 -> 0 | Q61: =K61*P61 -> 0
A62: III | B62: PA SYSTEM/ HỆ THỐNG ÂM THANH | M62: =SUM(M63:M79) -> #REF! | O62: =SUM(O63:O79) -> #REF! | Q62: =O62+M62 -> #REF!
A63: 1 | B63: Cabinet 19" - 27U Rack Power Distribution Unit, 12 Universal Outlets, 16A, 250V, MCB / Tủ rack điện nhẹ 19" - 27U, 12 Universal Outlets, 16A, 250V, MCB | D63: set | K63: 1 | L63: =T63*$T$5 -> #REF! | M63: =ROUND(L63*K63,0) -> #REF! | N63: =U63*$T$5 -> #REF! | O63: =ROUND(N63*K63,0) -> #REF! | P63: =N63+L63 -> #REF! | Q63: =P63*K63 -> #REF! | T63: 7285000 | U63: 420000
A64: 2 | B64: Ceiling Speaker 6W/ Loa âm trần 6W | C64: TOA | D64: pcs | K64: =8+11+1 -> 20 | L64: =T64*$T$5 -> #REF! | M64: =ROUND(L64*K64,0) -> #REF! | N64: =U64*$T$5 -> #REF! | O64: =ROUND(N64*K64,0) -> #REF! | P64: =N64+L64 -> #REF! | Q64: =P64*K64 -> #REF! | T64: 368000 | U64: 130000
A65: 3 | B65: Horn loudspeaker 30W/ Loa còi 30W | C65: TOA | D65: pcs | K65: 5 | L65: =T65*$T$5 -> #REF! | M65: =ROUND(L65*K65,0) -> #REF! | N65: =U65*$T$5 -> #REF! | O65: =ROUND(N65*K65,0) -> #REF! | P65: =N65+L65 -> #REF! | Q65: =P65*K65 -> #REF! | T65: 1520000 | U65: 130000
A66: 4 | B66: Emergency Notification/ Bộ phát thông báo khẩn cấp | C66: TOA | D66: set | K66: 1 | L66: =T66*$T$5 -> #REF! | M66: =ROUND(L66*K66,0) -> #REF! | N66: =U66*$T$5 -> #REF! | O66: =ROUND(N66*K66,0) -> #REF! | P66: =N66+L66 -> #REF! | Q66: =P66*K66 -> #REF! | T66: 17040000 | U66: 450000
A67: 5 | B67: Pre amplifier/ Bộ tiền khuếch đại | C67: TOA | D67: set | K67: 1 | L67: =T67*$T$5 -> #REF! | M67: =ROUND(L67*K67,0) -> #REF! | N67: =U67*$T$5 -> #REF! | O67: =ROUND(N67*K67,0) -> #REF! | P67: =N67+L67 -> #REF! | Q67: =P67*K67 -> #REF! | T67: 8710000 | U67: 450000
A68: 6 | B68: Central controller selects 16 zones/ Bộ trung tâm 16 vùng loa | C68: TOA | D68: set | K68: 1 | L68: =T68*$T$5 -> #REF! | M68: =ROUND(L68*K68,0) -> #REF! | N68: =U68*$T$5 -> #REF! | O68: =ROUND(N68*K68,0) -> #REF! | P68: =N68+L68 -> #REF! | Q68: =P68*K68 -> #REF! | T68: 15600000 | U68: 450000
A69: 7 | B69: 16-zone selector/ Bộ chọn 16 vùng loa | C69: TOA | D69: set | K69: 1 | L69: =T69*$T$5 -> #REF! | M69: =ROUND(L69*K69,0) -> #REF! | N69: =U69*$T$5 -> #REF! | O69: =ROUND(N69*K69,0) -> #REF! | P69: =N69+L69 -> #REF! | Q69: =P69*K69 -> #REF! | T69: 5265000 | U69: 250000
A70: 8 | B70: Microphone selection16 zones/ Micro thông báo chọn 16 vùng loa | C70: TOA | D70: set | K70: 1 | L70: =T70*$T$5 -> #REF! | M70: =ROUND(L70*K70,0) -> #REF! | N70: =U70*$T$5 -> #REF! | O70: =ROUND(N70*K70,0) -> #REF! | P70: =N70+L70 -> #REF! | Q70: =P70*K70 -> #REF! | T70: 7930000 | U70: 150000
A71: 9 | B71: Amplifier 650W/ Bộ khuyếch đại 650W | D71: set | K71: 1 | L71: =T71*$T$5 -> #REF! | M71: =ROUND(L71*K71,0) -> #REF! | N71: =U71*$T$5 -> #REF! | O71: =ROUND(N71*K71,0) -> #REF! | P71: =N71+L71 -> #REF! | Q71: =P71*K71 -> #REF! | T71: 20400000 | U71: 380000
A72: 10 | B72: UPS 1.5KVA, backup 2h/ Bộ lưu điện 1.5KVA , lưu điện 2h | D72: set | K72: 1 | L72: =T72*$T$5 -> #REF! | M72: =ROUND(L72*K72,0) -> #REF! | N72: =U72*$T$5 -> #REF! | O72: =ROUND(N72*K72,0) -> #REF! | P72: =N72+L72 -> #REF! | Q72: =P72*K72 -> #REF! | T72: 3200000
A73: 11 | B73: Cable 2C*1.5mm2 cu/pvc/pvc / Cáp 2C*1.5mm2 cu/pvc/pvc | D73: m | K73: 449 | L73: =T73*$T$5 -> #REF! | M73: =ROUND(L73*K73,0) -> #REF! | N73: =U73*$T$5 -> #REF! | O73: =ROUND(N73*K73,0) -> #REF! | P73: =N73+L73 -> #REF! | Q73: =P73*K73 -> #REF! | T73: 13000 | U73: 6200
A74: 12 | B74: Cable 3C*2.5mm2 cu/pvc/pvc / Cáp 3C*2.5mm2 cu/pvc/pvc | D74: m | K74: 12 | L74: =T74*$T$5 -> #REF! | M74: =ROUND(L74*K74,0) -> #REF! | N74: =U74*$T$5 -> #REF! | O74: =ROUND(N74*K74,0) -> #REF! | P74: =N74+L74 -> #REF! | Q74: =P74*K74 -> #REF! | T74: 34000 | U74: 7200
A75: 13 | B75: Cable FTP, CAT6, 4pair/ Cáp FTP, CAT6, 4pair | D75: m | K75: 46 | L75: =T75*$T$5 -> #REF! | M75: =ROUND(L75*K75,0) -> #REF! | N75: =U75*$T$5 -> #REF! | O75: =ROUND(N75*K75,0) -> #REF! | P75: =N75+L75 -> #REF! | Q75: =P75*K75 -> #REF! | T75: 19500 | U75: 6200
A76: 14 | B76: PVC Conduit D25, fire resistant 30min/ Ống điện D25 chống cháy 30 phút | D76: m | K76: 404 | L76: =T76*$T$5 -> #REF! | M76: =ROUND(L76*K76,0) -> #REF! | N76: =U76*$T$5 -> #REF! | O76: =ROUND(N76*K76,0) -> #REF! | P76: =N76+L76 -> #REF! | Q76: =P76*K76 -> #REF! | T76: 0 | U76: 25000
A77: 15 | B77: Vật tư phụ / Accessories | D77: lot | K77: 1 | L77: =T77*$T$5 -> #REF! | M77: =ROUND(L77*K77,0) -> #REF! | N77: =U77*$T$5 -> #REF! | O77: =ROUND(N77*K77,0) -> #REF! | P77: =N77+L77 -> #REF! | Q77: =P77*K77 -> #REF! | T77: 6300000
A78: 16 | B78: Install system, transport and programming using/ Lắp đặt, vận chuyển và cài đặt | D78: lot | K78: 1 | L78: =T78*$T$5 -> #REF! | M78: =ROUND(L78*K78,0) -> #REF! | N78: =U78*$T$5 -> #REF! | O78: =ROUND(N78*K78,0) -> #REF! | P78: =N78+L78 -> #REF! | Q78: =P78*K78 -> #REF! | U78: 10000000
M79: =K79*L79 -> 0 | O79: =K79*N79 -> 0 | P79: =L79+N79 -> 0 | Q79: =K79*P79 -> 0
A80: IV | B80: DOOR ACCESS CONTROL SYSTEM / HỆ THỐNG KIỂM SOÁT RA / VÀO | M80: =SUM(M81:M94) -> #REF! | O80: =SUM(O81:O94) -> #REF! | Q80: =O80+M80 -> #REF!
A81: 1 | B81: Bộ máy kiểm soát ra vào cửa Door Access Control - TCP/IP built-in connection LAN/WAN - Internal memory to manage 16,000 card or PIN users - Store 32,000 transactions when Off-Line - Connection coputer: TCP/IP hoặc RS485 - Full Access Control features: Automatically open the door according to Time Zone, Alarm when the door is broken or forgot to close | C81: Chiyu/ Taiwan | D81: set | K81: =1+2 -> 3 | L81: =T81*$T$5 -> #REF! | M81: =ROUND(L81*K81,0) -> #REF! | N81: =U81*$T$5 -> #REF! | O81: =ROUND(N81*K81,0) -> #REF! | P81: =N81+L81 -> #REF! | Q81: =P81*K81 -> #REF! | T81: 7029100 | U81: 600000
A82: 2 | B82: Push button / Nút nhấn mở cửa | C82: Pro-lock/ China | D82: set | K82: =2+1+7 -> 10 | L82: =T82*$T$5 -> #REF! | M82: =ROUND(L82*K82,0) -> #REF! | N82: =U82*$T$5 -> #REF! | O82: =ROUND(N82*K82,0) -> #REF! | P82: =N82+L82 -> #REF! | Q82: =P82*K82 -> #REF! | T82: 152100 | U82: 55000
A83: 3 | B83: Door lock/ Khóa từ | C83: Pro-lock/ China | D83: set | K83: =3+1+8 -> 12 | L83: =T83*$T$5 -> #REF! | M83: =ROUND(L83*K83,0) -> #REF! | N83: =U83*$T$5 -> #REF! | O83: =ROUND(N83*K83,0) -> #REF! | P83: =N83+L83 -> #REF! | Q83: =P83*K83 -> #REF! | T83: 754000 | U83: 250000
A84: 4 | B84: Door Sensor/ Cảm biến cửa | C84: ENFORCER/Taiwan | D84: set | K84: 12 | L84: =T84*$T$5 -> #REF! | M84: =ROUND(L84*K84,0) -> #REF! | N84: =U84*$T$5 -> #REF! | O84: =ROUND(N84*K84,0) -> #REF! | P84: =N84+L84 -> #REF! | Q84: =P84*K84 -> #REF! | T84: 195000 | U84: 250000
A85: 5 | B85: Backup power supply, battery backup 2hrs/ Bộ nguồn dự phòng mất điện công nghệ xung chuyên dụng Khả năng tích điện dự phòng từ 2 - 4 giờ trường hợp mất điện | C85: ACRO/ Taiwan | D85: set | K85: 1 | L85: =T85*$T$5 -> #REF! | M85: =ROUND(L85*K85,0) -> #REF! | N85: =U85*$T$5 -> #REF! | O85: =ROUND(N85*K85,0) -> #REF! | P85: =N85+L85 -> #REF! | Q85: =P85*K85 -> #REF! | T85: 1670500 | U85: 320000
A86: 6 | B86: Card reader/ Đầu đọc thẻ từ | C86: Chiyu/ Taiwan | D86: set | K86: =1+2 -> 3 | L86: =T86*$T$5 -> #REF! | M86: =ROUND(L86*K86,0) -> #REF! | N86: =U86*$T$5 -> #REF! | O86: =ROUND(N86*K86,0) -> #REF! | P86: =N86+L86 -> #REF! | Q86: =P86*K86 -> #REF! | T86: 1657500 | U86: 218000
A87: 7 | B87: Thick proximity card - 2mm - Surface: Milk white, cannot be printed by any thermal transfer printers or offset printing process/ Thẻ cảm ứng | C87: THIN PROXIMITY CARD | D87: set | K87: 20 | L87: =T87*$T$5 -> #REF! | M87: =ROUND(L87*K87,0) -> #REF! | N87: =U87*$T$5 -> #REF! | O87: =ROUND(N87*K87,0) -> #REF! | P87: =N87+L87 -> #REF! | Q87: =P87*K87 -> #REF! | T87: 10400 | U87: 0
A88: 8 | B88: Core Switch - 24port / Thiết bị chuyển mạch 24 cổng | C88: RUIJIE | D88: set | K88: 1 | L88: =T88*$T$5 -> #REF! | M88: =ROUND(L88*K88,0) -> #REF! | N88: =U88*$T$5 -> #REF! | O88: =ROUND(N88*K88,0) -> #REF! | P88: =N88+L88 -> #REF! | Q88: =P88*K88 -> #REF! | T88: 7144800 | U88: 580000
A89: 9 | B89: Cable FTP, CAT6, 4pair/ Cáp FTP, CAT6, 4pair | D89: m | K89: 173 | L89: =T89*$T$5 -> #REF! | M89: =ROUND(L89*K89,0) -> #REF! | N89: =U89*$T$5 -> #REF! | O89: =ROUND(N89*K89,0) -> #REF! | P89: =N89+L89 -> #REF! | Q89: =P89*K89 -> #REF! | T89: 19500 | U89: 6200
A90: 10 | B90: Cable 2C*1.5mm2 cu/pvc/pvc / Cáp 2C*1.5mm2 cu/pvc/pvc | D90: m | K90: 198 | L90: =T90*$T$5 -> #REF! | M90: =ROUND(L90*K90,0) -> #REF! | N90: =U90*$T$5 -> #REF! | O90: =ROUND(N90*K90,0) -> #REF! | P90: =N90+L90 -> #REF! | Q90: =P90*K90 -> #REF! | T90: 13000 | U90: 6200
A91: 11 | B91: PVC conduit D20/ Ống điện D20 | D91: m | K91: 334 | L91: =T91*$T$5 -> #REF! | M91: =ROUND(L91*K91,0) -> #REF! | N91: =U91*$T$5 -> #REF! | O91: =ROUND(N91*K91,0) -> #REF! | P91: =N91+L91 -> #REF! | Q91: =P91*K91 -> #REF! | U91: 22000
A92: 12 | B92: Testing and comisioning/ Kiểm tra và vận hành thử | D92: lot | K92: 1 | L92: =T92*$T$5 -> #REF! | M92: =ROUND(L92*K92,0) -> #REF! | N92: =U92*$T$5 -> #REF! | O92: =ROUND(N92*K92,0) -> #REF! | P92: =N92+L92 -> #REF! | Q92: =P92*K92 -> #REF! | U92: 5000000
A93: 13 | B93: Accessories / Vật tư phụ | D93: lot | K93: 1 | L93: =T93*$T$5 -> #REF! | M93: =ROUND(L93*K93,0) -> #REF! | N93: =U93*$T$5 -> #REF! | O93: =ROUND(N93*K93,0) -> #REF! | P93: =N93+L93 -> #REF! | Q93: =P93*K93 -> #REF! | T93: 0 | U93: 3000000
M94: =K94*L94 -> 0 | O94: =K94*N94 -> 0 | P94: =L94+N94 -> 0 | Q94: =K94*P94 -> 0
A95: V | B95: ELV EARTHING SYSTEM / HỆ THỐNG NỐI ĐẤT ELV | M95: =SUM(M96:M104) -> #REF! | O95: =SUM(O96:O104) -> #REF! | Q95: =O95+M95 -> #REF!
A96: 1 | B96: Earth rod D16, L=2,4m/Cọc tiếp địa D16, L2.4m | D96: set | K96: 6 | L96: =T96*$T$5 -> #REF! | M96: =ROUND(L96*K96,0) -> #REF! | N96: =U96*$T$5 -> #REF! | O96: =ROUND(N96*K96,0) -> #REF! | P96: =N96+L96 -> #REF! | Q96: =P96*K96 -> #REF! | T96: 120000 | U96: 250000
A97: 2 | B97: Grounding well 10m deep/Giếng khoan tiếp địa sâu 10m | D97: set | K97: 4 | L97: =T97*$T$5 -> #REF! | M97: =ROUND(L97*K97,0) -> #REF! | N97: =U97*$T$5 -> #REF! | O97: =ROUND(N97*K97,0) -> #REF! | P97: =N97+L97 -> #REF! | Q97: =P97*K97 -> #REF! | U97: 2500000
A98: 3 | B98: Bare Coper cable Cu-50mm2 /Cáp đồng trần 50mm2 | D98: m | K98: 74 | L98: =T98*$T$5 -> #REF! | M98: =ROUND(L98*K98,0) -> #REF! | N98: =U98*$T$5 -> #REF! | O98: =ROUND(N98*K98,0) -> #REF! | P98: =N98+L98 -> #REF! | Q98: =P98*K98 -> #REF! | T98: 118000 | U98: 60000
A99: 4 | B99: Cable CV 1C*16mm2/ Cáp CV 1C*16mm2 | D99: m | K99: 20 | L99: =T99*$T$5 -> #REF! | M99: =ROUND(L99*K99,0) -> #REF! | N99: =U99*$T$5 -> #REF! | O99: =ROUND(N99*K99,0) -> #REF! | P99: =N99+L99 -> #REF! | Q99: =P99*K99 -> #REF! | T99: 57040 | U99: 30000
A100: 5 | B100: Cadweld/ Hàn hóa nhiệt | D100: lot | K100: 6 | L100: =T100*$T$5 -> #REF! | M100: =ROUND(L100*K100,0) -> #REF! | N100: =U100*$T$5 -> #REF! | O100: =ROUND(N100*K100,0) -> #REF! | P100: =N100+L100 -> #REF! | Q100: =P100*K100 -> #REF! | T100: 300000 | U100: 150000
A101: 6 | B101: Earthing testbox/ Hộp kiểm tra tiếp địa | D101: set | K101: 1 | L101: =T101*$T$5 -> #REF! | M101: =ROUND(L101*K101,0) -> #REF! | N101: =U101*$T$5 -> #REF! | O101: =ROUND(N101*K101,0) -> #REF! | P101: =N101+L101 -> #REF! | Q101: =P101*K101 -> #REF! | T101: 300000 | U101: 150000
A102: 7 | B102: Dig and filling the ground / Đào và san lấp | D102: m3 | K102: =(0.4+0.6)*0.8*0.5*30 -> 12 | L102: =T102*$T$5 -> #REF! | M102: =ROUND(L102*K102,0) -> #REF! | N102: =U102*$T$5 -> #REF! | O102: =ROUND(N102*K102,0) -> #REF! | P102: =N102+L102 -> #REF! | Q102: =P102*K102 -> #REF! | U102: 220000
A103: 8 | B103: Accessories/ Vật tư phụ | D103: lot | K103: 1 | L103: =T103*$T$5 -> #REF! | M103: =ROUND(L103*K103,0) -> #REF! | N103: =U103*$T$5 -> #REF! | O103: =ROUND(N103*K103,0) -> #REF! | P103: =N103+L103 -> #REF! | Q103: =P103*K103 -> #REF! | T103: 1500000 | U103: 1000000
...

Sheet PL01.PLUMPING
A1: ESTIMATE DETAIL TABLE | N1: hd
A2: ='Bill 3-External works'!#REF! -> #REF!
A3: ITEM/HẠNG MỤC : PLUMPING SYSTEM/HỆ THỐNG NƯỚC
A5: No. | B5: DESCRIPTION | C5: STANDARD | D5: Unit | E5: DIMENSION | J5: QUANTITY | K5: Q'TY | L5: MATERIAL | N5: LABOUR & EQUIPMENT | P5: TOTAL COST | R5: REMARK | S5: ='E02.ELV SYSTEM '!S5 -> #REF! | T5: ='E02.ELV SYSTEM '!T5 -> #REF!
E6: No | F6: L | G6: W | H6: H | I6: HS | J6: COMPONENT | L6: UNIT | M6: AMOUNT | N6: UNIT | O6: AMOUNT | P6: UNIT | Q6: AMOUNT | T6: ='E02.ELV SYSTEM '!T6 -> #REF! | U6: ='E02.ELV SYSTEM '!U6 -> #REF!
A7: P01 | B7: PLUMPING SYSTEM/HỆ THỐNG CẤP THOÁT NƯỚC | M7: =SUM(M8:M11) -> #REF! | O7: =SUM(O8:O11) -> #REF! | Q7: =M7+O7 -> #REF!
A8: =A12 -> I | B8: =B12 -> WATER SUPPLY SYSTEM/ HỆ THỐNG CẤP NƯỚC | M8: =M12 -> #REF! | O8: =O12 -> #REF! | Q8: =Q12 -> #REF!
A9: =A61 -> II | B9: =B61 -> WATER DRAINAGE SYSTEM/ HỆ THỐNG THOÁT NƯỚC | M9: =M61 -> #REF! | O9: =O61 -> #REF! | Q9: =Q61 -> #REF!
A10: =A114 -> III | B10: =B114 -> OTHER WORKS/CÔNG TÁC KHÁC | M10: =M114 -> #REF! | O10: =O114 -> #REF! | Q10: =O10+M10 -> #REF!
A12: I | B12: WATER SUPPLY SYSTEM/ HỆ THỐNG CẤP NƯỚC | M12: =SUBTOTAL(109,M13:M60) -> #REF! | O12: =SUBTOTAL(109,O13:O60) -> #REF! | Q12: =O12+M12 -> #REF!
B13: PIPING WORKS/ ĐƯỜNG ỐNG
A14: 1 | B14: PP-R pipe DN65/ Ống PP-R DN65 | D14: m | K14: 90 | L14: =T14*$T$5 -> #REF! | M14: =ROUND(L14*K14,0) -> #REF! | N14: =U14*$T$5 -> #REF! | O14: =ROUND(N14*K14,0) -> #REF! | P14: =N14+L14 -> #REF! | Q14: =P14*K14 -> #REF! | T14: 134657.14 | U14: 54000
A15: 2 | B15: Galvanized steel pipe DN80/Ống tráng kẽm lồng DN80 | D15: m | K15: 36 | L15: =T15*$T$5 -> #REF! | M15: =ROUND(L15*K15,0) -> #REF! | N15: =U15*$T$5 -> #REF! | O15: =ROUND(N15*K15,0) -> #REF! | P15: =N15+L15 -> #REF! | Q15: =P15*K15 -> #REF! | T15: 158571.43 | U15: 160000
A16: 3 | B16: PP-R pipe DN50/ Ống PP-R DB50 | D16: m | K16: 23 | L16: =T16*$T$5 -> #REF! | M16: =ROUND(L16*K16,0) -> #REF! | N16: =U16*$T$5 -> #REF! | O16: =ROUND(N16*K16,0) -> #REF! | P16: =N16+L16 -> #REF! | Q16: =P16*K16 -> #REF! | T16: 84428.571 | U16: 44000
A17: 4 | B17: PP-R pipe DN40/ Ống PP-R DN40 | D17: m | K17: 132 | L17: =T17*$T$5 -> #REF! | M17: =ROUND(L17*K17,0) -> #REF! | N17: =U17*$T$5 -> #REF! | O17: =ROUND(N17*K17,0) -> #REF! | P17: =N17+L17 -> #REF! | Q17: =P17*K17 -> #REF! | T17: 57600 | U17: 36000
A18: 5 | B18: PP-R pipe DN32/ Ống PP-R DN32 | D18: m | K18: 160 | L18: =T18*$T$5 -> #REF! | M18: =ROUND(L18*K18,0) -> #REF! | N18: =U18*$T$5 -> #REF! | O18: =ROUND(N18*K18,0) -> #REF! | P18: =N18+L18 -> #REF! | Q18: =P18*K18 -> #REF! | T18: 42942.857 | U18: 32000
A19: 6 | B19: PP-R pipe DN25/ Ống PP-R DN25 | D19: m | K19: 149 | L19: =T19*$T$5 -> #REF! | M19: =ROUND(L19*K19,0) -> #REF! | N19: =U19*$T$5 -> #REF! | O19: =ROUND(N19*K19,0) -> #REF! | P19: =N19+L19 -> #REF! | Q19: =P19*K19 -> #REF! | T19: 23571.429 | U19: 25000
A20: 7 | B20: PP-R pipe DN20/ Ống PP-R DN20 | D20: m | K20: 172 | L20: =T20*$T$5 -> #REF! | M20: =ROUND(L20*K20,0) -> #REF! | N20: =U20*$T$5 -> #REF! | O20: =ROUND(N20*K20,0) -> #REF! | P20: =N20+L20 -> #REF! | Q20: =P20*K20 -> #REF! | T20: 15514.286 | U20: 20000
A21: 8 | B21: Fitting for pipe/ Phụ kiện đường ống | D21: lot | K21: 1 | L21: =T21*$T$5 -> #REF! | M21: =ROUND(L21*K21,0) -> #REF! | N21: =U21*$T$5 -> #REF! | O21: =ROUND(N21*K21,0) -> #REF! | P21: =N21+L21 -> #REF! | Q21: =P21*K21 -> #REF! | T21: 20727969 | U21: 6218390.6
A22: 9 | B22: Excavation and backfilling for underground pipe/ Đào và lắp đất cho đường ống ngầm | D22: lot | K22: 1 | L22: =T22*$T$5 -> #REF! | M22: =ROUND(L22*K22,0) -> #REF! | N22: =U22*$T$5 -> #REF! | O22: =ROUND(N22*K22,0) -> #REF! | P22: =N22+L22 -> #REF! | Q22: =P22*K22 -> #REF! | U22: 16800000
A23: 10 | B23: Hanger, support/ Giá đỡ, ty treo | D23: lot | K23: 1 | L23: =T23*$T$5 -> #REF! | M23: =ROUND(L23*K23,0) -> #REF! | N23: =U23*$T$5 -> #REF! | O23: =ROUND(N23*K23,0) -> #REF! | P23: =N23+L23 -> #REF! | Q23: =P23*K23 -> #REF! | T23: 6909322.9 | U23: 2072796.9
A24: 11 | B24: Accessories/Vật tư phụ | D24: lot | K24: 1 | L24: =T24*$T$5 -> #REF! | M24: =ROUND(L24*K24,0) -> #REF! | N24: =U24*$T$5 -> #REF! | O24: =ROUND(N24*K24,0) -> #REF! | P24: =N24+L24 -> #REF! | Q24: =P24*K24 -> #REF! | T24: 1750000 | U24: 350000
B25: VALVE/ VAN
A26: 8 | B26: Gate valve D63/ Van cổng D63 | D26: pcs | K26: 2 | L26: =T26*$T$5 -> #REF! | M26: =ROUND(L26*K26,0) -> #REF! | N26: =U26*$T$5 -> #REF! | O26: =ROUND(N26*K26,0) -> #REF! | P26: =N26+L26 -> #REF! | Q26: =P26*K26 -> #REF! | T26: 1057114.3 | U26: 80000
A27: 9 | B27: Gate valve D50/ Van cổng D50 | D27: pcs | K27: 2 | L27: =T27*$T$5 -> #REF! | M27: =ROUND(L27*K27,0) -> #REF! | N27: =U27*$T$5 -> #REF! | O27: =ROUND(N27*K27,0) -> #REF! | P27: =N27+L27 -> #REF! | Q27: =P27*K27 -> #REF! | T27: 679714.29 | U27: 60000
A28: 10 | B28: Gate valve D40/ Van cổng D40 | D28: pcs | K28: 1 | L28: =T28*$T$5 -> #REF! | M28: =ROUND(L28*K28,0) -> #REF! | N28: =U28*$T$5 -> #REF! | O28: =ROUND(N28*K28,0) -> #REF! | P28: =N28+L28 -> #REF! | Q28: =P28*K28 -> #REF! | T28: 441171.43 | U28: 50000
A29: 11 | B29: Gate valve D32/ Van cổng D32 | D29: pcs | K29: 9 | L29: =T29*$T$5 -> #REF! | M29: =ROUND(L29*K29,0) -> #REF! | N29: =U29*$T$5 -> #REF! | O29: =ROUND(N29*K29,0) -> #REF! | P29: =N29+L29 -> #REF! | Q29: =P29*K29 -> #REF! | T29: 262971.43 | U29: 45000
A30: 12 | B30: Gate valve D25/ Van cổng D25 | D30: pcs | K30: 7 | L30: =T30*$T$5 -> #REF! | M30: =ROUND(L30*K30,0) -> #REF! | N30: =U30*$T$5 -> #REF! | O30: =ROUND(N30*K30,0) -> #REF! | P30: =N30+L30 -> #REF! | Q30: =P30*K30 -> #REF! | T30: 185314.29 | U30: 40000
A31: 13 | B31: Gate valve D20/ Van cổng D20 | D31: pcs | K31: 6 | L31: =T31*$T$5 -> #REF! | M31: =ROUND(L31*K31,0) -> #REF! | N31: =U31*$T$5 -> #REF! | O31: =ROUND(N31*K31,0) -> #REF! | P31: =N31+L31 -> #REF! | Q31: =P31*K31 -> #REF! | T31: 158571.43 | U31: 35000
A32: 14 | B32: Faucet for watering plants/ Vòi nước tưới cây | D32: pcs | K32: 14 | L32: =T32*$T$5 -> #REF! | M32: =ROUND(L32*K32,0) -> #REF! | N32: =U32*$T$5 -> #REF! | O32: =ROUND(N32*K32,0) -> #REF! | P32: =N32+L32 -> #REF! | Q32: =P32*K32 -> #REF! | T32: 135000 | U32: 30000
B33: METER ASSEMBLY/ CỤM ĐỒNG HỒ
A34: 19 | B34: Gate valve DN50/ Van cổng DN50 | K34: 2 | L34: =T34*$T$5 -> #REF! | M34: =ROUND(L34*K34,0) -> #REF! | N34: =U34*$T$5 -> #REF! | O34: =ROUND(N34*K34,0) -> #REF! | P34: =N34+L34 -> #REF! | Q34: =P34*K34 -> #REF! | T34: 679714.29 | U34: 60000
A35: 20 | B35: Male socke DN65/ Đầu nối răng DN65 | K35: 4 | L35: =T35*$T$5 -> #REF! | M35: =ROUND(L35*K35,0) -> #REF! | N35: =U35*$T$5 -> #REF! | O35: =ROUND(N35*K35,0) -> #REF! | P35: =N35+L35 -> #REF! | Q35: =P35*K35 -> #REF! | T35: 276000 | U35: 60000
A36: 21 | B36: Adaptor DN65/ Rắc co DN65 | K36: 2 | L36: =T36*$T$5 -> #REF! | M36: =ROUND(L36*K36,0) -> #REF! | N36: =U36*$T$5 -> #REF! | O36: =ROUND(N36*K36,0) -> #REF! | P36: =N36+L36 -> #REF! | Q36: =P36*K36 -> #REF! | T36: 445000 | U36: 60000
A37: 22 | B37: Water meter DN50/ Đồng hồ nước DN50 | K37: 1 | L37: =T37*$T$5 -> #REF! | M37: =ROUND(L37*K37,0) -> #REF! | N37: =U37*$T$5 -> #REF! | O37: =ROUND(N37*K37,0) -> #REF! | P37: =N37+L37 -> #REF! | Q37: =P37*K37 -> #REF! | T37: 6500000 | U37: 2500000
A38: 23 | B38: Cover box water clock/Hộp chứa đồng hồ | K38: 1 | L38: =T38*$T$5 -> #REF! | M38: =ROUND(L38*K38,0) -> #REF! | N38: =U38*$T$5 -> #REF! | O38: =ROUND(N38*K38,0) -> #REF! | P38: =N38+L38 -> #REF! | Q38: =P38*K38 -> #REF! | T38: 555000 | U38: 125000
A39: 24 | B39: Accessories / Vật tư phụ | K39: 1 | L39: =T39*$T$5 -> #REF! | M39: =ROUND(L39*K39,0) -> #REF! | N39: =U39*$T$5 -> #REF! | O39: =ROUND(N39*K39,0) -> #REF! | P39: =N39+L39 -> #REF! | Q39: =P39*K39 -> #REF! | T39: 12833429 | U39: 3850028.6
B40: COMPLETED SET BOOSTER PUMP 1ST FLOOR/CỤM BỒN NƯỚC MÁY BƠM TẦNG TRỆT
A41: 25 | B41: 2000L SS304 water tank/Bồn nước đứng INOX 2000l | D41: pcs | K41: 1 | L41: =T41*$T$5 -> #REF! | M41: =ROUND(L41*K41,0) -> #REF! | N41: =U41*$T$5 -> #REF! | O41: =ROUND(N41*K41,0) -> #REF! | P41: =N41+L41 -> #REF! | Q41: =P41*K41 -> #REF! | T41: 8150000 | U41: 825000
A42: 26 | B42: Float vale/ Van phao cơ | D42: pcs | K42: 2 | L42: =T42*$T$5 -> #REF! | M42: =ROUND(L42*K42,0) -> #REF! | N42: =U42*$T$5 -> #REF! | O42: =ROUND(N42*K42,0) -> #REF! | P42: =N42+L42 -> #REF! | Q42: =P42*K42 -> #REF! | T42: 1850000 | U42: 115000
A43: 27 | B43: Water level probe/Que dò mực nước | D43: set | K43: 1 | L43: =T43*$T$5 -> #REF! | M43: =ROUND(L43*K43,0) -> #REF! | N43: =U43*$T$5 -> #REF! | O43: =ROUND(N43*K43,0) -> #REF! | P43: =N43+L43 -> #REF! | Q43: =P43*K43 -> #REF! | T43: 425000 | U43: 115000
A44: 28 | B44: Pump control panel/Tủ điều khiển bơm | D44: set | K44: 1 | L44: =T44*$T$5 -> #REF! | M44: =ROUND(L44*K44,0) -> #REF! | N44: =U44*$T$5 -> #REF! | O44: =ROUND(N44*K44,0) -> #REF! | P44: =N44+L44 -> #REF! | Q44: =P44*K44 -> #REF! | T44: 8500000 | U44: 750000
A45: 29 | B45: Booster pump Q=3 m3/h, H=25m / Bơm trung chuyển Q=3m3/h, H=25m | C45: Pentax | D45: set | K45: 2 | L45: =T45*$T$5 -> #REF! | M45: =ROUND(L45*K45,0) -> #REF! | N45: =U45*$T$5 -> #REF! | O45: =ROUND(N45*K45,0) -> #REF! | P45: =N45+L45 -> #REF! | Q45: =P45*K45 -> #REF! | T45: 12540000 | U45: 550000
A46: 30 | B46: Vavle assembly/ Cụm van | D46: lot | K46: 1 | L46: =T46*$T$5 -> #REF! | M46: =ROUND(L46*K46,0) -> #REF! | N46: =U46*$T$5 -> #REF! | O46: =ROUND(N46*K46,0) -> #REF! | P46: =N46+L46 -> #REF! | Q46: =P46*K46 -> #REF! | T46: 4500000 | U46: 1350000
A47: 31 | B47: Power and control cable/ Dây cấp nguồn và điều khiển | D47: lot | K47: 1 | L47: =T47*$T$5 -> #REF! | M47: =ROUND(L47*K47,0) -> #REF! | N47: =U47*$T$5 -> #REF! | O47: =ROUND(N47*K47,0) -> #REF! | P47: =N47+L47 -> #REF! | Q47: =P47*K47 -> #REF! | T47: 5000000 | U47: 2500000
A48: 32 | B48: Pump support/ Bệ đở bơm | D48: lot | K48: 1 | L48: =T48*$T$5 -> #REF! | M48: =ROUND(L48*K48,0) -> #REF! | N48: =U48*$T$5 -> #REF! | O48: =ROUND(N48*K48,0) -> #REF! | P48: =N48+L48 -> #REF! | Q48: =P48*K48 -> #REF! | T48: 3500000 | U48: 1500000
A49: 33 | B49: Accessories / Vật tư phụ | D49: lot | K49: 1 | L49: =T49*$T$5 -> #REF! | M49: =ROUND(L49*K49,0) -> #REF! | N49: =U49*$T$5 -> #REF! | O49: =ROUND(N49*K49,0) -> #REF! | P49: =N49+L49 -> #REF! | Q49: =P49*K49 -> #REF! | T49: 4172000 | U49: 1251600
B50: COMPLETED SET BOOSTER PUMP ROOF FLOOR/CỤM BỒN NƯỚC MÁY BƠM TẦNG MÁI
A51: 34 | B51: 1500L SS304 water tank/ Bồn nước ngang INOX 1500l | D51: bồn | K51: 1 | L51: =T51*$T$5 -> #REF! | M51: =ROUND(L51*K51,0) -> #REF! | N51: =U51*$T$5 -> #REF! | O51: =ROUND(N51*K51,0) -> #REF! | P51: =N51+L51 -> #REF! | Q51: =P51*K51 -> #REF! | T51: 7815000 | U51: 825000
A52: 35 | B52: Float vale/ Van phao cơ | D52: cái | K52: 1 | L52: =T52*$T$5 -> #REF! | M52: =ROUND(L52*K52,0) -> #REF! | N52: =U52*$T$5 -> #REF! | O52: =ROUND(N52*K52,0) -> #REF! | P52: =N52+L52 -> #REF! | Q52: =P52*K52 -> #REF! | T52: 1850000 | U52: 115000
A53: 36 | B53: Water level probe/Que dò mực nước | D53: bộ | K53: 1 | L53: =T53*$T$5 -> #REF! | M53: =ROUND(L53*K53,0) -> #REF! | N53: =U53*$T$5 -> #REF! | O53: =ROUND(N53*K53,0) -> #REF! | P53: =N53+L53 -> #REF! | Q53: =P53*K53 -> #REF! | T53: 550000 | U53: 115000
A54: 37 | B54: Pump control panel/Tủ điều khiển bơm | D54: tủ | K54: 1 | L54: =T54*$T$5 -> #REF! | M54: =ROUND(L54*K54,0) -> #REF! | N54: =U54*$T$5 -> #REF! | O54: =ROUND(N54*K54,0) -> #REF! | P54: =N54+L54 -> #REF! | Q54: =P54*K54 -> #REF! | T54: 8500000 | U54: 1200000
A55: 38 | B55: Booster pump Q=1.4l/s H=25m, inverter/ Bơm tăng áp Q=1.4l/s H=25m biến tần | D55: bơm | K55: 2 | L55: =T55*$T$5 -> #REF! | M55: =ROUND(L55*K55,0) -> #REF! | N55: =U55*$T$5 -> #REF! | O55: =ROUND(N55*K55,0) -> #REF! | P55: =N55+L55 -> #REF! | Q55: =P55*K55 -> #REF! | T55: 6500000 | U55: 1950000
A56: 39 | B56: Vavle assembly/ Cụm van | D56: lô | K56: 1 | L56: =T56*$T$5 -> #REF! | M56: =ROUND(L56*K56,0) -> #REF! | N56: =U56*$T$5 -> #REF! | O56: =ROUND(N56*K56,0) -> #REF! | P56: =N56+L56 -> #REF! | Q56: =P56*K56 -> #REF! | T56: 5000000 | U56: 2500000
A57: 40 | B57: Power and control cable/ Dây cấp nguồn và điều khiển | D57: lô | K57: 1 | L57: =T57*$T$5 -> #REF! | M57: =ROUND(L57*K57,0) -> #REF! | N57: =U57*$T$5 -> #REF! | O57: =ROUND(N57*K57,0) -> #REF! | P57: =N57+L57 -> #REF! | Q57: =P57*K57 -> #REF! | T57: 3500000 | U57: 1500000
A58: 41 | B58: Pump support/ Bệ đở bơm | D58: lô | K58: 1 | L58: =T58*$T$5 -> #REF! | M58: =ROUND(L58*K58,0) -> #REF! | N58: =U58*$T$5 -> #REF! | O58: =ROUND(N58*K58,0) -> #REF! | P58: =N58+L58 -> #REF! | Q58: =P58*K58 -> #REF! | T58: 5037000 | U58: 1511100
A59: 42 | B59: Accessories / Vật tư phụ | D59: lô | K59: 1 | L59: =T59*$T$5 -> #REF! | M59: =ROUND(L59*K59,0) -> #REF! | N59: =U59*$T$5 -> #REF! | O59: =ROUND(N59*K59,0) -> #REF! | P59: =N59+L59 -> #REF! | Q59: =P59*K59 -> #REF! | T59: 5691810 | U59: 1707543
A61: II | B61: WATER DRAINAGE SYSTEM/ HỆ THỐNG THOÁT NƯỚC | M61: =SUBTOTAL(109,M62:M118) -> #REF! | O61: =SUBTOTAL(109,O62:O118) -> #REF! | Q61: =O61+M61 -> #REF!
B62: STORM DRAINAGE WATER SYSTEM/ HỆ THỐNG THOÁT NƯỚC MƯA
A63: 1 | B63: uPVC pipe D60, 2.5mm thickness/ Ống nước uPVC D60 dày 2.5mm | D63: m | K63: 24 | L63: =T63*$T$5 -> #REF! | M63: =ROUND(L63*K63,0) -> #REF! | N63: =U63*$T$5 -> #REF! | O63: =ROUND(N63*K63,0) -> #REF! | P63: =N63+L63 -> #REF! | Q63: =P63*K63 -> #REF! | T63: 50722.857 | U63: 28000
A64: 2 | B64: uPVC pipe D90, 3.5mm thickness / Ống nước uPVC D90 dày 3.5mm | C64: Tiền Phong, Bình Minh | D64: m | K64: 65 | L64: =T64*$T$5 -> #REF! | M64: =ROUND(L64*K64,0) -> #REF! | N64: =U64*$T$5 -> #REF! | O64: =ROUND(N64*K64,0) -> #REF! | P64: =N64+L64 -> #REF! | Q64: =P64*K64 -> #REF! | T64: 102851.43 | U64: 40000
A65: 3 | B65: uPVC pipe D114, 4.5mm thickness / Ống nước uPVC D114 dày 4.5mm | C65: Tiền Phong, Bình Minh | D65: m | K65: 52 | L65: =T65*$T$5 -> #REF! | M65: =ROUND(L65*K65,0) -> #REF! | N65: =U65*$T$5 -> #REF! | O65: =ROUND(N65*K65,0) -> #REF! | P65: =N65+L65 -> #REF! | Q65: =P65*K65 -> #REF! | T65: 166460 | U65: 50000
A66: 4 | B66: uPVC pipe D140, 6.7mm thickness /Ống nước uPVC D140 dày 6.7mm | C66: Tiền Phong, Bình Minh | D66: m | K66: 416 | L66: =T66*$T$5 -> #REF! | M66: =ROUND(L66*K66,0) -> #REF! | N66: =U66*$T$5 -> #REF! | O66: =ROUND(N66*K66,0) -> #REF! | P66: =N66+L66 -> #REF! | Q66: =P66*K66 -> #REF! | T66: 302580 | U66: 60000
A67: 5 | B67: uPVC pipe D168, 6.6mm thickness / Ống nước uPVC D168 dày 6.6mm | C67: Tiền Phong, Bình Minh | D67: m | K67: 20 | L67: =T67*$T$5 -> #REF! | M67: =ROUND(L67*K67,0) -> #REF! | N67: =U67*$T$5 -> #REF! | O67: =ROUND(N67*K67,0) -> #REF! | P67: =N67+L67 -> #REF! | Q67: =P67*K67 -> #REF! | T67: 357168.57 | U67: 90000
A68: 6 | B68: uPVC pipe D220, 8.3mm thickness / Ống nước uPVC D220 dày 8.3mm | C68: Tiền Phong, Bình Minh | D68: m | K68: 70 | L68: =T68*$T$5 -> #REF! | M68: =ROUND(L68*K68,0) -> #REF! | N68: =U68*$T$5 -> #REF! | O68: =ROUND(N68*K68,0) -> #REF! | P68: =N68+L68 -> #REF! | Q68: =P68*K68 -> #REF! | T68: 579388.57 | U68: 120000
A69: 7 | B69: Fittings/ Phụ kiện đường ống uPVC | C69: Tiền Phong, Bình Minh | D69: lot | K69: 1 | L69: =T69*$T$5 -> #REF! | M69: =ROUND(L69*K69,0) -> #REF! | N69: =U69*$T$5 -> #REF! | O69: =ROUND(N69*K69,0) -> #REF! | P69: =N69+L69 -> #REF! | Q69: =P69*K69 -> #REF! | T69: 27480000 | U69: 11250000
A70: 9 | B70: Roof drain D100/ Cầu chắn rác D100 | C70: Tiền Phong, Bình Minh | D70: pcs | K70: 9 | L70: =T70*$T$5 -> #REF! | M70: =ROUND(L70*K70,0) -> #REF! | N70: =U70*$T$5 -> #REF! | O70: =ROUND(N70*K70,0) -> #REF! | P70: =N70+L70 -> #REF! | Q70: =P70*K70 -> #REF! | T70: 228571.43 | U70: 50000
A71: 10 | B71: Roof drain D80/ Cầu chắn rác D80 | C71: Tiền Phong, Bình Minh | D71: pcs | K71: 2 | L71: =T71*$T$5 -> #REF! | M71: =ROUND(L71*K71,0) -> #REF! | N71: =U71*$T$5 -> #REF! | O71: =ROUND(N71*K71,0) -> #REF! | P71: =N71+L71 -> #REF! | Q71: =P71*K71 -> #REF! | T71: 185714.29 | U71: 50000
A72: 11 | B72: Roof drain D60/ Cầu chắn rác D60 | C72: Tiền Phong, Bình Minh | D72: pcs | K72: 2 | L72: =T72*$T$5 -> #REF! | M72: =ROUND(L72*K72,0) -> #REF! | N72: =U72*$T$5 -> #REF! | O72: =ROUND(N72*K72,0) -> #REF! | P72: =N72+L72 -> #REF! | Q72: =P72*K72 -> #REF! | T72: 157142.86 | U72: 50000
A73: 13 | B73: Bedding sand backfilling for underground pipe/ đắp cát cho ống ngầm | C73: Tiền Phong, Bình Minh | D73: lot | K73: 1 | L73: =T73*$T$5 -> #REF! | M73: =ROUND(L73*K73,0) -> #REF! | N73: =U73*$T$5 -> #REF! | O73: =ROUND(N73*K73,0) -> #REF! | P73: =N73+L73 -> #REF! | Q73: =P73*K73 -> #REF! | T73: 1500000 | U73: 12000000
A74: 13 | B74: Excavation and backfilling for underground pipe/ đào và lấp đất ống ngầm | C74: Tiền Phong, Bình Minh | D74: lot | K74: 1 | L74: =T74*$T$5 -> #REF! | M74: =ROUND(L74*K74,0) -> #REF! | N74: =U74*$T$5 -> #REF! | O74: =ROUND(N74*K74,0) -> #REF! | P74: =N74+L74 -> #REF! | Q74: =P74*K74 -> #REF! | T74: 1500000 | U74: 12000000
A75: 9 | B75: Fitting for pipe/ Phụ kiện đường ống | D75: lot | K75: 1 | L75: =T75*$T$5 -> #REF! | M75: =ROUND(L75*K75,0) -> #REF! | N75: =U75*$T$5 -> #REF! | O75: =ROUND(N75*K75,0) -> #REF! | P75: =N75+L75 -> #REF! | Q75: =P75*K75 -> #REF! | T75: 20727969 | U75: 6218390.6
A76: 10 | B76: Hanger, support/ Giá đỡ, ty treo | D76: lot | K76: 1 | L76: =T76*$T$5 -> #REF! | M76: =ROUND(L76*K76,0) -> #REF! | N76: =U76*$T$5 -> #REF! | O76: =ROUND(N76*K76,0) -> #REF! | P76: =N76+L76 -> #REF! | Q76: =P76*K76 -> #REF! | T76: 13869868 | U76: 4160960.3
A77: 11 | B77: Accessories/Vật tư phụ | D77: lot | K77: 1 | L77: =T77*$T$5 -> #REF! | M77: =ROUND(L77*K77,0) -> #REF! | N77: =U77*$T$5 -> #REF! | O77: =ROUND(N77*K77,0) -> #REF! | P77: =N77+L77 -> #REF! | Q77: =P77*K77 -> #REF! | T77: 11558223 | U77: 3467466.9
K78: 0
B79: WASTE WATER DRAINAGE SYSTEM/ HỆ THỐNG THOÁT NƯỚC THẢI | K79: 0 | M79: =SUM(M80:M113) -> #REF! | O79: =SUM(O80:O113) -> #REF! | Q79: =O79+M79 -> #REF!
B80: Sanitary ware/ Thiết bị vệ sinh | K80: 0
A81: 1 | B81: Toilet/ Bồn cầu | C81: Caesar - CD1340 | D81: Bộ | K81: 17 | L81: =T81*$T$5 -> #REF! | M81: =ROUND(L81*K81,0) -> #REF! | N81: =U81*$T$5 -> #REF! | O81: =ROUND(N81*K81,0) -> #REF! | P81: =N81+L81 -> #REF! | Q81: =P81*K81 -> #REF! | T81: 3618000 | U81: 450000
A82: 2 | B82: Toilet spray including line/ Dây Xịt vệ sinh | C82: Caesar- BS304CW | D82: Bộ | K82: 17 | L82: =T82*$T$5 -> #REF! | M82: =ROUND(L82*K82,0) -> #REF! | N82: =U82*$T$5 -> #REF! | O82: =ROUND(N82*K82,0) -> #REF! | P82: =N82+L82 -> #REF! | Q82: =P82*K82 -> #REF! | T82: 475000 | U82: 75000
A83: 3 | B83: Urinal / Bồn tiểu nam | C83: Caesar -U0221 | D83: Bộ | K83: 12 | L83: =T83*$T$5 -> #REF! | M83: =ROUND(L83*K83,0) -> #REF! | N83: =U83*$T$5 -> #REF! | O83: =ROUND(N83*K83,0) -> #REF! | P83: =N83+L83 -> #REF! | Q83: =P83*K83 -> #REF! | T83: 713000 | U83: 550000
A84: 4 | B84: Urinal Drain Button/ Nút nhẫn xả bồn tiểu | C84: Caesar - BF412G | D84: set | K84: 12 | L84: =T84*$T$5 -> #REF! | M84: =ROUND(L84*K84,0) -> #REF! | N84: =U84*$T$5 -> #REF! | O84: =ROUND(N84*K84,0) -> #REF! | P84: =N84+L84 -> #REF! | Q84: =P84*K84 -> #REF! | T84: 517000 | U84: 75000
A85: 5 | B85: Lavabo under-table type/Bồn rữa tay âm bàn | C85: Caesar - L5113 | D85: set | K85: 14 | L85: =T85*$T$5 -> #REF! | M85: =ROUND(L85*K85,0) -> #REF! | N85: =U85*$T$5 -> #REF! | O85: =ROUND(N85*K85,0) -> #REF! | P85: =N85+L85 -> #REF! | Q85: =P85*K85 -> #REF! | T85: 1037000 | U85: 450000
B86: Wall mounted lavabo/Bồn rữa tay gắn tường | C86: Caesar - L2150+P2441 | D86: set | K86: 4 | L86: =T86*$T$5 -> #REF! | M86: =ROUND(L86*K86,0) -> #REF! | N86: =U86*$T$5 -> #REF! | O86: =ROUND(N86*K86,0) -> #REF! | P86: =N86+L86 -> #REF! | Q86: =P86*K86 -> #REF! | T86: =648000+583000 -> 1231000 | U86: 450000
B87: Wall mounted lavabo/Bồn rữa tay gắn tường | C87: Caesar - L2365-P2443 | D87: set | K87: 1 | L87: =T87*$T$5 -> #REF! | M87: =ROUND(L87*K87,0) -> #REF! | N87: =U87*$T$5 -> #REF! | O87: =ROUND(N87*K87,0) -> #REF! | P87: =N87+L87 -> #REF! | Q87: =P87*K87 -> #REF! | T87: =1166000+583000 -> 1749000 | U87: 450000
A88: 6 | B88: Faucet/ Vòi lavabol | C88: Caesar- B111C | D88: set | K88: 19 | L88: =T88*$T$5 -> #REF! | M88: =ROUND(L88*K88,0) -> #REF! | N88: =U88*$T$5 -> #REF! | O88: =ROUND(N88*K88,0) -> #REF! | P88: =N88+L88 -> #REF! | Q88: =P88*K88 -> #REF! | T88: 880000 | U88: 135000
A89: 7 | B89: Wash-bowl/Chậu rữa chén | C89: Son Ha | D89: set | K89: 1 | L89: =T89*$T$5 -> #REF! | M89: =ROUND(L89*K89,0) -> #REF! | N89: =U89*$T$5 -> #REF! | O89: =ROUND(N89*K89,0) -> #REF! | P89: =N89+L89 -> #REF! | Q89: =P89*K89 -> #REF! | T89: 3290000 | U89: 450000
A90: 8 | B90: Faucet for Wash-bowl/Chậu rữa bếp | C90: Caesar- K035C | D90: set | K90: 1 | L90: =T90*$T$5 -> #REF! | M90: =ROUND(L90*K90,0) -> #REF! | N90: =U90*$T$5 -> #REF! | O90: =ROUND(N90*K90,0) -> #REF! | P90: =N90+L90 -> #REF! | Q90: =P90*K90 -> #REF! | T90: 869000 | U90: 135000
A91: 9 | B91: Soap dispenser/ Hộp xà phòng | C91: Caesar - Q831 | D91: set | K91: 9 | L91: =T91*$T$5 -> #REF! | M91: =ROUND(L91*K91,0) -> #REF! | N91: =U91*$T$5 -> #REF! | O91: =ROUND(N91*K91,0) -> #REF! | P91: =N91+L91 -> #REF! | Q91: =P91*K91 -> #REF! | T91: 292000 | U91: 55000
A92: 10 | B92: Paper holder / Giá để giấy vệ sinh | C92: Caesar -Q8804 | D92: set | K92: 17 | L92: =T92*$T$5 -> #REF! | M92: =ROUND(L92*K92,0) -> #REF! | N92: =U92*$T$5 -> #REF! | O92: =ROUND(N92*K92,0) -> #REF! | P92: =N92+L92 -> #REF! | Q92: =P92*K92 -> #REF! | T92: 352000 | U92: 55000
A93: 11 | B93: Mirror 850x2335mm | D93: pcs | K93: 1 | L93: =T93*$T$5 -> #REF! | M93: =ROUND(L93*K93,0) -> #REF! | N93: =U93*$T$5 -> #REF! | O93: =ROUND(N93*K93,0) -> #REF! | P93: =N93+L93 -> #REF! | Q93: =P93*K93 -> #REF! | T93: 1850000 | U93: 210000
A94: 12 | B94: Mirror 650x1700mm | D94: pcs | K94: 5 | L94: =T94*$T$5 -> #REF! | M94: =ROUND(L94*K94,0) -> #REF! | N94: =U94*$T$5 -> #REF! | O94: =ROUND(N94*K94,0) -> #REF! | P94: =N94+L94 -> #REF! | Q94: =P94*K94 -> #REF! | T94: 1325000 | U94: 175000
A95: 13 | B95: Mirror 650x1400mm | D95: pcs | K95: 1 | L95: =T95*$T$5 -> #REF! | M95: =ROUND(L95*K95,0) -> #REF! | N95: =U95*$T$5 -> #REF! | O95: =ROUND(N95*K95,0) -> #REF! | P95: =N95+L95 -> #REF! | Q95: =P95*K95 -> #REF! | T95: 965000 | U95: 135000
A96: 14 | B96: Mirror 500x700mm | D96: pcs | K96: 2 | L96: =T96*$T$5 -> #REF! | M96: =ROUND(L96*K96,0) -> #REF! | N96: =U96*$T$5 -> #REF! | O96: =ROUND(N96*K96,0) -> #REF! | P96: =N96+L96 -> #REF! | Q96: =P96*K96 -> #REF! | T96: 443000 | U96: 90000
A97: 15 | B97: Floor Drainage D90/Ga thoát sàn D90 | C97: Caesar -ST1414L | D97: pcs | K97: 13 | L97: =T97*$T$5 -> #REF! | M97: =ROUND(L97*K97,0) -> #REF! | N97: =U97*$T$5 -> #REF! | O97: =ROUND(N97*K97,0) -> #REF! | P97: =N97+L97 -> #REF! | Q97: =P97*K97 -> #REF! | T97: 275000 | U97: 90000
A98: 16 | B98: Angle valve/ Van góc | D98: pcs | K98: 28 | L98: =T98*$T$5 -> #REF! | M98: =ROUND(L98*K98,0) -> #REF! | N98: =U98*$T$5 -> #REF! | O98: =ROUND(N98*K98,0) -> #REF! | P98: =N98+L98 -> #REF! | Q98: =P98*K98 -> #REF! | T98: 164285.71 | U98: 40000
A99: 17 | B99: Toilet vavle/ Van bồn cầu | D99: pcs | K99: 15 | L99: =T99*$T$5 -> #REF! | M99: =ROUND(L99*K99,0) -> #REF! | N99: =U99*$T$5 -> #REF! | O99: =ROUND(N99*K99,0) -> #REF! | P99: =N99+L99 -> #REF! | Q99: =P99*K99 -> #REF! | T99: 192857.14 | U99: 40000
A100: 18 | B100: SS304 Floor unblocking/ Thông tắt sàn inox 304 | C100: SS304 | D100: lot | K100: 15 | L100: =T100*$T$5 -> #REF! | M100: =ROUND(L100*K100,0) -> #REF! | N100: =U100*$T$5 -> #REF! | O100: =ROUND(N100*K100,0) -> #REF! | P100: =N100+L100 -> #REF! | Q100: =P100*K100 -> #REF! | T100: 464285.71 | U100: 90000
A101: 19 | B101: Fittings/ Phụ kiện | D101: lot | K101: 1 | L101: =T101*$T$5 -> #REF! | M101: =ROUND(L101*K101,0) -> #REF! | N101: =U101*$T$5 -> #REF! | O101: =ROUND(N101*K101,0) -> #REF! | P101: =N101+L101 -> #REF! | Q101: =P101*K101 -> #REF! | T101: 15250000 | U101: 2985000
A102: 20 | B102: Hanger, support/ Giá đỡ, ty treo | D102: lot | K102: 1 | L102: =T102*$T$5 -> #REF! | M102: =ROUND(L102*K102,0) -> #REF! | N102: =U102*$T$5 -> #REF! | O102: =ROUND(N102*K102,0) -> #REF! | P102: =N102+L102 -> #REF! | Q102: =P102*K102 -> #REF! | T102: 13869868 | U102: 4160960.3
A103: 21 | B103: Accessories/Vật tư phụ | D103: lot | K103: 1 | L103: =T103*$T$5 -> #REF! | M103: =ROUND(L103*K103,0) -> #REF! | N103: =U103*$T$5 -> #REF! | O103: =ROUND(N103*K103,0) -> #REF! | P103: =N103+L103 -> #REF! | Q103: =P103*K103 -> #REF! | T103: 11558223 | U103: 3467466.9
...

Sheet AC01.HVAC 
A1: ESTIMATE DETAIL TABLE | N1: hd
A2: ='Bill 3-External works'!#REF! -> #REF!
A3: ITEM/HẠNG MỤC : HVAC SYSTEM/ HỆ THỐNG HVAC
A5: No. | B5: DESCRIPTION | C5: STANDARD | D5: Unit | E5: DIMENSION | J5: QUANTITY | K5: Q'TY | L5: MATERIAL | N5: LABOUR & EQUIPMENT | P5: TOTAL COST(VND) | R5: REMARK | S5: ='C03.CSA_ANCILLARAY'!S5 -> Profit | T5: ='C03.CSA_ANCILLARAY'!T5 -> #REF!
E6: No | F6: L | G6: W | H6: H | I6: HS | J6: COMPONENT | L6: UNIT | M6: AMOUNT | N6: UNIT | O6: AMOUNT | P6: UNIT | Q6: AMOUNT | T6: ='C03.CSA_ANCILLARAY'!T6 -> Vật tư | U6: ='C03.CSA_ANCILLARAY'!U6 -> Nhân công
A7: AC01 | B7: HVAC SYSTEM/ HỆ THỐNG HVAC | M7: =SUBTOTAL(109,M8:M10) -> #REF! | O7: =SUBTOTAL(109,O8:O10) -> #REF! | Q7: =O7+M7 -> #REF!
A8: =A11 -> I | B8: =B11 -> AIR CONDITIONING SYSTEM /HỆ THỐNG ĐIỀU HÒA KHÔNG KHÍ | L8: =L11 -> 0 | M8: =M11 -> #REF! | N8: =N11 -> 0 | O8: =O11 -> #REF! | P8: =P11 -> 0 | Q8: =Q11 -> #REF!
A9: =A33 -> II | B9: =B33 -> VENTILATION SYSTEM/ HỆ THỐNG THÔNG GIÓ | L9: =L33 -> 0 | M9: =M33 -> #REF! | N9: =N33 -> 0 | O9: =O33 -> #REF! | P9: =P33 -> 0 | Q9: =Q33 -> #REF!
A11: I | B11: AIR CONDITIONING SYSTEM /HỆ THỐNG ĐIỀU HÒA KHÔNG KHÍ | M11: =SUBTOTAL(109,M12:M32) -> #REF! | O11: =SUBTOTAL(109,O12:O32) -> #REF! | Q11: =O11+M11 -> #REF!
A12: A | B12: Equipment / Thiết bị
A13: 1 | B13: Ceiling air conditioner,Cooling capacity: 24.000Btu/h / Máy lạnh âm trần,công suất lạnh: 24.000Btu/h | C13: Daikin-Inverter | D13: set | K13: 5 | L13: =T13*$T$5 -> #REF! | M13: =ROUND(L13*K13,0) -> #REF! | N13: =U13*$T$5 -> #REF! | O13: =ROUND(N13*K13,0) -> #REF! | P13: =N13+L13 -> #REF! | Q13: =P13*K13 -> #REF! | T13: 35687270 | U13: 1826000
A14: 2 | B14: Ceiling air conditioner,Cooling capacity: 36.000Btu/h/ Máy lạnh âm trần,công suất lạnh: 36.000Btu/h | C14: Daikin-Inverter | D14: set | K14: 2 | L14: =T14*$T$5 -> #REF! | M14: =ROUND(L14*K14,0) -> #REF! | N14: =U14*$T$5 -> #REF! | O14: =ROUND(N14*K14,0) -> #REF! | P14: =N14+L14 -> #REF! | Q14: =P14*K14 -> #REF! | T14: 46490000 | U14: 2310000
A15: 3 | B15: Wall mounted indoor unit,Capacity: 9.000Btu/h /Dàn lạnh gắn tường,công suất lạnh: 9.000Btu/h | C15: Daikin-Inverter | D15: set | K15: 4 | L15: =T15*$T$5 -> #REF! | M15: =ROUND(L15*K15,0) -> #REF! | N15: =U15*$T$5 -> #REF! | O15: =ROUND(N15*K15,0) -> #REF! | P15: =N15+L15 -> #REF! | Q15: =P15*K15 -> #REF! | T15: 10538182 | U15: 495000
A16: 4 | B16: Split air conditioner, Cooling Capacity: 12.000Btu/h / Máy lạnh gắn tường,công suất lạnh: 12.000Btu/h | C16: Daikin-Inverter | D16: set | K16: 2 | L16: =T16*$T$5 -> #REF! | M16: =ROUND(L16*K16,0) -> #REF! | N16: =U16*$T$5 -> #REF! | O16: =ROUND(N16*K16,0) -> #REF! | P16: =N16+L16 -> #REF! | Q16: =P16*K16 -> #REF! | T16: 12727273 | U16: 495000
A17: B | B17: Material/ Vật tư | L17: =T17*$T$5 -> #REF! | M17: =ROUND(L17*K17,0) -> #REF! | N17: =U17*$T$5 -> #REF! | O17: =ROUND(N17*K17,0) -> #REF! | P17: =N17+L17 -> #REF! | Q17: =P17*K17 -> #REF!
A18: 1 | B18: Copper pipe Ø6,35x0.81 C/w 13mm insulation/ Ống đồng Ø6,35x0.81 kèm cách nhiệt dầy 13mm | D18: m | K18: 97.9 | L18: =T18*$T$5 -> #REF! | M18: =ROUND(L18*K18,0) -> #REF! | N18: =U18*$T$5 -> #REF! | O18: =ROUND(N18*K18,0) -> #REF! | P18: =N18+L18 -> #REF! | Q18: =P18*K18 -> #REF! | T18: 75000 | U18: 60500
A19: 2 | B19: Copper pipe Ø12,7x0.81 C/w 13mm insulation/ Ống đồng Ø12,7x0.81 kèm cách nhiệt dầy 13mm | D19: m | K19: 11 | L19: =T19*$T$5 -> #REF! | M19: =ROUND(L19*K19,0) -> #REF! | N19: =U19*$T$5 -> #REF! | O19: =ROUND(N19*K19,0) -> #REF! | P19: =N19+L19 -> #REF! | Q19: =P19*K19 -> #REF! | T19: 115000 | U19: 70000
A20: 3 | B20: Copper pipe Ø9,52x0.81 C/w 13mm insulation/ Ống đồng Ø9,52x0.81 kèm cách nhiệt dầy 13mm | D20: m | K20: 248.82 | L20: =T20*$T$5 -> #REF! | M20: =ROUND(L20*K20,0) -> #REF! | N20: =U20*$T$5 -> #REF! | O20: =ROUND(N20*K20,0) -> #REF! | P20: =N20+L20 -> #REF! | Q20: =P20*K20 -> #REF! | T20: 95000 | U20: 64900
A21: 4 | B21: Copper pipe Ø15,9x0.81 C/w 13mm insulation/ Ống đồng Ø15,9x0.81kèm cách nhiệt dầy 13mm | D21: m | K21: 161.92 | L21: =T21*$T$5 -> #REF! | M21: =ROUND(L21*K21,0) -> #REF! | N21: =U21*$T$5 -> #REF! | O21: =ROUND(N21*K21,0) -> #REF! | P21: =N21+L21 -> #REF! | Q21: =P21*K21 -> #REF! | T21: 128000 | U21: 75000
A22: 5 | B22: Condensate pipe uPVC DN20 c/w insulation 13mm/ Ống uPVC DN20 bao gồm cách nhiệt dầy 13mm | D22: m | K22: 88 | L22: =T22*$T$5 -> #REF! | M22: =ROUND(L22*K22,0) -> #REF! | N22: =U22*$T$5 -> #REF! | O22: =ROUND(N22*K22,0) -> #REF! | P22: =N22+L22 -> #REF! | Q22: =P22*K22 -> #REF! | T22: 31000 | U22: 33000
A23: 6 | B23: Condensate pipe uPVC DN25 c/w insulation 13mm/ Ống uPVC DN25 bao gồm cách nhiệt dầy 13mm | D23: m | K23: 38.5 | L23: =T23*$T$5 -> #REF! | M23: =ROUND(L23*K23,0) -> #REF! | N23: =U23*$T$5 -> #REF! | O23: =ROUND(N23*K23,0) -> #REF! | P23: =N23+L23 -> #REF! | Q23: =P23*K23 -> #REF! | T23: 41000 | U23: 38000
A24: 7 | B24: Condensate pipe uPVC DN40 c/w insulation 13mm/Ống uPVC DN40 bao gồm cách nhiệt dầy 13mm | D24: m | K24: 38.5 | L24: =T24*$T$5 -> #REF! | M24: =ROUND(L24*K24,0) -> #REF! | N24: =U24*$T$5 -> #REF! | O24: =ROUND(N24*K24,0) -> #REF! | P24: =N24+L24 -> #REF! | Q24: =P24*K24 -> #REF! | T24: 61000 | U24: 57000
A25: 8 | B25: Condensate pipe uPVC DN50 c/w insulation 13mm/ Ống uPVC DN50 bao gồm cách nhiệt dầy 13mm | D25: m | K25: 33 | L25: =T25*$T$5 -> #REF! | M25: =ROUND(L25*K25,0) -> #REF! | N25: =U25*$T$5 -> #REF! | O25: =ROUND(N25*K25,0) -> #REF! | P25: =N25+L25 -> #REF! | Q25: =P25*K25 -> #REF! | T25: 70000 | U25: 55000
A26: 9 | B26: N2, Simily/ N2, xi quấn | D26: lot | K26: 1 | L26: =T26*$T$5 -> #REF! | M26: =ROUND(L26*K26,0) -> #REF! | N26: =U26*$T$5 -> #REF! | O26: =ROUND(N26*K26,0) -> #REF! | P26: =N26+L26 -> #REF! | Q26: =P26*K26 -> #REF! | T26: 3500000 | U26: 500000
A27: 10 | B27: Cable 3cx1.5mm2 + E1.5mm2 Cu/PVC from indoor unit to outdoor unit/ Cáp 3cx1.5mm2 + E1.5mm2 Cu/PVC từ giàn lạnh tới giàn nóng | D27: m | K27: 88 | L27: =T27*$T$5 -> #REF! | M27: =ROUND(L27*K27,0) -> #REF! | N27: =U27*$T$5 -> #REF! | O27: =ROUND(N27*K27,0) -> #REF! | P27: =N27+L27 -> #REF! | Q27: =P27*K27 -> #REF! | T27: =7750*4 -> 31000 | U27: 12000
A28: 10 | B28: Cable 3cx2.5mm2 + E2.5mm2 Cu/PVC from indoor unit to outdoor unit/ Cáp 3cx2.5mm2 + E1.5mm2 Cu/PVC từ giàn lạnh tới giàn nóng | D28: m | K28: 159.5 | L28: =T28*$T$5 -> #REF! | M28: =ROUND(L28*K28,0) -> #REF! | N28: =U28*$T$5 -> #REF! | O28: =ROUND(N28*K28,0) -> #REF! | P28: =N28+L28 -> #REF! | Q28: =P28*K28 -> #REF! | T28: =8750*4 -> 35000 | U28: 13500
A29: 12 | B29: Fittings/ Phụ kiện đường ống: Co, tê, bít… | D29: lot | E29: lot | K29: 1 | L29: =T29*$T$5 -> #REF! | M29: =ROUND(L29*K29,0) -> #REF! | N29: =U29*$T$5 -> #REF! | O29: =ROUND(N29*K29,0) -> #REF! | P29: =N29+L29 -> #REF! | Q29: =P29*K29 -> #REF! | T29: 6500000 | U29: 1750000
A30: 13 | B30: Hangers, support / Giá đỡ, ty treo, phụ kiện | D30: lot | K30: 1 | L30: =T30*$T$5 -> #REF! | M30: =ROUND(L30*K30,0) -> #REF! | N30: =U30*$T$5 -> #REF! | O30: =ROUND(N30*K30,0) -> #REF! | P30: =N30+L30 -> #REF! | Q30: =P30*K30 -> #REF! | T30: 7500000 | U30: 3000000
A31: 11 | B31: Accessories / Vật tư phụ | D31: lot | K31: 1 | L31: =T31*$T$5 -> #REF! | M31: =ROUND(L31*K31,0) -> #REF! | N31: =U31*$T$5 -> #REF! | O31: =ROUND(N31*K31,0) -> #REF! | P31: =N31+L31 -> #REF! | Q31: =P31*K31 -> #REF! | T31: 4500000 | U31: 550000
A33: II | B33: VENTILATION SYSTEM/ HỆ THỐNG THÔNG GIÓ | M33: =SUBTOTAL(109,M35:M66) -> #REF! | O33: =SUBTOTAL(109,O35:O66) -> #REF! | Q33: =O33+M33 -> #REF!
A34: A | B34: Equipment/ Thiết bị
A35: 1 | B35: Wall mounted exhaust fan 255CMH/Quạt hút gắn tường lưu lượng 255m3/h | D35: pcs | K35: 2 | L35: =T35*$T$5 -> #REF! | M35: =ROUND(L35*K35,0) -> #REF! | N35: =U35*$T$5 -> #REF! | O35: =ROUND(N35*K35,0) -> #REF! | P35: =N35+L35 -> #REF! | Q35: =P35*K35 -> #REF! | T35: 1230500 | U35: 319000
A36: 2 | B36: Wall mounted exhaust fan 546CMH/Quạt hút gắn tường lưu lượng 546m3/h | D36: pcs | K36: 1 | L36: =T36*$T$5 -> #REF! | M36: =ROUND(L36*K36,0) -> #REF! | N36: =U36*$T$5 -> #REF! | O36: =ROUND(N36*K36,0) -> #REF! | P36: =N36+L36 -> #REF! | Q36: =P36*K36 -> #REF! | T36: 3145800 | U36: 319000
A37: 4 | B37: Wall mounted exhaust fan 860CMH/Quạt hút gắn tường lưu lượng 860m3/h | D37: pcs | K37: 1 | L37: =T37*$T$5 -> #REF! | M37: =ROUND(L37*K37,0) -> #REF! | N37: =U37*$T$5 -> #REF! | O37: =ROUND(N37*K37,0) -> #REF! | P37: =N37+L37 -> #REF! | Q37: =P37*K37 -> #REF! | T37: 3145800 | U37: 319000
A38: 5 | B38: Wall mounted exhaust fan 1500CMH/Quạt hút gắn tường lưu lượng 1500m3/h | D38: pcs | K38: 1 | L38: =T38*$T$5 -> #REF! | M38: =ROUND(L38*K38,0) -> #REF! | N38: =U38*$T$5 -> #REF! | O38: =ROUND(N38*K38,0) -> #REF! | P38: =N38+L38 -> #REF! | Q38: =P38*K38 -> #REF! | T38: 4579600 | U38: 464000
A39: 6 | B39: Wall mounted exhaust fan 2670CMH/Quạt hút gắn tường lưu lượng 2670m3/h | D39: pcs | K39: 3 | L39: =T39*$T$5 -> #REF! | M39: =ROUND(L39*K39,0) -> #REF! | N39: =U39*$T$5 -> #REF! | O39: =ROUND(N39*K39,0) -> #REF! | P39: =N39+L39 -> #REF! | Q39: =P39*K39 -> #REF! | T39: 5906400 | U39: 599000
A40: 7 | B40: Ceiling mounted exhaust fan 260CMH/Quạt hút âm trần lưu lượng 260m3/h | D40: pcs | K40: 2 | L40: =T40*$T$5 -> #REF! | M40: =ROUND(L40*K40,0) -> #REF! | N40: =U40*$T$5 -> #REF! | O40: =ROUND(N40*K40,0) -> #REF! | P40: =N40+L40 -> #REF! | Q40: =P40*K40 -> #REF! | T40: 2568000 | U40: 319000
A41: 8 | B41: Ceiling mounted exhaust fan 400CMH/Quạt hút âm trần lưu lượng 400m3/h | D41: pcs | K41: 6 | L41: =T41*$T$5 -> #REF! | M41: =ROUND(L41*K41,0) -> #REF! | N41: =U41*$T$5 -> #REF! | O41: =ROUND(N41*K41,0) -> #REF! | P41: =N41+L41 -> #REF! | Q41: =P41*K41 -> #REF! | T41: 3777100 | U41: 319000
A42: 9 | B42: Ceiling mounted exhaust fan 530CMH/Quạt hút âm trần lưu lượng 530m3/h | D42: pcs | K42: 1 | L42: =T42*$T$5 -> #REF! | M42: =ROUND(L42*K42,0) -> #REF! | N42: =U42*$T$5 -> #REF! | O42: =ROUND(N42*K42,0) -> #REF! | P42: =N42+L42 -> #REF! | Q42: =P42*K42 -> #REF! | T42: 3777100 | U42: 319000
A43: 10 | B43: Ceiling mounted exhaust fan 800CMH/Quạt hút âm trần lưu lượng 800m3/h | D43: pcs | K43: 1 | L43: =T43*$T$5 -> #REF! | M43: =ROUND(L43*K43,0) -> #REF! | N43: =U43*$T$5 -> #REF! | O43: =ROUND(N43*K43,0) -> #REF! | P43: =N43+L43 -> #REF! | Q43: =P43*K43 -> #REF! | T43: 3777100 | U43: 319000
A44: 11 | B44: Inline centrifugal fan 1900CHM/Quạt hút ly tâm nối ống gió lưu lượng 1900m3/h | D44: pcs | K44: 1 | L44: =T44*$T$5 -> #REF! | M44: =ROUND(L44*K44,0) -> #REF! | N44: =U44*$T$5 -> #REF! | O44: =ROUND(N44*K44,0) -> #REF! | P44: =N44+L44 -> #REF! | Q44: =P44*K44 -> #REF! | T44: 7490000 | U44: 760000
A45: 12 | B45: Fitting for fan/Phụ kiện cho quạt | D45: lot | K45: 1 | L45: =T45*$T$5 -> #REF! | M45: =ROUND(L45*K45,0) -> #REF! | N45: =U45*$T$5 -> #REF! | O45: =ROUND(N45*K45,0) -> #REF! | P45: =N45+L45 -> #REF! | Q45: =P45*K45 -> #REF! | T45: 3500000 | U45: 580000
A46: 13 | B46: Hangers, support/Giá đỡ, ty treo | D46: lot | K46: 1 | L46: =T46*$T$5 -> #REF! | M46: =ROUND(L46*K46,0) -> #REF! | N46: =U46*$T$5 -> #REF! | O46: =ROUND(N46*K46,0) -> #REF! | P46: =N46+L46 -> #REF! | Q46: =P46*K46 -> #REF! | T46: 7500000 | U46: 2500000
A47: B | B47: Material/ Vật tư | L47: =T47*$T$5 -> #REF! | M47: =ROUND(L47*K47,0) -> #REF! | N47: =U47*$T$5 -> #REF! | O47: =ROUND(N47*K47,0) -> #REF! | P47: =N47+L47 -> #REF! | Q47: =P47*K47 -> #REF!
A48: 1 | B48: Ductwork 450x250/ Ống thẳng 450x250 | C48: Hoa Sen -Z8 | D48: m | K48: 10 | L48: =T48*$T$5 -> #REF! | M48: =ROUND(L48*K48,0) -> #REF! | N48: =U48*$T$5 -> #REF! | O48: =ROUND(N48*K48,0) -> #REF! | P48: =N48+L48 -> #REF! | Q48: =P48*K48 -> #REF! | T48: 529000 | U48: 322000
A49: 2 | B49: Ductwork 450x250 outlet/Ống thẳng 450x250 đầu ra | C49: Hoa Sen -Z8 | D49: m | K49: 1 | L49: =T49*$T$5 -> #REF! | M49: =ROUND(L49*K49,0) -> #REF! | N49: =U49*$T$5 -> #REF! | O49: =ROUND(N49*K49,0) -> #REF! | P49: =N49+L49 -> #REF! | Q49: =P49*K49 -> #REF! | T49: 529000 | U49: 322
A50: 3 | B50: Ductwork 300x250/ Ống thẳng 300x250 | C50: Hoa Sen -Z8 | D50: m | K50: 3 | L50: =T50*$T$5 -> #REF! | M50: =ROUND(L50*K50,0) -> #REF! | N50: =U50*$T$5 -> #REF! | O50: =ROUND(N50*K50,0) -> #REF! | P50: =N50+L50 -> #REF! | Q50: =P50*K50 -> #REF! | T50: 430000 | U50: 262000
A51: 4 | B51: Ductwork 300x250 (end cap)/Ống thẳng 300x250 bít đầu | C51: Hoa Sen -Z8 | D51: m | K51: 1 | L51: =T51*$T$5 -> #REF! | M51: =ROUND(L51*K51,0) -> #REF! | N51: =U51*$T$5 -> #REF! | O51: =ROUND(N51*K51,0) -> #REF! | P51: =N51+L51 -> #REF! | Q51: =P51*K51 -> #REF! | T51: 455000 | U51: 277000
A52: 5 | B52: Box 500x500 L100 | C52: Hoa Sen -Z8 | D52: m | K52: 2 | L52: =T52*$T$5 -> #REF! | M52: =ROUND(L52*K52,0) -> #REF! | N52: =U52*$T$5 -> #REF! | O52: =ROUND(N52*K52,0) -> #REF! | P52: =N52+L52 -> #REF! | Q52: =P52*K52 -> #REF! | T52: 164000 | U52: 89000
A53: 6 | B53: Giảm bằng đỉnh, bằng 1 bên 450x250/300x250 | C53: Hoa Sen -Z8 | D53: m | K53: 1 | L53: =T53*$T$5 -> #REF! | M53: =ROUND(L53*K53,0) -> #REF! | N53: =U53*$T$5 -> #REF! | O53: =ROUND(N53*K53,0) -> #REF! | P53: =N53+L53 -> #REF! | Q53: =P53*K53 -> #REF! | T53: 252000 | U53: 136000
A54: 7 | B54: Reduce 450x250 / 800x400/ Giảm bằng đỉnh, bằng 1 bên 450x250 / 800x400 | C54: Hoa Sen -Z8 | D54: m | K54: 1 | L54: =T54*$T$5 -> #REF! | M54: =ROUND(L54*K54,0) -> #REF! | N54: =U54*$T$5 -> #REF! | O54: =ROUND(N54*K54,0) -> #REF! | P54: =N54+L54 -> #REF! | Q54: =P54*K54 -> #REF! | T54: 373000 | U54: 202000
A55: 8 | B55: Elbow 450x250, R300/ Co 90 450x250, R300 | D55: m | K55: 1 | L55: =T55*$T$5 -> #REF! | M55: =ROUND(L55*K55,0) -> #REF! | N55: =U55*$T$5 -> #REF! | O55: =ROUND(N55*K55,0) -> #REF! | P55: =N55+L55 -> #REF! | Q55: =P55*K55 -> #REF! | T55: 492000 | U55: 266000
A56: 9 | B56: Exterior duct cover for ceiling fan/Cover chụp ống gió bên ngoài cho quạt gắn trần | D56: pcs | K56: 1 | L56: =T56*$T$5 -> #REF! | M56: =ROUND(L56*K56,0) -> #REF! | N56: =U56*$T$5 -> #REF! | O56: =ROUND(N56*K56,0) -> #REF! | P56: =N56+L56 -> #REF! | Q56: =P56*K56 -> #REF! | T56: 405000 | U56: 217000
A57: 10 | B57: Weather louver 800x400/Cửa gió ngoài trời 800x400 | D57: pcs | K57: 1 | L57: =T57*$T$5 -> #REF! | M57: =ROUND(L57*K57,0) -> #REF! | N57: =U57*$T$5 -> #REF! | O57: =ROUND(N57*K57,0) -> #REF! | P57: =N57+L57 -> #REF! | Q57: =P57*K57 -> #REF! | T57: 645000 | U57: 217000
A58: 11 | B58: EGG diffuser 600x600 c/w OBD/Miệng gió sọt trứng 600x600 có van chỉnh lưu lượng | D58: pcs | K58: 2 | L58: =T58*$T$5 -> #REF! | M58: =ROUND(L58*K58,0) -> #REF! | N58: =U58*$T$5 -> #REF! | O58: =ROUND(N58*K58,0) -> #REF! | P58: =N58+L58 -> #REF! | Q58: =P58*K58 -> #REF! | T58: 1485000 | U58: 465000
A59: 12 | B59: Vent cap D150/Chụp thông hơi D150 | D59: pcs | K59: 8 | L59: =T59*$T$5 -> #REF! | M59: =ROUND(L59*K59,0) -> #REF! | N59: =U59*$T$5 -> #REF! | O59: =ROUND(N59*K59,0) -> #REF! | P59: =N59+L59 -> #REF! | Q59: =P59*K59 -> #REF! | T59: 244000 | U59: 110000
A60: 13 | B60: Vent cap D200/ Chụp thông hơi D200 | D60: pcs | K60: 2 | L60: =T60*$T$5 -> #REF! | M60: =ROUND(L60*K60,0) -> #REF! | N60: =U60*$T$5 -> #REF! | O60: =ROUND(N60*K60,0) -> #REF! | P60: =N60+L60 -> #REF! | Q60: =P60*K60 -> #REF! | T60: 350000 | U60: 110000
A61: 14 | B61: Flexible duct D150 non insulation/ Ống gió mềm không cách nhiệt D150 | D61: m | K61: 16 | L61: =T61*$T$5 -> #REF! | M61: =ROUND(L61*K61,0) -> #REF! | N61: =U61*$T$5 -> #REF! | O61: =ROUND(N61*K61,0) -> #REF! | P61: =N61+L61 -> #REF! | Q61: =P61*K61 -> #REF! | T61: 285000 | U61: 66000
A62: 15 | B62: Flexible duct D200 non insulation/ Ống gió mềm không cách nhiệt D200 | D62: m | K62: 3 | L62: =T62*$T$5 -> #REF! | M62: =ROUND(L62*K62,0) -> #REF! | N62: =U62*$T$5 -> #REF! | O62: =ROUND(N62*K62,0) -> #REF! | P62: =N62+L62 -> #REF! | Q62: =P62*K62 -> #REF! | T62: 315000 | U62: 66000
A63: 16 | B63: PVC pipe D150/ Ống PVC D150 | D63: m | K63: 16 | L63: =T63*$T$5 -> #REF! | M63: =ROUND(L63*K63,0) -> #REF! | N63: =U63*$T$5 -> #REF! | O63: =ROUND(N63*K63,0) -> #REF! | P63: =N63+L63 -> #REF! | Q63: =P63*K63 -> #REF! | T63: ='PL01.PLUMPING'!T66 -> 302580 | U63: 132000
A64: 17 | B64: PVC pipe D200/ Ống PVC D200 | D64: m | K64: 3 | L64: =T64*$T$5 -> #REF! | M64: =ROUND(L64*K64,0) -> #REF! | N64: =U64*$T$5 -> #REF! | O64: =ROUND(N64*K64,0) -> #REF! | P64: =N64+L64 -> #REF! | Q64: =P64*K64 -> #REF! | T64: ='PL01.PLUMPING'!T68 -> 579388.57 | U64: 132000
A65: 18 | B65: Hangers, support/Giá đỡ ty treo | D65: lot | K65: 1 | L65: =T65*$T$5 -> #REF! | M65: =ROUND(L65*K65,0) -> #REF! | N65: =U65*$T$5 -> #REF! | O65: =ROUND(N65*K65,0) -> #REF! | P65: =N65+L65 -> #REF! | Q65: =P65*K65 -> #REF! | T65: 4500000 | U65: 1500000
A66: 19 | B66: Accessories / Vật tư phụ | D66: lot | K66: 1 | L66: =T66*$T$5 -> #REF! | M66: =ROUND(L66*K66,0) -> #REF! | N66: =U66*$T$5 -> #REF! | O66: =ROUND(N66*K66,0) -> #REF! | P66: =N66+L66 -> #REF! | Q66: =P66*K66 -> #REF! | T66: 5500000 | U66: 2500000

Sheet FF01.FIRE FIGHTING
A1: ESTIMATE DETAIL TABLE
A2: ='Bill 3-External works'!#REF! -> #REF!
A3: ITEM/HẠNG MỤC :FIRE FIGHTING SYSTEM/HỆ THỐNG PCCC
A5: No. | B5: DESCRIPTION | C5: STANDARD | D5: Unit | E5: DIMENSION | J5: QUANTITY | K5: Q'TY | L5: MATERIAL | N5: LABOUR & EQUIPMENT | P5: TOTAL COST | R5: REMARK | S5: ='AC01.HVAC '!S5 -> Profit | T5: ='AC01.HVAC '!T5 -> #REF!
E6: No | F6: L | G6: W | H6: H | I6: HS | J6: COMPONENT | L6: UNIT | M6: AMOUNT | N6: UNIT | O6: AMOUNT | P6: UNIT | Q6: AMOUNT | T6: ='AC01.HVAC '!T6 -> Vật tư | U6: ='AC01.HVAC '!U6 -> Nhân công
A7: FF01 | B7: FIRE FIGHTING SYSTEM/HỆ THỐNG PHÒNG CHÁY CHỮA CHÁY | M7: =SUBTOTAL(109,M8:M14) -> #REF! | O7: =SUBTOTAL(109,O8:O14) -> #REF! | Q7: =M7+O7 -> #REF!
A8: =A15 -> I | B8: =B15 -> FIRE FIGHTING PUMPING STATION/ TRẠM BƠM PCCC | M8: =M15 -> #REF! | O8: =O15 -> #REF! | Q8: =M8+O8 -> #REF!
A9: =A61 -> II | B9: =B61 -> FIRE FIGHTING SYSTEM,/ HỆ THỐNG CHỮA CHÁY | M9: =M61 -> #REF! | N9: =N61 -> 0 | O9: =O61 -> #REF! | Q9: =M9+O9 -> #REF!
A10: =A106 -> III | B10: =B106 -> FIRE ALARM SYSTEM/ HỆ THỐNG BÁO CHÁY | M10: =M106 -> #REF! | O10: =O106 -> #REF! | Q10: =M10+O10 -> #REF!
A11: =A135 -> IV | B11: =B135 -> LIGHNING SYSTEM/ HỆ THỐNG CHỐNG SÉT | M11: =M135 -> #REF! | O11: =O135 -> #REF! | Q11: =M11+O11 -> #REF!
A12: =A149 -> V | B12: =B149 -> SMOKE SYSTEM/ HỆ THỐNG HÚT KHÓI | M12: =M149 -> #REF! | O12: =O149 -> #REF! | Q12: =M12+O12 -> #REF!
A13: =A161 -> VI | B13: =B161 -> OTHERS WORKS | M13: =M161 -> #REF! | O13: =O161 -> #REF! | Q13: =M13+O13 -> #REF!
A15: I | B15: FIRE FIGHTING PUMPING STATION/ TRẠM BƠM PCCC | M15: =SUBTOTAL(109,M17:M60) -> #REF! | O15: =SUBTOTAL(109,O17:O60) -> #REF! | Q15: =O15+M15 -> #REF!
B16: FIRE PUM SET/ CỤM MÁY BƠM
A17: 1 | B17: Electric pump/ Máy bơm điện | C17: Centrifugal, Split - case type Q=91 l/s, H=0.82MPa Pump: Ebara- Indonesia Motor: Elektrim-Singapore | D17: set | E17: pcs | K17: 1 | L17: =T17*$T$5 -> #REF! | M17: =ROUND(L17*K17,0) -> #REF! | N17: =U17*$T$5 -> #REF! | O17: =ROUND(N17*K17,0) -> #REF! | P17: =N17+L17 -> #REF! | Q17: =P17*K17 -> #REF! | T17: 435000000 | U17: 23000000
A18: 2 | B18: Deisel pump/ Máy bơm Diesel | C18: Centrifugal, Split - case type Q=91 l/s, H=0.82MPa Pump: Ebara- Indonesia Motor: Hyundai-Korea | D18: set | E18: pcs | K18: 1 | L18: =T18*$T$5 -> #REF! | M18: =ROUND(L18*K18,0) -> #REF! | N18: =U18*$T$5 -> #REF! | O18: =ROUND(N18*K18,0) -> #REF! | P18: =N18+L18 -> #REF! | Q18: =P18*K18 -> #REF! | T18: 312500000 | U18: 18000000
A19: 3 | B19: Jockey pump/ Máy bơm bù áp: | C19: Centrifugal, Split - case type Q=2 l/s, H=0.82MPa Ebara- Indonesia | D19: set | E19: pcs | K19: 1 | L19: =T19*$T$5 -> #REF! | M19: =ROUND(L19*K19,0) -> #REF! | N19: =U19*$T$5 -> #REF! | O19: =ROUND(N19*K19,0) -> #REF! | P19: =N19+L19 -> #REF! | Q19: =P19*K19 -> #REF! | T19: 45000000 | U19: 7838400
A20: 4 | B20: Electric panel/ Tủ điện điều khiển | C20: Việt Nam/ Korea | D20: set | E20: pcs | K20: 1 | L20: =T20*$T$5 -> #REF! | M20: =ROUND(L20*K20,0) -> #REF! | N20: =U20*$T$5 -> #REF! | O20: =ROUND(N20*K20,0) -> #REF! | P20: =N20+L20 -> #REF! | Q20: =P20*K20 -> #REF! | T20: 85000000 | U20: 3200000
A21: 5 | B21: Electrical works ( From Fire control panel to all pumps, equipments) (Cable,Trunking,conduit ,..) Hạng mục điện( từ tủ điều khiển bơm đến các bơm, dây tín hiệu)( cáp, thang máng cáp, ống mềm…) | C21: Cadivi | D21: set | K21: 1 | L21: =T21*$T$5 -> #REF! | M21: =ROUND(L21*K21,0) -> #REF! | N21: =U21*$T$5 -> #REF! | O21: =ROUND(N21*K21,0) -> #REF! | P21: =N21+L21 -> #REF! | Q21: =P21*K21 -> #REF! | T21: 75000000 | U21: 8500000
B22: PIPING & FITTINGS/ ỐNG VÀ PHỤ KIỆN
A23: 6 | B23: Galvanized steel pipe ÞN200*5.16 mm/ Ống STK ÞN200*5.16 mm | C23: Hòa Phát/SeAH | D23: m | E23: m | K23: 6 | L23: =T23*$T$5 -> #REF! | M23: =ROUND(L23*K23,0) -> #REF! | N23: =U23*$T$5 -> #REF! | O23: =ROUND(N23*K23,0) -> #REF! | P23: =N23+L23 -> #REF! | Q23: =P23*K23 -> #REF! | T23: 920750 | U23: 323000
A24: 7 | B24: Galvanized steel pipe ÞN150*5.16 mm/ Ống STK ÞN150*5.16 mm | C24: Hòa Phát/SeAH | D24: m | E24: m | K24: 24 | L24: =T24*$T$5 -> #REF! | M24: =ROUND(L24*K24,0) -> #REF! | N24: =U24*$T$5 -> #REF! | O24: =ROUND(N24*K24,0) -> #REF! | P24: =N24+L24 -> #REF! | Q24: =P24*K24 -> #REF! | T24: 598850 | U24: 187000
A25: 8 | B25: Galvanized steel pipe ÞN100*3.2 mm/ Ống STK ÞN100*2.6 mm | C25: Hòa Phát/SeAH | D25: m | E25: m | K25: 6 | L25: =T25*$T$5 -> #REF! | M25: =ROUND(L25*K25,0) -> #REF! | N25: =U25*$T$5 -> #REF! | O25: =ROUND(N25*K25,0) -> #REF! | P25: =N25+L25 -> #REF! | Q25: =P25*K25 -> #REF! | T25: 299425 | U25: 114000
A26: 9 | B26: Galvanized steel pipe ÞN50*2.6 mm/ Ống STK ÞN50*2.6 mm | C26: Hòa Phát/SeAH | D26: m | E26: m | K26: 18 | L26: =T26*$T$5 -> #REF! | M26: =ROUND(L26*K26,0) -> #REF! | N26: =U26*$T$5 -> #REF! | O26: =ROUND(N26*K26,0) -> #REF! | P26: =N26+L26 -> #REF! | Q26: =P26*K26 -> #REF! | T26: 184150 | U26: 72000
A27: 10 | B27: Galvanized steel pipe ÞN32*2.6mm/ Ống STK ÞN32*2.6 mm | C27: Hòa Phát/SeAH | D27: m | E27: m | K27: 24 | L27: =T27*$T$5 -> #REF! | M27: =ROUND(L27*K27,0) -> #REF! | N27: =U27*$T$5 -> #REF! | O27: =ROUND(N27*K27,0) -> #REF! | P27: =N27+L27 -> #REF! | Q27: =P27*K27 -> #REF! | T27: 133400 | U27: 48000
A28: 11 | B28: Red painting/ Sơn đỏ | D28: lot | K28: 1 | L28: =T28*$T$5 -> #REF! | M28: =ROUND(L28*K28,0) -> #REF! | N28: =U28*$T$5 -> #REF! | O28: =ROUND(N28*K28,0) -> #REF! | P28: =N28+L28 -> #REF! | Q28: =P28*K28 -> #REF! | T28: 8500000 | U28: 1250000
A29: 12 | B29: Fittings/ Phụ kiện đường ống: Co, tê, bít… | D29: lot | E29: lot | K29: 1 | L29: =T29*$T$5 -> #REF! | M29: =ROUND(L29*K29,0) -> #REF! | N29: =U29*$T$5 -> #REF! | O29: =ROUND(N29*K29,0) -> #REF! | P29: =N29+L29 -> #REF! | Q29: =P29*K29 -> #REF! | T29: 35600000 | U29: 8525000
A30: 13 | B30: Hangers, support & accessories | D30: lot | K30: 1 | L30: =T30*$T$5 -> #REF! | M30: =ROUND(L30*K30,0) -> #REF! | N30: =U30*$T$5 -> #REF! | O30: =ROUND(N30*K30,0) -> #REF! | P30: =N30+L30 -> #REF! | Q30: =P30*K30 -> #REF! | T30: 25000000 | U30: 6500000
B31: VALVES & FITTINGS/ VAN VÀ PHỤ KIỆN | L31: =T31*$T$5 -> #REF! | M31: =ROUND(L31*K31,0) -> #REF! | N31: =U31*$T$5 -> #REF! | O31: =ROUND(N31*K31,0) -> #REF! | P31: =N31+L31 -> #REF! | Q31: =P31*K31 -> #REF!
A32: 13 | B32: Foot valve ÞN150/ Van Luppe ÞN150 | C32: Shinyi/Việt Nam | D32: pcs | E32: pcs | K32: 2 | L32: =T32*$T$5 -> #REF! | M32: =ROUND(L32*K32,0) -> #REF! | N32: =U32*$T$5 -> #REF! | O32: =ROUND(N32*K32,0) -> #REF! | P32: =N32+L32 -> #REF! | Q32: =P32*K32 -> #REF! | T32: 4106810 | U32: 685000
A33: 14 | B33: Foot valve ÞN50/ Van Luppe ÞN50 | C33: Miha/Việt Nam | D33: pcs | E33: pcs | K33: 1 | L33: =T33*$T$5 -> #REF! | M33: =ROUND(L33*K33,0) -> #REF! | N33: =U33*$T$5 -> #REF! | O33: =ROUND(N33*K33,0) -> #REF! | P33: =N33+L33 -> #REF! | Q33: =P33*K33 -> #REF! | T33: 1574858 | U33: 354000
A34: 15 | B34: Y strainer ÞN150/ Y lọc ÞN150 | C34: Shinyi/Việt Nam | D34: pcs | E34: pcs | K34: 2 | L34: =T34*$T$5 -> #REF! | M34: =ROUND(L34*K34,0) -> #REF! | N34: =U34*$T$5 -> #REF! | O34: =ROUND(N34*K34,0) -> #REF! | P34: =N34+L34 -> #REF! | Q34: =P34*K34 -> #REF! | T34: 2262000 | U34: 545000
A35: 16 | B35: Y strainer ÞN50/ Y lọc ÞN50 | C35: Miha/Việt Nam | D35: pcs | E35: pcs | K35: 1 | L35: =T35*$T$5 -> #REF! | M35: =ROUND(L35*K35,0) -> #REF! | N35: =U35*$T$5 -> #REF! | O35: =ROUND(N35*K35,0) -> #REF! | P35: =N35+L35 -> #REF! | Q35: =P35*K35 -> #REF! | T35: 986000 | U35: 230000
A36: 17 | B36: Flexible connection ÞN150/ Khớp nối mềm ÞN150 | C36: Shinyi/Việt Nam | D36: pcs | E36: pcs | K36: 4 | L36: =T36*$T$5 -> #REF! | M36: =ROUND(L36*K36,0) -> #REF! | N36: =U36*$T$5 -> #REF! | O36: =ROUND(N36*K36,0) -> #REF! | P36: =N36+L36 -> #REF! | Q36: =P36*K36 -> #REF! | T36: 1609661 | U36: 525000
A37: 18 | B37: Flexible connection ÞN50/ Khớp nối mềm ÞN50 | C37: Miha/Việt Nam | D37: pcs | E37: pcs | K37: 2 | L37: =T37*$T$5 -> #REF! | M37: =ROUND(L37*K37,0) -> #REF! | N37: =U37*$T$5 -> #REF! | O37: =ROUND(N37*K37,0) -> #REF! | P37: =N37+L37 -> #REF! | Q37: =P37*K37 -> #REF! | T37: 662112 | U37: 81270
A38: 19 | B38: Check valve ÞN150/ Van 1 chiều DÞN150 | C38: Shinyi/Việt Nam | D38: pcs | E38: pcs | K38: 2 | L38: =T38*$T$5 -> #REF! | M38: =ROUND(L38*K38,0) -> #REF! | N38: =U38*$T$5 -> #REF! | O38: =ROUND(N38*K38,0) -> #REF! | P38: =N38+L38 -> #REF! | Q38: =P38*K38 -> #REF! | T38: 3006150 | U38: 785000
A39: 20 | B39: Check valve ÞN100/ Van 1 chiều ÞN100 | C39: Miha/Việt Nam | D39: pcs | E39: pcs | K39: 1 | L39: =T39*$T$5 -> #REF! | M39: =ROUND(L39*K39,0) -> #REF! | N39: =U39*$T$5 -> #REF! | O39: =ROUND(N39*K39,0) -> #REF! | P39: =N39+L39 -> #REF! | Q39: =P39*K39 -> #REF! | T39: 1704501 | U39: 450000
A40: 21 | B40: Check valve ÞN50/ Van 1 chiều ÞN50 | C40: Miha/Việt Nam | D40: pcs | E40: pcs | K40: 1 | L40: =T40*$T$5 -> #REF! | M40: =ROUND(L40*K40,0) -> #REF! | N40: =U40*$T$5 -> #REF! | O40: =ROUND(N40*K40,0) -> #REF! | P40: =N40+L40 -> #REF! | Q40: =P40*K40 -> #REF! | T40: 1044104 | U40: 235000
A41: 22 | B41: Check valve ÞN32/ Van 1 chiều ÞN32 | C41: Miha/Việt Nam | D41: pcs | E41: pcs | K41: 6 | L41: =T41*$T$5 -> #REF! | M41: =ROUND(L41*K41,0) -> #REF! | N41: =U41*$T$5 -> #REF! | O41: =ROUND(N41*K41,0) -> #REF! | P41: =N41+L41 -> #REF! | Q41: =P41*K41 -> #REF! | T41: 622112 | U41: 98000
A42: 23 | B42: Gate valve ÞN150/ Van cổng ÞN150 | C42: Shinyi/Việt Nam | D42: pcs | E42: pcs | K42: 1 | L42: =T42*$T$5 -> #REF! | M42: =ROUND(L42*K42,0) -> #REF! | N42: =U42*$T$5 -> #REF! | O42: =ROUND(N42*K42,0) -> #REF! | P42: =N42+L42 -> #REF! | Q42: =P42*K42 -> #REF! | T42: 2813000 | U42: 765000
A43: 24 | B43: Gate valve ÞN100/ Van cổng ÞN100 | C43: Shinyi/Việt Nam | D43: pcs | E43: pcs | K43: 2 | L43: =T43*$T$5 -> #REF! | M43: =ROUND(L43*K43,0) -> #REF! | N43: =U43*$T$5 -> #REF! | O43: =ROUND(N43*K43,0) -> #REF! | P43: =N43+L43 -> #REF! | Q43: =P43*K43 -> #REF! | T43: 1667500 | U43: 545000
A44: 25 | B44: Butterfly valve with monitor ÞN150/ Van bướm kèm giám sát ÞN150 | C44: Shinyi/Việt Nam | D44: pcs | K44: 10 | L44: =T44*$T$5 -> #REF! | M44: =ROUND(L44*K44,0) -> #REF! | N44: =U44*$T$5 -> #REF! | O44: =ROUND(N44*K44,0) -> #REF! | P44: =N44+L44 -> #REF! | Q44: =P44*K44 -> #REF! | T44: 2224493 | U44: 765000
A45: 26 | B45: Butterfly valve with monitor ÞN50/ Van bướm kèm giám sát ÞN50 | C45: Shinyi/Việt Nam | D45: pcs | K45: 3 | L45: =T45*$T$5 -> #REF! | M45: =ROUND(L45*K45,0) -> #REF! | N45: =U45*$T$5 -> #REF! | O45: =ROUND(N45*K45,0) -> #REF! | P45: =N45+L45 -> #REF! | Q45: =P45*K45 -> #REF! | T45: 1145600 | U45: 320000
A46: 28 | B46: Ball vavle ÞN50/ Van bi ÞN50 | C46: Miha/Việt Nam | D46: pcs | E46: pcs | K46: 1 | L46: =T46*$T$5 -> #REF! | M46: =ROUND(L46*K46,0) -> #REF! | N46: =U46*$T$5 -> #REF! | O46: =ROUND(N46*K46,0) -> #REF! | P46: =N46+L46 -> #REF! | Q46: =P46*K46 -> #REF! | T46: 567000 | U46: 102060
A47: 29 | B47: Ball vavle ÞN32/ Van bi ÞN32 | C47: Miha/Việt Nam | D47: pcs | E47: pcs | K47: 4 | L47: =T47*$T$5 -> #REF! | M47: =ROUND(L47*K47,0) -> #REF! | N47: =U47*$T$5 -> #REF! | O47: =ROUND(N47*K47,0) -> #REF! | P47: =N47+L47 -> #REF! | Q47: =P47*K47 -> #REF! | T47: 462000 | U47: 83160
A48: 30 | B48: Pressure gauge / Đồng hồ áp suất | C48: China | D48: pcs | E48: pcs | K48: 3 | L48: =T48*$T$5 -> #REF! | M48: =ROUND(L48*K48,0) -> #REF! | N48: =U48*$T$5 -> #REF! | O48: =ROUND(N48*K48,0) -> #REF! | P48: =N48+L48 -> #REF! | Q48: =P48*K48 -> #REF! | T48: 450000 | U48: 35000
A49: 31 | B49: Alarm check valve ÞN150/ Van báo động ÞN150 | C49: Shinyi/Việt Nam | D49: pcs | K49: 1 | L49: =T49*$T$5 -> #REF! | M49: =ROUND(L49*K49,0) -> #REF! | N49: =U49*$T$5 -> #REF! | O49: =ROUND(N49*K49,0) -> #REF! | P49: =N49+L49 -> #REF! | Q49: =P49*K49 -> #REF! | T49: 14679000 | U49: 2642220
A50: 32 | B50: Water level sensor/Bộ cảm biến mực nước | C50: Taiwan | D50: set | K50: 1 | L50: =T50*$T$5 -> #REF! | M50: =ROUND(L50*K50,0) -> #REF! | N50: =U50*$T$5 -> #REF! | O50: =ROUND(N50*K50,0) -> #REF! | P50: =N50+L50 -> #REF! | Q50: =P50*K50 -> #REF! | T50: 1449000 | U50: 260820
A51: 33 | B51: Air vent valve DN32/ Van Xả khí DN32 | D51: pcs | K51: 1 | L51: =T51*$T$5 -> #REF! | M51: =ROUND(L51*K51,0) -> #REF! | N51: =U51*$T$5 -> #REF! | O51: =ROUND(N51*K51,0) -> #REF! | P51: =N51+L51 -> #REF! | Q51: =P51*K51 -> #REF! | T51: 913591 | U51: 92000
A52: 27 | B52: Pressure switch/ Công tắc áp lực | C52: Taiwan | D52: pcs | E52: pcs | K52: 3 | L52: =T52*$T$5 -> #REF! | M52: =ROUND(L52*K52,0) -> #REF! | N52: =U52*$T$5 -> #REF! | O52: =ROUND(N52*K52,0) -> #REF! | P52: =N52+L52 -> #REF! | Q52: =P52*K52 -> #REF! | T52: 725050 | U52: 68000
A53: 35 | B53: DN150 Water Flowmeter/ Đồng hồ đo lưu lượng nước | D53: pcs | K53: 1 | L53: =T53*$T$5 -> #REF! | M53: =ROUND(L53*K53,0) -> #REF! | N53: =U53*$T$5 -> #REF! | O53: =ROUND(N53*K53,0) -> #REF! | P53: =N53+L53 -> #REF! | Q53: =P53*K53 -> #REF! | T53: 10032103 | U53: 2325000
A54: 36 | B54: Pressure tank 200L/Bình tích áp 200 lít | D54: set | K54: 1 | L54: =T54*$T$5 -> #REF! | M54: =ROUND(L54*K54,0) -> #REF! | N54: =U54*$T$5 -> #REF! | O54: =ROUND(N54*K54,0) -> #REF! | P54: =N54+L54 -> #REF! | Q54: =P54*K54 -> #REF! | T54: 32000000 | U54: 4730000
A55: 37 | B55: Water tank 500L/Bình mồi nước | D55: set | K55: 1 | L55: =T55*$T$5 -> #REF! | M55: =ROUND(L55*K55,0) -> #REF! | N55: =U55*$T$5 -> #REF! | O55: =ROUND(N55*K55,0) -> #REF! | P55: =N55+L55 -> #REF! | Q55: =P55*K55 -> #REF! | T55: 2360000 | U55: 355000
B56: Float valve DN32/ Van phao DN32 | D56: pcs | K56: 1 | L56: =T56*$T$5 -> #REF! | M56: =ROUND(L56*K56,0) -> #REF! | N56: =U56*$T$5 -> #REF! | O56: =ROUND(N56*K56,0) -> #REF! | P56: =N56+L56 -> #REF! | Q56: =P56*K56 -> #REF! | T56: 878787 | U56: 156000
A57: 38 | B57: Fire Hose reel Cabinet , c/w: - DN50 angle valves - Coupling Adaptor - Canvas hose DN50mm x 20m & nozzle DN50x13mm. - Hangers, supports & all accessories | D57: pcs | K57: 1 | L57: =T57*$T$5 -> #REF! | M57: =ROUND(L57*K57,0) -> #REF! | N57: =U57*$T$5 -> #REF! | O57: =ROUND(N57*K57,0) -> #REF! | P57: =N57+L57 -> #REF! | Q57: =P57*K57 -> #REF! | T57: 2800000 | U57: 580000
A58: 39 | B58: Fittings/ Phụ kiện đường ống: Co, tê, bít… | D58: lot | E58: lot | K58: 1 | L58: =T58*$T$5 -> #REF! | M58: =ROUND(L58*K58,0) -> #REF! | N58: =U58*$T$5 -> #REF! | O58: =ROUND(N58*K58,0) -> #REF! | P58: =N58+L58 -> #REF! | Q58: =P58*K58 -> #REF! | T58: 20250000 | U58: 6552500
A59: 40 | B59: Hangers, support & accessories | D59: lot | K59: 1 | L59: =T59*$T$5 -> #REF! | M59: =ROUND(L59*K59,0) -> #REF! | N59: =U59*$T$5 -> #REF! | O59: =ROUND(N59*K59,0) -> #REF! | P59: =N59+L59 -> #REF! | Q59: =P59*K59 -> #REF! | T59: 28500000 | U59: 7250000
A61: II | B61: FIRE FIGHTING SYSTEM,/ HỆ THỐNG CHỮA CHÁY | M61: =SUBTOTAL(109,M62:M105) -> #REF! | O61: =SUBTOTAL(109,O62:O105) -> #REF! | Q61: =O61+M61 -> #REF!
B62: EXTERNAL FIRE FIGHTING SYSTEM/ HỆ THỐNG CHỮA CHÁY NGOÀI NHÀ
A63: * | B63: Equipment/ Thiết bị
A64: 1 | B64: Fire Department Connection (FDC) / Họng chữa cháy ngoài nhà | C64: Tomoken | D64: set | K64: 1 | L64: =T64*$T$5 -> #REF! | M64: =ROUND(L64*K64,0) -> #REF! | N64: =U64*$T$5 -> #REF! | O64: =ROUND(N64*K64,0) -> #REF! | P64: =N64+L64 -> #REF! | Q64: =P64*K64 -> #REF! | T64: 2641750 | U64: 650000
A65: 2 | B65: Fire Hydrant Pillar/Họng tiếp nước chưa cháy | C65: Tomoken | D65: set | K65: 1 | L65: =T65*$T$5 -> #REF! | M65: =ROUND(L65*K65,0) -> #REF! | N65: =U65*$T$5 -> #REF! | O65: =ROUND(N65*K65,0) -> #REF! | P65: =N65+L65 -> #REF! | Q65: =P65*K65 -> #REF! | T65: 2641750 | U65: 650000
A66: 3 | B66: Fire Hose reel Cabinet , c/w: - DN65 angle valves - Coupling Adaptor - Canvas hose DN65mm x 20m & nozzle DN65x18mm. - Hangers, supports & all accessories | C66: Viet Nam- Tomoken | D66: set | K66: 1 | L66: =T66*$T$5 -> #REF! | M66: =ROUND(L66*K66,0) -> #REF! | N66: =U66*$T$5 -> #REF! | O66: =ROUND(N66*K66,0) -> #REF! | P66: =N66+L66 -> #REF! | Q66: =P66*K66 -> #REF! | T66: 3850000 | U66: 750000
A67: * | B67: Pipings and fitting/Đường ống và phụ kiện
A68: 4 | B68: Hot-dip Galvanized steel pipe DN150 | C68: Hòa Phát | D68: m | K68: 86 | L68: =T68*$T$5 -> #REF! | M68: =ROUND(L68*K68,0) -> #REF! | N68: =U68*$T$5 -> #REF! | O68: =ROUND(N68*K68,0) -> #REF! | P68: =N68+L68 -> #REF! | Q68: =P68*K68 -> #REF! | T68: =T24 -> 598850 | U68: =U24 -> 187000
A69: 5 | B69: Hot-dip Galvanized steel pipe DN100 | C69: Hòa Phát | D69: m | K69: 55 | L69: =T69*$T$5 -> #REF! | M69: =ROUND(L69*K69,0) -> #REF! | N69: =U69*$T$5 -> #REF! | O69: =ROUND(N69*K69,0) -> #REF! | P69: =N69+L69 -> #REF! | Q69: =P69*K69 -> #REF! | T69: =T25 -> 299425 | U69: =U25 -> 114000
A70: 6 | B70: Concrete supports | D70: set | K70: 1 | L70: =T70*$T$5 -> #REF! | M70: =ROUND(L70*K70,0) -> #REF! | N70: =U70*$T$5 -> #REF! | O70: =ROUND(N70*K70,0) -> #REF! | P70: =N70+L70 -> #REF! | Q70: =P70*K70 -> #REF! | T70: 2200000 | U70: 450000
A71: 7 | B71: Red painting/ Sơn đỏ | D71: lot | K71: 1 | L71: =T71*$T$5 -> #REF! | M71: =ROUND(L71*K71,0) -> #REF! | N71: =U71*$T$5 -> #REF! | O71: =ROUND(N71*K71,0) -> #REF! | P71: =N71+L71 -> #REF! | Q71: =P71*K71 -> #REF! | T71: 9250000 | U71: 1720000
A72: 8 | B72: Fittings/ Phụ kiện đường ống: Co, tê, bít… | D72: lot | E72: lot | K72: 1 | L72: =T72*$T$5 -> #REF! | M72: =ROUND(L72*K72,0) -> #REF! | N72: =U72*$T$5 -> #REF! | O72: =ROUND(N72*K72,0) -> #REF! | P72: =N72+L72 -> #REF! | Q72: =P72*K72 -> #REF! | T72: 13250000 | U72: 3552500
A73: 9 | B73: Hangers, support & accessories | D73: lot | K73: 1 | L73: =T73*$T$5 -> #REF! | M73: =ROUND(L73*K73,0) -> #REF! | N73: =U73*$T$5 -> #REF! | O73: =ROUND(N73*K73,0) -> #REF! | P73: =N73+L73 -> #REF! | Q73: =P73*K73 -> #REF! | T73: 11500000 | U73: 4250000
B74: INTERNAL FIRE FIGHTING SYSTEM/ HỆ THỐNG CHỮA CHÁY TRONG NHÀ
A75: * | B75: Equipment/ Thiết bị
A76: 1 | B76: Fire Hose reel Cabinet , c/w: - DN50 angle valves - Coupling Adaptor - Canvas hose DN50mm x 20m & nozzle DN65x18mm. - Hangers, supports & all accessories | C76: Viet Nam- Tomoken | D76: set | K76: 18 | L76: =T76*$T$5 -> #REF! | M76: =ROUND(L76*K76,0) -> #REF! | N76: =U76*$T$5 -> #REF! | O76: =ROUND(N76*K76,0) -> #REF! | P76: =N76+L76 -> #REF! | Q76: =P76*K76 -> #REF! | T76: 3850000 | U76: 750000
A77: 2 | B77: Gate valve ÞN100/ Van cổng ÞN100 | C77: Shinyi/Việt Nam | D77: pcs | E77: pcs | K77: 4 | L77: =T77*$T$5 -> #REF! | M77: =ROUND(L77*K77,0) -> #REF! | N77: =U77*$T$5 -> #REF! | O77: =ROUND(N77*K77,0) -> #REF! | P77: =N77+L77 -> #REF! | Q77: =P77*K77 -> #REF! | T77: 1667500 | U77: 545000
A78: 3 | B78: Butterfly valve with monitor ÞN80/ Van bướm kèm giám sát ÞN80 | C78: Shinyi/Việt Nam | D78: pcs | K78: 2 | L78: =T78*$T$5 -> #REF! | M78: =ROUND(L78*K78,0) -> #REF! | N78: =U78*$T$5 -> #REF! | O78: =ROUND(N78*K78,0) -> #REF! | P78: =N78+L78 -> #REF! | Q78: =P78*K78 -> #REF! | T78: 1145600 | U78: 320000
A79: 4 | B79: Butterfly valve with monitor ÞN100/ Van bướm kèm giám sát ÞN100 | C79: Shinyi/Việt Nam | D79: pcs | K79: 2 | L79: =T79*$T$5 -> #REF! | M79: =ROUND(L79*K79,0) -> #REF! | N79: =U79*$T$5 -> #REF! | O79: =ROUND(N79*K79,0) -> #REF! | P79: =N79+L79 -> #REF! | Q79: =P79*K79 -> #REF! | T79: 1145600 | U79: 320000
A80: 5 | B80: Butterfly valve with monitor ÞN150/ Van bướm kèm giám sát ÞN150 | C80: Shinyi/Việt Nam | D80: pcs | K80: 2 | L80: =T80*$T$5 -> #REF! | M80: =ROUND(L80*K80,0) -> #REF! | N80: =U80*$T$5 -> #REF! | O80: =ROUND(N80*K80,0) -> #REF! | P80: =N80+L80 -> #REF! | Q80: =P80*K80 -> #REF! | T80: 2224493 | U80: 765000
A81: 6 | B81: Ball vavle ÞN25/ Van bi ÞN25 | C81: Miha/Việt Nam | D81: pcs | E81: pcs | K81: 2 | L81: =T81*$T$5 -> #REF! | M81: =ROUND(L81*K81,0) -> #REF! | N81: =U81*$T$5 -> #REF! | O81: =ROUND(N81*K81,0) -> #REF! | P81: =N81+L81 -> #REF! | Q81: =P81*K81 -> #REF! | T81: 462000 | U81: 83160
A82: 7 | B82: Air vent valve DN32/ Van Xả khí DN32 | D82: pcs | K82: 1 | L82: =T82*$T$5 -> #REF! | M82: =ROUND(L82*K82,0) -> #REF! | N82: =U82*$T$5 -> #REF! | O82: =ROUND(N82*K82,0) -> #REF! | P82: =N82+L82 -> #REF! | Q82: =P82*K82 -> #REF! | T82: 913591 | U82: 92000
A83: 8 | B83: Pressure gauge / Đồng hồ áp suất | C83: China | D83: pcs | E83: pcs | K83: 1 | L83: =T83*$T$5 -> #REF! | M83: =ROUND(L83*K83,0) -> #REF! | N83: =U83*$T$5 -> #REF! | O83: =ROUND(N83*K83,0) -> #REF! | P83: =N83+L83 -> #REF! | Q83: =P83*K83 -> #REF! | T83: 450000 | U83: 35000
A84: 9 | B84: Pendent sprinkler/ Đầu phun hướng xuống | C84: K=5.6-Tyco | D84: pcs | K84: 43 | L84: =T84*$T$5 -> #REF! | M84: =ROUND(L84*K84,0) -> #REF! | N84: =U84*$T$5 -> #REF! | O84: =ROUND(N84*K84,0) -> #REF! | P84: =N84+L84 -> #REF! | Q84: =P84*K84 -> #REF! | T84: 125000 | U84: 32000
A85: 10 | B85: Sprinkler upright/ Đầu phun hướng lên phản ứng nhanh | C85: K=11.2-Tyco | D85: pcs | K85: 585 | L85: =T85*$T$5 -> #REF! | M85: =ROUND(L85*K85,0) -> #REF! | N85: =U85*$T$5 -> #REF! | O85: =ROUND(N85*K85,0) -> #REF! | P85: =N85+L85 -> #REF! | Q85: =P85*K85 -> #REF! | T85: 335000 | U85: 32000
A86: 11 | B86: CO2 fire extingguisher 5kg/ Bình chữa cháy CO2 5Kg | C86: Dragon/Viet Nam | D86: pcs | K86: 37 | L86: =T86*$T$5 -> #REF! | M86: =ROUND(L86*K86,0) -> #REF! | N86: =U86*$T$5 -> #REF! | O86: =ROUND(N86*K86,0) -> #REF! | P86: =N86+L86 -> #REF! | Q86: =P86*K86 -> #REF! | T86: 1186500 | U86: 85000
A87: 12 | B87: BC dry chemical fire extingguisher 8Kg/ Bình chữa cháy BC 8Kg | C87: Dragon/Viet Nam | D87: pcs | K87: 37 | L87: =T87*$T$5 -> #REF! | M87: =ROUND(L87*K87,0) -> #REF! | N87: =U87*$T$5 -> #REF! | O87: =ROUND(N87*K87,0) -> #REF! | P87: =N87+L87 -> #REF! | Q87: =P87*K87 -> #REF! | T87: 819000 | U87: 85000
A88: 13 | B88: Fire extinguisher shelf/ Kệ đựng bình chữa cháy | C88: Viet Nam | D88: pcs | K88: 37 | L88: =T88*$T$5 -> #REF! | M88: =ROUND(L88*K88,0) -> #REF! | N88: =U88*$T$5 -> #REF! | O88: =ROUND(N88*K88,0) -> #REF! | P88: =N88+L88 -> #REF! | Q88: =P88*K88 -> #REF! | T88: 75000 | U88: 150000
A89: 14 | B89: Rule and regulation of fire and fighting/ Nội quy tiêu lệnh PCCC | C89: Viet Nam | D89: pcs | K89: 37 | L89: =T89*$T$5 -> #REF! | M89: =ROUND(L89*K89,0) -> #REF! | N89: =U89*$T$5 -> #REF! | O89: =ROUND(N89*K89,0) -> #REF! | P89: =N89+L89 -> #REF! | Q89: =P89*K89 -> #REF! | T89: 135000 | U89: 42000
A90: 15 | B90: Testing and comisioning/ Kiểm tra và vận hành thử | D90: lot | K90: 1 | L90: =T90*$T$5 -> #REF! | M90: =ROUND(L90*K90,0) -> #REF! | N90: =U90*$T$5 -> #REF! | O90: =ROUND(N90*K90,0) -> #REF! | P90: =N90+L90 -> #REF! | Q90: =P90*K90 -> #REF! | U90: 18000000
A91: 16 | B91: Certificate of inspection of fire fighting equipment/ Giấy chứng nhận kiểm định thiết bị chữa cháy | D91: lot | K91: 1 | N91: =U91*$T$5 -> #REF! | O91: =ROUND(N91*K91,0) -> #REF! | P91: =N91+L91 -> #REF! | Q91: =P91*K91 -> #REF! | U91: 37500000
A93: * | B93: Pipings and fitting/Đường ống và phụ kiện
A94: 4 | B94: Hot-dip Galvanized steel pipe DN150 | C94: Hòa Phát | D94: m | K94: 90 | L94: =T94*$T$5 -> #REF! | M94: =ROUND(L94*K94,0) -> #REF! | N94: =U94*$T$5 -> #REF! | O94: =ROUND(N94*K94,0) -> #REF! | P94: =N94+L94 -> #REF! | Q94: =P94*K94 -> #REF! | T94: =T68 -> 598850 | U94: =U36 -> 525000
A95: 5 | B95: Hot-dip Galvanized steel pipe DN100 | C95: Hòa Phát | D95: m | K95: 381 | L95: =T95*$T$5 -> #REF! | M95: =ROUND(L95*K95,0) -> #REF! | N95: =U95*$T$5 -> #REF! | O95: =ROUND(N95*K95,0) -> #REF! | P95: =N95+L95 -> #REF! | Q95: =P95*K95 -> #REF! | T95: =T69 -> 299425 | U95: =U69 -> 114000
A96: 5 | B96: Hot-dip Galvanized steel pipe DN80 | C96: Hòa Phát | D96: m | K96: 746 | L96: =T96*$T$5 -> #REF! | M96: =ROUND(L96*K96,0) -> #REF! | N96: =U96*$T$5 -> #REF! | O96: =ROUND(N96*K96,0) -> #REF! | P96: =N96+L96 -> #REF! | Q96: =P96*K96 -> #REF! | T96: 239250 | U96: 95000
A97: 5 | B97: Hot-dip Galvanized steel pipe DN65 | C97: Hòa Phát | D97: m | K97: 695 | L97: =T97*$T$5 -> #REF! | M97: =ROUND(L97*K97,0) -> #REF! | N97: =U97*$T$5 -> #REF! | O97: =ROUND(N97*K97,0) -> #REF! | P97: =N97+L97 -> #REF! | Q97: =P97*K97 -> #REF! | T97: 191400 | U97: 87000
A98: 5 | B98: Hot-dip Galvanized steel pipe DN50 | C98: Hòa Phát | D98: m | K98: 100 | L98: =T98*$T$5 -> #REF! | M98: =ROUND(L98*K98,0) -> #REF! | N98: =U98*$T$5 -> #REF! | O98: =ROUND(N98*K98,0) -> #REF! | P98: =N98+L98 -> #REF! | Q98: =P98*K98 -> #REF! | T98: =T26 -> 184150 | U98: =U26 -> 72000
A99: 5 | B99: Hot-dip Galvanized steel pipe DN40 | C99: Hòa Phát | D99: m | K99: 21 | L99: =T99*$T$5 -> #REF! | M99: =ROUND(L99*K99,0) -> #REF! | N99: =U99*$T$5 -> #REF! | O99: =ROUND(N99*K99,0) -> #REF! | P99: =N99+L99 -> #REF! | Q99: =P99*K99 -> #REF! | T99: 158750 | U99: 61500
A100: 5 | B100: Hot-dip Galvanized steel pipe DN32 | C100: Hòa Phát | D100: m | K100: 306 | L100: =T100*$T$5 -> #REF! | M100: =ROUND(L100*K100,0) -> #REF! | N100: =U100*$T$5 -> #REF! | O100: =ROUND(N100*K100,0) -> #REF! | P100: =N100+L100 -> #REF! | Q100: =P100*K100 -> #REF! | T100: 133400 | U100: 52500
A101: 5 | B101: Hot-dip Galvanized steel pipe DN25 | C101: Hòa Phát | D101: m | K101: 394 | L101: =T101*$T$5 -> #REF! | M101: =ROUND(L101*K101,0) -> #REF! | N101: =U101*$T$5 -> #REF! | O101: =ROUND(N101*K101,0) -> #REF! | P101: =N101+L101 -> #REF! | Q101: =P101*K101 -> #REF! | T101: 94350 | U101: 43000
A102: 7 | B102: Red painting/ Sơn đỏ | D102: lot | K102: 1 | L102: =T102*$T$5 -> #REF! | M102: =ROUND(L102*K102,0) -> #REF! | N102: =U102*$T$5 -> #REF! | O102: =ROUND(N102*K102,0) -> #REF! | P102: =N102+L102 -> #REF! | Q102: =P102*K102 -> #REF! | T102: 136500000 | U102: 2700000
A103: 8 | B103: Fittings/ Phụ kiện đường ống: Co, tê, bít… | D103: lot | E103: lot | K103: 1 | L103: =T103*$T$5 -> #REF! | M103: =ROUND(L103*K103,0) -> #REF! | N103: =U103*$T$5 -> #REF! | O103: =ROUND(N103*K103,0) -> #REF! | P103: =N103+L103 -> #REF! | Q103: =P103*K103 -> #REF! | T103: 278000000 | U103: 122300000
A104: 9 | B104: Hangers, support & accessories | D104: lot | K104: 1 | L104: =T104*$T$5 -> #REF! | M104: =ROUND(L104*K104,0) -> #REF! | N104: =U104*$T$5 -> #REF! | O104: =ROUND(N104*K104,0) -> #REF! | P104: =N104+L104 -> #REF! | Q104: =P104*K104 -> #REF! | T104: 125000000 | U104: 45000000
...

Sheet FF01.FIRE FIGHTING SYSTEM
A1: =#REF! -> #REF!
A2: =#REF! -> #REF!
A3: ITEM/HẠNG MỤC : FIRE FIGHTING SYSTEM/ HỆ THỐNG PCCC
A5: No. | B5: DESCRIPTION | C5: STANDARD | D5: Unit | E5: DIMENSION | J5: QUANTITY | K5: Q'TY | L5: MATERIAL | N5: LABOUR & EQUIPMENT | P5: TOTAL COST(VND) | R5: REMARK
E6: No | F6: L | G6: W | H6: H | I6: HS | J6: COMPONENT | L6: UNIT | M6: AMOUNT | N6: UNIT | O6: AMOUNT | P6: UNIT | Q6: AMOUNT
A7: FF01 | B7: FIRE FIGHTING SYSTEM/HỆ THỐNG PCCC | M7: =SUM(M8:M13) -> 0 | O7: =SUM(O8:O13) -> 0 | Q7: =M7+O7 -> 0
A8: 1 | B8: =B14 -> FIRE FIGHTING / HỆ CHỮA CHÁY | M8: =M14 -> 0 | O8: =O14 -> 0 | Q8: =M8+O8 -> 0
A9: =A30 -> II | B9: =B30 -> FIRE FIGHTING FOR PALLET CRACKING/ HỆ CHỮA CHÁYCHO KỆ HÀNG | M9: =M30 -> 0 | O9: =O30 -> 0 | Q9: =M9+O9 -> 0
A10: =A40 -> III | B10: =B40 -> FIRE ALARM SYSTEM/HỆ THỐNG BÁO CHÁY | M10: =M40 -> 0 | O10: =O40 -> 0 | Q10: =M10+O10 -> 0
A11: =A49 -> IV | B11: =B49 -> EXHAUST MOKE FAN SYSTEM/HỆ THỐNG QUẠT HÚT KHÓI | M11: =M49 -> 0 | O11: =O49 -> 0 | Q11: =M11+O11 -> 0
A12: =A68 -> V | B12: =B68 -> OTHER FEES/ CHI PHÍ KHÁC | M12: =M68 -> 0 | O12: =O68 -> 0 | Q12: =M12+O12 -> 0
A14: I | B14: FIRE FIGHTING / HỆ CHỮA CHÁY | M14: =SUM(M15:M29) -> 0 | O14: =SUM(O15:O29) -> 0 | Q14: =O14+M14 -> 0
A15: 1 | B15: Galvanize steel pipe ÞN125 - 4.78 ly /Ống thép nhúng kẽm nóng ÞN125 - 4.78 ly | C15: Viet Nam | D15: m | L15: =S15*$T$4 -> 0 | M15: =L15*K15 -> 0 | N15: =T15*$T$4 -> 0 | O15: =N15*K15 -> 0 | P15: =N15+L15 -> 0 | Q15: =O15+M15 -> 0
A16: 2 | B16: Galvanize steel pipe ÞN80 - 3.2 ly/ Ống thép nhúng kẽm nóng ÞN80 - 3.2 ly | C16: Viet Nam | D16: m | L16: =S16*$T$4 -> 0 | M16: =L16*K16 -> 0 | N16: =T16*$T$4 -> 0 | O16: =N16*K16 -> 0 | P16: =N16+L16 -> 0 | Q16: =O16+M16 -> 0
A17: 3 | B17: Galvanize steel pipe ÞN65 -2.9 ly /Ống thép nhúng kẽm nóng ÞN65 -2.9 ly | C17: Viet Nam | D17: m | L17: =S17*$T$4 -> 0 | M17: =L17*K17 -> 0 | N17: =T17*$T$4 -> 0 | O17: =N17*K17 -> 0 | P17: =N17+L17 -> 0 | Q17: =O17+M17 -> 0
A18: 4 | B18: Galvanize steel pipe ÞN50 - 2.9 ly/Ống thép nhúng kẽm nóng ÞN50 - 2.9 ly | C18: Viet Nam | D18: m | L18: =S18*$T$4 -> 0 | M18: =L18*K18 -> 0 | N18: =T18*$T$4 -> 0 | O18: =N18*K18 -> 0 | P18: =N18+L18 -> 0 | Q18: =O18+M18 -> 0
A19: 5 | B19: Galvanize steel pipe ÞN40 - 2.9 ly/Ống thép nhúng kẽm nóng ÞN40 - 2.9 ly | C19: Viet Nam | D19: m | L19: =S19*$T$4 -> 0 | M19: =L19*K19 -> 0 | N19: =T19*$T$4 -> 0 | O19: =N19*K19 -> 0 | P19: =N19+L19 -> 0 | Q19: =O19+M19 -> 0
A20: 6 | B20: Galvanize steel pipe ÞN32 - 2.9 ly /Ống thép nhúng kẽm nóng ÞN32 - 2.9 ly | C20: Viet Nam | D20: m | L20: =S20*$T$4 -> 0 | M20: =L20*K20 -> 0 | N20: =T20*$T$4 -> 0 | O20: =N20*K20 -> 0 | P20: =N20+L20 -> 0 | Q20: =O20+M20 -> 0
A21: 7 | B21: Trụ tiếp nước chữa cháy 2 cửa | C21: Shinyi | D21: pcs | L21: =S21*$T$4 -> 0 | M21: =L21*K21 -> 0 | N21: =T21*$T$4 -> 0 | O21: =N21*K21 -> 0 | P21: =N21+L21 -> 0 | Q21: =O21+M21 -> 0
A22: 8 | B22: Van cổng ty chìm ÞN125 | C22: Shinyi | D22: pcs | L22: =S22*$T$4 -> 0 | M22: =L22*K22 -> 0 | N22: =T22*$T$4 -> 0 | O22: =N22*K22 -> 0 | P22: =N22+L22 -> 0 | Q22: =O22+M22 -> 0
A23: 9 | B23: Van báo động ÞN125 | D23: pcs | L23: =S23*$T$4 -> 0 | M23: =L23*K23 -> 0 | N23: =T23*$T$4 -> 0 | O23: =N23*K23 -> 0 | P23: =N23+L23 -> 0 | Q23: =O23+M23 -> 0
A24: 10 | B24: Công tắc dòng chảy | D24: pcs | L24: =S24*$T$4 -> 0 | M24: =L24*K24 -> 0 | N24: =T24*$T$4 -> 0 | O24: =N24*K24 -> 0 | P24: =N24+L24 -> 0 | Q24: =O24+M24 -> 0
A25: 11 | B25: Sprinkle K=14.0/Đầu phun Sprinkler K=14.0 hướng lên | C25: Protector/Taiwan | D25: pcs | L25: =S25*$T$4 -> 0 | M25: =L25*K25 -> 0 | N25: =T25*$T$4 -> 0 | O25: =N25*K25 -> 0 | P25: =N25+L25 -> 0 | Q25: =O25+M25 -> 0
A26: 12 | B26: Painting and labelling/Sơn ống PCCC | C26: TayYang-Viet Nam | D26: lot | L26: =S26*$T$4 -> 0 | M26: =L26*K26 -> 0 | N26: =T26*$T$4 -> 0 | O26: =N26*K26 -> 0 | P26: =N26+L26 -> 0 | Q26: =O26+M26 -> 0
A27: 13 | B27: Hangers &supports | C27: Viet Nam | D27: lot | L27: =S27*$T$4 -> 0 | M27: =L27*K27 -> 0 | N27: =T27*$T$4 -> 0 | O27: =N27*K27 -> 0 | P27: =N27+L27 -> 0 | Q27: =O27+M27 -> 0
A28: 14 | B28: Accecesories | C28: Viet Nam | D28: lot | L28: =S28*$T$4 -> 0 | M28: =L28*K28 -> 0 | N28: =T28*$T$4 -> 0 | O28: =N28*K28 -> 0 | P28: =N28+L28 -> 0 | Q28: =O28+M28 -> 0
A30: II | B30: FIRE FIGHTING FOR PALLET CRACKING/ HỆ CHỮA CHÁYCHO KỆ HÀNG | M30: =SUM(M31:M39) -> 0 | O30: =SUM(O31:O39) -> 0 | Q30: =O30+M30 -> 0
A31: 1 | B31: Galvanize steel pipe ÞN100 - 3.2 ly /Ống thép nhúng kẽm nóng ÞN100-3.2 ly | C31: Viet Nam | D31: m | L31: =S31*$T$4 -> 0 | M31: =L31*K31 -> 0 | N31: =T31*$T$4 -> 0 | O31: =N31*K31 -> 0 | P31: =N31+L31 -> 0 | Q31: =O31+M31 -> 0
A32: 2 | B32: Galvanize steel pipe ÞN80 - 3.2 ly/ Ống thép nhúng kẽm nóng ÞN80 - 3.2 ly | C32: Viet Nam | D32: m | L32: =S32*$T$4 -> 0 | M32: =L32*K32 -> 0 | N32: =T32*$T$4 -> 0 | O32: =N32*K32 -> 0 | P32: =N32+L32 -> 0 | Q32: =O32+M32 -> 0
A33: 3 | B33: Galvanize steel pipe ÞN40 - 2.9 ly/Ống thép nhúng kẽm nóng ÞN40 - 2.9 ly | C33: Viet Nam | D33: m | L33: =S33*$T$4 -> 0 | M33: =L33*K33 -> 0 | N33: =T33*$T$4 -> 0 | O33: =N33*K33 -> 0 | P33: =N33+L33 -> 0 | Q33: =O33+M33 -> 0
A34: 4 | B34: Air valves/Van xả khí | C34: Shinyi | D34: pcs | L34: =S34*$T$4 -> 0 | M34: =L34*K34 -> 0 | N34: =T34*$T$4 -> 0 | O34: =N34*K34 -> 0 | P34: =N34+L34 -> 0 | Q34: =O34+M34 -> 0
A35: 5 | B35: Sprinkle K=5.6/Đầu phun Sprinkler K=5.6 hướng lên | C35: Protector/Taiwan | D35: pcs | L35: =S35*$T$4 -> 0 | M35: =L35*K35 -> 0 | N35: =T35*$T$4 -> 0 | O35: =N35*K35 -> 0 | P35: =N35+L35 -> 0 | Q35: =O35+M35 -> 0
A36: 6 | B36: Painting and labelling/Sơn ống PCCC | C36: TayYang-Viet Nam | D36: lot | L36: =S36*$T$4 -> 0 | M36: =L36*K36 -> 0 | N36: =T36*$T$4 -> 0 | O36: =N36*K36 -> 0 | P36: =N36+L36 -> 0 | Q36: =O36+M36 -> 0
A37: 7 | B37: Hangers &supports | C37: Viet Nam | D37: lot | L37: =S37*$T$4 -> 0 | M37: =L37*K37 -> 0 | N37: =T37*$T$4 -> 0 | O37: =N37*K37 -> 0 | P37: =N37+L37 -> 0 | Q37: =O37+M37 -> 0
A38: 8 | B38: Accecesories | C38: Viet Nam | D38: lot | L38: =S38*$T$4 -> 0 | M38: =L38*K38 -> 0 | N38: =T38*$T$4 -> 0 | O38: =N38*K38 -> 0 | P38: =N38+L38 -> 0 | Q38: =O38+M38 -> 0
A40: III | B40: FIRE ALARM SYSTEM/HỆ THỐNG BÁO CHÁY | M40: =SUM(M41:M48) -> 0 | O40: =SUM(O41:O48) -> 0 | Q40: =O40+M40 -> 0
A41: 1 | B41: Đầu báo khói | C41: Horing | D41: pcs | L41: =S41*$T$4 -> 0 | M41: =L41*K41 -> 0 | N41: =T41*$T$4 -> 0 | O41: =N41*K41 -> 0 | P41: =N41+L41 -> 0 | Q41: =O41+M41 -> 0
A42: 2 | B42: Còi báo cháy | C42: Horing | D42: pcs | L42: =S42*$T$4 -> 0 | M42: =L42*K42 -> 0 | N42: =T42*$T$4 -> 0 | O42: =N42*K42 -> 0 | P42: =N42+L42 -> 0 | Q42: =O42+M42 -> 0
A43: 3 | B43: Nút nhấn khẩn | C43: Horing | D43: pcs | L43: =S43*$T$4 -> 0 | M43: =L43*K43 -> 0 | N43: =T43*$T$4 -> 0 | O43: =N43*K43 -> 0 | P43: =N43+L43 -> 0 | Q43: =O43+M43 -> 0
A44: 4 | B44: Dây dẫn tín hiệu FR 2*1.5 | C44: Việt Nam | D44: m | L44: =S44*$T$4 -> 0 | M44: =L44*K44 -> 0 | N44: =T44*$T$4 -> 0 | O44: =N44*K44 -> 0 | P44: =N44+L44 -> 0 | Q44: =O44+M44 -> 0
A45: 5 | B45: Dây dẫn nguồn FR 2*2.5mm | C45: Việt Nam | D45: m | L45: =S45*$T$4 -> 0 | M45: =L45*K45 -> 0 | N45: =T45*$T$4 -> 0 | O45: =N45*K45 -> 0 | P45: =N45+L45 -> 0 | Q45: =O45+M45 -> 0
A46: 6 | B46: Ống luồn dây tín hiệu + nguồn PVC | C46: Việt Nam | D46: m | L46: =S46*$T$4 -> 0 | M46: =L46*K46 -> 0 | N46: =T46*$T$4 -> 0 | O46: =N46*K46 -> 0 | P46: =N46+L46 -> 0 | Q46: =O46+M46 -> 0
A47: 7 | B47: Accecesories | C47: Việt Nam | D47: lots | L47: =S47*$T$4 -> 0 | M47: =L47*K47 -> 0 | N47: =T47*$T$4 -> 0 | O47: =N47*K47 -> 0 | P47: =N47+L47 -> 0 | Q47: =O47+M47 -> 0
A49: IV | B49: EXHAUST MOKE FAN SYSTEM/HỆ THỐNG QUẠT HÚT KHÓI | M49: =SUM(M50:M71) -> 0 | O49: =SUM(O50:O71) -> 0 | Q49: =O49+M49 -> 0
A50: 1 | B50: Quạt hút khói 50.000 cmh @ 500 , D=1000 , motor 15hp ,, | C50: Motor fire protect 250oC, 120p | D50: pcs | L50: =S50*$T$4 -> 0 | M50: =L50*K50 -> 0 | N50: =T50*$T$4 -> 0 | O50: =N50*K50 -> 0 | P50: =N50+L50 -> 0 | Q50: =O50+M50 -> 0
A51: 2 | B51: Mặt bich quạt , lò xo chống rung | C51: Viet Nam | D51: set | L51: =S51*$T$4 -> 0 | M51: =L51*K51 -> 0 | N51: =T51*$T$4 -> 0 | O51: =N51*K51 -> 0 | P51: =N51+L51 -> 0 | Q51: =O51+M51 -> 0
A52: 3 | B52: Simii chống cháy | C52: Viet Nam | D52: pcs | L52: =S52*$T$4 -> 0 | M52: =L52*K52 -> 0 | N52: =T52*$T$4 -> 0 | O52: =N52*K52 -> 0 | P52: =N52+L52 -> 0 | Q52: =O52+M52 -> 0
A53: 4 | B53: Thùng quạt 1200 x 1200 x 1200 EI 60 | C53: Viet Nam | D53: pcs | L53: =S53*$T$4 -> 0 | M53: =L53*K53 -> 0 | N53: =T53*$T$4 -> 0 | O53: =N53*K53 -> 0 | P53: =N53+L53 -> 0 | Q53: =O53+M53 -> 0
A54: 5 | B54: Ống Chống Cháy EI 60 | C54: Metal sheet 0.75mm thk + fire protect sheet 15.9mm thk | D54: m2 | L54: =S54*$T$4 -> 0 | M54: =L54*K54 -> 0 | N54: =T54*$T$4 -> 0 | O54: =N54*K54 -> 0 | P54: =N54+L54 -> 0 | Q54: =O54+M54 -> 0
A55: 6 | B55: Miệng gió hút khói 600 x 600 + OBD + box | C55: Viet Nam | D55: pcs | L55: =S55*$T$4 -> 0 | M55: =L55*K55 -> 0 | N55: =T55*$T$4 -> 0 | O55: =N55*K55 -> 0 | P55: =N55+L55 -> 0 | Q55: =O55+M55 -> 0
A56: 7 | B56: Sleeve 2000 x 1000 | C56: Viet Nam | D56: pcs | L56: =S56*$T$4 -> 0 | M56: =L56*K56 -> 0 | N56: =T56*$T$4 -> 0 | O56: =N56*K56 -> 0 | P56: =N56+L56 -> 0 | Q56: =O56+M56 -> 0
A57: 8 | B57: Cover che mưa 1000 x 2000 | C57: Viet Nam | D57: pcs | L57: =S57*$T$4 -> 0 | M57: =L57*K57 -> 0 | N57: =T57*$T$4 -> 0 | O57: =N57*K57 -> 0 | P57: =N57+L57 -> 0 | Q57: =O57+M57 -> 0
A58: 9 | B58: Trunking kẽm 100 x 75mm | C58: Viet Nam | D58: m | L58: =S58*$T$4 -> 0 | M58: =L58*K58 -> 0 | N58: =T58*$T$4 -> 0 | O58: =N58*K58 -> 0 | P58: =N58+L58 -> 0 | Q58: =O58+M58 -> 0
A59: 10 | B59: Tủ điện điều khiển 2000 x 1400 x 300 , thiêt bị đóng ngắt LS | C59: Viet Nam | D59: pcs | L59: =S59*$T$4 -> 0 | M59: =L59*K59 -> 0 | N59: =T59*$T$4 -> 0 | O59: =N59*K59 -> 0 | P59: =N59+L59 -> 0 | Q59: =O59+M59 -> 0
A60: 11 | B60: Dây chống cháy 1c x 3 x 10mm2 + 1c x 4mm2 | C60: Viet Nam | D60: m | L60: =S60*$T$4 -> 0 | M60: =L60*K60 -> 0 | N60: =T60*$T$4 -> 0 | O60: =N60*K60 -> 0 | P60: =N60+L60 -> 0 | Q60: =O60+M60 -> 0
A61: 12 | B61: Ống ruột gà sắt | C61: Viet Nam | D61: m | L61: =S61*$T$4 -> 0 | M61: =L61*K61 -> 0 | N61: =T61*$T$4 -> 0 | O61: =N61*K61 -> 0 | P61: =N61+L61 -> 0 | Q61: =O61+M61 -> 0
... A64: 15 | B64: Vật tư phụ | C64: Viet Nam | D64: lots | L64: =S64*$T$4 -> 0 | M64: =L64*K64 -> 0 | N64: =T64*$T$4 -> 0 | O64: =N64*K64 -> 0 | P64: =N64+L64 -> 0 | Q64: =O64+M64 -> 0
A65: 16 | B65: Chi phí kiểm định cho ống gió và quạt chống cháy | D65: lots | L65: =S65*$T$4 -> 0 | M65: =L65*K65 -> 0 | N65: =T65*$T$4 -> 0 | O65: =N65*K65 -> 0 | P65: =N65+L65 -> 0 | Q65: =O65+M65 -> 0
A68: V | B68: OTHER FEES/ CHI PHÍ KHÁC | M68: =SUM(M69:M71) -> 0 | O68: =SUM(O69:O71) -> 0 | Q68: =O68+M68 -> 0
A69: 1 | B69: Chi phí kiểm định phương tiện, thiết bị PCCC trong phạm vi gói PCCC | C69: steel frame, oil paint | D69: set | L69: =S69*$T$4 -> 0 | M69: =L69*K69 -> 0 | N69: =T69*$T$4 -> 0 | O69: =N69*K69 -> 0 | P69: =N69+L69 -> 0 | Q69: =O69+M69 -> 0
A70: 2 | B70: Chi phí nghiệm thu trọn gói cho dự án | C70: Haliang/China Superlon/Malaysia | D70: lot | L70: =S70*$T$4 -> 0 | M70: =L70*K70 -> 0 | N70: =T70*$T$4 -> 0 | O70: =N70*K70 -> 0 | P70: =N70+L70 -> 0 | Q70: =O70+M70 -> 0

Sheet Material list
A1: Project : | B1: DB SCHENKER VEW3 COOL ROOM WAREHOUSE – VSIP2 BINH DUONG
A2: Location : | B2: ='01.BÌA'!E10 -> VSIP 3, BINH DUONG, VIETNAM
A3: Owner : | B3: ='01.BÌA'!E11 -> 0
A4: Contractor : | B4: New Investment Construction Consultant Joint Stock Company
A5: Package : | B5: Construction works
A6: Item : | B6: Material list
A8: SUMMARY LIST OF MATERIALS
A10: No | B10: Material | C10: Specifications | D10: Picture | E10: Brand name | F10: Country of origin | G10: Remarks
A11: A | B11: VẬT TƯ PHẦN THÔ
A12: 1 | B12: Bê tông thương phẩm | C12: TCVN 307:2003 | E12: Thế Giới Nhà/ Hồng Tín/ Hồng Hà hoặc tương đương | F12: Việt Nam
A13: =A12+1 -> 2 | B13: Thép xây dựng | C13: TCVN | E13: Hòa Phát / Tung Ho hoặc tương đương | F13: Việt Nam
A14: =A13+1 -> 3 | B14: Xi măng PC40 | C14: TCVN 2682:199 TCVN2682:1992 | E14: Hà Tiên/Insee/Fico hoặc tương đương | F14: Việt Nam
A15: =A14+1 -> 4 | B15: Cát vàng (Bê tông, xây tô) | C15: TCVN 1771:1987 | E15: Địa Phương | F15: Việt Nam
A16: =A15+1 -> 5 | B16: Đá 0-4, 1x2, 4x6 (Đá Xám) | C16: TCVN 1771:1987 | E16: Địa Phương | F16: Việt Nam
A17: =A16+1 -> 6 | B17: Gạch xây | C17: Gạch 8x8x18 Tuynel Gạch 4x8x18 Tuynel | E17: Địa Phương | F17: Việt Nam
A18: =A17+1 -> 7 | B18: Coffa | C18: Thép hộp, ván phủ phim | E18: Địa Phương | F18: Việt Nam
A19: =A18+1 -> 8 | B19: Cống BTLT | C19: D300 - D600 | E19: ACC/CIC319 hoặc tương đương | F19: Việt Nam
A20: =A19+1 -> 9 | B20: Gạch Block | E20: Địa Phương | F20: Việt Nam
A21: =A20+1 -> 10 | B21: Ống HDPE | E21: Bình Minh / Đệ Nhất / Hoa sen hoặc tương đương | F21: Việt Nam
A22: =A21+1 -> 11 | B22: Ống uPVC | E22: Bình Minh / Đệ Nhất / Hoa sen hoặc tương đương | F22: Việt Nam
A23: B | B23: VẬT TƯ PHẦN HOÀN THIỆN
A24: =A22+1 -> 12 | B24: Bột trét | E24: Nippon Paint hoặc tương đương | F24: Nhật Bản
A25: =A24+1 -> 13 | B25: Sơn nước | E25: =E24 -> Nippon Paint hoặc tương đương | F25: Nhật Bản
A26: =A25+1 -> 14 | B26: Sơn phủ sắt | E26: Benzo hoặc tương đương
A27: =A26+1 -> 15 | B27: Chống thấm | E27: Sika/Basf hoặc tương đương | F27: Việt Nam / Đức
A28: =A27+1 -> 16 | B28: Sơn nền | C28: Hệ lăn dày 0.3mm | E28: KCC/Samwha hoặc tương đương | F28: Hàn Quốc
A29: =A28+1 -> 17 | B29: Vách panel | C29: - Panel PU dày 100mm, 2 mặt tole, AZ50 dày 0.45mm | E29: Việt Nam | F29: Phương Nam/SY hoặc tương đương
A30: =A29+1 -> 18 | B30: Cửa cuốn thép | E30: Hoàng Tâm/ Minh Hòa hoặc tương đương | F30: Đài Loan
A31: =A30+1 -> 19 | B31: Cửa thép | C31: Cửa đi thép dày 1.2mm, sơn tỉnh điện, Kính trong dày 5mm | E31: Hoàng Tâm/ Dung Tien hoặc tương đương | F31: Việt Nam
A32: =A31+1 -> 20 | B32: Cửa đi nhôm kính | C32: Khung nhôm Hệ 1000, kính cường lực dày 5mm | E32: Tungshin / Xinfa Việt Nam hoặc tương đương | F32: Việt Nam
A33: =A32+1 -> 21 | B33: Lam thép | C33: Dày 1.2mm, sơn dầu | E33: Nam Kim/Hoa Sen / Đông Á hoặc tương đương
A34: =A33+1 -> 22 | B34: Trần Sanwich panel | C34: - Panel PU dày 75mm, 2 mặt tole, AZ50 dày 0.45mm | E34: =E29 -> Việt Nam | F34: =F29 -> Phương Nam/SY hoặc tương đương
A35: =A34+1 -> 23 | B35: Bê tông nhựa nóng | C35: C12.5, Dày 70mm | E35: Địa Phương | F35: Việt Nam
A36: C | B36: VẬT TƯ KẾT CẤU THÉP
A37: =A35+1 -> 24 | B37: Thép Tấm - kết cấu Thép Chính | C37: Thép tấm - Q345 hoặc tương đương Làm sạch SA 2.0 | E37: Trung Quốc | F37: Trung Quốc
A38: =A37+1 -> 25 | B38: Bulong Liên kết | C38: Bulong liên kết kết cấu chính G8.8 - Trung Quốc Bulong liên kết xà gồ G4.6 - Trung Quốc Mạ kẽm điện phân | E38: Trung Quốc | F38: Trung Quốc
A39: =A38+1 -> 26 | B39: Bulong neo | C39: Bulong neo - Trung Quốc G5.6 - Mạ kẽm điện phân | E39: Trung Quốc | F39: Trung Quốc
A40: =A39+1 -> 27 | B40: Xà gồ mạ kẽm | C40: Xà gồ Z275,G450 | E40: =E41 -> Nam Kim / Đông Á / Hoa Sen/TVP hoặc tương đương | F40: Việt Nam
A41: =A40+1 -> 28 | B41: Tôn | C41: Tôn AZ100G550 dày 0.45mm APT, 5 sóng cho mái, 9 sóng cho Vách | E41: Nam Kim / Đông Á / Hoa Sen/TVP hoặc tương đương | F41: Việt Nam
A42: =A41+1 -> 29 | B42: Tấm lấy sáng cho mái | C42: Dày 1.5mm | E42: Naaco hoặc tương đương | F42: Việt Nam
A43: =A42+1 -> 30 | B43: Tấm cách nhiệt | C43: 2 mặt nhôm A2 | E43: Cát Tường / Asia hoặc tương đương | F43: Việt Nam
A44: =A43+1 -> 31 | B44: Máng xối inox | C44: dày 0,8mm | E44: Posco hoặc tương đương | F44: Việt Nam

Sheet M. MECHANIC WORKS (2ND)
A1: ESTIMATE DETAIL TABLE
A2: PROJECT: JAKOB SAIGON FACTORY
A3: ITEM: MECHANIC WORKS
S4: USD/VND: | T4: 22700
A5: No. | B5: DESCRIPTION | C5: STANDARD | D5: MATERIAL PROPOSED BY CONTRACTOR: MODEL, BRAND, ORIGIN | E5: UNIT | F5: DIMENSION | K5: QUANTITY | L5: Q'TY | M5: MATERIAL | O5: LABOUR & EQUIPMENT | Q5: TOTAL COST | T5: REMARK
F6: No | G6: L | H6: W | I6: H | J6: HS | K6: COMPONENT | M6: UNIT | N6: AMOUNT | O6: UNIT | P6: AMOUNT | Q6: UNIT | R6: AMOUNT (VND) | S6: AMOUNT (USD)
A7: M. | B7: MECHANIC WORKS (PHASE 2) | C7: TOTAL | N7: =SUM(N8:N16) -> 0 | P7: =SUM(P8:P16) -> 0 | R7: =N7+P7 -> 0 | S7: =R7/$T$4 -> 0
A8: =A29 -> 1 | B8: =B29 -> WATER SUPPLY SYSTEM | E8: LOT | L8: 1 | N8: =N29 -> 0 | P8: =P29 -> 0 | R8: =N8+P8 -> 0 | S8: =R8/$T$4 -> 0
A9: =A57 -> 2 | B9: =B57 -> DRAINAGE PIPE SYSTEM | E9: LOT | L9: 1 | N9: =N57 -> 0 | P9: =P57 -> 0 | R9: =N9+P9 -> 0 | S9: =R9/$T$4 -> 0
A10: =A67 -> 3 | B10: =B67 -> SANITARY WARE FIXTURE | E10: LOT | L10: 1 | N10: =N67 -> 0 | P10: =P67 -> 0 | R10: =N10+P10 -> 0 | S10: =R10/$T$4 -> 0
A11: =A97 -> 5 | B11: =B97 -> COMPRESSOR PIPE WORKS | E11: LOT | L11: 1 | N11: =N97 -> 0 | P11: =P97 -> 0 | R11: =N11+P11 -> 0 | S11: =R11/$T$4 -> 0
A12: =A111 -> 6 | B12: =B111 -> VENTILATION WORKS | E12: LOT | L12: 1 | N12: =N111 -> 0 | P12: =P111 -> 0 | R12: =N12+P12 -> 0 | S12: =R12/$T$4 -> 0
A13: =A159 -> 7 | B13: =B159 -> HVAC WORKS | E13: LOT | L13: 1 | N13: =N159 -> 0 | P13: =P159 -> 0 | R13: =N13+P13 -> 0 | S13: =R13/$T$4 -> 0
A14: =A248 -> 8 | B14: =B248 -> ELEVATOR | E14: LOT | L14: 1 | N14: =N248 -> 0 | P14: =P248 -> 0 | R14: =N14+P14 -> 0 | S14: =R14/$T$4 -> 0
A15: =A264 -> 9 | B15: =B264 -> OVERHEAD CRANE | E15: LOT | L15: 1 | N15: =N264 -> 0 | P15: =P264 -> 0 | R15: =N15+P15 -> 0 | S15: =R15/$T$4 -> 0
A29: 1 | B29: WATER SUPPLY SYSTEM | N29: =SUM(N30:N55) -> 0 | P29: =SUM(P30:P55) -> 0 | R29: =P29+N29 -> 0 | S29: =R29/T$4 -> 0
A30: * | B30: Equipments
A31: 1 | B31: PPR gate valve DN50 | E31: EA | L31: 2 | N31: =M31*L31 -> 0 | P31: =O31*L31 -> 0 | Q31: =M31+O31 -> 0 | R31: =P31+N31 -> 0 | S31: =R31/T$4 -> 0
A32: 2 | B32: PPR gate valve DN40 | E32: EA | L32: 2 | N32: =M32*L32 -> 0 | P32: =O32*L32 -> 0 | Q32: =M32+O32 -> 0 | R32: =P32+N32 -> 0 | S32: =R32/T$4 -> 0
A33: 3 | B33: PPR gate valve DN32 | E33: EA | L33: 8 | N33: =M33*L33 -> 0 | P33: =O33*L33 -> 0 | Q33: =M33+O33 -> 0 | R33: =P33+N33 -> 0 | S33: =R33/T$4 -> 0
A34: 4 | B34: PPR gate valve DN25 | E34: EA | L34: 14 | N34: =M34*L34 -> 0 | P34: =O34*L34 -> 0 | Q34: =M34+O34 -> 0 | R34: =P34+N34 -> 0 | S34: =R34/T$4 -> 0
A35: 5 | B35: PPR gate valve DN20 | E35: EA | L35: 18 | N35: =M35*L35 -> 0 | P35: =O35*L35 -> 0 | Q35: =M35+O35 -> 0 | R35: =P35+N35 -> 0 | S35: =R35/T$4 -> 0
A36: 6 | B36: PPR gate valve DN15 | E36: EA | L36: 9 | N36: =M36*L36 -> 0 | P36: =O36*L36 -> 0 | Q36: =M36+O36 -> 0 | R36: =P36+N36 -> 0 | S36: =R36/T$4 -> 0
A37: 7 | B37: Accessories | C37: VN | E37: Lot | L37: 1 | N37: =M37*L37 -> 0 | P37: =O37*L37 -> 0 | Q37: =M37+O37 -> 0 | R37: =P37+N37 -> 0 | S37: =R37/T$4 -> 0
A38: * | B38: Water supply line
A39: 8 | B39: PPR pipe D110 | C39: Tien Phong | E39: m | L39: 80 | N39: =M39*L39 -> 0 | P39: =O39*L39 -> 0 | Q39: =M39+O39 -> 0 | R39: =P39+N39 -> 0 | S39: =R39/T$4 -> 0
A40: 9 | B40: PPR pipe D90 | C40: Tien Phong | E40: m | L40: 66 | N40: =M40*L40 -> 0 | P40: =O40*L40 -> 0 | Q40: =M40+O40 -> 0 | R40: =P40+N40 -> 0 | S40: =R40/T$4 -> 0
A41: 10 | B41: PPR pipe D76 | C41: Tien Phong | E41: m | L41: 25 | N41: =M41*L41 -> 0 | P41: =O41*L41 -> 0 | Q41: =M41+O41 -> 0 | R41: =P41+N41 -> 0 | S41: =R41/T$4 -> 0
A42: 11 | B42: PPR pipe D63 | C42: Tien Phong | E42: m | L42: 279 | N42: =M42*L42 -> 0 | P42: =O42*L42 -> 0 | Q42: =M42+O42 -> 0 | R42: =P42+N42 -> 0 | S42: =R42/T$4 -> 0
A43: 12 | B43: PPR pipe D50 | C43: Tien Phong | E43: m | L43: 82 | N43: =M43*L43 -> 0 | P43: =O43*L43 -> 0 | Q43: =M43+O43 -> 0 | R43: =P43+N43 -> 0 | S43: =R43/T$4 -> 0
A44: 13 | B44: PPR pipe D40 | C44: Tien Phong | E44: m | L44: 204 | N44: =M44*L44 -> 0 | P44: =O44*L44 -> 0 | Q44: =M44+O44 -> 0 | R44: =P44+N44 -> 0 | S44: =R44/T$4 -> 0
A45: 14 | B45: PPR pipe D32 | C45: Tien Phong | E45: m | L45: =154 -> 154 | N45: =M45*L45 -> 0 | P45: =O45*L45 -> 0 | Q45: =M45+O45 -> 0 | R45: =P45+N45 -> 0 | S45: =R45/T$4 -> 0
A46: 15 | B46: PPR pipe D25 | C46: Tien Phong | E46: m | L46: =327 -> 327 | N46: =M46*L46 -> 0 | P46: =O46*L46 -> 0 | Q46: =M46+O46 -> 0 | R46: =P46+N46 -> 0 | S46: =R46/T$4 -> 0
A47: 16 | B47: PPR pipe D20 | C47: Tien Phong | E47: m | L47: =954 -> 954 | N47: =M47*L47 -> 0 | P47: =O47*L47 -> 0 | Q47: =M47+O47 -> 0 | R47: =P47+N47 -> 0 | S47: =R47/T$4 -> 0
A48: 17 | B48: PPR pipe D32 - PN20 | C48: Tien Phong | E48: m | L48: 5 | N48: =M48*L48 -> 0 | P48: =O48*L48 -> 0 | Q48: =M48+O48 -> 0 | R48: =P48+N48 -> 0 | S48: =R48/T$4 -> 0
A49: 18 | B49: PPR pipe D25 - PN20 | C49: Tien Phong | E49: m | L49: 4 | N49: =M49*L49 -> 0 | P49: =O49*L49 -> 0 | Q49: =M49+O49 -> 0 | R49: =P49+N49 -> 0 | S49: =R49/T$4 -> 0
A50: 19 | B50: PPR pipe D20 - PN20 | C50: Tien Phong | E50: m | L50: 137 | N50: =M50*L50 -> 0 | P50: =O50*L50 -> 0 | Q50: =M50+O50 -> 0 | R50: =P50+N50 -> 0 | S50: =R50/T$4 -> 0
A51: 20 | B51: Fitting and accessories | C51: Tien Phong | E51: Lot | L51: 1 | N51: =M51*L51 -> 0 | P51: =O51*L51 -> 0 | Q51: =M51+O51 -> 0 | R51: =P51+N51 -> 0 | S51: =R51/T$4 -> 0
A52: 21 | B52: Testing and commissioning | E52: Lot | L52: 1 | N52: =M52*L52 -> 0 | P52: =O52*L52 -> 0 | Q52: =M52+O52 -> 0 | R52: =P52+N52 -> 0 | S52: =R52/T$4 -> 0
A53: 22 | B53: Hanger, Support | E53: Lot | L53: 1 | N53: =M53*L53 -> 0 | P53: =O53*L53 -> 0 | Q53: =M53+O53 -> 0 | R53: =P53+N53 -> 0 | S53: =R53/T$4 -> 0
A54: 23 | B54: Cutting, Excavation, Backfilling | E54: Lot | L54: 1 | N54: =M54*L54 -> 0 | P54: =O54*L54 -> 0 | Q54: =M54+O54 -> 0 | R54: =P54+N54 -> 0 | S54: =R54/T$4 -> 0
A55: 24 | B55: Transportation | E55: lot | L55: 1 | N55: =M55*L55 -> 0 | P55: =O55*L55 -> 0 | Q55: =M55+O55 -> 0 | R55: =P55+N55 -> 0 | S55: =R55/T$4 -> 0
A57: 2 | B57: DRAINAGE PIPE SYSTEM | N57: =SUM(N58:N65) -> 0 | P57: =SUM(P58:P65) -> 0 | R57: =P57+N57 -> 0 | S57: =R57/T$4 -> 0
A58: 1 | B58: Pipe uPVC D110 Thickness class 2 | C58: Tien Phong | E58: m | L58: 662 | N58: =M58*L58 -> 0 | P58: =O58*L58 -> 0 | Q58: =M58+O58 -> 0 | R58: =P58+N58 -> 0 | S58: =R58/T$4 -> 0
A59: 2 | B59: Pipe uPVC D90 Thickness class 2 | C59: Tien Phong | E59: m | L59: 350 | N59: =M59*L59 -> 0 | P59: =O59*L59 -> 0 | Q59: =M59+O59 -> 0 | R59: =P59+N59 -> 0 | S59: =R59/T$4 -> 0
A60: 3 | B60: Pipe uPVC D63 Thickness class 2 | C60: Tien Phong | E60: m | L60: 200 | N60: =M60*L60 -> 0 | P60: =O60*L60 -> 0 | Q60: =M60+O60 -> 0 | R60: =P60+N60 -> 0 | S60: =R60/T$4 -> 0
A61: 4 | B61: Pipe uPVC D50 Thickness class 2 | C61: Tien Phong | E61: m | L61: 120 | N61: =M61*L61 -> 0 | P61: =O61*L61 -> 0 | Q61: =M61+O61 -> 0 | R61: =P61+N61 -> 0 | S61: =R61/T$4 -> 0
A62: 5 | B62: Fitting | C62: Tien Phong | E62: lot | L62: 1 | N62: =M62*L62 -> 0 | P62: =O62*L62 -> 0 | Q62: =M62+O62 -> 0 | R62: =P62+N62 -> 0 | S62: =R62/T$4 -> 0
A63: 6 | B63: Vent cap | E63: set | L63: 10 | N63: =M63*L63 -> 0 | P63: =O63*L63 -> 0 | Q63: =M63+O63 -> 0 | R63: =P63+N63 -> 0 | S63: =R63/T$4 -> 0
A64: 7 | B64: Hanger, glue, support ,…….. | E64: lot | L64: 1 | N64: =M64*L64 -> 0 | P64: =O64*L64 -> 0 | Q64: =M64+O64 -> 0 | R64: =P64+N64 -> 0 | S64: =R64/T$4 -> 0
A65: 8 | B65: Excavation and backfill | E65: lot | L65: 1 | N65: =M65*L65 -> 0 | P65: =O65*L65 -> 0 | Q65: =M65+O65 -> 0 | R65: =P65+N65 -> 0 | S65: =R65/T$4 -> 0
A67: 3 | B67: SANITARY WARE FIXTURE | N67: =SUM(N68:N95) -> 0 | P67: =SUM(P68:P95) -> 0 | R67: =P67+N67 -> 0
A68: 1 | B68: Water closet C-909-VRN-1 | C68: Inax | E68: set | L68: 35 | N68: =M68*L68 -> 0 | P68: =O68*L68 -> 0 | Q68: =M68+O68 -> 0 | R68: =P68+N68 -> 0 | S68: =R68/T$4 -> 0
A69: 2 | B69: Water closet C-504VTN | C69: Inax | E69: set | L69: 8 | N69: =M69*L69 -> 0 | P69: =O69*L69 -> 0 | Q69: =M69+O69 -> 0 | R69: =P69+N69 -> 0 | S69: =R69/T$4 -> 0
A70: 2 | B70: Shower spray CFV-102M | C70: Inax | E70: set | L70: =L68+L69 -> 43 | N70: =M70*L70 -> 0 | P70: =O70*L70 -> 0 | Q70: =M70+O70 -> 0 | R70: =P70+N70 -> 0 | S70: =R70/T$4 -> 0
A71: 3 | B71: Paper holder CF-22H | C71: Inax | E71: set | L71: =L69+L68 -> 43 | N71: =M71*L71 -> 0 | P71: =O71*L71 -> 0 | Q71: =M71+O71 -> 0 | R71: =P71+N71 -> 0 | S71: =R71/T$4 -> 0
A72: 4 | B72: Lavabo L2395V | C72: Inax | E72: set | L72: 26 | N72: =M72*L72 -> 0 | P72: =O72*L72 -> 0 | Q72: =M72+O72 -> 0 | R72: =P72+N72 -> 0 | S72: =R72/T$4 -> 0
A73: 5 | B73: Lavabo L2397V | C73: Inax | E73: set | L73: 9 | N73: =M73*L73 -> 0 | P73: =O73*L73 -> 0 | Q73: =M73+O73 -> 0 | R73: =P73+N73 -> 0 | S73: =R73/T$4 -> 0
A74: 6 | B74: Lavabo Faucet LFV-4000S | C74: Inax | E74: set | L74: 5 | N74: =M74*L74 -> 0 | P74: =O74*L74 -> 0 | Q74: =M74+O74 -> 0 | R74: =P74+N74 -> 0 | S74: =R74/T$4 -> 0
