Workbook
Name \0: #REF!
Name \d: #N/A
Name \z: #REF!
Name _: #N/A
Name _?: #REF!
Name _??: #N/A
Name _??????: #REF!
Name _??_1: NA()
Name _??_1_1: NA()
Name _??_1_2: NA()
Name _??_1_3: NA()
Name _??_1_4: NA()
Name _??_1_5: NA()
Name _??_6: NA()
Name _??_7: NA()
Name _??_9: NA()
Name _?1: #N/A
Name _?1_1: NA()
Name _?1_1_1: NA()
Name _?1_1_2: NA()
Name _?1_1_3: NA()
Name _?1_1_4: NA()
Name _?1_1_5: NA()
Name _?1_6: NA()
Name _?1_7: NA()
Name _?1_9: NA()
Name _?271: #N/A
Name _?271_1: NA()
Name _?271_1_1: NA()
Name _?271_1_2: NA()
Name _?271_1_3: NA()
Name _?271_1_4: NA()
Name _?271_1_5: NA()
Name _?271_6: NA()
Name _?271_7: NA()
Name _?271_9: NA()
Name __: #REF!
Name __??: #N/A
Name __?1: #N/A
Name __?271: #N/A
Name ___??: #N/A
Name ___?1: #N/A
Name ___?271: #N/A
Name ________________________kr2: [0]!__
Name ________________________kr2: [0]!__
Name ________________________kr2: [0]!__
Name ________________________kr2: [0]!__
Name ________________________kr2: [0]!__
Name ________________________kr2: [0]!__
Name ________________________kr2: [0]!__
Name ________________________kr2: [0]!__
Name ________________________kr2: [0]!__
Name ________________________kr2: [0]!__
Name ________________________kr2: [0]!__
Name ________________________kr2: [0]!__
Name ________________________kr2: [0]!__
Name _______________________kr2: [0]!__
Name _______________________kr2: [0]!__
Name _______________________kr2: [0]!__
Name _______________________kr2: [0]!__

Sheet Cover 
A11: THIẾT KẾ & XIN PHÉP XÂY DỰNG, TỔNG THẦU THI CÔNG DESIGN & CONSTRUCTION PERMIT APPLICATION, GENERAL CONTRACTOR FOR CONSTRUCTION
B16: Công trình : Project:
B17: Địa chỉ: Address: | D17: KCN HỰU THẠNH, XÃ HỰU THẠNH, HUYỆN ĐỨC HÒA, TỈNH LONG AN, VIỆT NAM HUU THANH INDUSTRIAL PARK, HUU THANH COMMUNE, DUC HOA DISTRICT, LONG AN PROVINCE, VIETNAM
B18: Gói thầu: Tender Package: | D18: THIẾT KẾ & XIN PHÉP XÂY DỰNG, TỔNG THẦU THI CÔNG DESIGN & CONSTRUCTION PERMIT APPLICATION, GENERAL CONTRACTOR FOR CONSTRUCTION
B19: Nhà Thầu Chính : Main Contractor: | D19: CÔNG TY CỔ PHẦN TƯ VÂN ĐẦU TƯ XÂY DỰNG MỚI (NICON) NEW INVESTMENT CONSTRUCTION CONSULTANT JOINT STOCK COMPANY
A28: 45839

Sheet Total 
A1: DỰ ÁN: NHÀ MÁY SẢN XUẤT BAO BÌ
A2: ĐỊA ĐIỂM: KCN HỰUTHẠNH , XÃ HỰU THẠNH, HUYỆN ĐỨC HÒA,TỈNH LONG AN
A3: CHỦ ĐẦU TƯ : CÔNG TY …
A4: TỔNG HỢP DỰ TOÁN/ BOQ SUMMARY
A6: MỤC ITEM | B6: MÔ TẢ DESCRIPTION | C6: THÀNH TIỀN TRƯỚC THUẾ AMOUNT BEFORE VAT (VND) | D6: NOTED/ GHI CHÚ
A8: 1 | B8: Tổng giá trị phần Thi công | C8: ='Summary '!C28 -> 0 | D8: Chi tiết trang sau
A9: 2 | B9: Tổng giá trị thiết kế và xin phép | C9: ='Design and permit'!H35 -> 0 | D9: Chi tiết trang sau
B12: TỔNG CỘNG ( Chưa bao gồm thuế VAT ) TOTAL (Excluding VAT) | C12: =SUM(C8:C11) -> 0
A13: CÔNG TY TNHH BẢO MINH ÂN VIỆT NAM | C13: CÔNG TY CỔ PHẦN TƯ VẤN ĐẦU TƯ XÂY DỰNG MỚI (NICON)
A14: General Director | C14: General Director

Sheet Summary 
A1: DỰ ÁN: NHÀ MÁY SẢN XUẤT BAO BÌ
A2: ĐỊA ĐIỂM: KCN HỰU THẠNH , XÃ HỰU THẠNH, HUYỆN ĐỨC HÒA,TỈNH LONG AN
A3: ='Total '!A3 -> CHỦ ĐẦU TƯ : CÔNG TY …
A4: TỔNG HỢP DỰ TOÁN THI CÔNG
A6: MỤC ITEM | B6: MÔ TẢ DESCRIPTION | C6: THÀNH TIỀN TRƯỚC THUẾ AMOUNT BEFORE VAT (VND) | E6: đợt trước | H6: NOTED/ GHI CHÚ
A7: A | B7: HẠNG MỤC THEO HÌNH THỨC KHỐI LƯỢNG THỰC TẾ | C7: =SUM(C8:C9) -> 0
A8: 1 | B8: ='1. San lấp'!B8 -> HẠNG MỤC SAN LẤP NÂNG NỀN | F8: =C8-E8 -> 0 | H8: Chi tiết trang sau
A9: 2 | B9: ='Cọc BTCT D300'!B8 -> CỌC BTCT DUL D300 | H9: =H8 -> Chi tiết trang sau
A10: B | B10: HẠNG MỤC THEO HÌNH THỨC TRỌN GÓI | C10: =C11+C22 -> 0
A11: I | B11: THI CÔNG XÂY DỰNG | C11: =SUBTOTAL(9,C12:C21) -> 0 | D11: =C11/14897 -> 0 | E11: =SUM(E12:E21) -> 6.8737491e+10
A12: 1 | B12: CÔNG TÁC TẠM PHỤC VỤ THI CÔNG | E12: 544065570 | F12: =C12-E12 -> -544065570 | H12: Chi tiết trang sau
A13: 2 | B13: ='01 Nhà Xưởng 01+02'!B8 -> HẠNG MỤC NHÀ XƯỞNG 1 & 2 | D13: 12363 | E13: 4.828291e+10 | F13: =C13-E13 -> -4.828291e+10 | G13: =C13/D13 -> 0 | H13: Chi tiết trang sau
A14: 3 | B14: =' 02 Văn Phòng 01+02'!B8 -> HẠNG MỤC NHÀ VĂN PHÒNG 1&2 | D14: =1196+400 -> 1596 | E14: 1.1395223e+10 | F14: =C14-E14 -> -1.1395223e+10 | G14: =C14/D14 -> 0 | H14: Chi tiết trang sau
A15: 4 | B15: ='03 NHÀ BẢO VỆ 01 &02'!B8 -> HẠNG MỤC NHÀ BẢO VỆ 01 &02 | E15: 198000000 | F15: =C15-E15 -> -198000000 | H15: Chi tiết trang sau
A16: 5 | B16: ='04 NHÀ XE'!B18 -> HẠNG MỤC NHÀ XE 1 TẦNG | E16: 9.1844245e+08 | F16: =C16-E16 -> -9.1844245e+08 | H16: Chi tiết trang sau
A17: 6 | B17: ='05 BỂ PCCC & NHÀ BƠM'!B8 -> HẠNG MỤC BỂ NƯỚC PCCC, NHÀ BƠM | D17: 560 | E17: 1.9764115e+09 | F17: =C17-E17 -> -1.9764115e+09 | G17: =C17/D17 -> 0 | H17: Chi tiết trang sau | J17: =J15-J16 -> 0
A18: 7 | B18: ='07 BẢNG HIỆU+ CỔNG '!B8 -> BẢNG HIỆU +CỔNG 1,2,3+ 2 NHÀ TRẠM ĐIỆN | E18: 6.9084354e+08 | F18: =C18-E18 -> -6.9084354e+08 | H18: Chi tiết trang sau
A19: 8 | B19: ='08 GIAOTHONG'!B12 -> HẠNG MỤC HẠ TẦNG GIAO THÔNG | E19: 2.6498115e+09 | F19: =C19-E19 -> -2.6498115e+09 | H19: Chi tiết trang sau
A20: 9 | B20: ='09 Hàng Rào '!B17 -> HẠNG MỤC HÀNG RÀO | D20: 482 | E20: 1.271855e+09 | F20: =C20-E20 -> -1.271855e+09 | G20: =C20/D20 -> 0 | H20: Chi tiết trang sau
A21: 10 | B21: ='10 THOÁT NƯỚC MƯA'!B13 -> HẠNG MỤC THOÁT NƯỚC MƯA TỔNG THỂ | E21: 8.0992848e+08 | F21: =C21-E21 -> -8.0992848e+08 | H21: Chi tiết trang sau
A22: B | B22: HỆ THỐNG MEP | C22: =SUBTOTAL(9,C23:C27) -> 0 | E22: =SUM(E23:E27) -> 1.9151634e+10
A23: 1 | B23: HẠNG MỤC ĐIỆN XƯỞNG 1 | E23: 4.4352577e+09 | F23: =C23-E23 -> -4.4352577e+09 | H23: =H21 -> Chi tiết trang sau
A24: 2 | B24: HẠNG MỤC ĐIỆN XƯỞNG 2 | E24: 3.382905e+09 | F24: =C24-E24 -> -3.382905e+09 | G24: =1630*1.7 -> 2771 | H24: =H23 -> Chi tiết trang sau
A25: 3 | B25: HẠNG MỤC CẤP THOÁT NƯỚC | E25: 1.7270742e+09 | F25: =C25-E25 -> -1.7270742e+09 | G25: =7818-3900 -> 3918 | H25: =H23 -> Chi tiết trang sau
A26: 4 | B26: HẠNG MỤC MÁY LẠNH | E26: 1337622144 | F26: =C26-E26 -> -1337622144 | G26: =G25/14052 -> 0.27882152 | H26: =H24 -> Chi tiết trang sau
A27: 5 | B27: HẠNG MỤC PCCC | E27: 8268774660 | F27: =C27-E27 -> -8268774660 | H27: =H25 -> Chi tiết trang sau
B28: TỔNG CỘNG ( Chưa bao gồm thuế VAT ) TOTAL (Excluding VAT) | C28: =C10+C7 -> 0 | E28: =E22+E11 -> 8.7889125e+10 | F28: =SUM(F13:F27) -> -8.7345059e+10
B30: Ghi chú:
B31: 1. Không bao gồm thang máy nâng hàng 5t
B32: 2. Không bao gồm Máy phát điện
B33: 3. Không bao gồm Hệ thống máy lạnh cho nhà văn phòng 2, thiết bị máy lạnh văn phòng 1
B34: 4. Không bao gồm Hệ thống điện nhẹ: camera, internet, điện thoại
B35: 5. Hạng mục nâng nền cát sẽ được tính theo khối lượng thực tế sau khi xác định chiều cao nâng nền
B36: 6. Hạng mục cọc sẽ tính theo khối lượng thực tế
B37: 7. Không bao gồm hạng mục nhôm kính, cửa cuốn, vách trần panel
B38: 8. Không bao gồm tủ MSB xưởng 2, cáp điện hạ thế, thang máng cáp xưởng 2
B39: 9. Tải trọng nền xưởng 2 là 1T/m2
A41: CÔNG TY TNHH BẢO MINH ÂN VIỆT NAM | C41: CÔNG TY CỔ PHẦN TƯ VẤN ĐẦU TƯ XÂY DỰNG MỚI (NICON)
A42: General Director | C42: General Director
J45: Vo Tri Nguyen

Sheet Design and permit
A1: Công trình : Project:
A2: Địa chỉ: Address: | B2: =[4]Cover!D17 -> KCN HỰU THẠNH, XÃ HỰU THẠNH, HUYỆN ĐỨC HÒA, TỈNH LONG AN, VIỆT NAM HUU THANH INDUSTRIAL PARK, HUU THANH COMMUNE, DUC HOA DISTRICT, LONG AN PROVINCE, VIETNAM
A3: Gói thầu: Tender Package: | B3: =[4]Cover!D18 -> THIẾT KẾ & XIN PHÉP XÂY DỰNG, TỔNG THẦU THI CÔNG DESIGN & CONSTRUCTION PERMIT APPLICATION, GENERAL CONTRACTOR FOR CONSTRUCTION
A4: Nhà thầu Chính: Main Contractor: | B4: =[5]Cover!D19 -> CÔNG TY CỔ PHẦN TƯ VÂN ĐẦU TƯ XÂY DỰNG MỚI (NICON) NEW INVESTMENT CONSTRUCTION CONSULTANT JOINT STOCK COMPANY
A6: BẢNG DỰ TOÁN CHI PHÍ COST ESTIMATE
A7: =+'[5]1. Summary'!A7:A8 -> STT No. | B7: =+'[5]1. Summary'!B7:B8 -> Diễn Giải Interpretation | C7: Scope | E7: =+'[5]1. Summary'!C7:C8 -> Đơn Vị Unit | F7: =+'[5]1. Summary'!D7:D8 -> Khối Lượng Quantity | G7: Đơn Giá Price (VND) | H7: =+'[5]1. Summary'!F7:F8 -> Thành tiền Total amount (VND) | I7: =+'[5]1. Summary'!G7:G8 -> Ghi chú Notes
C8: NICON | D8: BMA
A9: A. | B9: CÔNG TÁC DỮ LIỆU PHỤC VỤ THIẾT KẾ VÀ XIN PHÉP DESIGN DATA SERVER AND ASK FOR PERMISSION | H9: =SUBTOTAL(9,H10:H12) -> 0
A10: 1 | B10: Công tác khảo sát, đo cao độ hiện trạng Survey and measurement of current elevation
A11: =A10+1 -> 2 | B11: Công tác khảo sát địa chất Geological survey work | H11: =SUBTOTAL(9,H12:H12) -> 0 | I11: Xác định khả năng chịu tải của nền đất, tính toán móng công trình 6 – 8 hố khoan (mỗi hố 30m sâu)
A12: 2.1 | B12: Khoan, thí nghiệm, lập báo cáo Drilling, testing, report | C12: x | E12: Lot | F12: 1 | H12: =G12*F12 -> 0
A13: B. | B13: CÔNG TÁC THIẾT KẾ ( PHỤC VỤ XIN PHÉP XÂY DỰNG) DESIGN WORK (FOR CONSTRUCTION PERMIT APPLICATION | H13: =SUBTOTAL(9,H14:H23) -> 0
A14: 1 | B14: LẬP BẢN VẼ THIẾT KẾ DESIGN DRAWING | H14: =SUBTOTAL(9,H15:H20) -> 0
A15: =+A14+0.1 -> 1.1 | B15: Thiết Kế Kiến trúc ( Bản vẽ + thuyết minh) Architectural Design ( drawing + explanation document) | C15: x | E15: Lot | F15: 1 | H15: =G15*F15 -> 0
A16: =+A15+0.1 -> 1.2 | B16: Thiết kế Kết cấu ( Bản vẽ + thuyết minh) Structural Design ( drawing + explanation document) | C16: x
A17: =+A16+0.1 -> 1.3 | B17: Thiết kế Hạ tầng kỹ thuật Infrastructure Design ( drawing + explanation document) | C17: x
A18: =+A17+0.1 -> 1.4 | B18: Thiết kế MEP ( Bản vẽ + thuyết minh) MEP Design ( drawing + explanation document) | C18: x
A19: =+A18+0.1 -> 1.5 | B19: Thiết kế PCCC ( drawing + explanation document) Fire Protection Design ( drawing + explanation document) | C19: x
B20: Đơn vị thiết kế cung cấp hồ sơ năng lực: Design unit provides capacity profile:
A21: 1 | B21: Chứng chỉ năng lực hoạt động xây dựng cho chức năng thiết kế Certificate of construction operation capacity for design function | C21: x | E21: Lot | F21: 1 | H21: =G21*F21 -> 0 | I21: Free
A22: 2 | B22: Chính chỉ hành nghề cá nhân tham gia thiết kế kiến trúc, kết cấu, cấp thoát nước, cơ điện, hạ tầng kỹ thuật Personal practice certificate participating in architectural, structural, water supply and drainage, mechanical and electrical design, technical infrastructure | C22: x | E22: Lot | F22: 1 | H22: =G22*F22 -> 0 | I22: Free
A23: 3 | B23: Chứng chỉ năng lực có chức năng thiết kế PCCC Certificate of capacity with fire protection design function | C23: x | E23: Lot | F23: 1 | H23: =G23*F23 -> 0 | I23: Free
A24: C. | B24: CÔNG TÁC XIN PHÉP XÂY DỰNG CONSTRUCTION PERMIT WORK | H24: =SUBTOTAL(9,H25:H34) -> 0
A25: 1 | B25: Xin phép quy hoạch 1/500 (Quy hoạch chi tiết rút gọn) Request for planning permission 1/500 (Shorten detailed planning) | C25: x | E25: Lot | F25: 1 | H25: =F25*G25 -> 0
A26: 2 | B26: Xin phép thi công công tác tạm (khảo sát, ép cọc thử…) Apply permission for temporary construction work (survey, test pile driving...) | C26: x
A27: =+A26+1 -> 3 | B27: Thỏa thuận đấu nối hạ tầng Infrastructure connection agreement | C27: x
A28: =+A27+1 -> 4 | B28: Xin phép môi trường Apply for environmental permit | C28: x | E28: Lot | F28: 1 | H28: =F28*G28 -> 0 | I28: Xin phép ở xã Hựu Thạnh
A29: =+A28+1 -> 5 | B29: Xin Phép PCCC Apply for fire protection permit | C29: x | E29: Lot | F29: 1 | H29: =F29*G29 -> 0
A30: =+A29+1 -> 6 | B30: Lập báo cáo thẩm tra thiết kế (phục vụ xin phép xây dựng) Prepare design review report (for construction permit application) | C30: x | E30: Lot | F30: 1 | H30: =F30*G30 -> 0
A31: =+A30+1 -> 7 | B31: Thẩm định báo cáo nghiên cứu khả thi đầu tư xây dựng Appraise investment feasibility study report | C31: x | E31: Lot
A32: =+A31+1 -> 8 | B32: Lập hồ sơ thẩm định thiết kế xây dựng triển khai sau thiết kế cơ sở ( Thiết kế kỹ thuật) Prepare construction design review file to be implemented after basic design ( technical design) | C32: x | E32: Lot
A33: =+A32+1 -> 9 | B33: Xin phép xây dựng Apply for construction permit | C33: x | E33: Lot
A34: =+A33+1 -> 10 | B34: Chi phí in hồ sơ và Scan tài liệu Cost of printing file and scanning documents | C34: x | E34: Lot | F34: 1 | G34: free | H34: 0
B35: TỔNG CỘNG GIÁ TRỊ : TOTAL VALUE: | H35: =SUBTOTAL(9,H9:H34) -> 0

Sheet Prelim
A1: Dự án / Project : Nhà máy BMA
A2: Hạng mục / Item : Common temporary works/Công tác chung, tạm thời
A5: STT/ No | B5: Diễn Giải / Description | E5: Đơn vị/ Unit | F5: Khối lượng/ Qty | G5: Đơn Giá / Unit Price (VND) | H5: Thành Tiền / Amount (VND)
A6: A | B6: Common temporary works/Công tác chung, tạm thời
A7: 1 | B7: Preparation work for working area, road/Công tác chuẩn bị đường tạm | E7: L/s | F7: 1 | H7: =G7*F7 -> 0
A8: 2 | B8: Temporary fence, gate door & sign for project/Hàng rào, cổng, bảng hiệu tạm | E8: L/s | F8: 1 | H8: =G8*F8 -> 0
A9: 3 | B9: Temporary site office/Văn phòng tạm | E9: L/s | F9: 1 | H9: =G9*F9 -> 0
A10: 5 | B10: Toilet for worker/Toilet tạm | E10: L/s | F10: 1 | H10: =G10*F10 -> 0
A11: 6 | B11: Security/An ninh | E11: L/s | F11: 1 | H11: =G11*F11 -> 0
A12: 7 | B12: Arranging & Cleaning/Vệ sinh | E12: L/s | F12: 1 | H12: =G12*F12 -> 0
A13: 8 | B13: Site records/ Camera công trình | E13: L/s | F13: 1 | H13: =G13*F13 -> 0
A14: 10 | B14: Transportation for common temporary work/Vận chuyển công tác tạm | E14: L/s | F14: 1 | H14: =G14*F14 -> 0
A15: 12 | B15: Insurances/Bảo hiểm | E15: L/s | F15: 1 | H15: =G15*F15 -> 0
A16: 13 | B16: Safety and environmental protection works/ Công tác an toàn và bảo vệ môi trường | E16: L/s | F16: 1 | H16: =G16*F16 -> 0
A17: 15 | B17: Fee of test Lab marterial, equipment/ Phí thí nghiệm vật liệu, thiết bị | E17: L/s | F17: 1 | H17: =G17*F17 -> 0
A18: 16 | B18: Fee shopdrawing, as built drawing/ Phí shopdrawing và bản vẽ hoàn công | E18: L/s | F18: 1 | H18: =G18*F18 -> 0
B19: Tổng cộng/ Total (I) | H19: =SUM(H7:H18) -> 0
A23: B | B23: Giai đoạn 2/ Stage 2
A24: III | B24: Phần xây dựng/ Construction
A25: 1 | B25: Nhà xưởng/ Factory | E25: set | F25: 1 | G25: =#REF! -> #REF! | H25: =G25*F25 -> #REF!
A26: 2 | B26: Giao thông/ Road | E26: L/s | F26: 1 | G26: =#REF! -> #REF! | H26: =G26*F26 -> #REF!
A27: 3 | B27: Hệ thống thoát nước mưa và bể tự hoại/ Storm drainage system and septic tank | E27: L/s | F27: 1 | G27: =#REF! -> #REF! | H27: =G27*F27 -> #REF!
B28: Tổng cộng/ Total (III) | H28: =SUM(H25:H27) -> #REF!
A29: IV | B29: Phần MEP
A30: 1 | B30: =#REF! -> #REF! | E30: =E26 -> L/s | F30: 1 | G30: =#REF! -> #REF! | H30: =_11B_19 -> #REF!
A31: =A30+1 -> 2 | B31: =#REF! -> #REF! | E31: =E27 -> L/s | F31: 1 | G31: =#REF! -> #REF! | H31: =_11B_19 -> #REF!
A32: =A31+1 -> 3 | B32: =#REF! -> #REF! | E32: =E31 -> L/s | F32: 1 | G32: =#REF! -> #REF! | H32: =_11B_19 -> #REF!
A33: =A32+1 -> 4 | B33: Hệ thống PCCC/ Fire fighting system | E33: L/s | F33: 1 | G33: =#REF! -> #REF! | H33: =_11B_19 -> #REF!
A34: =A33+1 -> 5 | B34: Hệ thống báo cháy/ Alarm fire fighting system | E34: L/s | F34: 1 | G34: =#REF! -> #REF! | H34: =_11B_19 -> #REF!
A35: =A34+1 -> 6 | B35: Hệ thống ĐHKK/ AC System | E35: =E32 -> L/s | F35: 1 | G35: =#REF! -> #REF! | H35: =_11B_19 -> #REF!
B36: Tổng cộng/ Total (IV) | H36: =SUM(H30:H35) -> #REF!
B37: Tổng cộng giai đoạn 2/ Total stage 2 (III)+(IV) | H37: =H28+H36 -> #REF!
C38: Total before VAT | H38: =#REF!+H37 -> #REF!
C39: VAT (10%) | H39: =H38*0.1 -> #REF!
C40: Total after VAT | H40: =SUM(H38:H39) -> #REF!

Sheet 1. San lấp
A1: BẢNG DỰ TOÁN BÁO GIÁ CÔNG TRÌNH / ESTIMATE TABLE
A3: ="HẠNG MỤC / ITEM : "&B8 -> HẠNG MỤC / ITEM : HẠNG MỤC SAN LẤP NÂNG NỀN
A6: STT NO. | B6: TÊN CÔNG VIỆC VÀ DIỄN GIẢI DESCRIPTION | C6: ĐẶC TÍNH KỸ THUẬT STANDARD | D6: NHÃN HIỆU & XUẤT XỨ BRAND NAME & ORIGIN | E6: Đvt Unit | F6: KL TỔNG Q'TY | G6: ĐƠN GIÁ / RATE | J6: TỔNG CỘNG (VNĐ) TOTAL COST(VND) | L6: REMARK GHI CHÚ
G7: VẬT TƯ RATE MATERIALS | H7: NHÂN CÔNG RATE LABOUR | I7: MMTB RATE EQUIPMENT | J7: ĐƠN GIÁ TỔNG TOTAL PRICE | K7: THÀNH TIỀN AMOUNT TOTAL
B8: HẠNG MỤC SAN LẤP NÂNG NỀN | K8: =K9 -> 0
A9: 1 | B9: Nâng nền toàn bộ bằng cát lấp lên cao 400mm, ban ủi nền cát, khối lượng sẽ tính thực tế hiện trường, đơn giá đã bao gồm hệ số đầm nén nền cát | C9: Cát Campuchia | E9: m3 | J9: =H9+G9 -> 0 | K9: =J9*F9 -> 0
A17: =IF(ISBLANK(E17),"",COUNTA($E$17:E17)) | G17: 0 | H17: 0 | J17: =+G17+H17 -> 0 | K17: =J17*$F17 -> 0
A18: =IF(ISBLANK(E18),"",COUNTA($E$17:E18)) | G18: 0 | H18: 0 | J18: =+G18+H18 -> 0 | K18: =J18*$F18 -> 0

Sheet Cọc BTCT D300
A1: BẢNG DỰ TOÁN BÁO GIÁ CÔNG TRÌNH / ESTIMATE TABLE
A6: STT NO. | B6: TÊN CÔNG VIỆC VÀ DIỄN GIẢI DESCRIPTION | C6: ĐẶC TÍNH KỸ THUẬT STANDARD | D6: NHÃN HIỆU & XUẤT XỨ BRAND NAME & ORIGIN | E6: Đvt Unit | F6: SL | G6: DÀI | H6: RỘNG | I6: CAO | J6: KL | K6: KL TỔNG Q'TY | L6: ĐƠN GIÁ / RATE | O6: TỔNG CỘNG (VNĐ) TOTAL COST(VND) | Q6: REMARK GHI CHÚ
L7: VẬT TƯ RATE MATERIALS | M7: NHÂN CÔNG RATE LABOUR | N7: MMTB RATE EQUIPMENT | O7: ĐƠN GIÁ TỔNG TOTAL PRICE | P7: THÀNH TIỀN AMOUNT TOTAL | R7: VẬT TƯ RATE MATERIALS | S7: NHÂN CÔNG RATE LABOUR
B8: CỌC BTCT DUL D300 | P8: =SUBTOTAL(9,P9:P14) -> 0 | Q8: Quyết toán theo khối lượng thực tế
A9: 1 | B9: NHÀ XƯỞNG 1 & NHÀ XƯỞNG 2 | P9: =P15 -> 0
A10: 2 | B10: NHÀ VĂN PHÒNG 1 & 2 | P10: =P33 -> 0
A11: 3 | B11: =B39 -> NHÀ XE 1 TẦNG | P11: =P39 -> 0
A12: 4 | B12: =B45 -> HẠNG MỤC BỂ NƯỚC PCCC, NHÀ BƠM | P12: =P45 -> 0
A13: 5 | B13: HÀNG RÀO | P13: =P51 -> 0
P14: =P148 -> 0
B15: =B9 -> NHÀ XƯỞNG 1 & NHÀ XƯỞNG 2 | P15: =SUM(P16:P32) -> 0
A16: 1 | B16: Cung cấp và thi công, kiểm tra cọc thử, PHC-A D300 Supply and construction of test piles, PHC-A D300 | C16: Cọc PHC A , D300, L=33m, Pmax =120 tấn PHC A pile, D300, L=33m, Pmax =120 tons | D16: Kiến Hoa, Phan Vũ, BT Thủ Đức, Việt Thái An Kien Hoa, Phan Vu, BT Thu Duc, VTA | E16: tim | K16: =SUM(J17:J20) -> 132 | O16: =+L16+M16+N16 -> 0 | P16: =O16*$K16 -> 0
B17: Nhà xưởng 01 | F17: 2 | G17: 33 | J17: =F17*G17 -> 66 | O17: =+L17+M17+N17 -> 0 | P17: =O17*$K17 -> 0
B20: Nhà xưởng 2 | F20: 2 | G20: 33 | J20: =F20*G20 -> 66 | O20: =+L20+M20+N20 -> 0 | P20: =O20*$K20 -> 0
A21: 3 | B21: Tập kết giàn ép tới công trình | E21: lot | K21: 2 | O21: =+L21+M21+N21 -> 0 | P21: =O21*$K21 -> 0
A22: 4 | B22: Cung cấp và thi công cọc đại trà, PHC-A D300 Supply and construction of mass piles, PHC-A D300 | C22: Cọc PHC A , D300, Pmax =120 tấn PHC A pile, D300, Pmax =120 tons | D22: Kiến Hoa, Phan Vũ, BT Thủ Đức, Việt Thái An Kien Hoa, Phan Vu, BT Thu Duc, VTA | E22: md | K22: =SUM(J23:J28) -> 18595 | O22: =+L22+M22+N22 -> 0 | P22: =O22*$K22 -> 0 | Q22: Cọc móng chính dự kiến ép 30md, cọc cho nền dự kiến ép 25md
B23: Nhà xưởng 02 | F23: 309 | J23: =F23*G23 -> 0 | O23: =+L23+M23+N23 -> 0 | P23: =O23*$K23 -> 0
B24: Cọc chính móng | F24: 106 | G24: 30 | J24: =PRODUCT(F24:H24) -> 3180
B25: Cọc nền | F25: =F23-F24 -> 203 | G25: 25 | J25: =PRODUCT(F25:H25) -> 5075
B26: Nhà xưởng 01 | F26: 396 | O26: =+L26+M26+N26 -> 0 | P26: =O26*$K26 -> 0
B27: Cọc chính móng | F27: 88 | G27: 30 | J27: =PRODUCT(F27:H27) -> 2640
B28: Cọc nền | F28: =F26-F27 -> 308 | G28: 25 | J28: =PRODUCT(F28:H28) -> 7700
A29: 6 | B29: Trắc đạt định vị cọc | E29: lot | J29: 1 | K29: 1 | O29: =+L29+M29+N29 -> 0 | P29: =O29*$K29 -> 0
A30: 7 | B30: Test cọc D300, thử tĩnh tải | E30: tim | J30: 4 | K30: 4 | O30: =+L30+M30+N30 -> 0 | P30: =O30*$K30 -> 0
A31: 8 | B31: Máy phát điện thi công cọc Pile construction generator | E31: md | J31: =K22 -> 18595 | K31: =J31 -> 18595 | O31: =+L31+M31+N31 -> 0 | P31: =O31*$K31 -> 0
A32: 9 | B32: Cắt đầu cọc Cutting pile heads | E32: cái | J32: =F23+F26 -> 705 | K32: =J32 -> 705 | O32: =+L32+M32+N32 -> 0 | P32: =O32*$K32 -> 0
B33: =B10 -> NHÀ VĂN PHÒNG 1 & 2 | P33: =SUM(P34:P38) -> 0
A34: 1 | B34: Cung cấp và thi công cọc đại trà, PHC-A D300 Supply and construction of mass piles, PHC-A D300 | C34: Cọc PHC A , D300, Pmax =120 tấn PHC A pile, D300, Pmax =120 tons | D34: Kiến Hoa, Phan Vũ, BT Thủ Đức, Việt Thái An Kien Hoa, Phan Vu, BT Thu Duc, VTA | E34: md | K34: =J35+J36 -> 2695 | O34: =+L34+M34+N34 -> 0 | P34: =O34*$K34 -> 0 | Q34: Dự kiến Cọc Vp1 dài 28m, cọc vp2 dài 25
B35: Nhà Văn Phòng 01 | F35: 65 | G35: 28 | J35: =F35*G35 -> 1820
B36: Nhà Văn Phòng 02 | F36: 35 | G36: 25 | J36: =F36*G36 -> 875
A37: 2 | B37: Máy phát điện thi công cọc Pile construction generator | E37: md | J37: =J35+J36 -> 2695 | K37: =J37 -> 2695 | O37: =+L37+M37+N37 -> 0 | P37: =O37*$K37 -> 0
A38: 3 | B38: Cắt đầu cọc Cutting pile heads | E38: cái | J38: =F35+F36 -> 100 | K38: =J38 -> 100 | O38: =+L38+M38+N38 -> 0 | P38: =O38*$K38 -> 0
B39: NHÀ XE 1 TẦNG | P39: =SUM(P40:P43) -> 0
A40: 1 | B40: Cung cấp và thi công cọc đại trà, PHC-A D300 Supply and construction of mass piles, PHC-A D300 | C40: Cọc PHC A , D300, L=27m, Pmax =120 tấn PHC A pile, D300, L=27m, Pmax =120 tons | D40: Kiến Hoa, Phan Vũ, BT Thủ Đức, Việt Thái An Kien Hoa, Phan Vu, BT Thu Duc, VTA | E40: md | K40: =J41 -> 351 | O40: =+L40+M40+N40 -> 0 | P40: =O40*$K40 -> 0 | Q40: Dự kiến ép cọc 27md
B41: Nhà xe | F41: 13 | G41: 27 | J41: =F41*G41 -> 351
A42: 2 | B42: Máy phát điện thi công cọc Pile construction generator | E42: md | J42: =J41 -> 351 | K42: =J42 -> 351 | O42: =+L42+M42+N42 -> 0 | P42: =O42*$K42 -> 0
A43: 3 | B43: Cắt đầu cọc Cutting pile heads | E43: cái | J43: =14 -> 14 | K43: =J43 -> 14 | O43: =+L43+M43+N43 -> 0 | P43: =O43*$K43 -> 0
O44: =+L44+M44+N44 -> 0 | P44: =O44*$K44 -> 0
B45: ='Summary '!B17 -> HẠNG MỤC BỂ NƯỚC PCCC, NHÀ BƠM | O45: =+L45+M45+N45 -> 0 | P45: =SUM(P47:P50) -> 0
O46: =+L46+M46+N46 -> 0 | P46: =O46*$K46 -> 0
A47: 1 | B47: Cung cấp và thi công cọc đại trà, PHC-A D300 Supply and construction of mass piles, PHC-A D300 | C47: Cọc PHC A , D300, L=27m, Pmax =120 tấn PHC A pile, D300, L=27m, Pmax =120 tons, | D47: Kiến Hoa, Phan Vũ, BT Thủ Đức, Việt Thái An Kien Hoa, Phan Vu, BT Thu Duc, VTA | E47: md | K47: =19*27 -> 513 | O47: =+L47+M47+N47 -> 0 | P47: =O47*$K47 -> 0 | Q47: =Q40 -> Dự kiến ép cọc 27md
B48: Bể PCCC | O48: =+L48+M48+N48 -> 0 | P48: =O48*$K48 -> 0
A49: 2 | B49: Máy phát điện thi công cọc Pile construction generator | E49: md | K49: =K47 -> 513 | O49: =+L49+M49+N49 -> 0 | P49: =O49*$K49 -> 0
A50: 3 | B50: Cắt đầu cọc Cutting pile heads | E50: cái | K50: 19 | O50: =+L50+M50+N50 -> 0 | P50: =O50*$K50 -> 0
B51: HÀNG RÀO | P51: =SUM(P52:P62) -> 0
A52: 1 | B52: Cung cấp và thi công cọc thử, PHC-A D300 M600 Supply and construction of test piles, PHC-A D300 | C52: Cọc PHC A , D300, L=20m, Pmax =140 tấn, Pmin=110 tấn PHC A pile, D300, L=20m, Pmax =120 tons | D52: Kiến Hoa, Phan Vũ, BT Thủ Đức, Việt Thái An Kien Hoa, Phan Vu, BT Thu Duc, VTA | E52: md | K52: 20 | O52: =M52+L52 -> 0 | P52: =O52*K52 -> 0
A53: 2 | B53: Thí nghiệm Cọc thử Test Pile Experiment | E53: tim | K53: 2 | O53: =M53+L53 -> 0 | P53: =O53*K53 -> 0
A54: 3 | B54: Cung cấp và thi công cọc đại trà, PHC-A D300 M600 Supply and construction of mass piles, PHC-A D300 | C54: =C52 -> Cọc PHC A , D300, L=20m, Pmax =140 tấn, Pmin=110 tấn PHC A pile, D300, L=20m, Pmax =120 tons | D54: Kiến Hoa, Phan Vũ, BT Thủ Đức, Việt Thái An Kien Hoa, Phan Vu, BT Thu Duc, VTA | E54: md | K54: =69*20 -> 1380 | O54: =M54+L54 -> 0 | P54: =O54*K54 -> 0
A55: 4 | B55: =B29 -> Trắc đạt định vị cọc | E55: lot | K55: 1 | O55: =M55+L55 -> 0 | P55: =O55*K55 -> 0
A56: 5 | B56: Máy phát điện thi công cọc Pile construction generator | E56: md | K56: =K54 -> 1380 | O56: =M56+L56 -> 0 | P56: =O56*K56 -> 0
A57: 6 | B57: Cắt đầu cọc Cutting pile heads | E57: cái | K57: 69 | O57: =M57+L57 -> 0 | P57: =O57*K57 -> 0
A65: =IF(ISBLANK(E65),"",MAX(#REF!)+1) | O65: =+L65+M65 -> 0 | P65: =O65*$K65 -> 0
A66: =IF(ISBLANK(E66),"",MAX($A$64:A65)+1) | O66: =+L66+M66+N66 -> 0 | P66: =O66*$K66 -> 0
A67: =IF(ISBLANK(E67),"",MAX($A$64:A66)+1) | O67: =+L67+M67+N67 -> 0 | P67: =O67*$K67 -> 0
A68: =IF(ISBLANK(E68),"",MAX($A$64:A67)+1) | O68: =+L68+M68+N68 -> 0 | P68: =O68*$K68 -> 0

Sheet 01 Nhà Xưởng 01+02
A1: BẢNG DỰ TOÁN BÁO GIÁ CÔNG TRÌNH / ESTIMATE TABLE
A3: ="HẠNG MỤC / ITEM : "&B8 -> HẠNG MỤC / ITEM : HẠNG MỤC NHÀ XƯỞNG 1 & 2
A6: STT NO. | B6: TÊN CÔNG VIỆC VÀ DIỄN GIẢI DESCRIPTION | C6: ĐẶC TÍNH KỸ THUẬT STANDARD | D6: NHÃN HIỆU & XUẤT XỨ BRAND NAME & ORIGIN | E6: Đvt Unit | F6: SL | G6: DÀI | H6: RỘNG | I6: CAO | J6: KL | K6: KL TỔNG Q'TY | L6: ĐƠN GIÁ / RATE | O6: TỔNG CỘNG (VNĐ) TOTAL COST(VND) | Q6: REMARK GHI CHÚ
L7: VẬT TƯ RATE MATERIALS | M7: NHÂN CÔNG RATE LABOUR | N7: MMTB RATE EQUIPMENT | O7: ĐƠN GIÁ TỔNG TOTAL PRICE | P7: THÀNH TIỀN AMOUNT TOTAL
B8: HẠNG MỤC NHÀ XƯỞNG 1 & 2 | K8: =SUM(K9:K22) -> 4.7237774e+10 | L8: =P8-K8 -> -4.7237774e+10 | P8: =SUBTOTAL(9,P9:P21) -> 0
A9: 1 | B9: =B23 -> CÔNG TÁC XỬ LÝ ĐẦU CỌC PILING WORKS | K9: 8.6873522e+09 | P9: =P23 -> 0
A10: 2 | B10: =B45 -> CÔNG TÁC ĐẤT EARTHWORKS | K10: 3.8678304e+08 | P10: =P45 -> 0
A11: 3 | B11: =B77 -> CÔNG TÁC BÊ TÔNG CONCRETE WORKS | K11: 5.4866826e+09 | P11: =P77 -> 0
A12: 4 | B12: =B126 -> CÔNG TÁC VÁN KHUÔN FORMWORK WORKS | K12: 675827296 | P12: =P126 -> 0
A13: 5 | B13: =B173 -> CÔNG TÁC CỐT THÉP REINFORCEMENT WORKS | K13: 3.2147143e+09 | P13: =P173 -> 0
A14: 6 | B14: =B182 -> CÔNG TÁC XÂY BRICK WALL | K14: 1.5126728e+09 | P14: =P182 -> 0 | R14: =2.5+3.2+1.7+0.8+1.7+0.8 -> 10.7
A15: 7 | B15: =B207 -> CÔNG TÁC TÔ TRÁT PLASTERING WORKS | K15: 670270440 | P15: =P207 -> 0
A16: 8 | B16: =B219 -> CÔNG TÁC SƠN PAINTING WORK | K16: 5.0721212e+08 | P16: =P219 -> 0
A17: 9 | B17: =B223 -> CÔNG TÁC HOÀN THIỆN NỀN SÀN FLOOR FINISHING WORK | K17: 992452188 | P17: =P223 -> 0
A18: 10 | B18: =B230 -> CÔNG TÁC TRẦN VÁCH CEILING & PARTITION WORKS | K18: 3253569200 | P18: =P230 -> 0
A19: 11 | B19: =B233 -> CÔNG TÁC CỬA DOOR WORKS | K19: 1.0316923e+09 | P19: =P233 -> 0
A20: 13 | B20: =B242 -> CÔNG TÁC KẾT CẤU THÉP VÀ MÁI STEEL STRUCTURE AND ROOF WORK | K20: 2.0653497e+10 | P20: =P242 -> 0
A21: 14 | B21: =B323 -> CÔNG TÁC HOÀN THIỆN KHÁC OTHER WORKS | K21: 165047700 | P21: =P323 -> 0
A23: 1 | B23: CÔNG TÁC XỬ LÝ ĐẦU CỌC PILING WORKS | P23: =SUBTOTAL(9,P24:P43) -> 0
A24: 1 | B24: Cung cấp và thi công, kiểm tra cọc thử, PHC-A D300 Supply and construction of test piles, PHC-A D300 | C24: Cọc PHC A , D300, L=33m, Pmax =120 tấn PHC A pile, D300, L=33m, Pmax =120 tons | D24: Kiến Hoa, Phan Vũ, BT Thủ Đức, Việt Thái An Kien Hoa, Phan Vu, BT Thu Duc, VTA | E24: tim | K24: =SUM(J25:J28) -> 132 | O24: =+L24+M24+N24 -> 0 | P24: =O24*$K24 -> 0
B25: Nhà xưởng 01 | F25: 2 | G25: 33 | J25: =F25*G25 -> 66 | O25: =+L25+M25+N25 -> 0 | P25: =O25*$K25 -> 0
B28: Nhà xưởng 2 | F28: 2 | G28: 33 | J28: =F28*G28 -> 66 | O28: =+L28+M28+N28 -> 0 | P28: =O28*$K28 -> 0
A29: 3 | B29: Tập kết giàn ép tới công trình | E29: lot | K29: 2 | O29: =+L29+M29+N29 -> 0 | P29: =O29*$K29 -> 0
A30: 4 | B30: Cung cấp và thi công cọc đại trà, PHC-A D300 Supply and construction of mass piles, PHC-A D300 | C30: Cọc PHC A , D300, Pmax =120 tấn PHC A pile, D300, Pmax =120 tons | D30: Kiến Hoa, Phan Vũ, BT Thủ Đức, Việt Thái An Kien Hoa, Phan Vu, BT Thu Duc, VTA | E30: md | K30: =SUM(J31:J36) -> 18595 | O30: =+L30+M30+N30 -> 0 | P30: =O30*$K30 -> 0
B31: Nhà xưởng 02 | F31: 309 | J31: =F31*G31 -> 0 | O31: =+L31+M31+N31 -> 0 | P31: =O31*$K31 -> 0
B32: Cọc chính móng | F32: 106 | G32: 30 | J32: =PRODUCT(F32:H32) -> 3180
B33: Cọc nền | F33: =F31-F32 -> 203 | G33: 25 | J33: =PRODUCT(F33:H33) -> 5075
B34: Nhà xưởng 01 | F34: 396 | O34: =+L34+M34+N34 -> 0 | P34: =O34*$K34 -> 0
B35: Cọc chính móng | F35: 88 | G35: 30 | J35: =PRODUCT(F35:H35) -> 2640
B36: Cọc nền | F36: =F34-F35 -> 308 | G36: 25 | J36: =PRODUCT(F36:H36) -> 7700
A37: 6 | B37: Trắc đạt định vị cọc | E37: lot | J37: 1 | K37: 1 | O37: =+L37+M37+N37 -> 0 | P37: =O37*$K37 -> 0
A38: 7 | B38: Test cọc D300, thử tĩnh tải | E38: tim | J38: 4 | K38: 4 | O38: =+L38+M38+N38 -> 0 | P38: =O38*$K38 -> 0
A39: 8 | B39: Máy phát điện thi công cọc Pile construction generator | E39: md | J39: =K30 -> 18595 | K39: =J39 -> 18595 | O39: =+L39+M39+N39 -> 0 | P39: =O39*$K39 -> 0
A40: 9 | B40: Cắt đầu cọc Cutting pile heads | E40: cái | J40: =F31+F34 -> 705 | K40: =J40 -> 705 | O40: =+L40+M40+N40 -> 0 | P40: =O40*$K40 -> 0
A41: 10 | B41: SXLD bản mã đầu cọc Anchor plate for pile heads | C41: Tấm dày 5mm, thép SS400 5mm thick plate, SS400 steel | D41: SS400 | E41: Kg | J41: =0.25*0.25*0.002*7850*739 -> 725.14375 | K41: =J41 -> 725.14375 | O41: =+L41+M41+N41 -> 0 | P41: =O41*$K41 -> 0
A42: 11 | B42: Cốt thép đầu cọc Anchor steel for pile heads | C42: 6D14, L=1500mm; D6a150 6D14, L=1500mm; D6a150 | E42: Kg | J42: =J40*11 -> 7755 | K42: =J42 -> 7755 | O42: =+L42+M42+N42 -> 0 | P42: =O42*$K42 -> 0
A43: 12 | B43: Bê tông đầu cọc Pile head concrete | C43: Độ sụt 10±2cm, Mác M300 Slump 10±2cm, Grade M300 | E43: m3 | J43: =0.2*0.2*1*739 -> 29.56 | K43: =J43 -> 29.56 | O43: =+L43+M43+N43 -> 0 | P43: =O43*$K43 -> 0
A45: 2 | B45: CÔNG TÁC ĐẤT EARTHWORKS | P45: =SUBTOTAL(9,P46:P76) -> 0
A46: =IF(ISBLANK(E46),"",COUNTA($E$22:E46)) -> 11 | B46: Đào đất móng, đà kiềng Excavation of foundation, tie beam | E46: m3 | K46: =SUM(J47:J53) -> 1152.104 | O46: =+L46+M46+N46 -> 0 | P46: =O46*$K46 -> 0
B47: Nhà xưởng 02
B48: M1 | F48: 309 | G48: 0.8 | H48: 0.8 | I48: 0.8 | J48: =F48*(G48+0.6)*(H48+0.6)*I48 -> 484.512
B49: M1 | G49: 0.8 | H49: 0.8 | I49: 2 | J49: =F49*(G49+0.6)*(H49+0.6)*I49 -> 0
B50: Nhà xưởng 01
B51: M1 | F51: =316-F52-F53 -> 263 | G51: 0.8 | H51: 0.8 | I51: 0.8 | J51: =F51*(G51+0.6)*(H51+0.6)*I51 -> 412.384
B52: M2 | F52: 17 | G52: 1.7 | H52: 0.8 | I52: 2 | J52: =F52*(G52+0.6)*(H52+0.6)*I52 -> 109.48
B53: M3 | F53: 36 | G53: 1.7 | H53: 1.6 | I53: 0.8 | J53: =F53*(G53+0.6)*(H53+0.6)*I53 -> 145.728
A57: =IF(ISBLANK(E57),"",COUNTA($E$22:E57)) -> 12 | B57: Đắp đất nền nhà xưởng Backfilling for warehouse floor | E57: m3 | K57: =(K73*0.25) -> 2425.75 | O57: =+L57+M57+N57 -> 0 | P57: =O57*$K57 -> 0
A58: =IF(ISBLANK(E58),"",COUNTA($E$22:E58)) -> 13 | B58: Lấp đất & đầm chặt Backfilling foundation and compacting | E58: m3 | K58: =K46-K78-K90-K103 -> 229.689 | O58: =+L58+M58+N58 -> 0 | P58: =O58*$K58 -> 0
A59: =IF(ISBLANK(E59),"",COUNTA($E$22:E59)) -> 14 | B59: Vận chuyển đất trong phạm vi công trình Transporting excavated soil within the construction site | E59: m3 | K59: =K46-K58 -> 922.415 | O59: =+L59+M59+N59 -> 0 | P59: =O59*$K59 -> 0
A60: =IF(ISBLANK(E60),"",COUNTA($E$22:E60)) -> 15 | B60: Sửa và Đầm chặt đáy hố móng & đà kiềng Compacting and treating the bottom soil of foudation and tie beams | E60: m2 | K60: =SUM(J61:J70) -> 992.38 | O60: =+L60+M60+N60 -> 0 | P60: =O60*$K60 -> 0
B61: Nhà xưởng 02
B62: M1 | F62: =F48 -> 309 | G62: 0.8 | H62: 0.8 | J62: =F62*(G62+0.2)*(H62+0.2) -> 309
B63: Nhà xưởng 01
B64: M1 | F64: =F51 -> 263 | G64: 0.8 | H64: 0.8 | J64: =F64*(G64+0.2)*(H64+0.2) -> 263
B65: M2 | F65: 17 | G65: 1.7 | H65: 0.8 | J65: =F65*(G65+0.2)*(H65+0.2) -> 32.3
B66: M3 | F66: 36 | G66: 1.7 | H66: 1.6 | J66: =F66*(G66+0.2)*(H66+0.2) -> 123.12
B67: Nhà Xưởng 01
B68: DK1 | F68: 1 | G68: 380 | H68: 0.2 | J68: =F68*(G68+0.2)*(H68+0.2) -> 152.08
B69: Nhà Xưởng 02
B70: DK2 | F70: 1 | G70: 282 | H70: 0.2 | J70: =F70*(G70+0.2)*(H70+0.2) -> 112.88
A73: =IF(ISBLANK(E73),"",COUNTA($E$22:E73)) -> 16 | B73: Lu lèn nền đất Compacting natural ground | E73: m2 | K73: =4973+4730 -> 9703 | O73: =+L73+M73+N73 -> 0 | P73: =O73*$K73 -> 0
A74: =IF(ISBLANK(E74),"",COUNTA($E$22:E74)) -> 17 | B74: Tấm PVC PVC layer | C74: 01 Lớp PVC dày 0.03mm 01 PVC layers 0.03mm thick | E74: m2 | K74: 9678 | O74: =+L74+M74+N74 -> 0 | P74: =O74*$K74 -> 0 | Q74: CĐT cung cấp
A77: 3 | B77: CÔNG TÁC BÊ TÔNG CONCRETE WORKS | D77: Hồng Tín, Hồng Hà, Đại Lộc Phát Hong Tin, Hong Ha, Dai Loc Phat | P77: =SUBTOTAL(9,P78:P125) -> 0
A78: =IF(ISBLANK(E78),"",COUNTA($E$22:E78)) -> 18 | B78: Bê tông lót, M150 Lean concrete, M150 | C78: Độ sụt 10±2cm, Mác M150 Slump 10±2cm, Grade M150 | E78: m3 | K78: =SUM(J79:J89) -> 511.839 | O78: =+L78+M78+N78 -> 0 | P78: =O78*$K78 -> 0
B79: Nhà xưởng 02
B80: M1 | F80: =F62 -> 309 | G80: 0.8 | H80: 0.8 | I80: 0.05 | J80: =F80*(G80+0.2)*(H80+0.2)*I80 -> 15.45
B81: Nhà xưởng 01
B82: M1 | F82: =F64 -> 263 | G82: 0.8 | H82: 0.8 | I82: 0.05 | J82: =F82*(G82+0.2)*(H82+0.2)*I82 -> 13.15
B83: M2 | F83: =F65 -> 17 | G83: 1.7 | H83: 0.8 | I83: 0.05 | J83: =F83*(G83+0.2)*(H83+0.2)*I83 -> 1.615
B84: M3 | F84: =F66 -> 36 | G84: 1.7 | H84: 1.6 | I84: 0.05 | J84: =F84*(G84+0.2)*(H84+0.2)*I84 -> 6.156
B85: Nhà Xưởng 01
B86: DK1 | F86: 1 | G86: 274 | H86: 0.2 | I86: 0.05 | J86: =F86*(G86+0.2)*(H86+0.2)*I86 -> 5.484
B87: Nhà Xưởng 01 | J87: =F87*(G87+0.2)*(H87+0.2)*I87 -> 0
B88: DK1 | F88: 1 | G88: 304 | H88: 0.2 | I88: 0.05 | J88: =F88*(G88+0.2)*(H88+0.2)*I88 -> 6.084
B89: Bê tông lót nền xưởng | G89: =K74 -> 9678 | H89: =-(F80+F82+F83+F84)*0.8*0.8 -> -400 | I89: =I88 -> 0.05 | J89: =(G89+H89)*I89 -> 463.9
A90: =IF(ISBLANK(E90),"",COUNTA($E$22:E90)) -> 19 | B90: Bê tông Móng, M250 Foundation concrete, M250 | C90: Độ sụt 10±2cm, Mác M250 Slump 10±2cm, Grade M250 | E90: m3 | K90: =SUM(J92:J96) -> 389.696 | O90: =+L90+M90+N90 -> 0 | P90: =O90*$K90 -> 0
B91: Nhà xưởng 02
B92: M1 | F92: =F62 -> 309 | G92: 0.8 | H92: 0.8 | I92: 0.8 | J92: =PRODUCT(F92:I92) -> 158.208
B93: Nhà xưởng 01 | J93: =PRODUCT(F93:I93) -> 0
B94: M1 | F94: =F64 -> 263 | G94: 0.8 | H94: 0.8 | I94: 0.8 | J94: =PRODUCT(F94:I94) -> 134.656
B95: M2 | F95: =F65 -> 17 | G95: 1.7 | H95: 0.8 | I95: 0.8 | J95: =PRODUCT(F95:I95) -> 18.496
B96: M3 | F96: =F66 -> 36 | G96: 1.7 | H96: 1.6 | I96: 0.8 | J96: =PRODUCT(F96:I96) -> 78.336
J97: =PRODUCT(F97:I97) -> 0
A98: =IF(ISBLANK(E98),"",COUNTA($E$22:E98)) -> 20 | B98: Bê tông Đà kiềng, Dầm Ground beam concrete | C98: Độ sụt 10±2cm, Mác M250 Slump 10±2cm, Grade M250 | E98: m3 | J98: =PRODUCT(F98:I98) -> 0 | K98: =SUM(J100:J102)*1.05 -> 55.608 | O98: =+L98+M98+N98 -> 0 | P98: =O98*$K98 -> 0
B99: Nhà Xưởng 01 | J99: =PRODUCT(F99:I99) -> 0
B100: DK1 | F100: 1 | G100: =G68 -> 380 | H100: 0.2 | I100: 0.4 | J100: =PRODUCT(F100:I100) -> 30.4
B101: Nhà Xưởng 02 | J101: =PRODUCT(F101:I101) -> 0
B102: DK2 | F102: 1 | G102: =G70 -> 282 | H102: 0.2 | I102: 0.4 | J102: =PRODUCT(F102:I102) -> 22.56
A103: =IF(ISBLANK(E103),"",COUNTA($E$22:E103)) -> 21 | B103: Bê tông Cổ cột và Cột Stump and column concrete | C103: Độ sụt 10±2cm, Mác M250 Slump 10±2cm, Grade M250 | E103: m3 | K103: =SUM(J105:J107) -> 20.88 | O103: =+L103+M103+N103 -> 0 | P103: =O103*$K103 -> 0
B104: Cổ cột nhà xưởng 01
B105: C1 | F105: 24 | G105: 0.3 | H105: 0.6 | I105: 2 | J105: =F105*G105*H105*I105 -> 8.64
B106: Cổ cột nhà xưởng 02
B107: C1 | F107: 34 | G107: 0.3 | H107: 0.6 | I107: 2 | J107: =F107*G107*H107*I107 -> 12.24
A109: =IF(ISBLANK(E109),"",COUNTA($E$22:E109)) -> 22 | B109: Bê tông hố Pit, Dock, Mương, cầu thang, ram dốc Pit, dock,trench, ramp concrete | C109: =C103 -> Độ sụt 10±2cm, Mác M250 Slump 10±2cm, Grade M250 | E109: m3 | K109: =SUM(J111:J116) -> 52.041 | O109: =+L109+M109+N109 -> 0 | P109: =O109*$K109 -> 0
B110: Nhà xưởng 01
B111: Ram dốc | F111: 5 | G111: 5 | H111: 1.8 | I111: 0.2 | J111: =F111*G111*H111*I111 -> 9
B112: Đáy | F112: 5 | G112: =G111+H111*2 -> 8.6 | H112: 0.2 | I112: 0.3 | J112: =F112*G112*H112*I112 -> 2.58
B113: Nhà xưởng 02
B114: Ram dốc
B115: Đáy | F115: 1 | G115: 29.9 | H115: 4.2 | I115: 0.2 | J115: =F115*G115*H115*I115 -> 25.116
...

Sheet  02 Văn Phòng 01+02
A1: BẢNG DỰ TOÁN BÁO GIÁ CÔNG TRÌNH / ESTIMATE TABLE
A3: ="HẠNG MỤC / ITEM : "&B8 -> HẠNG MỤC / ITEM : HẠNG MỤC NHÀ VĂN PHÒNG 1&2
A6: STT NO. | B6: TÊN CÔNG VIỆC VÀ DIỄN GIẢI DESCRIPTION | C6: ĐẶC TÍNH KỸ THUẬT STANDARD | D6: NHÃN HIỆU & XUẤT XỨ BRAND NAME & ORIGIN | E6: Đvt Unit | F6: SL | G6: DÀI | H6: RỘNG | I6: CAO | J6: KL | K6: KL TỔNG Q'TY | L6: ĐƠN GIÁ / RATE | O6: TỔNG CỘNG (VNĐ) TOTAL COST(VND) | Q6: REMARK GHI CHÚ
L7: VẬT TƯ RATE MATERIALS | M7: NHÂN CÔNG RATE LABOUR | N7: MMTB RATE EQUIPMENT | O7: ĐƠN GIÁ TỔNG TOTAL PRICE | P7: THÀNH TIỀN AMOUNT TOTAL
B8: HẠNG MỤC NHÀ VĂN PHÒNG 1&2 | K8: 1.1475749e+10 | P8: =SUBTOTAL(9,P9:P22) -> 0 | Q8: =P8/1596 -> 0
A9: A | B9: =B24 -> CÔNG TÁC XỬ LÝ ĐẦU CỌC PILING WORKS | K9: 1.2778588e+09 | P9: =P24 -> 0
A10: =A38 -> B | B10: =B38 -> CÔNG TÁC ĐẤT EARTHWORKS | K10: 32116252 | P10: =P38 -> 0
A11: =A83 -> C | B11: =B83 -> CÔNG TÁC BÊ TÔNG CONCRETE WORKS | K11: 1.1469311e+09 | P11: =P83 -> 0
A12: D | B12: =B200 -> CÔNG TÁC VÁN KHUÔN FORMWORK WORKS | K12: 9.5994736e+08 | P12: =P200 -> 0
A13: =A315 -> E | B13: =B315 -> CÔNG TÁC CỐT THÉP REINFORCEMENT WORKS | K13: 1.8461051e+09 | P13: =P315 -> 0
A14: =A323 -> F | B14: =B323 -> CÔNG TÁC XÂY BRICK WALL | K14: 1.1897028e+09 | P14: =P323 -> 0
A15: =A347 -> G | B15: =B347 -> CÔNG TÁC TÔ TRÁT PLASTERING WORKS | K15: 5.2699803e+08 | P15: =P347 -> 0
A16: =A373 -> H | B16: =B373 -> CÔNG TÁC SƠN PAINTING WORK | K16: 5.6652711e+08 | P16: =P373 -> 0
A17: =A378 -> I | B17: =B378 -> CÔNG TÁC CHỐNG THẤM WATERPROFING WORKS | K17: 1.9793814e+08 | P17: =P378 -> 0
A18: =A394 -> K | B18: =B394 -> CÔNG TÁC ỐP LÁT TILING WORK | K18: 1.3485196e+09 | P18: =P394 -> 0
A19: =A411 -> L | B19: =B411 -> CÔNG TÁC TRẦN VÁCH CEILING & PARTITION WORKS | K19: 486901085 | P19: =P411 -> 0
A20: =A428 -> M | B20: =B428 -> CÔNG TÁC CỬA DOOR WORKS | K20: 1868143276 | P20: =P428 -> 0
A21: =A440 -> P | B21: =B440 -> CÔNG TÁC HOÀN THIỆN KHÁC OTHER WORKS | K21: 28060000 | P21: =P440 -> 0
A24: A | B24: CÔNG TÁC XỬ LÝ ĐẦU CỌC PILING WORKS | P24: =SUBTOTAL(9,P25:P37) -> 0
A25: 1 | B25: Cung cấp và thi công cọc thử, PHC-A D300 Supply and construction of test piles, PHC-A D300
B26: Nhà Văn Phòng 01
B27: Nhà Văn Phòng 02
A28: 3 | B28: Thí nghiệm Cọc thử Test Pile Experiment
A29: 4 | B29: Cung cấp và thi công cọc đại trà, PHC-A D300 Supply and construction of mass piles, PHC-A D300 | C29: Cọc PHC A , D300, Pmax =120 tấn PHC A pile, D300, Pmax =120 tons | D29: Kiến Hoa, Phan Vũ, BT Thủ Đức, Việt Thái An Kien Hoa, Phan Vu, BT Thu Duc, VTA | E29: md | K29: =J30+J31 -> 2695 | O29: =+L29+M29+N29 -> 0 | P29: =O29*$K29 -> 0
B30: Nhà Văn Phòng 01 | F30: 65 | G30: 28 | J30: =F30*G30 -> 1820
B31: Nhà Văn Phòng 02 | F31: 35 | G31: 25 | J31: =F31*G31 -> 875
A32: 8 | B32: Máy phát điện thi công cọc Pile construction generator | E32: md | J32: =J30+J31 -> 2695 | K32: =J32 -> 2695 | O32: =+L32+M32+N32 -> 0 | P32: =O32*$K32 -> 0
A33: 9 | B33: Cắt đầu cọc Cutting pile heads | E33: cái | J33: =F30+F31 -> 100 | K33: =J33 -> 100 | O33: =+L33+M33+N33 -> 0 | P33: =O33*$K33 -> 0
A34: 10 | B34: SXLD bản mã đầu cọc Anchor plate for pile heads | D34: SS400 | E34: Kg | J34: =0.3*0.3*0.005*7850*108 -> 381.51 | K34: =J34 -> 381.51 | O34: =+L34+M34+N34 -> 0 | P34: =O34*$K34 -> 0
A35: 11 | B35: Cốt thép đầu cọc Anchor steel for pile heads | C35: 6D14, L=1500mm; D6a150 6D14, L=1500mm; D6a150 | E35: Kg | J35: =F35*(G35+0.6)*(H35+0.6)*I35 -> 0 | K35: =K33*11 -> 1100 | O35: =+L35+M35+N35 -> 0 | P35: =O35*$K35 -> 0
A36: 12 | B36: Bê tông đầu cọc Pile head concrete | C36: Độ sụt 10±2cm, Mác M300 Slump 10±2cm, Grade M300 | E36: m3 | J36: =F36*(G36+0.6)*(H36+0.6)*I36 -> 0 | K36: =0.2*0.2*1*108 -> 4.32 | O36: =+L36+M36+N36 -> 0 | P36: =O36*$K36 -> 0
A38: B | B38: CÔNG TÁC ĐẤT EARTHWORKS | P38: =SUBTOTAL(9,P39:P82) -> 0
A39: =IF(ISBLANK(E39),"",COUNTA($E$23:E39)) -> 7 | B39: Đào đất móng, đà kiềng Excavation of foundation, tie beam | E39: m3 | K39: =SUM(J40:J49) -> 178.465 | O39: =+L39+M39+N39 -> 0 | P39: =O39*$K39 -> 0
B40: Nhà Văn Phòng 01
B41: Mv1 | F41: 3 | G41: 1.7 | H41: 0.8 | I41: 1 | J41: =F41*(G41+0.6)*(H41+0.6)*I41 -> 9.66
B42: Mv2 | F42: 14 | G42: 1.7 | H42: 0.8 | I42: 1 | J42: =F42*(G42+0.6)*(H42+0.6)*I42 -> 45.08
B43: Mv3 | F43: 5 | G43: 1.7 | H43: 1.6 | I43: 1 | J43: =F43*(G43+0.6)*(H43+0.6)*I43 -> 25.3
B44: Mv4 | F44: 4 | G44: 1.7 | H44: 1.7 | I44: 1 | J44: =F44*(G44+0.6)*(H44+0.6)*I44 -> 21.16
B45: Mv5 | F45: 1 | G45: 2.6 | H45: 2.75 | I45: 1 | J45: =F45*(G45+0.6)*(H45+0.6)*I45 -> 10.72
B46: Mv6 | F46: 1 | G46: 2.1 | H46: 2.75 | I46: 1 | J46: =F46*(G46+0.6)*(H46+0.6)*I46 -> 9.045
B47: Nhà Văn Phòng 02
B48: Mv2.1 | F48: 10 | G48: 1.7 | H48: 0.8 | I48: 1 | J48: =F48*(G48+0.6)*(H48+0.6)*I48 -> 32.2
B49: Mv2.2 | F49: 5 | G49: 1.7 | H49: 1.6 | I49: 1 | J49: =F49*(G49+0.6)*(H49+0.6)*I49 -> 25.3
A52: =IF(ISBLANK(E52),"",COUNTA($E$23:E52)) -> 8 | B52: Đắp đất nền g tận dụng đất nền hiện hữu ko mua mới Backfilling for warehouse floor, reuse existing soil | E52: m3 | K52: =(G190+G196)*0.2 -> 99.8 | O52: =+L52+M52+N52 -> 0 | P52: =O52*$K52 -> 0
A53: =IF(ISBLANK(E53),"",COUNTA($E$23:E53)) -> 9 | B53: Lấp đất & đầm chặt Backfilling foundation and compacting | E53: m3 | K53: =K39-K84-K108-K174 -> 27.01125 | O53: =+L53+M53+N53 -> 0 | P53: =O53*$K53 -> 0
A54: =IF(ISBLANK(E54),"",COUNTA($E$23:E54)) -> 10 | B54: Vận chuyển đất trong phạm vi công trình Transporting excavated soil within the construction site | E54: m3 | K54: =K39-K53 -> 151.45375 | O54: =+L54+M54+N54 -> 0 | P54: =O54*$K54 -> 0
A55: =IF(ISBLANK(E55),"",COUNTA($E$23:E55)) -> 11 | B55: Sửa và Đầm chặt đáy hố móng & đà kiềng Compacting and treating the bottom soil of foudation and tie beams | E55: m2 | K55: =SUM(J56:J76) -> 279.755 | O55: =+L55+M55+N55 -> 0 | P55: =O55*$K55 -> 0
B56: Nhà Văn Phòng 01
B57: Mv1 | F57: 3 | G57: 1.7 | H57: 0.8 | J57: =F57*(G57+0.2)*(H57+0.2) -> 5.7
B58: Mv2 | F58: 14 | G58: 1.7 | H58: 0.8 | J58: =F58*(G58+0.2)*(H58+0.2) -> 26.6
B59: Mv3 | F59: 5 | G59: 1.7 | H59: 1.6 | J59: =F59*(G59+0.2)*(H59+0.2) -> 17.1
B60: Mv4 | F60: 4 | G60: 1.7 | H60: 1.7 | J60: =F60*(G60+0.2)*(H60+0.2) -> 14.44
B61: Mv5 | F61: 1 | G61: 2.6 | H61: 2.75 | J61: =F61*(G61+0.2)*(H61+0.2) -> 8.26
B62: Mv6 | F62: 1 | G62: 2.1 | H62: 2.75 | J62: =F62*(G62+0.2)*(H62+0.2) -> 6.785
B63: Nhà Văn Phòng 02 | J63: =F63*(G63+0.2)*(H63+0.2) -> 0
B64: Mv2.1 | F64: 10 | G64: 1.7 | H64: 0.8 | J64: =F64*(G64+0.2)*(H64+0.2) -> 19
B65: Mv2.2 | F65: 5 | G65: 1.7 | H65: 1.6 | J65: =F65*(G65+0.2)*(H65+0.2) -> 17.1
B66: Sàn Tầng 1 | J66: =F66*(G66+0.2)*(H66+0.2) -> 0
B67: D200x400 | F67: 1 | G67: =7.7+5.6*2+7.7+1.8+7.6+7.6+30.4*2+1.75+8.8+2.8+9.3+7.15*2+6 -> 147.35 | H67: 0.2 | J67: =F67*(G67+0.2)*(H67+0.2) -> 59.02
B68: D300x500 | F68: 1 | G68: =7.9*6 -> 47.4 | H68: 0.3 | J68: =F68*(G68+0.2)*(H68+0.2) -> 23.8
B69: D300x400 | F69: 1 | G69: =7.9*4 -> 31.6 | H69: 0.3 | J69: =F69*(G69+0.2)*(H69+0.2) -> 15.9
B70: D200x500 | F70: 1 | G70: =7.9*2 -> 15.8 | H70: 0.2 | J70: =F70*(G70+0.2)*(H70+0.2) -> 6.4
B71: D300x300 | F71: 1 | G71: 1.9 | H71: 0.3 | J71: =F71*(G71+0.2)*(H71+0.2) -> 1.05
B72: D400x600 | F72: 3 | G72: 4.8 | H72: 0.4 | J72: =F72*(G72+0.2)*(H72+0.2) -> 9
B73: Nhà Văn Phòng 02
B74: Tầng 1
B75: D200x400 | F75: 1 | G75: =21.2*3+3.3+4*4+10 -> 92.9 | H75: 0.2 | J75: =F75*(G75+0.2)*(H75+0.2) -> 37.24
B76: D200x500 | F76: 1 | G76: =6.7+6*4 -> 30.7 | H76: 0.2 | J76: =F76*(G76+0.2)*(H76+0.2) -> 12.36
A80: =IF(ISBLANK(E80),"",COUNTA($E$23:E80)) -> 12 | B80: Lu lèn nền đất K=0,92 Compacting natural ground | E80: m2 | K80: =(G190+G196) -> 499 | O80: =+L80+M80+N80 -> 0 | P80: =O80*$K80 -> 0
A81: =IF(ISBLANK(E81),"",COUNTA($E$23:E81)) -> 13 | B81: Tấm PVC PVC layer | C81: 01 Lớp PVC dày 0.03mm 01 PVC layers 0.03mm thick | E81: m2 | K81: =K80 -> 499 | O81: =+L81+M81+N81 -> 0 | P81: =O81*$K81 -> 0 | Q81: CĐT cung cấp
A83: C | B83: CÔNG TÁC BÊ TÔNG CONCRETE WORKS | D83: Hồng Tín, Hồng Hà, Đại Lộc Phát Hong Tin, Hong Ha, Dai Loc Phat | P83: =SUBTOTAL(9,P84:P199) -> 0
A84: =IF(ISBLANK(E84),"",COUNTA($E$23:E84)) -> 14 | B84: Bê tông lót, M150 Lean concrete, M150 | C84: Độ sụt 10±2cm, Mác M150 Slump 10±2cm, Grade M150 | E84: m3 | K84: =SUM(J85:J106) -> 26.03775 | O84: =+L84+M84+N84 -> 0 | P84: =O84*$K84 -> 0
B85: Nhà Văn Phòng 01
B86: Mv1 | F86: 3 | G86: 1.7 | H86: 0.8 | I86: 0.05 | J86: =F86*(G86+0.2)*(H86+0.2)*I86 -> 0.285
B87: Mv2 | F87: 14 | G87: 1.7 | H87: 0.8 | I87: 0.05 | J87: =F87*(G87+0.2)*(H87+0.2)*I87 -> 1.33
B88: Mv3 | F88: 5 | G88: 1.7 | H88: 1.6 | I88: 0.05 | J88: =F88*(G88+0.2)*(H88+0.2)*I88 -> 0.855
B89: Mv4 | F89: 4 | G89: 1.7 | H89: 1.7 | I89: 0.05 | J89: =F89*(G89+0.2)*(H89+0.2)*I89 -> 0.722
B90: Mv5 | F90: 1 | G90: 2.6 | H90: 2.75 | I90: 0.05 | J90: =F90*(G90+0.2)*(H90+0.2)*I90 -> 0.413
B91: Mv6 | F91: 1 | G91: 2.1 | H91: 2.75 | I91: 0.05 | J91: =F91*(G91+0.2)*(H91+0.2)*I91 -> 0.33925
B92: Sàn Tầng 1
B93: D200x400 | F93: 1 | G93: =7.7+5.6*2+7.7+1.8+7.6+7.6+30.4*2+1.75+8.8+2.8+9.3+7.15*2+6 -> 147.35 | H93: 0.2 | I93: 0.05 | J93: =F93*(G93+0.2)*(H93+0.2)*I93 -> 2.951
B94: D300x500 | F94: 1 | G94: =7.9*6 -> 47.4 | H94: 0.3 | I94: 0.05 | J94: =F94*(G94+0.2)*(H94+0.2)*I94 -> 1.19
B95: D300x400 | F95: 1 | G95: =7.9*4 -> 31.6 | H95: 0.3 | I95: 0.05 | J95: =F95*(G95+0.2)*(H95+0.2)*I95 -> 0.795
B96: D200x500 | F96: 1 | G96: =7.9*2 -> 15.8 | H96: 0.2 | I96: 0.05 | J96: =F96*(G96+0.2)*(H96+0.2)*I96 -> 0.32
B97: D300x300 | F97: 1 | G97: 1.9 | H97: 0.3 | I97: 0.05 | J97: =F97*(G97+0.2)*(H97+0.2)*I97 -> 0.0525
B98: D400x600 | F98: 3 | G98: 4.8 | H98: 0.4 | I98: 0.05 | J98: =F98*(G98+0.2)*(H98+0.2)*I98 -> 0.45
B99: Nhà Văn Phòng 02
B100: Mv2.1 | F100: 10 | G100: 1.7 | H100: 0.8 | I100: 0.05 | J100: 0.05
B101: Mv2.2 | F101: 5 | G101: 1.7 | H101: 1.6 | I101: 0.05 | J101: =F101*(G101+0.2)*(H101+0.2)*I101 -> 0.855
B102: Nhà Văn Phòng 02
B103: Tầng 1
B104: D200x400 | F104: 1 | G104: =21.2*3+3.3+4*4+10 -> 92.9 | H104: 0.2 | I104: 0.05 | J104: =F104*(G104+0.2)*(H104+0.2)*I104 -> 1.862
B105: D200x500 | F105: 1 | G105: =6.7+6*4 -> 30.7 | H105: 0.2 | I105: 0.05 | J105: =F105*(G105+0.2)*(H105+0.2)*I105 -> 0.618
B106: sàn nền trệt | H106: 499 | I106: 0.05 | J106: =I106*H106-12 -> 12.95
A108: =IF(ISBLANK(E108),"",COUNTA($E$23:E108)) -> 15 | B108: ='01 Nhà Xưởng 01+02'!B90 -> Bê tông Móng, M250 Foundation concrete, M250 | C108: ='01 Nhà Xưởng 01+02'!C90 -> Độ sụt 10±2cm, Mác M250 Slump 10±2cm, Grade M250 | E108: m3 | K108: =SUM(J110:J119) -> 70.724 | O108: =+L108+M108+N108 -> 0 | P108: =O108*$K108 -> 0
B109: Nhà Văn Phòng 01
B110: Mv1 | F110: 3 | G110: 1.7 | H110: 0.8 | I110: 0.8 | J110: =F110*G110*H110*I110 -> 3.264
B111: Mv2 | F111: 14 | G111: 1.7 | H111: 0.8 | I111: 0.8 | J111: =F111*G111*H111*I111 -> 15.232
B112: Mv3 | F112: 5 | G112: 1.7 | H112: 1.6 | I112: 0.8 | J112: =F112*G112*H112*I112 -> 10.88
B113: Mv4 | F113: 4 | G113: 1.7 | H113: 1.7 | I113: 0.8 | J113: =F113*G113*H113*I113 -> 9.248
...

Sheet 02 Nhà Bảo Vệ_& P. Y TẾ
A1: BẢNG DỰ TOÁN BÁO GIÁ CÔNG TRÌNH / ESTIMATE TABLE
A2: ="DỰ ÁN / PROJECT : "&#REF! -> #REF!
A3: ="HẠNG MỤC / ITEM : "&B8 -> HẠNG MỤC / ITEM : NHÀ BẢO VỆ & PHÒNG Y TẾ GUARD HOUSE & MEDICAL ROOM
A4: ="CHỦ ĐẦU TƯ / : "&#REF! -> #REF!
A6: STT NO. | B6: TÊN CÔNG VIỆC VÀ DIỄN GIẢI DESCRIPTION | C6: ĐẶC TÍNH KỸ THUẬT STANDARD | D6: NHÃN HIỆU & XUẤT XỨ BRAND NAME & ORIGIN | E6: Đvt Unit | F6: SL | G6: DÀI | H6: RỘNG | I6: CAO | J6: KL | K6: KL TỔNG Q'TY | L6: ĐƠN GIÁ / RATE | O6: TỔNG CỘNG (VNĐ) TOTAL COST(VND) | Q6: REMARK GHI CHÚ
L7: VẬT TƯ RATE MATERIALS | M7: NHÂN CÔNG RATE LABOUR | N7: MMTB RATE EQUIPMENT | O7: ĐƠN GIÁ TỔNG TOTAL PRICE | P7: THÀNH TIỀN AMOUNT TOTAL | R7: VẬT TƯ RATE MATERIALS | S7: NHÂN CÔNG RATE LABOUR
A8: =A21 -> *** | B8: =B21 -> NHÀ BẢO VỆ & PHÒNG Y TẾ GUARD HOUSE & MEDICAL ROOM | P8: =SUBTOTAL(9,P9:P20) -> #REF!
A9: A | B9: =B22 -> CÔNG TÁC ĐẤT EARTHWORK | P9: =P22 -> #REF!
A10: =A47 -> C | B10: =B47 -> CÔNG TÁC BÊ TÔNG CONCRETE WORK | P10: =P47 -> #REF!
A11: =A82 -> D | B11: =B82 -> CÔNG TÁC VÁN KHUÔN FORMWORK | P11: =P82 -> #REF!
A12: =A116 -> E | B12: =B116 -> CÔNG TÁC CỐT THÉP REBAR WORK | P12: =P116 -> #REF!
A13: =A123 -> F | B13: =B123 -> CÔNG TÁC XÂY BRICK WALL | P13: =P123 -> #REF!
A14: =A133 -> G | B14: =B133 -> CÔNG TÁC TÔ TRÁT PLASTERING WORK | P14: =P133 -> #REF!
A15: =A146 -> H | B15: =B146 -> CÔNG TÁC SƠN PAINTING WORK | P15: =P146 -> #REF!
A16: =A150 -> I | B16: =B150 -> CÔNG TÁC CHỐNG THẤM WATERPROOFING WORK | P16: =P150 -> #REF!
A17: =A158 -> J | B17: =B158 -> CÔNG TÁC TRẦN VÁCH CEILING & PARTITION WORKS | P17: =P158 -> #REF!
A18: =A162 -> K | B18: =B162 -> CÔNG TÁC CỬA DOOR WORK | P18: =P162 -> 60121000
A19: =A170 -> L | B19: =B170 -> CÔNG TÁC KHÁC OTHER WORKS | P19: =P170 -> 590000
A21: *** | B21: NHÀ BẢO VỆ & PHÒNG Y TẾ GUARD HOUSE & MEDICAL ROOM | P21: =SUBTOTAL(9,P178:P418) -> 0 | R21: Profit | T21: 1.18
A22: B | B22: CÔNG TÁC ĐẤT EARTHWORK | P22: =SUBTOTAL(9,P23:P46) -> #REF!
A23: =IF(ISBLANK(E23),"",COUNTA($E$21:E23)) -> 1 | B23: Đào đất hố móng, đường ống, khuôn đường Excavation of foundation pits, pipes, road molds | E23: m3 | K23: =SUM(J24:J26) -> 27.216 | L23: =R23*$T$21 -> #REF! | M23: =S23*$T$21 -> #REF! | O23: =+L23+M23+N23 -> #REF! | P23: =O23*$K23 -> #REF! | R23: ='01 Nhà Xưởng 01+02'!#REF! -> #REF! | S23: ='01 Nhà Xưởng 01+02'!#REF! -> #REF!
B24: M1 | F24: 3 | G24: 1.2 | H24: 1.2 | I24: 1.4 | J24: =F24*(G24+0.6)*(H24+0.6)*I24 -> 13.608
B25: M2 | F25: 2 | G25: 1.2 | H25: 1.2 | I25: 1.4 | J25: =F25*(G25+0.6)*(H25+0.6)*I25 -> 9.072
B26: M3 | F26: 1 | G26: 1.2 | H26: 1.2 | I26: 1.4 | J26: =F26*(G26+0.6)*(H26+0.6)*I26 -> 4.536
A27: =IF(ISBLANK(E27),"",COUNTA($E$21:E27)) -> 2 | B27: Đào đất đà kiềng, nền nhà Digging up the land and the foundation of the house | E27: m3 | K27: =SUM(J28:J31) -> 12.21 | L27: =R27*$T$21 -> 0 | M27: =S27*$T$21 -> 50740 | O27: =+L27+M27+N27 -> 50740 | P27: =O27*$K27 -> 619535.4 | S27: 43000
B28: DK1 | F28: 2 | G28: 9 | H28: 0.2 | I28: 0.4 | J28: =F28*(G28+0.6)*(H28+0.6)*I28 -> 6.144 | M28: =S28*$T$21 -> 0 | S28: =S24 -> 0
F29: 3 | G29: 4 | H29: 0.2 | I29: 0.4 | J29: =F29*(G29+0.6)*(H29+0.6)*I29 -> 4.416 | M29: =S29*$T$21 -> 0 | S29: =S25 -> 0
B30: DK2 | F30: 1 | G30: 4 | H30: 0.2 | I30: 0.3 | J30: =F30*(G30+0.6)*(H30+0.6)*I30 -> 1.104 | M30: =S30*$T$21 -> 0 | S30: =S26 -> 0
B31: DK3 | F31: 1 | G31: 2 | H31: 0.1 | I31: 0.3 | J31: =F31*(G31+0.6)*(H31+0.6)*I31 -> 0.546 | M31: =S31*$T$21 -> 50740 | S31: =S27 -> 43000
A32: 3 | B32: Đắp đất nền Backfilling for floor | E32: m3 | K32: =9*4*0.5*1.3 -> 23.4 | M32: =S32*$T$21 -> 50740 | O32: =+L32+M32+N32 -> 50740 | P32: =O32*$K32 -> 1187316 | S32: 43000
A33: =IF(ISBLANK(E33),"",COUNTA($E$21:E33)) -> 4 | B33: Đắp đất móng đầm chặt Compacting the foundation | E33: m3 | K33: =K23-K52-K57 -> 23.887 | L33: =R33*$T$21 -> 0 | M33: =S33*$T$21 -> 50740 | O33: =+L33+M33+N33 -> 50740 | P33: =O33*$K33 -> 1212026.4 | S33: 43000
A34: =IF(ISBLANK(E34),"",COUNTA($E$21:E34)) -> 5 | B34: Vận chuyển đất ra ngoài phạm vi công trình Transporting land outside the scope of the project | E34: m3 | K34: =K23-K33 -> 3.329 | L34: =R34*$T$21 -> 0 | M34: =S34*$T$21 -> #REF! | O34: =+L34+M34+N34 -> #REF! | P34: =O34*$K34 -> #REF! | S34: ='01 Nhà Xưởng 01+02'!#REF! -> #REF!
A35: =IF(ISBLANK(E35),"",COUNTA($E$21:E35)) -> 6 | B35: Đầm chặt và xử lý đất đáy đà kiềng và nền K≥0.92 Compaction and treatment of soil at the bottom of Da Kieng and the foundation K≥0.92 | E35: m2 | K35: =SUM(J36:J43) -> 65.14 | L35: =R35*$T$21 -> 0 | M35: =S35*$T$21 -> 21240 | O35: =+L35+M35+N35 -> 21240 | P35: =O35*$K35 -> 1383573.6 | S35: 18000
B36: M1 | F36: 3 | G36: 1.2 | H36: 1.2 | J36: =F36*(G36+0.2)*(H36+0.2) -> 5.88 | L36: =R36*$T$21 -> 0
B37: M2 | F37: 2 | G37: 1.2 | H37: 1.2 | J37: =F37*(G37+0.2)*(H37+0.2) -> 3.92 | L37: =R37*$T$21 -> 0
B38: M3 | F38: 1 | G38: 1.2 | H38: 1.2 | J38: =F38*(G38+0.2)*(H38+0.2) -> 1.96 | L38: =R38*$T$21 -> 0
B39: DK1 | F39: 2 | G39: 9 | H39: 0.2 | J39: =F39*(G39+0.2)*(H39+0.2) -> 7.36 | L39: =R39*$T$21 -> 0
F40: 3 | G40: 4 | H40: 0.2 | J40: =F40*(G40+0.2)*(H40+0.2) -> 5.04 | L40: =R40*$T$21 -> 0
B41: DK2 | F41: 1 | G41: 4 | H41: 0.2 | J41: =F41*(G41+0.2)*(H41+0.2) -> 1.68 | L41: =R41*$T$21 -> 0
B42: DK3 | F42: 1 | G42: 2 | H42: 0.1 | J42: =F42*(G42+0.2)*(H42+0.2) -> 0.66 | L42: =R42*$T$21 -> 0
F43: 1 | G43: 9 | H43: 4 | J43: =F43*(G43+0.2)*(H43+0.2) -> 38.64 | L43: =R43*$T$21 -> 0
A44: =IF(ISBLANK(E44),"",COUNTA($E$21:E44)) -> 7 | B44: Lớp PVC, dày 0.03mm PVC layer, 0.03mm thick | E44: m2 | K44: =9*4 -> 36 | L44: =R44*$T$21 -> #REF! | M44: =S44*$T$21 -> #REF! | O44: =+L44+M44+N44 -> #REF! | P44: =O44*$K44 -> #REF! | R44: ='01 Nhà Xưởng 01+02'!#REF! -> #REF! | S44: ='01 Nhà Xưởng 01+02'!#REF! -> #REF!
A45: 8 | B45: Lớp đá 0x4 Stone layer 0x4 | C45: Dày 200 đầm chặt K=0,92 Thickness 200 compacted K=0.95 | D45: Phú Giáo, Tân Uyên, địa phương Phu Giao, Tan Uyen, Local | E45: m3 | K45: =9*4*0.1*1.42 -> 5.112 | L45: =R45*$T$21 -> #REF! | M45: =S45*$T$21 -> #REF! | O45: =+L45+M45+N45 -> #REF! | P45: =O45*$K45 -> #REF! | R45: ='01 Nhà Xưởng 01+02'!#REF! -> #REF! | S45: ='01 Nhà Xưởng 01+02'!#REF! -> #REF!
A47: C | B47: CÔNG TÁC BÊ TÔNG CONCRETE WORK | D47: Hồng Tín, Hồng Hà, Đại Lộc Phát, HDH Hong Tin, Hong Ha, Dai Loc Phat, HDH | P47: =SUBTOTAL(9,P48:P81) -> #REF!
A48: =IF(ISBLANK(E48),"",COUNTA($E$21:E48)) -> 9 | B48: Bê tông lót móng đá 1x2 M150 Concrete lined with stone 1x2 M150 | E48: m3 | K48: =SUM(J49:J51) -> 0.588 | L48: =R48*$T$21 -> #REF! | M48: =S48*$T$21 -> #REF! | O48: =+L48+M48+N48 -> #REF! | P48: =O48*$K48 -> #REF! | R48: ='01 Nhà Xưởng 01+02'!#REF! -> #REF! | S48: ='01 Nhà Xưởng 01+02'!#REF! -> #REF!
B49: M1 | F49: 3 | G49: 1.2 | H49: 1.2 | I49: 0.05 | J49: =F49*(G49+0.2)*(H49+0.2)*I49 -> 0.294
B50: M2 | F50: 2 | G50: 1.2 | H50: 1.2 | I50: 0.05 | J50: =F50*(G50+0.2)*(H50+0.2)*I50 -> 0.196
B51: M3 | F51: 1 | G51: 1.2 | H51: 1.2 | I51: 0.05 | J51: =F51*(G51+0.2)*(H51+0.2)*I51 -> 0.098
A52: =IF(ISBLANK(E52),"",COUNTA($E$21:E52)) -> 10 | B52: Bê tông lót đá đà kiềng 1x2 M150 Concrete lined with stone 1x2 M150 | E52: m3 | K52: =SUM(J53:J56) -> 0.737 | L52: =R52*$T$21 -> #REF! | M52: =S52*$T$21 -> #REF! | O52: =+L52+M52+N52 -> #REF! | P52: =O52*$K52 -> #REF! | R52: =R48 -> #REF! | S52: =S48 -> #REF!
B53: DK1 | F53: 2 | G53: 9 | H53: 0.2 | I53: 0.05 | J53: =F53*(G53+0.2)*(H53+0.2)*I53 -> 0.368
F54: 3 | G54: 4 | H54: 0.2 | I54: 0.05 | J54: =F54*(G54+0.2)*(H54+0.2)*I54 -> 0.252
B55: DK2 | F55: 1 | G55: 4 | H55: 0.2 | I55: 0.05 | J55: =F55*(G55+0.2)*(H55+0.2)*I55 -> 0.084
B56: DK3 | F56: 1 | G56: 2 | H56: 0.1 | I56: 0.05 | J56: =F56*(G56+0.2)*(H56+0.2)*I56 -> 0.033
A57: =IF(ISBLANK(E57),"",COUNTA($E$21:E57)) -> 11 | B57: Bê tông móng đá 1x2 M250 Stone foundation concrete 1x2 M250 | E57: m3 | K57: =SUM(J58:J60) -> 2.592 | L57: =R57*$T$21 -> 1392400 | M57: =S57*$T$21 -> 212400 | O57: =+L57+M57+N57 -> 1604800 | P57: =O57*$K57 -> 4159641.6 | R57: 1180000 | S57: 180000
B58: M1 | F58: 3 | G58: 1.2 | H58: 1.2 | I58: 0.3 | J58: =F58*G58*H58*I58 -> 1.296
B59: M2 | F59: 2 | G59: 1.2 | H59: 1.2 | I59: 0.3 | J59: =F59*G59*H59*I59 -> 0.864
B60: M3 | F60: 1 | G60: 1.2 | H60: 1.2 | I60: 0.3 | J60: =F60*G60*H60*I60 -> 0.432
A61: =IF(ISBLANK(E61),"",COUNTA($E$21:E61)) -> 12 | B61: Bê tông cổ móng đá 1x2 M250 Stone foundation neck concrete 1x2 M250 | E61: m3 | K61: =SUM(J62) -> 0.24 | L61: =R61*$T$21 -> 1392400 | M61: =S61*$T$21 -> 212400 | O61: =+L61+M61+N61 -> 1604800 | P61: =O61*$K61 -> 385152 | R61: =R57 -> 1180000 | S61: =S57 -> 180000
B62: C1 | F62: 6 | G62: 0.2 | H62: 0.2 | I62: 1 | J62: =F62*G62*H62*I62 -> 0.24
A63: =IF(ISBLANK(E63),"",COUNTA($E$21:E63)) -> 13 | B63: Bê tông đà kiềng đá 1x2 M250 1x2 M300 Stone Concrete | E63: m3 | K63: =SUM(J64:J67) -> 2.7 | L63: =R63*$T$21 -> 1392400 | M63: =S63*$T$21 -> 212400 | O63: =+L63+M63+N63 -> 1604800 | P63: =O63*$K63 -> 4332960 | R63: =R61 -> 1180000 | S63: =S61 -> 180000
B64: DK1 | F64: 2 | G64: 9 | H64: 0.2 | I64: 0.4 | J64: =F64*G64*H64*I64 -> 1.44
F65: 3 | G65: 4 | H65: 0.2 | I65: 0.4 | J65: =F65*G65*H65*I65 -> 0.96
B66: DK2 | F66: 1 | G66: 4 | H66: 0.2 | I66: 0.3 | J66: =F66*G66*H66*I66 -> 0.24
B67: DK3 | F67: 1 | G67: 2 | H67: 0.1 | I67: 0.3 | J67: =F67*G67*H67*I67 -> 0.06
A68: =IF(ISBLANK(E68),"",COUNTA($E$21:E68)) -> 14 | B68: Bê tông nền đá 1x2 M250 Stone foundation concrete 1x2 M250 | E68: m3 | K68: =J69 -> 3.6 | L68: =R68*$T$21 -> 1392400 | M68: =S68*$T$21 -> 212400 | O68: =+L68+M68+N68 -> 1604800 | P68: =O68*$K68 -> 5777280 | R68: =R63 -> 1180000 | S68: =S63 -> 180000
F69: 1 | G69: 9 | H69: 4 | I69: 0.1 | J69: =F69*G69*H69*I69 -> 3.6
A70: =IF(ISBLANK(E70),"",COUNTA($E$21:E70)) -> 15 | B70: Bê tông cột đá 1x2 M250 1x2 M250 Stone Pillar Concrete | E70: m3 | K70: =SUM(J71) -> 0.96 | L70: =R70*$T$21 -> 1392400 | M70: =S70*$T$21 -> #REF! | O70: =+L70+M70+N70 -> #REF! | P70: =O70*$K70 -> #REF! | R70: =R68 -> 1180000 | S70: ='01 Nhà Xưởng 01+02'!#REF! -> #REF!
B71: C1 | F71: 6 | G71: 0.2 | H71: 0.2 | I71: 4 | J71: =F71*G71*H71*I71 -> 0.96
A72: =IF(ISBLANK(E72),"",COUNTA($E$21:E72)) -> 16 | B72: Bê tông dầm giằng đá 1x2 M250 Concrete stone bracing beam 1x2 M250 | C72: Phụ gia đông kết R7 R7 Coagulation Additive | E72: m3 | K72: =SUM(J73:J76) -> 4.784 | L72: =R72*$T$21 -> 1398518.5 | M72: =S72*$T$21 -> #REF! | O72: =+L72+M72+N72 -> #REF! | P72: =O72*$K72 -> #REF! | R72: =1280000/1.08 -> 1185185.2 | S72: =S70 -> #REF!
B73: DM1 | F73: 2 | G73: 10.8 | H73: 0.2 | I73: 0.4 | J73: =F73*G73*H73*I73 -> 1.728
F74: 3 | G74: 4 | H74: 0.2 | I74: 0.4 | J74: =F74*G74*H74*I74 -> 0.96
B75: DM2 | F75: 1 | G75: 4 | H75: 0.2 | I75: 0.4 | J75: =F75*G75*H75*I75 -> 0.32
B76: Dầm Biên | F76: 1 | G76: =(10.8+4)*2 -> 29.6 | H76: 0.2 | I76: 0.3 | J76: =F76*G76*H76*I76 -> 1.776
A77: =IF(ISBLANK(E77),"",COUNTA($E$21:E77)) -> 17 | B77: Bê tông sàn đá 1x2 M250 Concrete stone floor 1x2 M250 | C77: Phụ gia đông kết R7 R7 Coagulation Additive | E77: m3 | K77: =SUM(J78) -> 4.32 | L77: =R77*$T$21 -> 1398518.5 | M77: =S77*$T$21 -> #REF! | O77: =+L77+M77+N77 -> #REF! | P77: =O77*$K77 -> #REF! | R77: =R72 -> 1185185.2 | S77: =S72 -> #REF!
B78: Sàn mái | F78: 1 | G78: 10.8 | H78: 4 | I78: 0.1 | J78: =F78*G78*H78*I78 -> 4.32
A79: =IF(ISBLANK(E79),"",COUNTA($E$21:E79)) -> 18 | B79: Bê tông lanh tô đá 1x2 M250 1x2 Stone Bowl Linen Concrete M250 | E79: m3 | K79: 1 | L79: =R79*$T$21 -> 1392400 | M79: =S79*$T$21 -> #REF! | O79: =+L79+M79+N79 -> #REF! | P79: =O79*$K79 -> #REF! | R79: =R70 -> 1180000 | S79: =S77 -> #REF!
A80: =IF(ISBLANK(E80),"",COUNTA($E$21:E80)) -> 19 | B80: Bê tông bổ trụ đá 1x2 M250 Concrete reinforcement stone pillars 1x2 M250 | E80: m3 | K80: 1 | L80: =R80*$T$21 -> 1392400 | M80: =S80*$T$21 -> #REF! | O80: =+L80+M80+N80 -> #REF! | P80: =O80*$K80 -> #REF! | R80: =R79 -> 1180000 | S80: =S79 -> #REF!
A82: D | B82: CÔNG TÁC VÁN KHUÔN FORMWORK | P82: =SUBTOTAL(9,P83:P115) -> #REF!
A83: =IF(ISBLANK(E83),"",COUNTA($E$21:E83)) -> 20 | B83: Ván khuôn lót móng Foundation Liner Formwork | E83: m2 | K83: =SUM(J84:J86) -> 0.588 | L83: =R83*$T$21 -> #REF! | M83: =S83*$T$21 -> #REF! | O83: =+L83+M83+N83 -> #REF! | P83: =O83*$K83 -> #REF! | R83: ='01 Nhà Xưởng 01+02'!#REF! -> #REF! | S83: ='01 Nhà Xưởng 01+02'!#REF! -> #REF!
B84: M1 | F84: 3 | G84: 1.2 | H84: 1.2 | I84: 0.05 | J84: =F84*(G84+0.2)*(H84+0.2)*I84 -> 0.294
B85: M2 | F85: 2 | G85: 1.2 | H85: 1.2 | I85: 0.05 | J85: =F85*(G85+0.2)*(H85+0.2)*I85 -> 0.196
B86: M3 | F86: 1 | G86: 1.2 | H86: 1.2 | I86: 0.05 | J86: =F86*(G86+0.2)*(H86+0.2)*I86 -> 0.098
A87: =IF(ISBLANK(E87),"",COUNTA($E$21:E87)) -> 21 | B87: Ván khuôn lót đà kiềng Formwork lined with shackles | E87: m2 | K87: =SUM(J88:J91) -> 0.737 | L87: =R87*$T$21 -> #REF! | M87: =S87*$T$21 -> #REF! | O87: =+L87+M87+N87 -> #REF! | P87: =O87*$K87 -> #REF! | R87: =R83 -> #REF! | S87: =S83 -> #REF!
B88: DK1 | F88: 2 | G88: 9 | H88: 0.2 | I88: 0.05 | J88: =F88*(G88+0.2)*(H88+0.2)*I88 -> 0.368
F89: 3 | G89: 4 | H89: 0.2 | I89: 0.05 | J89: =F89*(G89+0.2)*(H89+0.2)*I89 -> 0.252
B90: DK2 | F90: 1 | G90: 4 | H90: 0.2 | I90: 0.05 | J90: =F90*(G90+0.2)*(H90+0.2)*I90 -> 0.084
B91: DK3 | F91: 1 | G91: 2 | H91: 0.1 | I91: 0.05 | J91: =F91*(G91+0.2)*(H91+0.2)*I91 -> 0.033
A92: =IF(ISBLANK(E92),"",COUNTA($E$21:E92)) -> 22 | B92: Ván khuôn nền Substrate Formwork | E92: m2 | K92: =J93 -> 2.6 | L92: =R92*$T$21 -> #REF! | M92: =S92*$T$21 -> #REF! | O92: =+L92+M92+N92 -> #REF! | P92: =O92*$K92 -> #REF! | R92: ='01 Nhà Xưởng 01+02'!#REF! -> #REF! | S92: ='01 Nhà Xưởng 01+02'!#REF! -> #REF!
F93: 1 | G93: 9 | H93: 4 | I93: 0.1 | J93: =F93*(G93+H93)*2*I93 -> 2.6
A94: =IF(ISBLANK(E94),"",COUNTA($E$21:E94)) -> 23 | B94: Ván khuôn móng Foundation Formwork | E94: m2 | K94: =SUM(J95:J97) -> 8.64 | L94: =R94*$T$21 -> #REF! | M94: =S94*$T$21 -> #REF! | O94: =+L94+M94+N94 -> #REF! | P94: =O94*$K94 -> #REF! | R94: =R92 -> #REF! | S94: =S92 -> #REF!
B95: M1 | F95: 3 | G95: 1.2 | H95: 1.2 | I95: 0.3 | J95: =F95*(G95+H95)*2*I95 -> 4.32
B96: M2 | F96: 2 | G96: 1.2 | H96: 1.2 | I96: 0.3 | J96: =F96*(G96+H96)*2*I96 -> 2.88
B97: M3 | F97: 1 | G97: 1.2 | H97: 1.2 | I97: 0.3 | J97: =F97*(G97+H97)*2*I97 -> 1.44
A98: =IF(ISBLANK(E98),"",COUNTA($E$21:E98)) -> 24 | B98: Ván khuôn cổ móng Foundation Neck Formwork | E98: m2 | K98: =SUM(J99) -> 4.8 | L98: =R98*$T$21 -> #REF! | M98: =S98*$T$21 -> #REF! | O98: =+L98+M98+N98 -> #REF! | P98: =O98*$K98 -> #REF! | R98: =R94 -> #REF! | S98: =S94 -> #REF!
B99: C1 | F99: 6 | G99: 0.2 | H99: 0.2 | I99: 1 | J99: =F99*(G99+H99)*2*I99 -> 4.8
A100: =IF(ISBLANK(E100),"",COUNTA($E$21:E100)) -> 25 | B100: Ván khuôn đà kiềng Formwork Beams | E100: m2 | K100: =SUM(J101:J104) -> 28.58 | L100: =R100*$T$21 -> #REF! | M100: =S100*$T$21 -> #REF! | O100: =+L100+M100+N100 -> #REF! | P100: =O100*$K100 -> #REF! | R100: =R98 -> #REF! | S100: =S98 -> #REF!
B101: DK1 | F101: 2 | G101: 9 | H101: 0.2 | I101: 0.4 | J101: =F101*(G101+H101)*2*I101 -> 14.72
F102: 3 | G102: 4 | H102: 0.2 | I102: 0.4 | J102: =F102*(G102+H102)*2*I102 -> 10.08
B103: DK2 | F103: 1 | G103: 4 | H103: 0.2 | I103: 0.3 | J103: =F103*(G103+H103)*2*I103 -> 2.52
B104: DK3 | F104: 1 | G104: 2 | H104: 0.1 | I104: 0.3 | J104: =F104*(G104+H104)*2*I104 -> 1.26
...

Sheet 03 NHÀ BẢO VỆ 01 &02
A1: BẢNG DỰ TOÁN BÁO GIÁ CÔNG TRÌNH / ESTIMATE TABLE
A3: ="HẠNG MỤC / ITEM : "&B8 -> HẠNG MỤC / ITEM : HẠNG MỤC NHÀ BẢO VỆ 01 &02
A6: STT NO. | B6: TÊN CÔNG VIỆC VÀ DIỄN GIẢI DESCRIPTION | C6: ĐẶC TÍNH KỸ THUẬT STANDARD | D6: NHÃN HIỆU & XUẤT XỨ BRAND NAME & ORIGIN | E6: Đvt Unit | F6: SL | G6: DÀI | H6: RỘNG | I6: CAO | J6: KL | K6: KL TỔNG Q'TY | L6: ĐƠN GIÁ / RATE | O6: TỔNG CỘNG (VNĐ) TOTAL COST(VND) | Q6: REMARK GHI CHÚ
L7: VẬT TƯ RATE MATERIALS | M7: NHÂN CÔNG RATE LABOUR | N7: MMTB RATE EQUIPMENT | O7: ĐƠN GIÁ TỔNG TOTAL PRICE | P7: THÀNH TIỀN AMOUNT TOTAL | R7: VẬT TƯ RATE MATERIALS | S7: NHÂN CÔNG RATE LABOUR
B8: HẠNG MỤC NHÀ BẢO VỆ 01 &02 | E8: m2 | K8: 33.6 | P8: =O8*K8 -> 0
A9: A | B9: CÔNG TÁC ĐẤT EARTHWORK
A10: B | B10: CÔNG TÁC BÊ TÔNG CONCRETE WORK
A11: C | B11: CÔNG TÁC VÁN KHUÔN FORMWORK
A12: D | B12: CÔNG TÁC CỐT THÉP REBAR WORK
A13: E | B13: CÔNG TÁC XÂY BRICK WALL
A14: F | B14: CÔNG TÁC TÔ TRÁT PLASTERING WORK
A15: G | B15: CÔNG TÁC SƠN PAINTING WORK
A16: H | B16: CÔNG TÁC CHỐNG THẤM WATERPROOFING WORK
A17: I | B17: CÔNG TÁC TRẦN VÁCH CEILING & PARTITION WORKS
A18: J | B18: CÔNG TÁC CỬA DOOR WORK
A19: L
A21: =IF(ISBLANK(E21),"",MAX(#REF!)+1) | O21: =+L21+M21 -> 0 | P21: =O21*$K21 -> 0
A22: =IF(ISBLANK(E22),"",MAX($A$20:A21)+1) | O22: =+L22+M22+N22 -> 0 | P22: =O22*$K22 -> 0
A23: =IF(ISBLANK(E23),"",MAX($A$20:A22)+1) | O23: =+L23+M23+N23 -> 0 | P23: =O23*$K23 -> 0
A24: =IF(ISBLANK(E24),"",MAX($A$20:A23)+1) | O24: =+L24+M24+N24 -> 0 | P24: =O24*$K24 -> 0

Sheet 04 NHÀ XE
A1: BẢNG DỰ TOÁN BÁO GIÁ CÔNG TRÌNH / ESTIMATE TABLE
A2: ='03 NHÀ BẢO VỆ 01 &02'!A2 -> 0
A3: ="HẠNG MỤC / ITEM : "&B8 -> HẠNG MỤC / ITEM : HẠNG MỤC NHÀ XE 1 TẦNG
A4: ='03 NHÀ BẢO VỆ 01 &02'!A4 -> 0
A6: STT NO. | B6: TÊN CÔNG VIỆC VÀ DIỄN GIẢI DESCRIPTION | C6: ĐẶC TÍNH KỸ THUẬT STANDARD | D6: NHÃN HIỆU & XUẤT XỨ BRAND NAME & ORIGIN | E6: Đvt Unit | F6: SL | G6: DÀI | H6: RỘNG | I6: CAO | J6: KL | K6: KL TỔNG Q'TY | L6: ĐƠN GIÁ / RATE | O6: TỔNG CỘNG (VNĐ) TOTAL COST(VND) | Q6: REMARK GHI CHÚ
L7: VẬT TƯ RATE MATERIALS | M7: NHÂN CÔNG RATE LABOUR | N7: MMTB RATE EQUIPMENT | O7: ĐƠN GIÁ TỔNG TOTAL PRICE | P7: THÀNH TIỀN AMOUNT TOTAL
A8: =A18 -> *** | B8: =B18 -> HẠNG MỤC NHÀ XE 1 TẦNG | P8: =SUBTOTAL(9,P9:P17) -> 0
A9: A | B9: =B19 -> CÔNG TÁC XỬ LÝ ĐẦU CỌC PILING WORKS | P9: =P19 -> 0
A10: =A44 -> 0 | B10: =B30 -> CÔNG TÁC ĐẤT EARTHWORK | P10: =P30 -> 0
A11: =A92 -> 0 | B11: =B40 -> CÔNG TÁC BÊ TÔNG CONCRETE WORK | P11: =P40 -> 0
A12: D | B12: =B54 -> CÔNG TÁC VÁN KHUÔN FORMWORK | P12: =P54 -> 0
A13: =A334 -> 0 | B13: =B67 -> CÔNG TÁC CỐT THÉP REBAR WORK | P13: =P67 -> 0
A14: =A341 -> 0 | B14: =B75 -> CÔNG TÁC HOÀN THIỆN NỀN SÀN FINISHING THE FLOOR | P14: =P75 -> 0
A15: =A366 -> 0 | B15: =B80 -> CÔNG TÁC KẾT CẤU THÉP STEEL STRUCTURE AND WORK | P15: =P81 -> 0
A18: *** | B18: HẠNG MỤC NHÀ XE 1 TẦNG
A19: A | B19: CÔNG TÁC XỬ LÝ ĐẦU CỌC PILING WORKS | P19: =SUBTOTAL(9,P20:P29) -> 0
A22: 4 | B22: Cung cấp và thi công cọc đại trà, PHC-A D300 Supply and construction of mass piles, PHC-A D300 | C22: Cọc PHC A , D300, L=27m, Pmax =120 tấn PHC A pile, D300, L=27m, Pmax =120 tons | D22: Kiến Hoa, Phan Vũ, BT Thủ Đức, Việt Thái An Kien Hoa, Phan Vu, BT Thu Duc, VTA | E22: md | K22: =J23 -> 351 | O22: =+L22+M22+N22 -> 0 | P22: =O22*$K22 -> 0 | Q22: ='05 BỂ PCCC & NHÀ BƠM'!L23 -> Dự kiến ép cọc 27md
B23: Nhà xe | F23: 13 | G23: 27 | J23: =F23*G23 -> 351
A24: 6 | B24: Ép âm cọc Embedded pressing | E24: md | J24: =F24*(G24+0.6)*(H24+0.6)*I24 -> 0
A25: 8 | B25: Máy phát điện thi công cọc Pile construction generator | E25: md | J25: =J23 -> 351 | K25: =J25 -> 351 | O25: =+L25+M25+N25 -> 0 | P25: =O25*$K25 -> 0
A26: 9 | B26: Cắt đầu cọc Cutting pile heads | E26: cái | J26: =14 -> 14 | K26: =J26 -> 14 | O26: =+L26+M26+N26 -> 0 | P26: =O26*$K26 -> 0
A27: 10 | B27: SXLD bản mã đầu cọc Anchor plate for pile heads | C27: Tấm dày 5mm, thép SS400 5mm thick plate, SS400 steel | D27: SS400 | E27: Kg | J27: =0.3*0.3*0.005*7850*14 -> 49.455 | K27: =J27 -> 49.455 | O27: =+L27+M27+N27 -> 0 | P27: =O27*$K27 -> 0
A28: 11 | B28: Cốt thép đầu cọc Anchor steel for pile heads | C28: 6D14, L=1500mm; D6a150 6D14, L=1500mm; D6a150 | E28: Kg | J28: =F28*(G28+0.6)*(H28+0.6)*I28 -> 0 | K28: =K26*11 -> 154 | O28: =+L28+M28+N28 -> 0 | P28: =O28*$K28 -> 0
A29: 12 | B29: Bê tông đầu cọc Pile head concrete | C29: Độ sụt 10±2cm, Mác M300 Slump 10±2cm, Grade M300 | E29: m3 | J29: =F29*(G29+0.6)*(H29+0.6)*I29 -> 0 | K29: =0.2*0.2*1*14 -> 0.56 | O29: =+L29+M29+N29 -> 0 | P29: =O29*$K29 -> 0
A30: II | B30: CÔNG TÁC ĐẤT EARTHWORK | P30: =SUBTOTAL(9,P31:P39) -> 0
A31: =IF(ISBLANK(E31),"",COUNTA($E$18:E31)) -> 8 | B31: Đào đất hố móng, đường ống, khuôn đường Excavation of foundation pits, pipes, road molds | E31: m3 | K31: =J32 -> 41.16 | O31: =+L31+M31+N31 -> 0 | P31: =O31*$K31 -> 0
B32: M1 | F32: 14 | G32: 0.8 | H32: 0.8 | I32: 1.5 | J32: =F32*(G32+0.6)*(H32+0.6)*I32 -> 41.16
A33: =IF(ISBLANK(E33),"",COUNTA($E$18:E33)) -> 9 | B33: Đào đất đà kiềng Digging up the land | E33: m3 | K33: =J34+J35 -> 30.861 | O33: =+L33+M33+N33 -> 0 | P33: =O33*$K33 -> 0
B34: 20x35 | F34: 1 | G34: =24*2 -> 48 | H34: 0.2 | I34: 0.35 | J34: =F34*(G34+0.6)*(H34+0.6)*I34 -> 13.608
B35: 30x45 | F35: 1 | G35: =6*7 -> 42 | H35: 0.3 | I35: 0.45 | J35: =F35*(G35+0.6)*(H35+0.6)*I35 -> 17.253
A36: =IF(ISBLANK(E36),"",COUNTA($E$18:E36)) -> 10 | B36: Đắp đất móng đầm chặt Compacting the foundation | E36: m3 | K36: =(K31+K33)-K41-K43-K46-K48 -> 60.244 | O36: =+L36+M36+N36 -> 0 | P36: =O36*$K36 -> 0
A37: =IF(ISBLANK(E37),"",COUNTA($E$18:E37)) -> 11 | B37: Vận chuyển đất bên trong phạm vi công trình Transporting land inside the scope of the project | E37: m3 | K37: =(K31+K33)-K36 -> 11.777 | O37: =+L37+M37+N37 -> 0 | P37: =O37*$K37 -> 0
A38: =IF(ISBLANK(E38),"",COUNTA($E$18:E38)) -> 12 | B38: Đầm chặt đất nền, K>=92 Compacting the soil, K>=92 | E38: m2 | K38: 212 | O38: =+L38+M38+N38 -> 0 | P38: =O38*$K38 -> 0
A39: =IF(ISBLANK(E39),"",COUNTA($E$18:E39)) -> 13 | B39: Lớp PVC, dày 0.3mm PVC layer, 0.3mm thick | E39: m2 | K39: =K38 -> 212 | O39: =+L39+M39+N39 -> 0 | P39: =O39*$K39 -> 0
A40: III | B40: CÔNG TÁC BÊ TÔNG CONCRETE WORK | P40: =SUBTOTAL(9,P41:P53) -> 0
A41: =IF(ISBLANK(E41),"",COUNTA($E$18:E41)) -> 14 | B41: Bê tông lót móng đá 1x2 M150 Concrete lining stone foundation 1x2 M150 | E41: m3 | K41: =J42 -> 0.7 | O41: =+L41+M41+N41 -> 0 | P41: =O41*$K41 -> 0
B42: M1 | F42: 14 | G42: 0.8 | H42: 0.8 | I42: 0.05 | J42: =F42*(G42+0.2)*(H42+0.2)*I42 -> 0.7
A43: =IF(ISBLANK(E43),"",COUNTA($E$18:E43)) -> 15 | B43: Bê tông lót đá đà kiềng 1x2 M150 Concrete lined with stone 1x2 M150 | E43: m3 | K43: =SUM(J44:J45) -> 2.019 | O43: =+L43+M43+N43 -> 0 | P43: =O43*$K43 -> 0
B44: 20x35 | F44: 1 | G44: =24*2 -> 48 | H44: 0.2 | I44: 0.05 | J44: =F44*(G44+0.2)*(H44+0.2)*I44 -> 0.964
B45: 30x45 | F45: 1 | G45: =6*7 -> 42 | H45: 0.3 | I45: 0.05 | J45: =F45*(G45+0.2)*(H45+0.2)*I45 -> 1.055
A46: =IF(ISBLANK(E46),"",COUNTA($E$18:E46)) -> 16 | B46: Bê tông móng đá 1x2 M250 Stone foundation concrete 1x2 M250 | C46: Độ sụt 10±2cm | D46: Kiến Hoa, Phan Vũ, BT Thủ Đức Kien Hoa, Phan Vu, BT Thu Duc | E46: m3 | K46: =J47 -> 7.168 | O46: =+L46+M46+N46 -> 0 | P46: =O46*$K46 -> 0
B47: M1 | F47: 14 | G47: 0.8 | H47: 0.8 | I47: 0.8 | J47: =F47*G47*H47*I47 -> 7.168
A48: =IF(ISBLANK(E48),"",COUNTA($E$18:E48)) -> 17 | B48: Bê tông cổ móng đá 1x2 M250 Stone foundation neck concrete 1x2 M250 | C48: Độ sụt 10±2cm | D48: Kiến Hoa, Phan Vũ, BT Thủ Đức Kien Hoa, Phan Vu, BT Thu Duc | E48: m3 | K48: =J49 -> 1.89 | O48: =+L48+M48+N48 -> 0 | P48: =O48*$K48 -> 0
F49: 14 | G49: 0.3 | H49: 0.3 | I49: 1.5 | J49: =F49*G49*H49*I49 -> 1.89
A50: =IF(ISBLANK(E50),"",COUNTA($E$18:E50)) -> 18 | B50: Bê tông đà kiềng đá 1x2 M250 1x2 M250 Stone Concrete | C50: Độ sụt 10±2cm | D50: Kiến Hoa, Phan Vũ, BT Thủ Đức Kien Hoa, Phan Vu, BT Thu Duc | E50: m3 | K50: =SUM(J51:J52) -> 9.03 | O50: =+L50+M50+N50 -> 0 | P50: =O50*$K50 -> 0
B51: 20x35 | F51: 1 | G51: =24*2 -> 48 | H51: 0.2 | I51: 0.35 | J51: =F51*G51*H51*I51 -> 3.36
B52: 30x45 | F52: 1 | G52: =6*7 -> 42 | H52: 0.3 | I52: 0.45 | J52: =F52*G52*H52*I52 -> 5.67
A53: =IF(ISBLANK(E53),"",COUNTA($E$18:E53)) -> 19 | B53: Bê tông nền đá 1x2 M250 Stone foundation concrete 1x2 M250 | C53: Độ sụt 10±2cm | D53: Kiến Hoa, Phan Vũ, BT Thủ Đức Kien Hoa, Phan Vu, BT Thu Duc | E53: m3 | K53: =212*0.15*2 -> 63.6 | O53: =+L53+M53+N53 -> 0 | P53: =O53*$K53 -> 0
A54: III | B54: CÔNG TÁC VÁN KHUÔN FORMWORK | P54: =SUBTOTAL(9,P55:P66) -> 0
A55: =IF(ISBLANK(E55),"",COUNTA($E$18:E55)) -> 20 | B55: Ván khuôn bê tông lót móng Formwork for foundation lean concrete | E55: m2 | K55: =J56 -> 2.24 | O55: =+L55+M55+N55 -> 0 | P55: =O55*$K55 -> 0
B56: M1 | F56: 14 | G56: 0.8 | H56: 0.8 | I56: 0.05 | J56: =F56*(G56+H56)*2*I56 -> 2.24
A57: =IF(ISBLANK(E57),"",COUNTA($E$18:E57)) -> 21 | B57: Ván khuôn bê tông lót đà kiềng Formwork for tie beam lean concrete | E57: m2 | K57: =SUM(J58:J59) -> 71.81 | O57: =+L57+M57+N57 -> 0 | P57: =O57*$K57 -> 0
B58: 20x35 | F58: 1 | G58: =24*2 -> 48 | H58: 0.2 | I58: 0.35 | J58: =F58*(G58+H58)*2*I58 -> 33.74
B59: 30x45 | F59: 1 | G59: =6*7 -> 42 | H59: 0.3 | I59: 0.45 | J59: =F59*(G59+H59)*2*I59 -> 38.07
A60: =IF(ISBLANK(E60),"",COUNTA($E$18:E60)) -> 22 | B60: Ván khuôn bê tông móng Formwork for foundation concrete | E60: m2 | K60: =J61 -> 35.84 | O60: =+L60+M60+N60 -> 0 | P60: =O60*$K60 -> 0
B61: M1 | F61: 14 | G61: 0.8 | H61: 0.8 | I61: 0.8 | J61: =F61*(G61+H61)*2*I61 -> 35.84
A62: =IF(ISBLANK(E62),"",COUNTA($E$18:E62)) -> 23 | B62: Ván khuôn bê tông đà kiềng Formwork for tie beam concrete | E62: m2 | K62: =SUM(J63:J64) -> 71.81 | O62: =+L62+M62+N62 -> 0 | P62: =O62*$K62 -> 0
B63: 20x35 | F63: 1 | G63: =24*2 -> 48 | H63: 0.2 | I63: 0.35 | J63: =F63*(G63+H63)*2*I63 -> 33.74
B64: 30x45 | F64: 1 | G64: =6*7 -> 42 | H64: 0.3 | I64: 0.45 | J64: =F64*(G64+H64)*2*I64 -> 38.07
A65: =IF(ISBLANK(E65),"",COUNTA($E$18:E65)) -> 24 | B65: Ván khuôn bê tông cột Formwork for column | E65: m2 | K65: =J66 -> 25.2 | O65: =+L65+M65+N65 -> 0 | P65: =O65*$K65 -> 0
F66: 14 | G66: 0.3 | H66: 0.3 | I66: 1.5 | J66: =F66*(G66+H66)*2*I66 -> 25.2
A67: III | B67: CÔNG TÁC CỐT THÉP REBAR WORK | P67: =SUBTOTAL(9,P68:P73) -> 0
A68: =IF(ISBLANK(E68),"",COUNTA($E$18:E68)) -> 25 | B68: Cốt thép móng Reinforcement for foundations. | C68: Thép D6, D8 : CB240T Thép Đường kính D>=10 : CB400V Steel D6, D8: CB240T Steel Diameter D>=10: CB500V | D68: Hoà Phát, Pomina Hoa Phat,Pomina | E68: kg | K68: =4*(2/0.15+1)*2.1*2*0.618+2*(1.6/0.15+1)*1.7*2*0.618 -> 197.8424 | O68: =+L68+M68+N68 -> 0 | P68: =O68*$K68 -> 0
A69: =IF(ISBLANK(E69),"",COUNTA($E$18:E69)) -> 26 | B69: Cốt thép đà kiềng Reinforcement tie beam | C69: Thép D6, D8 : CB240T Thép Đường kính D>=10 : CB400V Steel D6, D8: CB240T Steel Diameter D>=10: CB500V | D69: Hoà Phát, Pomina Hoa Phat,Pomina | E69: kg | K69: =((31.7*4*1.58+(30.5/0.15+1)*1.1*0.222)+6*(3*4*1.58+(2.4/0.15+1)*1.1*0.222)+(3*6*1.58+(2.4/0.15+1)*1.2*0.222)) -> 421.8794 | O69: =+L69+M69+N69 -> 0 | P69: =O69*$K69 -> 0
A70: =IF(ISBLANK(E70),"",COUNTA($E$18:E70)) -> 27 | B70: Cốt thép cột Column reinforcement | C70: Thép D6, D8 : CB240T Thép Đường kính D>=10 : CB400V Steel D6, D8: CB240T Steel Diameter D>=10: CB500V | D70: Hoà Phát, Pomina Hoa Phat,Pomina | E70: kg | K70: =6*((8*2.1*1.58+(1/0.15+1)*0.9*0.222+(1/0.3+1)*0.4*0.222)) -> 170.7636 | O70: =+L70+M70+N70 -> 0 | P70: =O70*$K70 -> 0
A71: =IF(ISBLANK(E71),"",COUNTA($E$18:E71)) -> 28 | B71: Cốt thép sàn (thép lưới hàn) Reinforcement for slabs(welded mesh) | C71: Thép D6, D8 : CB240T Thép Đường kính D>=10 : CB400V Steel D6, D8: CB240T Steel Diameter D>=10: CB500V | D71: Hoà Phát, Pomina Hoa Phat,Pomina | E71: kg | K71: =((30.5*5.2+2.4*3*2-3.7*2.5)+(30.5*5.2+2.4*3-3.7*2.5))*11*0.395 -> 1391.7035 | O71: =+L71+M71+N71 -> 0 | P71: =O71*$K71 -> 0
A72: =IF(ISBLANK(E72),"",COUNTA($E$18:E72)) -> 29 | B72: Cốt thép Ram dốc (thép lưới hàn) Reinforcement for Ramps(welded mesh) | C72: Thép D6, D8 : CB240T Thép Đường kính D>=10 : CB400V Steel D6, D8: CB240T Steel Diameter D>=10: CB500V | D72: Hoà Phát, Pomina Hoa Phat,Pomina | E72: kg | K72: =(22.4*2.2*2)*11*0.395 -> 428.2432 | O72: =+L72+M72+N72 -> 0 | P72: =O72*$K72 -> 0
A75: VII | B75: CÔNG TÁC HOÀN THIỆN NỀN SÀN FINISHING THE FLOOR | P75: =SUBTOTAL(9,P76:P78) -> 0
A76: =IF(ISBLANK(E76),"",COUNTA($E$18:E76)) -> 30 | B76: Lăn tạo nhám, sơn kẻ vạch chia ô đậu xe Roll to create a textured surface and paint line markings to delineate parking bays | E76: m2 | K76: =29.5*7.2*2 -> 424.8 | O76: =+L76+M76+N76 -> 0 | P76: =O76*$K76 -> 0
A77: =IF(ISBLANK(E77),"",COUNTA($E$18:E77)) -> 31 | B77: Xoa nền, cắt ron chống trượt D20 Trowel the floor surface and cut D20 anti-slip joints | E77: m2 | K77: =6*6+24 -> 60 | O77: =+L77+M77+N77 -> 0 | P77: =O77*$K77 -> 0
A78: =IF(ISBLANK(E78),"",MAX($A$18:A77)+1) | O78: =+L78+M78+N78 -> 0 | P78: =O78*$K78 -> 0
A79: =IF(ISBLANK(E79),"",MAX($A$18:A78)+1) | O79: =+L79+M79+N79 -> 0 | P79: =O79*$K79 -> 0
A80: VII | B80: CÔNG TÁC KẾT CẤU THÉP STEEL STRUCTURE AND WORK | P80: =SUM(P81:P82) -> 0
B81: Cung cấp và lắp đặt hệ khung thép nhà nhà xe 1 tầng, lợp mái tole | E81: m2 | K81: =214 -> 214 | O81: =M81+L81 -> 0 | P81: =O81*K81 -> 0 | Q81: Nhà xe 1 tầng

Sheet  TRẠM BƠM
A1: BẢNG DỰ TOÁN BÁO GIÁ CÔNG TRÌNH / ESTIMATE TABLE
A2: ="DỰ ÁN / PROJECT : "&[6]COVER!K10 -> DỰ ÁN / PROJECT : AN KHANG FOODS JSC
A3: ="HẠNG MỤC / ITEM : "&B8 -> HẠNG MỤC / ITEM : TRẠM BƠM PUMP STATION
A4: ="CHỦ ĐẦU TƯ / : "&[6]COVER!K19 -> CHỦ ĐẦU TƯ / : AN KHANG FOODS JSC
A6: STT NO. | B6: TÊN CÔNG VIỆC VÀ DIỄN GIẢI DESCRIPTION | C6: ĐẶC TÍNH KỸ THUẬT STANDARD | D6: NHÃN HIỆU & XUẤT XỨ BRAND NAME & ORIGIN | E6: Đvt Unit | F6: KL TỔNG Q'TY | G6: ĐƠN GIÁ / RATE | J6: TỔNG CỘNG (VNĐ) TOTAL COST(VND) | L6: REMARK GHI CHÚ
G7: VẬT TƯ RATE MATERIALS | H7: NHÂN CÔNG RATE LABOUR | I7: MMTB RATE EQUIPMENT | J7: ĐƠN GIÁ TỔNG TOTAL PRICE | K7: THÀNH TIỀN AMOUNT TOTAL
A8: =A21 -> *** | B8: =B21 -> TRẠM BƠM PUMP STATION | K8: =SUBTOTAL(9,K9:K20) -> #REF!
A9: =A22 -> II | B9: =B22 -> CÔNG TÁC ĐẤT EARTHWORK | K9: =K22 -> #REF!
A10: =A30 -> III | B10: =B30 -> CÔNG TÁC BÊ TÔNG CONCRETE WORK | K10: =K30 -> #REF!
A11: =A40 -> III | B11: =B40 -> CÔNG TÁC VÁN KHUÔN FORMWORK | K11: =K40 -> #REF!
A12: =A48 -> III | B12: =B48 -> CÔNG TÁC CỐT THÉP REBAR WORK | K12: =K48 -> #REF!
A13: =A55 -> VI | B13: =B55 -> CÔNG TÁC XÂY BRICK WALL | K13: =K55 -> #REF!
A14: =A61 -> VI | B14: =B61 -> CÔNG TÁC TÔ TRÁT PLASTERING WORK | K14: =K61 -> #REF!
A15: =A66 -> VII | B15: =B66 -> CÔNG TÁC SƠN PAINTING WORK | K15: =K66 -> #REF!
A16: =A69 -> VII | B16: =B69 -> CÔNG TÁC HOÀN THIỆN NỀN SÀN FINISHING THE FLOOR | K16: =K69 -> 0
A17: =A73 -> VII | B17: =B73 -> CÔNG TÁC CỬA DOOR WORK | K17: =K73 -> 17558400
A18: =A78 -> VII | B18: =B78 -> CÔNG TÁC KẾT CẤU THÉP STEEL STRUCTURE AND WORK | K18: =K78 -> #REF!
A21: *** | B21: TRẠM BƠM PUMP STATION | M21: Profit | O21: 1.18
A22: II | B22: CÔNG TÁC ĐẤT EARTHWORK | K22: =SUBTOTAL(9,K23:K29) -> #REF! | M22: VẬT TƯ RATE MATERIALS | N22: NHÂN CÔNG RATE LABOUR
A23: =IF(ISBLANK(E23),"",COUNTA($E$21:E23)) -> 1 | B23: Đào đất hố móng, đường ống, khuôn đường Excavation of foundation pits, pipes, road molds | E23: m3 | G23: =M23*$O$21 -> #REF! | H23: =N23*$O$21 -> #REF! | J23: =+G23+H23+I23 -> #REF! | K23: =J23*$F23 -> #REF! | M23: ='02 Nhà Bảo Vệ_& P. Y TẾ'!R23 -> #REF! | N23: ='02 Nhà Bảo Vệ_& P. Y TẾ'!S23 -> #REF!
A24: =IF(ISBLANK(E24),"",COUNTA($E$21:E24)) -> 2 | B24: Đào đất đà kiềng Digging up the land | E24: m3 | G24: =M24*$O$21 -> 0 | H24: =N24*$O$21 -> 50740 | J24: =+G24+H24+I24 -> 50740 | K24: =J24*$F24 -> 0 | M24: ='02 Nhà Bảo Vệ_& P. Y TẾ'!R27 -> 0 | N24: ='02 Nhà Bảo Vệ_& P. Y TẾ'!S27 -> 43000
A25: =IF(ISBLANK(E25),"",COUNTA($E$21:E25)) -> 3 | B25: Đắp đất móng đầm chặt Compacting the foundation | E25: m3 | G25: =M25*$O$21 -> 0 | H25: =N25*$O$21 -> 50740 | J25: =+G25+H25+I25 -> 50740 | K25: =J25*$F25 -> 0 | M25: ='02 Nhà Bảo Vệ_& P. Y TẾ'!R33 -> 0 | N25: ='02 Nhà Bảo Vệ_& P. Y TẾ'!S33 -> 43000
A26: =IF(ISBLANK(E26),"",COUNTA($E$21:E26)) -> 4 | B26: Vận chuyển đất bên trong phạm vi công trình Transporting land inside the scope of the project | E26: m3 | G26: =M26*$O$21 -> 0 | H26: =N26*$O$21 -> #REF! | J26: =+G26+H26+I26 -> #REF! | K26: =J26*$F26 -> #REF! | M26: ='02 Nhà Bảo Vệ_& P. Y TẾ'!R34 -> 0 | N26: ='02 Nhà Bảo Vệ_& P. Y TẾ'!S34 -> #REF!
A27: =IF(ISBLANK(E27),"",COUNTA($E$21:E27)) -> 5 | B27: Đầm chặt đất nền, K>=92 Compacting the soil, K>=92 | E27: m2 | G27: =M27*$O$21 -> 0 | H27: =N27*$O$21 -> 21240 | J27: =+G27+H27+I27 -> 21240 | K27: =J27*$F27 -> 0 | M27: ='02 Nhà Bảo Vệ_& P. Y TẾ'!R35 -> 0 | N27: ='02 Nhà Bảo Vệ_& P. Y TẾ'!S35 -> 18000
A28: =IF(ISBLANK(E28),"",COUNTA($E$21:E28)) -> 6 | B28: Đầm chặt và xử lý đất đáy đà kiềng, bó vỉa Compacting and treating the soil at the bottom of the dam, bundling the pavement | E28: m2 | G28: =M28*$O$21 -> 0 | H28: =N28*$O$21 -> 21240 | J28: =+G28+H28+I28 -> 21240 | K28: =J28*$F28 -> 0 | N28: =N27 -> 18000
A29: =IF(ISBLANK(E29),"",COUNTA($E$21:E29)) -> 7 | B29: Lớp PVC, dày 0.3mm PVC layer, 0.3mm thick | E29: m2 | G29: =M29*$O$21 -> #REF! | H29: =N29*$O$21 -> #REF! | J29: =+G29+H29+I29 -> #REF! | K29: =J29*$F29 -> #REF! | M29: ='02 Nhà Bảo Vệ_& P. Y TẾ'!R44 -> #REF! | N29: ='02 Nhà Bảo Vệ_& P. Y TẾ'!S44 -> #REF!
A30: III | B30: CÔNG TÁC BÊ TÔNG CONCRETE WORK | K30: =SUBTOTAL(9,K31:K39) -> #REF!
A31: =IF(ISBLANK(E31),"",COUNTA($E$21:E31)) -> 8 | B31: Bê tông lót móng đá 1x2 M150 Concrete lining stone foundation 1x2 M150 | E31: m3 | G31: =M31*$O$21 -> #REF! | H31: =N31*$O$21 -> #REF! | J31: =+G31+H31+I31 -> #REF! | K31: =J31*$F31 -> #REF! | M31: ='02 Nhà Bảo Vệ_& P. Y TẾ'!R48 -> #REF! | N31: ='02 Nhà Bảo Vệ_& P. Y TẾ'!S48 -> #REF!
A32: =IF(ISBLANK(E32),"",COUNTA($E$21:E32)) -> 9 | B32: Bê tông lót đá đà kiềng 1x2 M150 Concrete lined with stone 1x2 M150 | E32: m3 | G32: =M32*$O$21 -> #REF! | H32: =N32*$O$21 -> #REF! | J32: =+G32+H32+I32 -> #REF! | K32: =J32*$F32 -> #REF! | M32: ='02 Nhà Bảo Vệ_& P. Y TẾ'!R52 -> #REF! | N32: ='02 Nhà Bảo Vệ_& P. Y TẾ'!S52 -> #REF!
A33: =IF(ISBLANK(E33),"",COUNTA($E$21:E33)) -> 10 | B33: Bê tông móng đá 1x2 M250 Stone foundation concrete 1x2 M250 | C33: Độ sụt 10±2cm | D33: Kiến Hoa, Phan Vũ, BT Thủ Đức Kien Hoa, Phan Vu, BT Thu Duc | E33: m3 | G33: =M33*$O$21 -> 1392400 | H33: =N33*$O$21 -> 212400 | J33: =+G33+H33+I33 -> 1604800 | K33: =J33*$F33 -> 0 | M33: ='02 Nhà Bảo Vệ_& P. Y TẾ'!R57 -> 1180000 | N33: ='02 Nhà Bảo Vệ_& P. Y TẾ'!S57 -> 180000
A34: =IF(ISBLANK(E34),"",COUNTA($E$21:E34)) -> 11 | B34: Bê tông cổ móng đá 1x2 M250 Stone foundation neck concrete 1x2 M250 | C34: Độ sụt 10±2cm | D34: Kiến Hoa, Phan Vũ, BT Thủ Đức Kien Hoa, Phan Vu, BT Thu Duc | E34: m3 | G34: =M34*$O$21 -> 1392400 | H34: =N34*$O$21 -> 212400 | J34: =+G34+H34+I34 -> 1604800 | K34: =J34*$F34 -> 0 | M34: =M33 -> 1180000 | N34: =N33 -> 180000
A35: =IF(ISBLANK(E35),"",COUNTA($E$21:E35)) -> 12 | B35: Bê tông đà kiềng đá 1x2 M250 1x2 M250 Stone Concrete | C35: Độ sụt 10±2cm | D35: Kiến Hoa, Phan Vũ, BT Thủ Đức Kien Hoa, Phan Vu, BT Thu Duc | E35: m3 | G35: =M35*$O$21 -> 1392400 | H35: =N35*$O$21 -> 212400 | J35: =+G35+H35+I35 -> 1604800 | K35: =J35*$F35 -> 0 | M35: =M34 -> 1180000 | N35: =N34 -> 180000
A36: =IF(ISBLANK(E36),"",COUNTA($E$21:E36)) -> 13 | B36: Bê tông nền đá 1x2 M250 Stone foundation concrete 1x2 M250 | C36: Độ sụt 10±2cm | D36: Kiến Hoa, Phan Vũ, BT Thủ Đức Kien Hoa, Phan Vu, BT Thu Duc | E36: m3 | G36: =M36*$O$21 -> 1392400 | H36: =N36*$O$21 -> 212400 | J36: =+G36+H36+I36 -> 1604800 | K36: =J36*$F36 -> 0 | M36: =M35 -> 1180000 | N36: =N35 -> 180000
A37: =IF(ISBLANK(E37),"",COUNTA($E$21:E37)) -> 14 | B37: Bê tông cột đá 1x2 M250 1x2 M250 column Concrete | C37: Độ sụt 10±2cm | D37: Kiến Hoa, Phan Vũ, BT Thủ Đức Kien Hoa, Phan Vu, BT Thu Duc | E37: m3 | G37: =M37*$O$21 -> 1392400 | H37: =N37*$O$21 -> 212400 | J37: =+G37+H37+I37 -> 1604800 | K37: =J37*$F37 -> 0 | M37: =M36 -> 1180000 | N37: =N36 -> 180000
A38: =IF(ISBLANK(E38),"",COUNTA($E$21:E38)) -> 15 | B38: Bê tông sàn đá 1x2 M250 Concrete stone floor 1x2 M250 | C38: Độ sụt 10±2cm | D38: Kiến Hoa, Phan Vũ, BT Thủ Đức Kien Hoa, Phan Vu, BT Thu Duc | E38: m3 | G38: =M38*$O$21 -> 1392400 | H38: =N38*$O$21 -> 212400 | J38: =+G38+H38+I38 -> 1604800 | K38: =J38*$F38 -> 0 | M38: =M37 -> 1180000 | N38: =N37 -> 180000
A39: 21 | B39: Bê tông ram dốc 1x2 M250 Concrete Ramps 1x2 M250 | C39: Độ sụt 10±2cm | D39: Kiến Hoa, Phan Vũ, BT Thủ Đức Kien Hoa, Phan Vu, BT Thu Duc | E39: m3 | G39: =M39*$O$21 -> 1392400 | H39: =N39*$O$21 -> 212400 | J39: =+G39+H39+I39 -> 1604800 | K39: =J39*$F39 -> 0 | M39: =M38 -> 1180000 | N39: =N38 -> 180000
A40: III | B40: CÔNG TÁC VÁN KHUÔN FORMWORK | K40: =SUBTOTAL(9,K41:K47) -> #REF!
A41: =IF(ISBLANK(E41),"",COUNTA($E$21:E41)) -> 17 | B41: Ván khuôn bê tông lót móng Formwork for foundation lean concrete | E41: m2 | G41: =M41*$O$21 -> #REF! | H41: =N41*$O$21 -> #REF! | J41: =+G41+H41+I41 -> #REF! | K41: =J41*$F41 -> #REF! | M41: ='02 Nhà Bảo Vệ_& P. Y TẾ'!R83 -> #REF! | N41: ='02 Nhà Bảo Vệ_& P. Y TẾ'!S83 -> #REF!
A42: =IF(ISBLANK(E42),"",COUNTA($E$21:E42)) -> 18 | B42: Ván khuôn bê tông lót đà kiềng Formwork for tie beam lean concrete | E42: m2 | G42: =M42*$O$21 -> #REF! | H42: =N42*$O$21 -> #REF! | J42: =+G42+H42+I42 -> #REF! | K42: =J42*$F42 -> #REF! | M42: =M41 -> #REF! | N42: =N41 -> #REF!
A43: =IF(ISBLANK(E43),"",COUNTA($E$21:E43)) -> 19 | B43: Ván khuôn bê tông móng Formwork for foundation concrete | E43: m2 | G43: =M43*$O$21 -> #REF! | H43: =N43*$O$21 -> #REF! | J43: =+G43+H43+I43 -> #REF! | K43: =J43*$F43 -> #REF! | M43: =M42 -> #REF! | N43: =N42 -> #REF!
A44: =IF(ISBLANK(E44),"",COUNTA($E$21:E44)) -> 20 | B44: Ván khuôn bê tông đà kiềng Formwork for tie beam concrete | E44: m2 | G44: =M44*$O$21 -> #REF! | H44: =N44*$O$21 -> #REF! | J44: =+G44+H44+I44 -> #REF! | K44: =J44*$F44 -> #REF! | M44: =M43 -> #REF! | N44: =N43 -> #REF!
A45: =IF(ISBLANK(E45),"",COUNTA($E$21:E45)) -> 21 | B45: Ván khuôn bê tông cột Formwork for column | E45: m2 | G45: =M45*$O$21 -> #REF! | H45: =N45*$O$21 -> #REF! | J45: =+G45+H45+I45 -> #REF! | K45: =J45*$F45 -> #REF! | M45: =M44 -> #REF! | N45: =N44 -> #REF!
A46: =IF(ISBLANK(E46),"",COUNTA($E$21:E46)) -> 22 | B46: Ván khuôn bê tông bổ trụ Formwork for stiffener | E46: m2 | G46: =M46*$O$21 -> #REF! | H46: =N46*$O$21 -> #REF! | J46: =+G46+H46+I46 -> #REF! | K46: =J46*$F46 -> #REF! | M46: =M45 -> #REF! | N46: =N45 -> #REF!
A48: III | B48: CÔNG TÁC CỐT THÉP REBAR WORK | K48: =SUBTOTAL(9,K49:K54) -> #REF!
A49: =IF(ISBLANK(E49),"",COUNTA($E$21:E49)) -> 23 | B49: Cốt thép móng Reinforcement for foundations. | C49: Thép D6, D8 : CB240T Thép Đường kính D>=10 : CB500V Steel D6, D8: CB240T Steel Diameter D>=10: CB500V | D49: Hoà Phát, Pomina Hoa Phat,Pomina | E49: kg | G49: =M49*$O$21 -> #REF! | H49: =N49*$O$21 -> #REF! | J49: =+G49+H49+I49 -> #REF! | K49: =J49*$F49 -> #REF! | M49: ='02 Nhà Bảo Vệ_& P. Y TẾ'!R117 -> #REF! | N49: ='02 Nhà Bảo Vệ_& P. Y TẾ'!S117 -> #REF!
A50: =IF(ISBLANK(E50),"",COUNTA($E$21:E50)) -> 24 | B50: Cốt thép đà kiềng Reinforcement tie beam | C50: Thép D6, D8 : CB240T Thép Đường kính D>=10 : CB500V Steel D6, D8: CB240T Steel Diameter D>=10: CB500V | D50: Hoà Phát, Pomina Hoa Phat,Pomina | E50: kg | G50: =M50*$O$21 -> #REF! | H50: =N50*$O$21 -> #REF! | J50: =+G50+H50+I50 -> #REF! | K50: =J50*$F50 -> #REF! | M50: =M49 -> #REF! | N50: =N49 -> #REF!
A51: =IF(ISBLANK(E51),"",COUNTA($E$21:E51)) -> 25 | B51: Cốt thép cột Column reinforcement | C51: Thép D6, D8 : CB240T Thép Đường kính D>=10 : CB500V Steel D6, D8: CB240T Steel Diameter D>=10: CB500V | D51: Hoà Phát, Pomina Hoa Phat,Pomina | E51: kg | G51: =M51*$O$21 -> #REF! | H51: =N51*$O$21 -> #REF! | J51: =+G51+H51+I51 -> #REF! | K51: =J51*$F51 -> #REF! | M51: =M50 -> #REF! | N51: =N50 -> #REF!
A52: =IF(ISBLANK(E52),"",COUNTA($E$21:E52)) -> 26 | B52: Cốt thép sàn (thép lưới hàn) Reinforcement for slabs(welded mesh) | C52: Thép D6, D8 : CB240T Thép Đường kính D>=10 : CB500V Steel D6, D8: CB240T Steel Diameter D>=10: CB500V | D52: Hoà Phát, Pomina Hoa Phat,Pomina | E52: kg | G52: =M52*$O$21 -> #REF! | H52: =N52*$O$21 -> #REF! | J52: =+G52+H52+I52 -> #REF! | K52: =J52*$F52 -> #REF! | M52: =M51 -> #REF! | N52: =N51 -> #REF!
A53: =IF(ISBLANK(E53),"",COUNTA($E$21:E53)) -> 27 | B53: Cốt thép Ram dốc (thép lưới hàn) Reinforcement for Ramps(welded mesh) | C53: Thép D6, D8 : CB240T Thép Đường kính D>=10 : CB500V Steel D6, D8: CB240T Steel Diameter D>=10: CB500V | D53: Hoà Phát, Pomina Hoa Phat,Pomina | E53: kg | G53: =M53*$O$21 -> #REF! | H53: =N53*$O$21 -> #REF! | J53: =+G53+H53+I53 -> #REF! | K53: =J53*$F53 -> #REF! | M53: =M52 -> #REF! | N53: =N52 -> #REF!
A55: VI | B55: CÔNG TÁC XÂY BRICK WALL | K55: =SUBTOTAL(9,K56:K60) -> #REF!
A56: =IF(ISBLANK(E56),"",COUNTA($E$21:E56)) -> 28 | B56: Tường xây gạch dày 200mm 200mm thick brick wall | C56: Vữa mác M75, Gạch xây mác >= M50, Gạch 04 lỗ chèn gạch 02 lỗ (gồm công tác khoan râu liên kết với cột vách bê tông) Mortar grade M75, Brick grade >= M50, 04-hole bricks, 02-hole brick inserts | E56: m2 | F56: =(4.8+3.7)*2*3.4-2*2.6-2*0.6-1.2*1.6 -> 49.48 | G56: =M56*$O$21 -> #REF! | H56: =N56*$O$21 -> #REF! | J56: =+G56+H56+I56 -> #REF! | K56: =J56*$F56 -> #REF! | M56: ='02 Nhà Bảo Vệ_& P. Y TẾ'!R124 -> #REF! | N56: ='02 Nhà Bảo Vệ_& P. Y TẾ'!S124 -> #REF!
A57: =IF(ISBLANK(E57),"",COUNTA($E$21:E57)) -> 29 | B57: GCLD bổ trụ 200x200mm, 4D12, D6@150 Fabrication and assembly 200x200mm stiffener, 4D12, D6@150 | E57: md | F57: =2.4*2 -> 4.8 | G57: =M57*$O$21 -> #REF! | H57: =N57*$O$21 -> #REF! | J57: =+G57+H57+I57 -> #REF! | K57: =J57*$F57 -> #REF! | M57: ='02 Nhà Bảo Vệ_& P. Y TẾ'!R129 -> #REF! | N57: ='02 Nhà Bảo Vệ_& P. Y TẾ'!S129 -> #REF!
A58: =IF(ISBLANK(E58),"",COUNTA($E$21:E58)) -> 30 | B58: GCLD lanh tô 200x200mm, 4D10, D6@150 Fabrication and assembly 200x200mm lintel, 4D10, D6@150 | E58: md | F58: =2.5+1.7 -> 4.2 | G58: =M58*$O$21 -> #REF! | H58: =N58*$O$21 -> #REF! | J58: =+G58+H58+I58 -> #REF! | K58: =J58*$F58 -> #REF! | M58: =M57 -> #REF! | N58: =N57 -> #REF!
A59: =IF(ISBLANK(E59),"",COUNTA($E$21:E59)) -> 31 | B59: Lanh tô, đà giằng, bổ trụ kt 100x200mm Lintel, tie beam, column size 100x200mm | E59: md | F59: 1.7 | G59: =M59*$O$21 -> #REF! | H59: =N59*$O$21 -> #REF! | J59: =+G59+H59+I59 -> #REF! | K59: =J59*$F59 -> #REF! | M59: ='02 Nhà Bảo Vệ_& P. Y TẾ'!R131 -> #REF! | N59: =N58 -> #REF!
A61: VI | B61: CÔNG TÁC TÔ TRÁT PLASTERING WORK | K61: =SUBTOTAL(9,K62:K65) -> #REF!
A62: =IF(ISBLANK(E62),"",COUNTA($E$21:E62)) -> 32 | B62: Trát tường ngoài, vữa M75 dày 1.5cm Exterior wall painting, mortar M75, 1.5cm thk | E62: m2 | F62: =(5+3.7*2)*4-2*2.4-2*0.6-1.2*1.4 -> 41.92 | G62: =M62*$O$21 -> #REF! | H62: =N62*$O$21 -> #REF! | J62: =+G62+H62+I62 -> #REF! | K62: =J62*$F62 -> #REF! | M62: ='02 Nhà Bảo Vệ_& P. Y TẾ'!R134 -> #REF! | N62: ='02 Nhà Bảo Vệ_& P. Y TẾ'!S134 -> #REF!
A63: =IF(ISBLANK(E63),"",COUNTA($E$21:E63)) -> 33 | B63: Trát tường trong vữa M75 dày 1.5cm Plastering inside walls with 1.5cm thick M75 mortar | E63: m2 | F63: =(4.8+3.6)*2*3.6-2*2.4-2*0.6-1.2*1.4 -> 52.8 | G63: =M63*$O$21 -> #REF! | H63: =N63*$O$21 -> #REF! | J63: =+G63+H63+I63 -> #REF! | K63: =J63*$F63 -> #REF! | M63: ='02 Nhà Bảo Vệ_& P. Y TẾ'!R137 -> #REF! | N63: ='02 Nhà Bảo Vệ_& P. Y TẾ'!S137 -> #REF!
A64: =IF(ISBLANK(E64),"",COUNTA($E$21:E64)) -> 34 | B64: Trát má cửa, vữa M75 dày 1.5cm Door reveal plastering, M75 cement mortar, 15mm thick. | E64: md | F64: =(2.4*2+2)+(0.6+2)*2+(1.4+1.2)*2 -> 17.2 | G64: =M64*$O$21 -> #REF! | H64: =N64*$O$21 -> #REF! | J64: =+G64+H64+I64 -> #REF! | K64: =J64*$F64 -> #REF! | M64: ='02 Nhà Bảo Vệ_& P. Y TẾ'!R140 -> #REF! | N64: ='02 Nhà Bảo Vệ_& P. Y TẾ'!S140 -> #REF!
A66: VII | B66: CÔNG TÁC SƠN PAINTING WORK | K66: =SUBTOTAL(9,K67:K68) -> #REF!
A67: =IF(ISBLANK(E67),"",COUNTA($E$21:E67)) -> 35 | B67: Sơn nước cho tường bên trong ( hai lớp hoàn thiện) Painting interior walls with 2 finishing coats | D67: Sơn Nanpao gốc dầu | E67: m2 | F67: =F63 -> 52.8 | G67: =M67*$O$21 -> #REF! | H67: =N67*$O$21 -> #REF! | J67: =+G67+H67+I67 -> #REF! | K67: =J67*$F67 -> #REF! | M67: ='02 Nhà Bảo Vệ_& P. Y TẾ'!R147 -> #REF! | N67: ='02 Nhà Bảo Vệ_& P. Y TẾ'!S147 -> #REF!
A68: =IF(ISBLANK(E68),"",COUNTA($E$21:E68)) -> 36 | B68: Sơn tường ngoài nhà đã bả 1 nước lót + 2 nước phủ Paint exterior walls after putty application (1 primer coat + 2 finishing coats) | D68: Sơn Nanpao gốc dầu | E68: m2 | F68: =F62+F64*0.2 -> 45.36 | G68: =M68*$O$21 -> #REF! | H68: =N68*$O$21 -> #REF! | J68: =+G68+H68+I68 -> #REF! | K68: =J68*$F68 -> #REF! | M68: ='02 Nhà Bảo Vệ_& P. Y TẾ'!R148 -> #REF! | N68: ='02 Nhà Bảo Vệ_& P. Y TẾ'!S148 -> #REF!
A69: VII | B69: CÔNG TÁC HOÀN THIỆN NỀN SÀN FINISHING THE FLOOR | K69: =SUBTOTAL(9,K70:K72) -> 0
A70: =IF(ISBLANK(E70),"",COUNTA($E$21:E70)) -> 37 | B70: Lăn tạo nhám, sơn kẻ vạch chia ô đậu xe Roll to create a textured surface and paint line markings to delineate parking bays | E70: m2 | G70: =M70*$O$21 -> 106200 | H70: =N70*$O$21 -> 35400 | J70: =+G70+H70+I70 -> 141600 | K70: =J70*$F70 -> 0 | M70: 90000 | N70: 30000
A71: =IF(ISBLANK(E71),"",COUNTA($E$21:E71)) -> 38 | B71: Xoa nền, cắt ron chống trượt D20 Trowel the floor surface and cut D20 anti-slip joints | E71: m2 | G71: =M71*$O$21 -> 0 | H71: =N71*$O$21 -> 94400 | J71: =+G71+H71+I71 -> 94400 | K71: =J71*$F71 -> 0 | N71: 80000
A72: =IF(ISBLANK(E72),"",MAX($A$21:A71)+1) | J72: =+G72+H72+I72 -> 0 | K72: =J72*$F72 -> 0
A73: VII | B73: CÔNG TÁC CỬA DOOR WORK | K73: =SUBTOTAL(9,K74:K77) -> 17558400
A74: =IF(ISBLANK(E74),"",COUNTA($E$20:E74)) -> 39 | B74: D1 - 2000x2400 D1 - 2000x2400 | E74: bộ | F74: 1 | G74: =M74*$O$21 -> 9940320 | H74: =N74*$O$21 -> 1104480 | J74: =+G74+H74+I74 -> 11044800 | K74: =J74*$F74 -> 11044800 | M74: =O74*0.9 -> 8424000 | N74: =O74*0.1 -> 936000 | O74: =2*2.4*1950000 -> 9360000
A75: =IF(ISBLANK(E75),"",COUNTA($E$20:E75)) -> 40 | B75: Lam gió L1 - 2000x600, L1 - 2000x600, including insect net | E75: m2 | F75: 1.2 | G75: =M75*$O$21 -> 2230200 | H75: =N75*$O$21 -> 247800 | J75: =+G75+H75+I75 -> 2478000 | K75: =J75*$F75 -> 2973600 | M75: =O75*0.9 -> 1890000 | N75: =O75*0.1 -> 210000 | O75: 2100000
A76: =IF(ISBLANK(E76),"",COUNTA($E$20:E76)) -> 41 | B76: Cửa sổ S1 1200x1400, S1- 1200x1400 ,Windows | E76: bộ | F76: 1 | G76: =M76*$O$21 -> 3186000 | H76: =N76*$O$21 -> 354000 | J76: =+G76+H76+I76 -> 3540000 | K76: =J76*$F76 -> 3540000 | M76: =O76*0.9 -> 2700000 | N76: =O76*0.1 -> 300000 | O76: 3000000
A77: =IF(ISBLANK(E77),"",MAX($A$21:A73)+1) | J77: =+G77+H77+I77 -> 0 | K77: =J77*$F77 -> 0
A78: VII | B78: CÔNG TÁC KẾT CẤU THÉP STEEL STRUCTURE AND WORK | K78: =SUBTOTAL(9,K80:K108) -> #REF!
B79: KẾT CẤU THÉP
B80: Sản xuất khung thép từ thép tấm tổ hợp | E80: kg | G80: =M80*$O$21 -> 19824 | H80: =N80*$O$21 -> 6844 | J80: =+G80+H80+I80 -> 26668 | K80: =J80*$F80 -> 0 | M80: 16800 | N80: 5800
B81: Sản xuất khung thép từ thép hình | E81: kg | G81: =M81*$O$21 -> 23600 | H81: =N81*$O$21 -> 6844 | J81: =+G81+H81+I81 -> 30444 | K81: =J81*$F81 -> 0 | M81: 20000 | N81: 5800
B82: Phun bi, làm sạch cấu kiện khung thép | E82: m2 | G82: =M82*$O$21 -> 41300 | H82: =N82*$O$21 -> 23600 | J82: =+G82+H82+I82 -> 64900 | K82: =J82*$F82 -> 0 | M82: 35000 | N82: 20000
B83: XÀ GỒ MÁI VÀ VÁCH | G83: =M83*$O$21 -> 0 | H83: =N83*$O$21 -> 0 | J83: =+G83+H83+I83 -> 0 | K83: =J83*$F83 -> 0
B84: Cung cấp xà gồ mạ kẽm mái và Canopy | E84: kg | G84: =M84*$O$21 -> 23600 | H84: =N84*$O$21 -> 590 | J84: =+G84+H84+I84 -> 24190 | K84: =J84*$F84 -> 0 | M84: 20000 | N84: 500
B85: CUNG CẤP VÀ LẮP ĐẶT PHỤ KIỆN KHUNG KÈO
B86: Bulong neo M24, L=600 mm | E86: Bộ | G86: =M86*$O$21 -> 171100 | H86: =N86*$O$21 -> 53100 | J86: =+G86+H86+I86 -> 224200 | K86: =J86*$F86 -> 0 | M86: 145000 | N86: 45000
B87: Bulong neo M20, L=450 mm | E87: Bộ | G87: =M87*$O$21 -> 129800 | H87: =N87*$O$21 -> 47200 | J87: =+G87+H87+I87 -> 177000 | K87: =J87*$F87 -> 0 | M87: 110000 | N87: 40000
B88: Bulong liên kết M 20 | E88: Bộ | G88: =M88*$O$21 -> 17700 | H88: =N88*$O$21 -> 0 | J88: =+G88+H88+I88 -> 17700 | K88: =J88*$F88 -> 0 | M88: 15000
B89: Bulong liên kết M 12 | E89: Bộ | G89: =M89*$O$21 -> 4720 | H89: =N89*$O$21 -> 0 | J89: =+G89+H89+I89 -> 4720 | K89: =J89*$F89 -> 0 | M89: 4000
B90: Thanh giằng xà gồ (D12) | E90: m | G90: =M90*$O$21 -> 35400 | H90: =N90*$O$21 -> 7080 | J90: =+G90+H90+I90 -> 42480 | K90: =J90*$F90 -> 0 | M90: 30000 | N90: 6000
B91: Thanh giằng (Cáp D14) | E91: m | G91: =M91*$O$21 -> 29500 | H91: =N91*$O$21 -> 11800 | J91: =+G91+H91+I91 -> 41300 | K91: =J91*$F91 -> 0 | M91: 25000 | N91: 10000
B92: VẬN CHUYỂN & LẮP ĐẶT | G92: =M92*$O$21 -> 0 | H92: =N92*$O$21 -> 0 | J92: =+G92+H92+I92 -> 0 | K92: =J92*$F92 -> 0
B93: Vận chuyển | E93: kg | G93: =M93*$O$21 -> 0 | H93: =N93*$O$21 -> 590 | J93: =+G93+H93+I93 -> 590 | K93: =J93*$F93 -> 0 | N93: 500
B94: Lắp đặt kết cấu thép | E94: kg | G94: =M94*$O$21 -> 0 | H94: =N94*$O$21 -> 4248 | J94: =+G94+H94+I94 -> 4248 | K94: =J94*$F94 -> 0 | N94: 3600
B95: CUNG CẤP VÀ LẮP ĐẶT PHẦN BAO CHE | G95: =M95*$O$21 -> 0 | H95: =N95*$O$21 -> 0 | J95: =+G95+H95+I95 -> 0 | K95: =J95*$F95 -> 0
B96: Tôn mái lớp trên | E96: m2 | G96: =M96*$O$21 -> 171100 | H96: =N96*$O$21 -> 41300 | J96: =+G96+H96+I96 -> 212400 | K96: =J96*$F96 -> 0 | M96: 145000 | N96: 35000
B97: Tôn mặt dựng | E97: m2 | G97: =M97*$O$21 -> 129800 | H97: =N97*$O$21 -> 41300 | J97: =+G97+H97+I97 -> 171100 | K97: =J97*$F97 -> 0 | M97: 110000 | N97: 35000
B98: Tấm trãi sàn | E98: m2 | G98: =M98*$O$21 -> 177000 | H98: =N98*$O$21 -> 23600 | J98: =+G98+H98+I98 -> 200600 | K98: =J98*$F98 -> 0 | M98: 150000 | N98: 20000
B99: Tole bao xung quanh sàn Deck | E99: m | G99: =M99*$O$21 -> 106200 | H99: =N99*$O$21 -> 17700 | J99: =+G99+H99+I99 -> 123900 | K99: =J99*$F99 -> 0 | M99: 90000 | N99: 15000
B100: Đinh chống cắt M16 | E100: Bộ | G100: =M100*$O$21 -> 9440 | H100: =N100*$O$21 -> 5900 | J100: =+G100+H100+I100 -> 15340 | K100: =J100*$F100 -> 0 | M100: 8000 | N100: 5000
B101: CUNG CẤP VÀ LẮP ĐẶT PHẦN HOÀN THIỆN | G101: =M101*$O$21 -> 0 | H101: =N101*$O$21 -> 0 | J101: =+G101+H101+I101 -> 0 | K101: =J101*$F101 -> 0
B102: Máng xối biên nhà xưởng | E102: md | G102: =M102*$O$21 -> 826000 | H102: =N102*$O$21 -> 295000 | J102: =+G102+H102+I102 -> 1121000 | K102: =J102*$F102 -> 0 | M102: 700000 | N102: 250000
B103: Cầu chắn rác inox | E103: Bộ | G103: =M103*$O$21 -> 295000 | H103: =N103*$O$21 -> 0 | J103: =+G103+H103+I103 -> 295000 | K103: =J103*$F103 -> 0 | M103: 250000
B104: Ống xối nhà xưởng đến chân cột thép | E104: md | G104: =M104*$O$21 -> 531000 | H104: =N104*$O$21 -> 141600 | J104: =+G104+H104+I104 -> 672600 | K104: =J104*$F104 -> 0 | M104: 450000 | N104: 120000
B105: Diềm | E105: m | G105: =M105*$O$21 -> 141600 | H105: =N105*$O$21 -> 88500 | J105: =+G105+H105+I105 -> 230100 | K105: =J105*$F105 -> 0 | M105: 120000 | N105: 75000
A106: =IF(ISBLANK(E106),"",COUNTA($E$21:E106)) -> 63 | B106: Cầu chắn rác sê nô D90 Seno garbage barrier bridge D90 | E106: Cái | G106: =M106*$O$21 -> 295000 | H106: =N106*$O$21 -> 0 | J106: =+G106+H106+I106 -> 295000 | K106: =J106*$F106 -> 0 | M106: ='02 Nhà Bảo Vệ_& P. Y TẾ'!R171 -> 250000
A107: =IF(ISBLANK(E107),"",COUNTA($E$21:E107)) -> 64 | B107: Ống thoát nước tràn PVC D34 PVC D34 Overflow Drain Pipe | E107: m | G107: =M107*$O$21 -> 0 | H107: =N107*$O$21 -> 0 | J107: =+G107+H107+I107 -> 0 | K107: =J107*$F107 -> 0
...

Sheet 05 BỂ PCCC & NHÀ BƠM
A1: BẢNG DỰ TOÁN BÁO GIÁ CÔNG TRÌNH / ESTIMATE TABLE
A2: ='04 NHÀ XE'!A2 -> 0
A3: ="HẠNG MỤC / ITEM : "&B8 -> HẠNG MỤC / ITEM : HẠNG MỤC BỂ NƯỚC PCCC, NHÀ BƠM
A4: ='04 NHÀ XE'!A4 -> 0
A6: STT NO. | B6: TÊN CÔNG VIỆC VÀ DIỄN GIẢI DESCRIPTION | C6: ĐẶC TÍNH KỸ THUẬT STANDARD | D6: NHÃN HIỆU & XUẤT XỨ BRAND NAME & ORIGIN | E6: Đvt Unit | F6: KL TỔNG Q'TY | G6: ĐƠN GIÁ / RATE | J6: TỔNG CỘNG (VNĐ) TOTAL COST(VND) | L6: REMARK GHI CHÚ
G7: VẬT TƯ RATE MATERIALS | H7: NHÂN CÔNG RATE LABOUR | I7: MMTB RATE EQUIPMENT | J7: ĐƠN GIÁ TỔNG TOTAL PRICE | K7: THÀNH TIỀN AMOUNT TOTAL
A8: =A18 -> *** | B8: =B18 -> HẠNG MỤC BỂ NƯỚC PCCC, NHÀ BƠM | C8: BỂ NƯỚC 560M3 | K8: =SUBTOTAL(9,K9:K17) -> 0
A9: A | B9: =B19 -> CÔNG TÁC XỬ LÝ ĐẦU CỌC PILING WORKS | K9: =K19 -> 0
A10: B | B10: =B31 -> CÔNG TÁC ĐẤT EARTHWORK | K10: =K31 -> 0
A11: C | B11: =B36 -> CÔNG TÁC BÊ TÔNG CONCRETE WORK | K11: =K36 -> 0
A12: D | B12: =B42 -> CÔNG TÁC VÁN KHUÔN FORMWORK | K12: =K42 -> 0
A13: H | B13: =B54 -> CÔNG TÁC CỐT THÉP REBAR WORK | K13: =K54 -> 0
A14: K | B14: =B70 -> CÔNG TÁC CHỐNG THẤM WATERPROOFING WORK | K14: =K70 -> 0
A15: L | B15: =B78 -> CÔNG TÁC KHÁC OTHER WORKS | K15: =K78 -> 0
A18: *** | B18: HẠNG MỤC BỂ NƯỚC PCCC, NHÀ BƠM | K18: =SUBTOTAL(9,K89:K314) -> 0
A19: A | B19: CÔNG TÁC XỬ LÝ ĐẦU CỌC PILING WORKS | K19: =SUBTOTAL(9,K20:K30) -> 0
A23: 4 | B23: Cung cấp và thi công cọc đại trà, PHC-A D300 Supply and construction of mass piles, PHC-A D300 | C23: Cọc PHC A , D300, L=27m, Pmax =120 tấn PHC A pile, D300, L=27m, Pmax =120 tons, | D23: Kiến Hoa, Phan Vũ, BT Thủ Đức, Việt Thái An Kien Hoa, Phan Vu, BT Thu Duc, VTA | E23: md | F23: =19*27 -> 513 | J23: =+G23+H23+I23 -> 0 | K23: =J23*F23 -> 0 | L23: Dự kiến ép cọc 27md
B24: Bể PCCC
A25: 6 | B25: Ép âm cọc Embedded pressing | E25: md
A26: 8 | B26: Máy phát điện thi công cọc Pile construction generator | E26: md | F26: =20*33 -> 660 | J26: =+G26+H26+I26 -> 0 | K26: =J26*F26 -> 0
A27: 9 | B27: Cắt đầu cọc Cutting pile heads | E27: cái | F27: 19 | J27: =+G27+H27+I27 -> 0 | K27: =J27*F27 -> 0
A28: 10 | B28: SXLD bản mã đầu cọc Anchor plate for pile heads | C28: Tấm dày 5mm, thép SS400 5mm thick plate, SS400 steel | D28: SS400 | E28: Kg | F28: =0.3*0.3*0.005*7850*20 -> 70.65 | J28: =+G28+H28+I28 -> 0 | K28: =J28*F28 -> 0
A29: 11 | B29: Cốt thép đầu cọc Anchor steel for pile heads | C29: 6D14, L=1500mm; D6a150 6D14, L=1500mm; D6a150 | E29: Kg | F29: =F27*11 -> 209 | J29: =+G29+H29+I29 -> 0 | K29: =J29*F29 -> 0
A30: 12 | B30: Bê tông đầu cọc Pile head concrete | C30: Độ sụt 10±2cm, Mác M300 Slump 10±2cm, Grade M300 | E30: m3 | F30: =0.2*0.2*1*20 -> 0.8 | J30: =+G30+H30+I30 -> 0 | K30: =J30*F30 -> 0
A31: B | B31: CÔNG TÁC ĐẤT EARTHWORK | K31: =SUBTOTAL(9,K32:K35) -> 0
A32: =IF(ISBLANK(E32),"",COUNTA($E$18:E32)) -> 8 | B32: Đào đất bể nước Excavation of water tank | C32: Lấy đất đắp nền nhà xưởng, ko chuyển đi | E32: m3 | F32: =(20*(1*1*0.65)+65.6*0.25*0.25+5*30*5)*65% -> 498.615 | J32: =+G32+H32+I32 -> 0 | K32: =J32*$F32 -> 0
A33: =IF(ISBLANK(E33),"",COUNTA($E$18:E33)) -> 9 | B33: Đắp đất BỂ đầm chặt Compacting the water tank | E33: m3 | F33: =(F32-F37-30*5*4.9)*1.2 -> -300.9516 | J33: =+G33+H33+I33 -> 0 | K33: =J33*$F33 -> 0
A34: =IF(ISBLANK(E34),"",COUNTA($E$18:E34)) -> 10 | B34: Vận chuyển đất ra ngoài phạm vi công trình Transporting land outside the scope of the project | C34: Không vận chuyển ra ngoài | E34: m3 | F34: =F32-F33 -> 799.5666 | J34: =+G34+H34+I34 -> 0 | K34: =J34*$F34 -> 0
A35: =IF(ISBLANK(E35),"",COUNTA($E$18:E35)) -> 11 | B35: Đầm chặt đất nền Compacting the ground | E35: m2 | F35: =30.2*5.2 -> 157.04 | J35: =+G35+H35+I35 -> 0 | K35: =J35*$F35 -> 0
A36: B | B36: CÔNG TÁC BÊ TÔNG CONCRETE WORK | K36: =SUBTOTAL(9,K37:K41) -> 0
A37: =IF(ISBLANK(E37),"",COUNTA($E$18:E37)) -> 12 | B37: Bê tông lót đá đáy bể 1x2 M150 Concrete lining stone bottom tank 1x2 M100 | E37: m3 | F37: =20*1*0.05+65.6*0.35*0.05+(29.2*4.5-20*0.8*0.55)*0.1 -> 14.408 | J37: =+G37+H37+I37 -> 0 | K37: =J37*$F37 -> 0
A38: =IF(ISBLANK(E38),"",COUNTA($E$18:E38)) -> 13 | B38: Bê tông đáy bể đá 1x2, M250, phụ gia chống thấm B8 1x2 rock tank bottom concrete, M250, B8 waterproofing additive | E38: m3 | F38: =20*0.8*0.55+(60+3.4*2-20*0.8)*0.25*0.25+6.8*0.2*0.25+30*5*0.25 -> 49.815 | J38: =+G38+H38+I38 -> 0 | K38: =J38*$F38 -> 0
A39: =IF(ISBLANK(E39),"",COUNTA($E$18:E39)) -> 14 | B39: Bê tông thành bể đá 1x2, M250, phụ gia chống thấm B8 Concrete into stone tank 1x2, M250, waterproofing additive B8 | E39: m3 | F39: =(30*2+4.5*2)*4.5*0.25+4.5*2*4.5*0.2 -> 85.725 | J39: =+G39+H39+I39 -> 0 | K39: =J39*$F39 -> 0
A40: =IF(ISBLANK(E40),"",COUNTA($E$18:E40)) -> 15 | B40: Bê tông nắp bể đá 1x2, M300, phụ gia chống thấm 1x2 Stone Tank Cover Concrete, M250, Waterproofing Additive | E40: m3 | F40: =30*5*0.15-0.6*0.6*0.15*6 -> 22.176 | J40: =+G40+H40+I40 -> 0 | K40: =J40*$F40 -> 0
A41: =IF(ISBLANK(E41),"",COUNTA($E$18:E41))
A42: C | B42: CÔNG TÁC VÁN KHUÔN FORMWORK | K42: =SUBTOTAL(9,K43:K53) -> 0
A43: =IF(ISBLANK(E43),"",COUNTA($E$18:E43)) -> 16 | B43: Ván khuôn lót đáy bể Tank bottom lining formwork | E43: m2 | F43: =20*1*4*0.05+(60+3.4*2-20*0.8)*0.45*0.05+6.8*0.4*0.05 -> 5.279 | J43: =+G43+H43+I43 -> 0 | K43: =J43*$F43 -> 0
A44: =IF(ISBLANK(E44),"",COUNTA($E$18:E44)) -> 17 | B44: Ván khuôn đáy bể Tank bottom formwork | E44: m2 | F44: =20*0.8*4*0.55+(60+3.4*2-20*0.8)*0.25+6.8*0.25*2+(30+5)*2*0.5 -> 86.3 | J44: =+G44+H44+I44 -> 0 | K44: =J44*$F44 -> 0
A45: =IF(ISBLANK(E45),"",COUNTA($E$18:E45)) -> 18 | B45: Ván khuôn thành bể Tank Formwork | E45: m2 | F45: =(70*4.5+27.81*3*4.5)*80% -> 552.348 | J45: =+G45+H45+I45 -> 0 | K45: =J45*$F45 -> 0
A46: =IF(ISBLANK(E46),"",COUNTA($E$18:E46)) -> 19 | B46: Ván khuôn đà nắp bể Formwork Beams | E46: m2 | J46: =+G46+H46+I46 -> 0 | K46: =J46*$F46 -> 0
A47: =IF(ISBLANK(E47),"",COUNTA($E$18:E47)) -> 20 | B47: Ván khuôn cột bể Tank column formwork | E47: m2 | J47: =+G47+H47+I47 -> 0 | K47: =J47*$F47 -> 0
A48: =IF(ISBLANK(E48),"",COUNTA($E$18:E48)) -> 21 | B48: Ván khuôn cột Column Formwork | E48: m2 | J48: =+G48+H48+I48 -> 0 | K48: =J48*$F48 -> 0
A49: =IF(ISBLANK(E49),"",COUNTA($E$18:E49)) -> 22 | B49: Ván khuôn bổ trụ Formwork Pillar Supplement | E49: m2 | J49: =+G49+H49+I49 -> 0 | K49: =J49*$F49 -> 0
A50: =IF(ISBLANK(E50),"",COUNTA($E$18:E50)) -> 23 | B50: Ván khuôn dầm, giằng, lanh tô Beam formwork, bracing, linen bowls | E50: m2 | J50: =+G50+H50+I50 -> 0 | K50: =J50*$F50 -> 0
A51: =IF(ISBLANK(E51),"",COUNTA($E$18:E51)) -> 24 | B51: Ván khuôn sàn ~ Sê nô Floor Formwork ~ Seno | E51: m2 | J51: =+G51+H51+I51 -> 0 | K51: =J51*$F51 -> 0
A52: =IF(ISBLANK(E52),"",COUNTA($E$18:E52)) -> 25 | B52: Ván khuôn nắp bể Tank lid formwork | E52: m2 | F52: =70*0.15+43.52*3-0.6*0.6*6 -> 138.9 | J52: =+G52+H52+I52 -> 0 | K52: =J52*$F52 -> 0
A54: D | B54: CÔNG TÁC CỐT THÉP REBAR WORK | C54: Thép D6, D8 : CB240T Thép Đường kính D>=10 : CB400V Steel D6, D8: CB240T Steel Diameter D>=10: CB400V | D54: Hoà Phát, Pomina Hoa Phat, Pomina | K54: =SUBTOTAL(9,K56:K59) -> 0
B55: Cốt thép móng Reinforcement Foundation | E55: kg | F55: =20*(1.8*10*0.89+1.1*8*0.618+20*0.9*2*0.395)+20*4*1.8*1.58+20*0.8*4*0.222 -> 955.296 | J55: 21476 | K55: =J55*$F55 -> 20515937
A56: =IF(ISBLANK(E56),"",COUNTA($E$18:E56)) -> 27 | B56: Cốt thép đà kiềng Reinforcement Beam | E56: kg | F56: =75*6*2+(70/0.15)*1.4*0.395+10*6*1.58+(9.5/0.15)*1.3*0.395 -> 1285.3883 | J56: =+G56+H56+I56 -> 0 | K56: =J56*$F56 -> 0
A57: =IF(ISBLANK(E57),"",COUNTA($E$18:E57)) -> 28 | B57: Cốt thép cột, thành bể Reinforced columns, tank walls | E57: kg | F57: =70/0.15*2*(5+0.45+0.2)*0.89+4.5/0.2*2*72*0.618+4.5*4.5*12*2*0.618 -> 6995.9347 | J57: =+G57+H57+I57 -> 0 | K57: =J57*$F57 -> 0
A58: =IF(ISBLANK(E58),"",COUNTA($E$18:E58)) -> 29 | B58: Cốt thép đáy bể Tank bottom reinforcement | E58: kg | F58: =30*5*12*2*0.89+150*0.65*0.618 -> 3264.255 | J58: =+G58+H58+I58 -> 0 | K58: =J58*$F58 -> 0
A59: =IF(ISBLANK(E59),"",COUNTA($E$18:E59)) -> 30 | B59: Cốt thép nắp bể Reinforced tank cover | E59: kg | F59: =30*5*13*2*0.618 -> 2410.2 | J59: =+G59+H59+I59 -> 0 | K59: =J59*$F59 -> 0
A60: G | B60: CÔNG TÁC SƠN PAINTING WORK | K60: =SUBTOTAL(9,K61:K69) -> 0
A65: =IF(ISBLANK(E65),"",COUNTA($E$18:E65)) -> 31 | B65: Sơn dầm, trần, cột, tường trong nhà 1 nước lót + 2 nước phủ Paint beams, ceilings, columns, and walls in the house with 1 primer + 2 coatings | C65: Sơn lau chùi hiệu quả | D65: Dulux | E65: m2 | J65: =+G65+H65+I65 -> 0 | K65: =J65*$F65 -> 0
A66: =IF(ISBLANK(E66),"",COUNTA($E$18:E66)) -> 32 | B66: Sơn tường ngoài nhà 1 nước lót + 2 nước phủ Painting the walls outside the house with 1 primer + 2 coatings | C66: Sơn ngoại thất cao cấp | D66: Dulux | E66: m2 | J66: =+G66+H66+I66 -> 0 | K66: =J66*$F66 -> 0
A67: =IF(ISBLANK(E67),"",COUNTA($E$18:E67)) -> 33 | B67: Sơn nước cấu kiện bê tông (Cột, dầm, cầu thang) Paint concrete structures (columns, beams, stairs) | C67: Sơn lau chùi hiệu quả | D67: Dulux | E67: m2 | J67: =+G67+H67+I67 -> 0 | K67: =J67*$F67 -> 0
A70: H | B70: CÔNG TÁC CHỐNG THẤM WATERPROOFING WORK | K70: =SUBTOTAL(9,K71) -> 0
A71: =IF(ISBLANK(E71),"",COUNTA($E$18:E71)) -> 34 | B71: Quét chống thấm sika 2 lớp cho thành bể và đáy bể Apply 2 layers of waterproofing with Sika. | C71: sika top seal 107, 2 lớp (định mức 1.5kg/m2/lớp) Sweep top seal 107, 2 layers (rated 1.5kg/m2/layer) | E71: m2 | F71: =(43.52*3+70*4.9+27.81*3*4.5)*80% -> 679.196 | J71: =+G71+H71+I71 -> 0 | K71: =J71*$F71 -> 0
A72: I | B72: CÔNG TÁC HOÀN THIỆN NỀN SÀN FINISHING THE FLOOR | K72: =SUBTOTAL(9,K73:K73) -> 0
A73: =IF(ISBLANK(E73),"",COUNTA($E$18:E73)) -> 35 | B73: Op gạch nền và tường cho bể nước, gạch 300x600 Tilng work | E73: m2 | F73: =5*30+(30+5)*2*4.9+10*4.9*2 -> 591 | J73: =+G73+H73+I73 -> 0 | K73: =J73*$F73 -> 0
A74: J | B74: CÔNG TÁC CỬA DOOR WORK | K74: =SUBTOTAL(9,K75:K77) -> 0
A75: =IF(ISBLANK(E75),"",COUNTA($E$18:E75)) -> 36 | B75: D3 - 2000x2200 Cửa ngăn cháy 02 cánh, EI70 D3 - 2000x2200 02-wing fire doors, EI70 | C75: - Cửa đi sơn tĩnh điện - Khung thép dày1.2mm, độ dày khung 110mm - Cánh thép dày 0.8mm, độ dày cánh 50mm, Lõi vật liệu chống cháy; Ron cao su xung quanh, Bản lệ Inox - Ô kính chống cháy 300x600x25mm *Phụ kiện / Accessories: Khoá tay gạt; Thanh thoát hiểm; Tay co thuỷ lực; Kính chống cháy; Doorsill / - Powder coated doors - Steel frame thickness 1.2mm, frame thickness 110mm - Steel wing thickness 0.8mm, wing thickness 50mm, Flame retardant material core; Rubber Ron Around, Stainless Steel Rule - 300x600x25mm flame retardant glass pane *Accessories: Lever lock; Emergency exit bar; Hydraulic Shrink Arms; Flame retardant glass; Doorsill / | E75: bộ | J75: =+G75+H75+I75 -> 0 | K75: =J75*$F75 -> 0
A76: =IF(ISBLANK(E76),"",COUNTA($E$18:E76)) -> 37 | B76: L1 :2400x1200mm Lam gió nhôm + lưới chắn côn trùng L1:2400x1200mm Aluminum windmill + insect net | C76: Lam nhôn dày 1.4mm sơn tĩnh điện màu xám nhạt Lưới chắn côn trùng inox 1.4mm thick powder coated light grey Stainless Steel Insect Barrier | D76: Nhôm Xingfa Việt Nam Lưới inox Việt nam Xingfa Aluminum Vietnam Stainless Steel Mesh Vietnam | E76: bộ | J76: =+G76+H76+I76 -> 0 | K76: =J76*$F76 -> 0
A77: =IF(ISBLANK(E77),"",MAX($A$18:A74)+1) | J77: =+G77+H77 -> 0 | K77: =J77*$F77 -> 0
A78: K | B78: CÔNG TÁC KHÁC OTHER WORKS | K78: =SUBTOTAL(9,K79:K88) -> 0
A79: =IF(ISBLANK(E79),"",COUNTA($E$18:E79)) -> 38 | B79: Ống thoát nước PVC D60 PVC Drainage Pipe D60 | E79: m | F79: 20 | J79: =+G79+H79+I79 -> 0 | K79: =J79*$F79 -> 0
A80: =IF(ISBLANK(E80),"",COUNTA($E$18:E80)) -> 39 | B80: Cung cấp lắp đặt nắp thăm 600x600 Visiting Cover Installation Supply 600x600 | E80: cái | F80: 6 | J80: =+G80+H80+I80 -> 0 | K80: =J80*$F80 -> 0
A81: =IF(ISBLANK(E81),"",COUNTA($E$18:E81)) -> 40 | B81: Cung cấp lắp đặt thang thăm bể Install the inspection ladder for the water tank. | C81: Thang leo lên bể bằng inox SUS304 D21x1.4a300 | E81: md | F81: 6 | J81: =+G81+H81+I81 -> 0 | K81: =J81*$F81 -> 0
A82: 36 | B82: Cung cấp lắp đặt băng cản nước mạch ngừng Supply and installation of waterstop at construction joints. | E82: md | F82: 70 | J82: =+G82+H82+I82 -> 0 | K82: =J82*$F82 -> 0
A83: 37 | B83: Biện pháp cừ thép chống vách 2 lớp cừ Steel sheet pile shoring method | E83: md | F83: 65 | J83: =+G83+H83+I83 -> 0 | K83: =J83*$F83 -> 0
A84: 38 | B84: Thi công xây tô hoàn thiện nhà bơm | E84: m2 | F84: 32 | J84: =+G84+H84+I84 -> 0 | K84: =J84*F84 -> 0
A85: 39 | B85: Bể tự hoại bằng BTCT 3m3 | E85: cái | F85: 2 | J85: =+G85+H85+I85 -> 0 | K85: =J85*F85 -> 0
A86: 40 | B86: Bể tự hoại bằng BTCT 15m3 | E86: cái | F86: 1 | J86: =+G86+H86+I86 -> 0 | K86: =J86*F86 -> 0
A87: 41 | B87: Bể tự hoại bằng BTCT 8m3 | E87: cái | F87: 1 | J87: =+G87+H87+I87 -> 0 | K87: =J87*F87 -> 0
A88: =IF(ISBLANK(E88),"",MAX($A$18:A87)+1) | J88: =+G88+H88+I88 -> 0 | K88: =J88*$F88 -> 0

Sheet PHÒNG MÁY PHÁT ĐIỆN
A1: BẢNG DỰ TOÁN BÁO GIÁ CÔNG TRÌNH / ESTIMATE TABLE
A2: ="DỰ ÁN / PROJECT : "&[6]COVER!K10 -> DỰ ÁN / PROJECT : AN KHANG FOODS JSC
A3: ="HẠNG MỤC / ITEM : "&B8 -> HẠNG MỤC / ITEM : MÁY PHÁT GENERATOR
A4: ="CHỦ ĐẦU TƯ / : "&[6]COVER!K19 -> CHỦ ĐẦU TƯ / : AN KHANG FOODS JSC
A6: STT NO. | B6: TÊN CÔNG VIỆC VÀ DIỄN GIẢI DESCRIPTION | C6: ĐẶC TÍNH KỸ THUẬT STANDARD | D6: NHÃN HIỆU & XUẤT XỨ BRAND NAME & ORIGIN | E6: Đvt Unit | F6: KL TỔNG Q'TY | G6: ĐƠN GIÁ / RATE | J6: TỔNG CỘNG (VNĐ) TOTAL COST(VND) | L6: REMARK GHI CHÚ
G7: VẬT TƯ RATE MATERIALS | H7: NHÂN CÔNG RATE LABOUR | I7: MMTB RATE EQUIPMENT | J7: ĐƠN GIÁ TỔNG TOTAL PRICE | K7: THÀNH TIỀN AMOUNT TOTAL
A8: =A21 -> *** | B8: =B21 -> MÁY PHÁT GENERATOR | K8: =SUBTOTAL(9,K9:K20) -> #REF!
A9: =A22 -> II | B9: =B22 -> CÔNG TÁC ĐẤT EARTHWORK | K9: =K22 -> #REF!
A10: =A30 -> III | B10: =B30 -> CÔNG TÁC BÊ TÔNG CONCRETE WORK | K10: =K30 -> #REF!
A11: =A40 -> III | B11: =B40 -> CÔNG TÁC VÁN KHUÔN FORMWORK | K11: =K40 -> #REF!
A12: =A48 -> III | B12: =B48 -> CÔNG TÁC CỐT THÉP REBAR WORK | K12: =K48 -> #REF!
A13: =A55 -> VI | B13: =B55 -> CÔNG TÁC XÂY BRICK WALL | K13: =K55 -> #REF!
A14: =A61 -> VI | B14: =B61 -> CÔNG TÁC TÔ TRÁT PLASTERING WORK | K14: =K61 -> #REF!
A15: =A66 -> VII | B15: =B66 -> CÔNG TÁC SƠN PAINTING WORK | K15: =K66 -> #REF!
A16: =A69 -> VII | B16: =B69 -> CÔNG TÁC HOÀN THIỆN NỀN SÀN FINISHING THE FLOOR | K16: =K69 -> 0
A17: =A73 -> VII | B17: =B73 -> CÔNG TÁC CỬA DOOR WORK | K17: =K73 -> 16992000
A18: =A78 -> VII | B18: =B78 -> CÔNG TÁC KẾT CẤU THÉP STEEL STRUCTURE AND WORK | K18: =K78 -> #REF!
A21: *** | B21: MÁY PHÁT GENERATOR | M21: Profit | O21: 1.18
A22: II | B22: CÔNG TÁC ĐẤT EARTHWORK | K22: =SUBTOTAL(9,K23:K29) -> #REF! | M22: VẬT TƯ RATE MATERIALS | N22: NHÂN CÔNG RATE LABOUR
A23: =IF(ISBLANK(E23),"",COUNTA($E$21:E23)) -> 1 | B23: Đào đất hố móng, đường ống, khuôn đường Excavation of foundation pits, pipes, road molds | E23: m3 | G23: =M23*$O$21 -> #REF! | H23: =N23*$O$21 -> #REF! | J23: =+G23+H23+I23 -> #REF! | K23: =J23*$F23 -> #REF! | M23: ='02 Nhà Bảo Vệ_& P. Y TẾ'!R23 -> #REF! | N23: ='02 Nhà Bảo Vệ_& P. Y TẾ'!S23 -> #REF!
A24: =IF(ISBLANK(E24),"",COUNTA($E$21:E24)) -> 2 | B24: Đào đất đà kiềng Digging up the land | E24: m3 | G24: =M24*$O$21 -> 0 | H24: =N24*$O$21 -> 50740 | J24: =+G24+H24+I24 -> 50740 | K24: =J24*$F24 -> 0 | M24: ='02 Nhà Bảo Vệ_& P. Y TẾ'!R27 -> 0 | N24: ='02 Nhà Bảo Vệ_& P. Y TẾ'!S27 -> 43000
A25: =IF(ISBLANK(E25),"",COUNTA($E$21:E25)) -> 3 | B25: Đắp đất móng đầm chặt Compacting the foundation | E25: m3 | G25: =M25*$O$21 -> 0 | H25: =N25*$O$21 -> 50740 | J25: =+G25+H25+I25 -> 50740 | K25: =J25*$F25 -> 0 | M25: ='02 Nhà Bảo Vệ_& P. Y TẾ'!R33 -> 0 | N25: ='02 Nhà Bảo Vệ_& P. Y TẾ'!S33 -> 43000
A26: =IF(ISBLANK(E26),"",COUNTA($E$21:E26)) -> 4 | B26: Vận chuyển đất bên trong phạm vi công trình Transporting land inside the scope of the project | E26: m3 | G26: =M26*$O$21 -> 0 | H26: =N26*$O$21 -> #REF! | J26: =+G26+H26+I26 -> #REF! | K26: =J26*$F26 -> #REF! | M26: ='02 Nhà Bảo Vệ_& P. Y TẾ'!R34 -> 0 | N26: ='02 Nhà Bảo Vệ_& P. Y TẾ'!S34 -> #REF!
A27: =IF(ISBLANK(E27),"",COUNTA($E$21:E27)) -> 5 | B27: Đầm chặt đất nền, K>=92 Compacting the soil, K>=92 | E27: m2 | G27: =M27*$O$21 -> 0 | H27: =N27*$O$21 -> 21240 | J27: =+G27+H27+I27 -> 21240 | K27: =J27*$F27 -> 0 | M27: ='02 Nhà Bảo Vệ_& P. Y TẾ'!R35 -> 0 | N27: ='02 Nhà Bảo Vệ_& P. Y TẾ'!S35 -> 18000
A28: =IF(ISBLANK(E28),"",COUNTA($E$21:E28)) -> 6 | B28: Đầm chặt và xử lý đất đáy đà kiềng, bó vỉa Compacting and treating the soil at the bottom of the dam, bundling the pavement | E28: m2 | G28: =M28*$O$21 -> 0 | H28: =N28*$O$21 -> 21240 | J28: =+G28+H28+I28 -> 21240 | K28: =J28*$F28 -> 0 | N28: =N27 -> 18000
A29: =IF(ISBLANK(E29),"",COUNTA($E$21:E29)) -> 7 | B29: Lớp PVC, dày 0.3mm PVC layer, 0.3mm thick | E29: m2 | G29: =M29*$O$21 -> #REF! | H29: =N29*$O$21 -> #REF! | J29: =+G29+H29+I29 -> #REF! | K29: =J29*$F29 -> #REF! | M29: ='02 Nhà Bảo Vệ_& P. Y TẾ'!R44 -> #REF! | N29: ='02 Nhà Bảo Vệ_& P. Y TẾ'!S44 -> #REF!
A30: III | B30: CÔNG TÁC BÊ TÔNG CONCRETE WORK | K30: =SUBTOTAL(9,K31:K39) -> #REF!
A31: =IF(ISBLANK(E31),"",COUNTA($E$21:E31)) -> 8 | B31: Bê tông lót móng đá 1x2 M150 Concrete lining stone foundation 1x2 M150 | E31: m3 | G31: =M31*$O$21 -> #REF! | H31: =N31*$O$21 -> #REF! | J31: =+G31+H31+I31 -> #REF! | K31: =J31*$F31 -> #REF! | M31: ='02 Nhà Bảo Vệ_& P. Y TẾ'!R48 -> #REF! | N31: ='02 Nhà Bảo Vệ_& P. Y TẾ'!S48 -> #REF!
A32: =IF(ISBLANK(E32),"",COUNTA($E$21:E32)) -> 9 | B32: Bê tông lót đá đà kiềng 1x2 M150 Concrete lined with stone 1x2 M150 | E32: m3 | G32: =M32*$O$21 -> #REF! | H32: =N32*$O$21 -> #REF! | J32: =+G32+H32+I32 -> #REF! | K32: =J32*$F32 -> #REF! | M32: ='02 Nhà Bảo Vệ_& P. Y TẾ'!R52 -> #REF! | N32: ='02 Nhà Bảo Vệ_& P. Y TẾ'!S52 -> #REF!
A33: =IF(ISBLANK(E33),"",COUNTA($E$21:E33)) -> 10 | B33: Bê tông móng đá 1x2 M250 Stone foundation concrete 1x2 M250 | C33: Độ sụt 10±2cm | D33: Kiến Hoa, Phan Vũ, BT Thủ Đức Kien Hoa, Phan Vu, BT Thu Duc | E33: m3 | G33: =M33*$O$21 -> 1392400 | H33: =N33*$O$21 -> 212400 | J33: =+G33+H33+I33 -> 1604800 | K33: =J33*$F33 -> 0 | M33: ='02 Nhà Bảo Vệ_& P. Y TẾ'!R57 -> 1180000 | N33: ='02 Nhà Bảo Vệ_& P. Y TẾ'!S57 -> 180000
A34: =IF(ISBLANK(E34),"",COUNTA($E$21:E34)) -> 11 | B34: Bê tông cổ móng đá 1x2 M250 Stone foundation neck concrete 1x2 M250 | C34: Độ sụt 10±2cm | D34: Kiến Hoa, Phan Vũ, BT Thủ Đức Kien Hoa, Phan Vu, BT Thu Duc | E34: m3 | G34: =M34*$O$21 -> 1392400 | H34: =N34*$O$21 -> 212400 | J34: =+G34+H34+I34 -> 1604800 | K34: =J34*$F34 -> 0 | M34: =M33 -> 1180000 | N34: =N33 -> 180000
A35: =IF(ISBLANK(E35),"",COUNTA($E$21:E35)) -> 12 | B35: Bê tông đà kiềng đá 1x2 M250 1x2 M250 Stone Concrete | C35: Độ sụt 10±2cm | D35: Kiến Hoa, Phan Vũ, BT Thủ Đức Kien Hoa, Phan Vu, BT Thu Duc | E35: m3 | G35: =M35*$O$21 -> 1392400 | H35: =N35*$O$21 -> 212400 | J35: =+G35+H35+I35 -> 1604800 | K35: =J35*$F35 -> 0 | M35: =M34 -> 1180000 | N35: =N34 -> 180000
A36: =IF(ISBLANK(E36),"",COUNTA($E$21:E36)) -> 13 | B36: Bê tông nền đá 1x2 M250 Stone foundation concrete 1x2 M250 | C36: Độ sụt 10±2cm | D36: Kiến Hoa, Phan Vũ, BT Thủ Đức Kien Hoa, Phan Vu, BT Thu Duc | E36: m3 | G36: =M36*$O$21 -> 1392400 | H36: =N36*$O$21 -> 212400 | J36: =+G36+H36+I36 -> 1604800 | K36: =J36*$F36 -> 0 | M36: =M35 -> 1180000 | N36: =N35 -> 180000
A37: =IF(ISBLANK(E37),"",COUNTA($E$21:E37)) -> 14 | B37: Bê tông cột đá 1x2 M250 1x2 M250 column Concrete | C37: Độ sụt 10±2cm | D37: Kiến Hoa, Phan Vũ, BT Thủ Đức Kien Hoa, Phan Vu, BT Thu Duc | E37: m3 | G37: =M37*$O$21 -> 1392400 | H37: =N37*$O$21 -> 212400 | J37: =+G37+H37+I37 -> 1604800 | K37: =J37*$F37 -> 0 | M37: =M36 -> 1180000 | N37: =N36 -> 180000
A38: =IF(ISBLANK(E38),"",COUNTA($E$21:E38)) -> 15 | B38: Bê tông sàn đá 1x2 M250 Concrete stone floor 1x2 M250 | C38: Độ sụt 10±2cm | D38: Kiến Hoa, Phan Vũ, BT Thủ Đức Kien Hoa, Phan Vu, BT Thu Duc | E38: m3 | G38: =M38*$O$21 -> 1392400 | H38: =N38*$O$21 -> 212400 | J38: =+G38+H38+I38 -> 1604800 | K38: =J38*$F38 -> 0 | M38: =M37 -> 1180000 | N38: =N37 -> 180000
A39: 21 | B39: Bê tông ram dốc 1x2 M250 Concrete Ramps 1x2 M250 | C39: Độ sụt 10±2cm | D39: Kiến Hoa, Phan Vũ, BT Thủ Đức Kien Hoa, Phan Vu, BT Thu Duc | E39: m3 | G39: =M39*$O$21 -> 1392400 | H39: =N39*$O$21 -> 212400 | J39: =+G39+H39+I39 -> 1604800 | K39: =J39*$F39 -> 0 | M39: =M38 -> 1180000 | N39: =N38 -> 180000
A40: III | B40: CÔNG TÁC VÁN KHUÔN FORMWORK | K40: =SUBTOTAL(9,K41:K47) -> #REF!
A41: =IF(ISBLANK(E41),"",COUNTA($E$21:E41)) -> 17 | B41: Ván khuôn bê tông lót móng Formwork for foundation lean concrete | E41: m2 | G41: =M41*$O$21 -> #REF! | H41: =N41*$O$21 -> #REF! | J41: =+G41+H41+I41 -> #REF! | K41: =J41*$F41 -> #REF! | M41: ='02 Nhà Bảo Vệ_& P. Y TẾ'!R83 -> #REF! | N41: ='02 Nhà Bảo Vệ_& P. Y TẾ'!S83 -> #REF!
A42: =IF(ISBLANK(E42),"",COUNTA($E$21:E42)) -> 18 | B42: Ván khuôn bê tông lót đà kiềng Formwork for tie beam lean concrete | E42: m2 | G42: =M42*$O$21 -> #REF! | H42: =N42*$O$21 -> #REF! | J42: =+G42+H42+I42 -> #REF! | K42: =J42*$F42 -> #REF! | M42: =M41 -> #REF! | N42: =N41 -> #REF!
A43: =IF(ISBLANK(E43),"",COUNTA($E$21:E43)) -> 19 | B43: Ván khuôn bê tông móng Formwork for foundation concrete | E43: m2 | G43: =M43*$O$21 -> #REF! | H43: =N43*$O$21 -> #REF! | J43: =+G43+H43+I43 -> #REF! | K43: =J43*$F43 -> #REF! | M43: =M42 -> #REF! | N43: =N42 -> #REF!
A44: =IF(ISBLANK(E44),"",COUNTA($E$21:E44)) -> 20 | B44: Ván khuôn bê tông đà kiềng Formwork for tie beam concrete | E44: m2 | G44: =M44*$O$21 -> #REF! | H44: =N44*$O$21 -> #REF! | J44: =+G44+H44+I44 -> #REF! | K44: =J44*$F44 -> #REF! | M44: =M43 -> #REF! | N44: =N43 -> #REF!
A45: =IF(ISBLANK(E45),"",COUNTA($E$21:E45)) -> 21 | B45: Ván khuôn bê tông cột Formwork for column | E45: m2 | G45: =M45*$O$21 -> #REF! | H45: =N45*$O$21 -> #REF! | J45: =+G45+H45+I45 -> #REF! | K45: =J45*$F45 -> #REF! | M45: =M44 -> #REF! | N45: =N44 -> #REF!
A46: =IF(ISBLANK(E46),"",COUNTA($E$21:E46)) -> 22 | B46: Ván khuôn bê tông bổ trụ Formwork for stiffener | E46: m2 | G46: =M46*$O$21 -> #REF! | H46: =N46*$O$21 -> #REF! | J46: =+G46+H46+I46 -> #REF! | K46: =J46*$F46 -> #REF! | M46: =M45 -> #REF! | N46: =N45 -> #REF!
A48: III | B48: CÔNG TÁC CỐT THÉP REBAR WORK | K48: =SUBTOTAL(9,K49:K54) -> #REF!
A49: =IF(ISBLANK(E49),"",COUNTA($E$21:E49)) -> 23 | B49: Cốt thép móng Reinforcement for foundations. | C49: Thép D6, D8 : CB240T Thép Đường kính D>=10 : CB500V Steel D6, D8: CB240T Steel Diameter D>=10: CB500V | D49: Hoà Phát, Pomina Hoa Phat,Pomina | E49: kg | G49: =M49*$O$21 -> #REF! | H49: =N49*$O$21 -> #REF! | J49: =+G49+H49+I49 -> #REF! | K49: =J49*$F49 -> #REF! | M49: ='02 Nhà Bảo Vệ_& P. Y TẾ'!R117 -> #REF! | N49: ='02 Nhà Bảo Vệ_& P. Y TẾ'!S117 -> #REF!
A50: =IF(ISBLANK(E50),"",COUNTA($E$21:E50)) -> 24 | B50: Cốt thép đà kiềng Reinforcement tie beam | C50: Thép D6, D8 : CB240T Thép Đường kính D>=10 : CB500V Steel D6, D8: CB240T Steel Diameter D>=10: CB500V | D50: Hoà Phát, Pomina Hoa Phat,Pomina | E50: kg | G50: =M50*$O$21 -> #REF! | H50: =N50*$O$21 -> #REF! | J50: =+G50+H50+I50 -> #REF! | K50: =J50*$F50 -> #REF! | M50: =M49 -> #REF! | N50: =N49 -> #REF!
A51: =IF(ISBLANK(E51),"",COUNTA($E$21:E51)) -> 25 | B51: Cốt thép cột Column reinforcement | C51: Thép D6, D8 : CB240T Thép Đường kính D>=10 : CB500V Steel D6, D8: CB240T Steel Diameter D>=10: CB500V | D51: Hoà Phát, Pomina Hoa Phat,Pomina | E51: kg | G51: =M51*$O$21 -> #REF! | H51: =N51*$O$21 -> #REF! | J51: =+G51+H51+I51 -> #REF! | K51: =J51*$F51 -> #REF! | M51: =M50 -> #REF! | N51: =N50 -> #REF!
A52: =IF(ISBLANK(E52),"",COUNTA($E$21:E52)) -> 26 | B52: Cốt thép sàn (thép lưới hàn) Reinforcement for slabs(welded mesh) | C52: Thép D6, D8 : CB240T Thép Đường kính D>=10 : CB500V Steel D6, D8: CB240T Steel Diameter D>=10: CB500V | D52: Hoà Phát, Pomina Hoa Phat,Pomina | E52: kg | G52: =M52*$O$21 -> #REF! | H52: =N52*$O$21 -> #REF! | J52: =+G52+H52+I52 -> #REF! | K52: =J52*$F52 -> #REF! | M52: =M51 -> #REF! | N52: =N51 -> #REF!
A53: =IF(ISBLANK(E53),"",COUNTA($E$21:E53)) -> 27 | B53: Cốt thép Ram dốc (thép lưới hàn) Reinforcement for Ramps(welded mesh) | C53: Thép D6, D8 : CB240T Thép Đường kính D>=10 : CB500V Steel D6, D8: CB240T Steel Diameter D>=10: CB500V | D53: Hoà Phát, Pomina Hoa Phat,Pomina | E53: kg | G53: =M53*$O$21 -> #REF! | H53: =N53*$O$21 -> #REF! | J53: =+G53+H53+I53 -> #REF! | K53: =J53*$F53 -> #REF! | M53: =M52 -> #REF! | N53: =N52 -> #REF!
A55: VI | B55: CÔNG TÁC XÂY BRICK WALL | K55: =SUBTOTAL(9,K56:K60) -> #REF!
A56: =IF(ISBLANK(E56),"",COUNTA($E$21:E56)) -> 28 | B56: Tường xây gạch dày 200mm 200mm thick brick wall | C56: Vữa mác M75, Gạch xây mác >= M50, Gạch 04 lỗ chèn gạch 02 lỗ (gồm công tác khoan râu liên kết với cột vách bê tông) Mortar grade M75, Brick grade >= M50, 04-hole bricks, 02-hole brick inserts | E56: m2 | F56: =(5.6*2+4.8)*3.4-2.4*2-2*2*0.6 -> 47.2 | G56: =M56*$O$21 -> #REF! | H56: =N56*$O$21 -> #REF! | J56: =+G56+H56+I56 -> #REF! | K56: =J56*$F56 -> #REF! | M56: ='02 Nhà Bảo Vệ_& P. Y TẾ'!R124 -> #REF! | N56: ='02 Nhà Bảo Vệ_& P. Y TẾ'!S124 -> #REF!
A57: =IF(ISBLANK(E57),"",COUNTA($E$21:E57)) -> 29 | B57: GCLD bổ trụ 200x200mm, 4D12, D6@150 Fabrication and assembly 200x200mm stiffener, 4D12, D6@150 | E57: md | F57: =2.4*2 -> 4.8 | G57: =M57*$O$21 -> #REF! | H57: =N57*$O$21 -> #REF! | J57: =+G57+H57+I57 -> #REF! | K57: =J57*$F57 -> #REF! | M57: ='02 Nhà Bảo Vệ_& P. Y TẾ'!R129 -> #REF! | N57: ='02 Nhà Bảo Vệ_& P. Y TẾ'!S129 -> #REF!
A58: =IF(ISBLANK(E58),"",COUNTA($E$21:E58)) -> 30 | B58: GCLD lanh tô 200x200mm, 4D10, D6@150 Fabrication and assembly 200x200mm lintel, 4D10, D6@150 | E58: md | F58: =2.5*3 -> 7.5 | G58: =M58*$O$21 -> #REF! | H58: =N58*$O$21 -> #REF! | J58: =+G58+H58+I58 -> #REF! | K58: =J58*$F58 -> #REF! | M58: =M57 -> #REF! | N58: =N57 -> #REF!
A59: =IF(ISBLANK(E59),"",COUNTA($E$21:E59)) -> 31 | B59: Lanh tô, đà giằng, bổ trụ kt 100x200mm Lintel, tie beam, column size 100x200mm | E59: md | G59: =M59*$O$21 -> #REF! | H59: =N59*$O$21 -> #REF! | J59: =+G59+H59+I59 -> #REF! | K59: =J59*$F59 -> #REF! | M59: ='02 Nhà Bảo Vệ_& P. Y TẾ'!R131 -> #REF! | N59: =N58 -> #REF!
A61: VI | B61: CÔNG TÁC TÔ TRÁT PLASTERING WORK | K61: =SUBTOTAL(9,K62:K65) -> #REF!
A62: =IF(ISBLANK(E62),"",COUNTA($E$21:E62)) -> 32 | B62: Trát tường ngoài, vữa M75 dày 1.5cm Exterior wall painting, mortar M75, 1.5cm thk | E62: m2 | F62: =5.6*2*3.4-2.4*2-2*0.6 -> 32.08 | G62: =M62*$O$21 -> #REF! | H62: =N62*$O$21 -> #REF! | J62: =+G62+H62+I62 -> #REF! | K62: =J62*$F62 -> #REF! | M62: ='02 Nhà Bảo Vệ_& P. Y TẾ'!R134 -> #REF! | N62: ='02 Nhà Bảo Vệ_& P. Y TẾ'!S134 -> #REF!
A63: =IF(ISBLANK(E63),"",COUNTA($E$21:E63)) -> 33 | B63: Trát tường trong vữa M75 dày 1.5cm Plastering inside walls with 1.5cm thick M75 mortar | E63: m2 | F63: =5.6*2*3.4-2*2.4-3*2*0.6+4.8*2*3.4 -> 62.32 | G63: =M63*$O$21 -> #REF! | H63: =N63*$O$21 -> #REF! | J63: =+G63+H63+I63 -> #REF! | K63: =J63*$F63 -> #REF! | M63: ='02 Nhà Bảo Vệ_& P. Y TẾ'!R137 -> #REF! | N63: ='02 Nhà Bảo Vệ_& P. Y TẾ'!S137 -> #REF!
A64: =IF(ISBLANK(E64),"",COUNTA($E$21:E64)) -> 34 | B64: Trát má cửa, vữa M75 dày 1.5cm Door reveal plastering, M75 cement mortar, 15mm thick. | E64: md | F64: =(2.4*2+2)+2*(0.6+2)*2 -> 17.2 | G64: =M64*$O$21 -> #REF! | H64: =N64*$O$21 -> #REF! | J64: =+G64+H64+I64 -> #REF! | K64: =J64*$F64 -> #REF! | M64: ='02 Nhà Bảo Vệ_& P. Y TẾ'!R140 -> #REF! | N64: ='02 Nhà Bảo Vệ_& P. Y TẾ'!S140 -> #REF!
A66: VII | B66: CÔNG TÁC SƠN PAINTING WORK | K66: =SUBTOTAL(9,K67:K68) -> #REF!
A67: =IF(ISBLANK(E67),"",COUNTA($E$21:E67)) -> 35 | B67: Sơn nước cho tường bên trong ( hai lớp hoàn thiện) Painting interior walls with 2 finishing coats | D67: Sơn Nanpao gốc dầu | E67: m2 | F67: =F63 -> 62.32 | G67: =M67*$O$21 -> #REF! | H67: =N67*$O$21 -> #REF! | J67: =+G67+H67+I67 -> #REF! | K67: =J67*$F67 -> #REF! | M67: ='02 Nhà Bảo Vệ_& P. Y TẾ'!R147 -> #REF! | N67: ='02 Nhà Bảo Vệ_& P. Y TẾ'!S147 -> #REF!
A68: =IF(ISBLANK(E68),"",COUNTA($E$21:E68)) -> 36 | B68: Sơn tường ngoài nhà đã bả 1 nước lót + 2 nước phủ Paint exterior walls after putty application (1 primer coat + 2 finishing coats) | D68: Sơn Nanpao gốc dầu | E68: m2 | F68: =F62+F64*0.2 -> 35.52 | G68: =M68*$O$21 -> #REF! | H68: =N68*$O$21 -> #REF! | J68: =+G68+H68+I68 -> #REF! | K68: =J68*$F68 -> #REF! | M68: ='02 Nhà Bảo Vệ_& P. Y TẾ'!R148 -> #REF! | N68: ='02 Nhà Bảo Vệ_& P. Y TẾ'!S148 -> #REF!
A69: VII | B69: CÔNG TÁC HOÀN THIỆN NỀN SÀN FINISHING THE FLOOR | K69: =SUBTOTAL(9,K70:K72) -> 0
A70: =IF(ISBLANK(E70),"",COUNTA($E$21:E70)) -> 37 | B70: Lăn tạo nhám, sơn kẻ vạch chia ô đậu xe Roll to create a textured surface and paint line markings to delineate parking bays | E70: m2 | G70: =M70*$O$21 -> 106200 | H70: =N70*$O$21 -> 35400 | J70: =+G70+H70+I70 -> 141600 | K70: =J70*$F70 -> 0 | M70: 90000 | N70: 30000
A71: =IF(ISBLANK(E71),"",COUNTA($E$21:E71)) -> 38 | B71: Xoa nền, cắt ron chống trượt D20 Trowel the floor surface and cut D20 anti-slip joints | E71: m2 | G71: =M71*$O$21 -> 0 | H71: =N71*$O$21 -> 94400 | J71: =+G71+H71+I71 -> 94400 | K71: =J71*$F71 -> 0 | N71: 80000
A72: =IF(ISBLANK(E72),"",MAX($A$21:A71)+1) | J72: =+G72+H72+I72 -> 0 | K72: =J72*$F72 -> 0
A73: VII | B73: CÔNG TÁC CỬA DOOR WORK | K73: =SUBTOTAL(9,K74:K77) -> 16992000
A74: =IF(ISBLANK(E74),"",COUNTA($E$20:E74)) -> 39 | B74: D1 - 2000x2400 D1 - 2000x2400 | E74: bộ | F74: 1 | G74: =M74*$O$21 -> 9940320 | H74: =N74*$O$21 -> 1104480 | J74: =+G74+H74+I74 -> 11044800 | K74: =J74*$F74 -> 11044800 | M74: =O74*0.9 -> 8424000 | N74: =O74*0.1 -> 936000 | O74: =2*2.4*1950000 -> 9360000
A75: =IF(ISBLANK(E75),"",COUNTA($E$20:E75)) -> 40 | B75: Lam gió L1 - 2000x600, L1 - 2000x600, including insect net | E75: m2 | F75: 2.4 | G75: =M75*$O$21 -> 2230200 | H75: =N75*$O$21 -> 247800 | J75: =+G75+H75+I75 -> 2478000 | K75: =J75*$F75 -> 5947200 | M75: =O75*0.9 -> 1890000 | N75: =O75*0.1 -> 210000 | O75: 2100000
A76: =IF(ISBLANK(E76),"",COUNTA($E$20:E76)) -> 41 | B76: Cửa sổ S1 1200x1400, S1- 1200x1400 ,Windows | E76: bộ | G76: =M76*$O$21 -> 3186000 | H76: =N76*$O$21 -> 354000 | J76: =+G76+H76+I76 -> 3540000 | K76: =J76*$F76 -> 0 | M76: =O76*0.9 -> 2700000 | N76: =O76*0.1 -> 300000 | O76: 3000000
A77: =IF(ISBLANK(E77),"",MAX($A$21:A73)+1) | J77: =+G77+H77+I77 -> 0 | K77: =J77*$F77 -> 0
A78: VII | B78: CÔNG TÁC KẾT CẤU THÉP STEEL STRUCTURE AND WORK | K78: =SUBTOTAL(9,K80:K108) -> #REF!
B79: KẾT CẤU THÉP
B80: Sản xuất khung thép từ thép tấm tổ hợp | E80: kg | G80: =M80*$O$21 -> 19824 | H80: =N80*$O$21 -> 6844 | J80: =+G80+H80+I80 -> 26668 | K80: =J80*$F80 -> 0 | M80: 16800 | N80: 5800
B81: Sản xuất khung thép từ thép hình | E81: kg | G81: =M81*$O$21 -> 23600 | H81: =N81*$O$21 -> 6844 | J81: =+G81+H81+I81 -> 30444 | K81: =J81*$F81 -> 0 | M81: 20000 | N81: 5800
B82: Phun bi, làm sạch cấu kiện khung thép | E82: m2 | G82: =M82*$O$21 -> 41300 | H82: =N82*$O$21 -> 23600 | J82: =+G82+H82+I82 -> 64900 | K82: =J82*$F82 -> 0 | M82: 35000 | N82: 20000
B83: XÀ GỒ MÁI VÀ VÁCH | G83: =M83*$O$21 -> 0 | H83: =N83*$O$21 -> 0 | J83: =+G83+H83+I83 -> 0 | K83: =J83*$F83 -> 0
B84: Cung cấp xà gồ mạ kẽm mái và Canopy | E84: kg | G84: =M84*$O$21 -> 23600 | H84: =N84*$O$21 -> 590 | J84: =+G84+H84+I84 -> 24190 | K84: =J84*$F84 -> 0 | M84: 20000 | N84: 500
B85: CUNG CẤP VÀ LẮP ĐẶT PHỤ KIỆN KHUNG KÈO
B86: Bulong neo M24, L=600 mm | E86: Bộ | G86: =M86*$O$21 -> 171100 | H86: =N86*$O$21 -> 53100 | J86: =+G86+H86+I86 -> 224200 | K86: =J86*$F86 -> 0 | M86: 145000 | N86: 45000
B87: Bulong neo M20, L=450 mm | E87: Bộ | G87: =M87*$O$21 -> 129800 | H87: =N87*$O$21 -> 47200 | J87: =+G87+H87+I87 -> 177000 | K87: =J87*$F87 -> 0 | M87: 110000 | N87: 40000
B88: Bulong liên kết M 20 | E88: Bộ | G88: =M88*$O$21 -> 17700 | H88: =N88*$O$21 -> 0 | J88: =+G88+H88+I88 -> 17700 | K88: =J88*$F88 -> 0 | M88: 15000
B89: Bulong liên kết M 12 | E89: Bộ | G89: =M89*$O$21 -> 4720 | H89: =N89*$O$21 -> 0 | J89: =+G89+H89+I89 -> 4720 | K89: =J89*$F89 -> 0 | M89: 4000
B90: Thanh giằng xà gồ (D12) | E90: m | G90: =M90*$O$21 -> 35400 | H90: =N90*$O$21 -> 7080 | J90: =+G90+H90+I90 -> 42480 | K90: =J90*$F90 -> 0 | M90: 30000 | N90: 6000
B91: Thanh giằng (Cáp D14) | E91: m | G91: =M91*$O$21 -> 29500 | H91: =N91*$O$21 -> 11800 | J91: =+G91+H91+I91 -> 41300 | K91: =J91*$F91 -> 0 | M91: 25000 | N91: 10000
B92: VẬN CHUYỂN & LẮP ĐẶT | G92: =M92*$O$21 -> 0 | H92: =N92*$O$21 -> 0 | J92: =+G92+H92+I92 -> 0 | K92: =J92*$F92 -> 0
B93: Vận chuyển | E93: kg | G93: =M93*$O$21 -> 0 | H93: =N93*$O$21 -> 590 | J93: =+G93+H93+I93 -> 590 | K93: =J93*$F93 -> 0 | N93: 500
B94: Lắp đặt kết cấu thép | E94: kg | G94: =M94*$O$21 -> 0 | H94: =N94*$O$21 -> 4248 | J94: =+G94+H94+I94 -> 4248 | K94: =J94*$F94 -> 0 | N94: 3600
B95: CUNG CẤP VÀ LẮP ĐẶT PHẦN BAO CHE | G95: =M95*$O$21 -> 0 | H95: =N95*$O$21 -> 0 | J95: =+G95+H95+I95 -> 0 | K95: =J95*$F95 -> 0
B96: Tôn mái lớp trên | E96: m2 | G96: =M96*$O$21 -> 171100 | H96: =N96*$O$21 -> 41300 | J96: =+G96+H96+I96 -> 212400 | K96: =J96*$F96 -> 0 | M96: 145000 | N96: 35000
B97: Tôn mặt dựng | E97: m2 | G97: =M97*$O$21 -> 129800 | H97: =N97*$O$21 -> 41300 | J97: =+G97+H97+I97 -> 171100 | K97: =J97*$F97 -> 0 | M97: 110000 | N97: 35000
B98: Tấm trãi sàn | E98: m2 | G98: =M98*$O$21 -> 177000 | H98: =N98*$O$21 -> 23600 | J98: =+G98+H98+I98 -> 200600 | K98: =J98*$F98 -> 0 | M98: 150000 | N98: 20000
B99: Tole bao xung quanh sàn Deck | E99: m | G99: =M99*$O$21 -> 106200 | H99: =N99*$O$21 -> 17700 | J99: =+G99+H99+I99 -> 123900 | K99: =J99*$F99 -> 0 | M99: 90000 | N99: 15000
B100: Đinh chống cắt M16 | E100: Bộ | G100: =M100*$O$21 -> 9440 | H100: =N100*$O$21 -> 5900 | J100: =+G100+H100+I100 -> 15340 | K100: =J100*$F100 -> 0 | M100: 8000 | N100: 5000
B101: CUNG CẤP VÀ LẮP ĐẶT PHẦN HOÀN THIỆN | G101: =M101*$O$21 -> 0 | H101: =N101*$O$21 -> 0 | J101: =+G101+H101+I101 -> 0 | K101: =J101*$F101 -> 0
B102: Máng xối biên nhà xưởng | E102: md | G102: =M102*$O$21 -> 826000 | H102: =N102*$O$21 -> 295000 | J102: =+G102+H102+I102 -> 1121000 | K102: =J102*$F102 -> 0 | M102: 700000 | N102: 250000
B103: Cầu chắn rác inox | E103: Bộ | G103: =M103*$O$21 -> 295000 | H103: =N103*$O$21 -> 0 | J103: =+G103+H103+I103 -> 295000 | K103: =J103*$F103 -> 0 | M103: 250000
B104: Ống xối nhà xưởng đến chân cột thép | E104: md | G104: =M104*$O$21 -> 531000 | H104: =N104*$O$21 -> 141600 | J104: =+G104+H104+I104 -> 672600 | K104: =J104*$F104 -> 0 | M104: 450000 | N104: 120000
B105: Diềm | E105: m | G105: =M105*$O$21 -> 141600 | H105: =N105*$O$21 -> 88500 | J105: =+G105+H105+I105 -> 230100 | K105: =J105*$F105 -> 0 | M105: 120000 | N105: 75000
A106: =IF(ISBLANK(E106),"",COUNTA($E$21:E106)) -> 63 | B106: Cầu chắn rác sê nô D90 Seno garbage barrier bridge D90 | E106: Cái | G106: =M106*$O$21 -> 295000 | H106: =N106*$O$21 -> 0 | J106: =+G106+H106+I106 -> 295000 | K106: =J106*$F106 -> 0 | M106: ='02 Nhà Bảo Vệ_& P. Y TẾ'!R171 -> 250000
A107: =IF(ISBLANK(E107),"",COUNTA($E$21:E107)) -> 64 | B107: Ống thoát nước tràn PVC D34 PVC D34 Overflow Drain Pipe | E107: m | G107: =M107*$O$21 -> 0 | H107: =N107*$O$21 -> 0 | J107: =+G107+H107+I107 -> 0 | K107: =J107*$F107 -> 0
...

Sheet 05 Nhà Ăn
A1: BẢNG DỰ TOÁN BÁO GIÁ CÔNG TRÌNH / ESTIMATE TABLE
A2: ="DỰ ÁN / PROJECT : "&#REF! -> #REF!
A3: ="HẠNG MỤC / ITEM : "&B8 -> HẠNG MỤC / ITEM : NHÀ ĂN CANTEEN
A4: ="CHỦ ĐẦU TƯ / : "&#REF! -> #REF!
A6: STT NO. | B6: TÊN CÔNG VIỆC VÀ DIỄN GIẢI DESCRIPTION | C6: ĐẶC TÍNH KỸ THUẬT STANDARD | D6: NHÃN HIỆU & XUẤT XỨ BRAND NAME & ORIGIN | E6: Đvt Unit | F6: SL | G6: DÀI | H6: RỘNG | I6: CAO | J6: KL | K6: KL TỔNG Q'TY | L6: ĐƠN GIÁ / RATE | O6: TỔNG CỘNG (VNĐ) TOTAL COST(VND) | Q6: REMARK GHI CHÚ
L7: VẬT TƯ RATE MATERIALS | M7: NHÂN CÔNG RATE LABOUR | N7: MMTB RATE EQUIPMENT | O7: ĐƠN GIÁ TỔNG TOTAL PRICE | P7: THÀNH TIỀN AMOUNT TOTAL | R7: VẬT TƯ RATE MATERIALS | S7: NHÂN CÔNG RATE LABOUR
A8: =A22 -> *** | B8: =B22 -> NHÀ ĂN CANTEEN | P8: =SUBTOTAL(9,P9:P21) -> #REF!
A9: =A23 -> B | B9: =B23 -> CÔNG TÁC ĐẤT EARTHWORK | P9: =P23 -> #REF!
A10: =A43 -> C | B10: =B43 -> CÔNG TÁC BÊ TÔNG CONCRETE WORK | P10: =P43 -> #REF!
A11: =A88 -> D | B11: =B88 -> CÔNG TÁC VÁN KHUÔN FORMWORK | P11: =P88 -> #REF!
A12: =A121 -> E | B12: =B121 -> CÔNG TÁC CỐT THÉP REBAR WORK | P12: =P121 -> #REF!
A13: =A128 -> F | B13: =B128 -> CÔNG TÁC XÂY BRICK WALL | P13: =P128 -> #REF!
A14: =A154 -> G | B14: =B154 -> CÔNG TÁC TÔ TRÁT PLASTERING WORK | P14: =P154 -> #REF!
A15: =A171 -> H | B15: =B171 -> CÔNG TÁC SƠN PAINTING WORK | P15: =P171 -> #REF!
A16: =A175 -> I | B16: =B175 -> CÔNG TÁC CHỐNG THẤM WATERPROOFING WORK | P16: =P175 -> #REF!
A17: J | B17: =B179 -> CÔNG TÁC HOÀN THIỆN NỀN SÀN FLOOR FINISHING WORK | P17: =P179 -> #REF!
A18: =A200 -> K | B18: =B200 -> CÔNG TÁC TRẦN VÁCH CEILING & PARTITION WORKS | P18: =P200 -> #REF!
A19: =A204 -> L | B19: =B204 -> CÔNG TÁC CỬA DOOR WORK | P19: =P204 -> 199125000
A20: =A219 -> N | B20: =B219 -> CÔNG TÁC BỔ SUNG TỪ NHÀ THẦU ADDITIONAL WORK FROM THE CONTRACTOR | P20: =P219 -> 0
A22: *** | B22: NHÀ ĂN CANTEEN | P22: =SUBTOTAL(9,P224:P464) -> 0 | R22: Profit | T22: 1.18
A23: B | B23: CÔNG TÁC ĐẤT EARTHWORK | P23: =SUBTOTAL(9,P24:P42) -> #REF!
A24: =IF(ISBLANK(E24),"",COUNTA($E$22:E24)) -> 1 | B24: Đào đất hố móng, Excavation of foundation pits, | E24: m3 | K24: =SUM(J25:J28) -> 221.728 | L24: =R24*$T$22 -> #REF! | M24: =S24*$T$22 -> #REF! | O24: =+L24+M24+N24 -> #REF! | P24: =O24*$K24 -> #REF! | R24: ='04 NHÀ XE'!#REF! -> #REF! | S24: ='04 NHÀ XE'!#REF! -> #REF!
B25: M1 | F25: 8 | G25: 2.4 | H25: 2.4 | I25: 2.05 | J25: =F25*(G25+0.6)*(H25+0.6)*I25 -> 147.6
B26: M2 | F26: 2 | G26: 2 | H26: 2 | I26: 2.05 | J26: =F26*(G26+0.6)*(H26+0.6)*I26 -> 27.716
B27: M3 | F27: 4 | G27: 1.2 | H27: 1.2 | I27: 2.05 | J27: =F27*(G27+0.6)*(H27+0.6)*I27 -> 26.568
B28: M2A | F28: 2 | G28: 1.6 | H28: 1.6 | I28: 2.05 | J28: =F28*(G28+0.6)*(H28+0.6)*I28 -> 19.844
A29: =IF(ISBLANK(E29),"",COUNTA($E$22:E29)) -> 2 | B29: Đào đất đà kiềng, nền nhà Digging up the land and the foundation of the house | E29: m3 | K29: =SUM(J30:J32) -> 20.846 | L29: =R29*$T$22 -> #REF! | M29: =S29*$T$22 -> #REF! | O29: =+L29+M29+N29 -> #REF! | P29: =O29*$K29 -> #REF! | R29: =R24 -> #REF! | S29: =S24 -> #REF!
B30: DK1 | F30: 2 | G30: 20 | H30: 0.2 | I30: 0.4 | J30: =F30*(G30+0.6)*(H30+0.6)*I30 -> 13.184
B31: DK2 | F31: 4 | G31: 5.5 | H31: 0.2 | I31: 0.3 | J31: =F31*(G31+0.6)*(H31+0.6)*I31 -> 5.856
B32: DK3 | F32: 1 | G32: 8 | H32: 0.1 | I32: 0.3 | J32: =F32*(G32+0.6)*(H32+0.6)*I32 -> 1.806
A33: =IF(ISBLANK(E33),"",COUNTA($E$22:E33)) -> 3 | B33: Đắp đất móng đầm chặt Compacting the foundation | E33: m3 | K33: =K24-K49-K53 -> 196.757 | L33: =R33*$T$22 -> #REF! | M33: =S33*$T$22 -> #REF! | O33: =+L33+M33+N33 -> #REF! | P33: =O33*$K33 -> #REF! | R33: ='04 NHÀ XE'!#REF! -> #REF! | S33: ='04 NHÀ XE'!#REF! -> #REF!
A34: 4 | B34: Đắp đất nền Backfilling for floor | E34: m3 | K34: =20*5.5*0.5*1.3 -> 71.5 | L34: =R34*$T$22 -> 0 | M34: =S34*$T$22 -> 50740 | O34: =+L34+M34+N34 -> 50740 | P34: =O34*$K34 -> 3627910 | R34: ='02 Nhà Bảo Vệ_& P. Y TẾ'!R32 -> 0 | S34: ='02 Nhà Bảo Vệ_& P. Y TẾ'!S32 -> 43000
A35: =IF(ISBLANK(E35),"",COUNTA($E$22:E35)) -> 5 | B35: Vận chuyển đất ra ngoài phạm vi công trình Transporting land outside the scope of the project | E35: m3 | K35: =K24-K33 -> 24.971 | L35: =R35*$T$22 -> #REF! | M35: =S35*$T$22 -> #REF! | O35: =+L35+M35+N35 -> #REF! | P35: =O35*$K35 -> #REF! | R35: ='04 NHÀ XE'!#REF! -> #REF! | S35: ='04 NHÀ XE'!#REF! -> #REF!
A36: =IF(ISBLANK(E36),"",COUNTA($E$22:E36)) -> 6 | B36: Đầm chặt và xử lý đất đáy đà kiềng và nền K≥0.92 Compaction and treatment of soil at the bottom of Da Kieng and the foundation K≥0.92 | E36: m2 | K36: =SUM(J37:J40) -> 73.2 | L36: =R36*$T$22 -> #REF! | M36: =S36*$T$22 -> #REF! | O36: =+L36+M36+N36 -> #REF! | P36: =O36*$K36 -> #REF! | R36: ='04 NHÀ XE'!#REF! -> #REF! | S36: ='04 NHÀ XE'!#REF! -> #REF!
B37: M1 | F37: 8 | G37: 2.4 | H37: 2.4 | J37: =F37*(G37+0.2)*(H37+0.2) -> 54.08 | L37: =R37*$T$22 -> 0
B38: M2 | F38: 2 | G38: 1.2 | H38: 1.2 | J38: =F38*(G38+0.2)*(H38+0.2) -> 3.92 | L38: =R38*$T$22 -> 0
B39: M3 | F39: 4 | G39: 1.2 | H39: 1.2 | J39: =F39*(G39+0.2)*(H39+0.2) -> 7.84 | L39: =R39*$T$22 -> 0
B40: M2A | F40: 2 | G40: 9 | H40: 0.2 | J40: =F40*(G40+0.2)*(H40+0.2) -> 7.36 | L40: =R40*$T$22 -> 0
A41: =IF(ISBLANK(E41),"",COUNTA($E$22:E41)) -> 7 | B41: Lớp PVC, dày 0.03mm PVC layer, 0.03mm thick | E41: m2 | K41: =20*5.5 -> 110 | L41: =R41*$T$22 -> #REF! | M41: =S41*$T$22 -> #REF! | O41: =+L41+M41+N41 -> #REF! | P41: =O41*$K41 -> #REF! | R41: ='04 NHÀ XE'!#REF! -> #REF! | S41: ='04 NHÀ XE'!#REF! -> #REF!
A42: 8 | B42: Lớp đá 0x4 Stone layer 0x4 | D42: Phú Giáo, Tân Uyên, địa phương Phu Giao, Tan Uyen, Local | E42: m3 | K42: =K41*0.15*1.42 -> 23.43 | L42: =R42*$T$22 -> #REF! | M42: =S42*$T$22 -> #REF! | O42: =+L42+M42+N42 -> #REF! | P42: =O42*$K42 -> #REF! | R42: ='02 Nhà Bảo Vệ_& P. Y TẾ'!R45 -> #REF! | S42: ='02 Nhà Bảo Vệ_& P. Y TẾ'!S45 -> #REF!
A43: C | B43: CÔNG TÁC BÊ TÔNG CONCRETE WORK | D43: Hồng Tín, Hồng Hà, Đại Lộc Phát, HDH Hong Tin, Hong Ha, Dai Loc Phat, HDH | P43: =SUBTOTAL(9,P44:P87) -> #REF!
A44: =IF(ISBLANK(E44),"",COUNTA($E$22:E44)) -> 9 | B44: Bê tông lót móng đá 1x2 M150 Concrete lined with stone 1x2 M150 | E44: m3 | K44: =SUM(J45:J48) -> 3.904 | L44: =R44*$T$22 -> #REF! | M44: =S44*$T$22 -> #REF! | O44: =+L44+M44+N44 -> #REF! | P44: =O44*$K44 -> #REF! | R44: ='04 NHÀ XE'!#REF! -> #REF! | S44: ='04 NHÀ XE'!#REF! -> #REF!
B45: M1 | F45: 8 | G45: 2.4 | H45: 2.4 | I45: 0.05 | J45: =F45*(G45+0.2)*(H45+0.2)*I45 -> 2.704
B46: M2 | F46: 2 | G46: 2 | H46: 2 | I46: 0.05 | J46: =F46*(G46+0.2)*(H46+0.2)*I46 -> 0.484
B47: M3 | F47: 4 | G47: 1.2 | H47: 1.2 | I47: 0.05 | J47: =F47*(G47+0.2)*(H47+0.2)*I47 -> 0.392
B48: M2A | F48: 2 | G48: 1.6 | H48: 1.6 | I48: 0.05 | J48: =F48*(G48+0.2)*(H48+0.2)*I48 -> 0.324
A49: =IF(ISBLANK(E49),"",COUNTA($E$22:E49)) -> 10 | B49: Bê tông lót đá đà kiềng 1x2 M150 Concrete lined with stone 1x2 M150 | E49: m3 | K49: =SUM(J50:J52) -> 1.387 | L49: =R49*$T$22 -> #REF! | M49: =S49*$T$22 -> #REF! | O49: =+L49+M49+N49 -> #REF! | P49: =O49*$K49 -> #REF! | R49: =R44 -> #REF! | S49: =S44 -> #REF!
B50: DK1 | F50: 2 | G50: 20 | H50: 0.2 | I50: 0.05 | J50: =F50*(G50+0.2)*(H50+0.2)*I50 -> 0.808
B51: DK2 | F51: 4 | G51: 5.5 | H51: 0.2 | I51: 0.05 | J51: =F51*(G51+0.2)*(H51+0.2)*I51 -> 0.456
B52: DK3 | F52: 1 | G52: 8 | H52: 0.1 | I52: 0.05 | J52: =F52*(G52+0.2)*(H52+0.2)*I52 -> 0.123
A53: =IF(ISBLANK(E53),"",COUNTA($E$22:E53)) -> 11 | B53: Bê tông móng đá 1x2 M250 Stone foundation concrete 1x2 M250 | E53: m3 | K53: =SUM(J54:J57) -> 23.584 | L53: =R53*$T$22 -> #REF! | M53: =S53*$T$22 -> #REF! | O53: =+L53+M53+N53 -> #REF! | P53: =O53*$K53 -> #REF! | R53: ='04 NHÀ XE'!#REF! -> #REF! | S53: ='04 NHÀ XE'!#REF! -> #REF!
B54: M1 | F54: 8 | G54: 2.4 | H54: 2.4 | I54: 0.375 | J54: =F54*G54*H54*I54 -> 17.28
B55: M2 | F55: 2 | G55: 2 | H55: 2 | I55: 0.3 | J55: =F55*G55*H55*I55 -> 2.4
B56: M3 | F56: 4 | G56: 1.2 | H56: 1.2 | I56: 0.3 | J56: =F56*G56*H56*I56 -> 1.728
B57: M2A | F57: 2 | G57: 1.6 | H57: 1.6 | I57: =0.25+0.175 -> 0.425 | J57: =F57*G57*H57*I57 -> 2.176
A58: =IF(ISBLANK(E58),"",COUNTA($E$22:E58)) -> 12 | B58: Bê tông cổ móng đá 1x2 M250 Stone foundation neck concrete 1x2 M250 | E58: m3 | K58: =SUM(J59:J60) -> 0.88 | L58: =R58*$T$22 -> #REF! | M58: =S58*$T$22 -> #REF! | O58: =+L58+M58+N58 -> #REF! | P58: =O58*$K58 -> #REF! | R58: =R53 -> #REF! | S58: =S53 -> #REF!
B59: C1 | F59: 12 | G59: 0.2 | H59: 0.3 | I59: 1 | J59: =F59*G59*H59*I59 -> 0.72
B60: C2 | F60: 4 | G60: 0.2 | H60: 0.2 | I60: 1 | J60: =F60*G60*H60*I60 -> 0.16
A61: =IF(ISBLANK(E61),"",COUNTA($E$22:E61)) -> 13 | B61: Bê tông đà kiềng đá 1x2 M250 1x2 M300 Stone Concrete | E61: m3 | K61: =SUM(J62:J64) -> 4.76 | L61: =R61*$T$22 -> #REF! | M61: =S61*$T$22 -> #REF! | O61: =+L61+M61+N61 -> #REF! | P61: =O61*$K61 -> #REF! | R61: =R58 -> #REF! | S61: =S58 -> #REF!
B62: DK1 | F62: 2 | G62: 20 | H62: 0.2 | I62: 0.4 | J62: =F62*G62*H62*I62 -> 3.2
B63: DK2 | F63: 4 | G63: 5.5 | H63: 0.2 | I63: 0.3 | J63: =F63*G63*H63*I63 -> 1.32
B64: DK3 | F64: 1 | G64: 8 | H64: 0.1 | I64: 0.3 | J64: =F64*G64*H64*I64 -> 0.24
A65: =IF(ISBLANK(E65),"",COUNTA($E$22:E65)) -> 14 | B65: Bê tông nền đá 1x2 M250 Stone foundation concrete 1x2 M250 | E65: m3 | K65: =J66 -> 11 | L65: =R65*$T$22 -> #REF! | M65: =S65*$T$22 -> #REF! | O65: =+L65+M65+N65 -> #REF! | P65: =O65*$K65 -> #REF! | R65: =R61 -> #REF! | S65: =S61 -> #REF!
F66: 1 | G66: 20 | H66: 5.5 | I66: 0.1 | J66: =F66*G66*H66*I66 -> 11
A67: =IF(ISBLANK(E67),"",COUNTA($E$22:E67)) -> 15 | B67: Bê tông cột đá 1x2 M250 1x2 M250 Stone Pillar Concrete | E67: m3 | K67: =SUM(J68) -> 5.76 | L67: =R67*$T$22 -> #REF! | M67: =S67*$T$22 -> #REF! | O67: =+L67+M67+N67 -> #REF! | P67: =O67*$K67 -> #REF! | R67: =R65 -> #REF! | S67: =S65 -> #REF!
B68: C1 | F68: 12 | G68: 0.2 | H68: 0.3 | I68: 8 | J68: =F68*G68*H68*I68 -> 5.76 | R68: =R66 -> 0
A69: =IF(ISBLANK(E69),"",COUNTA($E$22:E69)) -> 16 | B69: Bê tông dầm giằng đá 1x2 M250 Concrete stone bracing beam 1x2 M250 | C69: Phụ gia đông kết R7 R7 Coagulation Additive | E69: m3 | K69: =SUM(J70:J81) -> 20.064 | L69: =R69*$T$22 -> #REF! | M69: =S69*$T$22 -> #REF! | O69: =+L69+M69+N69 -> #REF! | P69: =O69*$K69 -> #REF! | R69: =R67 -> #REF! | S69: =S67 -> #REF!
B70: Sàn Tầng 2
B71: DS1 | F71: 2 | G71: 20 | H71: 0.2 | I71: 0.4 | J71: =F71*G71*H71*I71 -> 3.2
B72: DS2 | F72: 6 | G72: =5.5+1.4 -> 6.9 | H72: 0.2 | I72: 0.4 | J72: =F72*G72*H72*I72 -> 3.312
B73: DS3 | F73: 1 | G73: =20+1.5*5 -> 27.5 | H73: 0.2 | I73: 0.3 | J73: =F73*G73*H73*I73 -> 1.65
B74: DS4 | F74: 1 | G74: 20 | H74: 0.2 | I74: 0.4 | J74: =F74*G74*H74*I74 -> 1.6
F75: 1 | G75: =20+2.8 -> 22.8 | H75: 0.1 | I75: 0.1 | J75: =F75*G75*H75*I75 -> 0.228
B76: Sàn Tầng Mái
B77: DM1 | F77: 3 | G77: 20 | H77: 0.2 | I77: 0.4 | J77: =F77*G77*H77*I77 -> 4.8
B78: DM2 | F78: 6 | G78: =5.5+1.4 -> 6.9 | H78: 0.2 | I78: 0.4 | J78: =F78*G78*H78*I78 -> 3.312
B79: DM3 | F79: 1 | G79: =20+1.4 -> 21.4 | H79: 0.2 | I79: 0.3 | J79: =F79*G79*H79*I79 -> 1.284
B80: DM4 | F80: 1 | G80: 2 | H80: 0.2 | I80: 0.4 | J80: =F80*G80*H80*I80 -> 0.16
B81: Gờ chắn nước | F81: 1 | G81: =(20+5.9)*2 -> 51.8 | H81: 0.1 | I81: 0.1 | J81: =F81*G81*H81*I81 -> 0.518
A82: =IF(ISBLANK(E82),"",COUNTA($E$22:E82)) -> 17 | B82: Bê tông sàn đá 1x2 M250 Concrete stone floor 1x2 M250 | C82: Phụ gia đông kết R7 R7 Coagulation Additive | E82: m3 | K82: =SUM(J83:J84) -> 30.36 | L82: =R82*$T$22 -> #REF! | M82: =S82*$T$22 -> #REF! | O82: =+L82+M82+N82 -> #REF! | P82: =O82*$K82 -> #REF! | R82: =R69 -> #REF! | S82: =S69 -> #REF!
B83: Sàn tầng 2 | F83: 1 | G83: 20 | H83: 6.9 | I83: 0.12 | J83: =F83*G83*H83*I83 -> 16.56
B84: Sàn mái | F84: 1 | G84: 20 | H84: 6.9 | I84: 0.1 | J84: =F84*G84*H84*I84 -> 13.8
A85: =IF(ISBLANK(E85),"",COUNTA($E$22:E85)) -> 18 | B85: Bê tông lanh tô đá 1x2 M250 1x2 Stone Bowl Linen Concrete M250 | E85: m3 | K85: 1 | L85: =R85*$T$22 -> #REF! | M85: =S85*$T$22 -> #REF! | O85: =+L85+M85+N85 -> #REF! | P85: =O85*$K85 -> #REF! | R85: =R67 -> #REF! | S85: =S82 -> #REF!
A86: =IF(ISBLANK(E86),"",COUNTA($E$22:E86)) -> 19 | B86: Bê tông bổ trụ đá 1x2 M250 Concrete reinforcement stone pillars 1x2 M250 | E86: m3 | K86: 1 | L86: =R86*$T$22 -> #REF! | M86: =S86*$T$22 -> #REF! | O86: =+L86+M86+N86 -> #REF! | P86: =O86*$K86 -> #REF! | R86: =R85 -> #REF! | S86: =S85 -> #REF!
A88: D | B88: CÔNG TÁC VÁN KHUÔN FORMWORK | P88: =SUBTOTAL(9,P89:P120) -> #REF!
A89: =IF(ISBLANK(E89),"",COUNTA($E$22:E89)) -> 20 | B89: Ván khuôn lót móng Foundation Liner Formwork | E89: m2 | K89: =SUM(J90:J92) -> 0.588 | L89: =R89*$T$22 -> #REF! | M89: =S89*$T$22 -> #REF! | O89: =+L89+M89+N89 -> #REF! | P89: =O89*$K89 -> #REF! | R89: ='04 NHÀ XE'!#REF! -> #REF! | S89: ='04 NHÀ XE'!#REF! -> #REF!
B90: M1 | F90: 3 | G90: 1.2 | H90: 1.2 | I90: 0.05 | J90: =F90*(G90+0.2)*(H90+0.2)*I90 -> 0.294
B91: M2 | F91: 2 | G91: 1.2 | H91: 1.2 | I91: 0.05 | J91: =F91*(G91+0.2)*(H91+0.2)*I91 -> 0.196
B92: M3 | F92: 1 | G92: 1.2 | H92: 1.2 | I92: 0.05 | J92: =F92*(G92+0.2)*(H92+0.2)*I92 -> 0.098
A93: =IF(ISBLANK(E93),"",COUNTA($E$22:E93)) -> 21 | B93: Ván khuôn lót đà kiềng Formwork lined with shackles | E93: m2 | K93: =SUM(J94:J97) -> 0.737 | L93: =R93*$T$22 -> #REF! | M93: =S93*$T$22 -> #REF! | O93: =+L93+M93+N93 -> #REF! | P93: =O93*$K93 -> #REF! | R93: =R89 -> #REF! | S93: =S89 -> #REF!
B94: DK1 | F94: 2 | G94: 9 | H94: 0.2 | I94: 0.05 | J94: =F94*(G94+0.2)*(H94+0.2)*I94 -> 0.368
F95: 3 | G95: 4 | H95: 0.2 | I95: 0.05 | J95: =F95*(G95+0.2)*(H95+0.2)*I95 -> 0.252
B96: DK2 | F96: 1 | G96: 4 | H96: 0.2 | I96: 0.05 | J96: =F96*(G96+0.2)*(H96+0.2)*I96 -> 0.084
B97: DK3 | F97: 1 | G97: 2 | H97: 0.1 | I97: 0.05 | J97: =F97*(G97+0.2)*(H97+0.2)*I97 -> 0.033
A98: =IF(ISBLANK(E98),"",COUNTA($E$22:E98)) -> 22 | B98: Ván khuôn nền Substrate Formwork | E98: m2 | K98: =J99 -> 2.6 | L98: =R98*$T$22 -> #REF! | M98: =S98*$T$22 -> #REF! | O98: =+L98+M98+N98 -> #REF! | P98: =O98*$K98 -> #REF! | R98: =R93 -> #REF! | S98: =S93 -> #REF!
F99: 1 | G99: 9 | H99: 4 | I99: 0.1 | J99: =F99*(G99+H99)*2*I99 -> 2.6
A100: =IF(ISBLANK(E100),"",COUNTA($E$22:E100)) -> 23 | B100: Ván khuôn móng Foundation Formwork | E100: m2 | K100: =SUM(J101:J103) -> 8.64 | L100: =R100*$T$22 -> #REF! | M100: =S100*$T$22 -> #REF! | O100: =+L100+M100+N100 -> #REF! | P100: =O100*$K100 -> #REF! | R100: =R98 -> #REF! | S100: =S98 -> #REF!
B101: M1 | F101: 3 | G101: 1.2 | H101: 1.2 | I101: 0.3 | J101: =F101*(G101+H101)*2*I101 -> 4.32
B102: M2 | F102: 2 | G102: 1.2 | H102: 1.2 | I102: 0.3 | J102: =F102*(G102+H102)*2*I102 -> 2.88
B103: M3 | F103: 1 | G103: 1.2 | H103: 1.2 | I103: 0.3 | J103: =F103*(G103+H103)*2*I103 -> 1.44
...

Sheet 06 WC,Bảo Trì, Chứa Rác 
A1: BẢNG DỰ TOÁN BÁO GIÁ CÔNG TRÌNH / ESTIMATE TABLE
A2: ="DỰ ÁN / PROJECT : "&[6]COVER!K10 -> DỰ ÁN / PROJECT : AN KHANG FOODS JSC
A3: ="HẠNG MỤC / ITEM : "&B8 -> HẠNG MỤC / ITEM : WC,Bảo Trì, Chứa Rác TOILET, MAINTENANCE, GARBAGE STORAGE
A4: ="CHỦ ĐẦU TƯ / : "&[6]COVER!K19 -> CHỦ ĐẦU TƯ / : AN KHANG FOODS JSC
A6: STT NO. | B6: TÊN CÔNG VIỆC VÀ DIỄN GIẢI DESCRIPTION | C6: ĐẶC TÍNH KỸ THUẬT STANDARD | D6: NHÃN HIỆU & XUẤT XỨ BRAND NAME & ORIGIN | E6: Đvt Unit | F6: KL TỔNG Q'TY | G6: ĐƠN GIÁ / RATE | J6: TỔNG CỘNG (VNĐ) TOTAL COST(VND) | L6: REMARK GHI CHÚ | M6: VẬT TƯ RATE MATERIALS | N6: NHÂN CÔNG RATE LABOUR
G7: VẬT TƯ RATE MATERIALS | H7: NHÂN CÔNG RATE LABOUR | I7: MMTB RATE EQUIPMENT | J7: ĐƠN GIÁ TỔNG TOTAL PRICE | K7: THÀNH TIỀN AMOUNT TOTAL
A8: =A23 -> *** | B8: =B23 -> WC,Bảo Trì, Chứa Rác TOILET, MAINTENANCE, GARBAGE STORAGE | K8: =SUBTOTAL(9,K9:K22) -> #REF! | M8: Profit | O8: 1.18
A9: =A24 -> B | B9: =B24 -> CÔNG TÁC ĐẤT EARTHWORK | K9: =K24 -> #REF!
A10: =A34 -> C | B10: =B34 -> CÔNG TÁC BÊ TÔNG CONCRETE WORK | K10: =K34 -> #REF!
A11: =A44 -> D | B11: =B44 -> CÔNG TÁC VÁN KHUÔN FORMWORK | K11: =K44 -> #REF!
A12: =A52 -> E | B12: =B52 -> CÔNG TÁC CỐT THÉP REBAR WORK | K12: =K52 -> #REF!
A13: =A59 -> F | B13: =B59 -> CÔNG TÁC XÂY BRICK WALL
A14: =A67 -> G | B14: =B67 -> CÔNG TÁC TÔ TRÁT PLASTERING WORK | K14: =K67 -> #REF!
A15: =A73 -> H | B15: =B73 -> CÔNG TÁC SƠN PAINTING WORK | K15: =K73 -> #REF!
A16: =A77 -> I | B16: =B77 -> CÔNG TÁC CHỐNG THẤM WATERPROOFING WORK | K16: =K77 -> #REF!
A17: J | B17: =B80 -> CÔNG TÁC HOÀN THIỆN NỀN SÀN FLOOR FINISHING WORK
A18: K | B18: =B84 -> CÔNG TÁC TRẦN VÁCH CEILING & PARTITION WORKS | K18: =K84 -> #REF!
A19: L | B19: =B88 -> CÔNG TÁC CỬA DOOR WORK | K19: =K88 -> 147141280
A20: M | B20: =B98 -> CÔNG TÁC KHÁC OTHER WORKS | K20: =K98 -> #REF!
A21: N | B21: =B102 -> CÔNG TÁC BỔ SUNG TỪ NHÀ THẦU ADDITIONAL WORK FROM THE CONTRACTOR | K21: =K102 -> 0
A23: *** | B23: WC,Bảo Trì, Chứa Rác TOILET, MAINTENANCE, GARBAGE STORAGE | K23: =SUBTOTAL(9,K107:K347) -> 0 | M23: Profit | O23: 1.18
A24: B | B24: CÔNG TÁC ĐẤT EARTHWORK | K24: =SUBTOTAL(9,K25:K33) -> #REF!
A25: =IF(ISBLANK(E25),"",COUNTA($E$23:E25)) -> 1 | B25: Đào đất hố móng, đường ống, khuôn đường Excavation of foundation pits, pipes, road molds | E25: m3 | F25: =(2*2.6*2.6*1.85+3*2.2*2.2*1.85+2.6*1.9*1.85+2*2*2*1.85+2*2.4*1.7*1.85)*1.3 -> 118.1817 | G25: =M25*$O$23 -> #REF! | H25: =N25*$O$23 -> #REF! | J25: =+G25+H25+I25 -> #REF! | K25: =J25*$F25 -> #REF! | M25: ='05 Nhà Ăn'!R24 -> #REF! | N25: ='05 Nhà Ăn'!S24 -> #REF!
A26: =IF(ISBLANK(E26),"",COUNTA($E$23:E26)) -> 2 | B26: Đào đất đà kiềng, nền nhà Digging up the land and the foundation of the house | E26: m3 | F26: =((18*2+5.6*5)*0.4*0.25+(3.7*3)*0.4*0.25+4*0.3*0.25)*1.3 -> 10.153 | G26: =M26*$O$23 -> #REF! | H26: =N26*$O$23 -> #REF! | J26: =+G26+H26+I26 -> #REF! | K26: =J26*$F26 -> #REF! | M26: ='05 Nhà Ăn'!R29 -> #REF! | N26: ='05 Nhà Ăn'!S29 -> #REF!
A27: =IF(ISBLANK(E27),"",COUNTA($E$23:E27)) -> 3 | B27: Đắp đất móng đầm chặt Compacting the foundation | E27: m3 | F27: =(F25/1.3-F35-F37-F38-F41/3-F36-F39/2)*1.2 -> 82.3656 | G27: =M27*$O$23 -> #REF! | H27: =N27*$O$23 -> #REF! | J27: =+G27+H27+I27 -> #REF! | K27: =J27*$F27 -> #REF! | M27: ='05 Nhà Ăn'!R33 -> #REF! | N27: ='05 Nhà Ăn'!S33 -> #REF!
A28: =IF(ISBLANK(E28),"",COUNTA($E$23:E28)) -> 4 | B28: Vận chuyển đất ra ngoài phạm vi công trình Transporting land outside the scope of the project | E28: m3 | F28: =F25+F26-F27 -> 45.9691 | G28: =M28*$O$23 -> #REF! | H28: =N28*$O$23 -> #REF! | J28: =+G28+H28+I28 -> #REF! | K28: =J28*$F28 -> #REF! | M28: ='05 Nhà Ăn'!R35 -> #REF! | N28: ='05 Nhà Ăn'!S35 -> #REF!
A29: =IF(ISBLANK(E29),"",COUNTA($E$23:E29)) -> 5 | B29: Đầm chặt đất nền, K>=92 Compacting the soil, K>=92 | E29: m2 | F29: =5.6*17 -> 95.2 | G29: =M29*$O$23 -> #REF! | H29: =N29*$O$23 -> #REF! | J29: =+G29+H29+I29 -> #REF! | K29: =J29*$F29 -> #REF! | M29: ='05 Nhà Ăn'!R36 -> #REF! | N29: ='05 Nhà Ăn'!S36 -> #REF!
A30: =IF(ISBLANK(E30),"",COUNTA($E$23:E30)) -> 6 | B30: Đầm chặt và xử lý đất đáy đà kiềng, bó vỉa Compacting and treating the soil at the bottom of the dam, bundling the pavement | E30: m2 | F30: =(18*2+5.6*5)*0.4+(3.7*3)*0.4+4*0.3 -> 31.24 | G30: =M30*$O$23 -> #REF! | H30: =N30*$O$23 -> #REF! | J30: =+G30+H30+I30 -> #REF! | K30: =J30*$F30 -> #REF! | M30: ='05 Nhà Ăn'!R36 -> #REF! | N30: ='05 Nhà Ăn'!S36 -> #REF!
A31: =IF(ISBLANK(E31),"",COUNTA($E$23:E31)) -> 7 | B31: Lớp đá cấp phối 0x4, đầm chặt K92 Mixed-grade rock layer 0x4, compacting K92 | E31: m3 | F31: =F29*0.15*1.3 -> 18.564 | G31: =M31*$O$23 -> #REF! | H31: =N31*$O$23 -> #REF! | J31: =+G31+H31+I31 -> #REF! | K31: =J31*$F31 -> #REF! | M31: ='05 Nhà Ăn'!R42 -> #REF! | N31: ='05 Nhà Ăn'!S42 -> #REF!
A32: =IF(ISBLANK(E32),"",COUNTA($E$23:E32)) -> 8 | B32: Lớp PE, dày 0.3mm PE layer, 0.3mm thick | E32: m2 | F32: =F29 -> 95.2 | G32: =M32*$O$23 -> #REF! | H32: =N32*$O$23 -> #REF! | J32: =+G32+H32+I32 -> #REF! | K32: =J32*$F32 -> #REF! | M32: ='05 Nhà Ăn'!R41 -> #REF! | N32: ='05 Nhà Ăn'!S41 -> #REF!
A34: C | B34: CÔNG TÁC BÊ TÔNG CONCRETE WORK | D34: Hồng Tín, Hồng Hà, Đại Lộc Phát, HDH Hong Tin, Hong Ha, Dai Loc Phat, HDH | K34: =SUBTOTAL(9,K35:K43) -> #REF!
A35: =IF(ISBLANK(E35),"",COUNTA($E$23:E35)) -> 9 | B35: Bê tông lót móng đá 1x2 M150 Concrete lined with stone 1x2 M150 | E35: m3 | F35: =2*2.6*2.6*0.05+3*2.2*2.2*0.05+2.6*1.9*0.05+2*2*2*0.05+2*2.4*1.7*0.05 -> 2.457 | G35: =M35*$O$23 -> #REF! | H35: =N35*$O$23 -> #REF! | J35: =+G35+H35+I35 -> #REF! | K35: =J35*$F35 -> #REF! | M35: ='05 Nhà Ăn'!R44 -> #REF! | N35: ='05 Nhà Ăn'!S44 -> #REF!
A36: =IF(ISBLANK(E36),"",COUNTA($E$23:E36)) -> 10 | B36: Bê tông lót đá đà kiềng 1x2 M150 Concrete lined with stone 1x2 M150 | E36: m3 | F36: =(18*2+5.6*5)*0.4*0.05+(3.7*3)*0.4*0.05+4*0.3*0.05 -> 1.562 | G36: =M36*$O$23 -> #REF! | H36: =N36*$O$23 -> #REF! | J36: =+G36+H36+I36 -> #REF! | K36: =J36*$F36 -> #REF! | M36: ='05 Nhà Ăn'!R49 -> #REF! | N36: ='05 Nhà Ăn'!S49 -> #REF!
A37: =IF(ISBLANK(E37),"",COUNTA($E$23:E37)) -> 11 | B37: Bê tông móng đá 1x2 M250 Stone foundation concrete 1x2 M250 | E37: m3 | F37: =2*(2.4*2.4*0.25)+3*(2*2*0.2)+(2.4*1.8*0.25)+2*(1.8*1.8*0.2)+2*(2.2*1.6*0.2) -> 9.064 | G37: =M37*$O$23 -> #REF! | H37: =N37*$O$23 -> #REF! | J37: =+G37+H37+I37 -> #REF! | K37: =J37*$F37 -> #REF! | M37: ='05 Nhà Ăn'!R53 -> #REF! | N37: ='05 Nhà Ăn'!S53 -> #REF!
A38: =IF(ISBLANK(E38),"",COUNTA($E$23:E38)) -> 12 | B38: Bê tông cổ móng đá 1x2 M250 Stone foundation neck concrete 1x2 M250 | E38: m3 | F38: =F37/2 -> 4.532 | G38: =M38*$O$23 -> #REF! | H38: =N38*$O$23 -> #REF! | J38: =+G38+H38+I38 -> #REF! | K38: =J38*$F38 -> #REF! | M38: =M37 -> #REF! | N38: =N37 -> #REF!
A39: =IF(ISBLANK(E39),"",COUNTA($E$23:E39)) -> 13 | B39: Bê tông đà kiềng đá 1x2 M300 1x2 M300 Stone Concrete | E39: m3 | F39: =(18*2+5.6*5+3.7*3)*0.2*0.4+4*0.1*0.3 -> 6.128 | G39: =M39*$O$23 -> #REF! | H39: =N39*$O$23 -> #REF! | J39: =+G39+H39+I39 -> #REF! | K39: =J39*$F39 -> #REF! | M39: =M38 -> #REF! | N39: =N38 -> #REF!
A40: =IF(ISBLANK(E40),"",COUNTA($E$23:E40)) -> 14 | B40: Bê tông nền đá 1x2 M250 concrete Ground slab 1x2 M250 | E40: m3 | F40: =17*5.6*0.1 -> 9.52 | G40: =M40*$O$23 -> #REF! | H40: =N40*$O$23 -> #REF! | J40: =+G40+H40+I40 -> #REF! | K40: =J40*$F40 -> #REF! | M40: =M39 -> #REF! | N40: =N39 -> #REF!
A41: =IF(ISBLANK(E41),"",COUNTA($E$23:E41)) -> 15 | B41: Bê tông cột đá 1x2 M250 1x2 M250 Stone Pillar Concrete | E41: m3 | F41: =8*(1+7.6)*0.2*0.3+2*(4.4+1)*0.2*0.3 -> 4.776 | G41: =M41*$O$23 -> #REF! | H41: =N41*$O$23 -> #REF! | J41: =+G41+H41+I41 -> #REF! | K41: =J41*$F41 -> #REF! | M41: =M40 -> #REF! | N41: =N40 -> #REF!
A42: =IF(ISBLANK(E42),"",COUNTA($E$23:E42)) -> 16 | B42: Bê tông dầm sàn đá 1x2 M250 Concrete floors,stone 1x2 M250 | E42: m3 | F42: =(5.4*5.4*0.12)+(3.7*5.6*0.1)+((18*2+5.6*5)*0.2*0.4)+(1.6*0.1*6)+(14.1*7*0.1)+((14*2+7*2+5.6*4)*0.2*0.4)+((13.7+5.6)*0.2*0.2)+(13.1*1.6*0.1) -> 29.5412 | G42: =M42*$O$23 -> #REF! | H42: =N42*$O$23 -> #REF! | J42: =+G42+H42+I42 -> #REF! | K42: =J42*$F42 -> #REF! | M42: =M41 -> #REF! | N42: =N41 -> #REF!
A44: D | B44: CÔNG TÁC VÁN KHUÔN FORMWORK | K44: =SUBTOTAL(9,K45:K51) -> #REF!
A45: =IF(ISBLANK(E45),"",COUNTA($E$23:E45)) -> 17 | B45: Ván khuôn lót móng Foundation Liner Formwork | E45: m2 | F45: =2*2.6*4*0.05+3*2.2*4*0.05+(2.6+1.9)*2*0.05+2*4*2*0.05+2*(2.4+1.7)*2*0.05 -> 4.43 | G45: =M45*$O$23 -> #REF! | H45: =N45*$O$23 -> #REF! | J45: =+G45+H45+I45 -> #REF! | K45: =J45*$F45 -> #REF! | M45: ='05 Nhà Ăn'!R89 -> #REF! | N45: ='05 Nhà Ăn'!S89 -> #REF!
A46: =IF(ISBLANK(E46),"",COUNTA($E$23:E46)) -> 18 | B46: Ván khuôn lót đà kiềng Formwork lined with shackles | E46: m2 | F46: =(18*2+5.6*5)*0.4*0.05+(3.7*3)*0.4*0.05+4*0.3*0.05 -> 1.562 | G46: =M46*$O$23 -> #REF! | H46: =N46*$O$23 -> #REF! | J46: =+G46+H46+I46 -> #REF! | K46: =J46*$F46 -> #REF! | M46: =M45 -> #REF! | N46: =N45 -> #REF!
A47: =IF(ISBLANK(E47),"",COUNTA($E$23:E47)) -> 19 | B47: Ván khuôn móng Foundation Formwork | E47: m2 | F47: =2*(2.4*2.4*0.25)+3*(2*2*0.2)+(2.4*1.8*0.25)+2*(1.8*1.8*0.2)+2*(2.2*1.6*0.2) -> 9.064 | G47: =M47*$O$23 -> #REF! | H47: =N47*$O$23 -> #REF! | J47: =+G47+H47+I47 -> #REF! | K47: =J47*$F47 -> #REF! | M47: =M46 -> #REF! | N47: =N46 -> #REF!
A48: =IF(ISBLANK(E48),"",COUNTA($E$23:E48)) -> 20 | B48: Ván khuôn đà kiềng Formwork Beams | E48: m2 | F48: =(18*2+5.6*5+3.7*3)*2*0.4+4*2*0.3 -> 62.48 | G48: =M48*$O$23 -> #REF! | H48: =N48*$O$23 -> #REF! | J48: =+G48+H48+I48 -> #REF! | K48: =J48*$F48 -> #REF! | M48: =M47 -> #REF! | N48: =N47 -> #REF!
A49: =IF(ISBLANK(E49),"",COUNTA($E$23:E49)) -> 21 | B49: Ván khuôn cột Column Formwork | E49: m2 | F49: =8*(1+7.6)*2*(0.2+0.3)+2*(4.4+1)*2*(0.2+0.3) -> 79.6 | G49: =M49*$O$23 -> #REF! | H49: =N49*$O$23 -> #REF! | J49: =+G49+H49+I49 -> #REF! | K49: =J49*$F49 -> #REF! | M49: =M48 -> #REF! | N49: =N48 -> #REF!
A50: =IF(ISBLANK(E50),"",COUNTA($E$23:E50)) -> 22 | B50: Ván khuôn dầm sàn Floor Formwork | E50: m2 | F50: =((5.4*5.4)+(3.7*5.6)+(1.6+1.4)*6+(18*2+5.6*5)*0.8)+((5.4*13.1)+(13.8*2+6.5*2)*0.8+(7*0.9*2)+(13.7+5.6)*0.6) -> 246.48 | G50: =M50*$O$23 -> #REF! | H50: =N50*$O$23 -> #REF! | J50: =+G50+H50+I50 -> #REF! | K50: =J50*$F50 -> #REF! | M50: =M49 -> #REF! | N50: =N49 -> #REF!
A52: E | B52: CÔNG TÁC CỐT THÉP REBAR WORK | K52: =SUBTOTAL(9,K53:K58) -> #REF!
A53: =IF(ISBLANK(E53),"",COUNTA($E$23:E53)) -> 23 | B53: Cốt thép móng Reinforcement for foundations. | E53: kg | F53: =F37*35 -> 317.24 | G53: =M53*$O$23 -> #REF! | H53: =N53*$O$23 -> #REF! | J53: =+G53+H53+I53 -> #REF! | K53: =J53*$F53 -> #REF! | M53: ='05 Nhà Ăn'!R122 -> #REF! | N53: ='05 Nhà Ăn'!S122 -> #REF!
A54: =IF(ISBLANK(E54),"",COUNTA($E$23:E54)) -> 24 | B54: Cốt thép cột Column reinforcement | E54: kg | F54: =F41*145 -> 692.52 | G54: =M54*$O$23 -> #REF! | H54: =N54*$O$23 -> #REF! | J54: =+G54+H54+I54 -> #REF! | K54: =J54*$F54 -> #REF! | M54: =M53 -> #REF! | N54: =N53 -> #REF!
A55: =IF(ISBLANK(E55),"",COUNTA($E$23:E55)) -> 25 | B55: Cốt thép đà kiềng Reinforcement tie beam | E55: kg | F55: =F39*145 -> 888.56 | G55: =M55*$O$23 -> #REF! | H55: =N55*$O$23 -> #REF! | J55: =+G55+H55+I55 -> #REF! | K55: =J55*$F55 -> #REF! | M55: =M54 -> #REF! | N55: =N54 -> #REF!
A56: =IF(ISBLANK(E56),"",COUNTA($E$23:E56)) -> 26 | B56: Cốt thép sàn (thép lưới hàn) Reinforcement for slabs(welded mesh) | E56: kg | F56: =5.6*17*12*0.222 -> 253.6128 | G56: =M56*$O$23 -> #REF! | H56: =N56*$O$23 -> #REF! | J56: =+G56+H56+I56 -> #REF! | K56: =J56*$F56 -> #REF! | M56: =M55 -> #REF! | N56: =N55 -> #REF!
A57: =IF(ISBLANK(E57),"",COUNTA($E$23:E57)) -> 27 | B57: Cốt thép dầm sàn, đường kính <=18 Reinforcement beams and floors, diameter <=18 | E57: kg | F57: =F42*145 -> 4283.474 | G57: =M57*$O$23 -> #REF! | H57: =N57*$O$23 -> #REF! | J57: =+G57+H57+I57 -> #REF! | K57: =J57*$F57 -> #REF! | M57: =M56 -> #REF! | N57: =N56 -> #REF!
A59: F | B59: CÔNG TÁC XÂY BRICK WALL | D59: - Cát : Campuchia, Dầu Tiếng, địa phương - Gạch tuynel địa phương (Bình Mỹ,…) - Xi măng : Hà Tiên, Fico | K59: =SUBTOTAL(9,K60:K66) -> #REF!
A60: =IF(ISBLANK(E60),"",COUNTA($E$23:E60)) -> 28 | B60: Tường xây gạch dày 200mm 200mm thick brick wall | C60: Vữa mác M75, Gạch xây mác >= M50, Gạch 04 lỗ chèn gạch 02 lỗ M75 grade mortar, Grade >= M50 masonry, 04 holes in bricks, 02 holes in brick inserts | E60: m2 | F60: =((17*2+5.6*3)*3.4-2*1.2*2.2-3*1.4*2.4-1.4*2.2-2*2.4*0.8)+((14.1*2+5.6*2)*3.2-4*1.8*2.4-2*1.8*0.8) -> 256.36 | G60: =M60*$O$23 -> #REF! | H60: =N60*$O$23 -> #REF! | J60: =+G60+H60+I60 -> #REF! | K60: =J60*$F60 -> #REF! | M60: ='05 Nhà Ăn'!R129 -> #REF! | N60: ='05 Nhà Ăn'!S129 -> #REF!
A61: =IF(ISBLANK(E61),"",COUNTA($E$23:E61)) -> 29 | B61: Tường xây gạch dày 100mm 100mm thick brick masonry wall | C61: Vữa mác M75, Gạch xây mác >= M50, Gạch 04 lỗ chèn gạch 02 lỗ M75 grade mortar, Grade >= M50 masonry, 04 holes in bricks, 02 holes in brick inserts | E61: m2 | F61: =((5.6*3+3+3.7*2+0.4)*3.4)-1.2*2.3-2*0.9*2.3 -> 86.94 | G61: =M61*$O$23 -> #REF! | H61: =N61*$O$23 -> #REF! | J61: =+G61+H61+I61 -> #REF! | K61: =J61*$F61 -> #REF! | M61: ='05 Nhà Ăn'!R143 -> #REF! | N61: ='05 Nhà Ăn'!S143 -> #REF!
A62: =IF(ISBLANK(E62),"",COUNTA($E$23:E62)) -> 30 | B62: GCLD bổ trụ 200x200, 4D12, D6@150 GCLD bổ trụ 200x200, 4D12, D6@150 | E62: md | F62: =6*3.4+6*3.2 -> 39.6 | G62: =M62*$O$23 -> #REF! | H62: =N62*$O$23 -> #REF! | J62: =+G62+H62+I62 -> #REF! | K62: =J62*$F62 -> #REF! | M62: ='05 Nhà Ăn'!R150 -> #REF! | N62: ='05 Nhà Ăn'!S150 -> #REF!
A63: =IF(ISBLANK(E63),"",COUNTA($E$23:E63)) -> 31 | B63: GCLD lanh tô 200x200, 4D10, D6@150 Linen 200x200, 4D10, D6@150 | E63: md | F63: =4.8+5.6+2.8 -> 13.2 | G63: =M63*$O$23 -> #REF! | H63: =N63*$O$23 -> #REF! | J63: =+G63+H63+I63 -> #REF! | K63: =J63*$F63 -> #REF! | M63: =M62 -> #REF! | N63: =N62 -> #REF!
B64: GCLD lanh tô 200x200+lam chắn nước rộng, 4D10, D6@150 Linen 200x200, 4D10, D6@150 + wide water barrier | E64: md | F64: =1.4+2.8+5.2+1.5+1.8 -> 12.7 | G64: =M64*$O$23 -> #REF! | H64: =N64*$O$23 -> #REF! | J64: =+G64+H64+I64 -> #REF! | K64: =J64*$F64 -> #REF! | M64: =M63 -> #REF! | N64: =N63 -> #REF!
A65: =IF(ISBLANK(E65),"",COUNTA($E$23:E65)) -> 33 | B65: Lanh tô, đà giằng, bổ trụ kt 100x200mm Linen, bracing, reinforcement kt 100x200mm | E65: md | F65: =6*2.4+14.1+7*2+1.6+1.3*2 -> 46.7 | G65: =M65*$O$23 -> #REF! | H65: =N65*$O$23 -> #REF! | J65: =+G65+H65+I65 -> #REF! | K65: =J65*$F65 -> #REF! | M65: ='05 Nhà Ăn'!R152 -> #REF! | N65: ='05 Nhà Ăn'!S152 -> #REF!
A67: G | B67: CÔNG TÁC TÔ TRÁT PLASTERING WORK | D67: - Cát : Campuchia, Dầu Tiếng, địa phương - Xi măng : Hà Tiên, Fico - Cat : Cambodia, Dau Tieng, local - Cement: Ha Tien, Fico | K67: =SUBTOTAL(9,K68:K72) -> #REF!
A68: =IF(ISBLANK(E68),"",COUNTA($E$23:E68)) -> 34 | B68: Trát tường ngoài, vữa M75 dày 2.0cm Plastering of exterior walls, M75 mortar 2.0cm thick | E68: m2 | F68: =F60-5.6*3.4 -> 237.32 | G68: =M68*$O$23 -> #REF! | H68: =N68*$O$23 -> #REF! | J68: =+G68+H68+I68 -> #REF! | K68: =J68*$F68 -> #REF! | M68: ='05 Nhà Ăn'!R155 -> #REF! | N68: ='05 Nhà Ăn'!S155 -> #REF!
A69: =IF(ISBLANK(E69),"",COUNTA($E$23:E69)) -> 35 | B69: Trát tường trong vữa M75 dày 1.5cm Wall plaster in M75 mortar 1.5cm thick | E69: m2 | F69: =F60+F61*2 -> 430.24 | G69: =M69*$O$23 -> #REF! | H69: =N69*$O$23 -> #REF! | J69: =+G69+H69+I69 -> #REF! | K69: =J69*$F69 -> #REF! | M69: ='05 Nhà Ăn'!R161 -> #REF! | N69: ='05 Nhà Ăn'!S161 -> #REF!
A70: =IF(ISBLANK(E70),"",COUNTA($E$23:E70)) -> 36 | B70: Trát cấu kiện đặc biệt vữa M75 dày 1.5cm (Cột, dầm, trần, thang…) Special structural plaster of M75 mortar with a thickness of 1.5cm (Columns, beams, ceilings, ladders...) | E70: m2 | F70: =7*10*0.6+(18*2+6*2)*0.4+(14+6)*2.4+(14+6*2)*0.5+(5.6+1.5+2.8)*0.5+(1.8+1.6)*2.1 -> 134.29 | G70: =M70*$O$23 -> #REF! | H70: =N70*$O$23 -> #REF! | J70: =+G70+H70+I70 -> #REF! | K70: =J70*$F70 -> #REF! | M70: =M69 -> #REF! | N70: =N69 -> #REF!
A71: =IF(ISBLANK(E71),"",COUNTA($E$23:E71)) -> 37 | B71: Trát má cửa, vữa M75 dày 1.5cm Door plaster, M75 mortar 1.5cm thick | E71: md | F71: =(2.4*2+1.2)+(2.4*2+1.4)*3+(0.9+2.2*2)*2+(1.2+2.2*2)*2+(5*2+4)+(2.4+0.6)*2*4+(1.6+2.4)*2*2+(1.8+0.6)*2*2 -> 110 | G71: =M71*$O$23 -> #REF! | H71: =N71*$O$23 -> #REF! | J71: =+G71+H71+I71 -> #REF! | K71: =J71*$F71 -> #REF! | M71: ='05 Nhà Ăn'!R162 -> #REF! | N71: ='05 Nhà Ăn'!S162 -> #REF!
A73: H | B73: CÔNG TÁC SƠN PAINTING WORK | K73: =SUBTOTAL(9,K74:K76) -> #REF!
A74: =IF(ISBLANK(E74),"",COUNTA($E$23:E74)) -> 38 | B74: Sơn dầm, trần, cột, tường trong nhà 1 nước lót + 2 nước phủ Paint beams, ceilings, columns, and walls in the house with 1 primer + 2 coatings | E74: m2 | F74: =F69-(5.6*4*3.4)+(5.6*5.6)+18.6*6.6 -> 508.2 | G74: =M74*$O$23 -> #REF! | H74: =N74*$O$23 -> #REF! | J74: =+G74+H74+I74 -> #REF! | K74: =J74*$F74 -> #REF! | M74: ='05 Nhà Ăn'!R172 -> #REF! | N74: ='05 Nhà Ăn'!S172 -> #REF!
A75: =IF(ISBLANK(E75),"",COUNTA($E$23:E75)) -> 39 | B75: Sơn tường ngoài nhà 1 nước lót + 2 nước phủ Painting the walls outside the house with 1 primer + 2 coatings | E75: m2 | F75: =F68+F70+F71*0.2 -> 393.61 | G75: =M75*$O$23 -> #REF! | H75: =N75*$O$23 -> #REF! | J75: =+G75+H75+I75 -> #REF! | K75: =J75*$F75 -> #REF! | M75: ='05 Nhà Ăn'!R173 -> #REF! | N75: ='05 Nhà Ăn'!S173 -> #REF!
A77: I | B77: CÔNG TÁC CHỐNG THẤM WATERPROOFING WORK | K77: =SUBTOTAL(9,K78:K79) -> #REF!
A78: =IF(ISBLANK(E78),"",COUNTA($E$23:E78)) -> 40 | B78: Quét chống thấm sika top seal 109, 2 lớp (định mức 1.5kg/m2/lớp) Sweep top seal 109, 2 layers (rated 1.5kg/m2/layer) | E78: m2 | F78: =4.4*2.2 -> 9.68 | G78: =M78*$O$23 -> #REF! | H78: =N78*$O$23 -> #REF! | J78: =+G78+H78+I78 -> #REF! | K78: =J78*$F78 -> #REF! | M78: ='05 Nhà Ăn'!R178 -> #REF! | N78: ='05 Nhà Ăn'!S178 -> #REF!
A79: =IF(ISBLANK(E79),"",COUNTA($E$23:E79)) -> 41 | B79: Chống thấm PU có lưới sợi thủy tinh dày 1.2mm PU waterproofing with 1.2mm thick fiberglass mesh | C79: 0 | E79: m2 | F79: =(7+0.8)*14.4+5*7.8 -> 151.32 | G79: =M79*$O$23 -> #REF! | H79: =N79*$O$23 -> #REF! | J79: =+G79+H79+I79 -> #REF! | K79: =J79*$F79 -> #REF! | M79: ='05 Nhà Ăn'!R177 -> #REF! | N79: ='05 Nhà Ăn'!S177 -> #REF!
A80: J | B80: CÔNG TÁC HOÀN THIỆN NỀN SÀN FLOOR FINISHING WORK | K80: =SUBTOTAL(9,K81:K82) -> #REF! | P80: =SUBTOTAL(9,P81:P99) -> 0 | S80: 0
A81: =IF(ISBLANK(E81),"",COUNTA($E$23:E81)) -> 42 | B81: Ốp gạch tường gạch Ceramic 300x600 Ceramic Wall Tiles 300x600 | E81: m2 | F81: =5.6*4*1.8-0.9*2.2*2 -> 36.36 | G81: =M81*$O$23 -> #REF! | H81: =N81*$O$23 -> #REF! | J81: =+G81+H81+I81 -> #REF! | K81: =J81*$F81 -> #REF! | M81: ='05 Nhà Ăn'!R190 -> #REF! | N81: ='05 Nhà Ăn'!S190 -> #REF!
A82: =IF(ISBLANK(E82),"",COUNTA($E$23:E82)) -> 43 | B82: Lát gạch nền gạch Ceramic nhám 600x600 chống trơn, bao gồm vữa láng M75 dày 20mm Installation of 600x600 non-slip ceramic floor tiles, including 20mm thick M75 screed | E82: m2 | F82: =5.6*5.5 -> 30.8 | G82: =M82*$O$23 -> #REF! | H82: =N82*$O$23 -> #REF! | J82: =+G82+H82+I82 -> #REF! | K82: =J82*$F82 -> #REF! | M82: ='05 Nhà Ăn'!R184 -> #REF! | N82: ='05 Nhà Ăn'!S184 -> #REF!
A83: =IF(ISBLANK(E83),"",MAX($A$23:A79)+1) | J83: =+G83+H83 -> 0 | K83: =J83*$F83 -> 0
A84: J | B84: CÔNG TÁC TRẦN VÁCH CEILING & PARTITION WORKS | K84: =SUBTOTAL(9,K85:K87) -> #REF!
A85: =IF(ISBLANK(E85),"",COUNTA($E$23:E85)) -> 44 | B85: Đóng trần thạch cao khung xương nổi chống ẩm 600x600 (bao gồm hệ khung treo) Installing 600x600mm moisture-resistant exposed-frame gypsum ceilings (including suspension system) | E85: m2 | F85: =5.6*5.6 -> 31.36 | G85: =M85*$O$23 -> #REF! | H85: =N85*$O$23 -> #REF! | J85: =+G85+H85+I85 -> #REF! | K85: =J85*$F85 -> #REF! | M85: ='05 Nhà Ăn'!R201 -> #REF! | N85: ='05 Nhà Ăn'!S201 -> #REF!
A86: =IF(ISBLANK(E86),"",COUNTA($E$23:E86)) -> 45 | B86: Cung cấp lắp đặt vách ngăn compact tấm dày 12mm, vách ngăn bồn tiểu Supplying and installing 12mm thick compact, urinal partitions with doors | E86: m2 | F86: =5*1.5*2+3*0.5*1+(3.6*2+1.2)*2 -> 33.3 | G86: =M86*$O$23 -> #REF! | H86: =N86*$O$23 -> #REF! | J86: =+G86+H86+I86 -> #REF! | K86: =J86*$F86 -> #REF! | M86: ='01 Nhà Xưởng 01+02'!#REF! -> #REF! | N86: ='01 Nhà Xưởng 01+02'!#REF! -> #REF!
A87: =IF(ISBLANK(E87),"",COUNTA($E$23:E87)) | J87: =+G87+H87+I87 -> 0 | K87: =J87*$F87 -> 0
A88: K | B88: CÔNG TÁC CỬA DOOR WORK | K88: =SUBTOTAL(9,K89:K97) -> 147141280
A89: =IF(ISBLANK(E89),"",COUNTA($E$23:E89)) -> 46 | B89: Cửa Sắt D1 - 900x2200 | E89: bộ | F89: 1 | G89: =M89*$O$23 -> 7327800 | H89: =N89*$O$23 -> 814200 | J89: =+G89+H89+I89 -> 8142000 | K89: =J89*$F89 -> 8142000 | M89: =O89*0.9 -> 6210000 | N89: =O89*0.1 -> 690000 | O89: 6900000
A90: =IF(ISBLANK(E90),"",COUNTA($E$23:E90)) -> 47 | B90: Cửa Sắt D2 - 1400x2400 | E90: bộ | F90: 3 | G90: =M90*$O$23 -> 8389800 | H90: =N90*$O$23 -> 932200 | J90: =+G90+H90+I90 -> 9322000 | K90: =J90*$F90 -> 27966000 | M90: =O90*0.9 -> 7110000 | N90: =O90*0.1 -> 790000 | O90: 7900000
A91: =IF(ISBLANK(E91),"",COUNTA($E$23:E91)) -> 48 | B91: Cửa Nhôm D3 - 900x2200 | E91: bộ | F91: 2 | G91: =M91*$O$23 -> 4248000 | H91: =N91*$O$23 -> 472000 | J91: =+G91+H91+I91 -> 4720000 | K91: =J91*$F91 -> 9440000 | M91: =O91*0.9 -> 3600000 | N91: =O91*0.1 -> 400000 | O91: 4000000
A92: =IF(ISBLANK(E92),"",COUNTA($E$23:E92)) -> 49 | B92: Cửa sắt D4 - 1200x2200 | E92: bộ | F92: 2 | G92: =M92*$O$23 -> 7965000 | H92: =N92*$O$23 -> 885000 | J92: =+G92+H92+I92 -> 8850000 | K92: =J92*$F92 -> 17700000 | M92: =O92*0.9 -> 6750000 | N92: =O92*0.1 -> 750000 | O92: 7500000
A93: =IF(ISBLANK(E93),"",COUNTA($E$23:E93)) -> 50 | B93: Cửa cuốn D5 - 4000x5000 | E93: bộ | F93: 1 | G93: =M93*$O$23 -> 39294000 | H93: =N93*$O$23 -> 4366000 | J93: =+G93+H93+I93 -> 43660000 | K93: =J93*$F93 -> 43660000 | M93: =O93*0.9 -> 33300000 | N93: =O93*0.1 -> 3700000 | O93: 37000000
A94: =IF(ISBLANK(E94),"",COUNTA($E$23:E94)) -> 51 | B94: L1 - 2400x600 | E94: m2 | F94: =4*2.4*0.6 -> 5.76 | G94: =M94*$O$23 -> 2230200 | H94: =N94*$O$23 -> 247800 | J94: =+G94+H94+I94 -> 2478000 | K94: =J94*$F94 -> 14273280 | M94: =O94*0.9 -> 1890000 | N94: =O94*0.1 -> 210000 | O94: 2100000
A95: =IF(ISBLANK(E95),"",COUNTA($E$23:E95)) -> 52 | B95: S1 - 2600x2400 | E95: bộ | F95: 2 | G95: =M95*$O$23 -> 7434000 | H95: =N95*$O$23 -> 826000 | J95: =+G95+H95+I95 -> 8260000 | K95: =J95*$F95 -> 16520000 | M95: =O95*0.9 -> 6300000 | N95: =O95*0.1 -> 700000 | O95: 7000000
A96: =IF(ISBLANK(E96),"",COUNTA($E$23:E96)) -> 53 | B96: S2 - 600x1800 | E96: bộ | F96: 2 | G96: =M96*$O$23 -> 4248000 | H96: =N96*$O$23 -> 472000 | J96: =+G96+H96+I96 -> 4720000 | K96: =J96*$F96 -> 9440000 | M96: =O96*0.9 -> 3600000 | N96: =O96*0.1 -> 400000 | O96: 4000000
A97: =IF(ISBLANK(E97),"",MAX($A$23:A88)+1) | J97: =+G97+H97 -> 0 | K97: =J97*$F97 -> 0
A98: L | B98: CÔNG TÁC KHÁC OTHER WORKS | K98: =SUBTOTAL(9,K99:K99) -> #REF!
A99: =IF(ISBLANK(E99),"",COUNTA($E$23:E99)) -> 54 | B99: Cầu chắn rác sê nô D90 Seno garbage barrier bridge D90 | E99: Cái | F99: 3 | G99: =M99*$O$23 -> #REF! | H99: =N99*$O$23 -> 0 | J99: =+G99+H99+I99 -> #REF! | K99: =J99*$F99 -> #REF! | M99: ='05 Nhà Ăn'!R215 -> #REF!
A101: =IF(ISBLANK(E101),"",MAX($A$23:A99)+1) | J101: =+G101+H101 -> 0 | K101: =J101*$F101 -> 0
A102: M | B102: CÔNG TÁC BỔ SUNG TỪ NHÀ THẦU ADDITIONAL WORK FROM THE CONTRACTOR | K102: =SUBTOTAL(9,K103:K106) -> 0
A103: =IF(ISBLANK(E103),"",MAX($A$23:A102)+1) | J103: =+G103+H103+I103 -> 0 | K103: =J103*$F103 -> 0
A104: =IF(ISBLANK(E104),"",MAX($A$23:A103)+1) | J104: =+G104+H104+I104 -> 0 | K104: =J104*$F104 -> 0
A105: =IF(ISBLANK(E105),"",MAX($A$23:A104)+1) | J105: =+G105+H105+I105 -> 0 | K105: =J105*$F105 -> 0
A106: =IF(ISBLANK(E106),"",MAX($A$23:A105)+1) | J106: =+G106+H106+I106 -> 0 | K106: =J106*$F106 -> 0
A107: =A122 -> 0 | B107: =B122 -> 0 | K107: =SUBTOTAL(9,K108:K121) -> 0 | M107: Profit | O107: 10067532

Sheet 07 Trạm Điện
A1: BẢNG DỰ TOÁN BÁO GIÁ CÔNG TRÌNH / ESTIMATE TABLE
A2: ="DỰ ÁN / PROJECT : "&[6]COVER!K10 -> DỰ ÁN / PROJECT : AN KHANG FOODS JSC
A3: ="HẠNG MỤC / ITEM : "&B8 -> HẠNG MỤC / ITEM : TRẠM ĐIỆN / POWER STATION
A4: ="CHỦ ĐẦU TƯ / : "&[6]COVER!K19 -> CHỦ ĐẦU TƯ / : AN KHANG FOODS JSC
A6: STT NO. | B6: TÊN CÔNG VIỆC VÀ DIỄN GIẢI DESCRIPTION | C6: ĐẶC TÍNH KỸ THUẬT STANDARD | D6: NHÃN HIỆU & XUẤT XỨ BRAND NAME & ORIGIN | E6: Đvt Unit | F6: KL TỔNG Q'TY | G6: ĐƠN GIÁ / RATE | J6: TỔNG CỘNG (VNĐ) TOTAL COST(VND) | L6: REMARK GHI CHÚ | M6: VẬT TƯ RATE MATERIALS | N6: NHÂN CÔNG RATE LABOUR
G7: VẬT TƯ RATE MATERIALS | H7: NHÂN CÔNG RATE LABOUR | I7: MMTB RATE EQUIPMENT | J7: ĐƠN GIÁ TỔNG TOTAL PRICE | K7: THÀNH TIỀN AMOUNT TOTAL
A8: =A17 -> *** | B8: =B17 -> TRẠM ĐIỆN / POWER STATION | K8: =SUBTOTAL(9,K9:K16) -> #REF!
A9: A | B9: CÔNG TÁC CỌC PILE WORK | K9: =K18 -> 0
A10: B | B10: CÔNG TÁC ĐẤT EARTHWORK | K10: =K25 -> #REF!
A11: C | B11: CÔNG TÁC BÊ TÔNG CONCRETE WORK | K11: =K36 -> #REF!
A12: D | B12: CÔNG TÁC VÁN KHUÔN FORMWORK | K12: =K46 -> #REF!
A13: E | B13: CÔNG TÁC CỐT THÉP REBAR WORK | K13: =K52 -> #REF!
A14: K | B14: CÔNG TÁC CỬA DOOR WORKS | K14: =K58 -> 10384000
A15: L | B15: CÔNG TÁC KHÁC OTHER WORK | K15: =K67 -> 71272000
A17: *** | B17: TRẠM ĐIỆN / POWER STATION | K17: =SUBTOTAL(9,K77:K317) -> 0 | M17: Profit | O17: 1.18
A18: A | B18: CÔNG TÁC CỌC PILE WORK | K18: =SUBTOTAL(9,K19:K24) -> 0
A19: =IF(ISBLANK(E19),"",COUNTA($E$17:E19)) -> 1 | B19: Cung cấp và ép cọc ly tâm BTCT D300 Supply and pressing of D300 reinforced concrete centrifugal pile | E19: m | J19: =+G19+H19+I19 -> 0 | K19: =J19*$F19 -> 0
A20: =IF(ISBLANK(E20),"",COUNTA($E$17:E20)) -> 2 | B20: Ép âm cọc D300 D300 Pile Driver | E20: m | J20: =+G20+H20+I20 -> 0 | K20: =J20*$F20 -> 0
A21: =IF(ISBLANK(E21),"",COUNTA($E$17:E21)) -> 3 | B21: Nối cọc Pile connection | E21: mối/ join | J21: =+G21+H21+I21 -> 0 | K21: =J21*$F21 -> 0
A22: =IF(ISBLANK(E22),"",COUNTA($E$17:E22)) -> 4 | B22: Cắt đầu cọc Cutting the pile head | E22: cọc/pile | J22: =+G22+H22+I22 -> 0 | K22: =J22*$F22 -> 0
A23: =IF(ISBLANK(E23),"",COUNTA($E$17:E23)) -> 5 | B23: Thép tấm neo đầu cọc Pile Head Anchor Steel Plate | E23: kg | J23: =+G23+H23+I23 -> 0 | K23: =J23*$F23 -> 0
A25: B | B25: CÔNG TÁC ĐẤT EARTHWORK | K25: =SUBTOTAL(9,K26:K35) -> #REF!
A26: =IF(ISBLANK(E26),"",COUNTA($E$17:E26)) -> 6 | B26: Đào đất hố móng, đường ống, khuôn đường Excavation of foundation pits, pipes, road molds | E26: m3 | F26: =1.9*1.7*1.35*1.3 -> 5.66865 | G26: =M26*$O$17 -> #REF! | H26: =N26*$O$17 -> #REF! | J26: =+G26+H26+I26 -> #REF! | K26: =J26*$F26 -> #REF! | M26: ='06 WC,Bảo Trì, Chứa Rác '!M25 -> #REF! | N26: ='06 WC,Bảo Trì, Chứa Rác '!N25 -> #REF!
A27: =IF(ISBLANK(E27),"",COUNTA($E$17:E27)) -> 7 | B27: Đào đất đà kiềng Digging up the land | E27: m3 | F27: =(5+3.2)*2*0.1*0.4*1.3 -> 0.8528 | G27: =M27*$O$17 -> #REF! | H27: =N27*$O$17 -> #REF! | J27: =+G27+H27+I27 -> #REF! | K27: =J27*$F27 -> #REF! | M27: ='06 WC,Bảo Trì, Chứa Rác '!M26 -> #REF! | N27: ='06 WC,Bảo Trì, Chứa Rác '!N26 -> #REF!
A28: =IF(ISBLANK(E28),"",COUNTA($E$17:E28)) -> 8 | B28: Đắp đất móng đầm chặt Compacting the foundation | E28: m3 | F28: =(F26/1.3-(1.8*1.6*1.25+1.9*1.7*0.1))*1.2 -> 0.525 | G28: =M28*$O$17 -> #REF! | H28: =N28*$O$17 -> #REF! | J28: =+G28+H28+I28 -> #REF! | K28: =J28*$F28 -> #REF! | M28: ='06 WC,Bảo Trì, Chứa Rác '!M27 -> #REF! | N28: ='06 WC,Bảo Trì, Chứa Rác '!N27 -> #REF!
A29: =IF(ISBLANK(E29),"",COUNTA($E$17:E29)) -> 9 | B29: Vận chuyển đất ra ngoài phạm vi công trình Transporting land outside the scope of the project | E29: m3 | F29: =F26+F27-F28 -> 5.99645 | G29: =M29*$O$17 -> #REF! | H29: =N29*$O$17 -> #REF! | J29: =+G29+H29+I29 -> #REF! | K29: =J29*$F29 -> #REF! | M29: ='06 WC,Bảo Trì, Chứa Rác '!M28 -> #REF! | N29: ='06 WC,Bảo Trì, Chứa Rác '!N28 -> #REF!
A30: =IF(ISBLANK(E30),"",COUNTA($E$17:E30)) -> 10 | B30: Đầm chặt và xử lý đất đáy đà kiềng, bó vỉa Compacting and treating the soil at the bottom of the dam, bundling the pavement | E30: m2 | F30: =(5+3.2)*2*0.4 -> 6.56 | G30: =M30*$O$17 -> #REF! | H30: =N30*$O$17 -> #REF! | J30: =+G30+H30+I30 -> #REF! | K30: =J30*$F30 -> #REF! | M30: ='06 WC,Bảo Trì, Chứa Rác '!M29 -> #REF! | N30: ='06 WC,Bảo Trì, Chứa Rác '!N29 -> #REF!
A31: =IF(ISBLANK(E31),"",COUNTA($E$17:E31)) -> 11 | B31: Đất san lấp, đầm chặt K92 Land leveling and compacting K92 | E31: m2 | F31: =3.6*4.6 -> 16.56 | G31: =M31*$O$17 -> #REF! | H31: =N31*$O$17 -> #REF! | J31: =+G31+H31+I31 -> #REF! | K31: =J31*$F31 -> #REF! | M31: ='06 WC,Bảo Trì, Chứa Rác '!M30 -> #REF! | N31: ='06 WC,Bảo Trì, Chứa Rác '!N30 -> #REF!
A32: =IF(ISBLANK(E32),"",COUNTA($E$17:E32)) -> 12 | B32: Lớp đá cấp phối 0x4, đầm chặt K92 Mixed-grade rock layer 0x4, compacting K92 | E32: m3 | F32: =4.6*3.6*0.15*1.3 -> 3.2292 | G32: =M32*$O$17 -> #REF! | H32: =N32*$O$17 -> #REF! | J32: =+G32+H32+I32 -> #REF! | K32: =J32*$F32 -> #REF! | M32: ='06 WC,Bảo Trì, Chứa Rác '!M31 -> #REF! | N32: ='06 WC,Bảo Trì, Chứa Rác '!N31 -> #REF!
A33: =IF(ISBLANK(E33),"",COUNTA($E$17:E33)) -> 13 | B33: Lớp PE, dày 0.03mm, PE layer, 0.03mm thick, | E33: m2 | F33: =4.6*3.6 -> 16.56 | G33: =M33*$O$17 -> #REF! | H33: =N33*$O$17 -> #REF! | J33: =+G33+H33+I33 -> #REF! | K33: =J33*$F33 -> #REF! | M33: ='06 WC,Bảo Trì, Chứa Rác '!M32 -> #REF! | N33: ='06 WC,Bảo Trì, Chứa Rác '!N32 -> #REF!
A36: C | B36: CÔNG TÁC BÊ TÔNG CONCRETE WORK | K36: =SUBTOTAL(9,K37:K45) -> #REF!
A37: =IF(ISBLANK(E37),"",COUNTA($E$17:E37)) -> 14 | B37: Bê tông lót móng đá 1x2 M150 Concrete lining stone foundation 1x2 M150 | E37: m3 | F37: =(1.9+1.7)*2*0.1 -> 0.72 | G37: =M37*$O$17 -> #REF! | H37: =N37*$O$17 -> #REF! | J37: =+G37+H37+I37 -> #REF! | K37: =J37*$F37 -> #REF! | M37: ='06 WC,Bảo Trì, Chứa Rác '!M35 -> #REF! | N37: ='06 WC,Bảo Trì, Chứa Rác '!N35 -> #REF!
A38: =IF(ISBLANK(E38),"",COUNTA($E$17:E38)) -> 15 | B38: Bê tông lót đá đà kiềng 1x2 M150 Concrete lined with stone 1x2 M150 | E38: m3 | F38: =(5+3.2)*2*0.4*0.1 -> 0.656 | G38: =M38*$O$17 -> #REF! | H38: =N38*$O$17 -> #REF! | J38: =+G38+H38+I38 -> #REF! | K38: =J38*$F38 -> #REF! | M38: ='06 WC,Bảo Trì, Chứa Rác '!M36 -> #REF! | N38: ='06 WC,Bảo Trì, Chứa Rác '!N36 -> #REF!
A39: =IF(ISBLANK(E39),"",COUNTA($E$17:E39)) -> 16 | B39: Bê tông đầu cọc đá 1x2 M300 Concrete stone pile head 1x2 M300 | E39: m3 | G39: =M39*$O$17 -> 0 | H39: =N39*$O$17 -> 0 | J39: =+G39+H39+I39 -> 0 | K39: =J39*$F39 -> 0
A40: =IF(ISBLANK(E40),"",COUNTA($E$17:E40)) -> 17 | B40: Bê tông móng đá 1x2 M250 Stone foundation concrete 1x2 M250 | E40: m3 | F40: 0.72 | G40: =M40*$O$17 -> #REF! | H40: =N40*$O$17 -> #REF! | J40: =+G40+H40+I40 -> #REF! | K40: =J40*$F40 -> #REF! | M40: ='06 WC,Bảo Trì, Chứa Rác '!M37 -> #REF! | N40: ='06 WC,Bảo Trì, Chứa Rác '!N37 -> #REF!
A41: =IF(ISBLANK(E41),"",COUNTA($E$17:E41)) -> 18 | B41: Bê tông cổ móng đá 1x2 M250 Stone stump column concrete 1x2 M250 | E41: m3 | F41: 0.46333333 | G41: =M41*$O$17 -> #REF! | H41: =N41*$O$17 -> #REF! | J41: =+G41+H41+I41 -> #REF! | K41: =J41*$F41 -> #REF! | M41: =M40 -> #REF! | N41: =N40 -> #REF!
A42: =IF(ISBLANK(E42),"",COUNTA($E$17:E42)) -> 19 | B42: Bê tông đà kiềng đá 1x2 M250 1x2 M250 stone tie beam Concrete | E42: m3 | F42: =(5+3.6)*2*0.3*0.2 -> 1.032 | G42: =M42*$O$17 -> #REF! | H42: =N42*$O$17 -> #REF! | J42: =+G42+H42+I42 -> #REF! | K42: =J42*$F42 -> #REF! | M42: =M41 -> #REF! | N42: =N41 -> #REF!
A43: =IF(ISBLANK(E43),"",COUNTA($E$17:E43)) -> 20 | B43: Bê tông nền đá 1x2 M250 Stone floor concrete 1x2 M250 | E43: m3 | F43: =4.6*3.6*0.1-(1.1*0.9*0.1) -> 1.557 | G43: =M43*$O$17 -> #REF! | H43: =N43*$O$17 -> #REF! | J43: =+G43+H43+I43 -> #REF! | K43: =J43*$F43 -> #REF! | M43: =M42 -> #REF! | N43: =N42 -> #REF!
A44: =IF(ISBLANK(E44),"",COUNTA($E$17:E44)) -> 21 | B44: Bê tông cột đá 1x2 M250 1x2 M300 stone column concrete | E44: m3 | F44: =1.1*0.9*1.15 -> 1.1385 | G44: =M44*$O$17 -> #REF! | H44: =N44*$O$17 -> #REF! | J44: =+G44+H44+I44 -> #REF! | K44: =J44*$F44 -> #REF! | M44: =M43 -> #REF! | N44: =N43 -> #REF!
A45: =IF(ISBLANK(E45),"",COUNTA($E$17:E45))
A46: D | B46: CÔNG TÁC VÁN KHUÔN FORMWORK | K46: =SUBTOTAL(9,K47:K51) -> #REF!
A47: =IF(ISBLANK(E47),"",COUNTA($E$17:E47)) -> 22 | B47: Ván khuôn lót móng, đà kiềng Formwork for lean concrete foundation, tie beam | E47: m2 | F47: =(1.9+1.7)*2*0.1+(5+3.6)*2*0.1 -> 2.44 | G47: =M47*$O$17 -> #REF! | H47: =N47*$O$17 -> #REF! | J47: =+G47+H47+I47 -> #REF! | K47: =J47*$F47 -> #REF! | M47: ='06 WC,Bảo Trì, Chứa Rác '!M45 -> #REF! | N47: ='06 WC,Bảo Trì, Chứa Rác '!N45 -> #REF!
A48: =IF(ISBLANK(E48),"",COUNTA($E$17:E48)) -> 23 | B48: Ván khuôn móng Foundation Formwork | E48: m2 | F48: =1.8*1.6*0.25 -> 0.72 | G48: =M48*$O$17 -> #REF! | H48: =N48*$O$17 -> #REF! | J48: =+G48+H48+I48 -> #REF! | K48: =J48*$F48 -> #REF! | M48: =M47 -> #REF! | N48: =N47 -> #REF!
A49: =IF(ISBLANK(E49),"",COUNTA($E$17:E49)) -> 24 | B49: Ván khuôn đà kiềng Beam Formwork | E49: m2 | F49: =(5+3.6)*2*0.3 -> 5.16 | G49: =M49*$O$17 -> #REF! | H49: =N49*$O$17 -> #REF! | J49: =+G49+H49+I49 -> #REF! | K49: =J49*$F49 -> #REF! | M49: =M48 -> #REF! | N49: =N48 -> #REF!
A50: =IF(ISBLANK(E50),"",COUNTA($E$17:E50)) -> 25 | B50: Ván khuôn cột Column Formwork | E50: m2 | F50: =(1.1*0.9)*2*1.15 -> 2.277 | G50: =M50*$O$17 -> #REF! | H50: =N50*$O$17 -> #REF! | J50: =+G50+H50+I50 -> #REF! | K50: =J50*$F50 -> #REF! | M50: =M49 -> #REF! | N50: =N49 -> #REF!
A52: E | B52: CÔNG TÁC CỐT THÉP REBAR WORK | C52: Thép D6, D8 : CB240T Thép Đường kính D>=10 : CB500V Steel D6, D8: CB240T Steel Diameter D>=10: CB500V | D52: Hoà Phát, Pomina Hoa Phat, Pomina | K52: =SUBTOTAL(9,K53:K57) -> #REF!
A53: =IF(ISBLANK(E53),"",COUNTA($E$17:E53)) -> 26 | B53: Cốt thép móng Foundation reinforcement | E53: kg | F53: =1.8*1.6*13*0.888 -> 33.24672 | G53: =M53*$O$17 -> #REF! | H53: =N53*$O$17 -> #REF! | J53: =+G53+H53+I53 -> #REF! | K53: =J53*$F53 -> #REF! | M53: ='06 WC,Bảo Trì, Chứa Rác '!M53 -> #REF! | N53: ='06 WC,Bảo Trì, Chứa Rác '!N53 -> #REF!
A54: =IF(ISBLANK(E54),"",COUNTA($E$17:E54)) -> 27 | B54: Cốt thép đà kiềng Reinforcement | E54: kg | F54: =((5.1+4.1)*2*4*1.21+((5+3.6)*2/0.15*0.9)*0.222) -> 111.9664 | G54: =M54*$O$17 -> #REF! | H54: =N54*$O$17 -> #REF! | J54: =+G54+H54+I54 -> #REF! | K54: =J54*$F54 -> #REF! | M54: =M53 -> #REF! | N54: =N53 -> #REF!
A55: =IF(ISBLANK(E55),"",COUNTA($E$17:E55)) -> 28 | B55: Cốt thép nền (thép hàn) Base reinforcement (welded steel) | E55: m2 | F55: =4.6*3.6 -> 16.56 | G55: =M55*$O$17 -> #REF! | H55: =N55*$O$17 -> #REF! | J55: =+G55+H55+I55 -> #REF! | K55: =J55*$F55 -> #REF! | M55: =M54 -> #REF! | N55: =N54 -> #REF!
A56: =IF(ISBLANK(E56),"",COUNTA($E$17:E56)) -> 29 | B56: Cốt thép cột Reinforcement Column | E56: kg | F56: =14*(1.52+0.3)*1.58+ 1.4/0.15*3.95*0.395 -> 54.820733 | G56: =M56*$O$17 -> #REF! | H56: =N56*$O$17 -> #REF! | J56: =+G56+H56+I56 -> #REF! | K56: =J56*$F56 -> #REF! | M56: =M55 -> #REF! | N56: =N55 -> #REF!
A58: K | B58: CÔNG TÁC CỬA DOOR WORKS | K58: =SUBTOTAL(9,K59:K66) -> 10384000
A59: =IF(ISBLANK(E59),"",COUNTA($E$17:E59)) -> 30 | B59: Cửa đi 2 cánh khung lưới B40 2000x2000 Double-leaf gate with B40 wire mesh frame, 2000x2000 | E59: bộ | F59: 1 | G59: =M59*$O$17 -> 8307200 | H59: =N59*$O$17 -> 2076800 | J59: =+G59+H59+I59 -> 10384000 | K59: =J59*$F59 -> 10384000 | M59: =O59*0.8 -> 7040000 | N59: =O59*0.2 -> 1760000 | O59: =2*2*2200000 -> 8800000
A60: =IF(ISBLANK(E60),"",COUNTA($E$17:E60)) -> 31 | B60: D2 - 1000x2200 Cửa ngăn cháy 01 cánh, EI70 D2 - 1000x2200 01-wing fire door, EI70 | C60: - Cửa đi sơn tĩnh điện - Khung thép dày1.2mm, độ dày khung 110mm - Cánh thép dày 0.8mm, độ dày cánh 50mm, Lõi vật liệu chống cháy; Ron cao su xung quanh, Bản lệ Inox - Ô kính chống cháy 300x600x25mm *Phụ kiện / Accessories: Khoá tay gạt; Thanh thoát hiểm; Tay co thuỷ lực; Kính chống cháy; Doorsill / - Powder coated doors - Steel frame thickness 1.2mm, frame thickness 110mm - Steel wing thickness 0.8mm, wing thickness 50mm, Flame retardant material core; Rubber Ron Around, Stainless Steel Rule - 300x600x25mm flame retardant glass pane *Accessories: Lever lock; Emergency exit bar; Hydraulic Shrink Arms; Flame retardant glass; Doorsill / | E60: bộ | J60: =+G60+H60+I60 -> 0 | K60: =J60*$F60 -> 0
A61: =IF(ISBLANK(E61),"",COUNTA($E$17:E61)) -> 32 | B61: D3 - 2000x2200 Cửa ngăn cháy 02 cánh, EI70 D3 - 2000x2200 02-wing fire doors, EI70 | C61: - Cửa đi sơn tĩnh điện - Khung thép dày1.2mm, độ dày khung 110mm - Cánh thép dày 0.8mm, độ dày cánh 50mm, Lõi vật liệu chống cháy; Ron cao su xung quanh, Bản lệ Inox - Ô kính chống cháy 300x600x25mm *Phụ kiện / Accessories: Khoá tay gạt; Thanh thoát hiểm; Tay co thuỷ lực; Kính chống cháy; Doorsill / - Powder coated doors - Steel frame thickness 1.2mm, frame thickness 110mm - Steel wing thickness 0.8mm, wing thickness 50mm, Flame retardant material core; Rubber Ron Around, Stainless Steel Rule - 300x600x25mm flame retardant glass pane *Accessories: Lever lock; Emergency exit bar; Hydraulic Shrink Arms; Flame retardant glass; Doorsill / | E61: bộ | J61: =+G61+H61+I61 -> 0 | K61: =J61*$F61 -> 0
A62: =IF(ISBLANK(E62),"",COUNTA($E$17:E62)) -> 33 | B62: D4 - 1600x2200 Cửa ngăn cháy 02 cánh, EI70 D4 - 1600x2200 02-wing fire doors, EI70 | C62: - Cửa đi sơn tĩnh điện - Khung thép dày1.2mm, độ dày khung 110mm - Cánh thép dày 0.8mm, độ dày cánh 50mm, Lõi vật liệu chống cháy; Ron cao su xung quanh, Bản lệ Inox - Ô kính chống cháy 300x600x25mm *Phụ kiện / Accessories: Khoá tay gạt; Thanh thoát hiểm; Tay co thuỷ lực; Kính chống cháy; Doorsill / - Powder coated doors - Steel frame thickness 1.2mm, frame thickness 110mm - Steel wing thickness 0.8mm, wing thickness 50mm, Flame retardant material core; Rubber Ron Around, Stainless Steel Rule - 300x600x25mm flame retardant glass pane *Accessories: Lever lock; Emergency exit bar; Hydraulic Shrink Arms; Flame retardant glass; Doorsill / | E62: bộ | J62: =+G62+H62+I62 -> 0 | K62: =J62*$F62 -> 0
A63: =IF(ISBLANK(E63),"",COUNTA($E$17:E63)) -> 34 | B63: DC - 3000x3000mm CỬA CUỐN DC - 3000x3000mm ROLLER DOORS | C63: - Lá cửa cuốn sắt sơn tĩnh điện , bản lá 100x1.2mm Sơn tĩnh điện hoàn thiện - Ray dẫn hướng có ron cao su, sử dụng U50x100x1.2mm - Trục : Ø168 x 3.96mm - Motor YH 1000kg + Remote điều khiển - Cảm biến tự dừng khi gặp vật cản ( KTX ) - Hộp che tole 13 sóng dày 0.45mm khung 25x25x1.2mm, dày 0.6mm ốp 3 mặt gồm khung đỡ - Gồm bình lưu điện - Powder Coated Iron Roller Door Leaf , 100x1.2mm Leaf Sheet Powder Coated Finish - Guide rail with rubber grout, use U50x100x1.2mm - Shaft : Ø168 x 3.96mm - YH Motor 1000kg + Remote Control - Sensor stops automatically when encountering an obstacle ( KTX ) - 13 wave tole cover box 0.45mm thick frame 25x25x1.2mm, thick 0.6mm 3-sided cladding including support frame - Includes an electric tank | D63: Austdoor/ US Door / Mitadoor | E63: bộ | J63: =+G63+H63+I63 -> 0 | K63: =J63*$F63 -> 0
A64: =IF(ISBLANK(E64),"",COUNTA($E$17:E64)) -> 35 | B64: L1 :2400x1200mm Lam gió nhôm L1:2400x1200mm Aluminum windmill | C64: Lam nhôn dày 1.4mm sơn tĩnh điện màu xám nhạt 1.4mm thick powder coated light grey | D64: Nhôm Xingfa Việt Nam Xingfa Aluminum Vietnam | E64: bộ | J64: =+G64+H64+I64 -> 0 | K64: =J64*$F64 -> 0
A65: =IF(ISBLANK(E65),"",COUNTA($E$17:E65)) -> 36 | B65: L2 :2400x600mm Lam gió nhôm L2:2400x600mm Aluminum windmill | C65: Lam nhôn dày 1.4mm sơn tĩnh điện màu xám nhạt 1.4mm thick powder coated light grey | D65: Nhôm Xingfa Việt Nam Xingfa Aluminum Vietnam | E65: bộ | J65: =+G65+H65+I65 -> 0 | K65: =J65*$F65 -> 0
A67: L | B67: CÔNG TÁC KHÁC OTHER WORK | K67: =SUBTOTAL(9,K68:K74) -> 71272000
A68: =IF(ISBLANK(E68),"",COUNTA($E$17:E68)) -> 37 | B68: Cầu chắn rác sê nô D90 Seno garbage barrier bridge D90 | E68: Cái | J68: =+G68+H68+I68 -> 0 | K68: =J68*$F68 -> 0
A69: =IF(ISBLANK(E69),"",COUNTA($E$17:E69)) -> 38 | B69: Ống thoát nước tràn PVC D34 PVC D34 Overflow Drain Pipe | E69: m | J69: =+G69+H69+I69 -> 0 | K69: =J69*$F69 -> 0
A70: =IF(ISBLANK(E70),"",COUNTA($E$17:E70)) -> 39 | B70: Ống thoát nước PVC D90 PVC Drainage Pipe D90 | E70: m | J70: =+G70+H70+I70 -> 0 | K70: =J70*$F70 -> 0
A71: =IF(ISBLANK(E71),"",COUNTA($E$17:E71)) -> 40 | B71: Thép hình góc, mạ kẽm, V50x5 Angle Steel, Galvanized, V50x5 | E71: kg | J71: =+G71+H71+I71 -> 0 | K71: =J71*$F71 -> 0
A72: =IF(ISBLANK(E72),"",COUNTA($E$17:E72)) -> 41 | B72: Thép hình góc, mạ kẽm, L40x3 Angle Steel, Galvanized, L40x3 | E72: kg | J72: =+G72+H72+I72 -> 0 | K72: =J72*$F72 -> 0
A73: =IF(ISBLANK(E73),"",COUNTA($E$17:E73)) -> 42 | B73: Hàng rào lưới B40 bao quanh Perimeter fence made of B40 wire mesh | C73: Khung bao lưới B40, 1000x2000mm Frame with B40 wire mesh, size 1000x2000mm | E73: m2 | F73: =16*2 -> 32 | G73: =M73*$O$17 -> 1132800 | H73: =N73*$O$17 -> 283200 | J73: =+G73+H73+I73 -> 1416000 | K73: =J73*$F73 -> 45312000 | M73: =O73*0.8 -> 960000 | N73: =O73*0.2 -> 240000 | O73: 1200000
A74: =IF(ISBLANK(E74),"",COUNTA($E$17:E74)) -> 43 | B74: Bulong cho cột Bulong | C74: Khung bao lưới B40, 1000x2000mm Frame with B40 wire mesh, size 1000x2000mm | E74: bộ | F74: 1 | G74: =M74*$O$17 -> 20768000 | H74: =N74*$O$17 -> 5192000 | J74: =+G74+H74+I74 -> 25960000 | K74: =J74*$F74 -> 25960000 | M74: =O74*0.8 -> 17600000 | N74: =O74*0.2 -> 4400000 | O74: 22000000
A75: =IF(ISBLANK(E75),"",COUNTA($E$17:E75)) | G75: 0 | H75: 0 | J75: =+G75+H75 -> 0 | K75: =J75*$F75 -> 0
A76: =IF(ISBLANK(E76),"",COUNTA($E$17:E76)) | G76: 0 | H76: 0 | J76: =+G76+H76 -> 0 | K76: =J76*$F76 -> 0

Sheet 08 BỂ PCCC-
A1: BẢNG DỰ TOÁN BÁO GIÁ CÔNG TRÌNH / ESTIMATE TABLE
A2: ="DỰ ÁN / PROJECT : "&[6]COVER!K10 -> DỰ ÁN / PROJECT : AN KHANG FOODS JSC
A3: ="HẠNG MỤC / ITEM : "&B8 -> HẠNG MỤC / ITEM : BỂ NƯỚC PCCC - PHÒNG BƠM GARAGE - UNDERGROUND WATER TANK - PUMP ROOM
A4: ="CHỦ ĐẦU TƯ / : "&[6]COVER!K19 -> CHỦ ĐẦU TƯ / : AN KHANG FOODS JSC
A6: STT NO. | B6: TÊN CÔNG VIỆC VÀ DIỄN GIẢI DESCRIPTION | C6: ĐẶC TÍNH KỸ THUẬT STANDARD | D6: NHÃN HIỆU & XUẤT XỨ BRAND NAME & ORIGIN | E6: Đvt Unit | F6: KL TỔNG Q'TY | G6: ĐƠN GIÁ / RATE | J6: TỔNG CỘNG (VNĐ) TOTAL COST(VND) | L6: REMARK GHI CHÚ
G7: VẬT TƯ RATE MATERIALS | H7: NHÂN CÔNG RATE LABOUR | I7: MMTB RATE EQUIPMENT | J7: ĐƠN GIÁ TỔNG TOTAL PRICE | K7: THÀNH TIỀN AMOUNT TOTAL
A8: =A21 -> *** | B8: =B21 -> BỂ NƯỚC PCCC - PHÒNG BƠM GARAGE - UNDERGROUND WATER TANK - PUMP ROOM | K8: =SUBTOTAL(9,K9:K20) -> #REF!
A9: =A22 -> A | B9: =B22 -> CÔNG TÁC ĐẤT EARTHWORK | K9: =K22 -> #REF!
A10: =A28 -> B | B10: =B28 -> CÔNG TÁC BÊ TÔNG CONCRETE WORK | K10: =K28 -> #REF!
A11: =A36 -> C | B11: =B36 -> CÔNG TÁC VÁN KHUÔN FORMWORK | K11: =K36 -> #REF!
A12: =A48 -> D | B12: =B48 -> CÔNG TÁC CỐT THÉP REBAR WORK | K12: =K48 -> #REF!
A13: =A53 -> G | B13: =B53 -> CÔNG TÁC SƠN PAINTING WORK | K13: =K53 -> 0
A14: =A63 -> H | B14: =B63 -> CÔNG TÁC CHỐNG THẤM WATERPROOFING WORK | K14: =K63 -> #REF!
A15: =A65 -> I | B15: =B65 -> CÔNG TÁC HOÀN THIỆN NỀN SÀN FINISHING THE FLOOR | K15: =K65 -> 6825662.8
A16: =A67 -> J | B16: =B67 -> CÔNG TÁC CỬA DOOR WORK | K16: =K67 -> 0
A17: =A71 -> K | B17: =B71 -> CÔNG TÁC KHÁC OTHER WORKS | K17: =K71 -> 61831705
A18: =A76 -> L | B18: =B76 -> CÔNG TÁC BỔ SUNG TỪ NHÀ THẦU ADDITIONAL WORK FROM THE CONTRACTOR | K18: =K76 -> 0
A21: *** | B21: BỂ NƯỚC PCCC - PHÒNG BƠM GARAGE - UNDERGROUND WATER TANK - PUMP ROOM | K21: =SUBTOTAL(9,K80:K320) -> 0 | M21: Profit | O21: 1.18
A22: A | B22: CÔNG TÁC ĐẤT EARTHWORK | K22: =SUBTOTAL(9,K23:K27) -> #REF!
A24: =IF(ISBLANK(E24),"",COUNTA($E$21:E24)) -> 1 | B24: Đào đất bể nước Excavation of water tank | E24: m3 | F24: =(31.5*9.7)*3.9*1.3 -> 1549.1385 | G24: =M24*$O$21 -> #REF! | H24: =N24*$O$21 -> #REF! | J24: =+G24+H24+I24 -> #REF! | K24: =J24*$F24 -> #REF! | M24: ='07 Trạm Điện'!M26 -> #REF! | N24: ='07 Trạm Điện'!N26 -> #REF!
A25: =IF(ISBLANK(E25),"",COUNTA($E$21:E25)) -> 2 | B25: Đắp đất BỂ đầm chặt Compacting the water tank | E25: m3 | F25: =(F24/1.3-F29-F30-3.45*8.7*30.5)*1.2 -> 152.031 | G25: =M25*$O$21 -> #REF! | H25: =N25*$O$21 -> #REF! | J25: =+G25+H25+I25 -> #REF! | K25: =J25*$F25 -> #REF! | M25: ='07 Trạm Điện'!M28 -> #REF! | N25: ='07 Trạm Điện'!N28 -> #REF!
A26: =IF(ISBLANK(E26),"",COUNTA($E$21:E26)) -> 3 | B26: Vận chuyển đất ra ngoài phạm vi công trình Transporting land outside the scope of the project | E26: m3 | F26: =F24-F25 -> 1397.1075 | G26: =M26*$O$21 -> #REF! | H26: =N26*$O$21 -> #REF! | J26: =+G26+H26+I26 -> #REF! | K26: =J26*$F26 -> #REF! | M26: ='07 Trạm Điện'!M29 -> #REF! | N26: ='07 Trạm Điện'!N29 -> #REF!
A27: =IF(ISBLANK(E27),"",COUNTA($E$21:E27)) -> 4 | B27: Đầm chặt đất nền Compacting the ground | E27: m2 | F27: =31.5*9.7 -> 305.55 | G27: =M27*$O$21 -> #REF! | H27: =N27*$O$21 -> #REF! | J27: =+G27+H27+I27 -> #REF! | K27: =J27*$F27 -> #REF! | M27: ='07 Trạm Điện'!M30 -> #REF! | N27: ='07 Trạm Điện'!N30 -> #REF!
A28: B | B28: CÔNG TÁC BÊ TÔNG CONCRETE WORK | D28: Hồng Tín, Hồng Hà, Đại Lộc Phát, HDH Hong Tin, Hong Ha, Dai Loc Phat, HDH | K28: =SUBTOTAL(9,K29:K35) -> #REF!
A29: =IF(ISBLANK(E29),"",COUNTA($E$21:E29)) -> 5 | B29: Bê tông lót đá đáy bể 1x2 M100 Concrete lining stone bottom tank 1x2 M100 | E29: m3 | F29: =31.5*9.7*0.1 -> 30.555 | G29: =M29*$O$21 -> #REF! | H29: =N29*$O$21 -> #REF! | J29: =+G29+H29+I29 -> #REF! | K29: =J29*$F29 -> #REF! | M29: ='06 WC,Bảo Trì, Chứa Rác '!M35 -> #REF! | N29: ='06 WC,Bảo Trì, Chứa Rác '!N35 -> #REF!
A30: =IF(ISBLANK(E30),"",COUNTA($E$21:E30)) -> 6 | B30: Bê tông đáy bể đá 1x2, M250, phụ gia chống thấm B8 1x2 rock tank bottom concrete, M250, B8 waterproofing additive | E30: m3 | F30: =9.5*31.3*0.4 -> 118.94 | G30: =M30*$O$21 -> 1392400 | H30: =N30*$O$21 -> #REF! | J30: =+G30+H30+I30 -> #REF! | K30: =J30*$F30 -> #REF! | M30: ='02 Nhà Bảo Vệ_& P. Y TẾ'!R70 -> 1180000 | N30: ='06 WC,Bảo Trì, Chứa Rác '!N36 -> #REF!
A31: =IF(ISBLANK(E31),"",COUNTA($E$21:E31)) -> 7 | B31: Bê tông thành bể đá 1x2, M250, phụ gia chống thấm B8 Concrete into stone tank 1x2, M250, waterproofing additive B8 | E31: m3 | F31: =(30.5+8.1)*2*3.32*0.3+(30.5+8.1)*2*0.3*0.3/2 -> 80.3652 | G31: =M31*$O$21 -> #REF! | H31: =N31*$O$21 -> #REF! | J31: =+G31+H31+I31 -> #REF! | K31: =J31*$F31 -> #REF! | M31: ='06 WC,Bảo Trì, Chứa Rác '!M37 -> #REF! | N31: =N30 -> #REF!
A32: =IF(ISBLANK(E32),"",COUNTA($E$21:E32)) -> 8 | B32: Bê tông nắp bể đá 1x2, M250, phụ gia chống thấm 1x2 Stone Tank Cover Concrete, M250, Waterproofing Additive | E32: m3 | F32: =30.5*8.7*0.13-(1.1*1.1*0.13*2) -> 34.1809 | G32: =M32*$O$21 -> #REF! | H32: =N32*$O$21 -> #REF! | J32: =+G32+H32+I32 -> #REF! | K32: =J32*$F32 -> #REF! | M32: ='06 WC,Bảo Trì, Chứa Rác '!M38 -> #REF! | N32: =N31 -> #REF!
A33: =IF(ISBLANK(E33),"",COUNTA($E$21:E33)) -> 9 | B33: Bê tông dầm bể đá 1x2, M250, phụ gia chống thấm 1x2 Stone Tank Beam Concrete, M250, Waterproofing Additive | E33: m3 | F33: =8.1*5*0.25*0.37+29.9*0.25*0.37+4.7*0.2*0.27+2*0.2*0.27 -> 6.8738 | G33: =M33*$O$21 -> #REF! | H33: =N33*$O$21 -> #REF! | J33: =+G33+H33+I33 -> #REF! | K33: =J33*$F33 -> #REF! | M33: ='06 WC,Bảo Trì, Chứa Rác '!M39 -> #REF! | N33: =N32 -> #REF!
A34: =IF(ISBLANK(E34),"",COUNTA($E$21:E34)) -> 10 | B34: Bê tông cột bể đá 1x2, M250, phụ gia chống thấm 1x2 stone tank column concrete, M250, waterproofing additive | E34: m3 | F34: =5*0.3*0.3*3.02+5*0.139 -> 2.054 | G34: =M34*$O$21 -> #REF! | H34: =N34*$O$21 -> #REF! | J34: =+G34+H34+I34 -> #REF! | K34: =J34*$F34 -> #REF! | M34: ='06 WC,Bảo Trì, Chứa Rác '!M40 -> #REF! | N34: =N33 -> #REF!
A35: =IF(ISBLANK(E35),"",COUNTA($E$21:E35))
A36: C | B36: CÔNG TÁC VÁN KHUÔN FORMWORK | K36: =SUBTOTAL(9,K37:K47) -> #REF!
A37: =IF(ISBLANK(E37),"",COUNTA($E$21:E37)) -> 11 | B37: Ván khuôn lót đáy bể Tank bottom lining formwork | E37: m2 | F37: =(31.5+9.7)*2*0.1 -> 8.24 | G37: =M37*$O$21 -> #REF! | H37: =N37*$O$21 -> #REF! | J37: =+G37+H37+I37 -> #REF! | K37: =J37*$F37 -> #REF! | M37: ='06 WC,Bảo Trì, Chứa Rác '!M45 -> #REF! | N37: ='06 WC,Bảo Trì, Chứa Rác '!N45 -> #REF!
A38: =IF(ISBLANK(E38),"",COUNTA($E$21:E38)) -> 12 | B38: Ván khuôn đáy bể Tank bottom formwork | E38: m2 | F38: =(31.3+9.5)*2*0.4 -> 32.64 | G38: =M38*$O$21 -> #REF! | H38: =N38*$O$21 -> #REF! | J38: =+G38+H38+I38 -> #REF! | K38: =J38*$F38 -> #REF! | M38: =M37 -> #REF! | N38: =N37 -> #REF!
A39: =IF(ISBLANK(E39),"",COUNTA($E$21:E39)) -> 13 | B39: Ván khuôn thành bể Tank Formwork | E39: m2 | F39: =(30.35+8.65)*2*3.32*2 -> 517.92 | G39: =M39*$O$21 -> #REF! | H39: =N39*$O$21 -> #REF! | J39: =+G39+H39+I39 -> #REF! | K39: =J39*$F39 -> #REF! | M39: =M38 -> #REF! | N39: =N38 -> #REF!
A40: =IF(ISBLANK(E40),"",COUNTA($E$21:E40)) -> 14 | B40: Ván khuôn đà nắp bể Formwork Beams | E40: m2 | F40: =5*8.1*(0.25+0.37*2)+29.9*(0.25+0.37*2)+5*4.7*(0.2+0.27*2)+2*(0.2+0.27*2) -> 88.566 | G40: =M40*$O$21 -> #REF! | H40: =N40*$O$21 -> #REF! | J40: =+G40+H40+I40 -> #REF! | K40: =J40*$F40 -> #REF! | M40: =M39 -> #REF! | N40: =N39 -> #REF!
A41: =IF(ISBLANK(E41),"",COUNTA($E$21:E41)) -> 15 | B41: Ván khuôn cột bể Tank column formwork | E41: m2 | F41: =5*0.3*0.3*3.02+((1+0.3)/2*0.3)*5 -> 2.334 | G41: =M41*$O$21 -> #REF! | H41: =N41*$O$21 -> #REF! | J41: =+G41+H41+I41 -> #REF! | K41: =J41*$F41 -> #REF! | M41: =M40 -> #REF! | N41: =N40 -> #REF!
A42: =IF(ISBLANK(E42),"",COUNTA($E$21:E42)) -> 16 | B42: Ván khuôn cột Column Formwork | E42: m2 | G42: =M42*$O$21 -> #REF! | H42: =N42*$O$21 -> #REF! | J42: =+G42+H42+I42 -> #REF! | K42: =J42*$F42 -> #REF! | M42: =M41 -> #REF! | N42: =N41 -> #REF!
A43: =IF(ISBLANK(E43),"",COUNTA($E$21:E43)) -> 17 | B43: Ván khuôn bổ trụ Formwork Pillar Supplement | E43: m2 | G43: =M43*$O$21 -> #REF! | H43: =N43*$O$21 -> #REF! | J43: =+G43+H43+I43 -> #REF! | K43: =J43*$F43 -> #REF! | M43: =M42 -> #REF! | N43: =N42 -> #REF!
A44: =IF(ISBLANK(E44),"",COUNTA($E$21:E44)) -> 18 | B44: Ván khuôn dầm, giằng, lanh tô Beam formwork, bracing, linen bowls | E44: m2 | G44: =M44*$O$21 -> #REF! | H44: =N44*$O$21 -> #REF! | J44: =+G44+H44+I44 -> #REF! | K44: =J44*$F44 -> #REF! | M44: =M43 -> #REF! | N44: =N43 -> #REF!
A45: =IF(ISBLANK(E45),"",COUNTA($E$21:E45)) -> 19 | B45: Ván khuôn sàn ~ Sê nô Floor Formwork ~ Seno | E45: m2 | G45: =M45*$O$21 -> #REF! | H45: =N45*$O$21 -> #REF! | J45: =+G45+H45+I45 -> #REF! | K45: =J45*$F45 -> #REF! | M45: =M44 -> #REF! | N45: =N44 -> #REF!
A46: =IF(ISBLANK(E46),"",COUNTA($E$21:E46)) -> 20 | B46: Ván khuôn nắp bể Tank lid formwork | E46: m2 | F46: =29.9*8.1-1.1*1.1*2 -> 239.77 | G46: =M46*$O$21 -> #REF! | H46: =N46*$O$21 -> #REF! | J46: =+G46+H46+I46 -> #REF! | K46: =J46*$F46 -> #REF! | M46: =M45 -> #REF! | N46: =N45 -> #REF!
A48: D | B48: CÔNG TÁC CỐT THÉP REBAR WORK | C48: Thép D6, D8 : CB240T Thép Đường kính D>=10 : CB500V Steel D6, D8: CB240T Steel Diameter D>=10: CB500V | D48: Hoà Phát, Pomina Hoa Phat, Pomina | K48: =SUBTOTAL(9,K49:K52) -> #REF!
A49: =IF(ISBLANK(E49),"",COUNTA($E$21:E49)) -> 21 | B49: Cốt thép đà kiềng Reinforcement Beam | E49: kg | F49: =((9.6*5*14*1.58+31.6*14*1.58)+(9.3/0.15*5+31.3/0.15)*(2.6+2.1+1.6)*0.395)*1.05 -> 3204.0267 | G49: =M49*$O$21 -> #REF! | H49: =N49*$O$21 -> #REF! | J49: =+G49+H49+I49 -> #REF! | K49: =J49*$F49 -> #REF! | M49: ='06 WC,Bảo Trì, Chứa Rác '!M53 -> #REF! | N49: ='06 WC,Bảo Trì, Chứa Rác '!N53 -> #REF!
A50: =IF(ISBLANK(E50),"",COUNTA($E$21:E50)) -> 22 | B50: Cốt thép cột, thành bể Reinforced columns, tank walls | E50: kg | F50: =((30.5+8.1)*2/0.15*2*4.2*1.21+2.95/0.2*2*(30.5+8.7)*2*0.89+(30.5+8.1)/0.15*2.1*1.21+(30.5+8.7)*2+16*4.2*6*1.58+5*8*4.2*1.58+2.95/0.15*1.3*21*0.395+2.95/0.3*26*0.45*0.395+5*4/0.15*2.1*3*1.21)*1.05 -> 10708.072 | G50: =M50*$O$21 -> #REF! | H50: =N50*$O$21 -> #REF! | J50: =+G50+H50+I50 -> #REF! | K50: =J50*$F50 -> #REF! | M50: =M49 -> #REF! | N50: =N49 -> #REF!
A51: =IF(ISBLANK(E51),"",COUNTA($E$21:E51)) -> 23 | B51: Cốt thép đáy bể Tank bottom reinforcement | E51: kg | F51: =(31.3*9.3*28*1.21+31.3*9.3*1.1*0.62)*1.04 -> 10463.079 | G51: =M51*$O$21 -> #REF! | H51: =N51*$O$21 -> #REF! | J51: =+G51+H51+I51 -> #REF! | K51: =J51*$F51 -> #REF! | M51: =M50 -> #REF! | N51: =N50 -> #REF!
A52: =IF(ISBLANK(E52),"",COUNTA($E$21:E52)) -> 24 | B52: Cốt thép nắp bể Reinforced tank cover | E52: kg | F52: =(30.5*8.7*24*0.62+29.9*8.1*0.65)*1.05 -> 4311.1231 | G52: =M52*$O$21 -> #REF! | H52: =N52*$O$21 -> #REF! | J52: =+G52+H52+I52 -> #REF! | K52: =J52*$F52 -> #REF! | M52: =M51 -> #REF! | N52: =N51 -> #REF!
A53: G | B53: CÔNG TÁC SƠN PAINTING WORK | H53: =N53*$O$21 -> 0 | K53: =SUBTOTAL(9,K54:K62) -> 0
H54: =N54*$O$21 -> 0
H55: =N55*$O$21 -> 0
H56: =N56*$O$21 -> 0
H57: =N57*$O$21 -> 0
A58: =IF(ISBLANK(E58),"",COUNTA($E$21:E58)) -> 25 | B58: Sơn dầm, trần, cột, tường trong nhà 1 nước lót + 2 nước phủ Paint beams, ceilings, columns, and walls in the house with 1 primer + 2 coatings | C58: Sơn lau chùi hiệu quả | D58: Dulux | E58: m2 | H58: =N58*$O$21 -> 0 | J58: =+G58+H58+I58 -> 0 | K58: =J58*$F58 -> 0
A59: =IF(ISBLANK(E59),"",COUNTA($E$21:E59)) -> 26 | B59: Sơn tường ngoài nhà 1 nước lót + 2 nước phủ Painting the walls outside the house with 1 primer + 2 coatings | C59: Sơn ngoại thất cao cấp | D59: Dulux | E59: m2 | H59: =N59*$O$21 -> 0 | J59: =+G59+H59+I59 -> 0 | K59: =J59*$F59 -> 0
A60: =IF(ISBLANK(E60),"",COUNTA($E$21:E60)) -> 27 | B60: Sơn nước cấu kiện bê tông (Cột, dầm, cầu thang) Paint concrete structures (columns, beams, stairs) | C60: Sơn lau chùi hiệu quả | D60: Dulux | E60: m2 | H60: =N60*$O$21 -> 0 | J60: =+G60+H60+I60 -> 0 | K60: =J60*$F60 -> 0
H61: =N61*$O$21 -> 0
H62: =N62*$O$21 -> 0
A63: H | B63: CÔNG TÁC CHỐNG THẤM WATERPROOFING WORK | K63: =SUBTOTAL(9,K64) -> #REF!
A64: =IF(ISBLANK(E64),"",COUNTA($E$21:E64)) -> 28 | B64: Quét chống thấm sika 2 lớp cho thành bể và đáy bể Apply 2 layers of waterproofing with Sika. | C64: sika top seal 107, 2 lớp (định mức 1.5kg/m2/lớp) Sweep top seal 107, 2 layers (rated 1.5kg/m2/layer) | E64: m2 | F64: =29.9*8.1+(29.9+8.1)*2*2.95 -> 466.39 | G64: =M64*$O$21 -> #REF! | H64: =N64*$O$21 -> #REF! | J64: =+G64+H64+I64 -> #REF! | K64: =J64*$F64 -> #REF! | M64: ='05 Nhà Ăn'!R178 -> #REF! | N64: ='05 Nhà Ăn'!S178 -> #REF!
A65: I | B65: CÔNG TÁC HOÀN THIỆN NỀN SÀN FINISHING THE FLOOR | K65: =SUBTOTAL(9,K66:K66) -> 6825662.8
A66: =IF(ISBLANK(E66),"",COUNTA($E$21:E66)) -> 29 | B66: Lăn tạo nhám mặt nắp bể Roll to roughen the surface | E66: m2 | F66: =30.5*8.7-1.1*1.1*2 -> 262.93 | G66: =M66*$O$21 -> 0 | H66: =N66*$O$21 -> 25960 | J66: =+G66+H66+I66 -> 25960 | K66: =J66*$F66 -> 6825662.8 | M66: 0 | N66: 22000
A67: J | B67: CÔNG TÁC CỬA DOOR WORK | K67: =SUBTOTAL(9,K68:K70) -> 0
